Workbook

Sheet Front Page
G23: Financial Modeling & Valuation Report
G25: ASIAN PAINTS LTD
D27: NSE / BSE: ASIANPAINT | BSE CODE: 500820 | SECTOR: PAINTS & HOME DECOR

Sheet Content
B2: Table of Content
B3: Asian Paints Ltd | BSE code: 500820
B8: 1 | C8: One Page Profile (Teaser) | K8: 1
B9: 2 | C9: Historical Financial Statements | K9: 2
B10: 3 | C10: Cash Flow Statement | K10: 3
B11: 4 | C11: Ratio Analysis | K11: 4
B12: 5 | C12: Common Size Staement | K12: 5
B13: 6 | C13: Assumptions Sheet | K13: 6
B14: 7 | C14: Forcasted Financial Statements | K14: 7
B15: 8 | C15: Beta Regression - Asian Paints Ltd | K15: 8
B16: 9 | C16: Comps Beta | K16: 9
B17: 10 | C17: Return on Market | K17: 10
B18: 11 | C18: Weighted Average Cost of Capital (WACC) | K18: 11
B19: 12 | C19: Intrinsic Growth | K19: 12
... B26: 19 | C26: Altman's Z Score Analysis | K26: 19

Sheet Teaser
B3: ='Data Sheet'!B1&" - One Page Profile" -> ASIAN PAINTS LTD - One Page Profile
C5: =InputSheet!C2 -> Asian Paints Ltd is an Indian multinational paint company, headquartered in Mumbai. The company is engaged in the business of manufacturing, selling and distribution of paints, coatings, products related to home décor, bath fittings and providing related services.
B7: Key Financial Metrics | C7: =HistoricalFS!H3 -> 44651 | D7: =HistoricalFS!I3 -> 45016 | E7: =HistoricalFS!J3 -> 45382 | F7: =HistoricalFS!K3 -> 45747 | G7: =HistoricalFS!L3 -> 46112 | I7: Share Price - 5Y
B9: Total Sales | C9: =HistoricalFS!H6 -> 29101.28 | D9: =HistoricalFS!I6 -> 34488.59 | E9: =HistoricalFS!J6 -> 35494.73 | F9: =HistoricalFS!K6 -> 33905.62 | G9: =HistoricalFS!L6 -> 35583.54
B10: Sales Growth (Y-O-Y) | C10: =HistoricalFS!H7 -> 0.34028285 | D10: =HistoricalFS!I7 -> 0.18512278 | E10: =HistoricalFS!J7 -> 0.029173127 | F10: =HistoricalFS!K7 -> -0.044770308 | G10: =HistoricalFS!L7 -> 0.049487961
B12: Gross Profit | C12: =HistoricalFS!H12 -> 8510.71 | D12: =HistoricalFS!I12 -> 10721.89 | E12: =HistoricalFS!J12 -> 12484.74 | F12: =HistoricalFS!K12 -> 11164.35 | G12: =HistoricalFS!L12 -> 12093.91
B13: Gross Profit Margins (%) | C13: =HistoricalFS!H13 -> 0.2924514 | D13: =HistoricalFS!I13 -> 0.31088224 | E13: =HistoricalFS!J13 -> 0.35173503 | F13: =HistoricalFS!K13 -> 0.32927727 | G13: =HistoricalFS!L13 -> 0.33987372
B14: EBITDA Margins (%) | C14: =HistoricalFS!H19 -> 0.16506525 | D14: =HistoricalFS!I19 -> 0.18150467 | E14: =HistoricalFS!J19 -> 0.21369313 | F14: =HistoricalFS!K19 -> 0.17714497 | G14: =HistoricalFS!L19 -> 0.18828172
B15: EBIT Margins (%) | C15: =HistoricalFS!H28 -> 0.14718012 | D15: =HistoricalFS!I28 -> 0.16913652 | E15: =HistoricalFS!J28 -> 0.21279046 | F15: =HistoricalFS!K28 -> 0.15720373 | G15: =HistoricalFS!L28 -> 0.17420555
B16: Net Profit Margins (In Rs) | C16: =HistoricalFS!H39 -> 3084.81 | D16: =HistoricalFS!I39 -> 4195.33 | E16: =HistoricalFS!J39 -> 5557.69 | F16: =HistoricalFS!K39 -> 3709.71 | G16: =HistoricalFS!L39 -> 4394.69
B17: Earning Per Share (In Rs) | C17: =HistoricalFS!H44 -> 32.160238 | D17: =HistoricalFS!I44 -> 43.737802 | E17: =HistoricalFS!J44 -> 57.940888 | F17: =HistoricalFS!K44 -> 38.675042 | G17: =HistoricalFS!L44 -> 45.816201
B18: EPS Growth (Y-O-Y) | C18: =HistoricalFS!H45 -> -0.038026039 | D18: =HistoricalFS!I45 -> 0.35999624 | E18: =HistoricalFS!J45 -> 0.3247325 | F18: =HistoricalFS!K45 -> -0.33250865 | G18: =HistoricalFS!L45 -> 0.18464516
B19: Dividend Per Share | C19: =HistoricalFS!H47 -> 19.150021 | D19: =HistoricalFS!I47 -> 25.650021 | E19: =HistoricalFS!J47 -> 33.300042 | F19: =HistoricalFS!K47 -> 24.800042 | G19: =HistoricalFS!L47 -> 27.5
B20: Dividend Growth | C20: ='Data Sheet'!G34 -> 0.072831553 | D20: ='Data Sheet'!H34 -> 0.33942522 | E20: ='Data Sheet'!I34 -> 0.29824618 | F20: ='Data Sheet'!J34 -> -0.25525494 | G20: ='Data Sheet'!K34 -> 0.1088691
B22: Key Financial Ratio | C22: =HistoricalFS!H3 -> 44651 | D22: =HistoricalFS!I3 -> 45016 | E22: =HistoricalFS!J3 -> 45382 | F22: =HistoricalFS!K3 -> 45747 | G22: =HistoricalFS!L3 -> 46112 | I22: Volumes - 5Y
B24: Price to Earning | C24: ='Data Sheet'!G96 -> 82.250636 | D24: ='Data Sheet'!H96 -> 60.478576 | E24: ='Data Sheet'!I96 -> 45.653425 | F24: ='Data Sheet'!J96 -> 68.395531 | G24: ='Data Sheet'!K96 -> 57.735036
B25: EV/EBITDA | C25: ='Data Sheet'!G99 -> 1.7928248 | D25: ='Data Sheet'!H99 -> 1.1006519 | E25: ='Data Sheet'!I99 -> 0.76064097 | F25: ='Data Sheet'!J99 -> 1.3434111 | G25: ='Data Sheet'!K99 -> 1.2527661
B26: EV/Sales | C26: ='Data Sheet'!G100 -> 0.29593307 | D26: ='Data Sheet'!H100 -> 0.19977346 | E26: ='Data Sheet'!I100 -> 0.16254375 | F26: ='Data Sheet'!J100 -> 0.23797852 | G26: ='Data Sheet'!K100 -> 0.23587295
B27: Price to Book Value | C27: ='Data Sheet'!G102 -> 0.57122302 | D27: ='Data Sheet'!H102 -> 0.36274522 | E27: ='Data Sheet'!I102 -> 0.23382136 | F27: ='Data Sheet'!J102 -> 0.33817338 | G27: ='Data Sheet'!K102 -> 0.25912647
B28: Return on Equity (%) | C28: ='Ratio Analysis'!H29 -> 0.22334986 | D28: ='Ratio Analysis'!I29 -> 0.26233552 | E28: ='Ratio Analysis'!J29 -> 0.29675358 | F28: ='Ratio Analysis'!K29 -> 0.19122404 | G28: ='Ratio Analysis'!L29 -> 0.20563234
B29: Return on Capital Employed (%) | C29: ='Ratio Analysis'!H27 -> 0.2781535 | D29: ='Ratio Analysis'!I27 -> 0.32542978 | E29: ='Ratio Analysis'!J27 -> 0.35622572 | F29: ='Ratio Analysis'!K27 -> 0.24573838 | G29: ='Ratio Analysis'!L27 -> 0.2450088
B31: Top 10 Share Holders | C31: =RawData!AB2 -> N. Shares (In Cr) | E31: =RawData!AC2 -> (%) Holding | F31: Market Value (In Cr) | I31: Share Holding Pattern
B33: =RawData!AA3 -> Life Insurance Corporation of India | C33: =RawData!AB3 -> 7.7822006 | E33: =RawData!AC3 -> 0.0811 | F33: =C33*'Data Sheet'!$B$8 -> 20585.477
B34: =RawData!AA4 -> Sattva Holding and Trading Private Limited | C34: =RawData!AB4 -> 5.4789183 | E34: =RawData!AC4 -> 0.0571 | F34: =C34*'Data Sheet'!$B$8 -> 14492.835
B35: =RawData!AA5 -> Smiti Holding and Trading Company Private Limited | C35: =RawData!AB5 -> 5.1442638 | E35: =RawData!AC5 -> 0.0536 | F35: =C35*'Data Sheet'!$B$8 -> 13607.607
B36: =RawData!AA6 -> SBI Mutual Fund | C36: =RawData!AB6 -> 4.9885007 | E36: =RawData!AC6 -> 0.052 | F36: =C36*'Data Sheet'!$B$8 -> 13195.582
B37: =RawData!AA7 -> Geetanjali Trading and Investments Private Limited | C37: =RawData!AB7 -> 4.570614 | E37: =RawData!AC7 -> 0.0477 | F37: =C37*'Data Sheet'!$B$8 -> 12090.188
B38: =RawData!AA8 -> Elcid Investments Limited | C38: =RawData!AB8 -> 2.831386 | E38: =RawData!AC8 -> 0.0295 | F38: =C38*'Data Sheet'!$B$8 -> 7489.5822
B39: =RawData!AA9 -> Shubhit Holdings Private Limited | C39: =RawData!AB9 -> 2.315073 | E39: =RawData!AC9 -> 0.0241 | F39: =C39*'Data Sheet'!$B$8 -> 6123.8311
B40: =RawData!AA10 -> ICICI Prudential Mutual Fund | C40: =RawData!AB10 -> 2.1582801 | E40: =RawData!AC10 -> 0.0225 | F40: =C40*'Data Sheet'!$B$8 -> 5709.0825
B41: =RawData!AA11 -> Sudhanva Investments and Trading Company Private Limited | C41: =RawData!AB11 -> 1.900176 | E41: =RawData!AC11 -> 0.0198 | F41: =C41*'Data Sheet'!$B$8 -> 5026.3456
B42: =RawData!AA12 -> Rupen Investment & Industries Private Limited | C42: =RawData!AB12 -> 1.8849825 | E42: =RawData!AC12 -> 0.0197 | F42: =C42*'Data Sheet'!$B$8 -> 4986.1557
B44: Managerial Remuneration | C44: Designation | D44: Remuneration | F44: Ratio to Median | I44: Capital Structure
B46: Mr. Amit Syngle | C46: MD & CEO | D46: 312446860 | F46: 249.09 | I46: Share Price | K46: ='Data Sheet'!B8 -> 2645.2
B47: R J Jeyamurugan | C47: CFO | D47: 53653863 | F47: 42.77 | I47: No of Share | K47: ='Data Sheet'!B6 -> 95.919779
B48: R Seshasayee | C48: Chairman | D48: 13700000 | F48: 10.92 | I48: Market Capitalization | K48: =K47*K46 -> 253727
B49: Manish Choksi | C49: V. Chairman | D49: 8000000 | F49: 6.38 | I49: Less: Cash & Equivalent | K49: =-'Data Sheet'!K69 -> -1073.68
I50: Add: Total Debt | K50: ='Data Sheet'!K59 -> 3928.93
I51: Add: Minority Interest | K51: 643.39
I52: Enterprise Value | K52: =SUM(K48:K51) -> 257225.64
B54: Recent Updates
B56: Asian Paints' market share continued slipping to ~52% by September 2025, with Birla Opus at ~6.6%, and Q3 FY26 operating margins were at 20%
B57: 80th AGM held today, 9th July 2026 — shareholders to approve FY26 final dividend via VC
B58: Renewable energy hits 56.5% of total electricity use in FY26
B59: Currently trading around ₹2,739–2,757, P/E in the ~57-60x range vs industry ~52-53x

Sheet HistoricalFS
B2: ="Historical Financial Statement"&" - " &'Data Sheet'!B1 -> Historical Financial Statement - ASIAN PAINTS LTD
B3: Years | C3: ='Data Sheet'!B16 -> 42825 | D3: ='Data Sheet'!C16 -> 43190 | E3: ='Data Sheet'!D16 -> 43555 | F3: ='Data Sheet'!E16 -> 43921 | G3: ='Data Sheet'!F16 -> 44286 | H3: ='Data Sheet'!G16 -> 44651 | I3: ='Data Sheet'!H16 -> 45016 | J3: ='Data Sheet'!I16 -> 45382 | ... L3: ='Data Sheet'!K16 -> 46112
A5: # | B5: ="Income Statement"&" - "&'Data Sheet'!B1 -> Income Statement - ASIAN PAINTS LTD
B6: Sales | C6: =IFERROR('Data Sheet'!B17,0) -> 15061.99 | D6: =IFERROR('Data Sheet'!C17,0) -> 16824.55 | E6: =IFERROR('Data Sheet'!D17,0) -> 19240.13 | F6: =IFERROR('Data Sheet'!E17,0) -> 20211.25 | G6: =IFERROR('Data Sheet'!F17,0) -> 21712.79 | H6: =IFERROR('Data Sheet'!G17,0) -> 29101.28 | I6: =IFERROR('Data Sheet'!H17,0) -> 34488.59 | J6: =IFERROR('Data Sheet'!I17,0) -> 35494.73 | ... L6: =IFERROR('Data Sheet'!K17,0) -> 35583.54
B7: Sales Growth | D7: =IFERROR(D6/C6-1,0) -> 0.11702039 | E7: =IFERROR(E6/D6-1,0) -> 0.14357472 | F7: =IFERROR(F6/E6-1,0) -> 0.050473671 | G7: =IFERROR(G6/F6-1,0) -> 0.074292288 | H7: =IFERROR(H6/G6-1,0) -> 0.34028285 | I7: =IFERROR(I6/H6-1,0) -> 0.18512278 | J7: =IFERROR(J6/I6-1,0) -> 0.029173127 | K7: =IFERROR(K6/J6-1,0) -> -0.044770308 | L7: =IFERROR(L6/K6-1,0) -> 0.049487961
B9: COGS | C9: =IFERROR(SUM('Data Sheet'!B18,'Data Sheet'!B20:B22)-1*'Data Sheet'!B19,0) -> 9732.66 | D9: =IFERROR(SUM('Data Sheet'!C18,'Data Sheet'!C20:C22)-1*'Data Sheet'!C19,0) -> 11194.17 | E9: =IFERROR(SUM('Data Sheet'!D18,'Data Sheet'!D20:D22)-1*'Data Sheet'!D19,0) -> 12905.81 | F9: =IFERROR(SUM('Data Sheet'!E18,'Data Sheet'!E20:E22)-1*'Data Sheet'!E19,0) -> 13158.02 | G9: =IFERROR(SUM('Data Sheet'!F18,'Data Sheet'!F20:F22)-1*'Data Sheet'!F19,0) -> 14035.07 | H9: =IFERROR(SUM('Data Sheet'!G18,'Data Sheet'!G20:G22)-1*'Data Sheet'!G19,0) -> 20590.57 | I9: =IFERROR(SUM('Data Sheet'!H18,'Data Sheet'!H20:H22)-1*'Data Sheet'!H19,0) -> 23766.7 | J9: =IFERROR(SUM('Data Sheet'!I18,'Data Sheet'!I20:I22)-1*'Data Sheet'!I19,0) -> 23009.99 | ... L9: =IFERROR(SUM('Data Sheet'!K18,'Data Sheet'!K20:K22)-1*'Data Sheet'!K19,0) -> 23489.63
B10: COGS % of Sales | C10: =IFERROR(C9/C6,0) -> 0.64617358 | D10: =IFERROR(D9/D6,0) -> 0.66534736 | E10: =IFERROR(E9/E6,0) -> 0.67077561 | F10: =IFERROR(F9/F6,0) -> 0.65102455 | G10: =IFERROR(G9/G6,0) -> 0.64639643 | H10: =IFERROR(H9/H6,0) -> 0.7075486 | I10: =IFERROR(I9/I6,0) -> 0.68911776 | J10: =IFERROR(J9/J6,0) -> 0.64826497 | ... L10: =IFERROR(L9/L6,0) -> 0.66012628
B12: Gross Profit | C12: =IFERROR(C6-C9,0) -> 5329.33 | D12: =IFERROR(D6-D9,0) -> 5630.38 | E12: =IFERROR(E6-E9,0) -> 6334.32 | F12: =IFERROR(F6-F9,0) -> 7053.23 | G12: =IFERROR(G6-G9,0) -> 7677.72 | H12: =IFERROR(H6-H9,0) -> 8510.71 | I12: =IFERROR(I6-I9,0) -> 10721.89 | J12: =IFERROR(J6-J9,0) -> 12484.74 | ... L12: =IFERROR(L6-L9,0) -> 12093.91
B13: Gross Margin | C13: =IFERROR(C12/C6,0) -> 0.35382642 | D13: =IFERROR(D12/D6,0) -> 0.33465264 | E13: =IFERROR(E12/E6,0) -> 0.32922439 | F13: =IFERROR(F12/F6,0) -> 0.34897545 | G13: =IFERROR(G12/G6,0) -> 0.35360357 | H13: =IFERROR(H12/H6,0) -> 0.2924514 | I13: =IFERROR(I12/I6,0) -> 0.31088224 | J13: =IFERROR(J12/J6,0) -> 0.35173503 | ... L13: =IFERROR(L12/L6,0) -> 0.33987372
B15: Selling & General Expenses | C15: =IFERROR(SUM('Data Sheet'!B23:B24),0) -> 2335.57 | D15: =IFERROR(SUM('Data Sheet'!C23:C24),0) -> 2426.37 | E15: =IFERROR(SUM('Data Sheet'!D23:D24),0) -> 2569.38 | F15: =IFERROR(SUM('Data Sheet'!E23:E24),0) -> 2891.46 | G15: =IFERROR(SUM('Data Sheet'!F23:F24),0) -> 2822.12 | H15: =IFERROR(SUM('Data Sheet'!G23:G24),0) -> 3707.1 | I15: =IFERROR(SUM('Data Sheet'!H23:H24),0) -> 4462.05 | J15: =IFERROR(SUM('Data Sheet'!I23:I24),0) -> 4899.76 | ... L15: =IFERROR(SUM('Data Sheet'!K23:K24),0) -> 5394.18
B16: S&G Exp % of Sales | C16: =IFERROR(C15/C6,0) -> 0.15506384 | D16: =IFERROR(D15/D6,0) -> 0.14421604 | E16: =IFERROR(E15/E6,0) -> 0.13354276 | F16: =IFERROR(F15/F6,0) -> 0.14306191 | G16: =IFERROR(G15/G6,0) -> 0.12997501 | H16: =IFERROR(H15/H6,0) -> 0.12738615 | I16: =IFERROR(I15/I6,0) -> 0.12937757 | J16: =IFERROR(J15/J6,0) -> 0.1380419 | ... L16: =IFERROR(L15/L6,0) -> 0.151592
B18: EBITDA | C18: =IFERROR(C12-C15,0) -> 2993.76 | D18: =IFERROR(D12-D15,0) -> 3204.01 | E18: =IFERROR(E12-E15,0) -> 3764.94 | F18: =IFERROR(F12-F15,0) -> 4161.77 | G18: =IFERROR(G12-G15,0) -> 4855.6 | H18: =IFERROR(H12-H15,0) -> 4803.61 | I18: =IFERROR(I12-I15,0) -> 6259.84 | J18: =IFERROR(J12-J15,0) -> 7584.98 | ... L18: =IFERROR(L12-L15,0) -> 6699.73
B19: EBITDA Margin | C19: =IFERROR(C18/C6,0) -> 0.19876258 | D19: =IFERROR(D18/D6,0) -> 0.19043659 | E19: =IFERROR(E18/E6,0) -> 0.19568163 | F19: =IFERROR(F18/F6,0) -> 0.20591354 | G19: =IFERROR(G18/G6,0) -> 0.22362856 | H19: =IFERROR(H18/H6,0) -> 0.16506525 | I19: =IFERROR(I18/I6,0) -> 0.18150467 | J19: =IFERROR(J18/J6,0) -> 0.21369313 | ... L19: =IFERROR(L18/L6,0) -> 0.18828172
B21: Other Income | C21: =IFERROR('Data Sheet'!B25,0) -> 337.9 | D21: =IFERROR('Data Sheet'!C25,0) -> 336.41 | E21: =IFERROR('Data Sheet'!D25,0) -> 273.77 | F21: =IFERROR('Data Sheet'!E25,0) -> 350.1 | G21: =IFERROR('Data Sheet'!F25,0) -> 331.65 | H21: =IFERROR('Data Sheet'!G25,0) -> 295.88 | I21: =IFERROR('Data Sheet'!H25,0) -> 431.46 | J21: =IFERROR('Data Sheet'!I25,0) -> 820.96 | ... L21: =IFERROR('Data Sheet'!K25,0) -> 727.97
B22: Other Income % of Sales | C22: =IFERROR(C21/C6,0) -> 0.022433955 | D22: =IFERROR(D21/D6,0) -> 0.019995186 | E22: =IFERROR(E21/E6,0) -> 0.014229114 | F22: =IFERROR(F21/F6,0) -> 0.017322036 | G22: =IFERROR(G21/G6,0) -> 0.015274407 | H22: =IFERROR(H21/H6,0) -> 0.01016725 | I22: =IFERROR(I21/I6,0) -> 0.012510224 | J22: =IFERROR(J21/J6,0) -> 0.023129067 | ... L22: =IFERROR(L21/L6,0) -> 0.020458054
B24: Depreciation | C24: =IFERROR('Data Sheet'!B26,0) -> 334.79 | D24: =IFERROR('Data Sheet'!C26,0) -> 360.47 | E24: =IFERROR('Data Sheet'!D26,0) -> 622.14 | F24: =IFERROR('Data Sheet'!E26,0) -> 780.5 | G24: =IFERROR('Data Sheet'!F26,0) -> 791.27 | H24: =IFERROR('Data Sheet'!G26,0) -> 816.36 | I24: =IFERROR('Data Sheet'!H26,0) -> 858.02 | J24: =IFERROR('Data Sheet'!I26,0) -> 853 | ... L24: =IFERROR('Data Sheet'!K26,0) -> 1228.85
B25: Depreciation % of Sales | C25: =IFERROR(C24/C6,0) -> 0.022227475 | D25: =IFERROR(D24/D6,0) -> 0.021425239 | E25: =IFERROR(E24/E6,0) -> 0.03233554 | F25: =IFERROR(F24/F6,0) -> 0.038617107 | G25: =IFERROR(G24/G6,0) -> 0.036442576 | H25: =IFERROR(H24/H6,0) -> 0.028052374 | I25: =IFERROR(I24/I6,0) -> 0.024878373 | J25: =IFERROR(J24/J6,0) -> 0.024031737 | ... L25: =IFERROR(L24/L6,0) -> 0.034534226
B27: EBIT | C27: =IFERROR(C18+C21-C24,0) -> 2996.87 | D27: =IFERROR(D18+D21-D24,0) -> 3179.95 | E27: =IFERROR(E18+E21-E24,0) -> 3416.57 | F27: =IFERROR(F18+F21-F24,0) -> 3731.37 | G27: =IFERROR(G18+G21-G24,0) -> 4395.98 | H27: =IFERROR(H18+H21-H24,0) -> 4283.13 | I27: =IFERROR(I18+I21-I24,0) -> 5833.28 | J27: =IFERROR(J18+J21-J24,0) -> 7552.94 | ... L27: =IFERROR(L18+L21-L24,0) -> 6198.85
B28: EBIT Margin | C28: =IFERROR(C27/C6,0) -> 0.19896906 | D28: =IFERROR(D27/D6,0) -> 0.18900654 | E28: =IFERROR(E27/E6,0) -> 0.1775752 | F28: =IFERROR(F27/F6,0) -> 0.18461847 | G28: =IFERROR(G27/G6,0) -> 0.20246039 | H28: =IFERROR(H27/H6,0) -> 0.14718012 | I28: =IFERROR(I27/I6,0) -> 0.16913652 | J28: =IFERROR(J27/J6,0) -> 0.21279046 | ... L28: =IFERROR(L27/L6,0) -> 0.17420555
B30: Interest | C30: =IFERROR('Data Sheet'!B27,0) -> 37.33 | D30: =IFERROR('Data Sheet'!C27,0) -> 41.47 | E30: =IFERROR('Data Sheet'!D27,0) -> 110.47 | F30: =IFERROR('Data Sheet'!E27,0) -> 102.33 | G30: =IFERROR('Data Sheet'!F27,0) -> 91.63 | H30: =IFERROR('Data Sheet'!G27,0) -> 95.41 | I30: =IFERROR('Data Sheet'!H27,0) -> 144.45 | J30: =IFERROR('Data Sheet'!I27,0) -> 205.17 | ... L30: =IFERROR('Data Sheet'!K27,0) -> 195.41
B31: Interest % of Sales | C31: =IFERROR(C30/C6,0) -> 0.0024784242 | D31: =IFERROR(D30/D6,0) -> 0.0024648505 | E31: =IFERROR(E30/E6,0) -> 0.0057416452 | F31: =IFERROR(F30/F6,0) -> 0.0050630218 | G31: =IFERROR(G30/G6,0) -> 0.0042200933 | H31: =IFERROR(H30/H6,0) -> 0.0032785499 | I31: =IFERROR(I30/I6,0) -> 0.0041883417 | J31: =IFERROR(J30/J6,0) -> 0.0057802947 | ... L31: =IFERROR(L30/L6,0) -> 0.005491584
B33: Earning Before Tax | C33: =IFERROR(C27-C30,0) -> 2959.54 | D33: =IFERROR(D27-D30,0) -> 3138.48 | E33: =IFERROR(E27-E30,0) -> 3306.1 | F33: =IFERROR(F27-F30,0) -> 3629.04 | G33: =IFERROR(G27-G30,0) -> 4304.35 | H33: =IFERROR(H27-H30,0) -> 4187.72 | I33: =IFERROR(I27-I30,0) -> 5688.83 | J33: =IFERROR(J27-J30,0) -> 7347.77 | ... L33: =IFERROR(L27-L30,0) -> 6003.44
B34: EBT % of Sales | C34: =IFERROR(C33/C6,0) -> 0.19649064 | D34: =IFERROR(D33/D6,0) -> 0.18654169 | E34: =IFERROR(E33/E6,0) -> 0.17183356 | F34: =IFERROR(F33/F6,0) -> 0.17955545 | G34: =IFERROR(G33/G6,0) -> 0.1982403 | H34: =IFERROR(H33/H6,0) -> 0.14390157 | I34: =IFERROR(I33/I6,0) -> 0.16494818 | J34: =IFERROR(J33/J6,0) -> 0.20701017 | ... L34: =IFERROR(L33/L6,0) -> 0.16871396
B36: Tax | C36: =IFERROR('Data Sheet'!B29,0) -> 943.29 | D36: =IFERROR('Data Sheet'!C29,0) -> 1040.96 | E36: =IFERROR('Data Sheet'!D29,0) -> 1098.06 | F36: =IFERROR('Data Sheet'!E29,0) -> 854.85 | G36: =IFERROR('Data Sheet'!F29,0) -> 1097.6 | H36: =IFERROR('Data Sheet'!G29,0) -> 1102.91 | I36: =IFERROR('Data Sheet'!H29,0) -> 1493.5 | J36: =IFERROR('Data Sheet'!I29,0) -> 1790.08 | ... L36: =IFERROR('Data Sheet'!K29,0) -> 1608.75
B37: Effective Tax Rate | C37: =IFERROR(C36/C33,0) -> 0.31872859 | D37: =IFERROR(D36/D33,0) -> 0.33167648 | E37: =IFERROR(E36/E33,0) -> 0.33213151 | F37: =IFERROR(F36/F33,0) -> 0.23555816 | G37: =IFERROR(G36/G33,0) -> 0.25499785 | H37: =IFERROR(H36/H33,0) -> 0.26336766 | I37: =IFERROR(I36/I33,0) -> 0.26253201 | J37: =IFERROR(J36/J33,0) -> 0.24362221 | ... L37: =IFERROR(L36/L33,0) -> 0.26797136
B39: Net Profit | C39: =IFERROR(C33-C36,0) -> 2016.25 | D39: =IFERROR(D33-D36,0) -> 2097.52 | E39: =IFERROR(E33-E36,0) -> 2208.04 | F39: =IFERROR(F33-F36,0) -> 2774.19 | G39: =IFERROR(G33-G36,0) -> 3206.75 | H39: =IFERROR(H33-H36,0) -> 3084.81 | I39: =IFERROR(I33-I36,0) -> 4195.33 | J39: =IFERROR(J33-J36,0) -> 5557.69 | ... L39: =IFERROR(L33-L36,0) -> 4394.69
B40: Net Profit Margin | C40: =IFERROR(C39/C6,0) -> 0.13386345 | D40: =IFERROR(D39/D6,0) -> 0.1246702 | E40: =IFERROR(E39/E6,0) -> 0.11476222 | F40: =IFERROR(F39/F6,0) -> 0.13725969 | G40: =IFERROR(G39/G6,0) -> 0.14768945 | H40: =IFERROR(H39/H6,0) -> 0.10600255 | I40: =IFERROR(I39/I6,0) -> 0.121644 | J40: =IFERROR(J39/J6,0) -> 0.15657789 | ... L40: =IFERROR(L39/L6,0) -> 0.12350345
B42: No of Equity Shares | C42: =IFERROR('Data Sheet'!B93,0) -> 95.92 | D42: =IFERROR('Data Sheet'!C93,0) -> 95.92 | E42: =IFERROR('Data Sheet'!D93,0) -> 95.92 | F42: =IFERROR('Data Sheet'!E93,0) -> 95.92 | G42: =IFERROR('Data Sheet'!F93,0) -> 95.92 | H42: =IFERROR('Data Sheet'!G93,0) -> 95.92 | I42: =IFERROR('Data Sheet'!H93,0) -> 95.92 | J42: =IFERROR('Data Sheet'!I93,0) -> 95.92 | ... L42: =IFERROR('Data Sheet'!K93,0) -> 95.92
B44: Earning Per Shares | C44: =IFERROR(C39/C42,0) -> 21.020121 | D44: =IFERROR(D39/D42,0) -> 21.867389 | E44: =IFERROR(E39/E42,0) -> 23.0196 | F44: =IFERROR(F39/F42,0) -> 28.921914 | G44: =IFERROR(G39/G42,0) -> 33.431505 | H44: =IFERROR(H39/H42,0) -> 32.160238 | I44: =IFERROR(I39/I42,0) -> 43.737802 | J44: =IFERROR(J39/J42,0) -> 57.940888 | ... L44: =IFERROR(L39/L42,0) -> 45.816201
B45: EPS Growth Rate | D45: =IFERROR(D44/C44-1,0) -> 0.040307502 | E45: =IFERROR(E44/D44-1,0) -> 0.052690797 | F45: =IFERROR(F44/E44-1,0) -> 0.25640387 | G45: =IFERROR(G44/F44-1,0) -> 0.15592299 | H45: =IFERROR(H44/G44-1,0) -> -0.038026039 | I45: =IFERROR(I44/H44-1,0) -> 0.35999624 | J45: =IFERROR(J44/I44-1,0) -> 0.3247325 | K45: =IFERROR(K44/J44-1,0) -> -0.33250865 | L45: =IFERROR(L44/K44-1,0) -> 0.18464516
B47: Dividend Per Shares | C47: =IFERROR('Data Sheet'!B31/HistoricalFS!C42,0) -> 10.300042 | D47: =IFERROR('Data Sheet'!C31/HistoricalFS!D42,0) -> 8.6999583 | E47: =IFERROR('Data Sheet'!D31/HistoricalFS!E42,0) -> 10.5 | F47: =IFERROR('Data Sheet'!E31/HistoricalFS!F42,0) -> 12 | G47: =IFERROR('Data Sheet'!F31/HistoricalFS!G42,0) -> 17.849979 | H47: =IFERROR('Data Sheet'!G31/HistoricalFS!H42,0) -> 19.150021 | I47: =IFERROR('Data Sheet'!H31/HistoricalFS!I42,0) -> 25.650021 | J47: =IFERROR('Data Sheet'!I31/HistoricalFS!J42,0) -> 33.300042 | ... L47: =IFERROR('Data Sheet'!K31/HistoricalFS!L42,0) -> 27.5
B48: Dividend Payout Ratio | C48: =IFERROR(C47/C44,0) -> 0.49000868 | D48: =IFERROR(D47/D44,0) -> 0.3978508 | E48: =IFERROR(E47/E44,0) -> 0.45613304 | F48: =IFERROR(F47/F44,0) -> 0.4149103 | G48: =IFERROR(G47/G44,0) -> 0.53392687 | H48: =IFERROR(H47/H44,0) -> 0.59545645 | I48: =IFERROR(I47/I44,0) -> 0.5864497 | J48: =IFERROR(J47/J44,0) -> 0.57472439 | ... L48: =IFERROR(L47/L44,0) -> 0.60022436
B50: Retained Earnings | C50: =IFERROR(IF(C44>C47,1-C48),0) -> 0.50999132 | D50: =IFERROR(IF(D44>D47,1-D48),0) -> 0.6021492 | E50: =IFERROR(IF(E44>E47,1-E48),0) -> 0.54386696 | F50: =IFERROR(IF(F44>F47,1-F48),0) -> 0.5850897 | G50: =IFERROR(IF(G44>G47,1-G48),0) -> 0.46607313 | H50: =IFERROR(IF(H44>H47,1-H48),0) -> 0.40454355 | I50: =IFERROR(IF(I44>I47,1-I48),0) -> 0.4135503 | J50: =IFERROR(IF(J44>J47,1-J48),0) -> 0.42527561 | ... L50: =IFERROR(IF(L44>L47,1-L48),0) -> 0.39977564
A52: # | B52: ="Balance Sheet"&" - "&'Data Sheet'!B1 -> Balance Sheet - ASIAN PAINTS LTD
B53: Equity Share Capital | C53: =IFERROR('Data Sheet'!B57,0) -> 95.92 | D53: =IFERROR('Data Sheet'!C57,0) -> 95.92 | E53: =IFERROR('Data Sheet'!D57,0) -> 95.92 | F53: =IFERROR('Data Sheet'!E57,0) -> 95.92 | G53: =IFERROR('Data Sheet'!F57,0) -> 95.92 | H53: =IFERROR('Data Sheet'!G57,0) -> 95.92 | I53: =IFERROR('Data Sheet'!H57,0) -> 95.92 | J53: =IFERROR('Data Sheet'!I57,0) -> 95.92 | ... L53: =IFERROR('Data Sheet'!K57,0) -> 95.92
B54: Reserves | C54: =IFERROR('Data Sheet'!B58,0) -> 7507.97 | D54: =IFERROR('Data Sheet'!C58,0) -> 8314.31 | E54: =IFERROR('Data Sheet'!D58,0) -> 9374.63 | F54: =IFERROR('Data Sheet'!E58,0) -> 10034.24 | G54: =IFERROR('Data Sheet'!F58,0) -> 12710.37 | H54: =IFERROR('Data Sheet'!G58,0) -> 13715.64 | I54: =IFERROR('Data Sheet'!H58,0) -> 15896.31 | J54: =IFERROR('Data Sheet'!I58,0) -> 18632.38 | ... L54: =IFERROR('Data Sheet'!K58,0) -> 21275.67
B55: Borrowings | C55: =IFERROR('Data Sheet'!B59,0) -> 560.34 | D55: =IFERROR('Data Sheet'!C59,0) -> 533.43 | E55: =IFERROR('Data Sheet'!D59,0) -> 1319.6 | F55: =IFERROR('Data Sheet'!E59,0) -> 1118.5 | G55: =IFERROR('Data Sheet'!F59,0) -> 1093.12 | H55: =IFERROR('Data Sheet'!G59,0) -> 1586.88 | I55: =IFERROR('Data Sheet'!H59,0) -> 1932.62 | J55: =IFERROR('Data Sheet'!I59,0) -> 2474.38 | ... L55: =IFERROR('Data Sheet'!K59,0) -> 3928.93
B56: Trade Payables | C56: =IFERROR('Data Sheet'!B74,0) -> 1923 | D56: =IFERROR('Data Sheet'!C74,0) -> 2160 | E56: =IFERROR('Data Sheet'!D74,0) -> 2394 | F56: =IFERROR('Data Sheet'!E74,0) -> 2137 | G56: =IFERROR('Data Sheet'!F74,0) -> 3379 | H56: =IFERROR('Data Sheet'!G74,0) -> 4164 | I56: =IFERROR('Data Sheet'!H74,0) -> 3635 | J56: =IFERROR('Data Sheet'!I74,0) -> 3831 | ... L56: =IFERROR('Data Sheet'!K74,0) -> 3863
B57: Other Liabilities | C57: =IFERROR('Data Sheet'!B60-'Data Sheet'!B74,0) -> 2317.96 | D57: =IFERROR('Data Sheet'!C60-'Data Sheet'!C74,0) -> 2659.82 | E57: =IFERROR('Data Sheet'!D60-'Data Sheet'!D74,0) -> 3064.69 | F57: =IFERROR('Data Sheet'!E60-'Data Sheet'!E74,0) -> 2752.31 | G57: =IFERROR('Data Sheet'!F60-'Data Sheet'!F74,0) -> 3076.93 | H57: =IFERROR('Data Sheet'!G60-'Data Sheet'!G74,0) -> 3395.99 | I57: =IFERROR('Data Sheet'!H60-'Data Sheet'!H74,0) -> 4219.48 | J57: =IFERROR('Data Sheet'!I60-'Data Sheet'!I74,0) -> 4867.09 | ... L57: =IFERROR('Data Sheet'!K60-'Data Sheet'!K74,0) -> 5355.23
B58: Total Liabilities | C58: =IFERROR(SUM(C53:C57),0) -> 12405.19 | D58: =IFERROR(SUM(D53:D57),0) -> 13763.48 | E58: =IFERROR(SUM(E53:E57),0) -> 16248.84 | F58: =IFERROR(SUM(F53:F57),0) -> 16137.97 | G58: =IFERROR(SUM(G53:G57),0) -> 20355.34 | H58: =IFERROR(SUM(H53:H57),0) -> 22958.43 | I58: =IFERROR(SUM(I53:I57),0) -> 25779.33 | J58: =IFERROR(SUM(J53:J57),0) -> 29900.77 | ... L58: =IFERROR(SUM(L53:L57),0) -> 34518.75
B60: Fixed Assets Net Block | C60: =IFERROR('Data Sheet'!B62,0) -> 3303.74 | D60: =IFERROR('Data Sheet'!C62,0) -> 3732.24 | E60: =IFERROR('Data Sheet'!D62,0) -> 6496.56 | F60: =IFERROR('Data Sheet'!E62,0) -> 6272.31 | G60: =IFERROR('Data Sheet'!F62,0) -> 5858.52 | H60: =IFERROR('Data Sheet'!G62,0) -> 5519.06 | I60: =IFERROR('Data Sheet'!H62,0) -> 5770.46 | J60: =IFERROR('Data Sheet'!I62,0) -> 7146.62 | ... L60: =IFERROR('Data Sheet'!K62,0) -> 9640.28
B61: Capital Work in Progress | C61: =IFERROR('Data Sheet'!B63,0) -> 257.54 | D61: =IFERROR('Data Sheet'!C63,0) -> 1405.11 | E61: =IFERROR('Data Sheet'!D63,0) -> 209.67 | F61: =IFERROR('Data Sheet'!E63,0) -> 140.24 | G61: =IFERROR('Data Sheet'!F63,0) -> 182.98 | H61: =IFERROR('Data Sheet'!G63,0) -> 426.43 | I61: =IFERROR('Data Sheet'!H63,0) -> 1019.59 | J61: =IFERROR('Data Sheet'!I63,0) -> 2698.37 | ... L61: =IFERROR('Data Sheet'!K63,0) -> 1848.67
B62: Investments | C62: =IFERROR('Data Sheet'!B64,0) -> 2651.99 | D62: =IFERROR('Data Sheet'!C64,0) -> 2140.7 | E62: =IFERROR('Data Sheet'!D64,0) -> 2568.58 | F62: =IFERROR('Data Sheet'!E64,0) -> 2018.85 | G62: =IFERROR('Data Sheet'!F64,0) -> 4736.8 | H62: =IFERROR('Data Sheet'!G64,0) -> 3247.53 | I62: =IFERROR('Data Sheet'!H64,0) -> 4261.71 | J62: =IFERROR('Data Sheet'!I64,0) -> 4587.92 | ... L62: =IFERROR('Data Sheet'!K64,0) -> 7061.74
B63: Other Assets | C63: =IFERROR('Data Sheet'!B65-SUM('Data Sheet'!B67:B69),0) -> 1317.17 | D63: =IFERROR('Data Sheet'!C65-SUM('Data Sheet'!C67:C69),0) -> 1691.84 | E63: =IFERROR('Data Sheet'!D65-SUM('Data Sheet'!D67:D69),0) -> 1471.96 | F63: =IFERROR('Data Sheet'!E65-SUM('Data Sheet'!E67:E69),0) -> 1738.71 | G63: =IFERROR('Data Sheet'!F65-SUM('Data Sheet'!F67:F69),0) -> 2565.52 | H63: =IFERROR('Data Sheet'!G65-SUM('Data Sheet'!G67:G69),0) -> 2876.66 | I63: =IFERROR('Data Sheet'!H65-SUM('Data Sheet'!H67:H69),0) -> 3036.17 | J63: =IFERROR('Data Sheet'!I65-SUM('Data Sheet'!I67:I69),0) -> 3571.39 | ... L63: =IFERROR('Data Sheet'!K65-SUM('Data Sheet'!K67:K69),0) -> 4688.89
B64: Total Current Assets | C64: =IFERROR(SUM(C60:C63),0) -> 7530.44 | D64: =IFERROR(SUM(D60:D63),0) -> 8969.89 | E64: =IFERROR(SUM(E60:E63),0) -> 10746.77 | F64: =IFERROR(SUM(F60:F63),0) -> 10170.11 | G64: =IFERROR(SUM(G60:G63),0) -> 13343.82 | H64: =IFERROR(SUM(H60:H63),0) -> 12069.68 | I64: =IFERROR(SUM(I60:I63),0) -> 14087.93 | J64: =IFERROR(SUM(J60:J63),0) -> 18004.3 | ... L64: =IFERROR(SUM(L60:L63),0) -> 23239.58
B66: Receivables | C66: =IFERROR('Data Sheet'!B67,0) -> 1446.6 | D66: =IFERROR('Data Sheet'!C67,0) -> 1730.63 | E66: =IFERROR('Data Sheet'!D67,0) -> 1907.33 | F66: =IFERROR('Data Sheet'!E67,0) -> 1795.22 | G66: =IFERROR('Data Sheet'!F67,0) -> 2602.17 | H66: =IFERROR('Data Sheet'!G67,0) -> 3871.44 | I66: =IFERROR('Data Sheet'!H67,0) -> 4636.94 | J66: =IFERROR('Data Sheet'!I67,0) -> 4889.05 | ... L66: =IFERROR('Data Sheet'!K67,0) -> 4461.8
B67: Inventory | C67: =IFERROR('Data Sheet'!B68,0) -> 2626.94 | D67: =IFERROR('Data Sheet'!C68,0) -> 2658.31 | E67: =IFERROR('Data Sheet'!D68,0) -> 3149.86 | F67: =IFERROR('Data Sheet'!E68,0) -> 3389.81 | G67: =IFERROR('Data Sheet'!F68,0) -> 3798.6 | H67: =IFERROR('Data Sheet'!G68,0) -> 6152.98 | I67: =IFERROR('Data Sheet'!H68,0) -> 6210.64 | J67: =IFERROR('Data Sheet'!I68,0) -> 5923.41 | ... L67: =IFERROR('Data Sheet'!K68,0) -> 5743.69
B68: Cash & Bank | C68: =IFERROR('Data Sheet'!B69,0) -> 801.21 | D68: =IFERROR('Data Sheet'!C69,0) -> 404.65 | E68: =IFERROR('Data Sheet'!D69,0) -> 444.88 | F68: =IFERROR('Data Sheet'!E69,0) -> 782.83 | G68: =IFERROR('Data Sheet'!F69,0) -> 610.75 | H68: =IFERROR('Data Sheet'!G69,0) -> 864.33 | I68: =IFERROR('Data Sheet'!H69,0) -> 843.82 | J68: =IFERROR('Data Sheet'!I69,0) -> 1084.01 | ... L68: =IFERROR('Data Sheet'!K69,0) -> 1073.68
B69: Total Non Current Assets | C69: =IFERROR(SUM(C66:C68),0) -> 4874.75 | D69: =IFERROR(SUM(D66:D68),0) -> 4793.59 | E69: =IFERROR(SUM(E66:E68),0) -> 5502.07 | F69: =IFERROR(SUM(F66:F68),0) -> 5967.86 | G69: =IFERROR(SUM(G66:G68),0) -> 7011.52 | H69: =IFERROR(SUM(H66:H68),0) -> 10888.75 | I69: =IFERROR(SUM(I66:I68),0) -> 11691.4 | J69: =IFERROR(SUM(J66:J68),0) -> 11896.47 | ... L69: =IFERROR(SUM(L66:L68),0) -> 11279.17
B71: Total Assets | C71: =IFERROR(SUM(C69,C64),0) -> 12405.19 | D71: =IFERROR(SUM(D69,D64),0) -> 13763.48 | E71: =IFERROR(SUM(E69,E64),0) -> 16248.84 | F71: =IFERROR(SUM(F69,F64),0) -> 16137.97 | G71: =IFERROR(SUM(G69,G64),0) -> 20355.34 | H71: =IFERROR(SUM(H69,H64),0) -> 22958.43 | I71: =IFERROR(SUM(I69,I64),0) -> 25779.33 | J71: =IFERROR(SUM(J69,J64),0) -> 29900.77 | ... L71: =IFERROR(SUM(L69,L64),0) -> 34518.75
B73: Check | C73: =IFERROR(C71=C58,0) -> TRUE | D73: =IFERROR(D71=D58,0) -> TRUE | E73: =IFERROR(E71=E58,0) -> TRUE | F73: =IFERROR(F71=F58,0) -> TRUE | G73: =IFERROR(G71=G58,0) -> TRUE | H73: =IFERROR(H71=H58,0) -> TRUE | I73: =IFERROR(I71=I58,0) -> TRUE | J73: =IFERROR(J71=J58,0) -> TRUE | ... L73: =IFERROR(L71=L58,0) -> TRUE
A75: # | B75: ="Cash Flow Statement"&" - "&'Data Sheet'!B1 -> Cash Flow Statement - ASIAN PAINTS LTD
B76: Operating Activities
B77: Profit from operations | C77: =IFERROR('CashFlow Statement'!E4,0) -> 3056 | D77: =IFERROR('CashFlow Statement'!F4,0) -> 3274 | E77: =IFERROR('CashFlow Statement'!G4,0) -> 3861 | F77: =IFERROR('CashFlow Statement'!H4,0) -> 4380 | G77: =IFERROR('CashFlow Statement'!I4,0) -> 4970 | H77: =IFERROR('CashFlow Statement'!J4,0) -> 4957 | I77: =IFERROR('CashFlow Statement'!K4,0) -> 6460 | J77: =IFERROR('CashFlow Statement'!L4,0) -> 7929 | ... L77: =IFERROR('CashFlow Statement'!N4,0) -> 7186
B78: Receivables | C78: =IFERROR('CashFlow Statement'!E5,0) -> -475 | D78: =IFERROR('CashFlow Statement'!F5,0) -> -483 | E78: =IFERROR('CashFlow Statement'!G5,0) -> -205 | F78: =IFERROR('CashFlow Statement'!H5,0) -> 160 | G78: =IFERROR('CashFlow Statement'!I5,0) -> -849 | H78: =IFERROR('CashFlow Statement'!J5,0) -> -1326 | I78: =IFERROR('CashFlow Statement'!K5,0) -> -834 | J78: =IFERROR('CashFlow Statement'!L5,0) -> -362 | ... L78: =IFERROR('CashFlow Statement'!N5,0) -> -274
B79: Inventory | C79: =IFERROR('CashFlow Statement'!E6,0) -> -629 | D79: =IFERROR('CashFlow Statement'!F6,0) -> -39 | E79: =IFERROR('CashFlow Statement'!G6,0) -> -492 | F79: =IFERROR('CashFlow Statement'!H6,0) -> -251 | G79: =IFERROR('CashFlow Statement'!I6,0) -> -409 | H79: =IFERROR('CashFlow Statement'!J6,0) -> -2354 | I79: =IFERROR('CashFlow Statement'!K6,0) -> -56 | J79: =IFERROR('CashFlow Statement'!L6,0) -> 315 | ... L79: =IFERROR('CashFlow Statement'!N6,0) -> 976
B80: Payables | C80: =IFERROR('CashFlow Statement'!E7,0) -> 501 | D80: =IFERROR('CashFlow Statement'!F7,0) -> 442 | E80: =IFERROR('CashFlow Statement'!G7,0) -> 287 | F80: =IFERROR('CashFlow Statement'!H7,0) -> -241 | G80: =IFERROR('CashFlow Statement'!I7,0) -> 1143 | H80: =IFERROR('CashFlow Statement'!J7,0) -> 644 | I80: =IFERROR('CashFlow Statement'!K7,0) -> -539 | J80: =IFERROR('CashFlow Statement'!L7,0) -> 269 | ... L80: =IFERROR('CashFlow Statement'!N7,0) -> 396
B81: Other WC items | C81: =IFERROR('CashFlow Statement'!E8,0) -> 0 | D81: =IFERROR('CashFlow Statement'!F8,0) -> 0 | E81: =IFERROR('CashFlow Statement'!G8,0) -> 0 | F81: =IFERROR('CashFlow Statement'!H8,0) -> 0 | G81: =IFERROR('CashFlow Statement'!I8,0) -> -92 | H81: =IFERROR('CashFlow Statement'!J8,0) -> 242 | I81: =IFERROR('CashFlow Statement'!K8,0) -> 657 | J81: =IFERROR('CashFlow Statement'!L8,0) -> -212 | ... L81: =IFERROR('CashFlow Statement'!N8,0) -> 378
B82: Working capital changes | C82: =IFERROR('CashFlow Statement'!E9,0) -> -603 | D82: =IFERROR('CashFlow Statement'!F9,0) -> -80 | E82: =IFERROR('CashFlow Statement'!G9,0) -> -410 | F82: =IFERROR('CashFlow Statement'!H9,0) -> -331 | G82: =IFERROR('CashFlow Statement'!I9,0) -> -206 | H82: =IFERROR('CashFlow Statement'!J9,0) -> -2795 | I82: =IFERROR('CashFlow Statement'!K9,0) -> -772 | J82: =IFERROR('CashFlow Statement'!L9,0) -> 10 | ... L82: =IFERROR('CashFlow Statement'!N9,0) -> 1476
B83: Direct taxes | C83: =IFERROR('CashFlow Statement'!E10,0) -> -925 | D83: =IFERROR('CashFlow Statement'!F10,0) -> -1081 | E83: =IFERROR('CashFlow Statement'!G10,0) -> -982 | F83: =IFERROR('CashFlow Statement'!H10,0) -> -1011 | G83: =IFERROR('CashFlow Statement'!I10,0) -> -1080 | H83: =IFERROR('CashFlow Statement'!J10,0) -> -1176 | I83: =IFERROR('CashFlow Statement'!K10,0) -> -1494 | J83: =IFERROR('CashFlow Statement'!L10,0) -> -1835 | ... L83: =IFERROR('CashFlow Statement'!N10,0) -> -1574
B84: Cash from Operating Activity | C84: =IFERROR((C77+C82+C83),0) -> 1528 | D84: =IFERROR((D77+D82+D83),0) -> 2113 | E84: =IFERROR((E77+E82+E83),0) -> 2469 | F84: =IFERROR((F77+F82+F83),0) -> 3038 | G84: =IFERROR((G77+G82+G83),0) -> 3684 | H84: =IFERROR((H77+H82+H83),0) -> 986 | I84: =IFERROR((I77+I82+I83),0) -> 4194 | J84: =IFERROR((J77+J82+J83),0) -> 6104 | ... L84: =IFERROR((L77+L82+L83),0) -> 7088
B86: Investing Activities
B87: Fixed assets purchased | C87: =IFERROR('CashFlow Statement'!E12,0) -> -684 | D87: =IFERROR('CashFlow Statement'!F12,0) -> -1426 | E87: =IFERROR('CashFlow Statement'!G12,0) -> -1151 | F87: =IFERROR('CashFlow Statement'!H12,0) -> -414 | G87: =IFERROR('CashFlow Statement'!I12,0) -> -289 | H87: =IFERROR('CashFlow Statement'!J12,0) -> -551 | I87: =IFERROR('CashFlow Statement'!K12,0) -> -1446 | J87: =IFERROR('CashFlow Statement'!L12,0) -> -2496 | ... L87: =IFERROR('CashFlow Statement'!N12,0) -> -1487
B88: Fixed assets sold | C88: =IFERROR('CashFlow Statement'!E13,0) -> 17 | D88: =IFERROR('CashFlow Statement'!F13,0) -> 17 | E88: =IFERROR('CashFlow Statement'!G13,0) -> 17 | F88: =IFERROR('CashFlow Statement'!H13,0) -> 37 | G88: =IFERROR('CashFlow Statement'!I13,0) -> 28 | H88: =IFERROR('CashFlow Statement'!J13,0) -> 40 | I88: =IFERROR('CashFlow Statement'!K13,0) -> 26 | J88: =IFERROR('CashFlow Statement'!L13,0) -> 5 | ... L88: =IFERROR('CashFlow Statement'!N13,0) -> 3
B89: Investments purchased | C89: =IFERROR('CashFlow Statement'!E14,0) -> -153 | D89: =IFERROR('CashFlow Statement'!F14,0) -> -320 | E89: =IFERROR('CashFlow Statement'!G14,0) -> -573 | F89: =IFERROR('CashFlow Statement'!H14,0) -> -25 | G89: =IFERROR('CashFlow Statement'!I14,0) -> -140 | H89: =IFERROR('CashFlow Statement'!J14,0) -> 0 | I89: =IFERROR('CashFlow Statement'!K14,0) -> -146 | J89: =IFERROR('CashFlow Statement'!L14,0) -> -212 | ... L89: =IFERROR('CashFlow Statement'!N14,0) -> 0
B90: Investments sold | C90: =IFERROR('CashFlow Statement'!E15,0) -> 357 | D90: =IFERROR('CashFlow Statement'!F15,0) -> 362 | E90: =IFERROR('CashFlow Statement'!G15,0) -> 733 | F90: =IFERROR('CashFlow Statement'!H15,0) -> 118 | G90: =IFERROR('CashFlow Statement'!I15,0) -> 272 | H90: =IFERROR('CashFlow Statement'!J15,0) -> 207 | I90: =IFERROR('CashFlow Statement'!K15,0) -> 446 | J90: =IFERROR('CashFlow Statement'!L15,0) -> 240 | ... L90: =IFERROR('CashFlow Statement'!N15,0) -> 1197
B91: Interest received | C91: =IFERROR('CashFlow Statement'!E16,0) -> 32 | D91: =IFERROR('CashFlow Statement'!F16,0) -> 39 | E91: =IFERROR('CashFlow Statement'!G16,0) -> 40 | F91: =IFERROR('CashFlow Statement'!H16,0) -> 65 | G91: =IFERROR('CashFlow Statement'!I16,0) -> 73 | H91: =IFERROR('CashFlow Statement'!J16,0) -> 77 | I91: =IFERROR('CashFlow Statement'!K16,0) -> 87 | J91: =IFERROR('CashFlow Statement'!L16,0) -> 135 | ... L91: =IFERROR('CashFlow Statement'!N16,0) -> 153
B92: Dividends received | C92: =IFERROR('CashFlow Statement'!E17,0) -> 74 | D92: =IFERROR('CashFlow Statement'!F17,0) -> 38 | E92: =IFERROR('CashFlow Statement'!G17,0) -> 40 | F92: =IFERROR('CashFlow Statement'!H17,0) -> 27 | G92: =IFERROR('CashFlow Statement'!I17,0) -> 8 | H92: =IFERROR('CashFlow Statement'!J17,0) -> 15 | I92: =IFERROR('CashFlow Statement'!K17,0) -> 56 | J92: =IFERROR('CashFlow Statement'!L17,0) -> 129 | ... L92: =IFERROR('CashFlow Statement'!N17,0) -> 118
B93: Investment in group cos | C93: =IFERROR('CashFlow Statement'!E18,0) -> 0 | D93: =IFERROR('CashFlow Statement'!F18,0) -> 0 | E93: =IFERROR('CashFlow Statement'!G18,0) -> 0 | F93: =IFERROR('CashFlow Statement'!H18,0) -> 0 | G93: =IFERROR('CashFlow Statement'!I18,0) -> 0 | H93: =IFERROR('CashFlow Statement'!J18,0) -> 0 | I93: =IFERROR('CashFlow Statement'!K18,0) -> -180 | J93: =IFERROR('CashFlow Statement'!L18,0) -> 0 | ... L93: =IFERROR('CashFlow Statement'!N18,0) -> 0
B94: Redemp n Canc of Shares | C94: =IFERROR('CashFlow Statement'!E19,0) -> 0 | D94: =IFERROR('CashFlow Statement'!F19,0) -> 141 | E94: =IFERROR('CashFlow Statement'!G19,0) -> 0 | F94: =IFERROR('CashFlow Statement'!H19,0) -> 17 | G94: =IFERROR('CashFlow Statement'!I19,0) -> 0 | H94: =IFERROR('CashFlow Statement'!J19,0) -> 0 | I94: =IFERROR('CashFlow Statement'!K19,0) -> 0 | J94: =IFERROR('CashFlow Statement'!L19,0) -> 0 | ... L94: =IFERROR('CashFlow Statement'!N19,0) -> 0
B95: Acquisition of companies | C95: =IFERROR('CashFlow Statement'!E20,0) -> 0 | D95: =IFERROR('CashFlow Statement'!F20,0) -> -525 | E95: =IFERROR('CashFlow Statement'!G20,0) -> 0 | F95: =IFERROR('CashFlow Statement'!H20,0) -> 0 | G95: =IFERROR('CashFlow Statement'!I20,0) -> 0 | H95: =IFERROR('CashFlow Statement'!J20,0) -> 0 | I95: =IFERROR('CashFlow Statement'!K20,0) -> 0 | J95: =IFERROR('CashFlow Statement'!L20,0) -> 0 | ... L95: =IFERROR('CashFlow Statement'!N20,0) -> 0
B96: Other investing items | C96: =IFERROR('CashFlow Statement'!E21,0) -> -324 | D96: =IFERROR('CashFlow Statement'!F21,0) -> 118 | E96: =IFERROR('CashFlow Statement'!G21,0) -> -24 | F96: =IFERROR('CashFlow Statement'!H21,0) -> -343 | G96: =IFERROR('CashFlow Statement'!I21,0) -> -493 | H96: =IFERROR('CashFlow Statement'!J21,0) -> -105 | I96: =IFERROR('CashFlow Statement'!K21,0) -> -126 | J96: =IFERROR('CashFlow Statement'!L21,0) -> -350 | ... L96: =IFERROR('CashFlow Statement'!N21,0) -> -1312
B97: Cash from Investing Activities | C97: =IFERROR(SUM(C87:C96),0) -> -681 | D97: =IFERROR(SUM(D87:D96),0) -> -1556 | E97: =IFERROR(SUM(E87:E96),0) -> -918 | F97: =IFERROR(SUM(F87:F96),0) -> -518 | G97: =IFERROR(SUM(G87:G96),0) -> -541 | H97: =IFERROR(SUM(H87:H96),0) -> -317 | I97: =IFERROR(SUM(I87:I96),0) -> -1283 | J97: =IFERROR(SUM(J87:J96),0) -> -2549 | ... L97: =IFERROR(SUM(L87:L96),0) -> -1328
B99: Financial Activities
B100: Proceeds from shares | C100: =IFERROR('CashFlow Statement'!E23,0) -> 0 | D100: =IFERROR('CashFlow Statement'!F23,0) -> 0 | E100: =IFERROR('CashFlow Statement'!G23,0) -> 0 | F100: =IFERROR('CashFlow Statement'!H23,0) -> 0 | G100: =IFERROR('CashFlow Statement'!I23,0) -> 0 | H100: =IFERROR('CashFlow Statement'!J23,0) -> 0 | I100: =IFERROR('CashFlow Statement'!K23,0) -> 0 | J100: =IFERROR('CashFlow Statement'!L23,0) -> 1 | ... L100: =IFERROR('CashFlow Statement'!N23,0) -> 0
B101: Proceeds from borrowings | C101: =IFERROR('CashFlow Statement'!E24,0) -> 271 | D101: =IFERROR('CashFlow Statement'!F24,0) -> 10 | E101: =IFERROR('CashFlow Statement'!G24,0) -> 243 | F101: =IFERROR('CashFlow Statement'!H24,0) -> 18 | G101: =IFERROR('CashFlow Statement'!I24,0) -> 155 | H101: =IFERROR('CashFlow Statement'!J24,0) -> 418 | I101: =IFERROR('CashFlow Statement'!K24,0) -> 254 | J101: =IFERROR('CashFlow Statement'!L24,0) -> 101 | ... L101: =IFERROR('CashFlow Statement'!N24,0) -> 1279
B102: Repayment of borrowings | C102: =IFERROR('CashFlow Statement'!E25,0) -> -58 | D102: =IFERROR('CashFlow Statement'!F25,0) -> -54 | E102: =IFERROR('CashFlow Statement'!G25,0) -> -26 | F102: =IFERROR('CashFlow Statement'!H25,0) -> -482 | G102: =IFERROR('CashFlow Statement'!I25,0) -> -14 | H102: =IFERROR('CashFlow Statement'!J25,0) -> -8 | I102: =IFERROR('CashFlow Statement'!K25,0) -> -25 | J102: =IFERROR('CashFlow Statement'!L25,0) -> -98 | ... L102: =IFERROR('CashFlow Statement'!N25,0) -> -452
B103: Interest paid fin | C103: =IFERROR('CashFlow Statement'!E26,0) -> -36 | D103: =IFERROR('CashFlow Statement'!F26,0) -> -35 | E103: =IFERROR('CashFlow Statement'!G26,0) -> -106 | F103: =IFERROR('CashFlow Statement'!H26,0) -> -101 | G103: =IFERROR('CashFlow Statement'!I26,0) -> -89 | H103: =IFERROR('CashFlow Statement'!J26,0) -> -94 | I103: =IFERROR('CashFlow Statement'!K26,0) -> -142 | J103: =IFERROR('CashFlow Statement'!L26,0) -> -191 | ... L103: =IFERROR('CashFlow Statement'!N26,0) -> -228
B104: Dividends paid | C104: =IFERROR('CashFlow Statement'!E27,0) -> -947 | D104: =IFERROR('CashFlow Statement'!F27,0) -> -1218 | E104: =IFERROR('CashFlow Statement'!G27,0) -> -1049 | F104: =IFERROR('CashFlow Statement'!H27,0) -> -2121 | G104: =IFERROR('CashFlow Statement'!I27,0) -> -499 | H104: =IFERROR('CashFlow Statement'!J27,0) -> -1763 | I104: =IFERROR('CashFlow Statement'!K27,0) -> -1936 | J104: =IFERROR('CashFlow Statement'!L27,0) -> -2551 | ... L104: =IFERROR('CashFlow Statement'!N27,0) -> -2425
B105: Financial liabilities | C105: =IFERROR('CashFlow Statement'!E28,0) -> 0 | D105: =IFERROR('CashFlow Statement'!F28,0) -> 0 | E105: =IFERROR('CashFlow Statement'!G28,0) -> -180 | F105: =IFERROR('CashFlow Statement'!H28,0) -> -179 | G105: =IFERROR('CashFlow Statement'!I28,0) -> -203 | H105: =IFERROR('CashFlow Statement'!J28,0) -> -221 | I105: =IFERROR('CashFlow Statement'!K28,0) -> -256 | J105: =IFERROR('CashFlow Statement'!L28,0) -> -286 | ... L105: =IFERROR('CashFlow Statement'!N28,0) -> -340
B106: Other financing items | C106: =IFERROR('CashFlow Statement'!E29,0) -> 13 | D106: =IFERROR('CashFlow Statement'!F29,0) -> -82 | E106: =IFERROR('CashFlow Statement'!G29,0) -> 0 | F106: =IFERROR('CashFlow Statement'!H29,0) -> -6 | G106: =IFERROR('CashFlow Statement'!I29,0) -> 0 | H106: =IFERROR('CashFlow Statement'!J29,0) -> -140 | I106: =IFERROR('CashFlow Statement'!K29,0) -> -36 | J106: =IFERROR('CashFlow Statement'!L29,0) -> 41 | ... L106: =IFERROR('CashFlow Statement'!N29,0) -> -210
B107: Cash from Financial Activities | C107: =IFERROR(SUM(C100:C106),0) -> -757 | D107: =IFERROR(SUM(D100:D106),0) -> -1379 | E107: =IFERROR(SUM(E100:E106),0) -> -1118 | F107: =IFERROR(SUM(F100:F106),0) -> -2871 | G107: =IFERROR(SUM(G100:G106),0) -> -650 | H107: =IFERROR(SUM(H100:H106),0) -> -1808 | I107: =IFERROR(SUM(I100:I106),0) -> -2141 | J107: =IFERROR(SUM(J100:J106),0) -> -2983 | ... L107: =IFERROR(SUM(L100:L106),0) -> -2376
B109: Net Cash Flow | C109: =IFERROR(SUM(C107,C97,C84),0) -> 90 | D109: =IFERROR(SUM(D107,D97,D84),0) -> -822 | E109: =IFERROR(SUM(E107,E97,E84),0) -> 433 | F109: =IFERROR(SUM(F107,F97,F84),0) -> -351 | G109: =IFERROR(SUM(G107,G97,G84),0) -> 2493 | H109: =IFERROR(SUM(H107,H97,H84),0) -> -1139 | I109: =IFERROR(SUM(I107,I97,I84),0) -> 770 | J109: =IFERROR(SUM(J107,J97,J84),0) -> 572 | ... L109: =IFERROR(SUM(L107,L97,L84),0) -> 3384

Sheet Ratio Analysis
B2: ='Data Sheet'!B1 -> ASIAN PAINTS LTD
B3: (ASIANPAINT | BSE Code: 500820)
B4: =CONCATENATE("INR "&'Data Sheet'!B8) -> INR 2645.2
B5: 52 Week (High - INR 2,985.7 & Low - 2115.0)
B8: ="Ratio Analysis"&" - "&'Data Sheet'!B1 -> Ratio Analysis - ASIAN PAINTS LTD
B9: Years | C9: =HistoricalFS!C3 -> 42825 | D9: =HistoricalFS!D3 -> 43190 | E9: =HistoricalFS!E3 -> 43555 | F9: =HistoricalFS!F3 -> 43921 | G9: =HistoricalFS!G3 -> 44286 | H9: =HistoricalFS!H3 -> 44651 | I9: =HistoricalFS!I3 -> 45016 | J9: =HistoricalFS!J3 -> 45382 | ... L9: =HistoricalFS!L3 -> 46112 | M9: Trend Line | N9: Mean | O9: Median
B11: Sales Growth | D11: =HistoricalFS!D6/HistoricalFS!C6-1 -> 0.11702039 | E11: =HistoricalFS!E6/HistoricalFS!D6-1 -> 0.14357472 | F11: =HistoricalFS!F6/HistoricalFS!E6-1 -> 0.050473671 | G11: =HistoricalFS!G6/HistoricalFS!F6-1 -> 0.074292288 | H11: =HistoricalFS!H6/HistoricalFS!G6-1 -> 0.34028285 | I11: =HistoricalFS!I6/HistoricalFS!H6-1 -> 0.18512278 | J11: =HistoricalFS!J6/HistoricalFS!I6-1 -> 0.029173127 | K11: =HistoricalFS!K6/HistoricalFS!J6-1 -> -0.044770308 | L11: =HistoricalFS!L6/HistoricalFS!K6-1 -> 0.049487961 | N11: =IFERROR(AVERAGE(D11:L11),0) -> 0.10496194 | O11: =IFERROR(MEDIAN(D11:L11),0) -> 0.074292288
B12: EBITDA Growth | D12: =HistoricalFS!D18/HistoricalFS!C18-1 -> 0.070229411 | E12: =HistoricalFS!E18/HistoricalFS!D18-1 -> 0.17507124 | F12: =HistoricalFS!F18/HistoricalFS!E18-1 -> 0.10540141 | G12: =HistoricalFS!G18/HistoricalFS!F18-1 -> 0.16671512 | H12: =HistoricalFS!H18/HistoricalFS!G18-1 -> -0.010707225 | I12: =HistoricalFS!I18/HistoricalFS!H18-1 -> 0.30315325 | J12: =HistoricalFS!J18/HistoricalFS!I18-1 -> 0.21168912 | K12: =HistoricalFS!K18/HistoricalFS!J18-1 -> -0.20814425 | L12: =HistoricalFS!L18/HistoricalFS!K18-1 -> 0.11546716 | N12: =IFERROR(AVERAGE(D12:L12),0) -> 0.10320836 | O12: =IFERROR(MEDIAN(D12:L12),0) -> 0.11546716
B13: EBIT Growth | D13: =HistoricalFS!D27/HistoricalFS!C27-1 -> 0.061090404 | E13: =HistoricalFS!E27/HistoricalFS!D27-1 -> 0.074409975 | F13: =HistoricalFS!F27/HistoricalFS!E27-1 -> 0.092139192 | G13: =HistoricalFS!G27/HistoricalFS!F27-1 -> 0.1781142 | H13: =HistoricalFS!H27/HistoricalFS!G27-1 -> -0.025671181 | I13: =HistoricalFS!I27/HistoricalFS!H27-1 -> 0.3619199 | J13: =HistoricalFS!J27/HistoricalFS!I27-1 -> 0.29480155 | K13: =HistoricalFS!K27/HistoricalFS!J27-1 -> -0.29430262 | L13: =HistoricalFS!L27/HistoricalFS!K27-1 -> 0.16299162 | N13: =IFERROR(AVERAGE(D13:L13),0) -> 0.10061034 | O13: =IFERROR(MEDIAN(D13:L13),0) -> 0.092139192
B14: Net Profit Growth | D14: =HistoricalFS!D39/HistoricalFS!C39-1 -> 0.040307502 | E14: =HistoricalFS!E39/HistoricalFS!D39-1 -> 0.052690797 | F14: =HistoricalFS!F39/HistoricalFS!E39-1 -> 0.25640387 | G14: =HistoricalFS!G39/HistoricalFS!F39-1 -> 0.15592299 | H14: =HistoricalFS!H39/HistoricalFS!G39-1 -> -0.038026039 | I14: =HistoricalFS!I39/HistoricalFS!H39-1 -> 0.35999624 | J14: =HistoricalFS!J39/HistoricalFS!I39-1 -> 0.3247325 | K14: =HistoricalFS!K39/HistoricalFS!J39-1 -> -0.33250865 | L14: =HistoricalFS!L39/HistoricalFS!K39-1 -> 0.18464516 | N14: =IFERROR(AVERAGE(D14:L14),0) -> 0.11157382 | O14: =IFERROR(MEDIAN(D14:L14),0) -> 0.15592299
B15: Dividend Growth | D15: =HistoricalFS!D47/HistoricalFS!C47-1 -> -0.15534727 | E15: =HistoricalFS!E47/HistoricalFS!D47-1 -> 0.20690234 | F15: =HistoricalFS!F47/HistoricalFS!E47-1 -> 0.14285714 | G15: =HistoricalFS!G47/HistoricalFS!F47-1 -> 0.48749826 | H15: =HistoricalFS!H47/HistoricalFS!G47-1 -> 0.072831553 | I15: =HistoricalFS!I47/HistoricalFS!H47-1 -> 0.33942522 | J15: =HistoricalFS!J47/HistoricalFS!I47-1 -> 0.29824618 | K15: =HistoricalFS!K47/HistoricalFS!J47-1 -> -0.25525494 | L15: =HistoricalFS!L47/HistoricalFS!K47-1 -> 0.1088691 | N15: =IFERROR(AVERAGE(D15:L15),0) -> 0.13844751 | O15: =IFERROR(MEDIAN(D15:L15),0) -> 0.14285714
B17: Gross Margin | C17: =HistoricalFS!C13 -> 0.35382642 | D17: =HistoricalFS!D13 -> 0.33465264 | E17: =HistoricalFS!E13 -> 0.32922439 | F17: =HistoricalFS!F13 -> 0.34897545 | G17: =HistoricalFS!G13 -> 0.35360357 | H17: =HistoricalFS!H13 -> 0.2924514 | I17: =HistoricalFS!I13 -> 0.31088224 | J17: =HistoricalFS!J13 -> 0.35173503 | ... L17: =HistoricalFS!L13 -> 0.33987372 | N17: =IFERROR(AVERAGE(C17:L17),0) -> 0.33445021 | O17: =IFERROR(MEDIAN(C17:L17),0) -> 0.33726318
B18: EBITDA Margin | C18: =HistoricalFS!C19 -> 0.19876258 | D18: =HistoricalFS!D19 -> 0.19043659 | E18: =HistoricalFS!E19 -> 0.19568163 | F18: =HistoricalFS!F19 -> 0.20591354 | G18: =HistoricalFS!G19 -> 0.22362856 | H18: =HistoricalFS!H19 -> 0.16506525 | I18: =HistoricalFS!I19 -> 0.18150467 | J18: =HistoricalFS!J19 -> 0.21369313 | ... L18: =HistoricalFS!L19 -> 0.18828172 | N18: =IFERROR(AVERAGE(C18:L18),0) -> 0.19401126 | O18: =IFERROR(MEDIAN(C18:L18),0) -> 0.19305911
B19: EBIT Margin | C19: =HistoricalFS!C28 -> 0.19896906 | D19: =HistoricalFS!D28 -> 0.18900654 | E19: =HistoricalFS!E28 -> 0.1775752 | F19: =HistoricalFS!F28 -> 0.18461847 | G19: =HistoricalFS!G28 -> 0.20246039 | H19: =HistoricalFS!H28 -> 0.14718012 | I19: =HistoricalFS!I28 -> 0.16913652 | J19: =HistoricalFS!J28 -> 0.21279046 | ... L19: =HistoricalFS!L28 -> 0.17420555 | N19: =IFERROR(AVERAGE(C19:L19),0) -> 0.1813146 | O19: =IFERROR(MEDIAN(C19:L19),0) -> 0.18109684
B20: EBT Margin | C20: =HistoricalFS!C34 -> 0.19649064 | D20: =HistoricalFS!D34 -> 0.18654169 | E20: =HistoricalFS!E34 -> 0.17183356 | F20: =HistoricalFS!F34 -> 0.17955545 | G20: =HistoricalFS!G34 -> 0.1982403 | H20: =HistoricalFS!H34 -> 0.14390157 | I20: =HistoricalFS!I34 -> 0.16494818 | J20: =HistoricalFS!J34 -> 0.20701017 | ... L20: =HistoricalFS!L34 -> 0.16871396 | N20: =IFERROR(AVERAGE(C20:L20),0) -> 0.17677436 | O20: =IFERROR(MEDIAN(C20:L20),0) -> 0.1756945
B21: Net Profit Margin | C21: =HistoricalFS!C40 -> 0.13386345 | D21: =HistoricalFS!D40 -> 0.1246702 | E21: =HistoricalFS!E40 -> 0.11476222 | F21: =HistoricalFS!F40 -> 0.13725969 | G21: =HistoricalFS!G40 -> 0.14768945 | H21: =HistoricalFS!H40 -> 0.10600255 | I21: =HistoricalFS!I40 -> 0.121644 | J21: =HistoricalFS!J40 -> 0.15657789 | ... L21: =HistoricalFS!L40 -> 0.12350345 | N21: =IFERROR(AVERAGE(C21:L21),0) -> 0.12753857 | O21: =IFERROR(MEDIAN(C21:L21),0) -> 0.12408683
B23: Sales Exp % Sales | C23: =HistoricalFS!C16 -> 0.15506384 | D23: =HistoricalFS!D16 -> 0.14421604 | E23: =HistoricalFS!E16 -> 0.13354276 | F23: =HistoricalFS!F16 -> 0.14306191 | G23: =HistoricalFS!G16 -> 0.12997501 | H23: =HistoricalFS!H16 -> 0.12738615 | I23: =HistoricalFS!I16 -> 0.12937757 | J23: =HistoricalFS!J16 -> 0.1380419 | ... L23: =HistoricalFS!L16 -> 0.151592 | N23: =IFERROR(AVERAGE(C23:L23),0) -> 0.14043895 | O23: =IFERROR(MEDIAN(C23:L23),0) -> 0.1405519
B24: Depreciation % Sales | C24: =HistoricalFS!C25 -> 0.022227475 | D24: =HistoricalFS!D25 -> 0.021425239 | E24: =HistoricalFS!E25 -> 0.03233554 | F24: =HistoricalFS!F25 -> 0.038617107 | G24: =HistoricalFS!G25 -> 0.036442576 | H24: =HistoricalFS!H25 -> 0.028052374 | I24: =HistoricalFS!I25 -> 0.024878373 | J24: =HistoricalFS!J25 -> 0.024031737 | ... L24: =HistoricalFS!L25 -> 0.034534226 | N24: =IFERROR(AVERAGE(C24:L24),0) -> 0.029281514 | O24: =IFERROR(MEDIAN(C24:L24),0) -> 0.029161436
B25: Operating Income % Sales | C25: =C19 -> 0.19896906 | D25: =D19 -> 0.18900654 | E25: =E19 -> 0.1775752 | F25: =F19 -> 0.18461847 | G25: =G19 -> 0.20246039 | H25: =H19 -> 0.14718012 | I25: =I19 -> 0.16913652 | J25: =J19 -> 0.21279046 | ... L25: =L19 -> 0.17420555 | N25: =IFERROR(AVERAGE(C25:L25),0) -> 0.1813146 | O25: =IFERROR(MEDIAN(C25:L25),0) -> 0.18109684
B27: Return on Capital Employed | C27: =HistoricalFS!C27/SUM(HistoricalFS!C53:C55) -> 0.3670732 | D27: =HistoricalFS!D27/SUM(HistoricalFS!D53:D55) -> 0.35555354 | E27: =HistoricalFS!E27/SUM(HistoricalFS!E53:E55) -> 0.31663786 | F27: =HistoricalFS!F27/SUM(HistoricalFS!F53:F55) -> 0.33171684 | G27: =HistoricalFS!G27/SUM(HistoricalFS!G53:G55) -> 0.31627098 | H27: =HistoricalFS!H27/SUM(HistoricalFS!H53:H55) -> 0.2781535 | I27: =HistoricalFS!I27/SUM(HistoricalFS!I53:I55) -> 0.32542978 | J27: =HistoricalFS!J27/SUM(HistoricalFS!J53:J55) -> 0.35622572 | ... L27: =HistoricalFS!L27/SUM(HistoricalFS!L53:L55) -> 0.2450088 | N27: =IFERROR(AVERAGE(C27:L27),0) -> 0.31378086 | O27: =IFERROR(MEDIAN(C27:L27),0) -> 0.32103382
B28: Retained Earning % | C28: =HistoricalFS!C50 -> 0.50999132 | D28: =HistoricalFS!D50 -> 0.6021492 | E28: =HistoricalFS!E50 -> 0.54386696 | F28: =HistoricalFS!F50 -> 0.5850897 | G28: =HistoricalFS!G50 -> 0.46607313 | H28: =HistoricalFS!H50 -> 0.40454355 | I28: =HistoricalFS!I50 -> 0.4135503 | J28: =HistoricalFS!J50 -> 0.42527561 | ... L28: =HistoricalFS!L50 -> 0.39977564 | N28: =IFERROR(AVERAGE(C28:L28),0) -> 0.47090739 | O28: =IFERROR(MEDIAN(C28:L28),0) -> 0.44567437
B29: Return on Equity % | C29: =HistoricalFS!C39/SUM(HistoricalFS!C53:C54) -> 0.26516033 | D29: =HistoricalFS!D39/SUM(HistoricalFS!D53:D54) -> 0.24940103 | E29: =HistoricalFS!E39/SUM(HistoricalFS!E53:E54) -> 0.23314802 | F29: =HistoricalFS!F39/SUM(HistoricalFS!F53:F54) -> 0.27385451 | G29: =HistoricalFS!G39/SUM(HistoricalFS!G53:G54) -> 0.25040429 | H29: =HistoricalFS!H39/SUM(HistoricalFS!H53:H54) -> 0.22334986 | I29: =HistoricalFS!I39/SUM(HistoricalFS!I53:I54) -> 0.26233552 | J29: =HistoricalFS!J39/SUM(HistoricalFS!J53:J54) -> 0.29675358 | ... L29: =HistoricalFS!L39/SUM(HistoricalFS!L53:L54) -> 0.20563234 | N29: =IFERROR(AVERAGE(C29:L29),0) -> 0.24512635 | O29: =IFERROR(MEDIAN(C29:L29),0) -> 0.24990266
B30: Self Sustained Growth Rate | C30: =C29*C28 -> 0.13522947 | D30: =D29*D28 -> 0.15017663 | E30: =E29*E28 -> 0.12680151 | F30: =F29*F28 -> 0.16022945 | G30: =G29*G28 -> 0.11670671 | H30: =H29*H28 -> 0.090354746 | I30: =I29*I28 -> 0.10848893 | J30: =J29*J28 -> 0.12620206 | ... L30: =L29*L28 -> 0.082206799 | N30: =IFERROR(AVERAGE(C30:L30),0) -> 0.11649996 | O30: =IFERROR(MEDIAN(C30:L30),0) -> 0.12145438
B31: Interest Coverage Ratio | C31: =HistoricalFS!C27/HistoricalFS!C30 -> 80.280471 | D31: =HistoricalFS!D27/HistoricalFS!D30 -> 76.680733 | E31: =HistoricalFS!E27/HistoricalFS!E30 -> 30.927582 | F31: =HistoricalFS!F27/HistoricalFS!F30 -> 36.464087 | G31: =HistoricalFS!G27/HistoricalFS!G30 -> 47.975336 | H31: =HistoricalFS!H27/HistoricalFS!H30 -> 44.891835 | I31: =HistoricalFS!I27/HistoricalFS!I30 -> 40.382693 | J31: =HistoricalFS!J27/HistoricalFS!J30 -> 36.813082 | ... L31: =HistoricalFS!L27/HistoricalFS!L30 -> 31.722276 | N31: =IFERROR(AVERAGE(C31:L31),0) -> 44.96166 | O31: =IFERROR(MEDIAN(C31:L31),0) -> 38.597887
B33: Debtor Turnover Ratio | C33: =HistoricalFS!C6/HistoricalFS!C66 -> 10.411994 | D33: =HistoricalFS!D6/HistoricalFS!D66 -> 9.7216332 | E33: =HistoricalFS!E6/HistoricalFS!E66 -> 10.087468 | F33: =HistoricalFS!F6/HistoricalFS!F66 -> 11.258369 | G33: =HistoricalFS!G6/HistoricalFS!G66 -> 8.344109 | H33: =HistoricalFS!H6/HistoricalFS!H66 -> 7.5169136 | I33: =HistoricalFS!I6/HistoricalFS!I66 -> 7.4377909 | J33: =HistoricalFS!J6/HistoricalFS!J66 -> 7.2600464 | ... L33: =HistoricalFS!L6/HistoricalFS!L66 -> 7.9751535 | N33: =IFERROR(AVERAGE(C33:L33),0) -> 8.7873554 | O33: =IFERROR(MEDIAN(C33:L33),0) -> 8.1596312
B34: Creditor Turnover Ratio | C34: =HistoricalFS!C6/HistoricalFS!C57 -> 6.4979508 | D34: =HistoricalFS!D6/HistoricalFS!D57 -> 6.3254468 | E34: =HistoricalFS!E6/HistoricalFS!E57 -> 6.278002 | F34: =HistoricalFS!F6/HistoricalFS!F57 -> 7.343377 | G34: =HistoricalFS!G6/HistoricalFS!G57 -> 7.0566409 | H34: =HistoricalFS!H6/HistoricalFS!H57 -> 8.5693067 | I34: =HistoricalFS!I6/HistoricalFS!I57 -> 8.1736588 | J34: =HistoricalFS!J6/HistoricalFS!J57 -> 7.2928033 | ... L34: =HistoricalFS!L6/HistoricalFS!L57 -> 6.6446334 | N34: =IFERROR(AVERAGE(C34:L34),0) -> 7.1220343 | O34: =IFERROR(MEDIAN(C34:L34),0) -> 7.0475818
B35: Inventory Turnover Ratio | C35: =HistoricalFS!C6/HistoricalFS!C67 -> 5.7336635 | D35: =HistoricalFS!D6/HistoricalFS!D67 -> 6.3290399 | E35: =HistoricalFS!E6/HistoricalFS!E67 -> 6.1082493 | F35: =HistoricalFS!F6/HistoricalFS!F67 -> 5.9623548 | G35: =HistoricalFS!G6/HistoricalFS!G67 -> 5.715998 | H35: =HistoricalFS!H6/HistoricalFS!H67 -> 4.7296237 | I35: =HistoricalFS!I6/HistoricalFS!I67 -> 5.5531459 | J35: =HistoricalFS!J6/HistoricalFS!J67 -> 5.9922798 | ... L35: =HistoricalFS!L6/HistoricalFS!L67 -> 6.1952403 | N35: =IFERROR(AVERAGE(C35:L35),0) -> 5.7365622 | O35: =IFERROR(MEDIAN(C35:L35),0) -> 5.8480092
B36: Fixed Asset Turnover | C36: =HistoricalFS!C6/HistoricalFS!C60 -> 4.5590724 | D36: =HistoricalFS!D6/HistoricalFS!D60 -> 4.5078961 | E36: =HistoricalFS!E6/HistoricalFS!E60 -> 2.9615874 | F36: =HistoricalFS!F6/HistoricalFS!F60 -> 3.2222977 | G36: =HistoricalFS!G6/HistoricalFS!G60 -> 3.7061903 | H36: =HistoricalFS!H6/HistoricalFS!H60 -> 5.2728689 | I36: =HistoricalFS!I6/HistoricalFS!I60 -> 5.9767488 | J36: =HistoricalFS!J6/HistoricalFS!J60 -> 4.9666458 | ... L36: =HistoricalFS!L6/HistoricalFS!L60 -> 3.6911314 | N36: =IFERROR(AVERAGE(C36:L36),0) -> 4.2541798 | O36: =IFERROR(MEDIAN(C36:L36),0) -> 4.1070432
B37: Capital Turnover Ratio | C37: =HistoricalFS!C6/SUM(HistoricalFS!C53:C54) -> 1.9808269 | D37: =HistoricalFS!D6/SUM(HistoricalFS!D53:D54) -> 2.0004863 | E37: =HistoricalFS!E6/SUM(HistoricalFS!E53:E54) -> 2.0315747 | F37: =HistoricalFS!F6/SUM(HistoricalFS!F53:F54) -> 1.995156 | G37: =HistoricalFS!G6/SUM(HistoricalFS!G53:G54) -> 1.6954785 | H37: =HistoricalFS!H6/SUM(HistoricalFS!H53:H54) -> 2.1070234 | I37: =HistoricalFS!I6/SUM(HistoricalFS!I53:I54) -> 2.1565842 | J37: =HistoricalFS!J6/SUM(HistoricalFS!J53:J54) -> 1.8952457 | ... L37: =HistoricalFS!L6/SUM(HistoricalFS!L53:L54) -> 1.6649926 | N37: =IFERROR(AVERAGE(C37:L37),0) -> 1.9275098 | O37: =IFERROR(MEDIAN(C37:L37),0) -> 1.9879915
B39: Debtor Days | C39: =(365/C33) -> 35.055726 | D39: =(365/D33) -> 37.545132 | E39: =(365/E33) -> 36.183511 | F39: =(365/F33) -> 32.420325 | G39: =(365/G33) -> 43.743436 | H39: =(365/H33) -> 48.557163 | I39: =(365/I33) -> 49.073711 | J39: =(365/J33) -> 50.275161 | ... L39: =(365/L33) -> 45.767144 | N39: =IFERROR(AVERAGE(C39:L39),0) -> 42.505852 | O39: =IFERROR(MEDIAN(C39:L39),0) -> 44.75529
B40: Payable Days | C40: =365/C34 -> 56.171555 | D40: =365/D34 -> 57.703433 | E40: =365/E34 -> 58.139516 | F40: =365/F34 -> 49.704652 | G40: =365/G34 -> 51.724327 | H40: =365/H34 -> 42.593877 | I40: =365/I34 -> 44.655644 | J40: =365/J34 -> 50.049341 | ... L40: =365/L34 -> 54.931548 | N40: =IFERROR(AVERAGE(C40:L40),0) -> 51.753137 | O40: =IFERROR(MEDIAN(C40:L40),0) -> 51.7909
B41: Inventory Days | C41: =365/C35 -> 63.659125 | D41: =365/D35 -> 57.670675 | E41: =365/E35 -> 59.755256 | F41: =365/F35 -> 61.217423 | G41: =365/G35 -> 63.855866 | H41: =365/H35 -> 77.173159 | I41: =365/I35 -> 65.728509 | J41: =365/J35 -> 60.911709 | ... L41: =365/L35 -> 58.916197 | N41: =IFERROR(AVERAGE(C41:L41),0) -> 64.122205 | O41: =IFERROR(MEDIAN(C41:L41),0) -> 62.438274
B42: Cash Conversion Cycle | C42: =SUM(C39+C41-C40) -> 42.543296 | D42: =SUM(D39+D41-D40) -> 37.512373 | E42: =SUM(E39+E41-E40) -> 37.799251 | F42: =SUM(F39+F41-F40) -> 43.933097 | G42: =SUM(G39+G41-G40) -> 55.874975 | H42: =SUM(H39+H41-H40) -> 83.136445 | I42: =SUM(I39+I41-I40) -> 70.146576 | J42: =SUM(J39+J41-J40) -> 61.137528 | ... L42: =SUM(L39+L41-L40) -> 49.751793 | N42: =IFERROR(AVERAGE(C42:L42),0) -> 54.87492 | O42: =IFERROR(MEDIAN(C42:L42),0) -> 52.813384
B44: CFO/Sales | C44: =HistoricalFS!C84/HistoricalFS!C6 -> 0.10144742 | D44: =HistoricalFS!D84/HistoricalFS!D6 -> 0.12559028 | E44: =HistoricalFS!E84/HistoricalFS!E6 -> 0.12832554 | F44: =HistoricalFS!F84/HistoricalFS!F6 -> 0.15031233 | G44: =HistoricalFS!G84/HistoricalFS!G6 -> 0.16966958 | H44: =HistoricalFS!H84/HistoricalFS!H6 -> 0.033881671 | I44: =HistoricalFS!I84/HistoricalFS!I6 -> 0.12160544 | J44: =HistoricalFS!J84/HistoricalFS!J6 -> 0.17196919 | ... L44: =HistoricalFS!L84/HistoricalFS!L6 -> 0.19919322 | N44: =IFERROR(AVERAGE(C44:L44),0) -> 0.13324745 | O44: =IFERROR(MEDIAN(C44:L44),0) -> 0.12940269
B45: CFO/Total Assets | C45: =HistoricalFS!C84/HistoricalFS!C71 -> 0.12317425 | D45: =HistoricalFS!D84/HistoricalFS!D71 -> 0.15352222 | E45: =HistoricalFS!E84/HistoricalFS!E71 -> 0.15194931 | F45: =HistoricalFS!F84/HistoricalFS!F71 -> 0.18825168 | G45: =HistoricalFS!G84/HistoricalFS!G71 -> 0.18098445 | H45: =HistoricalFS!H84/HistoricalFS!H71 -> 0.042947188 | I45: =HistoricalFS!I84/HistoricalFS!I71 -> 0.16268848 | J45: =HistoricalFS!J84/HistoricalFS!J71 -> 0.2041419 | ... L45: =HistoricalFS!L84/HistoricalFS!L71 -> 0.20533768 | N45: =IFERROR(AVERAGE(C45:L45),0) -> 0.1558738 | O45: =IFERROR(MEDIAN(C45:L45),0) -> 0.15810535
B46: CFO/Total Debt | C46: =HistoricalFS!C84/HistoricalFS!C55 -> 2.7269158 | D46: =HistoricalFS!D84/HistoricalFS!D55 -> 3.961157 | E46: =HistoricalFS!E84/HistoricalFS!E55 -> 1.8710215 | F46: =HistoricalFS!F84/HistoricalFS!F55 -> 2.7161377 | G46: =HistoricalFS!G84/HistoricalFS!G55 -> 3.3701698 | H46: =HistoricalFS!H84/HistoricalFS!H55 -> 0.62134503 | I46: =HistoricalFS!I84/HistoricalFS!I55 -> 2.170111 | J46: =HistoricalFS!J84/HistoricalFS!J55 -> 2.4668806 | ... L46: =HistoricalFS!L84/HistoricalFS!L55 -> 1.8040535 | N46: =IFERROR(AVERAGE(C46:L46),0) -> 2.3639425 | O46: =IFERROR(MEDIAN(C46:L46),0) -> 2.3184958

Sheet Common Size Statement
B2: ='Data Sheet'!B1 -> ASIAN PAINTS LTD
B3: (ASIANPAINT | BSE Code: 500820)
B4: =CONCATENATE("INR "&'Data Sheet'!B8) -> INR 2645.2
B5: 52 Week (High - INR 2,985.7 & Low - 2115.0)
B8: ="Common Size Income Statement"&" - "&'Data Sheet'!B1 -> Common Size Income Statement - ASIAN PAINTS LTD
B10: Particulars | C10: ='Data Sheet'!B16 -> 42825 | D10: ='Data Sheet'!C16 -> 43190 | E10: ='Data Sheet'!D16 -> 43555 | F10: ='Data Sheet'!E16 -> 43921 | G10: ='Data Sheet'!F16 -> 44286 | H10: ='Data Sheet'!G16 -> 44651 | I10: ='Data Sheet'!H16 -> 45016 | J10: ='Data Sheet'!I16 -> 45382 | ... L10: ='Data Sheet'!K16 -> 46112
B12: Sales | C12: ='Data Sheet'!B17/'Data Sheet'!B$17 -> 1 | D12: ='Data Sheet'!C17/'Data Sheet'!C$17 -> 1 | E12: ='Data Sheet'!D17/'Data Sheet'!D$17 -> 1 | F12: ='Data Sheet'!E17/'Data Sheet'!E$17 -> 1 | G12: ='Data Sheet'!F17/'Data Sheet'!F$17 -> 1 | H12: ='Data Sheet'!G17/'Data Sheet'!G$17 -> 1 | I12: ='Data Sheet'!H17/'Data Sheet'!H$17 -> 1 | J12: ='Data Sheet'!I17/'Data Sheet'!I$17 -> 1 | ... L12: ='Data Sheet'!K17/'Data Sheet'!K$17 -> 1
B13: Raw Material Cost | C13: ='Data Sheet'!B18/'Data Sheet'!B$17 -> 0.49479518 | D13: ='Data Sheet'!C18/'Data Sheet'!C$17 -> 0.48311366 | E13: ='Data Sheet'!D18/'Data Sheet'!D$17 -> 0.51841646 | F13: ='Data Sheet'!E18/'Data Sheet'!E$17 -> 0.49388286 | G13: ='Data Sheet'!F18/'Data Sheet'!F$17 -> 0.48015709 | H13: ='Data Sheet'!G18/'Data Sheet'!G$17 -> 0.58840195 | I13: ='Data Sheet'!H18/'Data Sheet'!H$17 -> 0.55048728 | J13: ='Data Sheet'!I18/'Data Sheet'!I$17 -> 0.49051902 | ... L13: ='Data Sheet'!K18/'Data Sheet'!K$17 -> 0.48173987
B14: Change in Inventory | C14: ='Data Sheet'!B19/'Data Sheet'!B$17 -> 0.035094964 | D14: ='Data Sheet'!C19/'Data Sheet'!C$17 -> -0.0084477742 | E14: ='Data Sheet'!D19/'Data Sheet'!D$17 -> 0.015242101 | F14: ='Data Sheet'!E19/'Data Sheet'!E$17 -> 0.011832519 | G14: ='Data Sheet'!F19/'Data Sheet'!F$17 -> 0.0042578591 | H14: ='Data Sheet'!G19/'Data Sheet'!G$17 -> 0.045529612 | I14: ='Data Sheet'!H19/'Data Sheet'!H$17 -> 0.0089806513 | J14: ='Data Sheet'!I19/'Data Sheet'!I$17 -> -0.010249409 | ... L14: ='Data Sheet'!K19/'Data Sheet'!K$17 -> -0.016965147
B15: Power and Fuel | C15: ='Data Sheet'!B20/'Data Sheet'!B$17 -> 0.0070389105 | D15: ='Data Sheet'!C20/'Data Sheet'!C$17 -> 0.006555896 | E15: ='Data Sheet'!D20/'Data Sheet'!D$17 -> 0.0062177335 | F15: ='Data Sheet'!E20/'Data Sheet'!E$17 -> 0.0048383945 | G15: ='Data Sheet'!F20/'Data Sheet'!F$17 -> 0.0039631019 | H15: ='Data Sheet'!G20/'Data Sheet'!G$17 -> 0.0040283451 | I15: ='Data Sheet'!H20/'Data Sheet'!H$17 -> 0.0040097319 | J15: ='Data Sheet'!I20/'Data Sheet'!I$17 -> 0.0037540784 | ... L15: ='Data Sheet'!K20/'Data Sheet'!K$17 -> 0.0046959915
B16: Other Mfr. Exp | C16: ='Data Sheet'!B21/'Data Sheet'!B$17 -> 0.11039378 | D16: ='Data Sheet'!C21/'Data Sheet'!C$17 -> 0.10054831 | E16: ='Data Sheet'!D21/'Data Sheet'!D$17 -> 0.096795084 | F16: ='Data Sheet'!E21/'Data Sheet'!E$17 -> 0.096288948 | G16: ='Data Sheet'!F21/'Data Sheet'!F$17 -> 0.09525768 | H16: ='Data Sheet'!G21/'Data Sheet'!G$17 -> 0.098980182 | I16: ='Data Sheet'!H21/'Data Sheet'!H$17 -> 0.084555501 | J16: ='Data Sheet'!I21/'Data Sheet'!I$17 -> 0.077960306 | ... L16: ='Data Sheet'!K21/'Data Sheet'!K$17 -> 0.077763764
B17: Employee Cost | C17: ='Data Sheet'!B22/'Data Sheet'!B$17 -> 0.069040678 | D17: ='Data Sheet'!C22/'Data Sheet'!C$17 -> 0.066681724 | E17: ='Data Sheet'!D22/'Data Sheet'!D$17 -> 0.064588441 | F17: ='Data Sheet'!E22/'Data Sheet'!E$17 -> 0.067846867 | G17: ='Data Sheet'!F22/'Data Sheet'!F$17 -> 0.071276423 | H17: ='Data Sheet'!G22/'Data Sheet'!G$17 -> 0.061667734 | I17: ='Data Sheet'!H22/'Data Sheet'!H$17 -> 0.059045905 | J17: ='Data Sheet'!I22/'Data Sheet'!I$17 -> 0.06578216 | ... L17: ='Data Sheet'!K22/'Data Sheet'!K$17 -> 0.078961509
B18: Selling and admin | C18: ='Data Sheet'!B23/'Data Sheet'!B$17 -> 0.28973861 | D18: ='Data Sheet'!C23/'Data Sheet'!C$17 -> 0.13402558 | E18: ='Data Sheet'!D23/'Data Sheet'!D$17 -> 0.12301736 | F18: ='Data Sheet'!E23/'Data Sheet'!E$17 -> 0.11436749 | G18: ='Data Sheet'!F23/'Data Sheet'!F$17 -> 0.10342706 | H18: ='Data Sheet'!G23/'Data Sheet'!G$17 -> 0.10109452 | I18: ='Data Sheet'!H23/'Data Sheet'!H$17 -> 0.10150719 | J18: ='Data Sheet'!I23/'Data Sheet'!I$17 -> 0.10739228 | ... L18: ='Data Sheet'!K23/'Data Sheet'!K$17 -> 0.11556102
B19: Other Expenses | C19: ='Data Sheet'!B24/'Data Sheet'!B$17 -> -0.13467477 | D19: ='Data Sheet'!C24/'Data Sheet'!C$17 -> 0.010190466 | E19: ='Data Sheet'!D24/'Data Sheet'!D$17 -> 0.010525397 | F19: ='Data Sheet'!E24/'Data Sheet'!E$17 -> 0.028694415 | G19: ='Data Sheet'!F24/'Data Sheet'!F$17 -> 0.026547947 | H19: ='Data Sheet'!G24/'Data Sheet'!G$17 -> 0.026291627 | I19: ='Data Sheet'!H24/'Data Sheet'!H$17 -> 0.027870377 | J19: ='Data Sheet'!I24/'Data Sheet'!I$17 -> 0.03064962 | ... L19: ='Data Sheet'!K24/'Data Sheet'!K$17 -> 0.036030985
B20: Other Income | C20: ='Data Sheet'!B25/'Data Sheet'!B$17 -> 0.022433955 | D20: ='Data Sheet'!C25/'Data Sheet'!C$17 -> 0.019995186 | E20: ='Data Sheet'!D25/'Data Sheet'!D$17 -> 0.014229114 | F20: ='Data Sheet'!E25/'Data Sheet'!E$17 -> 0.017322036 | G20: ='Data Sheet'!F25/'Data Sheet'!F$17 -> 0.015274407 | H20: ='Data Sheet'!G25/'Data Sheet'!G$17 -> 0.01016725 | I20: ='Data Sheet'!H25/'Data Sheet'!H$17 -> 0.012510224 | J20: ='Data Sheet'!I25/'Data Sheet'!I$17 -> 0.023129067 | ... L20: ='Data Sheet'!K25/'Data Sheet'!K$17 -> 0.020458054
B21: Depreciation | C21: ='Data Sheet'!B26/'Data Sheet'!B$17 -> 0.022227475 | D21: ='Data Sheet'!C26/'Data Sheet'!C$17 -> 0.021425239 | E21: ='Data Sheet'!D26/'Data Sheet'!D$17 -> 0.03233554 | F21: ='Data Sheet'!E26/'Data Sheet'!E$17 -> 0.038617107 | G21: ='Data Sheet'!F26/'Data Sheet'!F$17 -> 0.036442576 | H21: ='Data Sheet'!G26/'Data Sheet'!G$17 -> 0.028052374 | I21: ='Data Sheet'!H26/'Data Sheet'!H$17 -> 0.024878373 | J21: ='Data Sheet'!I26/'Data Sheet'!I$17 -> 0.024031737 | ... L21: ='Data Sheet'!K26/'Data Sheet'!K$17 -> 0.034534226
B22: Interest | C22: ='Data Sheet'!B27/'Data Sheet'!B$17 -> 0.0024784242 | D22: ='Data Sheet'!C27/'Data Sheet'!C$17 -> 0.0024648505 | E22: ='Data Sheet'!D27/'Data Sheet'!D$17 -> 0.0057416452 | F22: ='Data Sheet'!E27/'Data Sheet'!E$17 -> 0.0050630218 | G22: ='Data Sheet'!F27/'Data Sheet'!F$17 -> 0.0042200933 | H22: ='Data Sheet'!G27/'Data Sheet'!G$17 -> 0.0032785499 | I22: ='Data Sheet'!H27/'Data Sheet'!H$17 -> 0.0041883417 | J22: ='Data Sheet'!I27/'Data Sheet'!I$17 -> 0.0057802947 | ... L22: ='Data Sheet'!K27/'Data Sheet'!K$17 -> 0.005491584
B23: Profit before tax | C23: ='Data Sheet'!B28/'Data Sheet'!B$17 -> 0.19649064 | D23: ='Data Sheet'!C28/'Data Sheet'!C$17 -> 0.18654169 | E23: ='Data Sheet'!D28/'Data Sheet'!D$17 -> 0.17183356 | F23: ='Data Sheet'!E28/'Data Sheet'!E$17 -> 0.17955545 | G23: ='Data Sheet'!F28/'Data Sheet'!F$17 -> 0.1982403 | H23: ='Data Sheet'!G28/'Data Sheet'!G$17 -> 0.14390157 | I23: ='Data Sheet'!H28/'Data Sheet'!H$17 -> 0.16494818 | J23: ='Data Sheet'!I28/'Data Sheet'!I$17 -> 0.20701017 | ... L23: ='Data Sheet'!K28/'Data Sheet'!K$17 -> 0.16871396
... B26: Dividend Amount | C26: ='Data Sheet'!B31/'Data Sheet'!B$17 -> 0.065594254 | D26: ='Data Sheet'!C31/'Data Sheet'!C$17 -> 0.049600138 | E26: ='Data Sheet'!D31/'Data Sheet'!D$17 -> 0.05234684 | F26: ='Data Sheet'!E31/'Data Sheet'!E$17 -> 0.056950461 | G26: ='Data Sheet'!F31/'Data Sheet'!F$17 -> 0.078855366 | H26: ='Data Sheet'!G31/'Data Sheet'!G$17 -> 0.063119904 | I26: ='Data Sheet'!H31/'Data Sheet'!H$17 -> 0.071338086 | J26: ='Data Sheet'!I31/'Data Sheet'!I$17 -> 0.089989134 | ... L26: ='Data Sheet'!K31/'Data Sheet'!K$17 -> 0.07412978
B27: EBITDA | C27: =HistoricalFS!C18/'Data Sheet'!B$17 -> 0.19876258 | D27: =HistoricalFS!D18/'Data Sheet'!C$17 -> 0.19043659 | E27: =HistoricalFS!E18/'Data Sheet'!D$17 -> 0.19568163 | F27: =HistoricalFS!F18/'Data Sheet'!E$17 -> 0.20591354 | G27: =HistoricalFS!G18/'Data Sheet'!F$17 -> 0.22362856 | H27: =HistoricalFS!H18/'Data Sheet'!G$17 -> 0.16506525 | I27: =HistoricalFS!I18/'Data Sheet'!H$17 -> 0.18150467 | J27: =HistoricalFS!J18/'Data Sheet'!I$17 -> 0.21369313 | ... L27: =HistoricalFS!L18/'Data Sheet'!K$17 -> 0.18828172
B29: ="Common Size Balance Sheet"&" - "&'Data Sheet'!B1 -> Common Size Balance Sheet - ASIAN PAINTS LTD
B31: Particulars | C31: =C10 -> 42825 | D31: =D10 -> 43190 | E31: =E10 -> 43555 | F31: =F10 -> 43921 | G31: =G10 -> 44286 | H31: =H10 -> 44651 | I31: =I10 -> 45016 | J31: =J10 -> 45382 | ... L31: =L10 -> 46112
B33: Total Liabilities | C33: ='Data Sheet'!B61/'Data Sheet'!B$61 -> 1 | D33: ='Data Sheet'!C61/'Data Sheet'!C$61 -> 1 | E33: ='Data Sheet'!D61/'Data Sheet'!D$61 -> 1 | F33: ='Data Sheet'!E61/'Data Sheet'!E$61 -> 1 | G33: ='Data Sheet'!F61/'Data Sheet'!F$61 -> 1 | H33: ='Data Sheet'!G61/'Data Sheet'!G$61 -> 1 | I33: ='Data Sheet'!H61/'Data Sheet'!H$61 -> 1 | J33: ='Data Sheet'!I61/'Data Sheet'!I$61 -> 1 | ... L33: ='Data Sheet'!K61/'Data Sheet'!K$61 -> 1
B34: Equity Share Capital | C34: ='Data Sheet'!B57/'Data Sheet'!B$61 -> 0.0077322476 | D34: ='Data Sheet'!C57/'Data Sheet'!C$61 -> 0.0069691677 | E34: ='Data Sheet'!D57/'Data Sheet'!D$61 -> 0.0059031906 | F34: ='Data Sheet'!E57/'Data Sheet'!E$61 -> 0.0059437463 | G34: ='Data Sheet'!F57/'Data Sheet'!F$61 -> 0.004712277 | H34: ='Data Sheet'!G57/'Data Sheet'!G$61 -> 0.004177986 | I34: ='Data Sheet'!H57/'Data Sheet'!H$61 -> 0.0037208104 | J34: ='Data Sheet'!I57/'Data Sheet'!I$61 -> 0.0032079441 | ... L34: ='Data Sheet'!K57/'Data Sheet'!K$61 -> 0.0027787796
B35: Reserves | C35: ='Data Sheet'!B58/'Data Sheet'!B$61 -> 0.60522813 | D35: ='Data Sheet'!C58/'Data Sheet'!C$61 -> 0.60408487 | E35: ='Data Sheet'!D58/'Data Sheet'!D$61 -> 0.57694149 | F35: ='Data Sheet'!E58/'Data Sheet'!E$61 -> 0.62177833 | G35: ='Data Sheet'!F58/'Data Sheet'!F$61 -> 0.62442435 | H35: ='Data Sheet'!G58/'Data Sheet'!G$61 -> 0.59741193 | I35: ='Data Sheet'!H58/'Data Sheet'!H$61 -> 0.61663007 | J35: ='Data Sheet'!I58/'Data Sheet'!I$61 -> 0.62314047 | ... L35: ='Data Sheet'!K58/'Data Sheet'!K$61 -> 0.61635111
B36: Borrowings | C36: ='Data Sheet'!B59/'Data Sheet'!B$61 -> 0.045169804 | D36: ='Data Sheet'!C59/'Data Sheet'!C$61 -> 0.038756913 | E36: ='Data Sheet'!D59/'Data Sheet'!D$61 -> 0.081211951 | F36: ='Data Sheet'!E59/'Data Sheet'!E$61 -> 0.069308593 | G36: ='Data Sheet'!F59/'Data Sheet'!F$61 -> 0.053701879 | H36: ='Data Sheet'!G59/'Data Sheet'!G$61 -> 0.069119709 | I36: ='Data Sheet'!H59/'Data Sheet'!H$61 -> 0.074967813 | J36: ='Data Sheet'!I59/'Data Sheet'!I$61 -> 0.082753053 | ... L36: ='Data Sheet'!K59/'Data Sheet'!K$61 -> 0.11382017
B37: Other Liabilities | C37: ='Data Sheet'!B60/'Data Sheet'!B$61 -> 0.34186981 | D37: ='Data Sheet'!C60/'Data Sheet'!C$61 -> 0.35018905 | E37: ='Data Sheet'!D60/'Data Sheet'!D$61 -> 0.33594337 | F37: ='Data Sheet'!E60/'Data Sheet'!E$61 -> 0.30296933 | G37: ='Data Sheet'!F60/'Data Sheet'!F$61 -> 0.31716149 | H37: ='Data Sheet'!G60/'Data Sheet'!G$61 -> 0.32929037 | I37: ='Data Sheet'!H60/'Data Sheet'!H$61 -> 0.30468131 | J37: ='Data Sheet'!I60/'Data Sheet'!I$61 -> 0.29089853 | ... L37: ='Data Sheet'!K60/'Data Sheet'!K$61 -> 0.26704994
B39: Total Assets | C39: ='Data Sheet'!B66/'Data Sheet'!B$66 -> 1 | D39: ='Data Sheet'!C66/'Data Sheet'!C$66 -> 1 | E39: ='Data Sheet'!D66/'Data Sheet'!D$66 -> 1 | F39: ='Data Sheet'!E66/'Data Sheet'!E$66 -> 1 | G39: ='Data Sheet'!F66/'Data Sheet'!F$66 -> 1 | H39: ='Data Sheet'!G66/'Data Sheet'!G$66 -> 1 | I39: ='Data Sheet'!H66/'Data Sheet'!H$66 -> 1 | J39: ='Data Sheet'!I66/'Data Sheet'!I$66 -> 1 | ... L39: ='Data Sheet'!K66/'Data Sheet'!K$66 -> 1
B40: Net Block | C40: ='Data Sheet'!B62/'Data Sheet'!B$66 -> 0.26631918 | D40: ='Data Sheet'!C62/'Data Sheet'!C$66 -> 0.27116979 | E40: ='Data Sheet'!D62/'Data Sheet'!D$66 -> 0.39981685 | F40: ='Data Sheet'!E62/'Data Sheet'!E$66 -> 0.38866784 | G40: ='Data Sheet'!F62/'Data Sheet'!F$66 -> 0.28781244 | H40: ='Data Sheet'!G62/'Data Sheet'!G$66 -> 0.24039362 | I40: ='Data Sheet'!H62/'Data Sheet'!H$66 -> 0.22384057 | J40: ='Data Sheet'!I62/'Data Sheet'!I$66 -> 0.23901124 | ... L40: ='Data Sheet'!K62/'Data Sheet'!K$66 -> 0.27927663
B41: Capital Work in Progress | C41: ='Data Sheet'!B63/'Data Sheet'!B$66 -> 0.020760665 | D41: ='Data Sheet'!C63/'Data Sheet'!C$66 -> 0.10208973 | E41: ='Data Sheet'!D63/'Data Sheet'!D$66 -> 0.01290369 | F41: ='Data Sheet'!E63/'Data Sheet'!E$66 -> 0.0086900645 | G41: ='Data Sheet'!F63/'Data Sheet'!F$66 -> 0.0089892873 | H41: ='Data Sheet'!G63/'Data Sheet'!G$66 -> 0.018574005 | I41: ='Data Sheet'!H63/'Data Sheet'!H$66 -> 0.039550679 | J41: ='Data Sheet'!I63/'Data Sheet'!I$66 -> 0.090244164 | ... L41: ='Data Sheet'!K63/'Data Sheet'!K$66 -> 0.053555531
B42: Investments | C42: ='Data Sheet'!B64/'Data Sheet'!B$66 -> 0.21378068 | D42: ='Data Sheet'!C64/'Data Sheet'!C$66 -> 0.15553479 | E42: ='Data Sheet'!D64/'Data Sheet'!D$66 -> 0.15807775 | F42: ='Data Sheet'!E64/'Data Sheet'!E$66 -> 0.12509938 | G42: ='Data Sheet'!F64/'Data Sheet'!F$66 -> 0.23270552 | H42: ='Data Sheet'!G64/'Data Sheet'!G$66 -> 0.14145262 | I42: ='Data Sheet'!H64/'Data Sheet'!H$66 -> 0.165315 | J42: ='Data Sheet'!I64/'Data Sheet'!I$66 -> 0.15343819 | ... L42: ='Data Sheet'!K64/'Data Sheet'!K$66 -> 0.20457693
B43: Other Assets | C43: ='Data Sheet'!B75/'Data Sheet'!B$66 -> 0.10617895 | D43: ='Data Sheet'!C75/'Data Sheet'!C$66 -> 0.1229224 | E43: ='Data Sheet'!D75/'Data Sheet'!D$66 -> 0.09058862 | F43: ='Data Sheet'!E75/'Data Sheet'!E$66 -> 0.10774032 | G43: ='Data Sheet'!F75/'Data Sheet'!F$66 -> 0.12603671 | H43: ='Data Sheet'!G75/'Data Sheet'!G$66 -> 0.12529864 | I43: ='Data Sheet'!H75/'Data Sheet'!H$66 -> 0.11777536 | J43: ='Data Sheet'!I75/'Data Sheet'!I$66 -> 0.11944141 | ... L43: ='Data Sheet'!K75/'Data Sheet'!K$66 -> 0.13583603
B44: Receivables | C44: ='Data Sheet'!B67/'Data Sheet'!B$66 -> 0.11661248 | D44: ='Data Sheet'!C67/'Data Sheet'!C$66 -> 0.12574073 | E44: ='Data Sheet'!D67/'Data Sheet'!D$66 -> 0.11738253 | F44: ='Data Sheet'!E67/'Data Sheet'!E$66 -> 0.111242 | G44: ='Data Sheet'!F67/'Data Sheet'!F$66 -> 0.12783722 | H44: ='Data Sheet'!G67/'Data Sheet'!G$66 -> 0.16862826 | I44: ='Data Sheet'!H67/'Data Sheet'!H$66 -> 0.17987046 | J44: ='Data Sheet'!I67/'Data Sheet'!I$66 -> 0.16350917 | ... L44: ='Data Sheet'!K67/'Data Sheet'!K$66 -> 0.12925729
B45: Inventory | C45: ='Data Sheet'!B68/'Data Sheet'!B$66 -> 0.21176137 | D45: ='Data Sheet'!C68/'Data Sheet'!C$66 -> 0.19314229 | E45: ='Data Sheet'!D68/'Data Sheet'!D$66 -> 0.19385138 | F45: ='Data Sheet'!E68/'Data Sheet'!E$66 -> 0.21005182 | G45: ='Data Sheet'!F68/'Data Sheet'!F$66 -> 0.18661442 | H45: ='Data Sheet'!G68/'Data Sheet'!G$66 -> 0.26800526 | I45: ='Data Sheet'!H68/'Data Sheet'!H$66 -> 0.24091549 | J45: ='Data Sheet'!I68/'Data Sheet'!I$66 -> 0.19810226 | ... L45: ='Data Sheet'!K68/'Data Sheet'!K$66 -> 0.16639334
B46: Cash & Bank | C46: ='Data Sheet'!B69/'Data Sheet'!B$66 -> 0.064586677 | D46: ='Data Sheet'!C69/'Data Sheet'!C$66 -> 0.029400268 | E46: ='Data Sheet'!D69/'Data Sheet'!D$66 -> 0.027379185 | F46: ='Data Sheet'!E69/'Data Sheet'!E$66 -> 0.048508579 | G46: ='Data Sheet'!F69/'Data Sheet'!F$66 -> 0.030004412 | H46: ='Data Sheet'!G69/'Data Sheet'!G$66 -> 0.037647609 | I46: ='Data Sheet'!H69/'Data Sheet'!H$66 -> 0.032732426 | J46: ='Data Sheet'!I69/'Data Sheet'!I$66 -> 0.036253581 | ... L46: ='Data Sheet'!K69/'Data Sheet'!K$66 -> 0.031104255

Sheet Assumption Sheet
B2: ='Data Sheet'!B1 -> ASIAN PAINTS LTD
B3: (ASIANPAINT | BSE Code: 500820)
B4: =CONCATENATE("INR "&'Data Sheet'!B8) -> INR 2645.2
B5: 52 Week (High - INR 2,985.7 & Low - 2115.0)
B8: ="Assumption Sheet"&" - "&'Data Sheet'!B1 -> Assumption Sheet - ASIAN PAINTS LTD
A10: # | B10: 1. P & L Drivers
B11: Drivers | C11: =IFERROR(HistoricalFS!G3,0) -> 44286 | D11: =IFERROR(HistoricalFS!H3,0) -> 44651 | E11: =IFERROR(HistoricalFS!I3,0) -> 45016 | F11: =IFERROR(HistoricalFS!J3,0) -> 45382 | G11: =IFERROR(HistoricalFS!K3,0) -> 45747 | H11: =IFERROR(HistoricalFS!L3,0) -> 46112 | I11: =H11+365 -> 46477 | J11: =I11+365 -> 46842 | K11: =J11+365 -> 47207 | L11: =K11+365 -> 47572 | M11: =L11+365 -> 47937
B12: Sales Growth Rate (%) | C12: =IFERROR(HistoricalFS!G7,0) -> 0.074292288 | D12: =IFERROR(HistoricalFS!H7,0) -> 0.34028285 | E12: =IFERROR(HistoricalFS!I7,0) -> 0.18512278 | F12: =IFERROR(HistoricalFS!J7,0) -> 0.029173127 | G12: =IFERROR(HistoricalFS!K7,0) -> -0.044770308 | H12: =IFERROR(HistoricalFS!L7,0) -> 0.049487961 | I12: =IF($C$55="Bull Case",I58,I57) -> 0.07 | J12: =IF($C$55="Bull Case",J58,J57) -> 0.07 | K12: =IF($C$55="Bull Case",K58,K57) -> 0.075 | L12: =IF($C$55="Bull Case",L58,L57) -> 0.075 | M12: =IF($C$55="Bull Case",M58,M57) -> 0.08
B13: COGS % of Sales | C13: =IFERROR(HistoricalFS!G10,0) -> 0.64639643 | D13: =IFERROR(HistoricalFS!H10,0) -> 0.7075486 | E13: =IFERROR(HistoricalFS!I10,0) -> 0.68911776 | F13: =IFERROR(HistoricalFS!J10,0) -> 0.64826497 | G13: =IFERROR(HistoricalFS!K10,0) -> 0.67072273 | H13: =IFERROR(HistoricalFS!L10,0) -> 0.66012628 | I13: =IF($C$55="Bull Case",I60,I59) -> 0.66 | J13: =IF($C$55="Bull Case",J60,J59) -> 0.66 | K13: =IF($C$55="Bull Case",K60,K59) -> 0.655 | L13: =IF($C$55="Bull Case",L60,L59) -> 0.655 | M13: =IF($C$55="Bull Case",M60,M59) -> 0.65
B14: Gross Margin (%) | C14: =1-C13 -> 0.35360357 | D14: =1-D13 -> 0.2924514 | E14: =1-E13 -> 0.31088224 | F14: =1-F13 -> 0.35173503 | G14: =1-G13 -> 0.32927727 | H14: =1-H13 -> 0.33987372 | I14: =1-I13 -> 0.34 | J14: =1-J13 -> 0.34 | ... M14: =1-M13 -> 0.35
B15: S&G Exp % Of Sales | C15: =IFERROR(HistoricalFS!G16,0) -> 0.12997501 | D15: =IFERROR(HistoricalFS!H16,0) -> 0.12738615 | E15: =IFERROR(HistoricalFS!I16,0) -> 0.12937757 | F15: =IFERROR(HistoricalFS!J16,0) -> 0.1380419 | G15: =IFERROR(HistoricalFS!K16,0) -> 0.1521323 | H15: =IFERROR(HistoricalFS!L16,0) -> 0.151592 | I15: =IF($C$55="Bull Case",I62,I61) -> 0.15 | J15: =IF($C$55="Bull Case",J62,J61) -> 0.15 | K15: =IF($C$55="Bull Case",K62,K61) -> 0.15 | L15: =IF($C$55="Bull Case",L62,L61) -> 0.15 | M15: =IF($C$55="Bull Case",M62,M61) -> 0.15
B16: EBITDA Margin (%) | C16: =IFERROR(HistoricalFS!G19,0) -> 0.22362856 | D16: =IFERROR(HistoricalFS!H19,0) -> 0.16506525 | E16: =IFERROR(HistoricalFS!I19,0) -> 0.18150467 | F16: =IFERROR(HistoricalFS!J19,0) -> 0.21369313 | G16: =IFERROR(HistoricalFS!K19,0) -> 0.17714497 | H16: =IFERROR(HistoricalFS!L19,0) -> 0.18828172 | I16: =I14-I15 -> 0.19 | J16: =J14-J15 -> 0.19 | K16: =K14-K15 -> 0.195 | L16: =L14-L15 -> 0.195 | M16: =M14-M15 -> 0.2
B17: Depreciation (Cr) | C17: =IFERROR(HistoricalFS!G24,0) -> 791.27 | D17: =IFERROR(HistoricalFS!H24,0) -> 816.36 | E17: =IFERROR(HistoricalFS!I24,0) -> 858.02 | F17: =IFERROR(HistoricalFS!J24,0) -> 853 | G17: =IFERROR(HistoricalFS!K24,0) -> 1026.34 | H17: =IFERROR(HistoricalFS!L24,0) -> 1228.85 | I17: 1350 | J17: 1450 | K17: 1550 | L17: 1650 | M17: 1750
B18: Interest Expense (Cr) | C18: =IFERROR(HistoricalFS!G30,0) -> 91.63 | D18: =IFERROR(HistoricalFS!H30,0) -> 95.41 | E18: =IFERROR(HistoricalFS!I30,0) -> 144.45 | F18: =IFERROR(HistoricalFS!J30,0) -> 205.17 | G18: =IFERROR(HistoricalFS!K30,0) -> 227.02 | H18: =IFERROR(HistoricalFS!L30,0) -> 195.41 | I18: 210 | J18: 220 | K18: 230 | L18: 240 | M18: 250
B19: Effective Tax Rate(%) | C19: =IFERROR(HistoricalFS!G37,0) -> 0.25499785 | D19: =IFERROR(HistoricalFS!H37,0) -> 0.26336766 | E19: =IFERROR(HistoricalFS!I37,0) -> 0.26253201 | F19: =IFERROR(HistoricalFS!J37,0) -> 0.24362221 | G19: =IFERROR(HistoricalFS!K37,0) -> 0.27304348 | H19: =IFERROR(HistoricalFS!L37,0) -> 0.26797136 | I19: 0.26 | J19: 0.26 | K19: 0.26 | L19: 0.26 | M19: 0.26
B20: Other Income(Cr) | C20: =IFERROR(HistoricalFS!G21,0) -> 331.65 | D20: =IFERROR(HistoricalFS!H21,0) -> 295.88 | E20: =IFERROR(HistoricalFS!I21,0) -> 431.46 | F20: =IFERROR(HistoricalFS!J21,0) -> 820.96 | G20: =IFERROR(HistoricalFS!K21,0) -> 350.22 | H20: =IFERROR(HistoricalFS!L21,0) -> 727.97 | I20: 500 | J20: 500 | K20: 500 | L20: 500 | M20: 500
B21: Dividend Payout Ratio | C21: =IFERROR(HistoricalFS!G48,0) -> 0.53392687 | D21: =IFERROR(HistoricalFS!H48,0) -> 0.59545645 | E21: =IFERROR(HistoricalFS!I48,0) -> 0.5864497 | F21: =IFERROR(HistoricalFS!J48,0) -> 0.57472439 | G21: =IFERROR(HistoricalFS!K48,0) -> 0.6412415 | H21: =IFERROR(HistoricalFS!L48,0) -> 0.60022436 | I21: 0.6 | J21: 0.6 | K21: 0.6 | L21: 0.6 | M21: 0.6
A23: # | B23: 2. Working Capital Drivers
B24: Drivers | C24: =IFERROR(HistoricalFS!G3,0) -> 44286 | D24: =IFERROR(HistoricalFS!H3,0) -> 44651 | E24: =IFERROR(HistoricalFS!I3,0) -> 45016 | F24: =IFERROR(HistoricalFS!J3,0) -> 45382 | G24: =IFERROR(HistoricalFS!K3,0) -> 45747 | H24: =IFERROR(HistoricalFS!L3,0) -> 46112 | I24: =H24+365 -> 46477 | J24: =I24+365 -> 46842 | K24: =J24+365 -> 47207 | L24: =K24+365 -> 47572 | M24: =L24+365 -> 47937
B25: Debtor Days | C25: =IFERROR((HistoricalFS!G66/HistoricalFS!G6)*365,0) -> 43.743436 | D25: =IFERROR((HistoricalFS!H66/HistoricalFS!H6)*365,0) -> 48.557163 | E25: =IFERROR((HistoricalFS!I66/HistoricalFS!I6)*365,0) -> 49.073711 | F25: =IFERROR((HistoricalFS!J66/HistoricalFS!J6)*365,0) -> 50.275161 | G25: =IFERROR((HistoricalFS!K66/HistoricalFS!K6)*365,0) -> 46.437206 | H25: =IFERROR((HistoricalFS!L66/HistoricalFS!L6)*365,0) -> 45.767144 | I25: 46 | J25: 46 | K25: 45 | L25: 45 | M25: 44
B26: Inventory Days | C26: =IFERROR((HistoricalFS!G67/HistoricalFS!G9)*365,0) -> 98.787466 | D26: =IFERROR((HistoricalFS!H67/HistoricalFS!H9)*365,0) -> 109.07118 | E26: =IFERROR((HistoricalFS!I67/HistoricalFS!I9)*365,0) -> 95.380663 | F26: =IFERROR((HistoricalFS!J67/HistoricalFS!J9)*365,0) -> 93.961129 | G26: =IFERROR((HistoricalFS!K67/HistoricalFS!K9)*365,0) -> 107.84506 | H26: =IFERROR((HistoricalFS!L67/HistoricalFS!L9)*365,0) -> 89.249888 | I26: 90 | J26: 88 | K26: 86 | L26: 85 | M26: 83
B27: Creditor Days | C27: =IFERROR(('Data Sheet'!F74/HistoricalFS!G9)*365,0) -> 87.87523 | D27: =IFERROR(('Data Sheet'!G74/HistoricalFS!H9)*365,0) -> 73.813401 | E27: =IFERROR(('Data Sheet'!H74/HistoricalFS!I9)*365,0) -> 55.824957 | F27: =IFERROR(('Data Sheet'!I74/HistoricalFS!J9)*365,0) -> 60.769909 | G27: =IFERROR(('Data Sheet'!J74/HistoricalFS!K9)*365,0) -> 61.760843 | H27: =IFERROR(('Data Sheet'!K74/HistoricalFS!L9)*365,0) -> 60.026275 | I27: 60 | J27: 60 | K27: 60 | L27: 62 | M27: 62
A29: # | B29: 3. Capex & Fixed Assets
B30: Drivers | C30: =IFERROR('Assumption Sheet'!C24,0) -> 44286 | D30: =IFERROR('Assumption Sheet'!D24,0) -> 44651 | E30: =IFERROR('Assumption Sheet'!E24,0) -> 45016 | F30: =IFERROR('Assumption Sheet'!F24,0) -> 45382 | G30: =IFERROR('Assumption Sheet'!G24,0) -> 45747 | H30: =IFERROR('Assumption Sheet'!H24,0) -> 46112 | I30: =H30+365 -> 46477 | J30: =I30+365 -> 46842 | K30: =J30+365 -> 47207 | L30: =K30+365 -> 47572 | M30: =L30+365 -> 47937
B31: Capex (Cr) | C31: =ABS(HistoricalFS!G87) -> 289 | D31: =ABS(HistoricalFS!H87) -> 551 | E31: =ABS(HistoricalFS!I87) -> 1446 | F31: =ABS(HistoricalFS!J87) -> 2496 | G31: =ABS(HistoricalFS!K87) -> 1830 | H31: =ABS(HistoricalFS!L87) -> 1487 | I31: =IF($C$55="Bull Case",I64,ForecastFS!H6*I63) -> 1903.7194 | J31: =IF($C$55="Bull Case",J64,ForecastFS!I6*J63) -> 2036.9797 | K31: =IF($C$55="Bull Case",K64,ForecastFS!J6*K63) -> 2189.7532 | L31: =IF($C$55="Bull Case",L64,ForecastFS!K6*L63) -> 2353.9847 | M31: =IF($C$55="Bull Case",M64,ForecastFS!L6*M63) -> 2542.3035
B32: Capex % of Sales | C32: =IFERROR(C31/HistoricalFS!G6,0) -> 0.013310127 | D32: =IFERROR(D31/HistoricalFS!H6,0) -> 0.018933875 | E32: =IFERROR(E31/HistoricalFS!I6,0) -> 0.04192691 | F32: =IFERROR(F31/HistoricalFS!J6,0) -> 0.070320298 | G32: =IFERROR(G31/HistoricalFS!K6,0) -> 0.053973353 | H32: =IFERROR(H31/HistoricalFS!L6,0) -> 0.041788984 | I32: =IFERROR(I31/ForecastFS!H6,0) -> 0.05 | J32: =IFERROR(J31/ForecastFS!I6,0) -> 0.05 | K32: =IFERROR(K31/ForecastFS!J6,0) -> 0.05 | L32: =IFERROR(L31/ForecastFS!K6,0) -> 0.05 | M32: =IFERROR(M31/ForecastFS!L6,0) -> 0.05
B33: Parameter | I33: Value
B34: Risk-Free Rate
B35: Beta
B36: Equity Risk Premium
B37: Cost of Equity
B38: Pre-Tax Cost of Debt
B39: Tax Rate
B40: After-Tax Cost of Debt
B41: Debt
B42: Equity
B43: WACC
B44: Terminal Growth Rate
A46: # | B46: 5. Balance Sheet Drivers
B47: Drivers | C47: =IFERROR('Assumption Sheet'!C24,0) -> 44286 | D47: =IFERROR('Assumption Sheet'!D24,0) -> 44651 | E47: =IFERROR('Assumption Sheet'!E24,0) -> 45016 | F47: =IFERROR('Assumption Sheet'!F24,0) -> 45382 | G47: =IFERROR('Assumption Sheet'!G24,0) -> 45747 | H47: =IFERROR('Assumption Sheet'!H24,0) -> 46112 | I47: =IFERROR('Assumption Sheet'!I24,0) -> 46477 | J47: =IFERROR('Assumption Sheet'!J24,0) -> 46842 | ... M47: =IFERROR('Assumption Sheet'!M24,0) -> 47937
B48: Other Liabilities % of Sales | C48: =IFERROR(HistoricalFS!G57/HistoricalFS!G6,0) -> 0.14171048 | D48: =IFERROR(HistoricalFS!H57/HistoricalFS!H6,0) -> 0.11669555 | E48: =IFERROR(HistoricalFS!I57/HistoricalFS!I6,0) -> 0.12234423 | F48: =IFERROR(HistoricalFS!J57/HistoricalFS!J6,0) -> 0.13712148 | G48: =IFERROR(HistoricalFS!K57/HistoricalFS!K6,0) -> 0.14207527 | H48: =IFERROR(HistoricalFS!L57/HistoricalFS!L6,0) -> 0.15049739 | I48: =$H$48 -> 0.15049739 | J48: =$H$48 -> 0.15049739 | K48: =$H$48 -> 0.15049739 | L48: =$H$48 -> 0.15049739 | M48: =$H$48 -> 0.15049739
B49: Other Assets % of Sales | C49: =IFERROR(HistoricalFS!G63/HistoricalFS!G6,0) -> 0.11815709 | D49: =IFERROR(HistoricalFS!H63/HistoricalFS!H6,0) -> 0.098849947 | E49: =IFERROR(HistoricalFS!I63/HistoricalFS!I6,0) -> 0.088034043 | F49: =IFERROR(HistoricalFS!J63/HistoricalFS!J6,0) -> 0.10061747 | G49: =IFERROR(HistoricalFS!K63/HistoricalFS!K6,0) -> 0.098538531 | H49: =IFERROR(HistoricalFS!L63/HistoricalFS!L6,0) -> 0.13177132 | I49: =$H$49 -> 0.13177132 | J49: =$H$49 -> 0.13177132 | K49: =$H$49 -> 0.13177132 | L49: =$H$49 -> 0.13177132 | M49: =$H$49 -> 0.13177132
B50: Capital Work in Progress (Cr) | C50: =IFERROR(HistoricalFS!G61,0) -> 182.98 | D50: =IFERROR(HistoricalFS!H61,0) -> 426.43 | E50: =IFERROR(HistoricalFS!I61,0) -> 1019.59 | F50: =IFERROR(HistoricalFS!J61,0) -> 2698.37 | G50: =IFERROR(HistoricalFS!K61,0) -> 1254.49 | H50: =IFERROR(HistoricalFS!L61,0) -> 1848.67 | I50: =$H$50 -> 1848.67 | J50: =$H$50 -> 1848.67 | K50: =$H$50 -> 1848.67 | L50: =$H$50 -> 1848.67 | M50: =$H$50 -> 1848.67
B51: Investments (Cr) | C51: =IFERROR(HistoricalFS!G62,0) -> 4736.8 | D51: =IFERROR(HistoricalFS!H62,0) -> 3247.53 | E51: =IFERROR(HistoricalFS!I62,0) -> 4261.71 | F51: =IFERROR(HistoricalFS!J62,0) -> 4587.92 | G51: =IFERROR(HistoricalFS!K62,0) -> 4724.75 | H51: =IFERROR(HistoricalFS!L62,0) -> 7061.74 | I51: =$H$51 -> 7061.74 | J51: =$H$51 -> 7061.74 | K51: =$H$51 -> 7061.74 | L51: =$H$51 -> 7061.74 | M51: =$H$51 -> 7061.74
B52: Borrowings (Cr) | C52: =IFERROR(HistoricalFS!G55,0) -> 1093.12 | D52: =IFERROR(HistoricalFS!H55,0) -> 1586.88 | E52: =IFERROR(HistoricalFS!I55,0) -> 1932.62 | F52: =IFERROR(HistoricalFS!J55,0) -> 2474.38 | G52: =IFERROR(HistoricalFS!K55,0) -> 2290.29 | H52: =IFERROR(HistoricalFS!L55,0) -> 3928.93 | I52: =$H$52 -> 3928.93 | J52: =$H$52 -> 3928.93 | K52: =$H$52 -> 3928.93 | L52: =$H$52 -> 3928.93 | M52: =$H$52 -> 3928.93
A54: # | B54: 6. Scenario Analysis (Base Case vs Bull Case)
B55: Active Scenario (type: Base Case / Bull Case) | C55: Base Case
B57: Sales Growth Rate - Base Case (%) | I57: 0.07 | J57: 0.07 | K57: 0.075 | L57: 0.075 | M57: 0.08
B58: Sales Growth Rate - Bull Case (%) | I58: 0.08 | J58: 0.09 | K58: 0.09 | L58: 0.09 | M58: 0.1
B59: COGS % of Sales - Base Case | I59: 0.66 | J59: 0.66 | K59: 0.655 | L59: 0.655 | M59: 0.65
B60: COGS % of Sales - Bull Case | I60: 0.655 | J60: 0.655 | K60: 0.645 | L60: 0.645 | M60: 0.64
B61: S&G Exp % of Sales - Base Case | I61: 0.15 | J61: 0.15 | K61: 0.15 | L61: 0.15 | M61: 0.15
B62: S&G Exp % of Sales - Bull Case | I62: 0.15 | J62: 0.148 | K62: 0.145 | L62: 0.143 | M62: 0.14
B63: Capex % of Sales - Base Case | I63: 0.05 | J63: 0.05 | K63: 0.05 | L63: 0.05 | M63: 0.05
B64: Capex (Cr) - Bull Case | I64: 1600 | J64: 1500 | K64: 1400 | L64: 1300 | M64: 1200
B66: Implied EBITDA Margin - Base Case (%) [memo] | I66: =1-I59-I61 -> 0.19 | J66: =1-J59-J61 -> 0.19 | K66: =1-K59-K61 -> 0.195 | L66: =1-L59-L61 -> 0.195 | M66: =1-M59-M61 -> 0.2
B67: Implied EBITDA Margin - Bull Case (%) [memo] | I67: =1-I60-I62 -> 0.195 | J67: =1-J60-J62 -> 0.197 | K67: =1-K60-K62 -> 0.21 | L67: =1-L60-L62 -> 0.212 | M67: =1-M60-M62 -> 0.22

Sheet ForecastFS
B2: ="Forecasted Financial Statement"&" - "&'Data Sheet'!B1 -> Forecasted Financial Statement - ASIAN PAINTS LTD
A4: # | B4: ="Income Statement"&" - "&'Data Sheet'!B1 -> Income Statement - ASIAN PAINTS LTD
B5: Particulars | C5: =IFERROR('Assumption Sheet'!D11,0) -> 44651 | D5: =IFERROR('Assumption Sheet'!E11,0) -> 45016 | E5: =IFERROR('Assumption Sheet'!F11,0) -> 45382 | F5: =IFERROR('Assumption Sheet'!G11,0) -> 45747 | G5: =IFERROR('Assumption Sheet'!H11,0) -> 46112 | H5: =IFERROR('Assumption Sheet'!I11,0) -> 46477 | I5: =IFERROR('Assumption Sheet'!J11,0) -> 46842 | J5: =IFERROR('Assumption Sheet'!K11,0) -> 47207 | ... L5: =IFERROR('Assumption Sheet'!M11,0) -> 47937
B6: Sales | C6: =IFERROR(HistoricalFS!H6,0) -> 29101.28 | D6: =IFERROR(HistoricalFS!I6,0) -> 34488.59 | E6: =IFERROR(HistoricalFS!J6,0) -> 35494.73 | F6: =IFERROR(HistoricalFS!K6,0) -> 33905.62 | G6: =IFERROR(HistoricalFS!L6,0) -> 35583.54 | H6: =G6*(1+H7) -> 38074.388 | I6: =H6*(1+I7) -> 40739.595 | J6: =I6*(1+J7) -> 43795.065 | K6: =J6*(1+K7) -> 47079.694 | L6: =K6*(1+L7) -> 50846.07
B7: Sales Growth (%) | C7: =IFERROR(HistoricalFS!H7,0) -> 0.34028285 | D7: =IFERROR(HistoricalFS!I7,0) -> 0.18512278 | E7: =IFERROR(HistoricalFS!J7,0) -> 0.029173127 | F7: =IFERROR(HistoricalFS!K7,0) -> -0.044770308 | G7: =IFERROR(HistoricalFS!L7,0) -> 0.049487961 | H7: =IFERROR('Assumption Sheet'!I12,0) -> 0.07 | I7: =IFERROR('Assumption Sheet'!J12,0) -> 0.07 | J7: =IFERROR('Assumption Sheet'!K12,0) -> 0.075 | K7: =IFERROR('Assumption Sheet'!L12,0) -> 0.075 | L7: =IFERROR('Assumption Sheet'!M12,0) -> 0.08
B9: COGS | C9: =IFERROR(HistoricalFS!H9,0) -> 20590.57 | D9: =IFERROR(HistoricalFS!I9,0) -> 23766.7 | E9: =IFERROR(HistoricalFS!J9,0) -> 23009.99 | F9: =IFERROR(HistoricalFS!K9,0) -> 22741.27 | G9: =IFERROR(HistoricalFS!L9,0) -> 23489.63 | H9: =H6*H10 -> 25129.096 | I9: =I6*I10 -> 26888.133 | J9: =J6*J10 -> 28685.767 | K9: =K6*K10 -> 30837.2 | L9: =L6*L10 -> 33049.945
B10: COGS % of Sales | C10: =IFERROR(HistoricalFS!H10,0) -> 0.7075486 | D10: =IFERROR(HistoricalFS!I10,0) -> 0.68911776 | E10: =IFERROR(HistoricalFS!J10,0) -> 0.64826497 | F10: =IFERROR(HistoricalFS!K10,0) -> 0.67072273 | G10: =IFERROR(HistoricalFS!L10,0) -> 0.66012628 | H10: =IFERROR('Assumption Sheet'!I13,0) -> 0.66 | I10: =IFERROR('Assumption Sheet'!J13,0) -> 0.66 | J10: =IFERROR('Assumption Sheet'!K13,0) -> 0.655 | K10: =IFERROR('Assumption Sheet'!L13,0) -> 0.655 | L10: =IFERROR('Assumption Sheet'!M13,0) -> 0.65
B12: Gross Profit | C12: =C6-C9 -> 8510.71 | D12: =D6-D9 -> 10721.89 | E12: =E6-E9 -> 12484.74 | F12: =F6-F9 -> 11164.35 | G12: =G6-G9 -> 12093.91 | H12: =H6-H9 -> 12945.292 | I12: =I6-I9 -> 13851.462 | J12: =J6-J9 -> 15109.297 | ... L12: =L6-L9 -> 17796.124
B13: Gross Margin (%) | C13: =IFERROR(HistoricalFS!H13,0) -> 0.2924514 | D13: =IFERROR(HistoricalFS!I13,0) -> 0.31088224 | E13: =IFERROR(HistoricalFS!J13,0) -> 0.35173503 | F13: =IFERROR(HistoricalFS!K13,0) -> 0.32927727 | G13: =IFERROR(HistoricalFS!L13,0) -> 0.33987372 | H13: =IFERROR('Assumption Sheet'!I14,0) -> 0.34 | I13: =IFERROR('Assumption Sheet'!J14,0) -> 0.34 | J13: =IFERROR('Assumption Sheet'!K14,0) -> 0.345 | K13: =IFERROR('Assumption Sheet'!L14,0) -> 0.345 | L13: =IFERROR('Assumption Sheet'!M14,0) -> 0.35
B15: S&G Expenses | C15: =IFERROR(HistoricalFS!H15,0) -> 3707.1 | D15: =IFERROR(HistoricalFS!I15,0) -> 4462.05 | E15: =IFERROR(HistoricalFS!J15,0) -> 4899.76 | F15: =IFERROR(HistoricalFS!K15,0) -> 5158.14 | G15: =IFERROR(HistoricalFS!L15,0) -> 5394.18 | H15: =H6*H16 -> 5711.1582 | I15: =I6*I16 -> 6110.9392 | J15: =J6*J16 -> 6569.2597 | K15: =K6*K16 -> 7061.9542 | L15: =L6*L16 -> 7626.9105
B16: S&G % of Sales | C16: =IFERROR(HistoricalFS!H16,0) -> 0.12738615 | D16: =IFERROR(HistoricalFS!I16,0) -> 0.12937757 | E16: =IFERROR(HistoricalFS!J16,0) -> 0.1380419 | F16: =IFERROR(HistoricalFS!K16,0) -> 0.1521323 | G16: =IFERROR(HistoricalFS!L16,0) -> 0.151592 | H16: =IFERROR('Assumption Sheet'!I15,0) -> 0.15 | I16: =IFERROR('Assumption Sheet'!J15,0) -> 0.15 | J16: =IFERROR('Assumption Sheet'!K15,0) -> 0.15 | K16: =IFERROR('Assumption Sheet'!L15,0) -> 0.15 | L16: =IFERROR('Assumption Sheet'!M15,0) -> 0.15
B18: EBITDA | C18: =C12-C15 -> 4803.61 | D18: =D12-D15 -> 6259.84 | E18: =E12-E15 -> 7584.98 | F18: =F12-F15 -> 6006.21 | G18: =G12-G15 -> 6699.73 | H18: =H12-H15 -> 7234.1337 | I18: =I12-I15 -> 7740.523 | J18: =J12-J15 -> 8540.0376 | ... L18: =L12-L15 -> 10169.214
B19: EBITDA Margin (%) | C19: =IFERROR(C18/C6,0) -> 0.16506525 | D19: =IFERROR(D18/D6,0) -> 0.18150467 | E19: =IFERROR(E18/E6,0) -> 0.21369313 | F19: =IFERROR(F18/F6,0) -> 0.17714497 | G19: =IFERROR(G18/G6,0) -> 0.18828172 | H19: =IFERROR(H18/H6,0) -> 0.19 | I19: =IFERROR(I18/I6,0) -> 0.19 | J19: =IFERROR(J18/J6,0) -> 0.195 | ... L19: =IFERROR(L18/L6,0) -> 0.2
B21: Other Income | C21: =IFERROR(HistoricalFS!H21,0) -> 295.88 | D21: =IFERROR(HistoricalFS!I21,0) -> 431.46 | E21: =IFERROR(HistoricalFS!J21,0) -> 820.96 | F21: =IFERROR(HistoricalFS!K21,0) -> 350.22 | G21: =IFERROR(HistoricalFS!L21,0) -> 727.97 | H21: =IFERROR('Assumption Sheet'!I20,0) -> 500 | I21: =IFERROR('Assumption Sheet'!J20,0) -> 500 | J21: =IFERROR('Assumption Sheet'!K20,0) -> 500 | K21: =IFERROR('Assumption Sheet'!L20,0) -> 500 | L21: =IFERROR('Assumption Sheet'!M20,0) -> 500
B22: Depreciation | C22: =IFERROR(HistoricalFS!H24,0) -> 816.36 | D22: =IFERROR(HistoricalFS!I24,0) -> 858.02 | E22: =IFERROR(HistoricalFS!J24,0) -> 853 | F22: =IFERROR(HistoricalFS!K24,0) -> 1026.34 | G22: =IFERROR(HistoricalFS!L24,0) -> 1228.85 | H22: =IFERROR('Assumption Sheet'!I17,0) -> 1350 | I22: =IFERROR('Assumption Sheet'!J17,0) -> 1450 | J22: =IFERROR('Assumption Sheet'!K17,0) -> 1550 | K22: =IFERROR('Assumption Sheet'!L17,0) -> 1650 | L22: =IFERROR('Assumption Sheet'!M17,0) -> 1750
B24: EBIT | C24: =IFERROR(HistoricalFS!H27,0) -> 4283.13 | D24: =IFERROR(HistoricalFS!I27,0) -> 5833.28 | E24: =IFERROR(HistoricalFS!J27,0) -> 7552.94 | F24: =IFERROR(HistoricalFS!K27,0) -> 5330.09 | G24: =IFERROR(HistoricalFS!L27,0) -> 6198.85 | H24: =(H18+H21)-H22 -> 6384.1337 | I24: =(I18+I21)-I22 -> 6790.523 | J24: =(J18+J21)-J22 -> 7490.0376 | K24: =(K18+K21)-K22 -> 8030.5404 | L24: =(L18+L21)-L22 -> 8919.214
B25: EBIT Margin (%) | C25: =IFERROR(C24/C6,0) -> 0.14718012 | D25: =IFERROR(D24/D6,0) -> 0.16913652 | E25: =IFERROR(E24/E6,0) -> 0.21279046 | F25: =IFERROR(F24/F6,0) -> 0.15720373 | G25: =IFERROR(G24/G6,0) -> 0.17420555 | H25: =IFERROR(H24/H6,0) -> 0.16767528 | I25: =IFERROR(I24/I6,0) -> 0.16668116 | J25: =IFERROR(J24/J6,0) -> 0.1710247 | ... L25: =IFERROR(L24/L6,0) -> 0.175416
B27: Interest Expense | C27: =IFERROR(HistoricalFS!H30,0) -> 95.41 | D27: =IFERROR(HistoricalFS!I30,0) -> 144.45 | E27: =IFERROR(HistoricalFS!J30,0) -> 205.17 | F27: =IFERROR(HistoricalFS!K30,0) -> 227.02 | G27: =IFERROR(HistoricalFS!L30,0) -> 195.41 | H27: =IFERROR('Assumption Sheet'!I18,0) -> 210 | I27: =IFERROR('Assumption Sheet'!J18,0) -> 220 | J27: =IFERROR('Assumption Sheet'!K18,0) -> 230 | K27: =IFERROR('Assumption Sheet'!L18,0) -> 240 | L27: =IFERROR('Assumption Sheet'!M18,0) -> 250
B29: Earning Before Tax | C29: =C24-C27 -> 4187.72 | D29: =D24-D27 -> 5688.83 | E29: =E24-E27 -> 7347.77 | F29: =F24-F27 -> 5103.07 | G29: =G24-G27 -> 6003.44 | H29: =H24-H27 -> 6174.1337 | I29: =I24-I27 -> 6570.523 | J29: =J24-J27 -> 7260.0376 | ... L29: =L24-L27 -> 8669.214
B31: Tax | C31: =IFERROR(HistoricalFS!H36,0) -> 1102.91 | D31: =IFERROR(HistoricalFS!I36,0) -> 1493.5 | E31: =IFERROR(HistoricalFS!J36,0) -> 1790.08 | F31: =IFERROR(HistoricalFS!K36,0) -> 1393.36 | G31: =IFERROR(HistoricalFS!L36,0) -> 1608.75 | H31: =H29*H32 -> 1605.2748 | I31: =I29*I32 -> 1708.336 | J31: =J29*J32 -> 1887.6098 | K31: =K29*K32 -> 2025.5405 | L31: =L29*L32 -> 2253.9956
B32: Effective Tax Rate | C32: =IFERROR(HistoricalFS!H37,0) -> 0.26336766 | D32: =IFERROR(HistoricalFS!I37,0) -> 0.26253201 | E32: =IFERROR(HistoricalFS!J37,0) -> 0.24362221 | F32: =IFERROR(HistoricalFS!K37,0) -> 0.27304348 | G32: =IFERROR(HistoricalFS!L37,0) -> 0.26797136 | H32: =IFERROR('Assumption Sheet'!I19,0) -> 0.26 | I32: =IFERROR('Assumption Sheet'!J19,0) -> 0.26 | J32: =IFERROR('Assumption Sheet'!K19,0) -> 0.26 | K32: =IFERROR('Assumption Sheet'!L19,0) -> 0.26 | L32: =IFERROR('Assumption Sheet'!M19,0) -> 0.26
B34: Net Profit | C34: =C29-C31 -> 3084.81 | D34: =D29-D31 -> 4195.33 | E34: =E29-E31 -> 5557.69 | F34: =F29-F31 -> 3709.71 | G34: =G29-G31 -> 4394.69 | H34: =H29-H31 -> 4568.8589 | I34: =I29-I31 -> 4862.187 | J34: =J29-J31 -> 5372.4278 | ... L34: =L29-L31 -> 6415.2184
A36: # | B36: ="Balance Sheet"&" - "&'Data Sheet'!B1 -> Balance Sheet - ASIAN PAINTS LTD
B37: Particulars | C37: =IFERROR(C5,0) -> 44651 | D37: =IFERROR(D5,0) -> 45016 | E37: =IFERROR(E5,0) -> 45382 | F37: =IFERROR(F5,0) -> 45747 | G37: =IFERROR(G5,0) -> 46112 | H37: =IFERROR(H5,0) -> 46477 | I37: =IFERROR(I5,0) -> 46842 | J37: =IFERROR(J5,0) -> 47207 | ... L37: =IFERROR(L5,0) -> 47937
B38: =IFERROR(HistoricalFS!B53,0) -> Equity Share Capital | C38: =IFERROR(HistoricalFS!H53,0) -> 95.92 | D38: =IFERROR(HistoricalFS!I53,0) -> 95.92 | E38: =IFERROR(HistoricalFS!J53,0) -> 95.92 | F38: =IFERROR(HistoricalFS!K53,0) -> 95.92 | G38: =IFERROR(HistoricalFS!L53,0) -> 95.92 | H38: 95.92 | I38: 95.92 | J38: 95.92 | K38: 95.92 | L38: 95.92
B39: =IFERROR(HistoricalFS!B54,0) -> Reserves | C39: =IFERROR(HistoricalFS!H54,0) -> 13715.64 | D39: =IFERROR(HistoricalFS!I54,0) -> 15896.31 | E39: =IFERROR(HistoricalFS!J54,0) -> 18632.38 | F39: =IFERROR(HistoricalFS!K54,0) -> 19303.89 | G39: =IFERROR(HistoricalFS!L54,0) -> 21275.67 | H39: =G39+H34*(1-'Assumption Sheet'!I21) -> 23103.214 | I39: =H39+I34*(1-'Assumption Sheet'!J21) -> 25048.088 | J39: =I39+J34*(1-'Assumption Sheet'!K21) -> 27197.06 | K39: =J39+K34*(1-'Assumption Sheet'!L21) -> 29503.059 | L39: =K39+L34*(1-'Assumption Sheet'!M21) -> 32069.147
B40: =IFERROR(HistoricalFS!B55,0) -> Borrowings | C40: =IFERROR(HistoricalFS!H55,0) -> 1586.88 | D40: =IFERROR(HistoricalFS!I55,0) -> 1932.62 | E40: =IFERROR(HistoricalFS!J55,0) -> 2474.38 | F40: =IFERROR(HistoricalFS!K55,0) -> 2290.29 | G40: =IFERROR(HistoricalFS!L55,0) -> 3928.93 | H40: =IFERROR('Assumption Sheet'!I52,0) -> 3928.93 | I40: =IFERROR('Assumption Sheet'!J52,0) -> 3928.93 | J40: =IFERROR('Assumption Sheet'!K52,0) -> 3928.93 | K40: =IFERROR('Assumption Sheet'!L52,0) -> 3928.93 | L40: =IFERROR('Assumption Sheet'!M52,0) -> 3928.93
B41: =IFERROR(HistoricalFS!B56,0) -> Trade Payables | C41: =IFERROR(HistoricalFS!H56,0) -> 4164 | D41: =IFERROR(HistoricalFS!I56,0) -> 3635 | E41: =IFERROR(HistoricalFS!J56,0) -> 3831 | F41: =IFERROR(HistoricalFS!K56,0) -> 3848 | G41: =IFERROR(HistoricalFS!L56,0) -> 3863 | H41: =IFERROR('Assumption Sheet'!I27*(ForecastFS!H9/365),0) -> 4130.8103 | I41: =IFERROR('Assumption Sheet'!J27*(ForecastFS!I9/365),0) -> 4419.967 | J41: =IFERROR('Assumption Sheet'!K27*(ForecastFS!J9/365),0) -> 4715.4686 | K41: =IFERROR('Assumption Sheet'!L27*(ForecastFS!K9/365),0) -> 5238.0997 | L41: =IFERROR('Assumption Sheet'!M27*(ForecastFS!L9/365),0) -> 5613.9633
B42: =IFERROR(HistoricalFS!B57,0) -> Other Liabilities | C42: =IFERROR(HistoricalFS!H57,0) -> 3395.99 | D42: =IFERROR(HistoricalFS!I57,0) -> 4219.48 | E42: =IFERROR(HistoricalFS!J57,0) -> 4867.09 | F42: =IFERROR(HistoricalFS!K57,0) -> 4817.15 | G42: =IFERROR(HistoricalFS!L57,0) -> 5355.23 | H42: =H6*IFERROR('Assumption Sheet'!I48,0) -> 5730.0961 | I42: =I6*IFERROR('Assumption Sheet'!J48,0) -> 6131.2028 | J42: =J6*IFERROR('Assumption Sheet'!K48,0) -> 6591.043 | K42: =K6*IFERROR('Assumption Sheet'!L48,0) -> 7085.3713 | L42: =L6*IFERROR('Assumption Sheet'!M48,0) -> 7652.201
B43: =IFERROR(HistoricalFS!B58,0) -> Total Liabilities | C43: =IFERROR(HistoricalFS!H58,0) -> 22958.43 | D43: =IFERROR(HistoricalFS!I58,0) -> 25779.33 | E43: =IFERROR(HistoricalFS!J58,0) -> 29900.77 | F43: =IFERROR(HistoricalFS!K58,0) -> 30355.25 | G43: =IFERROR(HistoricalFS!L58,0) -> 34518.75 | H43: =SUM(H38:H42) -> 36988.97 | I43: =SUM(I38:I42) -> 39624.108 | J43: =SUM(J38:J42) -> 42528.421 | K43: =SUM(K38:K42) -> 45851.38 | L43: =SUM(L38:L42) -> 49360.161
B45: =IFERROR(HistoricalFS!B60,0) -> Fixed Assets Net Block | C45: =IFERROR(HistoricalFS!H60,0) -> 5519.06 | D45: =IFERROR(HistoricalFS!I60,0) -> 5770.46 | E45: =IFERROR(HistoricalFS!J60,0) -> 7146.62 | F45: =IFERROR(HistoricalFS!K60,0) -> 9220.1 | G45: =IFERROR(HistoricalFS!L60,0) -> 9640.28 | H45: =G45+'Assumption Sheet'!I31-H22 -> 10193.999 | I45: =H45+'Assumption Sheet'!J31-I22 -> 10780.979 | J45: =I45+'Assumption Sheet'!K31-J22 -> 11420.732 | K45: =J45+'Assumption Sheet'!L31-K22 -> 12124.717 | L45: =K45+'Assumption Sheet'!M31-L22 -> 12917.021
B46: =IFERROR(HistoricalFS!B61,0) -> Capital Work in Progress | C46: =IFERROR(HistoricalFS!H61,0) -> 426.43 | D46: =IFERROR(HistoricalFS!I61,0) -> 1019.59 | E46: =IFERROR(HistoricalFS!J61,0) -> 2698.37 | F46: =IFERROR(HistoricalFS!K61,0) -> 1254.49 | G46: =IFERROR(HistoricalFS!L61,0) -> 1848.67 | H46: =IFERROR('Assumption Sheet'!I50,0) -> 1848.67 | I46: =IFERROR('Assumption Sheet'!J50,0) -> 1848.67 | J46: =IFERROR('Assumption Sheet'!K50,0) -> 1848.67 | K46: =IFERROR('Assumption Sheet'!L50,0) -> 1848.67 | L46: =IFERROR('Assumption Sheet'!M50,0) -> 1848.67
B47: =IFERROR(HistoricalFS!B62,0) -> Investments | C47: =IFERROR(HistoricalFS!H62,0) -> 3247.53 | D47: =IFERROR(HistoricalFS!I62,0) -> 4261.71 | E47: =IFERROR(HistoricalFS!J62,0) -> 4587.92 | F47: =IFERROR(HistoricalFS!K62,0) -> 4724.75 | G47: =IFERROR(HistoricalFS!L62,0) -> 7061.74 | H47: =IFERROR('Assumption Sheet'!I51,0) -> 7061.74 | I47: =IFERROR('Assumption Sheet'!J51,0) -> 7061.74 | J47: =IFERROR('Assumption Sheet'!K51,0) -> 7061.74 | K47: =IFERROR('Assumption Sheet'!L51,0) -> 7061.74 | L47: =IFERROR('Assumption Sheet'!M51,0) -> 7061.74
B48: =IFERROR(HistoricalFS!B63,0) -> Other Assets | C48: =IFERROR(HistoricalFS!H63,0) -> 2876.66 | D48: =IFERROR(HistoricalFS!I63,0) -> 3036.17 | E48: =IFERROR(HistoricalFS!J63,0) -> 3571.39 | F48: =IFERROR(HistoricalFS!K63,0) -> 3341.01 | G48: =IFERROR(HistoricalFS!L63,0) -> 4688.89 | H48: =H6*IFERROR('Assumption Sheet'!I49,0) -> 5017.1123 | I48: =I6*IFERROR('Assumption Sheet'!J49,0) -> 5368.3102 | J48: =J6*IFERROR('Assumption Sheet'!K49,0) -> 5770.9334 | K48: =K6*IFERROR('Assumption Sheet'!L49,0) -> 6203.7534 | L48: =L6*IFERROR('Assumption Sheet'!M49,0) -> 6700.0537
B49: =IFERROR(HistoricalFS!B64,0) -> Total Current Assets | C49: =IFERROR(HistoricalFS!H64,0) -> 12069.68 | D49: =IFERROR(HistoricalFS!I64,0) -> 14087.93 | E49: =IFERROR(HistoricalFS!J64,0) -> 18004.3 | F49: =IFERROR(HistoricalFS!K64,0) -> 18540.35 | G49: =IFERROR(HistoricalFS!L64,0) -> 23239.58 | H49: =SUM(H45:H48) -> 24121.522 | I49: =SUM(I45:I48) -> 25059.699 | J49: =SUM(J45:J48) -> 26102.076 | K49: =SUM(K45:K48) -> 27238.881 | L49: =SUM(L45:L48) -> 28527.484
B51: =IFERROR(HistoricalFS!B66,0) -> Receivables | C51: =IFERROR(HistoricalFS!H66,0) -> 3871.44 | D51: =IFERROR(HistoricalFS!I66,0) -> 4636.94 | E51: =IFERROR(HistoricalFS!J66,0) -> 4889.05 | F51: =IFERROR(HistoricalFS!K66,0) -> 4313.65 | G51: =IFERROR(HistoricalFS!L66,0) -> 4461.8 | H51: =IFERROR('Assumption Sheet'!I25*(ForecastFS!H6/365),0) -> 4798.416 | I51: =IFERROR('Assumption Sheet'!J25*(ForecastFS!I6/365),0) -> 5134.3051 | J51: =IFERROR('Assumption Sheet'!K25*(ForecastFS!J6/365),0) -> 5399.3915 | K51: =IFERROR('Assumption Sheet'!L25*(ForecastFS!K6/365),0) -> 5804.3459 | L51: =IFERROR('Assumption Sheet'!M25*(ForecastFS!L6/365),0) -> 6129.3893
B52: =IFERROR(HistoricalFS!B67,0) -> Inventory | C52: =IFERROR(HistoricalFS!H67,0) -> 6152.98 | D52: =IFERROR(HistoricalFS!I67,0) -> 6210.64 | E52: =IFERROR(HistoricalFS!J67,0) -> 5923.41 | F52: =IFERROR(HistoricalFS!K67,0) -> 6719.27 | G52: =IFERROR(HistoricalFS!L67,0) -> 5743.69 | H52: =IFERROR('Assumption Sheet'!I26*(ForecastFS!H9/365),0) -> 6196.2154 | I52: =IFERROR('Assumption Sheet'!J26*(ForecastFS!I9/365),0) -> 6482.6183 | J52: =IFERROR('Assumption Sheet'!K26*(ForecastFS!J9/365),0) -> 6758.8383 | K52: =IFERROR('Assumption Sheet'!L26*(ForecastFS!K9/365),0) -> 7181.2657 | L52: =IFERROR('Assumption Sheet'!M26*(ForecastFS!L9/365),0) -> 7515.4671
B53: =IFERROR(HistoricalFS!B68,0) -> Cash & Bank | C53: =IFERROR(HistoricalFS!H68,0) -> 864.33 | D53: =IFERROR(HistoricalFS!I68,0) -> 843.82 | E53: =IFERROR(HistoricalFS!J68,0) -> 1084.01 | F53: =IFERROR(HistoricalFS!K68,0) -> 781.98 | G53: =IFERROR(HistoricalFS!L68,0) -> 1073.68 | H53: =H87 -> 1872.8168 | I53: =I87 -> 2947.4855 | J53: =J87 -> 4268.1155 | K53: =K87 -> 5626.8883 | L53: =L87 -> 7187.8205
B54: =IFERROR(HistoricalFS!B69,0) -> Total Non Current Assets | C54: =IFERROR(HistoricalFS!H69,0) -> 10888.75 | D54: =IFERROR(HistoricalFS!I69,0) -> 11691.4 | E54: =IFERROR(HistoricalFS!J69,0) -> 11896.47 | F54: =IFERROR(HistoricalFS!K69,0) -> 11814.9 | G54: =IFERROR(HistoricalFS!L69,0) -> 11279.17 | H54: =SUM(H51:H53) -> 12867.448 | I54: =SUM(I51:I53) -> 14564.409 | J54: =SUM(J51:J53) -> 16426.345 | K54: =SUM(K51:K53) -> 18612.5 | L54: =SUM(L51:L53) -> 20832.677
B56: =IFERROR(HistoricalFS!B71,0) -> Total Assets | C56: =IFERROR(HistoricalFS!H71,0) -> 22958.43 | D56: =IFERROR(HistoricalFS!I71,0) -> 25779.33 | E56: =IFERROR(HistoricalFS!J71,0) -> 29900.77 | F56: =IFERROR(HistoricalFS!K71,0) -> 30355.25 | G56: =IFERROR(HistoricalFS!L71,0) -> 34518.75 | H56: =SUM(H54,H49) -> 36988.97 | I56: =SUM(I54,I49) -> 39624.108 | J56: =SUM(J54,J49) -> 42528.421 | K56: =SUM(K54,K49) -> 45851.38 | L56: =SUM(L54,L49) -> 49360.161
B58: =IFERROR(HistoricalFS!B73,0) -> Check | C58: =IFERROR(C56=C43,0) -> TRUE | D58: =IFERROR(D56=D43,0) -> TRUE | E58: =IFERROR(E56=E43,0) -> TRUE | F58: =IFERROR(F56=F43,0) -> TRUE | G58: =IFERROR(G56=G43,0) -> TRUE | H58: =IFERROR(H56=H43,0) -> TRUE | I58: =IFERROR(I56=I43,0) -> TRUE | J58: =IFERROR(J56=J43,0) -> TRUE | ... L58: =IFERROR(L56=L43,0) -> TRUE
A60: # | B60: ="Cash Flow Statement"&" - "&'Data Sheet'!B1 -> Cash Flow Statement - ASIAN PAINTS LTD
B61: Particulars | C61: =IFERROR(C5,0) -> 44651 | D61: =IFERROR(D5,0) -> 45016 | E61: =IFERROR(E5,0) -> 45382 | F61: =IFERROR(F5,0) -> 45747 | G61: =IFERROR(G5,0) -> 46112 | H61: =IFERROR(H5,0) -> 46477 | I61: =IFERROR(I5,0) -> 46842 | J61: =IFERROR(J5,0) -> 47207 | ... L61: =IFERROR(L5,0) -> 47937
B62: A. Cash Flow From Operations (CFO)
B63: Net Profit (PAT) [post-tax] | C63: =C34 -> 3084.81 | D63: =D34 -> 4195.33 | E63: =E34 -> 5557.69 | F63: =F34 -> 3709.71 | G63: =G34 -> 4394.69 | H63: =H34 -> 4568.8589 | I63: =I34 -> 4862.187 | J63: =J34 -> 5372.4278 | ... L63: =L34 -> 6415.2184
B64: Add: Depreciation | C64: ='Assumption Sheet'!D17 -> 816.36 | D64: ='Assumption Sheet'!E17 -> 858.02 | E64: ='Assumption Sheet'!F17 -> 853 | F64: ='Assumption Sheet'!G17 -> 1026.34 | G64: ='Assumption Sheet'!H17 -> 1228.85 | H64: ='Assumption Sheet'!I17 -> 1350 | I64: ='Assumption Sheet'!J17 -> 1450 | J64: ='Assumption Sheet'!K17 -> 1550 | ... L64: ='Assumption Sheet'!M17 -> 1750
B66: Working Capital Change:
B67: ( - ) Increase in Receivables | D67: =-(C51-D51) -> 765.5 | E67: =-(D51-E51) -> 252.11 | F67: =-(E51-F51) -> -575.4 | G67: =-(F51-G51) -> 148.15 | H67: =-(H51-G51) -> -336.616 | I67: =-(I51-H51) -> -335.88912 | J67: =-(J51-I51) -> -265.08641 | K67: =-(K51-J51) -> -404.95436 | L67: =-(L51-K51) -> -325.04337
B68: ( - ) Increase in Inventory | D68: =-(C52-D52) -> 57.66 | E68: =-(D52-E52) -> -287.23 | F68: =-(E52-F52) -> 795.86 | G68: =-(F52-G52) -> -975.58 | H68: =-(H52-G52) -> -452.52544 | I68: =-(I52-H52) -> -286.40285 | J68: =-(J52-I52) -> -276.22003 | K68: =-(K52-J52) -> -422.4274 | L68: =-(L52-K52) -> -334.20134
B69: ( + ) Increase in Creditors | D69: =D41-C41 -> -529 | E69: =E41-D41 -> 196 | F69: =F41-E41 -> 17 | G69: =G41-F41 -> 15 | H69: =H41-G41 -> 267.81029 | I69: =I41-H41 -> 289.15672 | J69: =J41-I41 -> 295.50158 | K69: =K41-J41 -> 522.6311 | L69: =L41-K41 -> 375.86364
B70: ( +/- ) Other Working Capital Items | D70: =(D42-C42)-(D48-C48) -> 663.98 | E70: =(E42-D42)-(E48-D48) -> 112.39 | F70: =(F42-E42)-(F48-E48) -> 180.44 | G70: =(G42-F42)-(G48-F48) -> -809.8 | H70: =(H42-G42)-(H48-G48) -> 46.6438 | I70: =(I42-H42)-(I48-H48) -> 49.908866 | J70: =(J42-I42)-(J48-I48) -> 57.21695 | K70: =(K42-J42)-(K48-J48) -> 61.508221 | L70: =(L42-K42)-(L48-K48) -> 70.529427
B71: (Memo) Tax already reflected in PAT above | C71: =-C31 -> -1102.91 | D71: =-D31 -> -1493.5 | E71: =-E31 -> -1790.08 | F71: =-F31 -> -1393.36 | G71: =-G31 -> -1608.75 | H71: =-H31 -> -1605.2748 | I71: =-I31 -> -1708.336 | J71: =-J31 -> -1887.6098 | ... L71: =-L31 -> -2253.9956
B72: CFO | D72: =SUM(D67:D70,D63:D64,D71) -> 4517.99 | E72: =SUM(E67:E70,E63:E64,E71) -> 4893.88 | F72: =SUM(F67:F70,F63:F64,F71) -> 3760.59 | G72: =SUM(G67:G70,G63:G64,G71) -> 2392.56 | H72: =SUM(H67:H70,H63:H64) -> 5444.1716 | I72: =SUM(I67:I70,I63:I64) -> 6028.9607 | J72: =SUM(J67:J70,J63:J64) -> 6733.8399 | K72: =SUM(K67:K70,K63:K64) -> 7171.7575 | L72: =SUM(L67:L70,L63:L64) -> 7952.3667
B74: B. Cash Flow From Investing (CFI)
B75: ( - ) Capex | C75: =-'Assumption Sheet'!D31 -> -551 | D75: =-'Assumption Sheet'!E31 -> -1446 | E75: =-'Assumption Sheet'!F31 -> -2496 | F75: =-'Assumption Sheet'!G31 -> -1830 | G75: =-'Assumption Sheet'!H31 -> -1487 | H75: =-'Assumption Sheet'!I31 -> -1903.7194 | I75: =-'Assumption Sheet'!J31 -> -2036.9797 | J75: =-'Assumption Sheet'!K31 -> -2189.7532 | ... L75: =-'Assumption Sheet'!M31 -> -2542.3035
B76: ( - ) Increase in Investments | D76: =-(D47-C47) -> -1014.18 | E76: =-(E47-D47) -> -326.21 | F76: =-(F47-E47) -> -136.83 | G76: =-(G47-F47) -> -2336.99 | H76: =-(H47-G47) -> 0 | I76: =-(I47-H47) -> 0 | J76: =-(J47-I47) -> 0 | K76: =-(K47-J47) -> 0 | L76: =-(L47-K47) -> 0
B77: ( - ) Increase in CWIP | D77: =-(D46-C46) -> -593.16 | E77: =-(E46-D46) -> -1678.78 | F77: =-(F46-E46) -> 1443.88 | G77: =-(G46-F46) -> -594.18 | H77: =-(H46-G46) -> 0 | I77: =-(I46-H46) -> 0 | J77: =-(J46-I46) -> 0 | K77: =-(K46-J46) -> 0 | L77: =-(L46-K46) -> 0
B78: CFI | D78: =SUM(D75:D77) -> -3053.34 | E78: =SUM(E75:E77) -> -4500.99 | F78: =SUM(F75:F77) -> -522.95 | G78: =SUM(G75:G77) -> -4418.17 | H78: =SUM(H75:H77) -> -1903.7194 | I78: =SUM(I75:I77) -> -2036.9797 | J78: =SUM(J75:J77) -> -2189.7532 | K78: =SUM(K75:K77) -> -2353.9847 | L78: =SUM(L75:L77) -> -2542.3035
B80: C. Cash Flow From Financing (CFF)
B81: ( - ) Dividend Paid | C81: =-(C34*'Assumption Sheet'!D21) -> -1836.87 | D81: =-(D34*'Assumption Sheet'!E21) -> -2460.35 | E81: =-(E34*'Assumption Sheet'!F21) -> -3194.14 | F81: =-(F34*'Assumption Sheet'!G21) -> -2378.82 | G81: =-(G34*'Assumption Sheet'!H21) -> -2637.8 | H81: =-(H34*'Assumption Sheet'!I21) -> -2741.3154 | I81: =-(I34*'Assumption Sheet'!J21) -> -2917.3122 | J81: =-(J34*'Assumption Sheet'!K21) -> -3223.4567 | ... L81: =-(L34*'Assumption Sheet'!M21) -> -3849.131
B82: (+/-) Net Borrowing Change | D82: =D40-C40 -> 345.74 | E82: =E40-D40 -> 541.76 | F82: =F40-E40 -> -184.09 | G82: =G40-F40 -> 1638.64 | H82: =H40-G40 -> 0 | I82: =I40-H40 -> 0 | J82: =J40-I40 -> 0 | K82: =K40-J40 -> 0 | L82: =L40-K40 -> 0
B83: CFF | C83: =SUM(C81:C82) -> -1836.87 | D83: =SUM(D81:D82) -> -2114.61 | E83: =SUM(E81:E82) -> -2652.38 | F83: =SUM(F81:F82) -> -2562.91 | G83: =SUM(G81:G82) -> -999.16 | H83: =SUM(H81:H82) -> -2741.3154 | I83: =SUM(I81:I82) -> -2917.3122 | J83: =SUM(J81:J82) -> -3223.4567 | ... L83: =SUM(L81:L82) -> -3849.131
B85: Net Change in Cash | C85: =SUM(C83,C78,C72) -> -1836.87 | D85: =SUM(D83,D78,D72) -> -649.96 | E85: =SUM(E83,E78,E72) -> -2259.49 | F85: =SUM(F83,F78,F72) -> 674.73 | G85: =SUM(G83,G78,G72) -> -3024.77 | H85: =SUM(H83,H78,H72) -> 799.13684 | I85: =SUM(I83,I78,I72) -> 1074.6687 | J85: =SUM(J83,J78,J72) -> 1320.63 | ... L85: =SUM(L83,L78,L72) -> 1560.9322
B86: Opening Cash | D86: =C53 -> 864.33 | E86: =D53 -> 843.82 | F86: =E53 -> 1084.01 | G86: =F53 -> 781.98 | H86: =G53 -> 1073.68 | I86: =H53 -> 1872.8168 | J86: =I53 -> 2947.4855 | K86: =J53 -> 4268.1155 | L86: =K53 -> 5626.8883
B87: Closing Cash | C87: =SUM(C85:C86) -> -1836.87 | D87: =SUM(D85:D86) -> 214.37 | E87: =SUM(E85:E86) -> -1415.67 | F87: =SUM(F85:F86) -> 1758.74 | G87: =SUM(G85:G86) -> -2242.79 | H87: =SUM(H85:H86) -> 1872.8168 | I87: =SUM(I85:I86) -> 2947.4855 | J87: =SUM(J85:J86) -> 4268.1155 | ... L87: =SUM(L85:L86) -> 7187.8205

Sheet Beta-Regression
B2: Regression Beta
T3: Beta | U3: =SLOPE($V$8:$V$67,$H$8:$H$67) -> 1.1308176 | X3: Beta | Y3: =SLOPE($Z$8:$Z$67,$H$8:$H$67) -> 1.3418924 | AB3: Beta | AC3: =SLOPE($AD$8:$AD$67,$H$8:$H$67) -> 1.1511567
B4: ='Data Sheet'!B1 -> ASIAN PAINTS LTD | F4: NIFTY 50 | T4: =WACC!B17 -> Berger Paints | X4: =WACC!B19 -> Indigo Paints | AB4: =WACC!B18 -> Kansai Nerolac
B6: Date | C6: Close | D6: 5Y Monthly Return | F6: Date | G6: Close | H6: 5Y Monthly Return | J6: Beta Drifting | N6: Beta | O6: =K33 -> 1.088124 | T6: Date | U6: Close | V6: 5Y Monthly Return | X6: Date | Y6: Close | Z6: 5Y Monthly Return | AB6: Date | AC6: Close | AD6: 5Y Monthly Return
B7: Jul 3, 2026 | C7: 2737.8 | F7: Jul 3, 2026 | G7: 24270.85 | T7: Jul 3, 2026 | U7: 519.45 | X7: Jul 3, 2026 | Y7: 1065.9 | AB7: Jul 3, 2026 | AC7: 211.83
B8: Jul 1, 2026 | C8: 2744.5 | D8: =C8/C7-1 -> 0.0024472204 | F8: Jul 1, 2026 | G8: 24175.7 | H8: =G8/G7-1 -> -0.0039203407 | J8: Levered Raw Beta | L8: =O6 -> 1.088124 | T8: Jul 1, 2026 | U8: 520.75 | V8: =U8/U7-1 -> 0.002502647 | X8: Jul 1, 2026 | Y8: 1077.1 | Z8: =Y8/Y7-1 -> 0.010507552 | AB8: Jul 1, 2026 | AC8: 212.56 | AD8: =AC8/AC7-1 -> 0.0034461597
B9: Jun 1, 2026 | C9: 2635.7 | D9: =C9/C8-1 -> -0.039642922 | F9: Jun 1, 2026 | G9: 23865.75 | H9: =G9/G8-1 -> -0.012820725 | J9: Raw Beta Weight | L9: 0.75 | T9: Jun 1, 2026 | U9: 510.1 | V9: =U9/U8-1 -> -0.020451272 | X9: Jun 1, 2026 | Y9: 1015.25 | Z9: =Y9/Y8-1 -> -0.057422709 | AB9: Jun 1, 2026 | AC9: 204.06 | AD9: =AC9/AC8-1 -> -0.039988709
B10: May 1, 2026 | C10: 2648.62 | D10: =C10/C9-1 -> 0.0049019236 | F10: May 1, 2026 | G10: 23547.75 | H10: =G10/G9-1 -> -0.013324534 | T10: May 1, 2026 | U10: 500.6 | V10: =U10/U9-1 -> -0.018623799 | X10: May 1, 2026 | Y10: 990.9 | Z10: =Y10/Y9-1 -> -0.02398424 | AB10: May 1, 2026 | AC10: 215.49 | AD10: =AC10/AC9-1 -> 0.056012937
B11: Apr 1, 2026 | C11: 2423.47 | D11: =C11/C10-1 -> -0.085006532 | F11: Apr 1, 2026 | G11: 23997.55 | H11: =G11/G10-1 -> 0.019101613 | J11: Market Beta | L11: 1 | T11: Apr 1, 2026 | U11: 473.1 | V11: =U11/U10-1 -> -0.054934079 | X11: Apr 1, 2026 | Y11: 860.2 | Z11: =Y11/Y10-1 -> -0.13190029 | AB11: Apr 1, 2026 | AC11: 194.87 | AD11: =AC11/AC10-1 -> -0.095688895
B12: Mar 1, 2026 | C12: 2146.58 | D12: =C12/C11-1 -> -0.11425353 | F12: Mar 1, 2026 | G12: 22331.4 | H12: =G12/G11-1 -> -0.069430004 | J12: Market Beta weight | L12: 0.25 | T12: Mar 1, 2026 | U12: 410 | V12: =U12/U11-1 -> -0.13337561 | X12: Mar 1, 2026 | Y12: 710.8 | Z12: =Y12/Y11-1 -> -0.17368054 | AB12: Mar 1, 2026 | AC12: 165.25 | AD12: =AC12/AC11-1 -> -0.15199877
B13: Feb 1, 2026 | C13: 2355.76 | D13: =C13/C12-1 -> 0.097448034 | F13: Feb 1, 2026 | G13: 25178.65 | H13: =G13/G12-1 -> 0.12749984 | T13: Feb 1, 2026 | U13: 456.1 | V13: =U13/U12-1 -> 0.11243902 | X13: Feb 1, 2026 | Y13: 936.8 | Z13: =Y13/Y12-1 -> 0.3179516 | AB13: Feb 1, 2026 | AC13: 201.11 | AD13: =AC13/AC12-1 -> 0.21700454
B14: Jan 1, 2026 | C14: 2407.41 | D14: =C14/C13-1 -> 0.021924984 | F14: Jan 1, 2026 | G14: 25320.65 | H14: =G14/G13-1 -> 0.0056396987 | J14: Adjusted Beta | L14: =(L8*L9)+(L11*L12) -> 1.066093 | T14: Jan 1, 2026 | U14: 462.9 | V14: =U14/U13-1 -> 0.014909011 | X14: Jan 1, 2026 | Y14: 1044.4 | Z14: =Y14/Y13-1 -> 0.11485909 | AB14: Jan 1, 2026 | AC14: 227.48 | AD14: =AC14/AC13-1 -> 0.13112227
B15: Dec 1, 2025 | C15: 2745.68 | D15: =C15/C14-1 -> 0.140512 | F15: Dec 1, 2025 | G15: 26129.6 | H15: =G15/G14-1 -> 0.031948232 | T15: Dec 1, 2025 | U15: 536.55 | V15: =U15/U14-1 -> 0.15910564 | X15: Dec 1, 2025 | Y15: 1143.8 | Z15: =Y15/Y14-1 -> 0.095174263 | AB15: Dec 1, 2025 | AC15: 232.68 | AD15: =AC15/AC14-1 -> 0.022859152
B16: Nov 1, 2025 | C16: 2849.68 | D16: =C16/C15-1 -> 0.037877684 | F16: Nov 1, 2025 | G16: 26202.95 | H16: =G16/G15-1 -> 0.0028071612 | J16: SUMMARY OUTPUT | T16: Nov 1, 2025 | U16: 564.6 | V16: =U16/U15-1 -> 0.052278446 | X16: Nov 1, 2025 | Y16: 1283.65 | Z16: =Y16/Y15-1 -> 0.12226788 | AB16: Nov 1, 2025 | AC16: 233.71 | AD16: =AC16/AC15-1 -> 0.0044266804
B17: Oct 1, 2025 | C17: 2485.32 | D17: =C17/C16-1 -> -0.12785997 | F17: Oct 1, 2025 | G17: 25722.1 | H17: =G17/G16-1 -> -0.018350987 | T17: Oct 1, 2025 | U17: 542.1 | V17: =U17/U16-1 -> -0.039851222 | X17: Oct 1, 2025 | Y17: 999.9 | Z17: =Y17/Y16-1 -> -0.22104935 | AB17: Oct 1, 2025 | AC17: 245.04 | AD17: =AC17/AC16-1 -> 0.048478884
B18: Sep 1, 2025 | C18: 2326.16 | D18: =C18/C17-1 -> -0.064040043 | F18: Sep 1, 2025 | G18: 24611.1 | H18: =G18/G17-1 -> -0.04319243 | J18: Regression Statistics | T18: Sep 1, 2025 | U18: 515.2 | V18: =U18/U17-1 -> -0.049621841 | X18: Sep 1, 2025 | Y18: 1052.2 | Z18: =Y18/Y17-1 -> 0.052305231 | AB18: Sep 1, 2025 | AC18: 244.47 | AD18: =AC18/AC17-1 -> -0.0023261508
B19: Aug 1, 2025 | C19: 2493.05 | D19: =C19/C18-1 -> 0.07174485 | F19: Aug 1, 2025 | G19: 24426.85 | H19: =G19/G18-1 -> -0.0074864594 | J19: Multiple R | K19: 0.56444296 | T19: Aug 1, 2025 | U19: 533 | V19: =U19/U18-1 -> 0.034549689 | X19: Aug 1, 2025 | Y19: 1099.7 | Z19: =Y19/Y18-1 -> 0.045143509 | AB19: Aug 1, 2025 | AC19: 237.17 | AD19: =AC19/AC18-1 -> -0.029860515
B20: Jul 1, 2025 | C20: 2371.79 | D20: =C20/C19-1 -> -0.048639217 | F20: Jul 1, 2025 | G20: 24768.35 | H20: =G20/G19-1 -> 0.013980517 | J20: R Square | K20: 0.31859586 | T20: Jul 1, 2025 | U20: 561.13 | V20: =U20/U19-1 -> 0.052776735 | X20: Jul 1, 2025 | Y20: 1196.31 | Z20: =Y20/Y19-1 -> 0.087851232 | AB20: Jul 1, 2025 | AC20: 242.02 | AD20: =AC20/AC19-1 -> 0.020449467
B21: Jun 1, 2025 | C21: 2317.35 | D21: =C21/C20-1 -> -0.022953128 | F21: Jun 1, 2025 | G21: 25517.05 | H21: =G21/G20-1 -> 0.030228094 | J21: Adjusted R Square | K21: 0.30684751 | T21: Jun 1, 2025 | U21: 588.7 | V21: =U21/U20-1 -> 0.049132999 | X21: Jun 1, 2025 | Y21: 1158.63 | Z21: =Y21/Y20-1 -> -0.031496853 | AB21: Jun 1, 2025 | AC21: 249.18 | AD21: =AC21/AC20-1 -> 0.029584332
B22: May 1, 2025 | C22: 2215.74 | D22: =C22/C21-1 -> -0.043847498 | F22: May 1, 2025 | G22: 24750.7 | H22: =G22/G21-1 -> -0.03003286 | J22: Standard Error | K22: 0.060899735 | T22: May 1, 2025 | U22: 564.51 | V22: =U22/U21-1 -> -0.041090538 | X22: May 1, 2025 | Y22: 1076.13 | Z22: =Y22/Y21-1 -> -0.071204785 | AB22: May 1, 2025 | AC22: 246.79 | AD22: =AC22/AC21-1 -> -0.00959146
B23: Apr 1, 2025 | C23: 2379.14 | D23: =C23/C22-1 -> 0.073745114 | F23: Apr 1, 2025 | G23: 24334.2 | H23: =G23/G22-1 -> -0.016827807 | J23: Observations | K23: 60 | T23: Apr 1, 2025 | U23: 540.57 | V23: =U23/U22-1 -> -0.04240846 | X23: Apr 1, 2025 | Y23: 971.75 | Z23: =Y23/Y22-1 -> -0.096995716 | AB23: Apr 1, 2025 | AC23: 250.17 | AD23: =AC23/AC22-1 -> 0.013695855
B24: Mar 1, 2025 | C24: 2295.72 | D24: =C24/C23-1 -> -0.03506309 | F24: Mar 1, 2025 | G24: 23519.35 | H24: =G24/G23-1 -> -0.033485794 | T24: Mar 1, 2025 | U24: 496.87 | V24: =U24/U23-1 -> -0.080840594 | X24: Mar 1, 2025 | Y24: 939.8 | Z24: =Y24/Y23-1 -> -0.032878827 | AB24: Mar 1, 2025 | AC24: 226.56 | AD24: =AC24/AC23-1 -> -0.094375824
B25: Feb 1, 2025 | C25: 2137.91 | D25: =C25/C24-1 -> -0.068740961 | F25: Feb 1, 2025 | G25: 22124.7 | H25: =G25/G24-1 -> -0.059297982 | J25: ANOVA | T25: Feb 1, 2025 | U25: 485.29 | V25: =U25/U24-1 -> -0.023305895 | X25: Feb 1, 2025 | Y25: 1016.72 | Z25: =Y25/Y24-1 -> 0.081847202 | AB25: Feb 1, 2025 | AC25: 220.49 | AD25: =AC25/AC24-1 -> -0.02679202
B26: Jan 1, 2025 | C26: 2256.64 | D26: =C26/C25-1 -> 0.055535546 | F26: Jan 1, 2025 | G26: 23508.4 | H26: =G26/G25-1 -> 0.062540961 | K26: df | L26: SS | M26: MS | N26: F | O26: Significance F | T26: Jan 1, 2025 | U26: 469.6 | V26: =U26/U25-1 -> -0.032331183 | X26: Jan 1, 2025 | Y26: 1263.31 | Z26: =Y26/Y25-1 -> 0.24253482 | AB26: Jan 1, 2025 | AC26: 226.75 | AD26: =AC26/AC25-1 -> 0.02839131
B27: Dec 1, 2024 | C27: 2237.56 | D27: =C27/C26-1 -> -0.0084550482 | F27: Dec 1, 2024 | G27: 23644.8 | H27: =G27/G26-1 -> 0.0058021813 | J27: Regression | K27: 1 | L27: 0.10057595 | M27: 0.10057595 | N27: 27.118355 | O27: 2.6371799e-06 | T27: Dec 1, 2024 | U27: 445.56 | V27: =U27/U26-1 -> -0.051192504 | X27: Dec 1, 2024 | Y27: 1397.74 | Z27: =Y27/Y26-1 -> 0.10641094 | AB27: Dec 1, 2024 | AC27: 257.79 | AD27: =AC27/AC26-1 -> 0.13689085
B28: Nov 1, 2024 | C28: 2432 | D28: =C28/C27-1 -> 0.086898228 | F28: Nov 1, 2024 | G28: 24131.1 | H28: =G28/G27-1 -> 0.02056689 | J28: Residual | K28: 58 | L28: 0.21510911 | M28: 0.0037087777 | T28: Nov 1, 2024 | U28: 490.41 | V28: =U28/U27-1 -> 0.10065984 | X28: Nov 1, 2024 | Y28: 1429.15 | Z28: =Y28/Y27-1 -> 0.02247199 | AB28: Nov 1, 2024 | AC28: 273.3 | AD28: =AC28/AC27-1 -> 0.060165251
B29: Oct 1, 2024 | C29: 2874.37 | D29: =C29/C28-1 -> 0.18189556 | F29: Oct 1, 2024 | G29: 24205.35 | H29: =G29/G28-1 -> 0.0030769422 | J29: Total | K29: 59 | L29: 0.31568506 | T29: Oct 1, 2024 | U29: 533.22 | V29: =U29/U28-1 -> 0.087294305 | X29: Oct 1, 2024 | Y29: 1640.34 | Z29: =Y29/Y28-1 -> 0.14777315 | AB29: Oct 1, 2024 | AC29: 277.34 | AD29: =AC29/AC28-1 -> 0.014782291
B30: Sep 1, 2024 | C30: 3259.61 | D30: =C30/C29-1 -> 0.13402589 | F30: Sep 1, 2024 | G30: 25810.85 | H30: =G30/G29-1 -> 0.066328312 | T30: Sep 1, 2024 | U30: 618.15 | V30: =U30/U29-1 -> 0.1592776 | X30: Sep 1, 2024 | Y30: 1454.72 | Z30: =Y30/Y29-1 -> -0.11315947 | AB30: Sep 1, 2024 | AC30: 301.07 | AD30: =AC30/AC29-1 -> 0.085562847
B31: Aug 1, 2024 | C31: 3061.53 | D31: =C31/C30-1 -> -0.060768006 | F31: Aug 1, 2024 | G31: 25235.9 | H31: =G31/G30-1 -> -0.022275516 | K31: Coefficients | L31: Standard Error | M31: t Stat | N31: P-value | O31: Lower 95% | P31: Upper 95% | Q31: Lower 95.0% | R31: Upper 95.0% | T31: Aug 1, 2024 | U31: 567.24 | V31: =U31/U30-1 -> -0.082358651 | X31: Aug 1, 2024 | Y31: 1446.04 | Z31: =Y31/Y30-1 -> -0.005966784 | AB31: Aug 1, 2024 | AC31: 288.43 | AD31: =AC31/AC30-1 -> -0.041983592
B32: Jul 1, 2024 | C32: 3020.07 | D32: =C32/C31-1 -> -0.013542248 | F32: Jul 1, 2024 | G32: 24951.15 | H32: =G32/G31-1 -> -0.011283529 | J32: Intercept | K32: 0.0099648328 | L32: 0.0079336185 | M32: 1.2560262 | N32: 0.21414246 | O32: -0.0059160301 | P32: 0.025845696 | Q32: -0.0059160301 | R32: 0.025845696 | T32: Jul 1, 2024 | U32: 547.69 | V32: =U32/U31-1 -> -0.034465129 | X32: Jul 1, 2024 | Y32: 1490.86 | Z32: =Y32/Y31-1 -> 0.030994993 | AB32: Jul 1, 2024 | AC32: 298.84 | AD32: =AC32/AC31-1 -> 0.036091946
B33: Jun 1, 2024 | C33: 2856.16 | D33: =C33/C32-1 -> -0.054273576 | F33: Jun 1, 2024 | G33: 24010.6 | H33: =G33/G32-1 -> -0.037695657 | J33: X Variable 1 | K33: 1.088124 | L33: 0.20895209 | M33: 5.2075287 | N33: 2.6371799e-06 | O33: 0.66986097 | P33: 1.5063871 | Q33: 0.66986097 | R33: 1.5063871 | T33: Jun 1, 2024 | U33: 497.65 | V33: =U33/U32-1 -> -0.091365554 | X33: Jun 1, 2024 | Y33: 1365.59 | Z33: =Y33/Y32-1 -> -0.084025328 | AB33: Jun 1, 2024 | AC33: 262.75 | AD33: =AC33/AC32-1 -> -0.12076697
B34: May 1, 2024 | C34: 2794.03 | D34: =C34/C33-1 -> -0.021752983 | F34: May 1, 2024 | G34: 22530.7 | H34: =G34/G33-1 -> -0.061635278 | T34: May 1, 2024 | U34: 454.03 | V34: =U34/U33-1 -> -0.087651964 | X34: May 1, 2024 | Y34: 1333.07 | Z34: =Y34/Y33-1 -> -0.023813883 | AB34: May 1, 2024 | AC34: 258.79 | AD34: =AC34/AC33-1 -> -0.015071361
B35: Apr 1, 2024 | C35: 2788.89 | D35: =C35/C34-1 -> -0.0018396367 | F35: Apr 1, 2024 | G35: 22604.85 | H35: =G35/G34-1 -> 0.0032910651 | T35: Apr 1, 2024 | U35: 501.95 | V35: =U35/U34-1 -> 0.10554369 | X35: Apr 1, 2024 | Y35: 1366.54 | Z35: =Y35/Y34-1 -> 0.025107459 | AB35: Apr 1, 2024 | AC35: 268.53 | AD35: =AC35/AC34-1 -> 0.037636694
B36: Mar 1, 2024 | C36: 2760.62 | D36: =C36/C35-1 -> -0.010136649 | F36: Mar 1, 2024 | G36: 22326.9 | H36: =G36/G35-1 -> -0.012296034 | T36: Mar 1, 2024 | U36: 565.61 | V36: =U36/U35-1 -> 0.12682538 | X36: Mar 1, 2024 | Y36: 1249.82 | Z36: =Y36/Y35-1 -> -0.085412794 | AB36: Mar 1, 2024 | AC36: 251.73 | AD36: =AC36/AC35-1 -> -0.062562842
B37: Feb 1, 2024 | C37: 2736.52 | D37: =C37/C36-1 -> -0.008729923 | F37: Feb 1, 2024 | G37: 21982.8 | H37: =G37/G36-1 -> -0.015411902 | T37: Feb 1, 2024 | U37: 598.82 | V37: =U37/U36-1 -> 0.058715369 | X37: Feb 1, 2024 | Y37: 1391.3 | Z37: =Y37/Y36-1 -> 0.1132003 | AB37: Feb 1, 2024 | AC37: 277.98 | AD37: =AC37/AC36-1 -> 0.10427839
B38: Jan 1, 2024 | C38: 2868.36 | D38: =C38/C37-1 -> 0.048177978 | F38: Jan 1, 2024 | G38: 21725.7 | H38: =G38/G37-1 -> -0.011695507 | T38: Jan 1, 2024 | U38: 557.81 | V38: =U38/U37-1 -> -0.068484687 | X38: Jan 1, 2024 | Y38: 1435.66 | Z38: =Y38/Y37-1 -> 0.03188385 | AB38: Jan 1, 2024 | AC38: 328.04 | AD38: =AC38/AC37-1 -> 0.1800849
B39: Dec 1, 2023 | C39: 3299.46 | D39: =C39/C38-1 -> 0.15029494 | F39: Dec 1, 2023 | G39: 21731.4 | H39: =G39/G38-1 -> 0.00026236209 | T39: Dec 1, 2023 | U39: 596.8 | V39: =U39/U38-1 -> 0.069898352 | X39: Dec 1, 2023 | Y39: 1482.46 | Z39: =Y39/Y38-1 -> 0.032598247 | AB39: Dec 1, 2023 | AC39: 319.88 | AD39: =AC39/AC38-1 -> -0.024875015
B40: Nov 1, 2023 | C40: 3025.5 | D40: =C40/C39-1 -> -0.083031769 | F40: Nov 1, 2023 | G40: 20133.15 | H40: =G40/G39-1 -> -0.073545653 | T40: Nov 1, 2023 | U40: 566.94 | V40: =U40/U39-1 -> -0.050033512 | X40: Nov 1, 2023 | Y40: 1480.62 | Z40: =Y40/Y39-1 -> -0.0012411802 | AB40: Nov 1, 2023 | AC40: 307.4 | AD40: =AC40/AC39-1 -> -0.03901463
B41: Oct 1, 2023 | C41: 2900 | D41: =C41/C40-1 -> -0.041480747 | F41: Oct 1, 2023 | G41: 19079.6 | H41: =G41/G40-1 -> -0.052329119 | T41: Oct 1, 2023 | U41: 551.35 | V41: =U41/U40-1 -> -0.027498501 | X41: Oct 1, 2023 | Y41: 1392.45 | Z41: =Y41/Y40-1 -> -0.059549378 | AB41: Oct 1, 2023 | AC41: 302.46 | AD41: =AC41/AC40-1 -> -0.016070267
B42: Sep 1, 2023 | C42: 3060.07 | D42: =C42/C41-1 -> 0.055196552 | F42: Sep 1, 2023 | G42: 19638.3 | H42: =G42/G41-1 -> 0.029282585 | T42: Sep 1, 2023 | U42: 561.46 | V42: =U42/U41-1 -> 0.01833681 | X42: Sep 1, 2023 | Y42: 1477.78 | Z42: =Y42/Y41-1 -> 0.061280477 | AB42: Sep 1, 2023 | AC42: 304.72 | AD42: =AC42/AC41-1 -> 0.0074720624
B43: Aug 1, 2023 | C43: 3152.08 | D43: =C43/C42-1 -> 0.03006794 | F43: Aug 1, 2023 | G43: 19253.8 | H43: =G43/G42-1 -> -0.019579088 | T43: Aug 1, 2023 | U43: 591.06 | V43: =U43/U42-1 -> 0.052719695 | X43: Aug 1, 2023 | Y43: 1561.83 | Z43: =Y43/Y42-1 -> 0.056875854 | AB43: Aug 1, 2023 | AC43: 319.31 | AD43: =AC43/AC42-1 -> 0.047880021
B44: Jul 1, 2023 | C44: 3269.46 | D44: =C44/C43-1 -> 0.037238903 | F44: Jul 1, 2023 | G44: 19753.8 | H44: =G44/G43-1 -> 0.0259689 | T44: Jul 1, 2023 | U44: 558.71 | V44: =U44/U43-1 -> -0.054732176 | X44: Jul 1, 2023 | Y44: 1583.76 | Z44: =Y44/Y43-1 -> 0.014041221 | AB44: Jul 1, 2023 | AC44: 321.95 | AD44: =AC44/AC43-1 -> 0.0082678275
B45: Jun 1, 2023 | C45: 3254.65 | D45: =C45/C44-1 -> -0.0045298 | F45: Jun 1, 2023 | G45: 19189.05 | H45: =G45/G44-1 -> -0.028589436 | T45: Jun 1, 2023 | U45: 555.19 | V45: =U45/U44-1 -> -0.0063002273 | X45: Jun 1, 2023 | Y45: 1417.95 | Z45: =Y45/Y44-1 -> -0.10469389 | AB45: Jun 1, 2023 | AC45: 288.25 | AD45: =AC45/AC44-1 -> -0.10467464
... B67: Aug 1, 2021 | C67: 3052.92 | D67: =C67/C66-1 -> -0.013344279 | F67: Aug 1, 2021 | G67: 17132.2 | H67: =G67/G66-1 -> -0.027582351 | T67: Aug 1, 2021 | U67: 669.07 | V67: =U67/U66-1 -> 0.014587914 | X67: Aug 1, 2021 | Y67: 2561.55 | Z67: =Y67/Y66-1 -> 0.010035093 | AB67: Aug 1, 2021 | AC67: 392.04 | AD67: =AC67/AC66-1 -> -0.021636595

Sheet Rm
B2: Return on Market
B4: Year | C4: Annual | E4: Average Return | G4: =AVERAGE(C5:C30) -> 0.15149231
B5: 2000 | C5: -0.1465 | E5: Dividend Yield | G5: 1.30%1
B6: 2001 | C6: -0.1618 | E6: Total Market Return | G6: =SUM(G4:G5) -> 0.15149231
B7: 2002 | C7: 0.0325
B8: 2003 | C8: 0.719 | E8: Geometric Mean | G8: =EXP(SUMPRODUCT(LN(1+C5:C30))/COUNT(C5:C30))-1 -> 0.11650334
B9: 2004 | C9: 0.1068 | E9: Dividend Yield | G9: 1.30%1
B10: 2005 | C10: 0.3634 | E10: Total Market Return | G10: =SUM(G8:G9) -> 0.11650334
B11: 2006 | C11: 0.3983
B12: 2007 | C12: 0.5477
B13: 2008 | C13: -0.5179
B14: 2009 | C14: 0.7576
B15: 2010 | C15: 0.1795
B16: 2011 | C16: -0.2462
B17: 2012 | C17: 0.277
B18: 2013 | C18: 0.0676
B19: 2014 | C19: 0.3139
B20: 2015 | C20: -0.0406
B21: 2016 | C21: 0.0301
B22: 2017 | C22: 0.2865
... B30: 2025 | C30: 0.1051

Sheet WACC
B2: ='Data Sheet'!B1 -> ASIAN PAINTS LTD
B3: (ASIANPAINT | BSE Code: 500820)
B4: =CONCATENATE("INR "&'Data Sheet'!B8) -> INR 2645.2
B5: 52 Week (High - INR 2,985.7 & Low - 2115.0)
B8: Calculation of Weighted Average Cost of Capital
B10: All figures are in INR unless Stated otherwise
B12: Peer Comps
H13: Debt/ | I13: Debt/ | J13: Levered | K13: Unlevered
B14: Company Name | D14: Country | E14: Total Debt | F14: Total Equity | G14: Tax Rate1 | H14: Equity | I14: Capital | J14: Beta2 | K14: Beta3
B16: Asian Paints | D16: India | E16: 3928.93 | F16: 262791.1 | G16: 0.26 | H16: =E16/F16 -> 0.014950773 | I16: =E16/(F16+E16) -> 0.01473054 | J16: ='Beta-Regression'!O6 -> 1.088124 | K16: =J16/(1+(1-G16)*H16) -> 1.0762172
B17: Berger Paints | D17: India | E17: 635.13 | F17: 60457.55 | G17: 0.26 | H17: =E17/F17 -> 0.010505388 | I17: =E17/(F17+E17) -> 0.010396172 | J17: ='Beta-Regression'!U3 -> 1.1308176 | K17: =J17/(1+(1-G17)*H17) -> 1.1220945
B18: Kansai Nerolac | D18: India | E18: 302.73 | F18: 17156.01 | G18: 0.26 | H18: =E18/F18 -> 0.017645711 | I18: =E18/(F18+E18) -> 0.017339739 | J18: ='Beta-Regression'!AC3 -> 1.1511567 | K18: =J18/(1+(1-G18)*H18) -> 1.1363189
B19: Indigo Paints | D19: India | E19: 18.37 | F19: 5080.81 | G19: 0.26 | H19: =E19/F19 -> 0.0036155652 | I19: =E19/(F19+E19) -> 0.00360254 | J19: ='Beta-Regression'!Y3 -> 1.3418924 | K19: =J19/(1+(1-G19)*H19) -> 1.3383117
D21: Average | E21: =AVERAGE(E16:E19) -> 1221.29 | F21: =AVERAGE(F16:F19) -> 86371.367 | G21: =AVERAGE(G16:G19) -> 0.26 | H21: =AVERAGE(H16:H19) -> 0.011679359 | I21: =AVERAGE(I16:I19) -> 0.011517248 | J21: =AVERAGE(J16:J19) -> 1.1779977 | K21: =AVERAGE(K16:K19) -> 1.1682356
D22: Median | E22: =MEDIAN(E16:E19) -> 468.93 | F22: =MEDIAN(F16:F19) -> 38806.78 | G22: =MEDIAN(G16:G19) -> 0.26 | H22: =MEDIAN(H16:H19) -> 0.01272808 | I22: =MEDIAN(I16:I19) -> 0.012563356 | J22: =MEDIAN(J16:J19) -> 1.1409872 | K22: =MEDIAN(K16:K19) -> 1.1292067
B25: Cost of Debt | H25: Cost of Equity
B27: Pre-Tax Cost of Debt | F27: 0.0497 | H27: Risk Free Rate | K27: 0.0672
B28: Tax Rate | F28: =G21 -> 0.26 | H28: Equity Risk Premium | K28: =Rm!G10-WACC!K27 -> 0.049303341
B29: Post-Tax Cost of Debt | F29: =F27*(1-F28) -> 0.036778 | H29: Levered Beta4 | K29: =K37 -> 1.1389661
H30: Cost of Equity | K30: =K27+(K28*K29) -> 0.12335483
B32: Cost Structure | H32: Levered Beta
E34: Current | F34: Target | H34: Comps Median Unlevered Beta | K34: =K22 -> 1.1292067
B35: Total Debt | D35: 3928.93 | E35: =D35/D37 -> 0.01473054 | F35: =I21 -> 0.011517248 | H35: Target Debt/Equity | K35: =H21 -> 0.011679359
B36: Market Capitalization | D36: 262791.1 | E36: =E37-E35 -> 0.98526946 | F36: =F37-F35 -> 0.98848275 | H36: Tax Rate | K36: =G21 -> 0.26
B37: Total Capital | D37: =SUM(D35:D36) -> 266720.03 | E37: =D37/D37 -> 1 | F37: =E37/E37 -> 1 | H37: Levered Beta | K37: =K34*(1+(1-K36)*K35) -> 1.1389661
B39: Debt/Equity | E39: =E35 -> 0.01473054 | F39: =K35 -> 0.011679359 | H39: Weighted Average Cost of Capital
H41: Cost of Equity | K41: =K30 -> 0.12335483
B42: 1. Tax Rate considered as Marginal Tax Rate for the Country | H42: Equity Weight | K42: =F36 -> 0.98848275
B43: 2. Levered Beta is based on 5 year monthly Data
B44: 3. Unlevered Beta = Levered Beta/(1+(1-Tax Rate)*Debt/Equity | H44: Cost of Debt | K44: =F29 -> 0.036778
B45: 4. Levered Beta = Unlevered Beta*(1+(1-Tax Rate)*Debt/Equity | H45: Debt Weight | K45: =F35 -> 0.011517248
H46: WACC | K46: =(K41*K42)+(K44*K45) -> 0.12235771

Sheet IntrinsiGrowth
B2: Calculation of ROIC | E2: =RawFS!J2 -> 44621 | F2: =RawFS!K2 -> 44986 | G2: =RawFS!L2 -> 45352 | H2: =RawFS!M2 -> 45717 | I2: =RawFS!N2 -> 46082
A4: # | B4: Current Assets
B5: =RawFS!B35 -> Inventories | E5: =RawFS!J35 -> 6153 | F5: =RawFS!K35 -> 6211 | G5: =RawFS!L35 -> 5923 | H5: =RawFS!M35 -> 6719 | I5: =RawFS!N35 -> 5744
B6: =RawFS!B36 -> Trade receivables | E6: =RawFS!J36 -> 3871 | F6: =RawFS!K36 -> 4637 | G6: =RawFS!L36 -> 4889 | H6: =RawFS!M36 -> 4314 | I6: =RawFS!N36 -> 4462
B7: =RawFS!B38 -> Loans n Advances | E7: =RawFS!J38 -> 8 | F7: =RawFS!K38 -> 12 | G7: =RawFS!L38 -> 17 | H7: =RawFS!M38 -> 22 | I7: =RawFS!N38 -> 27
B8: =RawFS!B39 -> Other asset items | E8: =RawFS!J39 -> 2869 | F8: =RawFS!K39 -> 3024 | G8: =RawFS!L39 -> 3555 | H8: =RawFS!M39 -> 3319 | I8: =RawFS!N39 -> 4662
B9: Total Current Assets | E9: =SUM(E5:E8) -> 12901 | F9: =SUM(F5:F8) -> 13884 | G9: =SUM(G5:G8) -> 14384 | H9: =SUM(H5:H8) -> 14374 | I9: =SUM(I5:I8) -> 14895
B11: Current Liabilities
B12: =RawFS!B13 -> Trade Payables | E12: =RawFS!J13 -> 4164 | F12: =RawFS!K13 -> 3635 | G12: =RawFS!L13 -> 3831 | H12: =RawFS!M13 -> 3848 | I12: =RawFS!N13 -> 3863
B13: =RawFS!B14 -> Advance from Customers | E13: =RawFS!J14 -> 76 | F13: =RawFS!K14 -> 108 | G13: =RawFS!L14 -> 154 | H13: =RawFS!M14 -> 174 | I13: =RawFS!N14 -> 107
B14: =RawFS!B15 -> Other liability items | E14: =RawFS!J15 -> 2932 | F14: =RawFS!K15 -> 3657 | G14: =RawFS!L15 -> 4017 | H14: =RawFS!M15 -> 3984 | I14: =RawFS!N15 -> 4604
B15: Total Current Liabilties | E15: =SUM(E12:E14) -> 7172 | F15: =SUM(F12:F14) -> 7400 | G15: =SUM(G12:G14) -> 8002 | H15: =SUM(H12:H14) -> 8006 | I15: =SUM(I12:I14) -> 8574
B17: Net Working Capital | E17: =E9-E15 -> 5729 | F17: =F9-F15 -> 6484 | G17: =G9-G15 -> 6382 | H17: =H9-H15 -> 6368 | I17: =I9-I15 -> 6321
B19: Non Current Assets
B20: =RawFS!B19 -> Land | E20: =RawFS!J19 -> 644 | F20: =RawFS!K19 -> 804 | G20: =RawFS!L19 -> 1126 | H20: =RawFS!M19 -> 1035 | I20: =RawFS!N19 -> 1204
B21: =RawFS!B20 -> Building | E21: =RawFS!J20 -> 2325 | F21: =RawFS!K20 -> 2883 | G21: =RawFS!L20 -> 3390 | H21: =RawFS!M20 -> 3771 | I21: =RawFS!N20 -> 4124
B22: =RawFS!B21 -> Plant Machinery | E22: =RawFS!J21 -> 4531 | F22: =RawFS!K21 -> 4825 | G22: =RawFS!L21 -> 5422 | H22: =RawFS!M21 -> 7576 | I22: =RawFS!N21 -> 8210
B23: =RawFS!B22 -> Equipments | E23: =RawFS!J22 -> 253 | F23: =RawFS!K22 -> 270 | G23: =RawFS!L22 -> 298 | H23: =RawFS!M22 -> 325 | I23: =RawFS!N22 -> 351
B24: =RawFS!B23 -> Furniture n fittings | E24: =RawFS!J23 -> 113 | F24: =RawFS!K23 -> 146 | G24: =RawFS!L23 -> 175 | H24: =RawFS!M23 -> 203 | I24: =RawFS!N23 -> 216
B25: =RawFS!B24 -> Vehicles | E25: =RawFS!J24 -> 32 | F25: =RawFS!K24 -> 36 | G25: =RawFS!L24 -> 40 | H25: =RawFS!M24 -> 34 | I25: =RawFS!N24 -> 45
B26: =RawFS!B25 -> Intangible Assets | E26: =RawFS!J25 -> 345 | F26: =RawFS!K25 -> 422 | G26: =RawFS!L25 -> 850 | H26: =RawFS!M25 -> 827 | I26: =RawFS!N25 -> 833
B27: =RawFS!B26 -> Other fixed assets | E27: =RawFS!J26 -> 294 | F27: =RawFS!K26 -> 289 | G27: =RawFS!L26 -> 321 | H27: =RawFS!M26 -> 328 | I27: =RawFS!N26 -> 335
B28: =RawFS!B27 -> Gross Block | E28: =RawFS!J27 -> 8538 | F28: =RawFS!K27 -> 9676 | G28: =RawFS!L27 -> 11622 | H28: =RawFS!M27 -> 14099 | I28: =RawFS!N27 -> 15316
B29: =RawFS!B28 -> Accumulated Depreciation | E29: =RawFS!J28 -> 3019 | F29: =RawFS!K28 -> 3905 | G29: =RawFS!L28 -> 4475 | H29: =RawFS!M28 -> 4879 | I29: =RawFS!N28 -> 5676
B30: Total Non Current Assets | E30: =E28-E29 -> 5519 | F30: =F28-F29 -> 5771 | G30: =G28-G29 -> 7147 | H30: =H28-H29 -> 9220 | I30: =I28-I29 -> 9640
A32: # | B32: Invested Capital | E32: =E30+E17 -> 11248 | F32: =F30+F17 -> 12255 | G32: =G30+G17 -> 13529 | H32: =H30+H17 -> 15588 | I32: =I30+I17 -> 15961
B33: EBIT | E33: =HistoricalFS!H27 -> 4283.13 | F33: =HistoricalFS!I27 -> 5833.28 | G33: =HistoricalFS!J27 -> 7552.94 | H33: =HistoricalFS!K27 -> 5330.09 | I33: =HistoricalFS!L27 -> 6198.85
B34: NOPAT EBIT(1-T) | E34: =E33*(1-'Assumption Sheet'!D19) -> 3155.0921 | F34: =F33*(1-'Assumption Sheet'!E19) -> 4301.8573 | G34: =G33*(1-'Assumption Sheet'!F19) -> 5712.876 | H34: =H33*(1-'Assumption Sheet'!G19) -> 3874.7437 | I34: =I33*(1-'Assumption Sheet'!H19) -> 4537.7357
B36: ROIC | E36: =E34/E32 -> 0.2805025 | F36: =F34/F32 -> 0.35102874 | G36: =G34/G32 -> 0.42226891 | H36: =H34/H32 -> 0.24857221 | I36: =I34/I32 -> 0.28430147
B38: Calculation of Reinvested Capital | E38: =E2 -> 44621 | F38: =F2 -> 44986 | G38: =G2 -> 45352 | H38: =H2 -> 45717 | I38: =I2 -> 46082
B40: Net Capex | E40: =-SUM(RawFS!J54:J55) -> 511 | F40: =-SUM(RawFS!K54:K55) -> 1420 | G40: =-SUM(RawFS!L54:L55) -> 2491 | H40: =-SUM(RawFS!M54:M55) -> 1820 | I40: =-SUM(RawFS!N54:N55) -> 1484
B41: Change in Working Capital | F41: =F17-E17 -> 755 | G41: =G17-F17 -> -102 | H41: =H17-G17 -> -14 | I41: =I17-H17 -> -47
B43: EBIT | E43: =E33 -> 4283.13 | F43: =F33 -> 5833.28 | G43: =G33 -> 7552.94 | H43: =H33 -> 5330.09 | I43: =I33 -> 6198.85
B44: Marginal Tax Rate | E44: ='Assumption Sheet'!D19 -> 0.26336766 | F44: ='Assumption Sheet'!E19 -> 0.26253201 | G44: ='Assumption Sheet'!F19 -> 0.24362221 | H44: ='Assumption Sheet'!G19 -> 0.27304348 | I44: ='Assumption Sheet'!H19 -> 0.26797136
B45: EBIT(1-T) | E45: =E43*(1-E44) -> 3155.0921 | F45: =F43*(1-F44) -> 4301.8573 | G45: =G43*(1-G44) -> 5712.876 | H45: =H43*(1-H44) -> 3874.7437 | I45: =I43*(1-I44) -> 4537.7357
B47: Reinvestment | F47: =SUM(F40:F41) -> 2175 | G47: =SUM(G40:G41) -> 2389 | H47: =SUM(H40:H41) -> 1806 | I47: =SUM(I40:I41) -> 1437
B48: Reinvestment Rate | F48: =F47/F45 -> 0.50559558 | G48: =G47/G45 -> 0.41817816 | H48: =H47/H45 -> 0.46609535 | I48: =I47/I45 -> 0.31667776
G50: 4 Years Average | I50: =AVERAGE(F48:I48) -> 0.42663671
G51: 4Years Median | I51: =MEDIAN(F48:I48) -> 0.44213676
B53: Calculation of Growth Rate | E53: =E38 -> 44621 | F53: =F38 -> 44986 | G53: =G38 -> 45352 | H53: =H38 -> 45717 | I53: =I38 -> 46082
B55: Reinvestment Rate | F55: =F48 -> 0.50559558 | G55: =G48 -> 0.41817816 | H55: =H48 -> 0.46609535 | I55: =I48 -> 0.31667776
B56: ROIC | F56: =F36 -> 0.35102874 | G56: =G36 -> 0.42226891 | H56: =H36 -> 0.24857221 | I56: =I36 -> 0.28430147
B58: Intrinsic Growth Rate | F58: =F56*F55 -> 0.17747858 | G58: =G56*G55 -> 0.17658364 | H58: =H56*H55 -> 0.11585835 | I58: =I56*I55 -> 0.090031953

Sheet DCF
B2: ='Data Sheet'!B1 -> ASIAN PAINTS LTD
B3: (ASIANPAINT | BSE Code: 500820)
B4: =CONCATENATE("INR "&'Data Sheet'!B8) -> INR 2645.2
B5: 52 Week (High - INR 2,985.7 & Low - 2115.0)
B8: Calculation of PV of FCFF | G8: =ForecastFS!F5 -> 45747 | H8: =ForecastFS!G5 -> 46112 | I8: =ForecastFS!H5 -> 46477 | J8: =ForecastFS!I5 -> 46842 | K8: =ForecastFS!J5 -> 47207 | L8: =ForecastFS!K5 -> 47572 | M8: =ForecastFS!L5 -> 47937
B10: EBIT | G10: =ForecastFS!F24 -> 5330.09 | H10: =ForecastFS!G24 -> 6198.85 | I10: =ForecastFS!H24 -> 6384.1337 | J10: =ForecastFS!I24 -> 6790.523 | K10: =ForecastFS!J24 -> 7490.0376 | L10: =ForecastFS!K24 -> 8030.5404 | M10: =ForecastFS!L24 -> 8919.214
B12: Tax Rate | G12: =ForecastFS!F32 -> 0.27304348 | H12: =ForecastFS!G32 -> 0.26797136 | I12: =ForecastFS!H32 -> 0.26 | J12: =ForecastFS!I32 -> 0.26 | K12: =ForecastFS!J32 -> 0.26 | L12: =ForecastFS!K32 -> 0.26 | M12: =ForecastFS!L32 -> 0.26
B14: EBIT(1-T) | G14: =G10*(1-G12) -> 3874.7437 | H14: =H10*(1-H12) -> 4537.7357 | I14: =I10*(1-I12) -> 4724.2589 | J14: =J10*(1-J12) -> 5024.987 | K14: =K10*(1-K12) -> 5542.6278 | L14: =L10*(1-L12) -> 5942.5999 | M14: =M10*(1-M12) -> 6600.2184
B16: Less: Reinvestment Rate | G16: =IntrinsiGrowth!H48 -> 0.46609535 | H16: =IntrinsiGrowth!I48 -> 0.31667776 | I16: =H$16+(($M$16-$H$16)/4) -> 0.33750832 | J16: =I$16+(($M$16-$H$16)/4) -> 0.35833888 | K16: =J$16+(($M$16-$H$16)/4) -> 0.37916944 | L16: =K$16+(($M$16-$H$16)/4) -> 0.4 | M16: 0.4
B18: Free Cash Flow to Firm | G18: =G14*(1-G16) -> 2068.7437 | H18: =H14*(1-H16) -> 3100.7357 | I18: =I14*(1-I16) -> 3129.7822 | J18: =J14*(1-J16) -> 3224.3388 | K18: =K14*(1-K16) -> 3441.0327 | L18: =L14*(1-L16) -> 3565.5599 | M18: =M14*(1-M16) -> 3960.131
B20: Mid Year Covention | H20: 0.5 | I20: =H20+1 -> 1.5 | J20: =I20+1 -> 2.5 | K20: =J20+1 -> 3.5 | L20: =K20+1 -> 4.5 | M20: =L20+1 -> 5.5
B21: Discounting Factor | H21: =1/(1+$D$27)^H20 -> 0.94391819 | I21: =1/(1+$D$27)^I20 -> 0.84101368 | J21: =1/(1+$D$27)^J20 -> 0.74932767 | K21: =1/(1+$D$27)^K20 -> 0.66763712 | L21: =1/(1+$D$27)^L20 -> 0.59485235 | M21: =1/(1+$D$27)^M20 -> 0.53000246
B23: PV of FCFF | H23: =H18*H21 -> 2926.8408 | I23: =I18*I21 -> 2632.1897 | J23: =J18*J21 -> 2416.0863 | K23: =K18*K21 -> 2297.3612 | L23: =L18*L21 -> 2120.9817 | M23: =M18*M21 -> 2098.8792
B25: Expected Growth | D25: 0.1
B26: Terminal Growth | D26: 0.05
B27: WACC | D27: =WACC!K46 -> 0.12235771
B29: Calculation of Terminal Value | F29: Scenerio Analysis
B31: FCFF(n+1) | D31: =M18*(1+D26) -> 4158.1376 | K31: WACC
B32: WACC | D32: =D27 -> 0.12235771 | G32: =D47 -> 438.85033 | H32: 0.1 | I32: 0.11 | J32: 0.12235771 | K32: 0.13235771 | L32: 0.14235771 | M32: 0.15235771
B33: Terminal Growth Rate | D33: =D26 -> 0.05 | G33: 0.03 | H33: 449.5452 | I33: 408.51719 | J33: 370.08958 | K33: 345.78574 | L33: 325.80806 | M33: 309.09583
G34: 0.04 | H34: 504.24923 | I34: 449.5452 | J34: 400.29544 | K34: 370.08958 | L34: 345.78574 | M34: 325.80806
B35: Terminal Value | D35: =D31/(D32-D33) -> 57466.409 | F35: Growth Rate | G35: 0.05 | H35: 580.83486 | I35: 504.24923 | J35: 438.85033 | K35: 400.29544 | L35: 370.08958 | M35: 345.78574
G36: 0.06 | H36: 695.71332 | I36: 580.83486 | J36: 489.77095 | K36: 438.85033 | L36: 400.29544 | M36: 370.08958
B37: Calculation of Equity Value | G37: 0.07 | H37: 887.1774 | I37: 695.71332 | J37: 560.14261 | K37: 489.77095 | L37: 438.85033 | M37: 400.29544
B39: PV of FCFF | D39: =SUM(H23:M23) -> 14492.339
B40: PV of Terminal Value | D40: =D35*M21 -> 30457.338
B41: Value of Operating Assets | D41: =SUM(D39:D40) -> 44949.677
B43: Add: Cash | D43: ='Data Sheet'!K69 -> 1073.68
B44: Less: Debt | D44: ='Data Sheet'!K59 -> 3928.93
B45: Value of Equity | D45: =D41+D43-D44 -> 42094.427
B46: No of Shares | D46: ='Data Sheet'!B6 -> 95.919779
B47: Equity Value per Shares | D47: =D45/D46 -> 438.85033
B49: Share Price | D49: ='Data Sheet'!B8 -> 2645.2
B50: Discount/Premium | D50: =D49/D47-1 -> 5.0275675

Sheet Comp_Valuation
B2: ='Data Sheet'!B1 -> ASIAN PAINTS LTD
B3: (ASIANPAINT | BSE Code: 500820)
B4: =CONCATENATE("INR "&'Data Sheet'!B8) -> INR 2645.2
B5: 52 Week (High - INR 2,985.7 & Low - 2115.0)
B8: Comparable Company Valuation
D10: Market Data | K10: Financials | O10: Valuation
D12: Share | E12: Shares | F12: Equity | H12: Enterprise
B13: Company | C13: Ticker | D13: Price | E13: Outstanding | F13: Value | G13: Net Debt | H13: Value | K13: Revenue | L13: EBITDA | M13: Net Income | O13: EV/Revenue | P13: EV/EBITDA | Q13: P/E
B14: Asian Paints | D14: =Data!D4 -> 2737.8 | E14: =Data!E4 -> 95.92 | F14: =D14*E14 -> 262609.78 | G14: =Data!F4-Data!G4 -> 2855.25 | H14: =G14+F14 -> 265465.03 | K14: =Data!I4 -> 35583.54 | L14: =Data!L4 -> 7589.12 | M14: =Data!K4 -> 4394.69 | O14: =H14/K14 -> 7.4603321 | P14: =H14/L14 -> 34.979685 | Q14: =F14/M14 -> 59.756155
B15: Berger Paints | D15: =Data!D5 -> 519.45 | E15: =Data!E5 -> 116.6 | F15: =D15*E15 -> 60567.87 | G15: =Data!F5-Data!G5 -> 329.82 | H15: =G15+F15 -> 60897.69 | K15: =Data!I5 -> 11880.25 | L15: =Data!L5 -> 1991.05 | M15: =Data!K5 -> 1128.02 | O15: =H15/K15 -> 5.1259603 | P15: =H15/L15 -> 30.585716 | Q15: =F15/M15 -> 53.693968
B16: Kansai Nerolac | D16: =Data!D6 -> 211.83 | E16: =Data!E6 -> 80.87 | F16: =D16*E16 -> 17130.692 | G16: =Data!F6-Data!G6 -> 76.95 | H16: =G16+F16 -> 17207.642 | K16: =Data!I6 -> 8051.91 | L16: =Data!L6 -> 1049.22 | M16: =Data!K6 -> 575.84 | O16: =H16/K16 -> 2.1370882 | P16: =H16/L16 -> 16.400414 | Q16: =F16/M16 -> 29.749049
B17: JSW Dulux | D17: =Data!D7 -> 3276.6 | E17: =Data!E7 -> 4.55 | F17: =D17*E17 -> 14908.53 | G17: =Data!F7-Data!G7 -> -244.6 | H17: =G17+F17 -> 14663.93 | K17: =Data!I7 -> 3599.2 | L17: =Data!L7 -> 521.2 | M17: =Data!K7 -> 1973.8 | O17: =H17/K17 -> 4.0742193 | P17: =H17/L17 -> 28.134939 | Q17: =F17/M17 -> 7.5532121
B18: Indigo Paints | D18: =Data!D8 -> 1065.9 | E18: =Data!E8 -> 4.77 | F18: =D18*E18 -> 5084.343 | G18: =Data!F8-Data!G8 -> -10.18 | H18: =G18+F18 -> 5074.163 | K18: =Data!I8 -> 1330.12 | L18: =Data!L8 -> 258.94 | M18: =Data!K8 -> 145.39 | O18: =H18/K18 -> 3.814816 | P18: =H18/L18 -> 19.595903 | Q18: =F18/M18 -> 34.970376
B19: Sirca Paints | D19: =Data!D9 -> 402.45 | E19: =Data!E9 -> 5.68 | F19: =D19*E19 -> 2285.916 | G19: =Data!F9-Data!G9 -> -25.66 | H19: =G19+F19 -> 2260.256 | K19: =Data!I9 -> 492.48 | L19: =Data!L9 -> 102.75 | M19: =Data!K9 -> 65.05 | O19: =H19/K19 -> 4.5895387 | P19: =H19/L19 -> 21.997625 | Q19: =F19/M19 -> 35.140907
B20: Shalimar Paints | D20: =Data!D10 -> 51.82 | E20: =Data!E10 -> 8.37 | F20: =D20*E20 -> 433.7334 | G20: =Data!F10-Data!G10 -> 117.67 | H20: =G20+F20 -> 551.4034 | K20: =Data!I10 -> 575.63 | L20: =Data!L10 -> -15.88 | M20: =Data!K10 -> -64.95 | O20: =H20/K20 -> 0.9579129 | P20: =H20/L20 -> -34.723136 | Q20: =F20/M20 -> -6.6779584
B22: High | O22: =MAX(O14:O20) -> 7.4603321 | P22: =MAX(P14:P20) -> 34.979685 | Q22: =MAX(Q14:Q20) -> 59.756155
B23: 75th Percentile | O23: =QUARTILE(O14:O20,3) -> 4.8577495 | P23: =QUARTILE(P14:P20,3) -> 29.360327 | Q23: =QUARTILE(Q14:Q20,3) -> 44.417438
B24: Average | O24: =AVERAGE(O14:O20) -> 4.0228382 | P24: =AVERAGE(P14:P20) -> 16.710164 | Q24: =AVERAGE(Q14:Q20) -> 30.597958
B25: Median | O25: =MEDIAN(O14:O20) -> 4.0742193 | P25: =MEDIAN(P14:P20) -> 21.997625 | Q25: =MEDIAN(Q14:Q20) -> 34.970376
B26: 25th Percentile | O26: =QUARTILE(O14:O20,1) -> 2.9759521 | P26: =QUARTILE(P14:P20,1) -> 17.998158 | Q26: =QUARTILE(Q14:Q20,1) -> 18.65113
B27: Low | O27: =MIN(O14:O20) -> 0.9579129 | P27: =MIN(P14:P20) -> -34.723136 | Q27: =MIN(Q14:Q20) -> -6.6779584
B29: Asian Paints Valuation | O29: EV/Revenue | P29: EV/EBITDA | Q29: P/E
B31: Implied Enterprise Value | O31: =O25*K14 -> 144975.14 | P31: =P25*L14 -> 166942.62 | Q31: =Q32+Q33 -> 156539.21
B32: New Debt | O32: =$G$14 -> 2855.25 | P32: =$G$14 -> 2855.25 | Q32: =$G$14 -> 2855.25
B33: Implied Market Value | O33: =O31-O32 -> 142119.89 | P33: =P31-P32 -> 164087.37 | Q33: =Q25*M14 -> 153683.96
B34: Shares Outstanding | O34: =$E$14 -> 95.92 | P34: =$E$14 -> 95.92 | Q34: =$E$14 -> 95.92
B35: Implied Value Per Share | O35: =O33/O34 -> 1481.6503 | P35: =P33/P34 -> 1710.669 | Q35: =Q33/Q34 -> 1602.2098
O37: =IF(O35>$D$14,"Undervalued","Overvalued") -> Overvalued | P37: =IF(P35>$D$14,"Undervalued","Overvalued") -> Overvalued | Q37: =IF(Q35>$D$14,"Undervalued","Overvalued") -> Overvalued

Sheet Football_Field
B2: ='Data Sheet'!B1 -> ASIAN PAINTS LTD
B3: (ASIANPAINT | BSE Code: 500820)
B4: =CONCATENATE("INR "&'Data Sheet'!B8) -> INR 2645.2
B5: 52 Week (High - INR 2,985.7 & Low - 2115.0)
B9: ="Footbal Field Valuation Summary"&" - "&'Data Sheet'!B1 -> Footbal Field Valuation Summary - ASIAN PAINTS LTD
B11: Football Field Analysis
D12: OpenLow | E12: Low | F12: OpenHigh | G12: High
B13: Comps | D13: =E13 -> 1481.6503 | E13: =Comp_Valuation!O35 -> 1481.6503 | F13: =G13 -> 1602.2098 | G13: =Comp_Valuation!Q35 -> 1602.2098
B14: DCF Bear | D14: =E14 -> 309.09583 | E14: =DCF!M33 -> 309.09583 | F14: =G14 -> 400.29544 | G14: =DCF!M37 -> 400.29544
B15: DCF Base | D15: =E15 -> 370.08958 | E15: =DCF!J33 -> 370.08958 | F15: =G15 -> 560.14261 | G15: =DCF!J37 -> 560.14261
B16: DCF Bull | D16: =E16 -> 449.5452 | E16: =DCF!H33 -> 449.5452 | F16: =G16 -> 887.1774 | G16: =DCF!H37 -> 887.1774
B17: 52W H/L | D17: =E17 -> 2115 | E17: 2115 | F17: =G17 -> 2985.7 | G17: 2985.7

Sheet VAR Historical Approach
B2: Date | C2: Adj Close | D2: Return | E2: Sorted Return | G2: ="Calculation of VAR (Historical Approch)"&" - "&'Data Sheet'!B1 -> Calculation of VAR (Historical Approch) - ASIAN PAINTS LTD
B3: Jul 1, 2022 | C3: 3201.28 | D3: =(C3-C4)/C4 -> 0.12338227 | E3: 0.23692284
B4: Nov 1, 2025 | C4: 2849.68 | D4: =(C4-C5)/C5 -> 0.17586766 | E4: 0.14660486 | G4: Mean | K4: =AVERAGE(E3:E62) -> 0.00079612919
B5: Apr 1, 2026 | C5: 2423.47 | D5: =(C5-C6)/C6 -> -0.21072464 | E5: 0.12899123 | G5: Standard Deviation | K5: =STDEV(E3:E62) -> 0.073156735
B6: May 1, 2023 | C6: 3070.5 | D6: =(C6-C7)/C7 -> 0.15928295 | E6: 0.10012755 | G6: Max | K6: =MAX(E3:E62) -> 0.23692284
B7: May 1, 2026 | C7: 2648.62 | D7: =(C7-C8)/C8 -> -0.19725652 | E7: 0.092903977 | G7: Min | K7: =MIN(E3:E62) -> -0.15390155
B8: Dec 1, 2023 | C8: 3299.46 | D8: =(C8-C9)/C9 -> 0.021533108 | E8: 0.090550322 | G8: CMP | K8: 2752
B9: Dec 1, 2021 | C9: 3229.91 | D9: =(C9-C10)/C10 -> 0.4069268 | E9: 0.076120129
B10: Mar 1, 2025 | C10: 2295.72 | D10: =(C10-C11)/C11 -> -0.076287963 | E10: 0.073815081 | G10: Percentile | H10: Confidence | I10: VAR% | J10: Stock Price | K10: VAR(INR)
B11: Oct 1, 2025 | C11: 2485.32 | D11: =(C11-C12)/C12 -> -0.23754069 | E11: 0.068421777
B12: Sep 1, 2024 | C12: 3259.61 | D12: =(C12-C13)/C13 -> 0.0015239734 | E12: 0.064699676 | G12: 0.05 | H12: =100%-G12 -> 0.95 | I12: =_xlfn.PERCENTILE.INC(E3:E62,G12) -> -0.11843666 | J12: =$K$8*(1-G12) -> 2614.4 | K12: =$K$8-J12 -> 137.6
B13: Jun 1, 2023 | C13: 3254.65 | D13: =(C13-C14)/C14 -> 0.077673696 | E13: 0.059973946 | G13: 0.01 | H13: =100%-G13 -> 0.99 | I13: =_xlfn.PERCENTILE.INC(E4:E63,G13) -> -0.14042014 | J13: =$K$8*(1-G13) -> 2724.48 | K13: =$K$8-J13 -> 27.52
B14: Jul 1, 2024 | C14: 3020.07 | D14: =(C14-C15)/C15 -> 0.21139568 | E14: 0.057388242 | G14: 0.005 | H14: =100%-G14 -> 0.995 | I14: =_xlfn.PERCENTILE.INC(E5:E64,G14) -> -0.14727707 | J14: =$K$8*(1-G14) -> 2738.24 | K14: =$K$8-J14 -> 13.76
B15: Aug 1, 2025 | C15: 2493.05 | D15: =(C15-C16)/C16 -> -0.19338609 | E15: 0.051125943
B16: Apr 1, 2022 | C16: 3090.76 | D16: =(C16-C17)/C17 -> 0.10738649 | E16: 0.05105726
B17: Apr 1, 2023 | C17: 2791.04 | D17: =(C17-C18)/C18 -> 0.20441021 | E17: 0.050946252
B18: Jun 1, 2025 | C18: 2317.35 | D18: =(C18-C19)/C19 -> -0.23406049 | E18: 0.045858269
B19: Nov 1, 2023 | C19: 3025.5 | D19: =(C19-C20)/C20 -> 0.10238659 | E19: 0.043275862
B20: Jul 1, 2026 | C20: 2744.5 | D20: =(C20-C21)/C21 -> 0.0088923689 | E20: 0.041279357
B21: Feb 1, 2023 | C21: 2720.31 | D21: =(C21-C22)/C22 -> 0.14340056 | E21: 0.037767376
B22: Apr 1, 2025 | C22: 2379.14 | D22: =(C22-C23)/C23 -> 0.0030989253 | E22: 0.036337184
B23: Jul 1, 2025 | C23: 2371.79 | D23: =(C23-C24)/C24 -> -0.16958784 | E23: 0.023492351
B24: Jun 1, 2024 | C24: 2856.16 | D24: =(C24-C25)/C25 -> -0.064590716 | E24: 0.022236698
B25: Nov 1, 2022 | C25: 3053.38 | D25: =(C25-C26)/C26 -> -0.06246872 | E25: 0.02170305
B26: Aug 1, 2022 | C26: 3256.83 | D26: =(C26-C27)/C27 -> 0.085089157 | E26: 0.017352434
... B62: Nov 1, 2024 | C62: 2432 | D62: =(C62-C63)/C63 -> #DIV/0! | E62: -0.15390155

Sheet Monte Carlo Simulation
B2: Date | C2: Adj Close | D2: Return | E2: Sorted Return | F2: Replication | G2: Simulated Return | I2: ="Calculation of VAR (Monte Carlo Simulation)"&" - "&'Data Sheet'!B1 -> Calculation of VAR (Monte Carlo Simulation) - ASIAN PAINTS LTD
B3: Jul 1, 2022 | C3: 3201.28 | D3: =(C3-C4)/C4 -> 0.12338227 | E3: 0.23692284 | F3: 1 | G3: =_xlfn.NORM.INV(RAND(),'VAR Historical Approach'!K$4,'VAR Historical Approach'!K$5) -> -0.061158307
B4: Nov 1, 2025 | C4: 2849.68 | D4: =(C4-C5)/C5 -> 0.17586766 | E4: 0.14660486 | F4: 2 | G4: =_xlfn.NORM.INV(RAND(),'VAR Historical Approach'!K$4,'VAR Historical Approach'!K$5) -> -0.059200368 | I4: Mean | M4: =AVERAGE(G3:G62) -> 0.0017369751
B5: Apr 1, 2026 | C5: 2423.47 | D5: =(C5-C6)/C6 -> -0.21072464 | E5: 0.12899123 | F5: 3 | G5: =_xlfn.NORM.INV(RAND(),'VAR Historical Approach'!K$4,'VAR Historical Approach'!K$5) -> 0.031735213 | I5: Standard Deviation | M5: =STDEV(G3:G62) -> 0.077907867
B6: May 1, 2023 | C6: 3070.5 | D6: =(C6-C7)/C7 -> 0.15928295 | E6: 0.10012755 | F6: 4 | G6: =_xlfn.NORM.INV(RAND(),'VAR Historical Approach'!K$4,'VAR Historical Approach'!K$5) -> 0.076746249 | I6: Max | M6: =MAX(G3:G62) -> 0.1758102
B7: May 1, 2026 | C7: 2648.62 | D7: =(C7-C8)/C8 -> -0.19725652 | E7: 0.092903977 | F7: 5 | G7: =_xlfn.NORM.INV(RAND(),'VAR Historical Approach'!K$4,'VAR Historical Approach'!K$5) -> -0.014845475 | I7: Min | M7: =MIN(G3:G62) -> -0.21162357
B8: Dec 1, 2023 | C8: 3299.46 | D8: =(C8-C9)/C9 -> 0.021533108 | E8: 0.090550322 | F8: 6 | G8: =_xlfn.NORM.INV(RAND(),'VAR Historical Approach'!K$4,'VAR Historical Approach'!K$5) -> -0.046963692 | I8: CMP | M8: 2752
B9: Dec 1, 2021 | C9: 3229.91 | D9: =(C9-C10)/C10 -> 0.4069268 | E9: 0.076120129 | F9: 7 | G9: =_xlfn.NORM.INV(RAND(),'VAR Historical Approach'!K$4,'VAR Historical Approach'!K$5) -> -0.0016945982
B10: Mar 1, 2025 | C10: 2295.72 | D10: =(C10-C11)/C11 -> -0.076287963 | E10: 0.073815081 | F10: 8 | G10: =_xlfn.NORM.INV(RAND(),'VAR Historical Approach'!K$4,'VAR Historical Approach'!K$5) -> -0.017870643 | I10: Percentile | J10: Confidence | K10: VAR% | L10: Stock Price | M10: VAR(INR)
B11: Oct 1, 2025 | C11: 2485.32 | D11: =(C11-C12)/C12 -> -0.23754069 | E11: 0.068421777 | F11: 9 | G11: =_xlfn.NORM.INV(RAND(),'VAR Historical Approach'!K$4,'VAR Historical Approach'!K$5) -> 0.12499297
B12: Sep 1, 2024 | C12: 3259.61 | D12: =(C12-C13)/C13 -> 0.0015239734 | E12: 0.064699676 | F12: 10 | G12: =_xlfn.NORM.INV(RAND(),'VAR Historical Approach'!K$4,'VAR Historical Approach'!K$5) -> -0.040082643 | I12: 0.05 | J12: =100%-I12 -> 0.95 | K12: =_xlfn.PERCENTILE.INC($G$3:$G$62,I12) -> -0.10042275 | L12: =$M$8*(1-I12) -> 2614.4 | M12: =$M$8-L12 -> 137.6
B13: Jun 1, 2023 | C13: 3254.65 | D13: =(C13-C14)/C14 -> 0.077673696 | E13: 0.059973946 | F13: 11 | G13: =_xlfn.NORM.INV(RAND(),'VAR Historical Approach'!K$4,'VAR Historical Approach'!K$5) -> 0.059189809 | I13: 0.01 | J13: =100%-I13 -> 0.99 | K13: =_xlfn.PERCENTILE.INC($G$3:$G$62,I13) -> -0.15524988 | L13: =$M$8*(1-I13) -> 2724.48 | M13: =$M$8-L13 -> 27.52
B14: Jul 1, 2024 | C14: 3020.07 | D14: =(C14-C15)/C15 -> 0.21139568 | E14: 0.057388242 | F14: 12 | G14: =_xlfn.NORM.INV(RAND(),'VAR Historical Approach'!K$4,'VAR Historical Approach'!K$5) -> -0.026599526 | I14: 0.005 | J14: =100%-I14 -> 0.995 | K14: =_xlfn.PERCENTILE.INC($G$3:$G$62,I14) -> -0.18343672 | L14: =$M$8*(1-I14) -> 2738.24 | M14: =$M$8-L14 -> 13.76
B15: Aug 1, 2025 | C15: 2493.05 | D15: =(C15-C16)/C16 -> -0.19338609 | E15: 0.051125943 | F15: 13 | G15: =_xlfn.NORM.INV(RAND(),'VAR Historical Approach'!K$4,'VAR Historical Approach'!K$5) -> -0.055329475
B16: Apr 1, 2022 | C16: 3090.76 | D16: =(C16-C17)/C17 -> 0.10738649 | E16: 0.05105726 | F16: 14 | G16: =_xlfn.NORM.INV(RAND(),'VAR Historical Approach'!K$4,'VAR Historical Approach'!K$5) -> 0.075114335
B17: Apr 1, 2023 | C17: 2791.04 | D17: =(C17-C18)/C18 -> 0.20441021 | E17: 0.050946252 | F17: 15 | G17: =_xlfn.NORM.INV(RAND(),'VAR Historical Approach'!K$4,'VAR Historical Approach'!K$5) -> 0.0583674
B18: Jun 1, 2025 | C18: 2317.35 | D18: =(C18-C19)/C19 -> -0.23406049 | E18: 0.045858269 | F18: 16 | G18: =_xlfn.NORM.INV(RAND(),'VAR Historical Approach'!K$4,'VAR Historical Approach'!K$5) -> 0.052857081
B19: Nov 1, 2023 | C19: 3025.5 | D19: =(C19-C20)/C20 -> 0.10238659 | E19: 0.043275862 | F19: 17 | G19: =_xlfn.NORM.INV(RAND(),'VAR Historical Approach'!K$4,'VAR Historical Approach'!K$5) -> -0.075598405
B20: Jul 1, 2026 | C20: 2744.5 | D20: =(C20-C21)/C21 -> 0.0088923689 | E20: 0.041279357 | F20: 18 | G20: =_xlfn.NORM.INV(RAND(),'VAR Historical Approach'!K$4,'VAR Historical Approach'!K$5) -> 0.15093472
B21: Feb 1, 2023 | C21: 2720.31 | D21: =(C21-C22)/C22 -> 0.14340056 | E21: 0.037767376 | F21: 19 | G21: =_xlfn.NORM.INV(RAND(),'VAR Historical Approach'!K$4,'VAR Historical Approach'!K$5) -> 0.052384695
B22: Apr 1, 2025 | C22: 2379.14 | D22: =(C22-C23)/C23 -> 0.0030989253 | E22: 0.036337184 | F22: 20 | G22: =_xlfn.NORM.INV(RAND(),'VAR Historical Approach'!K$4,'VAR Historical Approach'!K$5) -> -0.10032164
B23: Jul 1, 2025 | C23: 2371.79 | D23: =(C23-C24)/C24 -> -0.16958784 | E23: 0.023492351 | F23: 21 | G23: =_xlfn.NORM.INV(RAND(),'VAR Historical Approach'!K$4,'VAR Historical Approach'!K$5) -> -0.025192823
B24: Jun 1, 2024 | C24: 2856.16 | D24: =(C24-C25)/C25 -> -0.064590716 | E24: 0.022236698 | F24: 22 | G24: =_xlfn.NORM.INV(RAND(),'VAR Historical Approach'!K$4,'VAR Historical Approach'!K$5) -> -0.057854662
B25: Nov 1, 2022 | C25: 3053.38 | D25: =(C25-C26)/C26 -> -0.06246872 | E25: 0.02170305 | F25: 23 | G25: =_xlfn.NORM.INV(RAND(),'VAR Historical Approach'!K$4,'VAR Historical Approach'!K$5) -> -0.11607494
B26: Aug 1, 2022 | C26: 3256.83 | D26: =(C26-C27)/C27 -> 0.085089157 | E26: 0.017352434 | F26: 24 | G26: =_xlfn.NORM.INV(RAND(),'VAR Historical Approach'!K$4,'VAR Historical Approach'!K$5) -> -0.060409753
... B62: Nov 1, 2024 | C62: 2432 | D62: =(C62-C63)/C63 -> #DIV/0! | E62: -0.15390155 | F62: 60 | G62: =_xlfn.NORM.INV(RAND(),'VAR Historical Approach'!K$4,'VAR Historical Approach'!K$5) -> -0.069282966

Sheet DUPONT Analysis
B2: ='Data Sheet'!B1 -> ASIAN PAINTS LTD
B3: (ASIANPAINT | BSE Code: 500820)
B4: =CONCATENATE("INR "&'Data Sheet'!B8) -> INR 2645.2
B5: 52 Week (High - INR 2,985.7 & Low - 2115.0)
B7: About The Company
B8: Asian Paints Ltd is an Indian multinational paint company, headquartered in Mumbai. The company is engaged in the business of manufacturing, selling and distribution of paints, coatings, products related to home décor, bath fittings and providing related services. Asian Paints is India's largest paints company by market share. The company has 27 paint manufacturing facilities in 15 countries, servicing consumers in over 60 countries. Asian Paints is also present in the home improvement and décor space in India.
B12: Financial Summary
B50: DUPONT Analysis - Return on Equity & Return on Assets
B52: Return on Equity (ROE)
C53: =HistoricalFS!F3 -> 43921 | D53: =HistoricalFS!G3 -> 44286 | E53: =HistoricalFS!H3 -> 44651 | F53: =HistoricalFS!I3 -> 45016 | G53: =HistoricalFS!J3 -> 45382 | H53: =HistoricalFS!K3 -> 45747 | I53: =HistoricalFS!L3 -> 46112
B54: Net Profit | C54: =HistoricalFS!F39 -> 2774.19 | D54: =HistoricalFS!G39 -> 3206.75 | E54: =HistoricalFS!H39 -> 3084.81 | F54: =HistoricalFS!I39 -> 4195.33 | G54: =HistoricalFS!J39 -> 5557.69 | H54: =HistoricalFS!K39 -> 3709.71 | I54: =HistoricalFS!L39 -> 4394.69
B55: Average Shareholders Equity | C55: =(('Data Sheet'!E57+'Data Sheet'!E58)+('Data Sheet'!D57+'Data Sheet'!D58))/2 -> 9800.355 | D55: =(('Data Sheet'!F57+'Data Sheet'!F58)+('Data Sheet'!E57+'Data Sheet'!E58))/2 -> 11468.225 | E55: =(('Data Sheet'!G57+'Data Sheet'!G58)+('Data Sheet'!F57+'Data Sheet'!F58))/2 -> 13308.925 | F55: =(('Data Sheet'!H57+'Data Sheet'!H58)+('Data Sheet'!G57+'Data Sheet'!G58))/2 -> 14901.895 | G55: =(('Data Sheet'!I57+'Data Sheet'!I58)+('Data Sheet'!H57+'Data Sheet'!H58))/2 -> 17360.265 | H55: =(('Data Sheet'!J57+'Data Sheet'!J58)+('Data Sheet'!I57+'Data Sheet'!I58))/2 -> 19064.055 | I55: =(('Data Sheet'!K57+'Data Sheet'!K58)+('Data Sheet'!J57+'Data Sheet'!J58))/2 -> 20385.7
B56: Return on Equity (ROE) | C56: =C54/C55 -> 0.28307036 | D56: =D54/D55 -> 0.27962043 | E56: =E54/E55 -> 0.23178506 | F56: =F54/F55 -> 0.28152997 | G56: =G54/G55 -> 0.32013855 | H56: =H54/H55 -> 0.19459186 | I56: =I54/I55 -> 0.2155771
B58: ROE - DUPONT Equation
C59: =C53 -> 43921 | D59: =D53 -> 44286 | E59: =E53 -> 44651 | F59: =F53 -> 45016 | G59: =G53 -> 45382 | H59: =H53 -> 45747 | I59: =I53 -> 46112
B60: Net Profit | C60: =C54 -> 2774.19 | D60: =D54 -> 3206.75 | E60: =E54 -> 3084.81 | F60: =F54 -> 4195.33 | G60: =G54 -> 5557.69 | H60: =H54 -> 3709.71 | I60: =I54 -> 4394.69
B61: Revenue | C61: ='Data Sheet'!E17 -> 20211.25 | D61: ='Data Sheet'!F17 -> 21712.79 | E61: ='Data Sheet'!G17 -> 29101.28 | F61: ='Data Sheet'!H17 -> 34488.59 | G61: ='Data Sheet'!I17 -> 35494.73 | H61: ='Data Sheet'!J17 -> 33905.62 | I61: ='Data Sheet'!K17 -> 35583.54
B62: Net Profit Margin (A) | C62: =C60/C61 -> 0.13725969 | D62: =D60/D61 -> 0.14768945 | E62: =E60/E61 -> 0.10600255 | F62: =F60/F61 -> 0.121644 | G62: =G60/G61 -> 0.15657789 | H62: =H60/H61 -> 0.10941283 | I62: =I60/I61 -> 0.12350345
B64: Revenue | C64: =C61 -> 20211.25 | D64: =D61 -> 21712.79 | E64: =E61 -> 29101.28 | F64: =F61 -> 34488.59 | G64: =G61 -> 35494.73 | H64: =H61 -> 33905.62 | I64: =I61 -> 35583.54
B65: Average Total Assets | C65: =('Data Sheet'!E66+'Data Sheet'!D66)/2 -> 16193.405 | D65: =('Data Sheet'!F66+'Data Sheet'!E66)/2 -> 18246.655 | E65: =('Data Sheet'!G66+'Data Sheet'!F66)/2 -> 21656.885 | F65: =('Data Sheet'!H66+'Data Sheet'!G66)/2 -> 24368.88 | G65: =('Data Sheet'!I66+'Data Sheet'!H66)/2 -> 27840.05 | H65: =('Data Sheet'!J66+'Data Sheet'!I66)/2 -> 30128.01 | I65: =('Data Sheet'!K66+'Data Sheet'!J66)/2 -> 32437
B66: Asset Turnover Ratio (B) | C66: =C64/C65 -> 1.2481161 | D66: =D64/D65 -> 1.18996 | E66: =E64/E65 -> 1.3437426 | F66: =F64/F65 -> 1.4152719 | G66: =G64/G65 -> 1.2749521 | H66: =H64/H65 -> 1.1253853 | I66: =I64/I65 -> 1.0970047
B68: Average Total Assets | C68: =C65 -> 16193.405 | D68: =D65 -> 18246.655 | E68: =E65 -> 21656.885 | F68: =F65 -> 24368.88 | G68: =G65 -> 27840.05 | H68: =H65 -> 30128.01 | I68: =I65 -> 32437
B69: Average Shareholders Equity | C69: =C55 -> 9800.355 | D69: =D55 -> 11468.225 | E69: =E55 -> 13308.925 | F69: =F55 -> 14901.895 | G69: =G55 -> 17360.265 | H69: =H55 -> 19064.055 | I69: =I55 -> 20385.7
B70: Equity Multiplier (C) | C70: =C68/C69 -> 1.6523284 | D70: =D68/D69 -> 1.5910618 | E70: =E68/E69 -> 1.6272453 | F70: =F68/F69 -> 1.6352873 | G70: =G68/G69 -> 1.603665 | H70: =H68/H69 -> 1.5803569 | I70: =I68/I69 -> 1.5911644
B72: Return on Equity (A*B*C) | C72: =C70*C66*C62 -> 0.28307036 | D72: =D70*D66*D62 -> 0.27962043 | E72: =E70*E66*E62 -> 0.23178506 | F72: =F70*F66*F62 -> 0.28152997 | G72: =G70*G66*G62 -> 0.32013855 | H72: =H70*H66*H62 -> 0.19459186 | I72: =I70*I66*I62 -> 0.2155771
B74: Return on Assets (ROA)
C75: =C53 -> 43921 | D75: =D53 -> 44286 | E75: =E53 -> 44651 | F75: =F53 -> 45016 | G75: =G53 -> 45382 | H75: =H53 -> 45747 | I75: =I53 -> 46112
B76: Net Profit | C76: =C54 -> 2774.19 | D76: =D54 -> 3206.75 | E76: =E54 -> 3084.81 | F76: =F54 -> 4195.33 | G76: =G54 -> 5557.69 | H76: =H54 -> 3709.71 | I76: =I54 -> 4394.69
B77: Average Total Assets | C77: =C65 -> 16193.405 | D77: =D65 -> 18246.655 | E77: =E65 -> 21656.885 | F77: =F65 -> 24368.88 | G77: =G65 -> 27840.05 | H77: =H65 -> 30128.01 | I77: =I65 -> 32437
B78: Return on Assets (ROA) | C78: =C76/C77 -> 0.17131604 | D78: =D76/D77 -> 0.17574454 | E78: =E76/E77 -> 0.14244015 | F78: =F76/F77 -> 0.17215933 | G78: =G76/G77 -> 0.19962931 | H78: =H76/H77 -> 0.1231316 | I78: =I76/I77 -> 0.13548386
B80: ROA - DUPONT Equation
C81: =C75 -> 43921 | D81: =D75 -> 44286 | E81: =E75 -> 44651 | F81: =F75 -> 45016 | G81: =G75 -> 45382 | H81: =H75 -> 45747 | I81: =I75 -> 46112
B82: Net Profit | C82: =C76 -> 2774.19 | D82: =D76 -> 3206.75 | E82: =E76 -> 3084.81 | F82: =F76 -> 4195.33 | G82: =G76 -> 5557.69 | H82: =H76 -> 3709.71 | I82: =I76 -> 4394.69
B83: Revenue | C83: =C61 -> 20211.25 | D83: =D61 -> 21712.79 | E83: =E61 -> 29101.28 | F83: =F61 -> 34488.59 | G83: =G61 -> 35494.73 | H83: =H61 -> 33905.62 | I83: =I61 -> 35583.54
B84: Net Profit Margin (A) | C84: =C82/C83 -> 0.13725969 | D84: =D82/D83 -> 0.14768945 | E84: =E82/E83 -> 0.10600255 | F84: =F82/F83 -> 0.121644 | G84: =G82/G83 -> 0.15657789 | H84: =H82/H83 -> 0.10941283 | I84: =I82/I83 -> 0.12350345
B86: Revenue | C86: =C83 -> 20211.25 | D86: =D83 -> 21712.79 | E86: =E83 -> 29101.28 | F86: =F83 -> 34488.59 | G86: =G83 -> 35494.73 | H86: =H83 -> 33905.62 | I86: =I83 -> 35583.54
B87: Average Total Assets | C87: =C77 -> 16193.405 | D87: =D77 -> 18246.655 | E87: =E77 -> 21656.885 | F87: =F77 -> 24368.88 | G87: =G77 -> 27840.05 | H87: =H77 -> 30128.01 | I87: =I77 -> 32437
B88: Asset Turnover Ratio (B) | C88: =C86/C87 -> 1.2481161 | D88: =D86/D87 -> 1.18996 | E88: =E86/E87 -> 1.3437426 | F88: =F86/F87 -> 1.4152719 | G88: =G86/G87 -> 1.2749521 | H88: =H86/H87 -> 1.1253853 | I88: =I86/I87 -> 1.0970047
B90: Return on Assets (A*B) | C90: =C88*C84 -> 0.17131604 | D90: =D88*D84 -> 0.17574454 | E90: =E88*E84 -> 0.14244015 | F90: =F88*F84 -> 0.17215933 | G90: =G88*G84 -> 0.19962931 | H90: =H88*H84 -> 0.1231316 | I90: =I88*I84 -> 0.13548386

Sheet ALTMAN'S Z SCORE
B2: ='Data Sheet'!B1 -> ASIAN PAINTS LTD
B3: (ASIANPAINT | BSE Code: 500820)
B4: =CONCATENATE("INR "&'Data Sheet'!B8) -> INR 2645.2
B5: 52 Week (High - INR 2,985.7 & Low - 2115.0)
B7: Altman's Z Score Analysis
B8: Asian Paints Ltd is an Indian multinational paint company, headquartered in Mumbai. The company is engaged in the business of manufacturing, selling and distribution of paints, coatings, products related to home décor, bath fittings and providing related services. Asian Paints is India's largest paints company by market share. The company has 27 paint manufacturing facilities in 15 countries, servicing consumers in over 60 countries. Asian Paints is also present in the home improvement and décor space in India.
B12: Financial Summary
B50: Altman's Z Score Analysis Calculation
B52: Working Capital/Total Assets
C53: =HistoricalFS!F3 -> 43921 | D53: =HistoricalFS!G3 -> 44286 | E53: =HistoricalFS!H3 -> 44651 | F53: =HistoricalFS!I3 -> 45016 | G53: =HistoricalFS!J3 -> 45382 | H53: =HistoricalFS!K3 -> 45747 | I53: =HistoricalFS!L3 -> 46112
B54: Working Capital | C54: ='Data Sheet'!E65-'Data Sheet'!E60 -> 2817.26 | D54: ='Data Sheet'!F65-'Data Sheet'!F60 -> 3121.11 | E54: ='Data Sheet'!G65-'Data Sheet'!G60 -> 6205.42 | F54: ='Data Sheet'!H65-'Data Sheet'!H60 -> 6873.09 | G54: ='Data Sheet'!I65-'Data Sheet'!I60 -> 6769.77 | H54: ='Data Sheet'!J65-'Data Sheet'!J60 -> 6490.76 | I54: ='Data Sheet'!K65-'Data Sheet'!K60 -> 6749.83
B55: Total Assets | C55: ='Data Sheet'!E66 -> 16137.97 | D55: ='Data Sheet'!F66 -> 20355.34 | E55: ='Data Sheet'!G66 -> 22958.43 | F55: ='Data Sheet'!H66 -> 25779.33 | G55: ='Data Sheet'!I66 -> 29900.77 | H55: ='Data Sheet'!J66 -> 30355.25 | I55: ='Data Sheet'!K66 -> 34518.75
B56: Working Capital/Total Assets (A) | C56: =C54/C55 -> 0.17457338 | D56: =D54/D55 -> 0.15333126 | E56: =E54/E55 -> 0.27028939 | F56: =F54/F55 -> 0.26661244 | G56: =G54/G55 -> 0.22640788 | H56: =H54/H55 -> 0.2138266 | I56: =I54/I55 -> 0.19554097
B58: Retained Earnings/Total Assets
C59: =C53 -> 43921 | D59: =D53 -> 44286 | E59: =E53 -> 44651 | F59: =F53 -> 45016 | G59: =G53 -> 45382 | H59: =H53 -> 45747 | I59: =I53 -> 46112
B60: Retained Earnings | C60: =HistoricalFS!F39*HistoricalFS!F50 -> 1623.15 | D60: =HistoricalFS!G39*HistoricalFS!G50 -> 1494.58 | E60: =HistoricalFS!H39*HistoricalFS!H50 -> 1247.94 | F60: =HistoricalFS!I39*HistoricalFS!I50 -> 1734.98 | G60: =HistoricalFS!J39*HistoricalFS!J50 -> 2363.55 | H60: =HistoricalFS!K39*HistoricalFS!K50 -> 1330.89 | I60: =HistoricalFS!L39*HistoricalFS!L50 -> 1756.89
B61: Total Assets | C61: =C55 -> 16137.97 | D61: =D55 -> 20355.34 | E61: =E55 -> 22958.43 | F61: =F55 -> 25779.33 | G61: =G55 -> 29900.77 | H61: =H55 -> 30355.25 | I61: =I55 -> 34518.75
B62: Retained Earnings/Total Assets (B) | C62: =C60/C61 -> 0.10057956 | D62: =D60/D61 -> 0.073424467 | E62: =E60/E61 -> 0.054356504 | F62: =F60/F61 -> 0.067301206 | G62: =G60/G61 -> 0.079046459 | H62: =H60/H61 -> 0.043843816 | I62: =I60/I61 -> 0.050896687
B64: EBIT/Total Assets
C65: =C59 -> 43921 | D65: =D59 -> 44286 | E65: =E59 -> 44651 | F65: =F59 -> 45016 | G65: =G59 -> 45382 | H65: =H59 -> 45747 | I65: =I59 -> 46112
B66: EBIT | C66: =HistoricalFS!F27 -> 3731.37 | D66: =HistoricalFS!G27 -> 4395.98 | E66: =HistoricalFS!H27 -> 4283.13 | F66: =HistoricalFS!I27 -> 5833.28 | G66: =HistoricalFS!J27 -> 7552.94 | H66: =HistoricalFS!K27 -> 5330.09 | I66: =HistoricalFS!L27 -> 6198.85
B67: Total Assets | C67: =C61 -> 16137.97 | D67: =D61 -> 20355.34 | E67: =E61 -> 22958.43 | F67: =F61 -> 25779.33 | G67: =G61 -> 29900.77 | H67: =H61 -> 30355.25 | I67: =I61 -> 34518.75
B68: EBIT/Total Assets (C) | C68: =C66/C67 -> 0.23121681 | D68: =D66/D67 -> 0.215962 | E68: =E66/E67 -> 0.18656023 | F68: =F66/F67 -> 0.22627741 | G68: =G66/G67 -> 0.25260018 | H68: =H66/H67 -> 0.17559038 | I68: =I66/I67 -> 0.17957921
B70: Market Cap./Long Term Liabilities
C71: =C65 -> 43921 | D71: =D65 -> 44286 | E71: =E65 -> 44651 | F71: =F65 -> 45016 | G71: =G65 -> 45382 | H71: =H65 -> 45747 | I71: =I65 -> 46112
B72: Market Capitalization (In Crs) | C72: ='Data Sheet'!E90*'Data Sheet'!E93 -> 159850.68 | D72: ='Data Sheet'!F90*'Data Sheet'!F93 -> 243387.41 | E72: ='Data Sheet'!G90*'Data Sheet'!G93 -> 295428.8 | F72: ='Data Sheet'!H90*'Data Sheet'!H93 -> 264897.47 | G72: ='Data Sheet'!I90*'Data Sheet'!I93 -> 273060.26 | H72: ='Data Sheet'!J90*'Data Sheet'!J93 -> 224515.15 | I72: ='Data Sheet'!K90*'Data Sheet'!K93 -> 207685.98
B73: Long Term Liability | C73: ='Data Sheet'!E59 -> 1118.5 | D73: ='Data Sheet'!F59 -> 1093.12 | E73: ='Data Sheet'!G59 -> 1586.88 | F73: ='Data Sheet'!H59 -> 1932.62 | G73: ='Data Sheet'!I59 -> 2474.38 | H73: ='Data Sheet'!J59 -> 2290.29 | I73: ='Data Sheet'!K59 -> 3928.93
B74: Market Cap./Long Term Liab. (D) | C74: =C72/C73 -> 142.91523 | D74: =D72/D73 -> 222.65388 | E74: =E72/E73 -> 186.16959 | F74: =F72/F73 -> 137.0665 | G74: =G72/G73 -> 110.35502 | H74: =H72/H73 -> 98.029135 | I74: =I72/I73 -> 52.860698
B76: Sales/Total Assets
C77: =C53 -> 43921 | D77: =D53 -> 44286 | E77: =E53 -> 44651 | F77: =F53 -> 45016 | G77: =G53 -> 45382 | H77: =H53 -> 45747 | I77: =I53 -> 46112
B78: Sales | C78: ='Data Sheet'!E17 -> 20211.25 | D78: ='Data Sheet'!F17 -> 21712.79 | E78: ='Data Sheet'!G17 -> 29101.28 | F78: ='Data Sheet'!H17 -> 34488.59 | G78: ='Data Sheet'!I17 -> 35494.73 | H78: ='Data Sheet'!J17 -> 33905.62 | I78: ='Data Sheet'!K17 -> 35583.54
B79: Total Assets | C79: ='Data Sheet'!E66 -> 16137.97 | D79: ='Data Sheet'!F66 -> 20355.34 | E79: ='Data Sheet'!G66 -> 22958.43 | F79: ='Data Sheet'!H66 -> 25779.33 | G79: ='Data Sheet'!I66 -> 29900.77 | H79: ='Data Sheet'!J66 -> 30355.25 | I79: ='Data Sheet'!K66 -> 34518.75
B80: Sales/Total Assets (E) | C80: =C78/C79 -> 1.2524035 | D80: =D78/D79 -> 1.0666877 | E80: =E78/E79 -> 1.267564 | F80: =F78/F79 -> 1.3378389 | G80: =G78/G79 -> 1.1870841 | H80: =H78/H79 -> 1.1169607 | I80: =I78/I79 -> 1.0308467
B82: Altman's Z Score
C83: =C77 -> 43921 | D83: =D77 -> 44286 | E83: =E77 -> 44651 | F83: =F77 -> 45016 | G83: =G77 -> 45382 | H83: =H77 -> 45747 | I83: =I77 -> 46112
B84: Final Score | C84: =(C56*1.2)+(C62*1.4)+(C68*3.3)+(C74*0.6)+(C80*1) -> 88.114854 | D84: =(D56*1.2)+(D62*1.4)+(D68*3.3)+(D74*0.6)+(D80*1) -> 135.65848 | E84: =(E56*1.2)+(E62*1.4)+(E68*3.3)+(E74*0.6)+(E80*1) -> 113.98542 | F84: =(F56*1.2)+(F62*1.4)+(F68*3.3)+(F74*0.6)+(F80*1) -> 84.738614 | G84: =(G56*1.2)+(G62*1.4)+(G68*3.3)+(G74*0.6)+(G80*1) -> 68.616033 | H84: =(H56*1.2)+(H62*1.4)+(H68*3.3)+(H74*0.6)+(H80*1) -> 60.831863 | I84: =(I56*1.2)+(I62*1.4)+(I68*3.3)+(I74*0.6)+(I80*1) -> 33.645782
B85: Financial Stability | C85: =IF(C84<1.81,"Distressed",IF(C84>3,"Strong","Grey Zone")) -> Strong | D85: =IF(D84<1.81,"Distressed",IF(D84>3,"Strong","Grey Zone")) -> Strong | E85: =IF(E84<1.81,"Distressed",IF(E84>3,"Strong","Grey Zone")) -> Strong | F85: =IF(F84<1.81,"Distressed",IF(F84>3,"Strong","Grey Zone")) -> Strong | G85: =IF(G84<1.81,"Distressed",IF(G84>3,"Strong","Grey Zone")) -> Strong | H85: =IF(H84<1.81,"Distressed",IF(H84>3,"Strong","Grey Zone")) -> Strong | I85: =IF(I84<1.81,"Distressed",IF(I84>3,"Strong","Grey Zone")) -> Strong

Sheet One Page Profile>

Sheet InputSheet
B2: Company Description | C2: Asian Paints Ltd is an Indian multinational paint company, headquartered in Mumbai. The company is engaged in the business of manufacturing, selling and distribution of paints, coatings, products related to home décor, bath fittings and providing related services.

Sheet Financials>

Sheet Data>

Sheet Data Sheet
A1: COMPANY NAME | B1: ASIAN PAINTS LTD | E1: =IF(B2<>B3, "A NEW VERSION OF THE WORKSHEET IS AVAILABLE", "")
A2: LATEST VERSION | B2: 2.1 | E2: PLEASE DO NOT MAKE ANY CHANGES TO THIS SHEET
A3: CURRENT VERSION | B3: 2.1
A5: META
A6: Number of shares | B6: =IF(B9>0, B9/B8, 0) -> 95.919779
A7: Face Value | B7: 1
A8: Current Price | B8: 2645.2
A9: Market Capitalization | B9: 253727
A15: PROFIT & LOSS
A16: Report Date | B16: 42825 | C16: 43190 | D16: 43555 | E16: 43921 | F16: 44286 | G16: 44651 | H16: 45016 | I16: 45382 | J16: 45747 | K16: 46112
A17: Sales | B17: 15061.99 | C17: 16824.55 | D17: 19240.13 | E17: 20211.25 | F17: 21712.79 | G17: 29101.28 | H17: 34488.59 | I17: 35494.73 | J17: 33905.62 | K17: 35583.54
A18: Raw Material Cost | B18: 7452.6 | C18: 8128.17 | D18: 9974.4 | E18: 9981.99 | F18: 10425.55 | G18: 17123.25 | H18: 18985.53 | I18: 17410.84 | J18: 17504.51 | K18: 17142.01
A19: Change in Inventory | B19: 528.6 | C19: -142.13 | D19: 293.26 | E19: 239.15 | F19: 92.45 | G19: 1324.97 | H19: 309.73 | I19: -363.8 | J19: 205 | K19: -603.68
A20: Power and Fuel | B20: 106.02 | C20: 110.3 | D20: 119.63 | E20: 97.79 | F20: 86.05 | G20: 117.23 | H20: 138.29 | I20: 133.25 | J20: 148.58 | K20: 167.1
A21: Other Mfr. Exp | B21: 1662.75 | C21: 1691.68 | D21: 1862.35 | E21: 1946.12 | F21: 2068.31 | G21: 2880.45 | H21: 2916.2 | I21: 2767.18 | J21: 2687.4 | K21: 2767.11
A22: Employee Cost | B22: 1039.89 | C22: 1121.89 | D22: 1242.69 | E22: 1371.27 | F22: 1547.61 | G22: 1794.61 | H22: 2036.41 | I22: 2334.92 | J22: 2605.78 | K22: 2809.73
A23: Selling and admin | B23: 4364.04 | C23: 2254.92 | D23: 2366.87 | E23: 2311.51 | F23: 2245.69 | G23: 2941.98 | H23: 3500.84 | I23: 3811.86 | J23: 3874.94 | K23: 4112.07
A24: Other Expenses | B24: -2028.47 | C24: 171.45 | D24: 202.51 | E24: 579.95 | F24: 576.43 | G24: 765.12 | H24: 961.21 | I24: 1087.9 | J24: 1283.2 | K24: 1282.11
A25: Other Income | B25: 337.9 | C25: 336.41 | D25: 273.77 | E25: 350.1 | F25: 331.65 | G25: 295.88 | H25: 431.46 | I25: 820.96 | J25: 350.22 | K25: 727.97
A26: Depreciation | B26: 334.79 | C26: 360.47 | D26: 622.14 | E26: 780.5 | F26: 791.27 | G26: 816.36 | H26: 858.02 | I26: 853 | J26: 1026.34 | K26: 1228.85
A27: Interest | B27: 37.33 | C27: 41.47 | D27: 110.47 | E27: 102.33 | F27: 91.63 | G27: 95.41 | H27: 144.45 | I27: 205.17 | J27: 227.02 | K27: 195.41
... A31: Dividend Amount | B31: 987.98 | C31: 834.5 | D31: 1007.16 | E31: 1151.04 | F31: 1712.17 | G31: 1836.87 | H31: 2460.35 | I31: 3194.14 | J31: 2378.82 | K31: 2637.8
A33: Dividend Per Share | B33: ='Data Sheet'!B31/HistoricalFS!C42 -> 10.300042 | C33: ='Data Sheet'!C31/HistoricalFS!D42 -> 8.6999583 | D33: ='Data Sheet'!D31/HistoricalFS!E42 -> 10.5 | E33: ='Data Sheet'!E31/HistoricalFS!F42 -> 12 | F33: ='Data Sheet'!F31/HistoricalFS!G42 -> 17.849979 | G33: ='Data Sheet'!G31/HistoricalFS!H42 -> 19.150021 | H33: ='Data Sheet'!H31/HistoricalFS!I42 -> 25.650021 | I33: ='Data Sheet'!I31/HistoricalFS!J42 -> 33.300042 | ... K33: ='Data Sheet'!K31/HistoricalFS!L42 -> 27.5
A34: Dividend Growth | C34: =C33/B33-1 -> -0.15534727 | D34: =D33/C33-1 -> 0.20690234 | E34: =E33/D33-1 -> 0.14285714 | F34: =F33/E33-1 -> 0.48749826 | G34: =G33/F33-1 -> 0.072831553 | H34: =H33/G33-1 -> 0.33942522 | I34: =I33/H33-1 -> 0.29824618 | J34: =J33/I33-1 -> -0.25525494 | K34: =K33/J33-1 -> 0.1088691
A40: Quarters
A41: Report Date | B41: 45291 | C41: 45382 | D41: 45473 | E41: 45565 | F41: 45657 | G41: 45747 | H41: 45838 | I41: 45930 | J41: 46022 | K41: 46112
A42: Sales | B42: 9103.09 | C42: 8730.76 | D42: 8969.73 | E42: 8027.54 | F42: 8549.44 | G42: 8358.91 | H42: 8938.55 | I42: 8531.27 | J42: 8867.02 | K42: 9246.7
A43: Expenses | B43: 7047 | C43: 7039.39 | D43: 7275.96 | E43: 6788.03 | F43: 6912.71 | G43: 6922.71 | H43: 7313.58 | I43: 7027.89 | J43: 7086.06 | K43: 7460.09
A44: Other Income | B44: 186.46 | C44: 212.43 | D44: 192.93 | E44: 24.53 | F44: 192.82 | G44: -60.06 | H44: 229.11 | I44: 236.94 | J44: 69.14 | K44: 196.59
A45: Depreciation | B45: 220.35 | C45: 225.61 | D45: 227.7 | E45: 241.99 | F45: 255.55 | G45: 301.1 | H45: 300.87 | I45: 304.93 | J45: 313.07 | K45: 309.98
A46: Interest | B46: 54.42 | C46: 54.1 | D46: 55.38 | E46: 63.01 | F46: 55.84 | G46: 52.79 | H46: 44.5 | I46: 43.87 | J46: 47.94 | K46: 59.1
A47: Profit before tax | B47: 1967.78 | C47: 1624.09 | D47: 1603.62 | E47: 959.04 | F47: 1518.16 | G47: 1022.25 | H47: 1508.71 | I47: 1391.52 | J47: 1489.09 | K47: 1614.12
A48: Tax | B48: 492.62 | C48: 348.79 | D48: 416.83 | E48: 265.38 | F48: 389.73 | G48: 321.42 | H48: 391.66 | I48: 373.29 | J48: 415.17 | K48: 428.63
A49: Net profit | B49: 1447.72 | C49: 1256.72 | D49: 1169.98 | E49: 694.64 | F49: 1110.48 | G49: 692.13 | H49: 1099.77 | I49: 993.59 | J49: 1059.87 | K49: 1172.12
A50: Operating Profit | B50: 2056.09 | C50: 1691.37 | D50: 1693.77 | E50: 1239.51 | F50: 1636.73 | G50: 1436.2 | H50: 1624.97 | I50: 1503.38 | J50: 1780.96 | K50: 1786.61
A55: BALANCE SHEET
A56: Report Date | B56: 42825 | C56: 43190 | D56: 43555 | E56: 43921 | F56: 44286 | G56: 44651 | H56: 45016 | I56: 45382 | J56: 45747 | K56: 46112
A57: Equity Share Capital | B57: 95.92 | C57: 95.92 | D57: 95.92 | E57: 95.92 | F57: 95.92 | G57: 95.92 | H57: 95.92 | I57: 95.92 | J57: 95.92 | K57: 95.92
A58: Reserves | B58: 7507.97 | C58: 8314.31 | D58: 9374.63 | E58: 10034.24 | F58: 12710.37 | G58: 13715.64 | H58: 15896.31 | I58: 18632.38 | J58: 19303.89 | K58: 21275.67
A59: Borrowings | B59: 560.34 | C59: 533.43 | D59: 1319.6 | E59: 1118.5 | F59: 1093.12 | G59: 1586.88 | H59: 1932.62 | I59: 2474.38 | J59: 2290.29 | K59: 3928.93
A60: Other Liabilities | B60: 4240.96 | C60: 4819.82 | D60: 5458.69 | E60: 4889.31 | F60: 6455.93 | G60: 7559.99 | H60: 7854.48 | I60: 8698.09 | J60: 8665.15 | K60: 9218.23
A61: Total | B61: 12405.19 | C61: 13763.48 | D61: 16248.84 | E61: 16137.97 | F61: 20355.34 | G61: 22958.43 | H61: 25779.33 | I61: 29900.77 | J61: 30355.25 | K61: 34518.75
A62: Net Block | B62: 3303.74 | C62: 3732.24 | D62: 6496.56 | E62: 6272.31 | F62: 5858.52 | G62: 5519.06 | H62: 5770.46 | I62: 7146.62 | J62: 9220.1 | K62: 9640.28
A63: Capital Work in Progress | B63: 257.54 | C63: 1405.11 | D63: 209.67 | E63: 140.24 | F63: 182.98 | G63: 426.43 | H63: 1019.59 | I63: 2698.37 | J63: 1254.49 | K63: 1848.67
A64: Investments | B64: 2651.99 | C64: 2140.7 | D64: 2568.58 | E64: 2018.85 | F64: 4736.8 | G64: 3247.53 | H64: 4261.71 | I64: 4587.92 | J64: 4724.75 | K64: 7061.74
A65: Other Assets | B65: 6191.92 | C65: 6485.43 | D65: 6974.03 | E65: 7706.57 | F65: 9577.04 | G65: 13765.41 | H65: 14727.57 | I65: 15467.86 | J65: 15155.91 | K65: 15968.06
A66: Total | B66: 12405.19 | C66: 13763.48 | D66: 16248.84 | E66: 16137.97 | F66: 20355.34 | G66: 22958.43 | H66: 25779.33 | I66: 29900.77 | J66: 30355.25 | K66: 34518.75
A67: Receivables | B67: 1446.6 | C67: 1730.63 | D67: 1907.33 | E67: 1795.22 | F67: 2602.17 | G67: 3871.44 | H67: 4636.94 | I67: 4889.05 | J67: 4313.65 | K67: 4461.8
... A70: No. of Equity Shares | B70: 959197790 | C70: 959197790 | D70: 959197790 | E70: 959197790 | F70: 959197790 | G70: 959197790 | H70: 959197790 | I70: 959197790 | J70: 959197790 | K70: 959197790
A71: New Bonus Shares
A72: Face value | B72: 1 | C72: 1 | D72: 1 | E72: 1 | F72: 1 | G72: 1 | H72: 1 | I72: 1 | J72: 1 | K72: 1
A74: Trade Payables | B74: 1923 | C74: 2160 | D74: 2394 | E74: 2137 | F74: 3379 | G74: 4164 | H74: 3635 | I74: 3831 | J74: 3848 | K74: 3863
A75: Other Assets | B75: =B65-SUM(B67:B69) -> 1317.17 | C75: =C65-SUM(C67:C69) -> 1691.84 | D75: =D65-SUM(D67:D69) -> 1471.96 | E75: =E65-SUM(E67:E69) -> 1738.71 | F75: =F65-SUM(F67:F69) -> 2565.52 | G75: =G65-SUM(G67:G69) -> 2876.66 | H75: =H65-SUM(H67:H69) -> 3036.17 | I75: =I65-SUM(I67:I69) -> 3571.39 | ... K75: =K65-SUM(K67:K69) -> 4688.89
A80: CASH FLOW:
A81: Report Date | B81: 42825 | C81: 43190 | D81: 43555 | E81: 43921 | F81: 44286 | G81: 44651 | H81: 45016 | I81: 45382 | J81: 45747 | K81: 46112
A82: Cash from Operating Activity | B82: 1527.33 | C82: 2113.44 | D82: 2469.54 | E82: 3038.15 | F82: 3683.35 | G82: 986.49 | H82: 4193.43 | I82: 6103.6 | J82: 4423.96 | K82: 7088.18
A83: Cash from Investing Activity | B83: -681.11 | C83: -1556.14 | D83: -917.79 | E83: -517.91 | F83: -540.54 | G83: -316.75 | H83: -1282.34 | I83: -2548.48 | J83: -940.91 | K83: -1328.23
A84: Cash from Financing Activity | B84: -756.43 | C84: -1379.14 | D84: -1117.46 | E84: -2871.46 | F84: -650.4 | G84: -1807.61 | H84: -2140.05 | I84: -2982.5 | J84: -3752.58 | K84: -2376.51
A85: Net Cash Flow | B85: 89.79 | C85: -821.84 | D85: 434.29 | E85: -351.22 | F85: 2492.41 | G85: -1137.87 | H85: 771.04 | I85: 572.62 | J85: -269.53 | K85: 3383.44
A90: PRICE: | B90: 1073.5 | C90: 1120.4 | D90: 1492.7 | E90: 1666.5 | F90: 2537.4 | G90: 3079.95 | H90: 2761.65 | I90: 2846.75 | J90: 2340.65 | K90: 2165.2
A92: DERIVED:
A93: Adjusted Equity Shares in Cr | B93: 95.92 | C93: 95.92 | D93: 95.92 | E93: 95.92 | F93: 95.92 | G93: 95.92 | H93: 95.92 | I93: 95.92 | J93: 95.92 | K93: 95.92
A96: Market Price per Share | B96: =$B$8/HistoricalFS!C44 -> 125.84133 | C96: =$B$8/HistoricalFS!D44 -> 120.96551 | D96: =$B$8/HistoricalFS!E44 -> 114.91077 | E96: =$B$8/HistoricalFS!F44 -> 91.46006 | F96: =$B$8/HistoricalFS!G44 -> 79.12297 | G96: =$B$8/HistoricalFS!H44 -> 82.250636 | H96: =$B$8/HistoricalFS!I44 -> 60.478576 | I96: =$B$8/HistoricalFS!J44 -> 45.653425 | ... K96: =$B$8/HistoricalFS!L44 -> 57.735036
A97: Market Capitalization | B97: =B93*B96 -> 12070.7 | C97: =C93*C96 -> 11603.012 | D97: =D93*D96 -> 11022.241 | E97: =E93*E96 -> 8772.849 | F97: =F93*F96 -> 7589.4753 | G97: =G93*G96 -> 7889.481 | H97: =H93*H96 -> 5801.105 | I97: =I93*I96 -> 4379.0765 | ... K97: =K93*K96 -> 5537.9446
A98: Enterprise Value(EV) | B98: =B97+B59-B69 -> 11829.83 | C98: =C97+C59-C69 -> 11731.792 | D98: =D97+D59-D69 -> 11896.961 | E98: =E97+E59-E69 -> 9108.519 | F98: =F97+F59-F69 -> 8071.8453 | G98: =G97+G59-G69 -> 8612.031 | H98: =H97+H59-H69 -> 6889.905 | I98: =I97+I59-I69 -> 5769.4465 | ... K98: =K97+K59-K69 -> 8393.1946
A99: EV/EBITDA | B99: =B98/HistoricalFS!C18 -> 3.9514959 | C99: =C98/HistoricalFS!D18 -> 3.6615966 | D99: =D98/HistoricalFS!E18 -> 3.1599339 | E99: =E98/HistoricalFS!F18 -> 2.1886166 | F99: =F98/HistoricalFS!G18 -> 1.6623785 | G99: =G98/HistoricalFS!H18 -> 1.7928248 | H99: =H98/HistoricalFS!I18 -> 1.1006519 | I99: =I98/HistoricalFS!J18 -> 0.76064097 | ... K99: =K98/HistoricalFS!L18 -> 1.2527661
A100: EV/Sales | B100: =B98/B17 -> 0.78540953 | C100: =C98/C17 -> 0.69730198 | D100: =D98/D17 -> 0.61834101 | E100: =E98/E17 -> 0.45066579 | F100: =F98/F17 -> 0.37175532 | G100: =G98/G17 -> 0.29593307 | H100: =H98/H17 -> 0.19977346 | I100: =I98/I17 -> 0.16254375 | ... K100: =K98/K17 -> 0.23587295
A101: Book Value | B101: =SUM(B57:B58) -> 7603.89 | C101: =SUM(C57:C58) -> 8410.23 | D101: =SUM(D57:D58) -> 9470.55 | E101: =SUM(E57:E58) -> 10130.16 | F101: =SUM(F57:F58) -> 12806.29 | G101: =SUM(G57:G58) -> 13811.56 | H101: =SUM(H57:H58) -> 15992.23 | I101: =SUM(I57:I58) -> 18728.3 | ... K101: =SUM(K57:K58) -> 21371.59
A102: Price to book (P/B) | B102: =B97/B101 -> 1.5874375 | C102: =C97/C101 -> 1.3796308 | D102: =D97/D101 -> 1.1638439 | E102: =E97/E101 -> 0.86601287 | F102: =F97/F101 -> 0.59263653 | G102: =G97/G101 -> 0.57122302 | H102: =H97/H101 -> 0.36274522 | I102: =I97/I101 -> 0.23382136 | ... K102: =K97/K101 -> 0.25912647

Sheet CashFlow Statement
C2: 42064 | D2: 42430 | E2: 42795 | F2: 43160 | G2: 43525 | H2: 43891 | I2: 44256 | J2: 44621 | K2: 44986 | L2: 45352 | M2: 45717 | N2: 46082
B3: Cash from Operating Activity - | C3: 1188 | D3: 2243 | E3: 1527 | F3: 2113 | G3: 2470 | H3: 3038 | I3: 3683 | J3: 986 | K3: 4193 | L3: 6104 | M3: 4424 | N3: 7088
B4: Profit from operations | C4: 2271 | D4: 2848 | E4: 3056 | F4: 3274 | G4: 3861 | H4: 4380 | I4: 4970 | J4: 4957 | K4: 6460 | L4: 7929 | M4: 6390 | N4: 7186
B5: Receivables | C5: -155 | D5: -146 | E5: -475 | F5: -483 | G5: -205 | H5: 160 | I5: -849 | J5: -1326 | K5: -834 | L5: -362 | M5: 282 | N5: -274
B6: Inventory | C6: -144 | D6: 202 | E6: -629 | F6: -39 | G6: -492 | H6: -251 | I6: -409 | J6: -2354 | K6: -56 | L6: 315 | M6: -805 | N6: 976
B7: Payables | C7: -151 | D7: 142 | E7: 501 | F7: 442 | G7: 287 | H7: -241 | I7: 1143 | J7: 644 | K7: -539 | L7: 269 | M7: -160 | N7: 396
B8: Other WC items | C8: 0 | D8: 0 | E8: 0 | F8: 0 | G8: 0 | H8: 0 | I8: -92 | J8: 242 | K8: 657 | L8: -212 | M8: 114 | N8: 378
B9: Working capital changes | C9: -450 | D9: 198 | E9: -603 | F9: -80 | G9: -410 | H9: -331 | I9: -206 | J9: -2795 | K9: -772 | L9: 10 | M9: -570 | N9: 1476
B10: Direct taxes | C10: -633 | D10: -802 | E10: -925 | F10: -1081 | G10: -982 | H10: -1011 | I10: -1080 | J10: -1176 | K10: -1494 | L10: -1835 | M10: -1396 | N10: -1574
B11: Cash from Investing Activity - | C11: -465 | D11: -866 | E11: -681 | F11: -1556 | G11: -918 | H11: -518 | I11: -541 | J11: -317 | K11: -1282 | L11: -2548 | M11: -941 | N11: -1328
B12: Fixed assets purchased | C12: -454 | D12: -817 | E12: -684 | F12: -1426 | G12: -1151 | H12: -414 | I12: -289 | J12: -551 | K12: -1446 | L12: -2496 | M12: -1830 | N12: -1487
B13: Fixed assets sold | C13: 16 | D13: 15 | E13: 17 | F13: 17 | G13: 17 | H13: 37 | I13: 28 | J13: 40 | K13: 26 | L13: 5 | M13: 10 | N13: 3
B14: Investments purchased | C14: -243 | D14: -282 | E14: -153 | F14: -320 | G14: -573 | H14: -25 | I14: -140 | J14: 0 | K14: -146 | L14: -212 | M14: -1 | N14: 0
... B30: Net Cash Flow | C30: 147 | D30: 528 | E30: 90 | F30: -822 | G30: 434 | H30: -351 | I30: 2492 | J30: -1138 | K30: 771 | L30: 573 | M30: -270 | N30: 3383

Sheet DCF>

Sheet RawFS
B2: Particulars | C2: 42064 | D2: 42430 | E2: 42795 | F2: 43160 | G2: 43525 | H2: 43891 | I2: 44256 | J2: 44621 | K2: 44986 | L2: 45352 | M2: 45717 | N2: 46082
B4: Equity Capital | C4: 96 | D4: 96 | E4: 96 | F4: 96 | G4: 96 | H4: 96 | I4: 96 | J4: 96 | K4: 96 | L4: 96 | M4: 96 | N4: 96
B5: Reserves | C5: 4646 | D5: 6429 | E5: 7508 | F5: 8314 | G5: 9375 | H5: 10034 | I5: 12710 | J5: 13716 | K5: 15896 | L5: 18632 | M5: 19304 | N5: 21276
B6: Borrowings -
B7: Long term Borrowings | C7: 78 | D7: 73 | E7: 41 | F7: 28 | G7: 19 | H7: 19 | I7: 15 | J7: 45 | K7: 76 | L7: 54 | M7: 260 | N7: 1247
B8: Short term Borrowings | C8: 332 | D8: 231 | E8: 504 | F8: 492 | G8: 597 | H8: 321 | I8: 334 | J8: 731 | K8: 896 | L8: 1053 | M8: 604 | N8: 1046
B9: Lease Liabilities | C9: 0 | D9: 0 | E9: 0 | F9: 0 | G9: 693 | H9: 764 | I9: 745 | J9: 811 | K9: 960 | L9: 1367 | M9: 1427 | N9: 1636
B10: Other Borrowings | C10: 8 | D10: 20 | E10: 15 | F10: 13 | G10: 11 | H10: 15 | I10: 0 | J10: 0 | K10: 0 | L10: 0 | M10: 0 | N10: 0
B11: Other Liabilities -
B12: Non controlling int | C12: 264 | D12: 384 | E12: 375 | F12: 328 | G12: 361 | H12: 404 | I12: 423 | J12: 388 | K12: 454 | L12: 695 | M12: 659 | N12: 643
B13: Trade Payables | C13: 1549 | D13: 1565 | E13: 1923 | F13: 2160 | G13: 2394 | H13: 2137 | I13: 3379 | J13: 4164 | K13: 3635 | L13: 3831 | M13: 3848 | N13: 3863
B14: Advance from Customers | C14: 5 | D14: 12 | E14: 17 | F14: 16 | G14: 13 | H14: 29 | I14: 41 | J14: 76 | K14: 108 | L14: 154 | M14: 174 | N14: 107
B15: Other liability items | C15: 1937 | D15: 1750 | E15: 1925 | F15: 2316 | G15: 2690 | H15: 2320 | I15: 2613 | J15: 2932 | K15: 3657 | L15: 4017 | M15: 3984 | N15: 4604
B16: Total Liabilities | C16: 8914 | D16: 10559 | E16: 12405 | F16: 13763 | G16: 16249 | H16: 16138 | I16: 20355 | J16: 22958 | K16: 25779 | L16: 29901 | M16: 30355 | N16: 34519
B18: Fixed Assets -
B19: Land | C19: 251 | D19: 429 | E19: 408 | F19: 586 | G19: 605 | H19: 640 | I19: 644 | J19: 644 | K19: 804 | L19: 1126 | M19: 1035 | N19: 1204
B20: Building | C20: 962 | D20: 923 | E20: 931 | F20: 957 | G20: 2402 | H20: 2257 | I20: 2249 | J20: 2325 | K20: 2883 | L20: 3390 | M20: 3771 | N20: 4124
B21: Plant Machinery | C21: 2132 | D21: 1793 | E21: 1980 | F21: 2157 | G21: 4006 | H21: 4208 | I21: 4340 | J21: 4531 | K21: 4825 | L21: 5422 | M21: 7576 | N21: 8210
B22: Equipments | C22: 171 | D22: 97 | E22: 119 | F22: 200 | G22: 221 | H22: 241 | I22: 243 | J22: 253 | K22: 270 | L22: 298 | M22: 325 | N22: 351
B23: Furniture n fittings | C23: 83 | D23: 49 | E23: 59 | F23: 72 | G23: 88 | H23: 94 | I23: 99 | J23: 113 | K23: 146 | L23: 175 | M23: 203 | N23: 216
B24: Vehicles | C24: 18 | D24: 11 | E24: 14 | F24: 27 | G24: 47 | H24: 43 | I24: 38 | J24: 32 | K24: 36 | L24: 40 | M24: 34 | N24: 45
B25: Intangible Assets | C25: 351 | D25: 339 | E25: 276 | F25: 468 | G25: 512 | H25: 505 | I25: 476 | J25: 345 | K25: 422 | L25: 850 | M25: 827 | N25: 833
B26: Other fixed assets | C26: 145 | D26: 103 | E26: 128 | F26: 238 | G26: 261 | H26: 293 | I26: 302 | J26: 294 | K26: 289 | L26: 321 | M26: 328 | N26: 335
B27: Gross Block | C27: 4112 | D27: 3744 | E27: 3914 | F27: 4705 | G27: 8141 | H27: 8282 | I27: 8392 | J27: 8538 | K27: 9676 | L27: 11622 | M27: 14099 | N27: 15316
B28: Accumulated Depreciation | C28: 1452 | D28: 327 | E28: 610 | F28: 973 | G28: 1644 | H28: 2010 | I28: 2533 | J28: 3019 | K28: 3905 | L28: 4475 | M28: 4879 | N28: 5676
B29: Net Block | C29: =C27-C28 -> 2660 | D29: =D27-D28 -> 3417 | E29: =E27-E28 -> 3304 | F29: =F27-F28 -> 3732 | G29: =G27-G28 -> 6497 | H29: =H27-H28 -> 6272 | I29: =I27-I28 -> 5859 | J29: =J27-J28 -> 5519 | ... N29: =N27-N28 -> 9640
B31: CWIP | C31: 196 | D31: 107 | E31: 258 | F31: 1405 | G31: 210 | H31: 140 | I31: 183 | J31: 426 | K31: 1020 | L31: 2698 | M31: 1254 | N31: 1849
B32: Investments | C32: 1588 | D32: 2712 | E32: 2652 | F32: 2141 | G32: 2569 | H32: 2019 | I32: 4737 | J32: 3248 | K32: 4262 | L32: 4588 | M32: 4725 | N32: 7062
B34: Other Assets -
B35: Inventories | C35: 2259 | D35: 1998 | E35: 2627 | F35: 2658 | G35: 3150 | H35: 3390 | I35: 3799 | J35: 6153 | K35: 6211 | L35: 5923 | M35: 6719 | N35: 5744
B36: Trade receivables | C36: 1182 | D36: 1187 | E36: 1447 | F36: 1731 | G36: 1907 | H36: 1795 | I36: 2602 | J36: 3871 | K36: 4637 | L36: 4889 | M36: 4314 | N36: 4462
B37: Cash Equivalents | C37: 204 | D37: 424 | E37: 801 | F37: 405 | G37: 445 | H37: 783 | I37: 611 | J37: 864 | K37: 844 | L37: 1084 | M37: 782 | N37: 1074
B38: Loans n Advances | C38: 8 | D38: 9 | E38: 14 | F38: 13 | G38: 16 | H38: 12 | I38: 11 | J38: 8 | K38: 12 | L38: 17 | M38: 22 | N38: 27
B39: Other asset items | C39: 817 | D39: 705 | E39: 1303 | F39: 1678 | G39: 1456 | H39: 1727 | I39: 2555 | J39: 2869 | K39: 3024 | L39: 3555 | M39: 3319 | N39: 4662
B40: Total Assets | C40: =SUM(C35:C39,C31:C32,C29) -> 8914 | D40: =SUM(D35:D39,D31:D32,D29) -> 10559 | E40: =SUM(E35:E39,E31:E32,E29) -> 12406 | F40: =SUM(F35:F39,F31:F32,F29) -> 13763 | G40: =SUM(G35:G39,G31:G32,G29) -> 16250 | H40: =SUM(H35:H39,H31:H32,H29) -> 16138 | I40: =SUM(I35:I39,I31:I32,I29) -> 20357 | J40: =SUM(J35:J39,J31:J32,J29) -> 22958 | ... N40: =SUM(N35:N39,N31:N32,N29) -> 34520
B42: Particulars | C42: 42064 | D42: 42430 | E42: 42795 | F42: 43160 | G42: 43525 | H42: 43891 | I42: 44256 | J42: 44621 | K42: 44986 | L42: 45352 | M42: 45717 | N42: 46082
B44: Cash from Operating Activity - | C44: 1188 | D44: 2243 | E44: 1527 | F44: 2113 | G44: 2470 | H44: 3038 | I44: 3683 | J44: 986 | K44: 4193 | L44: 6104 | M44: 4424 | N44: 7088
B45: Profit from operations | C45: 2271 | D45: 2848 | E45: 3056 | F45: 3274 | G45: 3861 | H45: 4380 | I45: 4970 | J45: 4957 | K45: 6460 | L45: 7929 | M45: 6390 | N45: 7186
B46: Receivables | C46: -155 | D46: -146 | E46: -475 | F46: -483 | G46: -205 | H46: 160 | I46: -849 | J46: -1326 | K46: -834 | L46: -362 | M46: 282 | N46: -274
B47: Inventory | C47: -144 | D47: 202 | E47: -629 | F47: -39 | G47: -492 | H47: -251 | I47: -409 | J47: -2354 | K47: -56 | L47: 315 | M47: -805 | N47: 976
B48: Payables | C48: -151 | D48: 142 | E48: 501 | F48: 442 | G48: 287 | H48: -241 | I48: 1143 | J48: 644 | K48: -539 | L48: 269 | M48: -160 | N48: 396
B49: Other WC items | C49: 0 | D49: 0 | E49: 0 | F49: 0 | G49: 0 | H49: 0 | I49: -92 | J49: 242 | K49: 657 | L49: -212 | M49: 114 | N49: 378
B50: Working capital changes | C50: -450 | D50: 198 | E50: -603 | F50: -80 | G50: -410 | H50: -331 | I50: -206 | J50: -2795 | K50: -772 | L50: 10 | M50: -570 | N50: 1476
B51: Direct taxes | C51: -633 | D51: -802 | E51: -925 | F51: -1081 | G51: -982 | H51: -1011 | I51: -1080 | J51: -1176 | K51: -1494 | L51: -1835 | M51: -1396 | N51: -1574
B53: Cash from Investing Activity - | C53: -465 | D53: -866 | E53: -681 | F53: -1556 | G53: -918 | H53: -518 | I53: -541 | J53: -317 | K53: -1282 | L53: -2548 | M53: -941 | N53: -1328
B54: Fixed assets purchased | C54: -454 | D54: -817 | E54: -684 | F54: -1426 | G54: -1151 | H54: -414 | I54: -289 | J54: -551 | K54: -1446 | L54: -2496 | M54: -1830 | N54: -1487
B55: Fixed assets sold | C55: 16 | D55: 15 | E55: 17 | F55: 17 | G55: 17 | H55: 37 | I55: 28 | J55: 40 | K55: 26 | L55: 5 | M55: 10 | N55: 3
... B76: CFO/OP | C76: 0.81 | D76: 1.12 | E76: 0.82 | F76: 1 | G76: 0.92 | H76: 0.97 | I76: 0.98 | J76: 0.45 | K76: 0.91 | L76: 1.05 | M76: 0.97 | N76: 1.29

Sheet RawData
B2: S.No. | C2: Name | E2: Mar Cap Rs.Cr. | F2: Debt Rs.Cr. | H2: asian paints | L2: nifty 50 | O2: berger paints | R2: narolac | U2: indigo | X2: Nifty 50 returns | AA2: Shareholder's name | AB2: N. Shares (In Cr) | AC2: (%) Holding | AD2: Quarter Ending
B3: 1 | C3: Asian Paints | E3: 262791.1 | F3: 3928.93 | H3: Date | I3: Adj Close | J3: Volume | L3: Date | M3: Adj Close | O3: Date | P3: Adj Close | R3: Date | S3: Adj Close | U3: Date | V3: Adj Close | X3: Year | Y3: Annual | AA3: Life Insurance Corporation of India | AB3: 7.7822006 | AC3: 0.0811 | AD3: 46082
B4: 2 | C4: Berger Paints | E4: 60457.55 | F4: 635.13 | H4: Jul 3, 2026 | I4: 2737.8 | J4: 0.472095 | L4: Jul 3, 2026 | M4: 24270.85 | O4: Jul 3, 2026 | P4: 519.45 | R4: Jul 3, 2026 | S4: 211.83 | U4: Jul 3, 2026 | V4: 1065.9 | X4: 2000 | Y4: -14.65 | AA4: Sattva Holding and Trading Private Limited | AB4: 5.4789183 | AC4: 0.0571 | AD4: 46082
B5: 3 | C5: Kansai Nerolac | E5: 17156.01 | F5: 302.73 | H5: Jul 1, 2026 | I5: 2744.5 | J5: 2.727079 | L5: Jul 1, 2026 | M5: 24175.7 | O5: Jul 1, 2026 | P5: 520.75 | R5: Jul 1, 2026 | S5: 212.56 | U5: Jul 1, 2026 | V5: 1077.1 | X5: 2001 | Y5: -16.18 | AA5: Smiti Holding and Trading Company Private Limited | AB5: 5.1442638 | AC5: 0.0536 | AD5: 46082
B6: 4 | C6: JSW Dulux | E6: 14868.24 | F6: 79.1 | H6: Jun 1, 2026 | I6: 2635.7 | J6: 31.407028 | L6: Jun 1, 2026 | M6: 23865.75 | O6: Jun 1, 2026 | P6: 510.1 | R6: Jun 1, 2026 | S6: 204.06 | U6: Jun 1, 2026 | V6: 1015.25 | X6: 2002 | Y6: 3.25 | AA6: SBI Mutual Fund | AB6: 4.9885007 | AC6: 0.052 | AD6: 46082
B7: 5 | C7: Indigo Paints | E7: 5080.81 | F7: 18.37 | H7: May 1, 2026 | I7: 2648.62 | J7: 24.922732 | L7: May 1, 2026 | M7: 23547.75 | O7: May 1, 2026 | P7: 500.6 | R7: May 1, 2026 | S7: 215.49 | U7: May 1, 2026 | V7: 990.9 | X7: 2003 | Y7: 71.9 | AA7: Geetanjali Trading and Investments Private Limited | AB7: 4.570614 | AC7: 0.0477 | AD7: 46082
H8: Apr 1, 2026 | I8: 2423.47 | J8: 28.781051 | L8: Apr 1, 2026 | M8: 23997.55 | O8: Apr 1, 2026 | P8: 473.1 | R8: Apr 1, 2026 | S8: 194.87 | U8: Apr 1, 2026 | V8: 860.2 | X8: 2004 | Y8: 10.68 | AA8: Elcid Investments Limited | AB8: 2.831386 | AC8: 0.0295 | AD8: 46082
H9: Mar 1, 2026 | I9: 2146.58 | J9: 23.464907 | L9: Mar 1, 2026 | M9: 22331.4 | O9: Mar 1, 2026 | P9: 410 | R9: Mar 1, 2026 | S9: 165.25 | U9: Mar 1, 2026 | V9: 710.8 | X9: 2005 | Y9: 36.34 | AA9: Shubhit Holdings Private Limited | AB9: 2.315073 | AC9: 0.0241 | AD9: 46082
H10: Feb 1, 2026 | I10: 2355.76 | J10: 22.708371 | L10: Feb 1, 2026 | M10: 25178.65 | O10: Feb 1, 2026 | P10: 456.1 | R10: Feb 1, 2026 | S10: 201.11 | U10: Feb 1, 2026 | V10: 936.8 | X10: 2006 | Y10: 39.83 | AA10: ICICI Prudential Mutual Fund | AB10: 2.1582801 | AC10: 0.0225 | AD10: 46082
H11: Jan 1, 2026 | I11: 2407.41 | J11: 29.42148 | L11: Jan 1, 2026 | M11: 25320.65 | O11: Jan 1, 2026 | P11: 462.9 | R11: Jan 1, 2026 | S11: 227.48 | U11: Jan 1, 2026 | V11: 1044.4 | X11: 2007 | Y11: 54.77 | AA11: Sudhanva Investments and Trading Company Private Limited | AB11: 1.900176 | AC11: 0.0198 | AD11: 46082
H12: Dec 1, 2025 | I12: 2745.68 | J12: 27.446915 | L12: Dec 1, 2025 | M12: 26129.6 | O12: Dec 1, 2025 | P12: 536.55 | R12: Dec 1, 2025 | S12: 232.68 | U12: Dec 1, 2025 | V12: 1143.8 | X12: 2008 | Y12: -51.79 | AA12: Rupen Investment & Industries Private Limited | AB12: 1.8849825 | AC12: 0.0197 | AD12: 46082
H13: Nov 1, 2025 | I13: 2849.68 | J13: 35.174896 | L13: Nov 1, 2025 | M13: 26202.95 | O13: Nov 1, 2025 | P13: 564.6 | R13: Nov 1, 2025 | S13: 233.71 | U13: Nov 1, 2025 | V13: 1283.65 | X13: 2009 | Y13: 75.76
H14: Oct 1, 2025 | I14: 2485.32 | J14: 16.363165 | L14: Oct 1, 2025 | M14: 25722.1 | O14: Oct 1, 2025 | P14: 542.1 | R14: Oct 1, 2025 | S14: 245.04 | U14: Oct 1, 2025 | V14: 999.9 | X14: 2010 | Y14: 17.95
H15: Sep 1, 2025 | I15: 2326.16 | J15: 21.304014 | L15: Sep 1, 2025 | M15: 24611.1 | O15: Sep 1, 2025 | P15: 515.2 | R15: Sep 1, 2025 | S15: 244.47 | U15: Sep 1, 2025 | V15: 1052.2 | X15: 2011 | Y15: -24.62 | AB15: 10000000 | AC15: 100
H16: Aug 1, 2025 | I16: 2493.05 | J16: 26.744337 | L16: Aug 1, 2025 | M16: 24426.85 | O16: Aug 1, 2025 | P16: 533 | R16: Aug 1, 2025 | S16: 237.17 | U16: Aug 1, 2025 | V16: 1099.7 | X16: 2012 | Y16: 27.7
H17: Jul 1, 2025 | I17: 2371.79 | J17: 22.879351 | L17: Jul 1, 2025 | M17: 24768.35 | O17: Jul 1, 2025 | P17: 561.13 | R17: Jul 1, 2025 | S17: 242.02 | U17: Jul 1, 2025 | V17: 1196.31 | X17: 2013 | Y17: 6.76 | AB17: 45078 | AC17: 45170 | AD17: 45261 | AE17: 45352 | AF17: 45444 | AG17: 45536 | AH17: 45627 | AI17: 45717 | AJ17: 45809 | AK17: 45901 | AL17: 45992 | AM17: 46082
H18: Jun 1, 2025 | I18: 2317.35 | J18: 25.721771 | L18: Jun 1, 2025 | M18: 25517.05 | O18: Jun 1, 2025 | P18: 588.7 | R18: Jun 1, 2025 | S18: 249.18 | U18: Jun 1, 2025 | V18: 1158.63 | X18: 2014 | Y18: 31.39 | AA18: Promoters | AB18: 0.5263 | AC18: 0.5263 | AD18: 0.5263 | AE18: 0.5263 | AF18: 0.5263 | AG18: 0.5263 | AH18: 0.5263 | AI18: 0.5263 | AJ18: 0.5263 | AK18: 0.5263 | AL18: 0.5263 | AM18: 0.5263
H19: May 1, 2025 | I19: 2215.74 | J19: 27.390695 | L19: May 1, 2025 | M19: 24750.7 | O19: May 1, 2025 | P19: 564.51 | R19: May 1, 2025 | S19: 246.79 | U19: May 1, 2025 | V19: 1076.13 | X19: 2015 | Y19: -4.06 | AA19: FIIs | AB19: 0.1748 | AC19: 0.1765 | AD19: 0.1732 | AE19: 0.1589 | AF19: 0.1527 | AG19: 0.1528 | AH19: 0.1361 | AI19: 0.1223 | AJ19: 0.1185 | AK19: 0.1164 | AL19: 0.1278 | AM19: 0.1211
H20: Apr 1, 2025 | I20: 2379.14 | J20: 19.512308 | L20: Apr 1, 2025 | M20: 24334.2 | O20: Apr 1, 2025 | P20: 540.57 | R20: Apr 1, 2025 | S20: 250.17 | U20: Apr 1, 2025 | V20: 971.75 | X20: 2016 | Y20: 3.01 | AA20: DIIs | AB20: 0.1001 | AC20: 0.1001 | AD20: 0.1052 | AE20: 0.1161 | AF20: 0.123 | AG20: 0.131 | AH20: 0.1398 | AI20: 0.1551 | AJ20: 0.2098 | AK20: 0.215 | AL20: 0.2108 | AM20: 0.2174
H21: Mar 1, 2025 | I21: 2295.72 | J21: 22.686751 | L21: Mar 1, 2025 | M21: 23519.35 | O21: Mar 1, 2025 | P21: 496.87 | R21: Mar 1, 2025 | S21: 226.56 | U21: Mar 1, 2025 | V21: 939.8 | X21: 2017 | Y21: 28.65 | AA21: Public & Govt. | AB21: 0.1982 | AC21: 0.1964 | AD21: 0.1944 | AE21: 0.1978 | AF21: 0.1968 | AG21: 0.1888 | AH21: 0.1966 | AI21: 0.1951 | AJ21: 0.1441 | AK21: 0.1409 | AL21: 0.1337 | AM21: 0.1352
H22: Feb 1, 2025 | I22: 2137.91 | J22: 28.272421 | L22: Feb 1, 2025 | M22: 22124.7 | O22: Feb 1, 2025 | P22: 485.29 | R22: Feb 1, 2025 | S22: 220.49 | U22: Feb 1, 2025 | V22: 1016.72 | X22: 2018 | Y22: 3.15
H23: Jan 1, 2025 | I23: 2256.64 | J23: 26.548648 | L23: Jan 1, 2025 | M23: 23508.4 | O23: Jan 1, 2025 | P23: 469.6 | R23: Jan 1, 2025 | S23: 226.75 | U23: Jan 1, 2025 | V23: 1263.31 | X23: 2019 | Y23: 12.02
H24: Dec 1, 2024 | I24: 2237.56 | J24: 28.639502 | L24: Dec 1, 2024 | M24: 23644.8 | O24: Dec 1, 2024 | P24: 445.56 | R24: Dec 1, 2024 | S24: 257.79 | U24: Dec 1, 2024 | V24: 1397.74 | X24: 2020 | Y24: 14.9
H25: Nov 1, 2024 | I25: 2432 | J25: 35.976547 | L25: Nov 1, 2024 | M25: 24131.1 | O25: Nov 1, 2024 | P25: 490.41 | R25: Nov 1, 2024 | S25: 273.3 | U25: Nov 1, 2024 | V25: 1429.15 | X25: 2021 | Y25: 24.12
H26: Oct 1, 2024 | I26: 2874.37 | J26: 20.203893 | L26: Oct 1, 2024 | M26: 24205.35 | O26: Oct 1, 2024 | P26: 533.22 | R26: Oct 1, 2024 | S26: 277.34 | U26: Oct 1, 2024 | V26: 1640.34 | X26: 2022 | Y26: 4.32
H27: Sep 1, 2024 | I27: 3259.61 | J27: 24.86929 | L27: Sep 1, 2024 | M27: 25810.85 | O27: Sep 1, 2024 | P27: 618.15 | R27: Sep 1, 2024 | S27: 301.07 | U27: Sep 1, 2024 | V27: 1454.72 | X27: 2023 | Y27: 19.42
