Workbook
Name UPDATE: 'Data Sheet'!$E$1

Sheet Front Page

Sheet Index
B3: Table of Content
B4: (TITAN | BSE Code: 500114)
B9: 1 | C9: One Page Profile (Teaser) | M9: 1
B10: 2 | C10: Historical Income Statement & Balance Sheet | M10: 2
B11: 3 | C11: Historical Cash Flow Statement | M11: 3
B12: 4 | C12: Ratio Analysis | M12: 4
B13: 5 | C13: Common Size Staement | M13: 5
B14: 6 | C14: Assumptions Sheet | M14: 6
B15: 7 | C15: Forcasted Financial Statements | M15: 7
B16: 8 | C16: Beta Regression - Titan Company Ltd. | M16: 8-10
B17: 9 | C17: Comps Beta | M17: 11-13
B18: 10 | C18: Return on Market | M18: 14
B19: 11 | C19: Weighted Average Cost of Capital (WACC) | M19: 15
B20: 12 | C20: Intrinsic Growth | M20: 16
B21: 13 | C21: DCF Valuation (FCFF) | M21: 17
B22: 14 | C22: Comparable Company Valuation | M22: 18
B23: 15 | C23: Football Field Analysis | M23: 19
B24: 16 | C24: Value at Risk - Historical | M24: 20
B25: 17 | C25: Value at Risk - Monte Carlo Method | M25: 21
B26: 18 | C26: DUPONT Analysis (ROE & ROA) | M26: 22-23
B27: 19 | C27: Altman's Z Score Analysis | M27: 24-25

Sheet One Page Summary
B4: ='Data Sheet'!B1&" - One Page Profile" -> TITAN COMPANY LTD - One Page Profile
C5: Titan Company Limited is an Indian fashion accessories company that mainly manufactures items such as jewellery, watches and eyewear. Part of the Tata Group and started as a joint venture with TIDCO, the company has its corporate headquarters in Electronic City, Bangalore and registered office in Hosur, Tamil Nadu. In 1994, Titan diversified into jewellery with Tanishq and subsequently into eyewear with Titan Eyeplus.
B8: Key Financial Metrics | C8: =HistoricalFS!H5 -> 44651 | D8: =HistoricalFS!I5 -> 45016 | E8: =HistoricalFS!J5 -> 45382 | F8: =HistoricalFS!K5 -> 45747 | G8: =HistoricalFS!L5 -> 46112 | I8: Share Price - 5Y
B10: Total Sales | C10: =HistoricalFS!H9 -> 28799 | D10: =HistoricalFS!I9 -> 40575 | E10: =HistoricalFS!J9 -> 51084 | F10: =HistoricalFS!K9 -> 60456 | G10: =HistoricalFS!L9 -> 87584
B11: Sales Growth (Y-O-Y) | C11: =HistoricalFS!H10 -> 0.3305766 | D11: =HistoricalFS!I10 -> 0.40890309 | E11: =HistoricalFS!J10 -> 0.25900185 | F11: =HistoricalFS!K10 -> 0.18346253 | G11: =HistoricalFS!L10 -> 0.44872304
B13: Gross Profit | C13: =HistoricalFS!H15 -> 5574 | D13: =HistoricalFS!I15 -> 8280 | E13: =HistoricalFS!J15 -> 9420 | F13: =HistoricalFS!K15 -> 10432 | G13: =HistoricalFS!L15 -> 14123
B14: Gross Profit Margins (%) | C14: =HistoricalFS!H16 -> 0.19354839 | D14: =HistoricalFS!I16 -> 0.20406654 | E14: =HistoricalFS!J16 -> 0.18440216 | F14: =HistoricalFS!K16 -> 0.17255525 | G14: =HistoricalFS!L16 -> 0.16125091
B15: EBITDA Margins (%) | C15: =HistoricalFS!H22 -> 0.11611514 | D15: =HistoricalFS!I22 -> 0.12032039 | E15: =HistoricalFS!J22 -> 0.10359408 | F15: =HistoricalFS!K22 -> 0.0941842 | G15: =HistoricalFS!L22 -> 0.095416971
B16: EBIT Margins (%) | C16: =HistoricalFS!H31 -> 0.10840654 | D16: =HistoricalFS!I31 -> 0.11699322 | E16: =HistoricalFS!J31 -> 0.1026153 | F16: =HistoricalFS!K31 -> 0.090776763 | G16: =HistoricalFS!L31 -> 0.09112395
B17: Net Profit Margins (In Rs) | C17: =HistoricalFS!H42 -> 2198 | D17: =HistoricalFS!I42 -> 3274 | E17: =HistoricalFS!J42 -> 3496 | F17: =HistoricalFS!K42 -> 3337 | G17: =HistoricalFS!L42 -> 5073
B18: Earning Per Share (In Rs) | C18: =HistoricalFS!H47 -> 24.757828 | D18: =HistoricalFS!I47 -> 36.877675 | E18: =HistoricalFS!J47 -> 39.378238 | F18: =HistoricalFS!K47 -> 37.587294 | G18: =HistoricalFS!L47 -> 57.141248
B19: EPS Growth (Y-O-Y) | C19: =HistoricalFS!H48 -> 1.2566735 | D19: =HistoricalFS!I48 -> 0.48953594 | E19: =HistoricalFS!J48 -> 0.067806964 | F19: =HistoricalFS!K48 -> -0.045480549 | G19: =HistoricalFS!L48 -> 0.52022775
B20: Dividend Per Share | C20: =HistoricalFS!H50 -> 7.5185853 | D20: =HistoricalFS!I50 -> 10.02478 | E20: =HistoricalFS!J50 -> 11.027258 | F20: =HistoricalFS!K50 -> 11.027258 | G20: =HistoricalFS!L50 -> 15.037171
B21: Dividend Growth | C21: ='Data Sheet'!G97 -> 0.875 | D21: ='Data Sheet'!H97 -> 0.33333333 | E21: ='Data Sheet'!I97 -> 0.1 | F21: ='Data Sheet'!J97 -> 0 | G21: ='Data Sheet'!K97 -> 0.36363636
B23: Key Financial Ratio | C23: =C8 -> 44651 | D23: =D8 -> 45016 | E23: =E8 -> 45382 | F23: =F8 -> 45747 | G23: =G8 -> 46112 | I23: Volumes in Million - 5Y
B25: Price to Earning | C25: ='Data Sheet'!G105 -> 185.16971 | D25: ='Data Sheet'!H105 -> 124.31369 | E25: ='Data Sheet'!I105 -> 116.41963 | F25: ='Data Sheet'!J105 -> 121.96675 | G25: ='Data Sheet'!K105 -> 80.229259
B26: EV/EBITDA | C26: ='Data Sheet'!G101 -> 69.037499 | D26: ='Data Sheet'!H101 -> 47.377473 | E26: ='Data Sheet'!I101 -> 66.425889 | F26: ='Data Sheet'!J101 -> 51.134038 | G26: ='Data Sheet'!K101 -> 52.136775
B27: EV/Sales | C27: ='Data Sheet'!G102 -> 8.0162991 | D27: ='Data Sheet'!H102 -> 5.7004762 | E27: ='Data Sheet'!I102 -> 6.8813289 | F27: ='Data Sheet'!J102 -> 4.8160185 | G27: ='Data Sheet'!K102 -> 4.9747332
B28: Price to Book Value | C28: ='Data Sheet'!G104 -> 0.27261636 | D28: ='Data Sheet'!H104 -> 0.21220994 | E28: ='Data Sheet'!I104 -> 0.40474822 | F28: ='Data Sheet'!J104 -> 0.26353665 | G28: ='Data Sheet'!K104 -> 0.29194421
B29: Return on Equity (%) | C29: ='DUPONT Analysis'!F57 -> 0.26166667 | D29: ='DUPONT Analysis'!G57 -> 0.30953957 | E29: ='DUPONT Analysis'!H57 -> 0.32912822 | F29: ='DUPONT Analysis'!I57 -> 0.31755246 | G29: ='DUPONT Analysis'!J57 -> 0.37128115
B30: Return on Capital Employed (%) | C30: ='Ratio Analysis'!H21 -> 0.18832187 | D30: ='Ratio Analysis'!I21 -> 0.22372514 | E30: ='Ratio Analysis'!J21 -> 0.21034469 | F30: ='Ratio Analysis'!K21 -> 0.16937749 | G30: ='Ratio Analysis'!L21 -> 0.1722865
B32: Top 10 Share Holders | C32: =comps_data!C11 -> No. of Shares (Cr) | E32: =comps_data!D11 -> Shareholding (%) | F32: Market Value (In Cr) | I32: Share Holding Pattern
B34: =comps_data!B12 -> Tamilnadu Industrial Development Corporation Ltd | C34: =comps_data!C12 -> 24.747672 | E34: =comps_data!D12 -> 0.2788 | F34: =C34*'Data Sheet'!$B$6 -> 2197.0641
B35: =comps_data!B13 -> Tata Sons Private Limited | C35: =comps_data!C13 -> 18.50589 | E35: =comps_data!D13 -> 0.2084 | F35: =C35*'Data Sheet'!$B$6 -> 1642.9273
B36: =comps_data!B14 -> Rekha Jhunjhunwala | C36: =comps_data!C14 -> 3.7643895 | E36: =comps_data!D14 -> 0.0424 | F36: =C36*'Data Sheet'!$B$6 -> 334.19729
B37: =comps_data!B15 -> Life Insurance Corporation Of India | C37: =comps_data!C15 -> 1.9224672 | E37: =comps_data!D15 -> 0.0217 | F37: =C37*'Data Sheet'!$B$6 -> 170.67398
B38: =comps_data!B16 -> Tata Investment Corporation Ltd | C38: =comps_data!C16 -> 1.787564 | E38: =comps_data!D16 -> 0.0201 | F38: =C38*'Data Sheet'!$B$6 -> 158.69746
B39: =comps_data!B17 -> Sbi Nifty 50 Etf | C39: =comps_data!C17 -> 1.5999057 | E39: =comps_data!D17 -> 0.018 | F39: =C39*'Data Sheet'!$B$6 -> 142.03741
B40: =comps_data!B18 -> Nps Trust A/C Uti Pension Fund Limited-Scheme State Govt | C40: =comps_data!C18 -> 1.5386048 | E40: =comps_data!D18 -> 0.0173 | F40: =C40*'Data Sheet'!$B$6 -> 136.59521
B41: =comps_data!B19 -> Tata Chemicals Limited | C41: =comps_data!C19 -> 1.382618 | E41: =comps_data!D19 -> 0.0156 | F41: =C41*'Data Sheet'!$B$6 -> 122.74691
B42: =comps_data!B20 -> Icici Prudential Balanced Advantage Fund | C42: =comps_data!C20 -> 1.1184971 | E42: =comps_data!D20 -> 0.0126 | F42: =C42*'Data Sheet'!$B$6 -> 99.298625
B43: =comps_data!B21 -> Uti Nifty 50 Etf | C43: =comps_data!C21 -> 0.9851148 | E43: =comps_data!D21 -> 0.0111 | F43: =C43*'Data Sheet'!$B$6 -> 87.457129
B45: Managerial Remuneration | C45: Designation | D45: Remuneration | F45: Ratio to Median | I45: Capital Structure
B47: Dr. S Vijayakumar, IAS | C47: Chairman | D47: - | F47: - | I47: Share Price | K47: ='Data Sheet'!B8 -> 4584.4
B48: Mr. N. N. Tata | C48: Vice Chairman | D48: 7440000 | F48: 6.91X | I48: No of Share | K48: ='Data Sheet'!B6 -> 88.778617
B49: Mr. Ajoy Chawla | C49: MD | D49: 29597925 | F49: 5.13X | I49: Market Capitalization | K49: =K48*K47 -> 406996.69
B50: Mr. Puneet Chhatwal | C50: Director | D50: - | F50: - | I50: Less: Cash & Equivalent | K50: =-'Data Sheet'!K69 -> -1917
I51: Add: Total Debt | K51: ='Data Sheet'!K59 -> 30621
I52: Add: Minority Interest | K52: Nil
I53: Enterprise Value | K53: =SUM(K49:K52) -> 435700.69
B55: Recent Updates
B57: Stock Peak: Reached an all-time high of ₹4,858.20 on NSE amid strong luxury retail demand.
B58: AGM Concluded: Held its 42nd AGM on July 27, discussing governance and Noel Tata's upcoming retirement.
B59: Dividend Disbursed: Paid a final dividend of ₹15 per share (1500%) earlier this month.
B60: Earnings Countdown: Board will meet on August 7, 2026, to approve Q1 FY27 financial results.

Sheet HistoricalFS
B4: ="Historical Financial Statements"&" - "&'Data Sheet'!B1 -> Historical Financial Statements - TITAN COMPANY LTD
B5: Years | C5: ='Data Sheet'!B16 -> 42825 | D5: ='Data Sheet'!C16 -> 43190 | E5: ='Data Sheet'!D16 -> 43555 | F5: ='Data Sheet'!E16 -> 43921 | G5: ='Data Sheet'!F16 -> 44286 | H5: ='Data Sheet'!G16 -> 44651 | I5: ='Data Sheet'!H16 -> 45016 | J5: ='Data Sheet'!I16 -> 45382 | ... L5: ='Data Sheet'!K16 -> 46112
A7: # | B7: ="Income Statement"&" - "&'Data Sheet'!B1 -> Income Statement - TITAN COMPANY LTD
B9: Sales | C9: =IFERROR('Data Sheet'!B17,0) -> 13260.83 | D9: =IFERROR('Data Sheet'!C17,0) -> 16119.77 | E9: =IFERROR('Data Sheet'!D17,0) -> 19778.52 | F9: =IFERROR('Data Sheet'!E17,0) -> 21052 | G9: =IFERROR('Data Sheet'!F17,0) -> 21644 | H9: =IFERROR('Data Sheet'!G17,0) -> 28799 | I9: =IFERROR('Data Sheet'!H17,0) -> 40575 | J9: =IFERROR('Data Sheet'!I17,0) -> 51084 | ... L9: =IFERROR('Data Sheet'!K17,0) -> 87584
B10: Sales Growth | D10: =IFERROR(D9/C9-1,0) -> 0.21559284 | E10: =IFERROR(E9/D9-1,0) -> 0.22697284 | F10: =IFERROR(F9/E9-1,0) -> 0.064387022 | G10: =IFERROR(G9/F9-1,0) -> 0.028120844 | H10: =IFERROR(H9/G9-1,0) -> 0.3305766 | I10: =IFERROR(I9/H9-1,0) -> 0.40890309 | J10: =IFERROR(J9/I9-1,0) -> 0.25900185 | K10: =IFERROR(K9/J9-1,0) -> 0.18346253 | L10: =IFERROR(L9/K9-1,0) -> 0.44872304
B12: COGS | C12: =IFERROR(SUM('Data Sheet'!B18,'Data Sheet'!B20:B22)-1*'Data Sheet'!B19,0) -> 10606.01 | D12: =IFERROR(SUM('Data Sheet'!C18,'Data Sheet'!C20:C22)-1*'Data Sheet'!C19,0) -> 12762.63 | E12: =IFERROR(SUM('Data Sheet'!D18,'Data Sheet'!D20:D22)-1*'Data Sheet'!D19,0) -> 15660.48 | F12: =IFERROR(SUM('Data Sheet'!E18,'Data Sheet'!E20:E22)-1*'Data Sheet'!E19,0) -> 16626 | G12: =IFERROR(SUM('Data Sheet'!F18,'Data Sheet'!F20:F22)-1*'Data Sheet'!F19,0) -> 17661 | H12: =IFERROR(SUM('Data Sheet'!G18,'Data Sheet'!G20:G22)-1*'Data Sheet'!G19,0) -> 23225 | I12: =IFERROR(SUM('Data Sheet'!H18,'Data Sheet'!H20:H22)-1*'Data Sheet'!H19,0) -> 32295 | J12: =IFERROR(SUM('Data Sheet'!I18,'Data Sheet'!I20:I22)-1*'Data Sheet'!I19,0) -> 41664 | ... L12: =IFERROR(SUM('Data Sheet'!K18,'Data Sheet'!K20:K22)-1*'Data Sheet'!K19,0) -> 73461
B13: COGS % of Sales | C13: =IFERROR(C12/C9,0) -> 0.79979986 | D13: =IFERROR(D12/D9,0) -> 0.79173772 | E13: =IFERROR(E12/E9,0) -> 0.79179231 | F13: =IFERROR(F12/F9,0) -> 0.78975869 | G13: =IFERROR(G12/G9,0) -> 0.81597671 | H13: =IFERROR(H12/H9,0) -> 0.80645161 | I13: =IFERROR(I12/I9,0) -> 0.79593346 | J13: =IFERROR(J12/J9,0) -> 0.81559784 | ... L13: =IFERROR(L12/L9,0) -> 0.83874909
B15: Gross Profit | C15: =C9-C12 -> 2654.82 | D15: =D9-D12 -> 3357.14 | E15: =E9-E12 -> 4118.04 | F15: =F9-F12 -> 4426 | G15: =G9-G12 -> 3983 | H15: =H9-H12 -> 5574 | I15: =I9-I12 -> 8280 | J15: =J9-J12 -> 9420 | ... L15: =L9-L12 -> 14123
B16: Gross Margins | C16: =IFERROR(C15/C9,0) -> 0.20020014 | D16: =IFERROR(D15/D9,0) -> 0.20826228 | E16: =IFERROR(E15/E9,0) -> 0.20820769 | F16: =IFERROR(F15/F9,0) -> 0.21024131 | G16: =IFERROR(G15/G9,0) -> 0.18402329 | H16: =IFERROR(H15/H9,0) -> 0.19354839 | I16: =IFERROR(I15/I9,0) -> 0.20406654 | J16: =IFERROR(J15/J9,0) -> 0.18440216 | ... L16: =IFERROR(L15/L9,0) -> 0.16125091
B18: Selling & General Expenses | C18: =IFERROR(SUM('Data Sheet'!B23:B24),0) -> 1490.92 | D18: =IFERROR(SUM('Data Sheet'!C23:C24),0) -> 1712.94 | E18: =IFERROR(SUM('Data Sheet'!D23:D24),0) -> 2124.25 | F18: =IFERROR(SUM('Data Sheet'!E23:E24),0) -> 1963 | G18: =IFERROR(SUM('Data Sheet'!F23:F24),0) -> 2258 | H18: =IFERROR(SUM('Data Sheet'!G23:G24),0) -> 2230 | I18: =IFERROR(SUM('Data Sheet'!H23:H24),0) -> 3398 | J18: =IFERROR(SUM('Data Sheet'!I23:I24),0) -> 4128 | ... L18: =IFERROR(SUM('Data Sheet'!K23:K24),0) -> 5766
B19: S&G % of Sales | C19: =IFERROR(C18/C9,0) -> 0.11243037 | D19: =IFERROR(D18/D9,0) -> 0.1062633 | E19: =IFERROR(E18/E9,0) -> 0.10740187 | F19: =IFERROR(F18/F9,0) -> 0.093245297 | G19: =IFERROR(G18/G9,0) -> 0.10432452 | H19: =IFERROR(H18/H9,0) -> 0.077433244 | I19: =IFERROR(I18/I9,0) -> 0.083746149 | J19: =IFERROR(J18/J9,0) -> 0.080808081 | ... L19: =IFERROR(L18/L9,0) -> 0.065833942
B21: EBITDA | C21: =C15-C18 -> 1163.9 | D21: =D15-D18 -> 1644.2 | E21: =E15-E18 -> 1993.79 | F21: =F15-F18 -> 2463 | G21: =G15-G18 -> 1725 | H21: =H15-H18 -> 3344 | I21: =I15-I18 -> 4882 | J21: =J15-J18 -> 5292 | ... L21: =L15-L18 -> 8357
B22: EBITDA Margins | C22: =IFERROR(C21/C9,0) -> 0.08776977 | D22: =IFERROR(D21/D9,0) -> 0.10199897 | E22: =IFERROR(E21/E9,0) -> 0.10080582 | F22: =IFERROR(F21/F9,0) -> 0.11699601 | G22: =IFERROR(G21/G9,0) -> 0.079698762 | H22: =IFERROR(H21/H9,0) -> 0.11611514 | I22: =IFERROR(I21/I9,0) -> 0.12032039 | J22: =IFERROR(J21/J9,0) -> 0.10359408 | ... L22: =IFERROR(L21/L9,0) -> 0.095416971
B24: Other Income | C24: =IFERROR('Data Sheet'!B25,0) -> -42.38 | D24: =IFERROR('Data Sheet'!C25,0) -> 69.93 | E24: =IFERROR('Data Sheet'!D25,0) -> 178.48 | F24: =IFERROR('Data Sheet'!E25,0) -> 153 | G24: =IFERROR('Data Sheet'!F25,0) -> 180 | H24: =IFERROR('Data Sheet'!G25,0) -> 177 | I24: =IFERROR('Data Sheet'!H25,0) -> 306 | J24: =IFERROR('Data Sheet'!I25,0) -> 534 | ... L24: =IFERROR('Data Sheet'!K25,0) -> 450
B25: Other Income % of Sales | C25: =IFERROR(C24/C9,0) -> -0.0031958784 | D25: =IFERROR(D24/D9,0) -> 0.0043381512 | E25: =IFERROR(E24/E9,0) -> 0.009023931 | F25: =IFERROR(F24/F9,0) -> 0.007267718 | G25: =IFERROR(G24/G9,0) -> 0.0083163925 | H25: =IFERROR(H24/H9,0) -> 0.0061460467 | I25: =IFERROR(I24/I9,0) -> 0.0075415896 | J25: =IFERROR(J24/J9,0) -> 0.010453371 | ... L25: =IFERROR(L24/L9,0) -> 0.0051379247
B27: Depreciation | C27: =IFERROR('Data Sheet'!B26,0) -> 110.53 | D27: =IFERROR('Data Sheet'!C26,0) -> 131.43 | E27: =IFERROR('Data Sheet'!D26,0) -> 162.84 | F27: =IFERROR('Data Sheet'!E26,0) -> 348 | G27: =IFERROR('Data Sheet'!F26,0) -> 375 | H27: =IFERROR('Data Sheet'!G26,0) -> 399 | I27: =IFERROR('Data Sheet'!H26,0) -> 441 | J27: =IFERROR('Data Sheet'!I26,0) -> 584 | ... L27: =IFERROR('Data Sheet'!K26,0) -> 826
B28: Depreciation % of Sales | C28: =IFERROR(C27/C9,0) -> 0.008335074 | D28: =IFERROR(D27/D9,0) -> 0.0081533421 | E28: =IFERROR(E27/E9,0) -> 0.0082331742 | F28: =IFERROR(F27/F9,0) -> 0.016530496 | G28: =IFERROR(G27/G9,0) -> 0.017325818 | H28: =IFERROR(H27/H9,0) -> 0.013854648 | I28: =IFERROR(I27/I9,0) -> 0.010868762 | J28: =IFERROR(J27/J9,0) -> 0.011432151 | ... L28: =IFERROR(L27/L9,0) -> 0.0094309463
B30: EBIT | C30: =SUM(C21,C24)-C27 -> 1010.99 | D30: =SUM(D21,D24)-D27 -> 1582.7 | E30: =SUM(E21,E24)-E27 -> 2009.43 | F30: =SUM(F21,F24)-F27 -> 2268 | G30: =SUM(G21,G24)-G27 -> 1530 | H30: =SUM(H21,H24)-H27 -> 3122 | I30: =SUM(I21,I24)-I27 -> 4747 | J30: =SUM(J21,J24)-J27 -> 5242 | ... L30: =SUM(L21,L24)-L27 -> 7981
B31: EBIT Margins | C31: =IFERROR(C30/C9,0) -> 0.076238818 | D31: =IFERROR(D30/D9,0) -> 0.098183783 | E31: =IFERROR(E30/E9,0) -> 0.10159658 | F31: =IFERROR(F30/F9,0) -> 0.10773323 | G31: =IFERROR(G30/G9,0) -> 0.070689337 | H31: =IFERROR(H30/H9,0) -> 0.10840654 | I31: =IFERROR(I30/I9,0) -> 0.11699322 | J31: =IFERROR(J30/J9,0) -> 0.1026153 | ... L31: =IFERROR(L30/L9,0) -> 0.09112395
B33: Interest Expense | C33: =IFERROR('Data Sheet'!B27,0) -> 37.74 | D33: =IFERROR('Data Sheet'!C27,0) -> 52.92 | E33: =IFERROR('Data Sheet'!D27,0) -> 52.54 | F33: =IFERROR('Data Sheet'!E27,0) -> 166 | G33: =IFERROR('Data Sheet'!F27,0) -> 203 | H33: =IFERROR('Data Sheet'!G27,0) -> 218 | I33: =IFERROR('Data Sheet'!H27,0) -> 300 | J33: =IFERROR('Data Sheet'!I27,0) -> 619 | ... L33: =IFERROR('Data Sheet'!K27,0) -> 1180
B34: Interest % of Sales | C34: =IFERROR(C33/C9,0) -> 0.0028459757 | D34: =IFERROR(D33/D9,0) -> 0.0032829253 | E34: =IFERROR(E33/E9,0) -> 0.0026564172 | F34: =IFERROR(F33/F9,0) -> 0.0078852366 | G34: =IFERROR(G33/G9,0) -> 0.0093790427 | H34: =IFERROR(H33/H9,0) -> 0.0075697073 | I34: =IFERROR(I33/I9,0) -> 0.0073937153 | J34: =IFERROR(J33/J9,0) -> 0.012117297 | ... L34: =IFERROR(L33/L9,0) -> 0.01347278
B36: Earning before Tax | C36: =C30-C33 -> 973.25 | D36: =D30-D33 -> 1529.78 | E36: =E30-E33 -> 1956.89 | F36: =F30-F33 -> 2102 | G36: =G30-G33 -> 1327 | H36: =H30-H33 -> 2904 | I36: =I30-I33 -> 4447 | J36: =J30-J33 -> 4623 | ... L36: =L30-L33 -> 6801
B37: EBT % of Sales | C37: =IFERROR(C36/C9,0) -> 0.073392842 | D37: =IFERROR(D36/D9,0) -> 0.094900858 | E37: =IFERROR(E36/E9,0) -> 0.098940163 | F37: =IFERROR(F36/F9,0) -> 0.099847995 | G37: =IFERROR(G36/G9,0) -> 0.061310294 | H37: =IFERROR(H36/H9,0) -> 0.10083683 | I37: =IFERROR(I36/I9,0) -> 0.10959951 | J37: =IFERROR(J36/J9,0) -> 0.090498003 | ... L37: =IFERROR(L36/L9,0) -> 0.077651169
B39: Tax Expense | C39: =IFERROR('Data Sheet'!B29,0) -> 275.97 | D39: =IFERROR('Data Sheet'!C29,0) -> 427.87 | E39: =IFERROR('Data Sheet'!D29,0) -> 568.24 | F39: =IFERROR('Data Sheet'!E29,0) -> 609 | G39: =IFERROR('Data Sheet'!F29,0) -> 353 | H39: =IFERROR('Data Sheet'!G29,0) -> 706 | I39: =IFERROR('Data Sheet'!H29,0) -> 1173 | J39: =IFERROR('Data Sheet'!I29,0) -> 1127 | ... L39: =IFERROR('Data Sheet'!K29,0) -> 1728
B40: Effective Tax Rate | C40: =IFERROR(C39/C36,0) -> 0.2835551 | D40: =IFERROR(D39/D36,0) -> 0.27969381 | E40: =IFERROR(E39/E36,0) -> 0.29037912 | F40: =IFERROR(F39/F36,0) -> 0.28972407 | G40: =IFERROR(G39/G36,0) -> 0.26601356 | H40: =IFERROR(H39/H36,0) -> 0.24311295 | I40: =IFERROR(I39/I36,0) -> 0.26377333 | J40: =IFERROR(J39/J36,0) -> 0.24378109 | ... L40: =IFERROR(L39/L36,0) -> 0.25408028
B42: Net Profit | C42: =C36-C39 -> 697.28 | D42: =D36-D39 -> 1101.91 | E42: =E36-E39 -> 1388.65 | F42: =F36-F39 -> 1493 | G42: =G36-G39 -> 974 | H42: =H36-H39 -> 2198 | I42: =I36-I39 -> 3274 | J42: =J36-J39 -> 3496 | ... L42: =L36-L39 -> 5073
B43: Net Profit Margins | C43: =IFERROR(C42/C9,0) -> 0.052581927 | D43: =IFERROR(D42/D9,0) -> 0.068357675 | E43: =IFERROR(E42/E9,0) -> 0.070210006 | F43: =IFERROR(F42/F9,0) -> 0.070919628 | G43: =IFERROR(G42/G9,0) -> 0.045000924 | H43: =IFERROR(H42/H9,0) -> 0.076322095 | I43: =IFERROR(I42/I9,0) -> 0.08069008 | J43: =IFERROR(J42/J9,0) -> 0.068436301 | ... L43: =IFERROR(L42/L9,0) -> 0.057921538
B45: No of Equity Shares | C45: =IFERROR('Data Sheet'!B93,0) -> 88.78 | D45: =IFERROR('Data Sheet'!C93,0) -> 88.78 | E45: =IFERROR('Data Sheet'!D93,0) -> 88.78 | F45: =IFERROR('Data Sheet'!E93,0) -> 88.78 | G45: =IFERROR('Data Sheet'!F93,0) -> 88.78 | H45: =IFERROR('Data Sheet'!G93,0) -> 88.78 | I45: =IFERROR('Data Sheet'!H93,0) -> 88.78 | J45: =IFERROR('Data Sheet'!I93,0) -> 88.78 | ... L45: =IFERROR('Data Sheet'!K93,0) -> 88.78
B47: Earnings Per Share | C47: =IFERROR(C42/C45,0) -> 7.8540212 | D47: =IFERROR(D42/D45,0) -> 12.411692 | E47: =IFERROR(E42/E45,0) -> 15.641473 | F47: =IFERROR(F42/F45,0) -> 16.816851 | G47: =IFERROR(G42/G45,0) -> 10.970939 | H47: =IFERROR(H42/H45,0) -> 24.757828 | I47: =IFERROR(I42/I45,0) -> 36.877675 | J47: =IFERROR(J42/J45,0) -> 39.378238 | ... L47: =IFERROR(L42/L45,0) -> 57.141248
B48: EPS Growth Rate | D48: =D47/C47-1 -> 0.58029773 | E48: =E47/D47-1 -> 0.26022089 | F48: =F47/E47-1 -> 0.075144925 | G48: =G47/F47-1 -> -0.34762224 | H48: =H47/G47-1 -> 1.2566735 | I48: =I47/H47-1 -> 0.48953594 | J48: =J47/I47-1 -> 0.067806964 | K48: =K47/J47-1 -> -0.045480549 | L48: =L47/K47-1 -> 0.52022775
B50: Dividend Per Shares | C50: =IFERROR('Data Sheet'!B31/HistoricalFS!C45,0) -> 2.6000225 | D50: =IFERROR('Data Sheet'!C31/HistoricalFS!D45,0) -> 3.7499437 | E50: =IFERROR('Data Sheet'!D31/HistoricalFS!E45,0) -> 5 | F50: =IFERROR('Data Sheet'!E31/HistoricalFS!F45,0) -> 4.0099121 | G50: =IFERROR('Data Sheet'!F31/HistoricalFS!G45,0) -> 4.0099121 | H50: =IFERROR('Data Sheet'!G31/HistoricalFS!H45,0) -> 7.5185853 | I50: =IFERROR('Data Sheet'!H31/HistoricalFS!I45,0) -> 10.02478 | J50: =IFERROR('Data Sheet'!I31/HistoricalFS!J45,0) -> 11.027258 | ... L50: =IFERROR('Data Sheet'!K31/HistoricalFS!L45,0) -> 15.037171
B51: Dividend Payout Ratio | C51: =IFERROR(C50/C47,0) -> 0.33104348 | D51: =IFERROR(D50/D47,0) -> 0.30212994 | E51: =IFERROR(E50/E47,0) -> 0.31966298 | F51: =IFERROR(F50/F47,0) -> 0.23844608 | G51: =IFERROR(G50/G47,0) -> 0.36550308 | H51: =IFERROR(H50/H47,0) -> 0.30368517 | I51: =IFERROR(I50/I47,0) -> 0.27183873 | J51: =IFERROR(J50/J47,0) -> 0.28003432 | ... L51: =IFERROR(L50/L47,0) -> 0.26315789
B53: Retained Earnings | C53: =IFERROR(1-C51,0) -> 0.66895652 | D53: =IFERROR(1-D51,0) -> 0.69787006 | E53: =IFERROR(1-E51,0) -> 0.68033702 | F53: =IFERROR(1-F51,0) -> 0.76155392 | G53: =IFERROR(1-G51,0) -> 0.63449692 | H53: =IFERROR(1-H51,0) -> 0.69631483 | I53: =IFERROR(1-I51,0) -> 0.72816127 | J53: =IFERROR(1-J51,0) -> 0.71996568 | ... L53: =IFERROR(1-L51,0) -> 0.73684211
A55: # | B55: ="Balance Sheet"&" - "&'Data Sheet'!B1 -> Balance Sheet - TITAN COMPANY LTD
B56: Equity Share Capital | C56: =IFERROR('Data Sheet'!B57,0) -> 88.78 | D56: =IFERROR('Data Sheet'!C57,0) -> 88.78 | E56: =IFERROR('Data Sheet'!D57,0) -> 88.78 | F56: =IFERROR('Data Sheet'!E57,0) -> 89 | G56: =IFERROR('Data Sheet'!F57,0) -> 89 | H56: =IFERROR('Data Sheet'!G57,0) -> 89 | I56: =IFERROR('Data Sheet'!H57,0) -> 89 | J56: =IFERROR('Data Sheet'!I57,0) -> 89 | ... L56: =IFERROR('Data Sheet'!K57,0) -> 89
B57: Reserves | C57: =IFERROR('Data Sheet'!B58,0) -> 4143.6 | D57: =IFERROR('Data Sheet'!C58,0) -> 5001.1 | E57: =IFERROR('Data Sheet'!D58,0) -> 5981.37 | F57: =IFERROR('Data Sheet'!E58,0) -> 6580 | G57: =IFERROR('Data Sheet'!F58,0) -> 7408 | H57: =IFERROR('Data Sheet'!G58,0) -> 9214 | I57: =IFERROR('Data Sheet'!H58,0) -> 11762 | J57: =IFERROR('Data Sheet'!I58,0) -> 9304 | ... L57: =IFERROR('Data Sheet'!K58,0) -> 15614
B58: Borrowings | C58: =IFERROR('Data Sheet'!B59,0) -> 1882.43 | D58: =IFERROR('Data Sheet'!C59,0) -> 1691.01 | E58: =IFERROR('Data Sheet'!D59,0) -> 2392.98 | F58: =IFERROR('Data Sheet'!E59,0) -> 3562 | G58: =IFERROR('Data Sheet'!F59,0) -> 5638 | H58: =IFERROR('Data Sheet'!G59,0) -> 7275 | I58: =IFERROR('Data Sheet'!H59,0) -> 9367 | J58: =IFERROR('Data Sheet'!I59,0) -> 15528 | ... L58: =IFERROR('Data Sheet'!K59,0) -> 30621
B59: Trade Payables | C59: =IFERROR('Data Sheet'!B33,0) -> 783 | D59: =IFERROR('Data Sheet'!C33,0) -> 878 | E59: =IFERROR('Data Sheet'!D33,0) -> 906 | F59: =IFERROR('Data Sheet'!E33,0) -> 596 | G59: =IFERROR('Data Sheet'!F33,0) -> 789 | H59: =IFERROR('Data Sheet'!G33,0) -> 1294 | I59: =IFERROR('Data Sheet'!H33,0) -> 1214 | J59: =IFERROR('Data Sheet'!I33,0) -> 1410 | ... L59: =IFERROR('Data Sheet'!K33,0) -> 2864
B60: Other Liabilities | C60: =IFERROR('Data Sheet'!B60-'Data Sheet'!B33,0) -> 1509.76 | D60: =IFERROR('Data Sheet'!C60-'Data Sheet'!C33,0) -> 1862.15 | E60: =IFERROR('Data Sheet'!D60-'Data Sheet'!D33,0) -> 2340.71 | F60: =IFERROR('Data Sheet'!E60-'Data Sheet'!E33,0) -> 2717 | G60: =IFERROR('Data Sheet'!F60-'Data Sheet'!F33,0) -> 2520 | H60: =IFERROR('Data Sheet'!G60-'Data Sheet'!G33,0) -> 3316 | I60: =IFERROR('Data Sheet'!H60-'Data Sheet'!H33,0) -> 4588 | J60: =IFERROR('Data Sheet'!I60-'Data Sheet'!I33,0) -> 5216 | ... L60: =IFERROR('Data Sheet'!K60-'Data Sheet'!K33,0) -> 11373
B61: Total Liabilities | C61: =SUM(C56:C60) -> 8407.57 | D61: =SUM(D56:D60) -> 9521.04 | E61: =SUM(E56:E60) -> 11709.84 | F61: =SUM(F56:F60) -> 13544 | G61: =SUM(G56:G60) -> 16444 | H61: =SUM(H56:H60) -> 21188 | I61: =SUM(I56:I60) -> 27020 | J61: =SUM(J56:J60) -> 31547 | ... L61: =SUM(L56:L60) -> 60561
B63: Fixed Assets Net Block | C63: =IFERROR('Data Sheet'!B62,0) -> 1188.72 | D63: =IFERROR('Data Sheet'!C62,0) -> 1473.81 | E63: =IFERROR('Data Sheet'!D62,0) -> 1566.63 | F63: =IFERROR('Data Sheet'!E62,0) -> 2633 | G63: =IFERROR('Data Sheet'!F62,0) -> 2523 | H63: =IFERROR('Data Sheet'!G62,0) -> 2544 | I63: =IFERROR('Data Sheet'!H62,0) -> 2998 | J63: =IFERROR('Data Sheet'!I62,0) -> 3709 | ... L63: =IFERROR('Data Sheet'!K62,0) -> 6878
B64: Capital Work in Progress | C64: =IFERROR('Data Sheet'!B63,0) -> 152.07 | D64: =IFERROR('Data Sheet'!C63,0) -> 43.37 | E64: =IFERROR('Data Sheet'!D63,0) -> 31.77 | F64: =IFERROR('Data Sheet'!E63,0) -> 18 | G64: =IFERROR('Data Sheet'!F63,0) -> 32 | H64: =IFERROR('Data Sheet'!G63,0) -> 85 | I64: =IFERROR('Data Sheet'!H63,0) -> 144 | J64: =IFERROR('Data Sheet'!I63,0) -> 97 | ... L64: =IFERROR('Data Sheet'!K63,0) -> 163
B65: Investments | C65: =IFERROR('Data Sheet'!B64,0) -> 430.73 | D65: =IFERROR('Data Sheet'!C64,0) -> 35.99 | E65: =IFERROR('Data Sheet'!D64,0) -> 108.42 | F65: =IFERROR('Data Sheet'!E64,0) -> 158 | G65: =IFERROR('Data Sheet'!F64,0) -> 2824 | H65: =IFERROR('Data Sheet'!G64,0) -> 294 | I65: =IFERROR('Data Sheet'!H64,0) -> 2515 | J65: =IFERROR('Data Sheet'!I64,0) -> 2345 | ... L65: =IFERROR('Data Sheet'!K64,0) -> 3506
B66: Other Assets | C66: =IFERROR('Data Sheet'!B65-SUM('Data Sheet'!B67:B69),0) -> 723.78 | D66: =IFERROR('Data Sheet'!C65-SUM('Data Sheet'!C67:C69),0) -> 1129.43 | E66: =IFERROR('Data Sheet'!D65-SUM('Data Sheet'!D67:D69),0) -> 1477.27 | F66: =IFERROR('Data Sheet'!E65-SUM('Data Sheet'!E67:E69),0) -> 1939 | G66: =IFERROR('Data Sheet'!F65-SUM('Data Sheet'!F67:F69),0) -> 1731 | H66: =IFERROR('Data Sheet'!G65-SUM('Data Sheet'!G67:G69),0) -> 2518 | I66: =IFERROR('Data Sheet'!H65-SUM('Data Sheet'!H67:H69),0) -> 2762 | J66: =IFERROR('Data Sheet'!I65-SUM('Data Sheet'!I67:I69),0) -> 3801 | ... L66: =IFERROR('Data Sheet'!K65-SUM('Data Sheet'!K67:K69),0) -> 4438
B67: Total Non Current Assets | C67: =SUM(C63:C66) -> 2495.3 | D67: =SUM(D63:D66) -> 2682.6 | E67: =SUM(E63:E66) -> 3184.09 | F67: =SUM(F63:F66) -> 4748 | G67: =SUM(G63:G66) -> 7110 | H67: =SUM(H63:H66) -> 5441 | I67: =SUM(I63:I66) -> 8419 | J67: =SUM(J63:J66) -> 9952 | ... L67: =SUM(L63:L66) -> 14985
B69: Receivables | C69: =IFERROR('Data Sheet'!B67,0) -> 207.6 | D69: =IFERROR('Data Sheet'!C67,0) -> 295.69 | E69: =IFERROR('Data Sheet'!D67,0) -> 420.45 | F69: =IFERROR('Data Sheet'!E67,0) -> 312 | G69: =IFERROR('Data Sheet'!F67,0) -> 366 | H69: =IFERROR('Data Sheet'!G67,0) -> 565 | I69: =IFERROR('Data Sheet'!H67,0) -> 674 | J69: =IFERROR('Data Sheet'!I67,0) -> 1018 | ... L69: =IFERROR('Data Sheet'!K67,0) -> 916
B70: Inventory | C70: =IFERROR('Data Sheet'!B68,0) -> 4925.74 | D70: =IFERROR('Data Sheet'!C68,0) -> 5924.84 | E70: =IFERROR('Data Sheet'!D68,0) -> 7038.82 | F70: =IFERROR('Data Sheet'!E68,0) -> 8103 | G70: =IFERROR('Data Sheet'!F68,0) -> 8408 | H70: =IFERROR('Data Sheet'!G68,0) -> 13609 | I70: =IFERROR('Data Sheet'!H68,0) -> 16584 | J70: =IFERROR('Data Sheet'!I68,0) -> 19051 | ... L70: =IFERROR('Data Sheet'!K68,0) -> 42743
B71: Cash & Bank | C71: =IFERROR('Data Sheet'!B69,0) -> 778.93 | D71: =IFERROR('Data Sheet'!C69,0) -> 617.91 | E71: =IFERROR('Data Sheet'!D69,0) -> 1066.48 | F71: =IFERROR('Data Sheet'!E69,0) -> 381 | G71: =IFERROR('Data Sheet'!F69,0) -> 560 | H71: =IFERROR('Data Sheet'!G69,0) -> 1573 | I71: =IFERROR('Data Sheet'!H69,0) -> 1343 | J71: =IFERROR('Data Sheet'!I69,0) -> 1526 | ... L71: =IFERROR('Data Sheet'!K69,0) -> 1917
B72: Total Current Assets | C72: =SUM(C69:C71) -> 5912.27 | D72: =SUM(D69:D71) -> 6838.44 | E72: =SUM(E69:E71) -> 8525.75 | F72: =SUM(F69:F71) -> 8796 | G72: =SUM(G69:G71) -> 9334 | H72: =SUM(H69:H71) -> 15747 | I72: =SUM(I69:I71) -> 18601 | J72: =SUM(J69:J71) -> 21595 | ... L72: =SUM(L69:L71) -> 45576
B74: Total Assets | C74: =SUM(C72,C67) -> 8407.57 | D74: =SUM(D72,D67) -> 9521.04 | E74: =SUM(E72,E67) -> 11709.84 | F74: =SUM(F72,F67) -> 13544 | G74: =SUM(G72,G67) -> 16444 | H74: =SUM(H72,H67) -> 21188 | I74: =SUM(I72,I67) -> 27020 | J74: =SUM(J72,J67) -> 31547 | ... L74: =SUM(L72,L67) -> 60561
B76: Check | C76: =IFERROR(C74=C61,0) -> TRUE | D76: =IFERROR(D74=D61,0) -> TRUE | E76: =IFERROR(E74=E61,0) -> TRUE | F76: =IFERROR(F74=F61,0) -> TRUE | G76: =IFERROR(G74=G61,0) -> TRUE | H76: =IFERROR(H74=H61,0) -> TRUE | I76: =IFERROR(I74=I61,0) -> TRUE | J76: =IFERROR(J74=J61,0) -> TRUE | ... L76: =IFERROR(L74=L61,0) -> TRUE
A78: # | B78: ="Income Statement"&" - "&'Data Sheet'!B1 -> Income Statement - TITAN COMPANY LTD
B79: Cash from Operating Activity -
B80: Profit from operations | C80: =IFERROR(CashFlow!E4,0) -> 1073 | D80: =IFERROR(CashFlow!F4,0) -> 1642 | E80: =IFERROR(CashFlow!G4,0) -> 2183 | F80: =IFERROR(CashFlow!H4,0) -> 2481 | G80: =IFERROR(CashFlow!I4,0) -> 1789 | H80: =IFERROR(CashFlow!J4,0) -> 3298 | I80: =IFERROR(CashFlow!K4,0) -> 4937 | J80: =IFERROR(CashFlow!L4,0) -> 5404 | ... L80: =IFERROR(CashFlow!N4,0) -> 8447
B81: Receivables | C81: =IFERROR(CashFlow!E5,0) -> -12 | D81: =IFERROR(CashFlow!F5,0) -> -90 | E81: =IFERROR(CashFlow!G5,0) -> -139 | F81: =IFERROR(CashFlow!H5,0) -> 109 | G81: =IFERROR(CashFlow!I5,0) -> -59 | H81: =IFERROR(CashFlow!J5,0) -> -207 | I81: =IFERROR(CashFlow!K5,0) -> -112 | J81: =IFERROR(CashFlow!L5,0) -> -348 | ... L81: =IFERROR(CashFlow!N5,0) -> 210
B82: Inventory | C82: =IFERROR(CashFlow!E6,0) -> -448 | D82: =IFERROR(CashFlow!F6,0) -> -996 | E82: =IFERROR(CashFlow!G6,0) -> -1120 | F82: =IFERROR(CashFlow!H6,0) -> -1057 | G82: =IFERROR(CashFlow!I6,0) -> -316 | H82: =IFERROR(CashFlow!J6,0) -> -5199 | I82: =IFERROR(CashFlow!K6,0) -> -2977 | J82: =IFERROR(CashFlow!L6,0) -> -2462 | ... L82: =IFERROR(CashFlow!N6,0) -> -11592
B83: Payables | C83: =IFERROR(CashFlow!E7,0) -> 238 | D83: =IFERROR(CashFlow!F7,0) -> 95 | E83: =IFERROR(CashFlow!G7,0) -> 32 | F83: =IFERROR(CashFlow!H7,0) -> -310 | G83: =IFERROR(CashFlow!I7,0) -> 195 | H83: =IFERROR(CashFlow!J7,0) -> 504 | I83: =IFERROR(CashFlow!K7,0) -> -89 | J83: =IFERROR(CashFlow!L7,0) -> 196 | ... L83: =IFERROR(CashFlow!N7,0) -> 472
B84: Loans Advances | C84: =IFERROR(CashFlow!E8,0) -> 0 | D84: =IFERROR(CashFlow!F8,0) -> 3 | E84: =IFERROR(CashFlow!G8,0) -> -24 | F84: =IFERROR(CashFlow!H8,0) -> -20 | G84: =IFERROR(CashFlow!I8,0) -> -8 | H84: =IFERROR(CashFlow!J8,0) -> -3 | I84: =IFERROR(CashFlow!K8,0) -> -18 | J84: =IFERROR(CashFlow!L8,0) -> -21 | ... L84: =IFERROR(CashFlow!N8,0) -> -8
B85: Operating borrowings | C85: =IFERROR(CashFlow!E9,0) -> 763 | D85: =IFERROR(CashFlow!F9,0) -> -270 | E85: =IFERROR(CashFlow!G9,0) -> 741 | F85: =IFERROR(CashFlow!H9,0) -> -768 | G85: =IFERROR(CashFlow!I9,0) -> 2625 | H85: =IFERROR(CashFlow!J9,0) -> 1188 | I85: =IFERROR(CashFlow!K9,0) -> -99 | J85: =IFERROR(CashFlow!L9,0) -> 42 | ... L85: =IFERROR(CashFlow!N9,0) -> 7304
B86: Other WC items | C86: =IFERROR(CashFlow!E10,0) -> 375 | D86: =IFERROR(CashFlow!F10,0) -> 22 | E86: =IFERROR(CashFlow!G10,0) -> 206 | F86: =IFERROR(CashFlow!H10,0) -> -226 | G86: =IFERROR(CashFlow!I10,0) -> 184 | H86: =IFERROR(CashFlow!J10,0) -> 497 | I86: =IFERROR(CashFlow!K10,0) -> 882 | J86: =IFERROR(CashFlow!L10,0) -> 57 | ... L86: =IFERROR(CashFlow!N10,0) -> 2494
B87: Working capital changes | C87: =IFERROR(CashFlow!E11,0) -> 916 | D87: =IFERROR(CashFlow!F11,0) -> -1237 | E87: =IFERROR(CashFlow!G11,0) -> -304 | F87: =IFERROR(CashFlow!H11,0) -> -2272 | G87: =IFERROR(CashFlow!I11,0) -> 2621 | H87: =IFERROR(CashFlow!J11,0) -> -3220 | I87: =IFERROR(CashFlow!K11,0) -> -2413 | J87: =IFERROR(CashFlow!L11,0) -> -2536 | ... L87: =IFERROR(CashFlow!N11,0) -> -1120
B88: Direct taxes | C88: =IFERROR(CashFlow!E12,0) -> -277 | D88: =IFERROR(CashFlow!F12,0) -> -456 | E88: =IFERROR(CashFlow!G12,0) -> -636 | F88: =IFERROR(CashFlow!H12,0) -> -557 | G88: =IFERROR(CashFlow!I12,0) -> -271 | H88: =IFERROR(CashFlow!J12,0) -> -802 | I88: =IFERROR(CashFlow!K12,0) -> -1154 | J88: =IFERROR(CashFlow!L12,0) -> -1173 | ... L88: =IFERROR(CashFlow!N12,0) -> -1737
B89: Cash from Operating Activity | C89: =SUM(C87:C88,C80) -> 1712 | D89: =SUM(D87:D88,D80) -> -51 | E89: =SUM(E87:E88,E80) -> 1243 | F89: =SUM(F87:F88,F80) -> -348 | G89: =SUM(G87:G88,G80) -> 4139 | H89: =SUM(H87:H88,H80) -> -724 | I89: =SUM(I87:I88,I80) -> 1370 | J89: =SUM(J87:J88,J80) -> 1695 | ... L89: =SUM(L87:L88,L80) -> 5590
B91: Cash from Investing Activity -
B92: Fixed assets purchased | C92: =IFERROR(CashFlow!E14,0) -> -256 | D92: =IFERROR(CashFlow!F14,0) -> -305 | E92: =IFERROR(CashFlow!G14,0) -> -265 | F92: =IFERROR(CashFlow!H14,0) -> -355 | G92: =IFERROR(CashFlow!I14,0) -> -146 | H92: =IFERROR(CashFlow!J14,0) -> -224 | I92: =IFERROR(CashFlow!K14,0) -> -432 | J92: =IFERROR(CashFlow!L14,0) -> -691 | ... L92: =IFERROR(CashFlow!N14,0) -> -902
B93: Fixed assets sold | C93: =IFERROR(CashFlow!E15,0) -> 5 | D93: =IFERROR(CashFlow!F15,0) -> 6 | E93: =IFERROR(CashFlow!G15,0) -> 1 | F93: =IFERROR(CashFlow!H15,0) -> 10 | G93: =IFERROR(CashFlow!I15,0) -> 7 | H93: =IFERROR(CashFlow!J15,0) -> 8 | I93: =IFERROR(CashFlow!K15,0) -> 12 | J93: =IFERROR(CashFlow!L15,0) -> 20 | ... L93: =IFERROR(CashFlow!N15,0) -> 25
B94: Investments purchased | C94: =IFERROR(CashFlow!E16,0) -> -325 | D94: =IFERROR(CashFlow!F16,0) -> 0 | E94: =IFERROR(CashFlow!G16,0) -> -36 | F94: =IFERROR(CashFlow!H16,0) -> -13 | G94: =IFERROR(CashFlow!I16,0) -> -2656 | H94: =IFERROR(CashFlow!J16,0) -> -253 | I94: =IFERROR(CashFlow!K16,0) -> -2104 | J94: =IFERROR(CashFlow!L16,0) -> -21893 | ... L94: =IFERROR(CashFlow!N16,0) -> -22035
B95: Investments sold | C95: =IFERROR(CashFlow!E17,0) -> 0 | D95: =IFERROR(CashFlow!F17,0) -> 412 | E95: =IFERROR(CashFlow!G17,0) -> 18 | F95: =IFERROR(CashFlow!H17,0) -> 0 | G95: =IFERROR(CashFlow!I17,0) -> 43 | H95: =IFERROR(CashFlow!J17,0) -> 2870 | I95: =IFERROR(CashFlow!K17,0) -> 0 | J95: =IFERROR(CashFlow!L17,0) -> 22213 | ... L95: =IFERROR(CashFlow!N17,0) -> 20797
B96: Interest received | C96: =IFERROR(CashFlow!E18,0) -> 41 | D96: =IFERROR(CashFlow!F18,0) -> 64 | E96: =IFERROR(CashFlow!G18,0) -> 85 | F96: =IFERROR(CashFlow!H18,0) -> 73 | G96: =IFERROR(CashFlow!I18,0) -> 49 | H96: =IFERROR(CashFlow!J18,0) -> 56 | I96: =IFERROR(CashFlow!K18,0) -> 143 | J96: =IFERROR(CashFlow!L18,0) -> 249 | ... L96: =IFERROR(CashFlow!N18,0) -> 227
B97: Invest in subsidiaries | C97: =IFERROR(CashFlow!E19,0) -> 0 | D97: =IFERROR(CashFlow!F19,0) -> 0 | E97: =IFERROR(CashFlow!G19,0) -> 0 | F97: =IFERROR(CashFlow!H19,0) -> -39 | G97: =IFERROR(CashFlow!I19,0) -> 0 | H97: =IFERROR(CashFlow!J19,0) -> 0 | I97: =IFERROR(CashFlow!K19,0) -> 0 | J97: =IFERROR(CashFlow!L19,0) -> 0 | ... L97: =IFERROR(CashFlow!N19,0) -> 0
B98: Investment in group cos | C98: =IFERROR(CashFlow!E20,0) -> 0 | D98: =IFERROR(CashFlow!F20,0) -> 0 | E98: =IFERROR(CashFlow!G20,0) -> 0 | F98: =IFERROR(CashFlow!H20,0) -> 0 | G98: =IFERROR(CashFlow!I20,0) -> 0 | H98: =IFERROR(CashFlow!J20,0) -> 0 | I98: =IFERROR(CashFlow!K20,0) -> 0 | J98: =IFERROR(CashFlow!L20,0) -> 0 | ... L98: =IFERROR(CashFlow!N20,0) -> 0
B99: Acquisition of companies | C99: =IFERROR(CashFlow!E21,0) -> -385 | D99: =IFERROR(CashFlow!F21,0) -> 0 | E99: =IFERROR(CashFlow!G21,0) -> 0 | F99: =IFERROR(CashFlow!H21,0) -> 0 | G99: =IFERROR(CashFlow!I21,0) -> 0 | H99: =IFERROR(CashFlow!J21,0) -> 0 | I99: =IFERROR(CashFlow!K21,0) -> 0 | J99: =IFERROR(CashFlow!L21,0) -> 0 | ... L99: =IFERROR(CashFlow!N21,0) -> 0
B100: Inter corporate deposits | C100: =IFERROR(CashFlow!E22,0) -> 5 | D100: =IFERROR(CashFlow!F22,0) -> -35 | E100: =IFERROR(CashFlow!G22,0) -> -115 | F100: =IFERROR(CashFlow!H22,0) -> 200 | G100: =IFERROR(CashFlow!I22,0) -> -50 | H100: =IFERROR(CashFlow!J22,0) -> -344 | I100: =IFERROR(CashFlow!K22,0) -> 294 | J100: =IFERROR(CashFlow!L22,0) -> -143 | ... L100: =IFERROR(CashFlow!N22,0) -> 0
B101: Other investing items | C101: =IFERROR(CashFlow!E23,0) -> -38 | D101: =IFERROR(CashFlow!F23,0) -> -43 | E101: =IFERROR(CashFlow!G23,0) -> -485 | F101: =IFERROR(CashFlow!H23,0) -> 359 | G101: =IFERROR(CashFlow!I23,0) -> -46 | H101: =IFERROR(CashFlow!J23,0) -> -948 | I101: =IFERROR(CashFlow!K23,0) -> 273 | J101: =IFERROR(CashFlow!L23,0) -> 56 | ... L101: =IFERROR(CashFlow!N23,0) -> -1077
B102: Cash from Investing Activity | C102: =SUM(C92:C101) -> -953 | D102: =SUM(D92:D101) -> 99 | E102: =SUM(E92:E101) -> -797 | F102: =SUM(F92:F101) -> 235 | G102: =SUM(G92:G101) -> -2799 | H102: =SUM(H92:H101) -> 1165 | I102: =SUM(I92:I101) -> -1814 | J102: =SUM(J92:J101) -> -189 | ... L102: =SUM(L92:L101) -> -2965
B104: Cash from Financing Activity -
B105: Proceeds from borrowings | C105: =IFERROR(CashFlow!E25,0) -> 0 | D105: =IFERROR(CashFlow!F25,0) -> 0 | E105: =IFERROR(CashFlow!G25,0) -> 0 | F105: =IFERROR(CashFlow!H25,0) -> 693 | G105: =IFERROR(CashFlow!I25,0) -> 0 | H105: =IFERROR(CashFlow!J25,0) -> 349 | I105: =IFERROR(CashFlow!K25,0) -> 1684 | J105: =IFERROR(CashFlow!L25,0) -> 5629 | ... L105: =IFERROR(CashFlow!N25,0) -> 3314
B106: Repayment of borrowings | C106: =IFERROR(CashFlow!E26,0) -> 0 | D106: =IFERROR(CashFlow!F26,0) -> 0 | E106: =IFERROR(CashFlow!G26,0) -> -39 | F106: =IFERROR(CashFlow!H26,0) -> 0 | G106: =IFERROR(CashFlow!I26,0) -> -562 | H106: =IFERROR(CashFlow!J26,0) -> -7 | I106: =IFERROR(CashFlow!K26,0) -> -7 | J106: =IFERROR(CashFlow!L26,0) -> 0 | ... L106: =IFERROR(CashFlow!N26,0) -> -2632
B107: Interest paid fin | C107: =IFERROR(CashFlow!E27,0) -> -38 | D107: =IFERROR(CashFlow!F27,0) -> -54 | E107: =IFERROR(CashFlow!G27,0) -> -53 | F107: =IFERROR(CashFlow!H27,0) -> -399 | G107: =IFERROR(CashFlow!I27,0) -> -317 | H107: =IFERROR(CashFlow!J27,0) -> -218 | I107: =IFERROR(CashFlow!K27,0) -> -300 | J107: =IFERROR(CashFlow!L27,0) -> -619 | ... L107: =IFERROR(CashFlow!N27,0) -> -1000
B108: Dividends paid | C108: =IFERROR(CashFlow!E28,0) -> -4 | D108: =IFERROR(CashFlow!F28,0) -> -277 | E108: =IFERROR(CashFlow!G28,0) -> -397 | F108: =IFERROR(CashFlow!H28,0) -> -536 | G108: =IFERROR(CashFlow!I28,0) -> -355 | H108: =IFERROR(CashFlow!J28,0) -> -355 | I108: =IFERROR(CashFlow!K28,0) -> -666 | J108: =IFERROR(CashFlow!L28,0) -> -888 | ... L108: =IFERROR(CashFlow!N28,0) -> -976
B109: Financial liabilities | C109: =IFERROR(CashFlow!E29,0) -> 0 | D109: =IFERROR(CashFlow!F29,0) -> 0 | E109: =IFERROR(CashFlow!G29,0) -> 0 | F109: =IFERROR(CashFlow!H29,0) -> 0 | G109: =IFERROR(CashFlow!I29,0) -> 0 | H109: =IFERROR(CashFlow!J29,0) -> -172 | I109: =IFERROR(CashFlow!K29,0) -> -254 | J109: =IFERROR(CashFlow!L29,0) -> -318 | ... L109: =IFERROR(CashFlow!N29,0) -> -865
B110: Other financing items | C110: =IFERROR(CashFlow!E30,0) -> -124 | D110: =IFERROR(CashFlow!F30,0) -> 79 | E110: =IFERROR(CashFlow!G30,0) -> 0 | F110: =IFERROR(CashFlow!H30,0) -> 0 | G110: =IFERROR(CashFlow!I30,0) -> 0 | H110: =IFERROR(CashFlow!J30,0) -> 0 | I110: =IFERROR(CashFlow!K30,0) -> 0 | J110: =IFERROR(CashFlow!L30,0) -> -5133 | ... L110: =IFERROR(CashFlow!N30,0) -> 0
B111: Cash from Financing Activity | C111: =SUM(C105:C110) -> -166 | D111: =SUM(D105:D110) -> -252 | E111: =SUM(E105:E110) -> -489 | F111: =SUM(F105:F110) -> -242 | G111: =SUM(G105:G110) -> -1234 | H111: =SUM(H105:H110) -> -403 | I111: =SUM(I105:I110) -> 457 | J111: =SUM(J105:J110) -> -1329 | ... L111: =SUM(L105:L110) -> -2159
B113: Net Cash Flow | C113: =SUM(C111,C102,C89) -> 593 | D113: =SUM(D111,D102,D89) -> -204 | E113: =SUM(E111,E102,E89) -> -43 | F113: =SUM(F111,F102,F89) -> -355 | G113: =SUM(G111,G102,G89) -> 106 | H113: =SUM(H111,H102,H89) -> 38 | I113: =SUM(I111,I102,I89) -> 13 | J113: =SUM(J111,J102,J89) -> 177 | ... L113: =SUM(L111,L102,L89) -> 466

Sheet Ratio Analysis
B2: ="Ratio Analysis"&" - " &'Data Sheet'!B1 -> Ratio Analysis - TITAN COMPANY LTD
B3: Years | C3: =HistoricalFS!C5 -> 42825 | D3: =HistoricalFS!D5 -> 43190 | E3: =HistoricalFS!E5 -> 43555 | F3: =HistoricalFS!F5 -> 43921 | G3: =HistoricalFS!G5 -> 44286 | H3: =HistoricalFS!H5 -> 44651 | I3: =HistoricalFS!I5 -> 45016 | J3: =HistoricalFS!J5 -> 45382 | ... L3: =HistoricalFS!L5 -> 46112 | M3: Trend Line | N3: Average | O3: Median
B5: Sales Growth | D5: =HistoricalFS!D10 -> 0.21559284 | E5: =HistoricalFS!E10 -> 0.22697284 | F5: =HistoricalFS!F10 -> 0.064387022 | G5: =HistoricalFS!G10 -> 0.028120844 | H5: =HistoricalFS!H10 -> 0.3305766 | I5: =HistoricalFS!I10 -> 0.40890309 | J5: =HistoricalFS!J10 -> 0.25900185 | K5: =HistoricalFS!K10 -> 0.18346253 | L5: =HistoricalFS!L10 -> 0.44872304 | N5: =AVERAGE(D5:L5) -> 0.24063785 | O5: =MEDIAN(D5:L5) -> 0.22697284
B6: EBITDA Growth | D6: =HistoricalFS!D21/HistoricalFS!C21-1 -> 0.41266432 | E6: =HistoricalFS!E21/HistoricalFS!D21-1 -> 0.21262012 | F6: =HistoricalFS!F21/HistoricalFS!E21-1 -> 0.23533572 | G6: =HistoricalFS!G21/HistoricalFS!F21-1 -> -0.29963459 | H6: =HistoricalFS!H21/HistoricalFS!G21-1 -> 0.93855072 | I6: =HistoricalFS!I21/HistoricalFS!H21-1 -> 0.45992823 | J6: =HistoricalFS!J21/HistoricalFS!I21-1 -> 0.083981975 | K6: =HistoricalFS!K21/HistoricalFS!J21-1 -> 0.075963719 | L6: =HistoricalFS!L21/HistoricalFS!K21-1 -> 0.46768528 | N6: =AVERAGE(D6:L6) -> 0.28745505 | O6: =MEDIAN(D6:L6) -> 0.23533572
B7: EBIT Growth | D7: =HistoricalFS!D30/HistoricalFS!C30-1 -> 0.56549521 | E7: =HistoricalFS!E30/HistoricalFS!D30-1 -> 0.26962153 | F7: =HistoricalFS!F30/HistoricalFS!E30-1 -> 0.12867828 | G7: =HistoricalFS!G30/HistoricalFS!F30-1 -> -0.32539683 | H7: =HistoricalFS!H30/HistoricalFS!G30-1 -> 1.0405229 | I7: =HistoricalFS!I30/HistoricalFS!H30-1 -> 0.52049968 | J7: =HistoricalFS!J30/HistoricalFS!I30-1 -> 0.10427639 | K7: =HistoricalFS!K30/HistoricalFS!J30-1 -> 0.046928653 | L7: =HistoricalFS!L30/HistoricalFS!K30-1 -> 0.45426385 | N7: =AVERAGE(D7:L7) -> 0.3116544 | O7: =MEDIAN(D7:L7) -> 0.26962153
B8: Net Profit Growth | D8: =HistoricalFS!D42/HistoricalFS!C42-1 -> 0.58029773 | E8: =HistoricalFS!E42/HistoricalFS!D42-1 -> 0.26022089 | F8: =HistoricalFS!F42/HistoricalFS!E42-1 -> 0.075144925 | G8: =HistoricalFS!G42/HistoricalFS!F42-1 -> -0.34762224 | H8: =HistoricalFS!H42/HistoricalFS!G42-1 -> 1.2566735 | I8: =HistoricalFS!I42/HistoricalFS!H42-1 -> 0.48953594 | J8: =HistoricalFS!J42/HistoricalFS!I42-1 -> 0.067806964 | K8: =HistoricalFS!K42/HistoricalFS!J42-1 -> -0.045480549 | L8: =HistoricalFS!L42/HistoricalFS!K42-1 -> 0.52022775 | N8: =AVERAGE(D8:L8) -> 0.31742277 | O8: =MEDIAN(D8:L8) -> 0.26022089
B9: Dividend Growth | D9: =HistoricalFS!D50/HistoricalFS!C50-1 -> 0.44227353 | E9: =HistoricalFS!E50/HistoricalFS!D50-1 -> 0.33335336 | F9: =HistoricalFS!F50/HistoricalFS!E50-1 -> -0.19801757 | G9: =HistoricalFS!G50/HistoricalFS!F50-1 -> 0 | H9: =HistoricalFS!H50/HistoricalFS!G50-1 -> 0.875 | I9: =HistoricalFS!I50/HistoricalFS!H50-1 -> 0.33333333 | J9: =HistoricalFS!J50/HistoricalFS!I50-1 -> 0.1 | K9: =HistoricalFS!K50/HistoricalFS!J50-1 -> 0 | L9: =HistoricalFS!L50/HistoricalFS!K50-1 -> 0.36363636 | N9: =AVERAGE(D9:L9) -> 0.24995322 | O9: =MEDIAN(D9:L9) -> 0.33333333
B11: Gross Margins | C11: =HistoricalFS!C16 -> 0.20020014 | D11: =HistoricalFS!D16 -> 0.20826228 | E11: =HistoricalFS!E16 -> 0.20820769 | F11: =HistoricalFS!F16 -> 0.21024131 | G11: =HistoricalFS!G16 -> 0.18402329 | H11: =HistoricalFS!H16 -> 0.19354839 | I11: =HistoricalFS!I16 -> 0.20406654 | J11: =HistoricalFS!J16 -> 0.18440216 | ... L11: =HistoricalFS!L16 -> 0.16125091 | N11: =AVERAGE(C11:L11) -> 0.1926758 | O11: =MEDIAN(C11:L11) -> 0.19687426
B12: EBITDA Margins | C12: =HistoricalFS!C22 -> 0.08776977 | D12: =HistoricalFS!D22 -> 0.10199897 | E12: =HistoricalFS!E22 -> 0.10080582 | F12: =HistoricalFS!F22 -> 0.11699601 | G12: =HistoricalFS!G22 -> 0.079698762 | H12: =HistoricalFS!H22 -> 0.11611514 | I12: =HistoricalFS!I22 -> 0.12032039 | J12: =HistoricalFS!J22 -> 0.10359408 | ... L12: =HistoricalFS!L22 -> 0.095416971 | N12: =AVERAGE(C12:L12) -> 0.10169001 | O12: =MEDIAN(C12:L12) -> 0.1014024
B13: EBIT Margins | C13: =HistoricalFS!C31 -> 0.076238818 | D13: =HistoricalFS!D31 -> 0.098183783 | E13: =HistoricalFS!E31 -> 0.10159658 | F13: =HistoricalFS!F31 -> 0.10773323 | G13: =HistoricalFS!G31 -> 0.070689337 | H13: =HistoricalFS!H31 -> 0.10840654 | I13: =HistoricalFS!I31 -> 0.11699322 | J13: =HistoricalFS!J31 -> 0.1026153 | ... L13: =HistoricalFS!L31 -> 0.09112395 | N13: =AVERAGE(C13:L13) -> 0.096435753 | O13: =MEDIAN(C13:L13) -> 0.099890182
B14: EBT Margins | C14: =HistoricalFS!C37 -> 0.073392842 | D14: =HistoricalFS!D37 -> 0.094900858 | E14: =HistoricalFS!E37 -> 0.098940163 | F14: =HistoricalFS!F37 -> 0.099847995 | G14: =HistoricalFS!G37 -> 0.061310294 | H14: =HistoricalFS!H37 -> 0.10083683 | I14: =HistoricalFS!I37 -> 0.10959951 | J14: =HistoricalFS!J37 -> 0.090498003 | ... L14: =HistoricalFS!L37 -> 0.077651169 | N14: =AVERAGE(C14:L14) -> 0.08819909 | O14: =MEDIAN(C14:L14) -> 0.092699431
B15: Net Profit Margins | C15: =HistoricalFS!C43 -> 0.052581927 | D15: =HistoricalFS!D43 -> 0.068357675 | E15: =HistoricalFS!E43 -> 0.070210006 | F15: =HistoricalFS!F43 -> 0.070919628 | G15: =HistoricalFS!G43 -> 0.045000924 | H15: =HistoricalFS!H43 -> 0.076322095 | I15: =HistoricalFS!I43 -> 0.08069008 | J15: =HistoricalFS!J43 -> 0.068436301 | ... L15: =HistoricalFS!L43 -> 0.057921538 | N15: =AVERAGE(C15:L15) -> 0.064563734 | O15: =MEDIAN(C15:L15) -> 0.068396988
B17: S&E % of Sales | C17: =HistoricalFS!C19 -> 0.11243037 | D17: =HistoricalFS!D19 -> 0.1062633 | E17: =HistoricalFS!E19 -> 0.10740187 | F17: =HistoricalFS!F19 -> 0.093245297 | G17: =HistoricalFS!G19 -> 0.10432452 | H17: =HistoricalFS!H19 -> 0.077433244 | I17: =HistoricalFS!I19 -> 0.083746149 | J17: =HistoricalFS!J19 -> 0.080808081 | ... L17: =HistoricalFS!L19 -> 0.065833942 | N17: =AVERAGE(C17:L17) -> 0.090985782 | O17: =MEDIAN(C17:L17) -> 0.088495723
B18: Depreciation % of Sales | C18: =HistoricalFS!C28 -> 0.008335074 | D18: =HistoricalFS!D28 -> 0.0081533421 | E18: =HistoricalFS!E28 -> 0.0082331742 | F18: =HistoricalFS!F28 -> 0.016530496 | G18: =HistoricalFS!G28 -> 0.017325818 | H18: =HistoricalFS!H28 -> 0.013854648 | I18: =HistoricalFS!I28 -> 0.010868762 | J18: =HistoricalFS!J28 -> 0.011432151 | ... L18: =HistoricalFS!L28 -> 0.0094309463 | N18: =AVERAGE(C18:L18) -> 0.011562729 | O18: =MEDIAN(C18:L18) -> 0.011150456
B19: Operating Income % of Sales | C19: =C13 -> 0.076238818 | D19: =D13 -> 0.098183783 | E19: =E13 -> 0.10159658 | F19: =F13 -> 0.10773323 | G19: =G13 -> 0.070689337 | H19: =H13 -> 0.10840654 | I19: =I13 -> 0.11699322 | J19: =J13 -> 0.1026153 | ... L19: =L13 -> 0.09112395 | N19: =AVERAGE(C19:L19) -> 0.096435753 | O19: =MEDIAN(C19:L19) -> 0.099890182
B21: Return on capital employed | C21: =HistoricalFS!C30/SUM(HistoricalFS!C56:C58) -> 0.16533465 | D21: =HistoricalFS!D30/SUM(HistoricalFS!D56:D58) -> 0.23340594 | E21: =HistoricalFS!E30/SUM(HistoricalFS!E56:E58) -> 0.23743343 | F21: =HistoricalFS!F30/SUM(HistoricalFS!F56:F58) -> 0.22167921 | G21: =HistoricalFS!G30/SUM(HistoricalFS!G56:G58) -> 0.11648268 | H21: =HistoricalFS!H30/SUM(HistoricalFS!H56:H58) -> 0.18832187 | I21: =HistoricalFS!I30/SUM(HistoricalFS!I56:I58) -> 0.22372514 | J21: =HistoricalFS!J30/SUM(HistoricalFS!J56:J58) -> 0.21034469 | ... L21: =HistoricalFS!L30/SUM(HistoricalFS!L56:L58) -> 0.1722865 | N21: =AVERAGE(C21:L21) -> 0.19383916 | O21: =MEDIAN(C21:L21) -> 0.19933328
B22: Return on Equity % | C22: =HistoricalFS!C42/SUM(HistoricalFS!C56:C57) -> 0.16474891 | D22: =HistoricalFS!D42/SUM(HistoricalFS!D56:D57) -> 0.21649037 | E22: =HistoricalFS!E42/SUM(HistoricalFS!E56:E57) -> 0.228767 | F22: =HistoricalFS!F42/SUM(HistoricalFS!F56:F57) -> 0.22387164 | G22: =HistoricalFS!G42/SUM(HistoricalFS!G56:G57) -> 0.12991863 | H22: =HistoricalFS!H42/SUM(HistoricalFS!H56:H57) -> 0.23626787 | I22: =HistoricalFS!I42/SUM(HistoricalFS!I56:I57) -> 0.27626361 | J22: =HistoricalFS!J42/SUM(HistoricalFS!J56:J57) -> 0.37219206 | ... L22: =HistoricalFS!L42/SUM(HistoricalFS!L56:L57) -> 0.32305929 | N22: =AVERAGE(C22:L22) -> 0.24586578 | O22: =MEDIAN(C22:L22) -> 0.23251743
B23: Retained Earnings % | C23: =HistoricalFS!C53 -> 0.66895652 | D23: =HistoricalFS!D53 -> 0.69787006 | E23: =HistoricalFS!E53 -> 0.68033702 | F23: =HistoricalFS!F53 -> 0.76155392 | G23: =HistoricalFS!G53 -> 0.63449692 | H23: =HistoricalFS!H53 -> 0.69631483 | I23: =HistoricalFS!I53 -> 0.72816127 | J23: =HistoricalFS!J53 -> 0.71996568 | ... L23: =HistoricalFS!L53 -> 0.73684211 | N23: =AVERAGE(C23:L23) -> 0.7031121 | O23: =MEDIAN(C23:L23) -> 0.70224639
B24: Self Sustained Growth Rate | C24: =C22*C23 -> 0.11020986 | D24: =D22*D23 -> 0.15108215 | E24: =E22*E23 -> 0.15563866 | F24: =F22*F23 -> 0.17049033 | G24: =G22*G23 -> 0.082432973 | H24: =H22*H23 -> 0.16451682 | I24: =I22*I23 -> 0.20116446 | J24: =J22*J23 -> 0.26796551 | ... L24: =L22*L23 -> 0.23804369 | N24: =AVERAGE(C24:L24) -> 0.17444006 | O24: =MEDIAN(C24:L24) -> 0.16750358
B25: Interest Coverage Ratio | C25: =HistoricalFS!C30/HistoricalFS!C33 -> 26.788288 | D25: =HistoricalFS!D30/HistoricalFS!D33 -> 29.907407 | E25: =HistoricalFS!E30/HistoricalFS!E33 -> 38.245718 | F25: =HistoricalFS!F30/HistoricalFS!F33 -> 13.662651 | G25: =HistoricalFS!G30/HistoricalFS!G33 -> 7.5369458 | H25: =HistoricalFS!H30/HistoricalFS!H33 -> 14.321101 | I25: =HistoricalFS!I30/HistoricalFS!I33 -> 15.823333 | J25: =HistoricalFS!J30/HistoricalFS!J33 -> 8.4684976 | ... L25: =HistoricalFS!L30/HistoricalFS!L33 -> 6.7635593 | N25: =AVERAGE(C25:L25) -> 16.727616 | O25: =MEDIAN(C25:L25) -> 13.991876
B27: Debtor Turnover Ratio | C27: =HistoricalFS!C9/HistoricalFS!C69 -> 63.87683 | D27: =HistoricalFS!D9/HistoricalFS!D69 -> 54.515777 | E27: =HistoricalFS!E9/HistoricalFS!E69 -> 47.041313 | F27: =HistoricalFS!F9/HistoricalFS!F69 -> 67.474359 | G27: =HistoricalFS!G9/HistoricalFS!G69 -> 59.136612 | H27: =HistoricalFS!H9/HistoricalFS!H69 -> 50.971681 | I27: =HistoricalFS!I9/HistoricalFS!I69 -> 60.200297 | J27: =HistoricalFS!J9/HistoricalFS!J69 -> 50.180747 | ... L27: =HistoricalFS!L9/HistoricalFS!L69 -> 95.615721 | N27: =AVERAGE(C27:L27) -> 60.562008 | O27: =MEDIAN(C27:L27) -> 57.871677
B28: Creditor Turnover Ratio | C28: =HistoricalFS!C12/HistoricalFS!C59 -> 13.545351 | D28: =HistoricalFS!D12/HistoricalFS!D59 -> 14.536025 | E28: =HistoricalFS!E12/HistoricalFS!E59 -> 17.285298 | F28: =HistoricalFS!F12/HistoricalFS!F59 -> 27.895973 | G28: =HistoricalFS!G12/HistoricalFS!G59 -> 22.38403 | H28: =HistoricalFS!H12/HistoricalFS!H59 -> 17.948223 | I28: =HistoricalFS!I12/HistoricalFS!I59 -> 26.602142 | J28: =HistoricalFS!J12/HistoricalFS!J59 -> 29.548936 | ... L28: =HistoricalFS!L12/HistoricalFS!L59 -> 25.649791 | N28: =AVERAGE(C28:L28) -> 22.087921 | O28: =MEDIAN(C28:L28) -> 23.933737
B29: Inventory Turnover Ratio | C29: =HistoricalFS!C12/HistoricalFS!C70 -> 2.153181 | D29: =HistoricalFS!D12/HistoricalFS!D70 -> 2.1540885 | E29: =HistoricalFS!E12/HistoricalFS!E70 -> 2.2248729 | F29: =HistoricalFS!F12/HistoricalFS!F70 -> 2.0518327 | G29: =HistoricalFS!G12/HistoricalFS!G70 -> 2.1004995 | H29: =HistoricalFS!H12/HistoricalFS!H70 -> 1.7065912 | I29: =HistoricalFS!I12/HistoricalFS!I70 -> 1.9473589 | J29: =HistoricalFS!J12/HistoricalFS!J70 -> 2.1869718 | ... L29: =HistoricalFS!L12/HistoricalFS!L70 -> 1.7186674 | N29: =AVERAGE(C29:L29) -> 2.0018972 | O29: =MEDIAN(C29:L29) -> 2.0761661
B30: Fixed Asset Turnover Ratio | C30: =HistoricalFS!C9/HistoricalFS!C63 -> 11.155554 | D30: =HistoricalFS!D9/HistoricalFS!D63 -> 10.937482 | E30: =HistoricalFS!E9/HistoricalFS!E63 -> 12.624883 | F30: =HistoricalFS!F9/HistoricalFS!F63 -> 7.9954425 | G30: =HistoricalFS!G9/HistoricalFS!G63 -> 8.5786762 | H30: =HistoricalFS!H9/HistoricalFS!H63 -> 11.320362 | I30: =HistoricalFS!I9/HistoricalFS!I63 -> 13.534023 | J30: =HistoricalFS!J9/HistoricalFS!J63 -> 13.772985 | ... L30: =HistoricalFS!L9/HistoricalFS!L63 -> 12.733934 | N30: =AVERAGE(C30:L30) -> 11.753665 | O30: =MEDIAN(C30:L30) -> 11.972622
B31: Capital Turnover Ratio | C31: =HistoricalFS!C9/SUM(HistoricalFS!C56:C58) -> 2.1686414 | D31: =HistoricalFS!D9/SUM(HistoricalFS!D56:D58) -> 2.3772351 | E31: =HistoricalFS!E9/SUM(HistoricalFS!E56:E58) -> 2.3370219 | F31: =HistoricalFS!F9/SUM(HistoricalFS!F56:F58) -> 2.0576679 | G31: =HistoricalFS!G9/SUM(HistoricalFS!G56:G58) -> 1.6478112 | H31: =HistoricalFS!H9/SUM(HistoricalFS!H56:H58) -> 1.7371818 | I31: =HistoricalFS!I9/SUM(HistoricalFS!I56:I58) -> 1.9122915 | J31: =HistoricalFS!J9/SUM(HistoricalFS!J56:J58) -> 2.0498375 | ... L31: =HistoricalFS!L9/SUM(HistoricalFS!L56:L58) -> 1.890683 | N31: =AVERAGE(C31:L31) -> 2.004424 | O31: =MEDIAN(C31:L31) -> 1.9810645
B32: In Days
B33: Debtor Days | C33: =365/C27 -> 5.714122 | D33: =365/D27 -> 6.6953095 | E33: =365/E27 -> 7.7591372 | F33: =365/F27 -> 5.4094623 | G33: =365/G27 -> 6.1721493 | H33: =365/H27 -> 7.1608389 | I33: =365/I27 -> 6.063093 | J33: =365/J27 -> 7.2737061 | ... L33: =365/L27 -> 3.8173639 | N33: =AVERAGE(C33:L33) -> 6.2513177 | O33: =MEDIAN(C33:L33) -> 6.3100723
B34: Creditor Days | C34: =365/C28 -> 26.946514 | D34: =365/D28 -> 25.110028 | E34: =365/E28 -> 21.116211 | F34: =365/F28 -> 13.084326 | G34: =365/G28 -> 16.306268 | H34: =365/H28 -> 20.336276 | I34: =365/I28 -> 13.7207 | J34: =365/J28 -> 12.352391 | ... L34: =365/L28 -> 14.230136 | N34: =AVERAGE(C34:L34) -> 17.752587 | O34: =MEDIAN(C34:L34) -> 15.314646
B35: Inventory Days | C35: =365/C29 -> 169.51663 | D35: =365/D29 -> 169.44522 | E35: =365/E29 -> 164.05431 | F35: =365/F29 -> 177.88975 | G35: =365/G29 -> 173.76819 | H35: =365/H29 -> 213.87664 | I35: =365/I29 -> 187.43335 | J35: =365/J29 -> 166.89744 | ... L35: =365/L29 -> 212.37384 | N35: =AVERAGE(C35:L35) -> 184.08999 | O35: =MEDIAN(C35:L35) -> 175.82897
B36: Cash Conversion Cycle | C36: =SUM(C33,C35)-C34 -> 148.28424 | D36: =SUM(D33,D35)-D34 -> 151.0305 | E36: =SUM(E33,E35)-E34 -> 150.69724 | F36: =SUM(F33,F35)-F34 -> 170.21489 | G36: =SUM(G33,G35)-G34 -> 163.63407 | H36: =SUM(H33,H35)-H34 -> 200.7012 | I36: =SUM(I33,I35)-I34 -> 179.77574 | J36: =SUM(J33,J35)-J34 -> 161.81876 | ... L36: =SUM(L33,L35)-L34 -> 201.96107 | N36: =AVERAGE(C36:L36) -> 172.58872 | O36: =MEDIAN(C36:L36) -> 166.92448
B38: CFO/Sales | C38: =HistoricalFS!C89/HistoricalFS!C9 -> 0.12910202 | D38: =HistoricalFS!D89/HistoricalFS!D9 -> -0.0031638169 | E38: =HistoricalFS!E89/HistoricalFS!E9 -> 0.062845956 | F38: =HistoricalFS!F89/HistoricalFS!F9 -> -0.016530496 | G38: =HistoricalFS!G89/HistoricalFS!G9 -> 0.19123083 | H38: =HistoricalFS!H89/HistoricalFS!H9 -> -0.025139762 | I38: =HistoricalFS!I89/HistoricalFS!I9 -> 0.033764633 | J38: =HistoricalFS!J89/HistoricalFS!J9 -> 0.033180644 | ... L38: =HistoricalFS!L89/HistoricalFS!L9 -> 0.063824443 | N38: =AVERAGE(C38:L38) -> 0.04601658 | O38: =MEDIAN(C38:L38) -> 0.033472639
B39: CFO/Total Assets | C39: =HistoricalFS!C89/HistoricalFS!C74 -> 0.20362602 | D39: =HistoricalFS!D89/HistoricalFS!D74 -> -0.0053565577 | E39: =HistoricalFS!E89/HistoricalFS!E74 -> 0.10615004 | F39: =HistoricalFS!F89/HistoricalFS!F74 -> -0.025694034 | G39: =HistoricalFS!G89/HistoricalFS!G74 -> 0.25170275 | H39: =HistoricalFS!H89/HistoricalFS!H74 -> -0.034170285 | I39: =HistoricalFS!I89/HistoricalFS!I74 -> 0.050703183 | J39: =HistoricalFS!J89/HistoricalFS!J74 -> 0.053729356 | ... L39: =HistoricalFS!L89/HistoricalFS!L74 -> 0.092303628 | N39: =AVERAGE(C39:L39) -> 0.067968373 | O39: =MEDIAN(C39:L39) -> 0.05221627
B40: CFO/Total Debt | C40: =HistoricalFS!C89/HistoricalFS!C58 -> 0.90946277 | D40: =HistoricalFS!D89/HistoricalFS!D58 -> -0.03015949 | E40: =HistoricalFS!E89/HistoricalFS!E58 -> 0.51943602 | F40: =HistoricalFS!F89/HistoricalFS!F58 -> -0.097697923 | G40: =HistoricalFS!G89/HistoricalFS!G58 -> 0.73412558 | H40: =HistoricalFS!H89/HistoricalFS!H58 -> -0.0995189 | I40: =HistoricalFS!I89/HistoricalFS!I58 -> 0.14625814 | J40: =HistoricalFS!J89/HistoricalFS!J58 -> 0.10915765 | ... L40: =HistoricalFS!L89/HistoricalFS!L58 -> 0.18255446 | N40: =AVERAGE(C40:L40) -> 0.23475799 | O40: =MEDIAN(C40:L40) -> 0.1277079

Sheet Common Size Statement
B2: ="Common Size Income Statement"&" - "&'Data Sheet'!B1 -> Common Size Income Statement - TITAN COMPANY LTD
B4: Pariculars | C4: ='Data Sheet'!B16 -> 42825 | D4: ='Data Sheet'!C16 -> 43190 | E4: ='Data Sheet'!D16 -> 43555 | F4: ='Data Sheet'!E16 -> 43921 | G4: ='Data Sheet'!F16 -> 44286 | H4: ='Data Sheet'!G16 -> 44651 | I4: ='Data Sheet'!H16 -> 45016 | J4: ='Data Sheet'!I16 -> 45382 | ... L4: ='Data Sheet'!K16 -> 46112
B6: ='Data Sheet'!A17 -> Sales | C6: ='Data Sheet'!B17/'Data Sheet'!B17 -> 1 | D6: ='Data Sheet'!C17/'Data Sheet'!C17 -> 1 | E6: ='Data Sheet'!D17/'Data Sheet'!D17 -> 1 | F6: ='Data Sheet'!E17/'Data Sheet'!E17 -> 1 | G6: ='Data Sheet'!F17/'Data Sheet'!F17 -> 1 | H6: ='Data Sheet'!G17/'Data Sheet'!G17 -> 1 | I6: ='Data Sheet'!H17/'Data Sheet'!H17 -> 1 | J6: ='Data Sheet'!I17/'Data Sheet'!I17 -> 1 | ... L6: ='Data Sheet'!K17/'Data Sheet'!K17 -> 1
B7: ='Data Sheet'!A18 -> Raw Material Cost | C7: ='Data Sheet'!B18/'Data Sheet'!B$17 -> 0.74061277 | D7: ='Data Sheet'!C18/'Data Sheet'!C$17 -> 0.78567064 | E7: ='Data Sheet'!D18/'Data Sheet'!D$17 -> 0.76702706 | F7: ='Data Sheet'!E18/'Data Sheet'!E$17 -> 0.76159035 | G7: ='Data Sheet'!F18/'Data Sheet'!F$17 -> 0.75272593 | H7: ='Data Sheet'!G18/'Data Sheet'!G$17 -> 0.91794854 | I7: ='Data Sheet'!H18/'Data Sheet'!H$17 -> 0.8031793 | J7: ='Data Sheet'!I18/'Data Sheet'!I$17 -> 0.82419153 | ... L7: ='Data Sheet'!K18/'Data Sheet'!K$17 -> 0.91618332
B8: ='Data Sheet'!A19 -> Change in Inventory | C8: ='Data Sheet'!B19/'Data Sheet'!B$17 -> 0.02365689 | D8: ='Data Sheet'!C19/'Data Sheet'!C$17 -> 0.060708683 | E8: ='Data Sheet'!D19/'Data Sheet'!D$17 -> 0.039255212 | F8: ='Data Sheet'!E19/'Data Sheet'!E$17 -> 0.041706251 | G8: ='Data Sheet'!F19/'Data Sheet'!F$17 -> -0.0056366661 | H8: ='Data Sheet'!G19/'Data Sheet'!G$17 -> 0.16649884 | I8: ='Data Sheet'!H19/'Data Sheet'!H$17 -> 0.055058534 | J8: ='Data Sheet'!I19/'Data Sheet'!I$17 -> 0.05228643 | ... L8: ='Data Sheet'!K19/'Data Sheet'!K$17 -> 0.11344538
B9: ='Data Sheet'!A20 -> Power and Fuel | C9: ='Data Sheet'!B20/'Data Sheet'!B$17 -> 0.0033059771 | D9: ='Data Sheet'!C20/'Data Sheet'!C$17 -> 0.0028114545 | E9: ='Data Sheet'!D20/'Data Sheet'!D$17 -> 0.0024526608 | F9: ='Data Sheet'!E20/'Data Sheet'!E$17 -> 0.0024700741 | G9: ='Data Sheet'!F20/'Data Sheet'!F$17 -> 0.0017094807 | H9: ='Data Sheet'!G20/'Data Sheet'!G$17 -> 0.0015625543 | I9: ='Data Sheet'!H20/'Data Sheet'!H$17 -> 0.0014540974 | J9: ='Data Sheet'!I20/'Data Sheet'!I$17 -> 0.0013898677 | ... L9: ='Data Sheet'!K20/'Data Sheet'!K$17 -> 0.00099333212
B10: ='Data Sheet'!A21 -> Other Mfr. Exp | C10: ='Data Sheet'!B21/'Data Sheet'!B$17 -> 0.012097282 | D10: ='Data Sheet'!C21/'Data Sheet'!C$17 -> 0.007743907 | E10: ='Data Sheet'!D21/'Data Sheet'!D$17 -> 0.0097722175 | F10: ='Data Sheet'!E21/'Data Sheet'!E$17 -> 0.010212806 | G10: ='Data Sheet'!F21/'Data Sheet'!F$17 -> 0.0065145075 | H10: ='Data Sheet'!G21/'Data Sheet'!G$17 -> 0.0063543873 | I10: ='Data Sheet'!H21/'Data Sheet'!H$17 -> 0.0055452865 | J10: ='Data Sheet'!I21/'Data Sheet'!I$17 -> 0.0055986219 | ... L10: ='Data Sheet'!K21/'Data Sheet'!K$17 -> 0.0042816039
B11: ='Data Sheet'!A22 -> Employee Cost | C11: ='Data Sheet'!B22/'Data Sheet'!B$17 -> 0.067440726 | D11: ='Data Sheet'!C22/'Data Sheet'!C$17 -> 0.056220405 | E11: ='Data Sheet'!D22/'Data Sheet'!D$17 -> 0.051795584 | F11: ='Data Sheet'!E22/'Data Sheet'!E$17 -> 0.057191716 | G11: ='Data Sheet'!F22/'Data Sheet'!F$17 -> 0.049390131 | H11: ='Data Sheet'!G22/'Data Sheet'!G$17 -> 0.047084968 | I11: ='Data Sheet'!H22/'Data Sheet'!H$17 -> 0.040813309 | J11: ='Data Sheet'!I22/'Data Sheet'!I$17 -> 0.036704252 | ... L11: ='Data Sheet'!K22/'Data Sheet'!K$17 -> 0.030736208
B12: ='Data Sheet'!A23 -> Selling and admin | C12: ='Data Sheet'!B23/'Data Sheet'!B$17 -> 0.09133365 | D12: ='Data Sheet'!C23/'Data Sheet'!C$17 -> 0.079269741 | E12: ='Data Sheet'!D23/'Data Sheet'!D$17 -> 0.073530274 | F12: ='Data Sheet'!E23/'Data Sheet'!E$17 -> 0.069827095 | G12: ='Data Sheet'!F23/'Data Sheet'!F$17 -> 0.047542044 | H12: ='Data Sheet'!G23/'Data Sheet'!G$17 -> 0.058925657 | I12: ='Data Sheet'!H23/'Data Sheet'!H$17 -> 0.066913124 | J12: ='Data Sheet'!I23/'Data Sheet'!I$17 -> 0.063601128 | ... L12: ='Data Sheet'!K23/'Data Sheet'!K$17 -> 0.0477827
B13: ='Data Sheet'!A24 -> Other Expenses | C13: ='Data Sheet'!B24/'Data Sheet'!B$17 -> 0.021096719 | D13: ='Data Sheet'!C24/'Data Sheet'!C$17 -> 0.026993561 | E13: ='Data Sheet'!D24/'Data Sheet'!D$17 -> 0.033871594 | F13: ='Data Sheet'!E24/'Data Sheet'!E$17 -> 0.023418203 | G13: ='Data Sheet'!F24/'Data Sheet'!F$17 -> 0.05678248 | H13: ='Data Sheet'!G24/'Data Sheet'!G$17 -> 0.018507587 | I13: ='Data Sheet'!H24/'Data Sheet'!H$17 -> 0.016833025 | J13: ='Data Sheet'!I24/'Data Sheet'!I$17 -> 0.017206953 | ... L13: ='Data Sheet'!K24/'Data Sheet'!K$17 -> 0.018051242
B14: ='Data Sheet'!A25 -> Other Income | C14: ='Data Sheet'!B25/'Data Sheet'!B$17 -> -0.0031958784 | D14: ='Data Sheet'!C25/'Data Sheet'!C$17 -> 0.0043381512 | E14: ='Data Sheet'!D25/'Data Sheet'!D$17 -> 0.009023931 | F14: ='Data Sheet'!E25/'Data Sheet'!E$17 -> 0.007267718 | G14: ='Data Sheet'!F25/'Data Sheet'!F$17 -> 0.0083163925 | H14: ='Data Sheet'!G25/'Data Sheet'!G$17 -> 0.0061460467 | I14: ='Data Sheet'!H25/'Data Sheet'!H$17 -> 0.0075415896 | J14: ='Data Sheet'!I25/'Data Sheet'!I$17 -> 0.010453371 | ... L14: ='Data Sheet'!K25/'Data Sheet'!K$17 -> 0.0051379247
B15: ='Data Sheet'!A26 -> Depreciation | C15: ='Data Sheet'!B26/'Data Sheet'!B$17 -> 0.008335074 | D15: ='Data Sheet'!C26/'Data Sheet'!C$17 -> 0.0081533421 | E15: ='Data Sheet'!D26/'Data Sheet'!D$17 -> 0.0082331742 | F15: ='Data Sheet'!E26/'Data Sheet'!E$17 -> 0.016530496 | G15: ='Data Sheet'!F26/'Data Sheet'!F$17 -> 0.017325818 | H15: ='Data Sheet'!G26/'Data Sheet'!G$17 -> 0.013854648 | I15: ='Data Sheet'!H26/'Data Sheet'!H$17 -> 0.010868762 | J15: ='Data Sheet'!I26/'Data Sheet'!I$17 -> 0.011432151 | ... L15: ='Data Sheet'!K26/'Data Sheet'!K$17 -> 0.0094309463
B16: ='Data Sheet'!A27 -> Interest | C16: ='Data Sheet'!B27/'Data Sheet'!B$17 -> 0.0028459757 | D16: ='Data Sheet'!C27/'Data Sheet'!C$17 -> 0.0032829253 | E16: ='Data Sheet'!D27/'Data Sheet'!D$17 -> 0.0026564172 | F16: ='Data Sheet'!E27/'Data Sheet'!E$17 -> 0.0078852366 | G16: ='Data Sheet'!F27/'Data Sheet'!F$17 -> 0.0093790427 | H16: ='Data Sheet'!G27/'Data Sheet'!G$17 -> 0.0075697073 | I16: ='Data Sheet'!H27/'Data Sheet'!H$17 -> 0.0073937153 | J16: ='Data Sheet'!I27/'Data Sheet'!I$17 -> 0.012117297 | ... L16: ='Data Sheet'!K27/'Data Sheet'!K$17 -> 0.01347278
B17: ='Data Sheet'!A28 -> Profit before tax | C17: ='Data Sheet'!B28/'Data Sheet'!B$17 -> 0.073392842 | D17: ='Data Sheet'!C28/'Data Sheet'!C$17 -> 0.094900858 | E17: ='Data Sheet'!D28/'Data Sheet'!D$17 -> 0.098940163 | F17: ='Data Sheet'!E28/'Data Sheet'!E$17 -> 0.099847995 | G17: ='Data Sheet'!F28/'Data Sheet'!F$17 -> 0.061310294 | H17: ='Data Sheet'!G28/'Data Sheet'!G$17 -> 0.10083683 | I17: ='Data Sheet'!H28/'Data Sheet'!H$17 -> 0.10959951 | J17: ='Data Sheet'!I28/'Data Sheet'!I$17 -> 0.090498003 | ... L17: ='Data Sheet'!K28/'Data Sheet'!K$17 -> 0.077651169
B18: ='Data Sheet'!A29 -> Tax | C18: ='Data Sheet'!B29/'Data Sheet'!B$17 -> 0.020810915 | D18: ='Data Sheet'!C29/'Data Sheet'!C$17 -> 0.026543183 | E18: ='Data Sheet'!D29/'Data Sheet'!D$17 -> 0.028730158 | F18: ='Data Sheet'!E29/'Data Sheet'!E$17 -> 0.028928368 | G18: ='Data Sheet'!F29/'Data Sheet'!F$17 -> 0.01630937 | H18: ='Data Sheet'!G29/'Data Sheet'!G$17 -> 0.02451474 | I18: ='Data Sheet'!H29/'Data Sheet'!H$17 -> 0.028909427 | J18: ='Data Sheet'!I29/'Data Sheet'!I$17 -> 0.022061702 | ... L18: ='Data Sheet'!K29/'Data Sheet'!K$17 -> 0.019729631
... B20: ='Data Sheet'!A31 -> Dividend Amount | C20: ='Data Sheet'!B31/'Data Sheet'!B$17 -> 0.017406904 | D20: ='Data Sheet'!C31/'Data Sheet'!C$17 -> 0.0206529 | E20: ='Data Sheet'!D31/'Data Sheet'!D$17 -> 0.02244354 | F20: ='Data Sheet'!E31/'Data Sheet'!E$17 -> 0.016910507 | G20: ='Data Sheet'!F31/'Data Sheet'!F$17 -> 0.016447976 | H20: ='Data Sheet'!G31/'Data Sheet'!G$17 -> 0.023177888 | I20: ='Data Sheet'!H31/'Data Sheet'!H$17 -> 0.021934689 | J20: ='Data Sheet'!I31/'Data Sheet'!I$17 -> 0.019164513 | ... L20: ='Data Sheet'!K31/'Data Sheet'!K$17 -> 0.01524251
B21: ='Data Sheet'!A34 -> EBITDA | C21: ='Data Sheet'!B34/'Data Sheet'!B$17 -> 0.08776977 | D21: ='Data Sheet'!C34/'Data Sheet'!C$17 -> 0.10199897 | E21: ='Data Sheet'!D34/'Data Sheet'!D$17 -> 0.10080582 | F21: ='Data Sheet'!E34/'Data Sheet'!E$17 -> 0.11699601 | G21: ='Data Sheet'!F34/'Data Sheet'!F$17 -> 0.079698762 | H21: ='Data Sheet'!G34/'Data Sheet'!G$17 -> 0.11611514 | I21: ='Data Sheet'!H34/'Data Sheet'!H$17 -> 0.12032039 | J21: ='Data Sheet'!I34/'Data Sheet'!I$17 -> 0.10359408 | ... L21: ='Data Sheet'!K34/'Data Sheet'!K$17 -> 0.095416971
B23: ="Common Size Balance Sheet Statement"&" - "&'Data Sheet'!B1 -> Common Size Balance Sheet Statement - TITAN COMPANY LTD
B25: Pariculars | C25: =C4 -> 42825 | D25: =D4 -> 43190 | E25: =E4 -> 43555 | F25: =F4 -> 43921 | G25: =G4 -> 44286 | H25: =H4 -> 44651 | I25: =I4 -> 45016 | J25: =J4 -> 45382 | ... L25: =L4 -> 46112
B27: Total Liabilities | C27: ='Data Sheet'!B61/'Data Sheet'!B61 -> 1 | D27: ='Data Sheet'!C61/'Data Sheet'!C61 -> 1 | E27: ='Data Sheet'!D61/'Data Sheet'!D61 -> 1 | F27: ='Data Sheet'!E61/'Data Sheet'!E61 -> 1 | G27: ='Data Sheet'!F61/'Data Sheet'!F61 -> 1 | H27: ='Data Sheet'!G61/'Data Sheet'!G61 -> 1 | I27: ='Data Sheet'!H61/'Data Sheet'!H61 -> 1 | J27: ='Data Sheet'!I61/'Data Sheet'!I61 -> 1 | ... L27: ='Data Sheet'!K61/'Data Sheet'!K61 -> 1
B28: ='Data Sheet'!A57 -> Equity Share Capital | C28: ='Data Sheet'!B57/'Data Sheet'!B$61 -> 0.010559531 | D28: ='Data Sheet'!C57/'Data Sheet'!C$61 -> 0.0093246116 | E28: ='Data Sheet'!D57/'Data Sheet'!D$61 -> 0.0075816578 | F28: ='Data Sheet'!E57/'Data Sheet'!E$61 -> 0.0065711754 | G28: ='Data Sheet'!F57/'Data Sheet'!F$61 -> 0.0054123084 | H28: ='Data Sheet'!G57/'Data Sheet'!G$61 -> 0.0042004908 | I28: ='Data Sheet'!H57/'Data Sheet'!H$61 -> 0.0032938564 | J28: ='Data Sheet'!I57/'Data Sheet'!I$61 -> 0.0028211874 | ... L28: ='Data Sheet'!K57/'Data Sheet'!K$61 -> 0.0014695926
B29: ='Data Sheet'!A58 -> Reserves | C29: ='Data Sheet'!B58/'Data Sheet'!B$61 -> 0.49284157 | D29: ='Data Sheet'!C58/'Data Sheet'!C$61 -> 0.52526825 | E29: ='Data Sheet'!D58/'Data Sheet'!D$61 -> 0.51079861 | F29: ='Data Sheet'!E58/'Data Sheet'!E$61 -> 0.48582398 | G29: ='Data Sheet'!F58/'Data Sheet'!F$61 -> 0.45049866 | H29: ='Data Sheet'!G58/'Data Sheet'!G$61 -> 0.43486879 | I29: ='Data Sheet'!H58/'Data Sheet'!H$61 -> 0.43530718 | J29: ='Data Sheet'!I58/'Data Sheet'!I$61 -> 0.29492503 | ... L29: ='Data Sheet'!K58/'Data Sheet'!K$61 -> 0.25782269
B30: ='Data Sheet'!A59 -> Borrowings | C30: ='Data Sheet'!B59/'Data Sheet'!B$61 -> 0.22389704 | D30: ='Data Sheet'!C59/'Data Sheet'!C$61 -> 0.1776077 | E30: ='Data Sheet'!D59/'Data Sheet'!D$61 -> 0.20435634 | F30: ='Data Sheet'!E59/'Data Sheet'!E$61 -> 0.26299468 | G30: ='Data Sheet'!F59/'Data Sheet'!F$61 -> 0.34286062 | H30: ='Data Sheet'!G59/'Data Sheet'!G$61 -> 0.34335473 | I30: ='Data Sheet'!H59/'Data Sheet'!H$61 -> 0.34666913 | J30: ='Data Sheet'!I59/'Data Sheet'!I$61 -> 0.49221796 | ... L30: ='Data Sheet'!K59/'Data Sheet'!K$61 -> 0.50562243
B31: ='Data Sheet'!A33 -> Trade Payables | C31: ='Data Sheet'!B33/'Data Sheet'!B$61 -> 0.093130358 | D31: ='Data Sheet'!C33/'Data Sheet'!C$61 -> 0.092216817 | E31: ='Data Sheet'!D33/'Data Sheet'!D$61 -> 0.077370827 | F31: ='Data Sheet'!E33/'Data Sheet'!E$61 -> 0.044004725 | G31: ='Data Sheet'!F33/'Data Sheet'!F$61 -> 0.047981027 | H31: ='Data Sheet'!G33/'Data Sheet'!G$61 -> 0.061072305 | I31: ='Data Sheet'!H33/'Data Sheet'!H$61 -> 0.044929682 | J31: ='Data Sheet'!I33/'Data Sheet'!I$61 -> 0.044695217 | ... L31: ='Data Sheet'!K33/'Data Sheet'!K$61 -> 0.047291161
B32: ='Data Sheet'!A60 -> Other Liabilities | C32: =('Data Sheet'!B60-'Data Sheet'!B33)/'Data Sheet'!B$61 -> 0.17957151 | D32: =('Data Sheet'!C60-'Data Sheet'!C33)/'Data Sheet'!C$61 -> 0.19558263 | E32: =('Data Sheet'!D60-'Data Sheet'!D33)/'Data Sheet'!D$61 -> 0.19989257 | F32: =('Data Sheet'!E60-'Data Sheet'!E33)/'Data Sheet'!E$61 -> 0.20060543 | G32: =('Data Sheet'!F60-'Data Sheet'!F33)/'Data Sheet'!F$61 -> 0.15324739 | H32: =('Data Sheet'!G60-'Data Sheet'!G33)/'Data Sheet'!G$61 -> 0.15650368 | I32: =('Data Sheet'!H60-'Data Sheet'!H33)/'Data Sheet'!H$61 -> 0.16980015 | J32: =('Data Sheet'!I60-'Data Sheet'!I33)/'Data Sheet'!I$61 -> 0.1653406 | ... L32: =('Data Sheet'!K60-'Data Sheet'!K33)/'Data Sheet'!K$61 -> 0.18779412
B34: Total Assets | C34: ='Data Sheet'!B66/'Data Sheet'!B66 -> 1 | D34: ='Data Sheet'!C66/'Data Sheet'!C66 -> 1 | E34: ='Data Sheet'!D66/'Data Sheet'!D66 -> 1 | F34: ='Data Sheet'!E66/'Data Sheet'!E66 -> 1 | G34: ='Data Sheet'!F66/'Data Sheet'!F66 -> 1 | H34: ='Data Sheet'!G66/'Data Sheet'!G66 -> 1 | I34: ='Data Sheet'!H66/'Data Sheet'!H66 -> 1 | J34: ='Data Sheet'!I66/'Data Sheet'!I66 -> 1 | ... L34: ='Data Sheet'!K66/'Data Sheet'!K66 -> 1
B35: ='Data Sheet'!A62 -> Net Block | C35: ='Data Sheet'!B62/'Data Sheet'!B$61 -> 0.14138687 | D35: ='Data Sheet'!C62/'Data Sheet'!C$61 -> 0.15479506 | E35: ='Data Sheet'!D62/'Data Sheet'!D$61 -> 0.13378748 | F35: ='Data Sheet'!E62/'Data Sheet'!E$61 -> 0.19440343 | G35: ='Data Sheet'!F62/'Data Sheet'!F$61 -> 0.15342982 | H35: ='Data Sheet'!G62/'Data Sheet'!G$61 -> 0.12006796 | I35: ='Data Sheet'!H62/'Data Sheet'!H$61 -> 0.11095485 | J35: ='Data Sheet'!I62/'Data Sheet'!I$61 -> 0.11757061 | ... L35: ='Data Sheet'!K62/'Data Sheet'!K$61 -> 0.11357144
B36: ='Data Sheet'!A63 -> Capital Work in Progress | C36: ='Data Sheet'!B63/'Data Sheet'!B$61 -> 0.018087271 | D36: ='Data Sheet'!C63/'Data Sheet'!C$61 -> 0.0045551746 | E36: ='Data Sheet'!D63/'Data Sheet'!D$61 -> 0.0027131028 | F36: ='Data Sheet'!E63/'Data Sheet'!E$61 -> 0.0013290018 | G36: ='Data Sheet'!F63/'Data Sheet'!F$61 -> 0.0019459985 | H36: ='Data Sheet'!G63/'Data Sheet'!G$61 -> 0.0040117047 | I36: ='Data Sheet'!H63/'Data Sheet'!H$61 -> 0.0053293856 | J36: ='Data Sheet'!I63/'Data Sheet'!I$61 -> 0.0030747773 | ... L36: ='Data Sheet'!K63/'Data Sheet'!K$61 -> 0.0026915011
B37: ='Data Sheet'!A64 -> Investments | C37: ='Data Sheet'!B64/'Data Sheet'!B$61 -> 0.051231212 | D37: ='Data Sheet'!C64/'Data Sheet'!C$61 -> 0.0037800492 | E37: ='Data Sheet'!D64/'Data Sheet'!D$61 -> 0.0092588797 | F37: ='Data Sheet'!E64/'Data Sheet'!E$61 -> 0.011665682 | G37: ='Data Sheet'!F64/'Data Sheet'!F$61 -> 0.17173437 | H37: ='Data Sheet'!G64/'Data Sheet'!G$61 -> 0.013875779 | I37: ='Data Sheet'!H64/'Data Sheet'!H$61 -> 0.093079201 | J37: ='Data Sheet'!I64/'Data Sheet'!I$61 -> 0.074333534 | ... L37: ='Data Sheet'!K64/'Data Sheet'!K$61 -> 0.057892043
B38: ='Data Sheet'!A65 -> Other Assets | C38: ='Data Sheet'!B74/'Data Sheet'!B$66 -> 0.086086705 | D38: ='Data Sheet'!C74/'Data Sheet'!C$66 -> 0.11862465 | E38: ='Data Sheet'!D74/'Data Sheet'!D$66 -> 0.12615629 | F38: ='Data Sheet'!E74/'Data Sheet'!E$66 -> 0.14316302 | G38: ='Data Sheet'!F74/'Data Sheet'!F$66 -> 0.10526636 | H38: ='Data Sheet'!G74/'Data Sheet'!G$66 -> 0.11884085 | I38: ='Data Sheet'!H74/'Data Sheet'!H$66 -> 0.10222058 | J38: ='Data Sheet'!I74/'Data Sheet'!I$66 -> 0.12048689 | ... L38: ='Data Sheet'!K74/'Data Sheet'!K$66 -> 0.073281485
B39: ='Data Sheet'!A67 -> Receivables | C39: ='Data Sheet'!B67/'Data Sheet'!B$61 -> 0.024692033 | D39: ='Data Sheet'!C67/'Data Sheet'!C$61 -> 0.031056481 | E39: ='Data Sheet'!D67/'Data Sheet'!D$61 -> 0.0359057 | F39: ='Data Sheet'!E67/'Data Sheet'!E$61 -> 0.023036031 | G39: ='Data Sheet'!F67/'Data Sheet'!F$61 -> 0.022257358 | H39: ='Data Sheet'!G67/'Data Sheet'!G$61 -> 0.026666037 | I39: ='Data Sheet'!H67/'Data Sheet'!H$61 -> 0.024944486 | J39: ='Data Sheet'!I67/'Data Sheet'!I$61 -> 0.032269312 | ... L39: ='Data Sheet'!K67/'Data Sheet'!K$61 -> 0.015125246
B40: ='Data Sheet'!A68 -> Inventory | C40: ='Data Sheet'!B68/'Data Sheet'!B$61 -> 0.58586964 | D40: ='Data Sheet'!C68/'Data Sheet'!C$61 -> 0.62228916 | E40: ='Data Sheet'!D68/'Data Sheet'!D$61 -> 0.601103 | F40: ='Data Sheet'!E68/'Data Sheet'!E$61 -> 0.5982723 | G40: ='Data Sheet'!F68/'Data Sheet'!F$61 -> 0.51131112 | H40: ='Data Sheet'!G68/'Data Sheet'!G$61 -> 0.64229753 | I40: ='Data Sheet'!H68/'Data Sheet'!H$61 -> 0.61376758 | J40: ='Data Sheet'!I68/'Data Sheet'!I$61 -> 0.6038926 | ... L40: ='Data Sheet'!K68/'Data Sheet'!K$61 -> 0.70578425
B41: ='Data Sheet'!A69 -> Cash & Bank | C41: ='Data Sheet'!B69/'Data Sheet'!B$61 -> 0.09264627 | D41: ='Data Sheet'!C69/'Data Sheet'!C$61 -> 0.064899423 | E41: ='Data Sheet'!D69/'Data Sheet'!D$61 -> 0.09107554 | F41: ='Data Sheet'!E69/'Data Sheet'!E$61 -> 0.028130538 | G41: ='Data Sheet'!F69/'Data Sheet'!F$61 -> 0.034054974 | H41: ='Data Sheet'!G69/'Data Sheet'!G$61 -> 0.074240136 | I41: ='Data Sheet'!H69/'Data Sheet'!H$61 -> 0.049703923 | J41: ='Data Sheet'!I69/'Data Sheet'!I$61 -> 0.04837227 | ... L41: ='Data Sheet'!K69/'Data Sheet'!K$61 -> 0.031654035

Sheet Assumptions Sheet
B2: ="Assumption Sheet"&" - "&'Data Sheet'!B1 -> Assumption Sheet - TITAN COMPANY LTD
B4: 1. P & L Drivers
B5: Years | C5: ='Data Sheet'!F56 -> 44286 | D5: ='Data Sheet'!G56 -> 44651 | E5: ='Data Sheet'!H56 -> 45016 | F5: ='Data Sheet'!I56 -> 45382 | G5: ='Data Sheet'!J56 -> 45747 | H5: ='Data Sheet'!K56 -> 46112 | I5: =H5+365 -> 46477 | J5: =I5+365 -> 46842 | K5: =J5+365 -> 47207 | L5: =K5+365 -> 47572 | M5: =L5+365 -> 47937
B7: =HistoricalFS!B10 -> Sales Growth | C7: =HistoricalFS!G10 -> 0.028120844 | D7: =HistoricalFS!H10 -> 0.3305766 | E7: =HistoricalFS!I10 -> 0.40890309 | F7: =HistoricalFS!J10 -> 0.25900185 | G7: =HistoricalFS!K10 -> 0.18346253 | H7: =HistoricalFS!L10 -> 0.44872304 | I7: =IF($C$39="Bull",I42,I41) -> 0.18 | J7: =IF($C$39="Bull",J42,J41) -> 0.16 | K7: =IF($C$39="Bull",K42,K41) -> 0.15 | L7: =IF($C$39="Bull",L42,L41) -> 0.14 | M7: =IF($C$39="Bull",M42,M41) -> 0.13
B8: =HistoricalFS!B13 -> COGS % of Sales | C8: =HistoricalFS!G13 -> 0.81597671 | D8: =HistoricalFS!H13 -> 0.80645161 | E8: =HistoricalFS!I13 -> 0.79593346 | F8: =HistoricalFS!J13 -> 0.81559784 | G8: =HistoricalFS!K13 -> 0.82744475 | H8: =HistoricalFS!L13 -> 0.83874909 | I8: =IF($C$39="Bull",I44,I43) -> 0.835 | J8: =IF($C$39="Bull",J44,J43) -> 0.83 | K8: =IF($C$39="Bull",K44,K43) -> 0.825 | L8: =IF($C$39="Bull",L44,L43) -> 0.82 | M8: =IF($C$39="Bull",M44,M43) -> 0.815
B9: =HistoricalFS!B16 -> Gross Margins | C9: =HistoricalFS!G16 -> 0.18402329 | D9: =HistoricalFS!H16 -> 0.19354839 | E9: =HistoricalFS!I16 -> 0.20406654 | F9: =HistoricalFS!J16 -> 0.18440216 | G9: =HistoricalFS!K16 -> 0.17255525 | H9: =HistoricalFS!L16 -> 0.16125091 | I9: =1-I8 -> 0.165 | J9: =1-J8 -> 0.17 | K9: =1-K8 -> 0.175 | L9: =1-L8 -> 0.18 | M9: =1-M8 -> 0.185
B10: =HistoricalFS!B19 -> S&G % of Sales | C10: =HistoricalFS!G19 -> 0.10432452 | D10: =HistoricalFS!H19 -> 0.077433244 | E10: =HistoricalFS!I19 -> 0.083746149 | F10: =HistoricalFS!J19 -> 0.080808081 | G10: =HistoricalFS!K19 -> 0.078371047 | H10: =HistoricalFS!L19 -> 0.065833942 | I10: =IF($C$39="Bull",I46,I45) -> 0.064 | J10: =IF($C$39="Bull",J46,J45) -> 0.062 | K10: =IF($C$39="Bull",K46,K45) -> 0.06 | L10: =IF($C$39="Bull",L46,L45) -> 0.059 | M10: =IF($C$39="Bull",M46,M45) -> 0.058
B11: =HistoricalFS!B22 -> EBITDA Margins | C11: =HistoricalFS!G22 -> 0.079698762 | D11: =HistoricalFS!H22 -> 0.11611514 | E11: =HistoricalFS!I22 -> 0.12032039 | F11: =HistoricalFS!J22 -> 0.10359408 | G11: =HistoricalFS!K22 -> 0.0941842 | H11: =HistoricalFS!L22 -> 0.095416971 | I11: =I9-I10 -> 0.101 | J11: =J9-J10 -> 0.108 | K11: =K9-K10 -> 0.115 | L11: =L9-L10 -> 0.121 | M11: =M9-M10 -> 0.127
B12: Other Income (Crs) | C12: =HistoricalFS!G24 -> 180 | D12: =HistoricalFS!H24 -> 177 | E12: =HistoricalFS!I24 -> 306 | F12: =HistoricalFS!J24 -> 534 | G12: =HistoricalFS!K24 -> 487 | H12: =HistoricalFS!L24 -> 450 | I12: =H12*(1+0.1) -> 495 | J12: =I12*(1+0.1) -> 544.5 | K12: =J12*(1+0.1) -> 598.95 | L12: =K12*(1+0.1) -> 658.845 | M12: =L12*(1+0.1) -> 724.7295
B13: Depreciation (Crs) | C13: =HistoricalFS!G27 -> 375 | D13: =HistoricalFS!H27 -> 399 | E13: =HistoricalFS!I27 -> 441 | F13: =HistoricalFS!J27 -> 584 | G13: =HistoricalFS!K27 -> 693 | H13: =HistoricalFS!L27 -> 826 | I13: =H13*(1+0.15) -> 949.9 | J13: =I13*(1+0.15) -> 1092.385 | K13: =J13*(1+0.15) -> 1256.2427 | L13: =K13*(1+0.15) -> 1444.6792 | M13: =L13*(1+0.15) -> 1661.381
B14: Interest Expense (Crs) | C14: =HistoricalFS!G33 -> 203 | D14: =HistoricalFS!H33 -> 218 | E14: =HistoricalFS!I33 -> 300 | F14: =HistoricalFS!J33 -> 619 | G14: =HistoricalFS!K33 -> 953 | H14: =HistoricalFS!L33 -> 1180 | I14: =H14*(1+0.18) -> 1392.4 | J14: =I14*(1+0.15) -> 1601.26 | K14: =J14*(1+0.13) -> 1809.4238 | L14: =K14*(1+0.11) -> 2008.4604 | M14: =L14*(1+0.1) -> 2209.3065
B15: Dividend Payout | C15: =HistoricalFS!G51 -> 0.36550308 | D15: =HistoricalFS!H51 -> 0.30368517 | E15: =HistoricalFS!I51 -> 0.27183873 | F15: =HistoricalFS!J51 -> 0.28003432 | G15: =HistoricalFS!K51 -> 0.29337728 | H15: =HistoricalFS!L51 -> 0.26315789 | I15: 0.27 | J15: 0.27 | K15: 0.27 | L15: 0.27 | M15: 0.27
B16: Tax Rate | C16: =HistoricalFS!G40 -> 0.26601356 | D16: =HistoricalFS!H40 -> 0.24311295 | E16: =HistoricalFS!I40 -> 0.26377333 | F16: =HistoricalFS!J40 -> 0.24378109 | G16: =HistoricalFS!K40 -> 0.26416759 | H16: =HistoricalFS!L40 -> 0.25408028 | I16: 0.2535 | J16: 0.2535 | K16: 0.2535 | L16: 0.2535 | M16: 0.2535
B18: 2. Working Capital Drivers
B19: Years | C19: =C5 -> 44286 | D19: =D5 -> 44651 | E19: =E5 -> 45016 | F19: =F5 -> 45382 | G19: =G5 -> 45747 | H19: =H5 -> 46112 | I19: =I5 -> 46477 | J19: =J5 -> 46842 | ... M19: =M5 -> 47937
B20: ='Ratio Analysis'!B33 -> Debtor Days | C20: ='Ratio Analysis'!G33 -> 6.1721493 | D20: ='Ratio Analysis'!H33 -> 7.1608389 | E20: ='Ratio Analysis'!I33 -> 6.063093 | F20: ='Ratio Analysis'!J33 -> 7.2737061 | G20: ='Ratio Analysis'!K33 -> 6.4479952 | H20: ='Ratio Analysis'!L33 -> 3.8173639 | I20: 4.5 | J20: 5 | K20: 5.5 | L20: 5.5 | M20: 5.5
B21: ='Ratio Analysis'!B34 -> Creditor Days | C21: ='Ratio Analysis'!G34 -> 16.306268 | D21: ='Ratio Analysis'!H34 -> 20.336276 | E21: ='Ratio Analysis'!I34 -> 13.7207 | F21: ='Ratio Analysis'!J34 -> 12.352391 | G21: ='Ratio Analysis'!K34 -> 14.323025 | H21: ='Ratio Analysis'!L34 -> 14.230136 | I21: 14 | J21: 14 | K21: 14 | L21: 14 | M21: 14
B22: ='Ratio Analysis'!B35 -> Inventory Days | C22: ='Ratio Analysis'!G35 -> 173.76819 | D22: ='Ratio Analysis'!H35 -> 213.87664 | E22: ='Ratio Analysis'!I35 -> 187.43335 | F22: ='Ratio Analysis'!J35 -> 166.89744 | G22: ='Ratio Analysis'!K35 -> 205.64449 | H22: ='Ratio Analysis'!L35 -> 212.37384 | I22: 205 | J22: 200 | K22: 195 | L22: 190 | M22: 185
B24: 3. Capex & Fixed Assets
B25: Years | C25: =C19 -> 44286 | D25: =D19 -> 44651 | E25: =E19 -> 45016 | F25: =F19 -> 45382 | G25: =G19 -> 45747 | H25: =H19 -> 46112 | I25: =I19 -> 46477 | J25: =J19 -> 46842 | ... M25: =M19 -> 47937
B26: Capex (Crs) | C26: =-HistoricalFS!G92 -> 146 | D26: =-HistoricalFS!H92 -> 224 | E26: =-HistoricalFS!I92 -> 432 | F26: =-HistoricalFS!J92 -> 691 | G26: =-HistoricalFS!K92 -> 494 | H26: =-HistoricalFS!L92 -> 902 | I26: =HistoricalFS!$L$9*(1+I7)*I27 -> 1136.8403 | J26: =HistoricalFS!$L$9*(1+I7)*(1+J7)*J27 -> 1378.6773 | K26: =HistoricalFS!$L$9*(1+I7)*(1+J7)*(1+K7)*K27 -> 1654.4127 | L26: =HistoricalFS!$L$9*(1+I7)*(1+J7)*(1+K7)*(1+L7)*L27 -> 1886.0305 | M26: =HistoricalFS!$L$9*(1+I7)*(1+J7)*(1+K7)*(1+L7)*(1+M7)*M27 -> 2042.4139
B27: Capex % of Sales | C27: =C26/HistoricalFS!G9 -> 0.0067455184 | D27: =D26/HistoricalFS!H9 -> 0.0077780478 | E27: =E26/HistoricalFS!I9 -> 0.01064695 | F27: =F26/HistoricalFS!J9 -> 0.01352674 | G27: =G26/HistoricalFS!K9 -> 0.008171232 | H27: =H26/HistoricalFS!L9 -> 0.010298685 | I27: =IF($C$39="Bull",I48,I47) -> 0.011 | J27: =IF($C$39="Bull",J48,J47) -> 0.0115 | K27: =IF($C$39="Bull",K48,K47) -> 0.012 | L27: =IF($C$39="Bull",L48,L47) -> 0.012 | M27: =IF($C$39="Bull",M48,M47) -> 0.0115
B29: 4. Balance Sheet Drivers
B30: Years | C30: =C25 -> 44286 | D30: =D25 -> 44651 | E30: =E25 -> 45016 | F30: =F25 -> 45382 | G30: =G25 -> 45747 | H30: =H25 -> 46112 | I30: =I25 -> 46477 | J30: =J25 -> 46842 | ... M30: =M25 -> 47937
B31: Other Liabilities % of Sales | C31: =HistoricalFS!C60/HistoricalFS!C9 -> 0.11385109 | D31: =HistoricalFS!D60/HistoricalFS!D9 -> 0.11551964 | E31: =HistoricalFS!E60/HistoricalFS!E9 -> 0.11834606 | F31: =HistoricalFS!F60/HistoricalFS!F9 -> 0.12906137 | G31: =HistoricalFS!G60/HistoricalFS!G9 -> 0.1164295 | H31: =HistoricalFS!H60/HistoricalFS!H9 -> 0.11514289 | I31: 0.115 | J31: 0.115 | K31: 0.115 | L31: 0.115 | M31: 0.115
B32: Other Assets % of Sales | C32: =HistoricalFS!C66/HistoricalFS!C9 -> 0.054580294 | D32: =HistoricalFS!D66/HistoricalFS!D9 -> 0.070064895 | E32: =HistoricalFS!E66/HistoricalFS!E9 -> 0.074690624 | F32: =HistoricalFS!F66/HistoricalFS!F9 -> 0.092105263 | G32: =HistoricalFS!G66/HistoricalFS!G9 -> 0.079975975 | H32: =HistoricalFS!H66/HistoricalFS!H9 -> 0.087433591 | I32: 0.088 | J32: 0.09 | K32: 0.09 | L32: 0.09 | M32: 0.09
B33: Capital WIP (Crs) | C33: =HistoricalFS!C64 -> 152.07 | D33: =HistoricalFS!D64 -> 43.37 | E33: =HistoricalFS!E64 -> 31.77 | F33: =HistoricalFS!F64 -> 18 | G33: =HistoricalFS!G64 -> 32 | H33: =HistoricalFS!H64 -> 85 | I33: 95 | J33: 105 | K33: 115 | L33: 125 | M33: 135
B34: Investments (Crs) | C34: =HistoricalFS!C65 -> 430.73 | D34: =HistoricalFS!D65 -> 35.99 | E34: =HistoricalFS!E65 -> 108.42 | F34: =HistoricalFS!F65 -> 158 | G34: =HistoricalFS!G65 -> 2824 | H34: =HistoricalFS!H65 -> 294 | I34: =H34*(1+0.12) -> 329.28 | J34: =I34*(1+0.12) -> 368.7936 | K34: =J34*(1+0.12) -> 413.04883 | L34: =K34*(1+0.12) -> 462.61469 | M34: =L34*(1+0.12) -> 518.12845
B35: Borrowings (Crs) | C35: =HistoricalFS!C58 -> 1882.43 | D35: =HistoricalFS!D58 -> 1691.01 | E35: =HistoricalFS!E58 -> 2392.98 | F35: =HistoricalFS!F58 -> 3562 | G35: =HistoricalFS!G58 -> 5638 | H35: =HistoricalFS!H58 -> 7275 | I35: =H35*(1+0.2) -> 8730 | J35: =I35*(1+0.18) -> 10301.4 | K35: =J35*(1+0.16) -> 11949.624 | L35: =K35*(1+0.15) -> 13742.068 | M35: =L35*(1+0.14) -> 15665.957
B37: 3. Scenario Analysis (Base Case vs Bull Case)
B38: Years | I38: =I30 -> 46477 | J38: =J30 -> 46842 | K38: =K30 -> 47207 | L38: =L30 -> 47572 | M38: =M30 -> 47937
B39: Active Scenario (type: Base Case / Bull Case) | C39: Base
B41: Sales Growth Rate - Base Case (%) | I41: 0.18 | J41: 0.16 | K41: 0.15 | L41: 0.14 | M41: 0.13
B42: Sales Growth Rate - Bull Case (%) | I42: 0.22 | J42: 0.2 | K42: 0.19 | L42: 0.18 | M42: 0.17
B43: COGS % of Sales - Base Case | I43: 0.835 | J43: 0.83 | K43: 0.825 | L43: 0.82 | M43: 0.815
B44: COGS % of Sales - Bull Case | I44: 0.82 | J44: 0.815 | K44: 0.81 | L44: 0.805 | M44: 0.8
B45: S&G Exp % of Sales - Base Case | I45: 0.064 | J45: 0.062 | K45: 0.06 | L45: 0.059 | M45: 0.058
B46: S&G Exp % of Sales - Bull Case | I46: 0.061 | J46: 0.059 | K46: 0.057 | L46: 0.056 | M46: 0.055
B47: Capex % of Sales - Base Case | I47: 0.011 | J47: 0.0115 | K47: 0.012 | L47: 0.012 | M47: 0.0115
B48: Capex % of Sales - Bull Case | I48: 0.0103 | J48: 0.0105 | K48: 0.0105 | L48: 0.0103 | M48: 0.01
B50: Implied EBITDA Margin - Base Case (%) [memo] | I50: =(1-I43)-I45 -> 0.101 | J50: =(1-J43)-J45 -> 0.108 | K50: =(1-K43)-K45 -> 0.115 | L50: =(1-L43)-L45 -> 0.121 | M50: =(1-M43)-M45 -> 0.127
B51: Implied EBITDA Margin - Bull Case (%) [memo] | I51: =(1-I44)-I46 -> 0.119 | J51: =(1-J44)-J46 -> 0.126 | K51: =(1-K44)-K46 -> 0.133 | L51: =(1-L44)-L46 -> 0.139 | M51: =(1-M44)-M46 -> 0.145
B53: 4. DCF Drivers
B54: Years | I54: =I38 -> 46477 | J54: =J38 -> 46842 | K54: =K38 -> 47207 | L54: =L38 -> 47572 | M54: =M38 -> 47937
B55: ReInvestment Rate | I55: =(-ForcastedFS!H75-SUM(ForcastedFS!H67:H70))/(ForcastedFS!H24*(1-ForcastedFS!H32)) -> 1.4650611 | J55: =(-ForcastedFS!I75-SUM(ForcastedFS!I67:I70))/(ForcastedFS!I24*(1-ForcastedFS!I32)) -> 0.76580649 | K55: =(-ForcastedFS!J75-SUM(ForcastedFS!J67:J70))/(ForcastedFS!J24*(1-ForcastedFS!J32)) -> 0.64668816 | L55: =(-ForcastedFS!K75-SUM(ForcastedFS!K67:K70))/(ForcastedFS!K24*(1-ForcastedFS!K32)) -> 0.54633705 | M55: =(-ForcastedFS!L75-SUM(ForcastedFS!L67:L70))/(ForcastedFS!L24*(1-ForcastedFS!L32)) -> 0.46518057

Sheet ForcastedFS
B2: ="Forcasted Financial Statements"&" - "&'Data Sheet'!B1 -> Forcasted Financial Statements - TITAN COMPANY LTD
A4: # | B4: ="Income Statement"&" - "&'Data Sheet'!B1 -> Income Statement - TITAN COMPANY LTD
B5: Particulars | C5: ='Assumptions Sheet'!D5 -> 44651 | D5: ='Assumptions Sheet'!E5 -> 45016 | E5: ='Assumptions Sheet'!F5 -> 45382 | F5: ='Assumptions Sheet'!G5 -> 45747 | G5: ='Assumptions Sheet'!H5 -> 46112 | H5: ='Assumptions Sheet'!I5 -> 46477 | I5: ='Assumptions Sheet'!J5 -> 46842 | J5: ='Assumptions Sheet'!K5 -> 47207 | ... L5: ='Assumptions Sheet'!M5 -> 47937
B6: Sales | C6: =HistoricalFS!H9 -> 28799 | D6: =HistoricalFS!I9 -> 40575 | E6: =HistoricalFS!J9 -> 51084 | F6: =HistoricalFS!K9 -> 60456 | G6: =HistoricalFS!L9 -> 87584 | H6: =G6*(1+H7) -> 103349.12 | I6: =H6*(1+I7) -> 119884.98 | J6: =I6*(1+J7) -> 137867.73 | K6: =J6*(1+K7) -> 157169.21 | L6: =K6*(1+L7) -> 177601.2
B7: Sales Growth (%) | C7: =HistoricalFS!H10 -> 0.3305766 | D7: =HistoricalFS!I10 -> 0.40890309 | E7: =HistoricalFS!J10 -> 0.25900185 | F7: =HistoricalFS!K10 -> 0.18346253 | G7: =HistoricalFS!L10 -> 0.44872304 | H7: ='Assumptions Sheet'!I7 -> 0.18 | I7: ='Assumptions Sheet'!J7 -> 0.16 | J7: ='Assumptions Sheet'!K7 -> 0.15 | K7: ='Assumptions Sheet'!L7 -> 0.14 | L7: ='Assumptions Sheet'!M7 -> 0.13
B9: COGS | C9: =HistoricalFS!H12 -> 23225 | D9: =HistoricalFS!I12 -> 32295 | E9: =HistoricalFS!J12 -> 41664 | F9: =HistoricalFS!K12 -> 50024 | G9: =HistoricalFS!L12 -> 73461 | H9: =H6*H10 -> 86296.515 | I9: =I6*I10 -> 99504.533 | J9: =J6*J10 -> 113740.87 | K9: =K6*K10 -> 128878.75 | L9: =L6*L10 -> 144744.98
B10: COGS % of Sales | C10: =C9/C6 -> 0.80645161 | D10: =D9/D6 -> 0.79593346 | E10: =E9/E6 -> 0.81559784 | F10: =F9/F6 -> 0.82744475 | G10: =G9/G6 -> 0.83874909 | H10: ='Assumptions Sheet'!I8 -> 0.835 | I10: ='Assumptions Sheet'!J8 -> 0.83 | J10: ='Assumptions Sheet'!K8 -> 0.825 | K10: ='Assumptions Sheet'!L8 -> 0.82 | L10: ='Assumptions Sheet'!M8 -> 0.815
B12: Gross Profit | C12: =C6-C9 -> 5574 | D12: =D6-D9 -> 8280 | E12: =E6-E9 -> 9420 | F12: =F6-F9 -> 10432 | G12: =G6-G9 -> 14123 | H12: =H6-H9 -> 17052.605 | I12: =I6-I9 -> 20380.446 | J12: =J6-J9 -> 24126.852 | ... L12: =L6-L9 -> 32856.223
B13: Gross Margin (%) | C13: =C12/C6 -> 0.19354839 | D13: =D12/D6 -> 0.20406654 | E13: =E12/E6 -> 0.18440216 | F13: =F12/F6 -> 0.17255525 | G13: =G12/G6 -> 0.16125091 | H13: =H12/H6 -> 0.165 | I13: =I12/I6 -> 0.17 | J13: =J12/J6 -> 0.175 | ... L13: =L12/L6 -> 0.185
B15: S&G Expenses | C15: =HistoricalFS!H18 -> 2230 | D15: =HistoricalFS!I18 -> 3398 | E15: =HistoricalFS!J18 -> 4128 | F15: =HistoricalFS!K18 -> 4738 | G15: =HistoricalFS!L18 -> 5766 | H15: =H6*H16 -> 6614.3437 | I15: =I6*I16 -> 7432.8687 | J15: =J6*J16 -> 8272.0636 | K15: =K6*K16 -> 9272.9833 | L15: =L6*L16 -> 10300.87
B16: S&G % of Sales | C16: =C15/C6 -> 0.077433244 | D16: =D15/D6 -> 0.083746149 | E16: =E15/E6 -> 0.080808081 | F16: =F15/F6 -> 0.078371047 | G16: =G15/G6 -> 0.065833942 | H16: ='Assumptions Sheet'!I10 -> 0.064 | I16: ='Assumptions Sheet'!J10 -> 0.062 | J16: ='Assumptions Sheet'!K10 -> 0.06 | K16: ='Assumptions Sheet'!L10 -> 0.059 | L16: ='Assumptions Sheet'!M10 -> 0.058
B18: EBITDA | C18: =C12-C15 -> 3344 | D18: =D12-D15 -> 4882 | E18: =E12-E15 -> 5292 | F18: =F12-F15 -> 5694 | G18: =G12-G15 -> 8357 | H18: =H12-H15 -> 10438.261 | I18: =I12-I15 -> 12947.578 | J18: =J12-J15 -> 15854.788 | ... L18: =L12-L15 -> 22555.353
B19: EBITDA Margin (%) | C19: =C18/C6 -> 0.11611514 | D19: =D18/D6 -> 0.12032039 | E19: =E18/E6 -> 0.10359408 | F19: =F18/F6 -> 0.0941842 | G19: =G18/G6 -> 0.095416971 | H19: ='Assumptions Sheet'!I11 -> 0.101 | I19: ='Assumptions Sheet'!J11 -> 0.108 | J19: ='Assumptions Sheet'!K11 -> 0.115 | K19: ='Assumptions Sheet'!L11 -> 0.121 | L19: ='Assumptions Sheet'!M11 -> 0.127
B21: Other Income | C21: =HistoricalFS!H24 -> 177 | D21: =HistoricalFS!I24 -> 306 | E21: =HistoricalFS!J24 -> 534 | F21: =HistoricalFS!K24 -> 487 | G21: =HistoricalFS!L24 -> 450 | H21: ='Assumptions Sheet'!I12 -> 495 | I21: ='Assumptions Sheet'!J12 -> 544.5 | J21: ='Assumptions Sheet'!K12 -> 598.95 | K21: ='Assumptions Sheet'!L12 -> 658.845 | L21: ='Assumptions Sheet'!M12 -> 724.7295
B22: Depreciation | C22: =HistoricalFS!H27 -> 399 | D22: =HistoricalFS!I27 -> 441 | E22: =HistoricalFS!J27 -> 584 | F22: =HistoricalFS!K27 -> 693 | G22: =HistoricalFS!L27 -> 826 | H22: ='Assumptions Sheet'!I13 -> 949.9 | I22: ='Assumptions Sheet'!J13 -> 1092.385 | J22: ='Assumptions Sheet'!K13 -> 1256.2427 | K22: ='Assumptions Sheet'!L13 -> 1444.6792 | L22: ='Assumptions Sheet'!M13 -> 1661.381
B24: EBIT | C24: =SUM(C18,C21)-C22 -> 3122 | D24: =SUM(D18,D21)-D22 -> 4747 | E24: =SUM(E18,E21)-E22 -> 5242 | F24: =SUM(F18,F21)-F22 -> 5488 | G24: =SUM(G18,G21)-G22 -> 7981 | H24: =SUM(H18,H21)-H22 -> 9983.3611 | I24: =SUM(I18,I21)-I22 -> 12399.693 | J24: =SUM(J18,J21)-J22 -> 15197.496 | ... L24: =SUM(L18,L21)-L22 -> 21618.701
B25: EBIT Margin (%) | C25: =C24/C6 -> 0.10840654 | D25: =D24/D6 -> 0.11699322 | E25: =E24/E6 -> 0.1026153 | F25: =F24/F6 -> 0.090776763 | G25: =G24/G6 -> 0.09112395 | H25: =H24/H6 -> 0.096598414 | I25: =I24/I6 -> 0.10342991 | J25: =J24/J6 -> 0.11023244 | ... L25: =L24/L6 -> 0.1217261
B27: Interest Expense | C27: =HistoricalFS!H33 -> 218 | D27: =HistoricalFS!I33 -> 300 | E27: =HistoricalFS!J33 -> 619 | F27: =HistoricalFS!K33 -> 953 | G27: =HistoricalFS!L33 -> 1180 | H27: ='Assumptions Sheet'!I14 -> 1392.4 | I27: ='Assumptions Sheet'!J14 -> 1601.26 | J27: ='Assumptions Sheet'!K14 -> 1809.4238 | K27: ='Assumptions Sheet'!L14 -> 2008.4604 | L27: ='Assumptions Sheet'!M14 -> 2209.3065
B29: Earning Before Tax | C29: =C24-C27 -> 2904 | D29: =D24-D27 -> 4447 | E29: =E24-E27 -> 4623 | F29: =F24-F27 -> 4535 | G29: =G24-G27 -> 6801 | H29: =H24-H27 -> 8590.9611 | I29: =I24-I27 -> 10798.433 | J29: =J24-J27 -> 13388.072 | ... L29: =L24-L27 -> 19409.395
B31: Tax | C31: =HistoricalFS!H39 -> 706 | D31: =HistoricalFS!I39 -> 1173 | E31: =HistoricalFS!J39 -> 1127 | F31: =HistoricalFS!K39 -> 1198 | G31: =HistoricalFS!L39 -> 1728 | H31: =H29*H32 -> 2177.8086 | I31: =I29*I32 -> 2737.4027 | J31: =J29*J32 -> 3393.8762 | K31: =K29*K32 -> 4112.576 | L31: =L29*L32 -> 4920.2816
B32: Effective Tax Rate | C32: =C31/C29 -> 0.24311295 | D32: =D31/D29 -> 0.26377333 | E32: =E31/E29 -> 0.24378109 | F32: =F31/F29 -> 0.26416759 | G32: =G31/G29 -> 0.25408028 | H32: ='Assumptions Sheet'!I16 -> 0.2535 | I32: ='Assumptions Sheet'!J16 -> 0.2535 | J32: ='Assumptions Sheet'!K16 -> 0.2535 | K32: ='Assumptions Sheet'!L16 -> 0.2535 | L32: ='Assumptions Sheet'!M16 -> 0.2535
B34: Net Profit | C34: =C29-C31 -> 2198 | D34: =D29-D31 -> 3274 | E34: =E29-E31 -> 3496 | F34: =F29-F31 -> 3337 | G34: =G29-G31 -> 5073 | H34: =H29-H31 -> 6413.1525 | I34: =I29-I31 -> 8061.0301 | J34: =J29-J31 -> 9994.1957 | ... L34: =L29-L31 -> 14489.113
A36: # | B36: ="Balance Sheet"&" - "&'Data Sheet'!B1 -> Balance Sheet - TITAN COMPANY LTD
B37: Particulars | C37: =C5 -> 44651 | D37: =D5 -> 45016 | E37: =E5 -> 45382 | F37: =F5 -> 45747 | G37: =G5 -> 46112 | H37: =H5 -> 46477 | I37: =I5 -> 46842 | J37: =J5 -> 47207 | ... L37: =L5 -> 47937
B38: Equity Share Capital | C38: =HistoricalFS!G56 -> 89 | D38: =HistoricalFS!H56 -> 89 | E38: =HistoricalFS!I56 -> 89 | F38: =HistoricalFS!J56 -> 89 | G38: =HistoricalFS!K56 -> 89 | H38: 89 | I38: 89 | J38: 89 | K38: 89 | L38: 89
B39: Reserves | C39: =HistoricalFS!H57 -> 9214 | D39: =HistoricalFS!I57 -> 11762 | E39: =HistoricalFS!J57 -> 9304 | F39: =HistoricalFS!K57 -> 11535 | G39: =HistoricalFS!L57 -> 15614 | H39: =G39+H34*(1-'Assumptions Sheet'!I15) -> 20295.601 | I39: =H39+I34*(1-'Assumptions Sheet'!J15) -> 26180.153 | J39: =I39+J34*(1-'Assumptions Sheet'!K15) -> 33475.916 | K39: =J39+K34*(1-'Assumptions Sheet'!L15) -> 42316.657 | L39: =K39+L34*(1-'Assumptions Sheet'!M15) -> 52893.709
B40: Borrowings | C40: =HistoricalFS!H58 -> 7275 | D40: =HistoricalFS!I58 -> 9367 | E40: =HistoricalFS!J58 -> 15528 | F40: =HistoricalFS!K58 -> 20777 | G40: =HistoricalFS!L58 -> 30621 | H40: ='Assumptions Sheet'!I35 -> 8730 | I40: ='Assumptions Sheet'!J35 -> 10301.4 | J40: ='Assumptions Sheet'!K35 -> 11949.624 | K40: ='Assumptions Sheet'!L35 -> 13742.068 | L40: ='Assumptions Sheet'!M35 -> 15665.957
B41: Trade Payables | C41: =HistoricalFS!H59 -> 1294 | D41: =HistoricalFS!I59 -> 1214 | E41: =HistoricalFS!J59 -> 1410 | F41: =HistoricalFS!K59 -> 1963 | G41: =HistoricalFS!L59 -> 2864 | H41: ='Assumptions Sheet'!I21*(ForcastedFS!H9/365) -> 3310.0033 | I41: ='Assumptions Sheet'!J21*(ForcastedFS!I9/365) -> 3816.6122 | J41: ='Assumptions Sheet'!K21*(ForcastedFS!J9/365) -> 4362.6637 | K41: ='Assumptions Sheet'!L21*(ForcastedFS!K9/365) -> 4943.2945 | L41: ='Assumptions Sheet'!M21*(ForcastedFS!L9/365) -> 5551.8623
B42: Other Liabilities | C42: =HistoricalFS!H60 -> 3316 | D42: =HistoricalFS!I60 -> 4588 | E42: =HistoricalFS!J60 -> 5216 | F42: =HistoricalFS!K60 -> 6281 | G42: =HistoricalFS!L60 -> 11373 | H42: =H6*'Assumptions Sheet'!I31 -> 11885.149 | I42: =I6*'Assumptions Sheet'!J31 -> 13786.773 | J42: =J6*'Assumptions Sheet'!K31 -> 15854.788 | K42: =K6*'Assumptions Sheet'!L31 -> 18074.459 | L42: =L6*'Assumptions Sheet'!M31 -> 20424.139
B43: Total Liabilities | C43: =SUM(C38:C42) -> 21188 | D43: =SUM(D38:D42) -> 27020 | E43: =SUM(E38:E42) -> 31547 | F43: =SUM(F38:F42) -> 40645 | G43: =SUM(G38:G42) -> 60561 | H43: =SUM(H38:H42) -> 44309.753 | I43: =SUM(I38:I42) -> 54173.938 | J43: =SUM(J38:J42) -> 65731.992 | ... L43: =SUM(L38:L42) -> 94624.667
B45: Fixed Assets Net Block | C45: =HistoricalFS!H63 -> 2544 | D45: =HistoricalFS!I63 -> 2998 | E45: =HistoricalFS!J63 -> 3709 | F45: =HistoricalFS!K63 -> 4062 | G45: =HistoricalFS!L63 -> 6878 | H45: =G45+'Assumptions Sheet'!I26-'Assumptions Sheet'!I13 -> 7064.9403 | I45: =H45+'Assumptions Sheet'!J26-'Assumptions Sheet'!J13 -> 7351.2326 | J45: =I45+'Assumptions Sheet'!K26-'Assumptions Sheet'!K13 -> 7749.4025 | K45: =J45+'Assumptions Sheet'!L26-'Assumptions Sheet'!L13 -> 8190.7539 | L45: =K45+'Assumptions Sheet'!M26-'Assumptions Sheet'!M13 -> 8571.7867
B46: Capital Work in Progress | C46: =HistoricalFS!H64 -> 85 | D46: =HistoricalFS!I64 -> 144 | E46: =HistoricalFS!J64 -> 97 | F46: =HistoricalFS!K64 -> 105 | G46: =HistoricalFS!L64 -> 163 | H46: ='Assumptions Sheet'!I33 -> 95 | I46: ='Assumptions Sheet'!J33 -> 105 | J46: ='Assumptions Sheet'!K33 -> 115 | K46: ='Assumptions Sheet'!L33 -> 125 | L46: ='Assumptions Sheet'!M33 -> 135
B47: Investments | C47: =HistoricalFS!H65 -> 294 | D47: =HistoricalFS!I65 -> 2515 | E47: =HistoricalFS!J65 -> 2345 | F47: =HistoricalFS!K65 -> 1988 | G47: =HistoricalFS!L65 -> 3506 | H47: ='Assumptions Sheet'!I34 -> 329.28 | I47: ='Assumptions Sheet'!J34 -> 368.7936 | J47: ='Assumptions Sheet'!K34 -> 413.04883 | K47: ='Assumptions Sheet'!L34 -> 462.61469 | L47: ='Assumptions Sheet'!M34 -> 518.12845
B48: Other Assets | C48: =HistoricalFS!H66 -> 2518 | D48: =HistoricalFS!I66 -> 2762 | E48: =HistoricalFS!J66 -> 3801 | F48: =HistoricalFS!K66 -> 3654 | G48: =HistoricalFS!L66 -> 4438 | H48: =H6*'Assumptions Sheet'!I32 -> 9094.7226 | I48: =I6*'Assumptions Sheet'!J32 -> 10789.648 | J48: =J6*'Assumptions Sheet'!K32 -> 12408.095 | K48: =K6*'Assumptions Sheet'!L32 -> 14145.229 | L48: =L6*'Assumptions Sheet'!M32 -> 15984.108
B49: Total Current Assets | C49: =SUM(C45:C48) -> 5441 | D49: =SUM(D45:D48) -> 8419 | E49: =SUM(E45:E48) -> 9952 | F49: =SUM(F45:F48) -> 9809 | G49: =SUM(G45:G48) -> 14985 | H49: =SUM(H45:H48) -> 16583.943 | I49: =SUM(I45:I48) -> 18614.674 | J49: =SUM(J45:J48) -> 20685.547 | ... L49: =SUM(L45:L48) -> 25209.024
B51: Receivables | C51: =HistoricalFS!H69 -> 565 | D51: =HistoricalFS!I69 -> 674 | E51: =HistoricalFS!J69 -> 1018 | F51: =HistoricalFS!K69 -> 1068 | G51: =HistoricalFS!L69 -> 916 | H51: ='Assumptions Sheet'!I20*(ForcastedFS!H6/365) -> 1274.1672 | I51: ='Assumptions Sheet'!J20*(ForcastedFS!I6/365) -> 1642.26 | J51: ='Assumptions Sheet'!K20*(ForcastedFS!J6/365) -> 2077.4589 | K51: ='Assumptions Sheet'!L20*(ForcastedFS!K6/365) -> 2368.3031 | L51: ='Assumptions Sheet'!M20*(ForcastedFS!L6/365) -> 2676.1825
B52: Inventory | C52: =HistoricalFS!H70 -> 13609 | D52: =HistoricalFS!I70 -> 16584 | E52: =HistoricalFS!J70 -> 19051 | F52: =HistoricalFS!K70 -> 28184 | G52: =HistoricalFS!L70 -> 42743 | H52: ='Assumptions Sheet'!I22*(ForcastedFS!H9/365) -> 48467.906 | I52: ='Assumptions Sheet'!J22*(ForcastedFS!I9/365) -> 54523.032 | J52: ='Assumptions Sheet'!K22*(ForcastedFS!J9/365) -> 60765.672 | K52: ='Assumptions Sheet'!L22*(ForcastedFS!K9/365) -> 67087.569 | L52: ='Assumptions Sheet'!M22*(ForcastedFS!L9/365) -> 73363.895
B53: Cash & Bank | C53: =HistoricalFS!H71 -> 1573 | D53: =HistoricalFS!I71 -> 1343 | E53: =HistoricalFS!J71 -> 1526 | F53: =HistoricalFS!K71 -> 1584 | G53: =HistoricalFS!L71 -> 1917 | H53: =H87 -> -22016.262 | I53: =I87 -> -20606.028 | J53: =J87 -> -17796.686 | K53: =K87 -> -13213.991 | L53: =L87 -> -6624.4336
B54: Total Non Current Assets | C54: =SUM(C51:C53) -> 15747 | D54: =SUM(D51:D53) -> 18601 | E54: =SUM(E51:E53) -> 21595 | F54: =SUM(F51:F53) -> 30836 | G54: =SUM(G51:G53) -> 45576 | H54: =SUM(H51:H53) -> 27725.811 | I54: =SUM(I51:I53) -> 35559.264 | J54: =SUM(J51:J53) -> 45046.446 | ... L54: =SUM(L51:L53) -> 69415.644
B56: Total Assets | C56: =SUM(C54,C49) -> 21188 | D56: =SUM(D54,D49) -> 27020 | E56: =SUM(E54,E49) -> 31547 | F56: =SUM(F54,F49) -> 40645 | G56: =SUM(G54,G49) -> 60561 | H56: =SUM(H54,H49) -> 44309.753 | I56: =SUM(I54,I49) -> 54173.938 | J56: =SUM(J54,J49) -> 65731.992 | ... L56: =SUM(L54,L49) -> 94624.667
B58: Check | C58: =IF(ROUND(C56-C43,0)=0,"TRUE","FALSE") -> TRUE | D58: =IF(ROUND(D56-D43,0)=0,"TRUE","FALSE") -> TRUE | E58: =IF(ROUND(E56-E43,0)=0,"TRUE","FALSE") -> TRUE | F58: =IF(ROUND(F56-F43,0)=0,"TRUE","FALSE") -> TRUE | G58: =IF(ROUND(G56-G43,0)=0,"TRUE","FALSE") -> TRUE | H58: =IF(ROUND(H56-H43,0)=0,"TRUE","FALSE") -> TRUE | I58: =IF(ROUND(I56-I43,0)=0,"TRUE","FALSE") -> TRUE | J58: =IF(ROUND(J56-J43,0)=0,"TRUE","FALSE") -> TRUE | ... L58: =IF(ROUND(L56-L43,0)=0,"TRUE","FALSE") -> TRUE
A60: # | B60: ="Balance Sheet"&" - "&'Data Sheet'!B1 -> Balance Sheet - TITAN COMPANY LTD
B61: Particulars | C61: =C37 -> 44651 | D61: =D37 -> 45016 | E61: =E37 -> 45382 | F61: =F37 -> 45747 | G61: =G37 -> 46112 | H61: =H37 -> 46477 | I61: =I37 -> 46842 | J61: =J37 -> 47207 | ... L61: =L37 -> 47937
B62: A. Cash Flow From Operations (CFO)
B63: Net Profit (PAT) [post-tax] | C63: =C34 -> 2198 | D63: =D34 -> 3274 | E63: =E34 -> 3496 | F63: =F34 -> 3337 | G63: =G34 -> 5073 | H63: =H34 -> 6413.1525 | I63: =I34 -> 8061.0301 | J63: =J34 -> 9994.1957 | ... L63: =L34 -> 14489.113
B64: Add: Depreciation | C64: =C22 -> 399 | D64: =D22 -> 441 | E64: =E22 -> 584 | F64: =F22 -> 693 | G64: =G22 -> 826 | H64: =H22 -> 949.9 | I64: =I22 -> 1092.385 | J64: =J22 -> 1256.2427 | ... L64: =L22 -> 1661.381
B66: Working Capital Change:
B67: ( - ) Increase in Receivables | D67: =-(D51-C51) -> -109 | E67: =-(E51-D51) -> -344 | F67: =-(F51-E51) -> -50 | G67: =-(G51-F51) -> 152 | H67: =-(H51-G51) -> -358.16723 | I67: =-(I51-H51) -> -368.09276 | J67: =-(J51-I51) -> -435.1989 | K67: =-(K51-J51) -> -290.84424 | L67: =-(L51-K51) -> -307.87941
B68: ( - ) Increase in Inventory | D68: =-(D52-C52) -> -2975 | E68: =-(E52-D52) -> -2467 | F68: =-(F52-E52) -> -9133 | G68: =-(G52-F52) -> -14559 | H68: =-(H52-G52) -> -5724.9058 | I68: =-(I52-H52) -> -6055.1258 | J68: =-(J52-I52) -> -6242.6408 | K68: =-(K52-J52) -> -6321.8963 | L68: =-(L52-K52) -> -6276.3262
B69: ( + ) Increase in Creditors | D69: =(D41-C41) -> -80 | E69: =(E41-D41) -> 196 | F69: =(F41-E41) -> 553 | G69: =(G41-F41) -> 901 | H69: =(H41-G41) -> 446.00332 | I69: =(I41-H41) -> 506.60889 | J69: =(J41-I41) -> 546.05145 | K69: =(K41-J41) -> 580.63087 | L69: =(L41-K41) -> 608.56778
B70: ( +/- ) Other Working Capital Items | D70: =-(D48-C48)+(D42-C42) -> 1028 | E70: =-(E48-D48)+(E42-D42) -> -411 | F70: =-(F48-E48)+(F42-E42) -> 1212 | G70: =-(G48-F48)+(G42-F42) -> 4308 | H70: =-(H48-G48)+(H42-G42) -> -4144.5738 | I70: =-(I48-H48)+(I42-H42) -> 206.69824 | J70: =-(J48-I48)+(J42-I42) -> 449.56867 | K70: =-(K48-J48)+(K42-J42) -> 482.53704 | L70: =-(L48-K48)+(L42-K42) -> 510.79993
B71: (Memo) Tax already reflected in PAT above | C71: =-C31 -> -706 | D71: =-D31 -> -1173 | E71: =-E31 -> -1127 | F71: =-F31 -> -1198 | G71: =-G31 -> -1728 | H71: =-H31 -> -2177.8086 | I71: =-I31 -> -2737.4027 | J71: =-J31 -> -3393.8762 | ... L71: =-L31 -> -4920.2816
B72: CFO | D72: =SUM(D67:D70,D63:D64) -> 1579 | E72: =SUM(E67:E70,E63:E64) -> 1054 | F72: =SUM(F67:F70,F63:F64) -> -3388 | G72: =SUM(G67:G70,G63:G64) -> -3299 | H72: =SUM(H67:H70,H63:H64) -> -2418.591 | I72: =SUM(I67:I70,I63:I64) -> 3443.5036 | J72: =SUM(J67:J70,J63:J64) -> 5568.2189 | K72: =SUM(K67:K70,K63:K64) -> 8005.7101 | L72: =SUM(L67:L70,L63:L64) -> 10685.656
B74: B. Cash Flow From Investing (CFI)
B75: ( - ) Capex | C75: =-'Assumptions Sheet'!D26 -> -224 | D75: =-'Assumptions Sheet'!E26 -> -432 | E75: =-'Assumptions Sheet'!F26 -> -691 | F75: =-'Assumptions Sheet'!G26 -> -494 | G75: =-'Assumptions Sheet'!H26 -> -902 | H75: =-'Assumptions Sheet'!I26 -> -1136.8403 | I75: =-'Assumptions Sheet'!J26 -> -1378.6773 | J75: =-'Assumptions Sheet'!K26 -> -1654.4127 | ... L75: =-'Assumptions Sheet'!M26 -> -2042.4139
B76: ( - ) Increase in Investments | D76: =-(D47-C47) -> -2221 | E76: =-(E47-D47) -> 170 | F76: =-(F47-E47) -> 357 | G76: =-(G47-F47) -> -1518 | H76: =-(H47-G47) -> 3176.72 | I76: =-(I47-H47) -> -39.5136 | J76: =-(J47-I47) -> -44.255232 | K76: =-(K47-J47) -> -49.56586 | L76: =-(L47-K47) -> -55.513763
B77: ( - ) Increase in CWIP | D77: =-(D46-C46) -> -59 | E77: =-(E46-D46) -> 47 | F77: =-(F46-E46) -> -8 | G77: =-(G46-F46) -> -58 | H77: =-(H46-G46) -> 68 | I77: =-(I46-H46) -> -10 | J77: =-(J46-I46) -> -10 | K77: =-(K46-J46) -> -10 | L77: =-(L46-K46) -> -10
B78: CFI | D78: =SUM(D75:D77) -> -2712 | E78: =SUM(E75:E77) -> -474 | F78: =SUM(F75:F77) -> -145 | G78: =SUM(G75:G77) -> -2478 | H78: =SUM(H75:H77) -> 2107.8797 | I78: =SUM(I75:I77) -> -1428.1909 | J78: =SUM(J75:J77) -> -1708.6679 | K78: =SUM(K75:K77) -> -1945.5964 | L78: =SUM(L75:L77) -> -2107.9276
B80: C. Cash Flow From Financing (CFF)
B81: ( - ) Dividend Paid | C81: =-C34*'Assumptions Sheet'!D15 -> -667.5 | D81: =-D34*'Assumptions Sheet'!E15 -> -890 | E81: =-E34*'Assumptions Sheet'!F15 -> -979 | F81: =-F34*'Assumptions Sheet'!G15 -> -979 | G81: =-G34*'Assumptions Sheet'!H15 -> -1335 | H81: =-H34*'Assumptions Sheet'!I15 -> -1731.5512 | I81: =-I34*'Assumptions Sheet'!J15 -> -2176.4781 | J81: =-J34*'Assumptions Sheet'!K15 -> -2698.4328 | ... L81: =-L34*'Assumptions Sheet'!M15 -> -3912.0606
B82: (+/-) Net Borrowing Change | D82: =D40-C40 -> 2092 | E82: =E40-D40 -> 6161 | F82: =F40-E40 -> 5249 | G82: =G40-F40 -> 9844 | H82: =H40-G40 -> -21891 | I82: =I40-H40 -> 1571.4 | J82: =J40-I40 -> 1648.224 | K82: =K40-J40 -> 1792.4436 | L82: =L40-K40 -> 1923.8895
B83: CFF | C83: =SUM(C81:C82) -> -667.5 | D83: =SUM(D81:D82) -> 1202 | E83: =SUM(E81:E82) -> 5182 | F83: =SUM(F81:F82) -> 4270 | G83: =SUM(G81:G82) -> 8509 | H83: =SUM(H81:H82) -> -23622.551 | I83: =SUM(I81:I82) -> -605.07811 | J83: =SUM(J81:J82) -> -1050.2088 | ... L83: =SUM(L81:L82) -> -1988.1711
B85: Net Change in Cash | D85: =SUM(D83,D78,D72) -> 69 | E85: =SUM(E83,E78,E72) -> 5762 | F85: =SUM(F83,F78,F72) -> 737 | G85: =SUM(G83,G78,G72) -> 2732 | H85: =SUM(H83,H78,H72) -> -23933.262 | I85: =SUM(I83,I78,I72) -> 1410.2346 | J85: =SUM(J83,J78,J72) -> 2809.3421 | K85: =SUM(K83,K78,K72) -> 4582.6944 | L85: =SUM(L83,L78,L72) -> 6589.5577
B86: Opening Cash | D86: =C53 -> 1573 | E86: =D53 -> 1343 | F86: =E53 -> 1526 | G86: =F53 -> 1584 | H86: =G53 -> 1917 | I86: =H53 -> -22016.262 | J86: =I53 -> -20606.028 | K86: =J53 -> -17796.686 | L86: =K53 -> -13213.991
B87: Closing Cash | D87: =SUM(D85:D86) -> 1642 | E87: =SUM(E85:E86) -> 7105 | F87: =SUM(F85:F86) -> 2263 | G87: =SUM(G85:G86) -> 4316 | H87: =SUM(H85:H86) -> -22016.262 | I87: =SUM(I85:I86) -> -20606.028 | J87: =SUM(J85:J86) -> -17796.686 | K87: =SUM(K85:K86) -> -13213.991 | L87: =SUM(L85:L86) -> -6624.4336

Sheet Beta-Regression
B2: Beta Regression
U3: Beta | V3: =SLOPE(W8:W261,H8:H261) -> 0.60935632 | Y3: Beta | Z3: =SLOPE(AA8:AA261,H8:H261) -> 1.1254699 | AC3: Beta | AD3: =SLOPE(AE8:AE261,H8:H261) -> 1.1272013
B4: Titan Company Ltd Return | F4: NIFTY Return | U4: Thangamayil Jew. | Y4: Kalyan Jewellers | AC4: Rajesh Exports
B6: Date | C6: Close | D6: Weekly Return | F6: Date | G6: Close | H6: Weekly Return | J6: Beta Drifting | U6: Date | V6: Close | W6: Weekly Return | Y6: Date | Z6: Close | AA6: Weekly Return | AC6: Date | AD6: Close | AE6: Weekly Return
B7: 46213.646 | C7: 4584.4 | F7: 46213.646 | G7: 24206.9 | U7: 46213.646 | V7: 6540.5 | Y7: 46213.646 | Z7: 476.15 | AC7: 46213.646 | AD7: 93.67
B8: 46206.646 | C8: 4461.1 | D8: =C8/C7-1 -> -0.026895559 | F8: 46206.646 | G8: 24270.85 | H8: =G8/G7-1 -> 0.0026418087 | J8: Levered Raw Beta | M8: =N17 -> 1.1357276 | U8: 46206.646 | V8: 6159.5 | W8: =V8/V7-1 -> -0.058252427 | Y8: 46206.646 | Z8: 382.05 | AA8: =Z8/Z7-1 -> -0.1976268 | AC8: 46206.646 | AD8: 95.02 | AE8: =AD8/AD7-1 -> 0.014412298
B9: 46198.646 | C9: 4291.3 | D9: =C9/C8-1 -> -0.038062361 | F9: 46198.646 | G9: 24056 | H9: =G9/G8-1 -> -0.0088521828 | J9: Raw Beta Weight | M9: 0.75 | U9: 46198.646 | V9: 5594.2 | W9: =V9/V8-1 -> -0.09177693 | Y9: 46198.646 | Z9: 377.8 | AA9: =Z9/Z8-1 -> -0.011124198 | AC9: 46198.646 | AD9: 97.02 | AE9: =AD9/AD8-1 -> 0.0210482
B10: 46192.646 | C10: 4419.9 | D10: =C10/C9-1 -> 0.029967609 | F10: 46192.646 | G10: 24013.1 | H10: =G10/G9-1 -> -0.0017833389 | U10: 46192.646 | V10: 5454.6 | W10: =V10/V9-1 -> -0.024954417 | Y10: 46192.646 | Z10: 383.5 | AA10: =Z10/Z9-1 -> 0.015087348 | AC10: 46192.646 | AD10: 97.51 | AE10: =AD10/AD9-1 -> 0.0050505051
B11: 46185.646 | C11: 4184 | D11: =C11/C10-1 -> -0.053372248 | F11: 46185.646 | G11: 23622.9 | H11: =G11/G10-1 -> -0.016249464 | J11: Market Beta | M11: 1 | U11: 46185.646 | V11: 5478.7 | W11: =V11/V10-1 -> 0.0044182892 | Y11: 46185.646 | Z11: 344.75 | AA11: =Z11/Z10-1 -> -0.10104302 | AC11: 46185.646 | AD11: 76.41 | AE11: =AD11/AD10-1 -> -0.21638806
B12: 46178.646 | C12: 4260.2 | D12: =C12/C11-1 -> 0.018212237 | F12: 46178.646 | G12: 23366.7 | H12: =G12/G11-1 -> -0.010845408 | J12: Market Beta Weight | M12: 0.25 | U12: 46178.646 | V12: 5351.9 | W12: =V12/V11-1 -> -0.023144177 | Y12: 46178.646 | Z12: 371.85 | AA12: =Z12/Z11-1 -> 0.078607687 | AC12: 46178.646 | AD12: 98.73 | AE12: =AD12/AD11-1 -> 0.29210836
B13: 46171.646 | C13: 4074.9 | D13: =C13/C12-1 -> -0.043495611 | F13: 46171.646 | G13: 23547.75 | H13: =G13/G12-1 -> 0.0077482058 | U13: 46171.646 | V13: 4204.9 | W13: =V13/V12-1 -> -0.21431641 | Y13: 46171.646 | Z13: 355.05 | AA13: =Z13/Z12-1 -> -0.045179508 | AC13: 46171.646 | AD13: 118.33 | AE13: =AD13/AD12-1 -> 0.19852122
B14: 46164.646 | C14: 4079.8 | D14: =C14/C13-1 -> 0.0012024835 | F14: 46164.646 | G14: 23719.3 | H14: =G14/G13-1 -> 0.0072851971 | J14: Adjusted Beta | M14: =(M8*M9)+(M11*M12) -> 1.1017957 | U14: 46164.646 | V14: 3817.3 | W14: =V14/V13-1 -> -0.092178173 | Y14: 46164.646 | Z14: 352.4 | AA14: =Z14/Z13-1 -> -0.0074637375 | AC14: 46164.646 | AD14: 107.44 | AE14: =AD14/AD13-1 -> -0.092030761
B15: 46157.646 | C15: 4169.1 | D15: =C15/C14-1 -> 0.021888328 | F15: 46157.646 | G15: 23643.5 | H15: =G15/G14-1 -> -0.0031957098 | U15: 46157.646 | V15: 3594.2 | W15: =V15/V14-1 -> -0.05844445 | Y15: 46157.646 | Z15: 353.05 | AA15: =Z15/Z14-1 -> 0.0018444949 | AC15: 46157.646 | AD15: 109.77 | AE15: =AD15/AD14-1 -> 0.021686523
B16: 46150.646 | C16: 4509 | D16: =C16/C15-1 -> 0.081528387 | F16: 46150.646 | G16: 24176.15 | H16: =G16/G15-1 -> 0.02252839 | J16: SUMMARY OUTPUT | U16: 46150.646 | V16: 4246.7 | W16: =V16/V15-1 -> 0.18154249 | Y16: 46150.646 | Z16: 424.55 | AA16: =Z16/Z15-1 -> 0.20252089 | AC16: 46150.646 | AD16: 121.99 | AE16: =AD16/AD15-1 -> 0.11132368
B17: 46142.646 | C17: 4385.2 | D17: =C17/C16-1 -> -0.027456199 | F17: 46142.646 | G17: 23997.55 | H17: =G17/G16-1 -> -0.0073874459 | M17: Beta | N17: =K33 -> 1.1357276 | U17: 46142.646 | V17: 3955.8 | W17: =V17/V16-1 -> -0.068500247 | Y17: 46142.646 | Z17: 412.75 | AA17: =Z17/Z16-1 -> -0.027794135 | AC17: 46142.646 | AD17: 119.2 | AE17: =AD17/AD16-1 -> -0.022870727
B18: 46136.646 | C18: 4410 | D18: =C18/C17-1 -> 0.0056553863 | F18: 46136.646 | G18: 23897.95 | H18: =G18/G17-1 -> -0.0041504237 | J18: Regression Statistics | U18: 46136.646 | V18: 3799.3 | W18: =V18/V17-1 -> -0.039562162 | Y18: 46136.646 | Z18: 405.3 | AA18: =Z18/Z17-1 -> -0.018049667 | AC18: 46136.646 | AD18: 126.81 | AE18: =AD18/AD17-1 -> 0.063842282
B19: 46129.646 | C19: 4525.9 | D19: =C19/C18-1 -> 0.026281179 | F19: 46129.646 | G19: 24353.55 | H19: =G19/G18-1 -> 0.019064397 | J19: Multiple R | K19: 0.60488736 | U19: 46129.646 | V19: 4210.6 | W19: =V19/V18-1 -> 0.10825678 | Y19: 46129.646 | Z19: 426.85 | AA19: =Z19/Z18-1 -> 0.053170491 | AC19: 46129.646 | AD19: 126.31 | AE19: =AD19/AD18-1 -> -0.0039429067
B20: 46122.646 | C20: 4505 | D20: =C20/C19-1 -> -0.0046178661 | F20: 46122.646 | G20: 24050.6 | H20: =G20/G19-1 -> -0.012439665 | J20: R Square | K20: 0.36588872 | U20: 46122.646 | V20: 4138.8 | W20: =V20/V19-1 -> -0.017052202 | Y20: 46122.646 | Z20: 449.15 | AA20: =Z20/Z19-1 -> 0.052243177 | AC20: 46122.646 | AD20: 109.76 | AE20: =AD20/AD19-1 -> -0.13102684
B21: 46114.646 | C21: 4097.2 | D21: =C21/C20-1 -> -0.090521643 | F21: 46114.646 | G21: 22713.1 | H21: =G21/G20-1 -> -0.055611918 | J21: Adjusted R Square | K21: 0.3633724 | U21: 46114.646 | V21: 3543.8 | W21: =V21/V20-1 -> -0.14376148 | Y21: 46114.646 | Z21: 394.35 | AA21: =Z21/Z20-1 -> -0.12200824 | AC21: 46114.646 | AD21: 87.28 | AE21: =AD21/AD20-1 -> -0.2048105
B22: 46108.646 | C22: 3981.5 | D22: =C22/C21-1 -> -0.028238797 | F22: 46108.646 | G22: 22819.6 | H22: =G22/G21-1 -> 0.004688924 | J22: Standard Error | K22: 0.027833702 | U22: 46108.646 | V22: 3431 | W22: =V22/V21-1 -> -0.031830239 | Y22: 46108.646 | Z22: 388.35 | AA22: =Z22/Z21-1 -> -0.015214911 | AC22: 46108.646 | AD22: 84.61 | AE22: =AD22/AD21-1 -> -0.030591201
B23: 46101.646 | C23: 4106.6 | D23: =C23/C22-1 -> 0.031420319 | F23: 46101.646 | G23: 23114.5 | H23: =G23/G22-1 -> 0.012923101 | J23: Observations | K23: 254 | U23: 46101.646 | V23: 3328.8 | W23: =V23/V22-1 -> -0.029787234 | Y23: 46101.646 | Z23: 382.7 | AA23: =Z23/Z22-1 -> -0.014548732 | AC23: 46101.646 | AD23: 94.01 | AE23: =AD23/AD22-1 -> 0.11109798
B24: 46094.646 | C24: 4073.2 | D24: =C24/C23-1 -> -0.0081332489 | F24: 46094.646 | G24: 23151.1 | H24: =G24/G23-1 -> 0.0015834217 | U24: 46094.646 | V24: 3504.1 | W24: =V24/V23-1 -> 0.05266162 | Y24: 46094.646 | Z24: 379 | AA24: =Z24/Z23-1 -> -0.0096681474 | AC24: 46094.646 | AD24: 110.06 | AE24: =AD24/AD23-1 -> 0.17072652
B25: 46087.646 | C25: 4244.6 | D25: =C25/C24-1 -> 0.042079937 | F25: 46087.646 | G25: 24450.45 | H25: =G25/G24-1 -> 0.056124763 | J25: ANOVA | U25: 46087.646 | V25: 3695.2 | W25: =V25/V24-1 -> 0.054536115 | Y25: 46087.646 | Z25: 395.55 | AA25: =Z25/Z24-1 -> 0.043667546 | AC25: 46087.646 | AD25: 118.89 | AE25: =AD25/AD24-1 -> 0.080228966
B26: 46080.646 | C26: 4327.5 | D26: =C26/C25-1 -> 0.019530698 | F26: 46080.646 | G26: 25178.65 | H26: =G26/G25-1 -> 0.029782683 | K26: df | L26: SS | M26: MS | N26: F | O26: Significance F | U26: 46080.646 | V26: 3959.2 | W26: =V26/V25-1 -> 0.071444036 | Y26: 46080.646 | Z26: 410.1 | AA26: =Z26/Z25-1 -> 0.036784224 | AC26: 46080.646 | AD26: 143.81 | AE26: =AD26/AD25-1 -> 0.20960552
B27: 46073.646 | C27: 4236.4 | D27: =C27/C26-1 -> -0.021051415 | F27: 46073.646 | G27: 25571.25 | H27: =G27/G26-1 -> 0.015592575 | J27: Regression | K27: 1 | L27: 0.11264866 | M27: 0.11264866 | N27: 145.40659 | O27: 9.7514758e-27 | U27: 46073.646 | V27: 3556.6 | W27: =V27/V26-1 -> -0.10168721 | Y27: 46073.646 | Z27: 401.2 | AA27: =Z27/Z26-1 -> -0.021702024 | AC27: 46073.646 | AD27: 157.91 | AE27: =AD27/AD26-1 -> 0.098046033
B28: 46066.646 | C28: 4179.2 | D28: =C28/C27-1 -> -0.01350203 | F28: 46066.646 | G28: 25471.1 | H28: =G28/G27-1 -> -0.0039165078 | J28: Residual | K28: 252 | L28: 0.19522817 | M28: 0.00077471496 | U28: 46066.646 | V28: 3581.6 | W28: =V28/V27-1 -> 0.0070291852 | Y28: 46066.646 | Z28: 418.05 | AA28: =Z28/Z27-1 -> 0.041999003 | AC28: 46066.646 | AD28: 177.92 | AE28: =AD28/AD27-1 -> 0.12671775
B29: 46059.646 | C29: 4141 | D29: =C29/C28-1 -> -0.0091405054 | F29: 46059.646 | G29: 25693.7 | H29: =G29/G28-1 -> 0.0087393163 | J29: Total | K29: 253 | L29: 0.30787683 | U29: 46059.646 | V29: 3400.2 | W29: =V29/V28-1 -> -0.050647755 | Y29: 46059.646 | Z29: 380.25 | AA29: =Z29/Z28-1 -> -0.090419806 | AC29: 46059.646 | AD29: 172.72 | AE29: =AD29/AD28-1 -> -0.029226619
B30: 46052.646 | C30: 3977.4 | D30: =C30/C29-1 -> -0.039507365 | F30: 46052.646 | G30: 25320.65 | H30: =G30/G29-1 -> -0.014519123 | U30: 46052.646 | V30: 3320.6 | W30: =V30/V29-1 -> -0.023410388 | Y30: 46052.646 | Z30: 361.65 | AA30: =Z30/Z29-1 -> -0.048915187 | AC30: 46052.646 | AD30: 162.36 | AE30: =AD30/AD29-1 -> -0.059981473
B31: 46045.646 | C31: 4021.8 | D31: =C31/C30-1 -> 0.011163071 | F31: 46045.646 | G31: 25048.65 | H31: =G31/G30-1 -> -0.01074222 | K31: Coefficients | L31: Standard Error | M31: t Stat | N31: P-value | O31: Lower 95% | P31: Upper 95% | Q31: Lower 95.0% | R31: Upper 95.0% | U31: 46045.646 | V31: 3568 | W31: =V31/V30-1 -> 0.074504608 | Y31: 46045.646 | Z31: 367.2 | AA31: =Z31/Z30-1 -> 0.015346329 | AC31: 46045.646 | AD31: 163.18 | AE31: =AD31/AD30-1 -> 0.0050505051
B32: 46038.646 | C32: 4196.9 | D32: =C32/C31-1 -> 0.043537719 | F32: 46038.646 | G32: 25694.35 | H32: =G32/G31-1 -> 0.025777836 | J32: Intercept | K32: -0.0015959279 | L32: 0.0017520929 | M32: -0.91086946 | N32: 0.36323461 | O32: -0.0050465387 | P32: 0.001854683 | Q32: -0.0050465387 | R32: 0.001854683 | U32: 46038.646 | V32: 3764 | W32: =V32/V31-1 -> 0.054932735 | Y32: 46038.646 | Z32: 467.5 | AA32: =Z32/Z31-1 -> 0.27314815 | AC32: 46038.646 | AD32: 173.32 | AE32: =AD32/AD31-1 -> 0.062139968
B33: 46031.646 | C33: 4201.8 | D33: =C33/C32-1 -> 0.0011675284 | F33: 46031.646 | G33: 25683.3 | H33: =G33/G32-1 -> -0.00043005563 | J33: X Variable 1 | K33: 1.1357276 | L33: 0.094185084 | M33: 12.058465 | N33: 9.7514758e-27 | O33: 0.95023735 | P33: 1.3212178 | Q33: 0.95023735 | R33: 1.3212178 | U33: 46031.646 | V33: 3620.4 | W33: =V33/V32-1 -> -0.038150903 | Y33: 46031.646 | Z33: 506.9 | AA33: =Z33/Z32-1 -> 0.084278075 | AC33: 46031.646 | AD33: 168.68 | AE33: =AD33/AD32-1 -> -0.02677129
B34: 46024.646 | C34: 4051.7 | D34: =C34/C33-1 -> -0.035722785 | F34: 46024.646 | G34: 26328.55 | H34: =G34/G33-1 -> 0.025123329 | U34: 46024.646 | V34: 3229.5 | W34: =V34/V33-1 -> -0.10797149 | Y34: 46024.646 | Z34: 495.7 | AA34: =Z34/Z33-1 -> -0.022095088 | AC34: 46024.646 | AD34: 180.99 | AE34: =AD34/AD33-1 -> 0.072978421
B35: 46017.646 | C35: 3992 | D35: =C35/C34-1 -> -0.014734556 | F35: 46017.646 | G35: 26042.3 | H35: =G35/G34-1 -> -0.010872228 | U35: 46017.646 | V35: 3208.3 | W35: =V35/V34-1 -> -0.0065644837 | Y35: 46017.646 | Z35: 491.15 | AA35: =Z35/Z34-1 -> -0.0091789389 | AC35: 46017.646 | AD35: 212.78 | AE35: =AD35/AD34-1 -> 0.17564506
B36: 46010.646 | C36: 3930.1 | D36: =C36/C35-1 -> -0.015506012 | F36: 46010.646 | G36: 25966.4 | H36: =G36/G35-1 -> -0.0029144891 | U36: 46010.646 | V36: 3339.5 | W36: =V36/V35-1 -> 0.040893931 | Y36: 46010.646 | Z36: 484.85 | AA36: =Z36/Z35-1 -> -0.012827039 | AC36: 46010.646 | AD36: 204.36 | AE36: =AD36/AD35-1 -> -0.039571388
B37: 46003.646 | C37: 3880.2 | D37: =C37/C36-1 -> -0.012696878 | F37: 46003.646 | G37: 26046.95 | H37: =G37/G36-1 -> 0.0031020858 | U37: 46003.646 | V37: 3196.6 | W37: =V37/V36-1 -> -0.042790837 | Y37: 46003.646 | Z37: 479.3 | AA37: =Z37/Z36-1 -> -0.011446839 | AC37: 46003.646 | AD37: 192.25 | AE37: =AD37/AD36-1 -> -0.059258172
B38: 45996.646 | C38: 3813.3 | D38: =C38/C37-1 -> -0.017241379 | F38: 45996.646 | G38: 26186.45 | H38: =G38/G37-1 -> 0.0053557134 | U38: 45996.646 | V38: 3223.3 | W38: =V38/V37-1 -> 0.0083526247 | Y38: 45996.646 | Z38: 492.5 | AA38: =Z38/Z37-1 -> 0.027540163 | AC38: 45996.646 | AD38: 184.65 | AE38: =AD38/AD37-1 -> -0.03953186
B39: 45989.646 | C39: 3907.7 | D39: =C39/C38-1 -> 0.024755461 | F39: 45989.646 | G39: 26202.95 | H39: =G39/G38-1 -> 0.00063009686 | U39: 45989.646 | V39: 3254 | W39: =V39/V38-1 -> 0.0095244005 | Y39: 45989.646 | Z39: 505.35 | AA39: =Z39/Z38-1 -> 0.026091371 | AC39: 45989.646 | AD39: 186.53 | AE39: =AD39/AD38-1 -> 0.010181424
B40: 45982.646 | C40: 3904.2 | D40: =C40/C39-1 -> -0.00089566753 | F40: 45982.646 | G40: 26068.15 | H40: =G40/G39-1 -> -0.0051444589 | U40: 45982.646 | V40: 3025.4 | W40: =V40/V39-1 -> -0.070251998 | Y40: 45982.646 | Z40: 496.45 | AA40: =Z40/Z39-1 -> -0.017611556 | AC40: 45982.646 | AD40: 186.13 | AE40: =AD40/AD39-1 -> -0.0021444272
B41: 45975.646 | C41: 3829.2 | D41: =C41/C40-1 -> -0.019210081 | F41: 45975.646 | G41: 25910.05 | H41: =G41/G40-1 -> -0.0060648723 | U41: 45975.646 | V41: 3296 | W41: =V41/V40-1 -> 0.089442718 | Y41: 45975.646 | Z41: 495.5 | AA41: =Z41/Z40-1 -> -0.0019135865 | AC41: 45975.646 | AD41: 187.33 | AE41: =AD41/AD40-1 -> 0.0064471069
B42: 45968.646 | C42: 3769.3 | D42: =C42/C41-1 -> -0.015642954 | F42: 45968.646 | G42: 25492.3 | H42: =G42/G41-1 -> -0.016123087 | U42: 45968.646 | V42: 3389.3 | W42: =V42/V41-1 -> 0.028307039 | Y42: 45968.646 | Z42: 512.8 | AA42: =Z42/Z41-1 -> 0.034914228 | AC42: 45968.646 | AD42: 179.8 | AE42: =AD42/AD41-1 -> -0.040196445
B43: 45961.646 | C43: 3746.7 | D43: =C43/C42-1 -> -0.0059958082 | F43: 45961.646 | G43: 25722.1 | H43: =G43/G42-1 -> 0.0090144867 | U43: 45961.646 | V43: 2169.6 | W43: =V43/V42-1 -> -0.35986782 | Y43: 45961.646 | Z43: 509.7 | AA43: =Z43/Z42-1 -> -0.0060452418 | AC43: 45961.646 | AD43: 181.91 | AE43: =AD43/AD42-1 -> 0.011735261
B44: 45954.646 | C44: 3714.9 | D44: =C44/C43-1 -> -0.008487469 | F44: 45954.646 | G44: 25795.15 | H44: =G44/G43-1 -> 0.0028399703 | U44: 45954.646 | V44: 2039.5 | W44: =V44/V43-1 -> -0.059964971 | Y44: 45954.646 | Z44: 495.3 | AA44: =Z44/Z43-1 -> -0.028251913 | AC44: 45954.646 | AD44: 180.29 | AE44: =AD44/AD43-1 -> -0.0089055027
B45: 45947.646 | C45: 3674.8 | D45: =C45/C44-1 -> -0.010794369 | F45: 45947.646 | G45: 25709.85 | H45: =G45/G44-1 -> -0.0033068232 | U45: 45947.646 | V45: 1962.9 | W45: =V45/V44-1 -> -0.037558225 | Y45: 45947.646 | Z45: 489.85 | AA45: =Z45/Z44-1 -> -0.011003432 | AC45: 45947.646 | AD45: 177.86 | AE45: =AD45/AD44-1 -> -0.013478285
... B261: 44400.646 | C261: 1700.95 | D261: =C261/C260-1 -> -0.0079321105 | F261: 44400.646 | G261: 15856.05 | H261: =G261/G260-1 -> 0.0058998734 | U261: 44400.646 | V261: 403.68 | W261: =V261/V260-1 -> -0.046327577 | Y261: 44400.646 | Z261: 72.3 | AA261: =Z261/Z260-1 -> 0.019027484 | AC261: 44400.646 | AD261: 580.5 | AE261: =AD261/AD260-1 -> -0.063634164

Sheet Rm
B2: Return on Market
B4: Year | C4: Annual | E4: Average Return | G4: =AVERAGE(C5:C30) -> 0.15149231
B5: 2000 | C5: -0.1465 | E5: Dividend Yield | G5: 1.30%1
B6: 2001 | C6: -0.1618 | E6: Total Market Return | G6: =SUM(G4:G5) -> 0.15149231
B7: 2002 | C7: 0.0325
B8: 2003 | C8: 0.719 | E8: Geometric Mean | G8: =EXP(SUMPRODUCT(LN(1+C5:C30))/COUNT(C5:C30))-1 -> 0.11650334
B9: 2004 | C9: 0.1068 | E9: Dividend Yield | G9: 1.30%1
B10: 2005 | C10: 0.3634 | E10: Total Market Return | G10: =SUM(G8:G9) -> 0.11650334
B11: 2006 | C11: 0.3983
B12: 2007 | C12: 0.5477
B13: 2008 | C13: -0.5179
B14: 2009 | C14: 0.7576
B15: 2010 | C15: 0.1795
B16: 2011 | C16: -0.2462
B17: 2012 | C17: 0.277
B18: 2013 | C18: 0.0676
B19: 2014 | C19: 0.3139
B20: 2015 | C20: -0.0406
B21: 2016 | C21: 0.0301
B22: 2017 | C22: 0.2865
... B30: 2025 | C30: 0.1051

Sheet WACC
B2: Calculation of WACC
B4: All figures are in INR unless stated otherwise
B6: Peer Comps
G7: Debt/ | H7: Debt/ | I7: Levered | J7: Unlevered
B8: Company | C8: Country | D8: Total Debt | E8: Total Equity | F8: Tax Rate | G8: Equity | H8: Capital | I8: Beta1 | J8: Beta2
B10: Titan Company | C10: India | D10: 30621 | E10: 411770.52 | F10: 0.254 | G10: =D10/E10 -> 0.074364236 | H10: =D10/(D10+E10) -> 0.069216969 | I10: ='Beta-Regression'!N17 -> 1.1357276 | J10: =I10/(1+(1-F10)*G10) -> 1.0760338
B11: Kalyan Jewellers | C11: India | D11: 6117.33 | E11: 59318.288 | F11: 0.254 | G11: =D11/E11 -> 0.10312722 | H11: =D11/(D11+E11) -> 0.093486242 | I11: ='Beta-Regression'!Z3 -> 1.1254699 | J11: =I11/(1+(1-F11)*G11) -> 1.0450696
B12: Thangamayil Jew. | C12: India | D12: 913.21 | E12: 20015.96 | F12: 0.254 | G12: =D12/E12 -> 0.045624092 | H12: =D12/(D12+E12) -> 0.04363336 | I12: ='Beta-Regression'!V3 -> 0.60935632 | J12: =I12/(1+(1-F12)*G12) -> 0.58929919
B13: Rajesh Exports Limited | C13: India | D13: 1015.9 | E13: 2583.875 | F13: 0.254 | G13: =D13/E13 -> 0.39316917 | H13: =D13/(D13+E13) -> 0.28221208 | I13: ='Beta-Regression'!AD3 -> 1.1272013 | J13: =I13/(1+(1-F13)*G13) -> 0.87156704
C15: Average | D15: =AVERAGE(D10:D13) -> 9666.86 | E15: =AVERAGE(E10:E13) -> 123422.16 | F15: =AVERAGE(F10:F13) -> 0.254 | G15: =AVERAGE(G10:G13) -> 0.15407118 | H15: =AVERAGE(H10:H13) -> 0.12213716 | I15: =AVERAGE(I10:I13) -> 0.99943877 | J15: =AVERAGE(J10:J13) -> 0.89549242
C16: Median | D16: =MEDIAN(D10:D13) -> 3566.615 | E16: =MEDIAN(E10:E13) -> 39667.124 | F16: =MEDIAN(F10:F13) -> 0.254 | G16: =MEDIAN(G10:G13) -> 0.088745727 | H16: =MEDIAN(H10:H13) -> 0.081351605 | I16: =MEDIAN(I10:I13) -> 1.1263356 | J16: =MEDIAN(J10:J13) -> 0.95831833
B18: Cost of Debt | G18: Cost of Equity
B20: Pre-Tax Cost of Debt | E20: 0.0385 | G20: Risk Free Rate | J20: 0.068
B21: Tax Rate | E21: =F15 -> 0.254 | G21: Equity Risk Premium (ERP) | J21: =Rm!G10-WACC!J20 -> 0.048503341
B22: After-Tax Cost of Debt | E22: =E20*(1-E21) -> 0.028721 | G22: Levered Beta | J22: =J30 -> 1.0684647
G23: Cost of Equity | J23: =J20+(J21*J22) -> 0.11982411
B25: Cost Structure | G25: Levered Beta
D27: Current | E27: Target | G27: Comps Median Unlevered Beta | J27: =J16 -> 0.95831833
B28: Total Debt | C28: =D10 -> 30621 | D28: =C28/C30 -> 0.069216969 | E28: =H15 -> 0.12213716 | G28: Target Debt/Equity | J28: =G15 -> 0.15407118
B29: Market Capitalization | C29: =E10 -> 411770.52 | D29: =D30-D28 -> 0.93078303 | E29: =E30-E28 -> 0.87786284 | G29: Tax Rate | J29: =F15 -> 0.254
B30: Total Capital | C30: =SUM(C28:C29) -> 442391.52 | D30: =C30/C30 -> 1 | E30: =D30 -> 1 | G30: Levered Beta | J30: =J27*(1+(1-J29)*J28) -> 1.0684647
G32: Calculation of WACC
B33: Debt/Equity | D33: =G10 -> 0.074364236 | E33: =J28 -> 0.15407118
B34: Debt/Capital | D34: =D28 -> 0.069216969 | E34: =E28 -> 0.12213716 | G34: Cost of Debt | J34: =E22 -> 0.028721
G35: Debt Weight | J35: =E28 -> 0.12213716
B37: 1. Tax Rate considered as Marginal Tax Rate for the Country | G37: Cost of Equity | J37: =J23 -> 0.11982411
B38: 2. Levered Beta is based on 5 year Weekly Data | G38: Equity Weight | J38: =E29 -> 0.87786284
B39: 3. Unlevered Beta = Levered Beta/(1+(1-Tax Rate)*Debt/Equity
B40: 4. Levered Beta = Unlevered Beta*(1+(1-Tax Rate)*Debt/Equity | G40: WACC | J40: =(J38*J37)+(J35*J34) -> 0.10869703

Sheet Intrinsic Growth
B2: Calculation of ROIC | E2: =HistoricalFS!H5 -> 44651 | F2: =HistoricalFS!I5 -> 45016 | G2: =HistoricalFS!J5 -> 45382 | H2: =HistoricalFS!K5 -> 45747 | I2: =HistoricalFS!L5 -> 46112
B4: Current Assets
B5: =RawFS!B36 -> Inventories | E5: =RawFS!J36 -> 13609 | F5: =RawFS!K36 -> 16584 | G5: =RawFS!L36 -> 19051 | H5: =RawFS!M36 -> 28184 | I5: =RawFS!N36 -> 42743
B6: =RawFS!B37 -> Trade receivables | E6: =RawFS!J37 -> 565 | F6: =RawFS!K37 -> 674 | G6: =RawFS!L37 -> 1018 | H6: =RawFS!M37 -> 1068 | I6: =RawFS!N37 -> 916
B7: =RawFS!B39 -> Loans n Advances | E7: =RawFS!J39 -> 29 | F7: =RawFS!K39 -> 167 | G7: =RawFS!L39 -> 151 | H7: =RawFS!M39 -> 324 | I7: =RawFS!N39 -> 399
B8: =RawFS!B40 -> Other asset items | E8: =RawFS!J40 -> 2489 | F8: =RawFS!K40 -> 2595 | G8: =RawFS!L40 -> 3650 | H8: =RawFS!M40 -> 3330 | I8: =RawFS!N40 -> 4039
B9: Total Current Assets | E9: =SUM(E5:E8) -> 16692 | F9: =SUM(F5:F8) -> 20020 | G9: =SUM(G5:G8) -> 23870 | H9: =SUM(H5:H8) -> 32906 | I9: =SUM(I5:I8) -> 48097
B11: Current Liabilities
B12: =RawFS!B13 -> Trade Payables | E12: =RawFS!J13 -> 1294 | F12: =RawFS!K13 -> 1214 | G12: =RawFS!L13 -> 1410 | H12: =RawFS!M13 -> 1963 | I12: =RawFS!N13 -> 2864
B13: =RawFS!B14 -> Advance from Customers | E13: =RawFS!J14 -> 532 | F13: =RawFS!K14 -> 718 | G13: =RawFS!L14 -> 1085 | H13: =RawFS!M14 -> 2140 | I13: =RawFS!N14 -> 4745
B14: =RawFS!B15 -> Other liability items | E14: =RawFS!J15 -> 2754 | F14: =RawFS!K15 -> 3817 | G14: =RawFS!L15 -> 4131 | H14: =RawFS!M15 -> 4141 | I14: =RawFS!N15 -> 6628
B15: Total Current Liabilities | E15: =SUM(E12:E14) -> 4580 | F15: =SUM(F12:F14) -> 5749 | G15: =SUM(G12:G14) -> 6626 | H15: =SUM(H12:H14) -> 8244 | I15: =SUM(I12:I14) -> 14237
B17: Net Working Capital | E17: =E9-E15 -> 12112 | F17: =F9-F15 -> 14271 | G17: =G9-G15 -> 17244 | H17: =H9-H15 -> 24662 | I17: =I9-I15 -> 33860
B19: Non Current Assets
B20: =RawFS!B19 -> Land | E20: =RawFS!J19 -> 136 | F20: =RawFS!K19 -> 144 | G20: =RawFS!L19 -> 163 | H20: =RawFS!M19 -> 163 | I20: =RawFS!N19 -> 440
B21: =RawFS!B20 -> Building | E21: =RawFS!J20 -> 1853 | F21: =RawFS!K20 -> 2403 | G21: =RawFS!L20 -> 3546 | H21: =RawFS!M20 -> 4177 | I21: =RawFS!N20 -> 5239
B22: =RawFS!B21 -> Plant Machinery | E22: =RawFS!J21 -> 768 | F22: =RawFS!K21 -> 838 | G22: =RawFS!L21 -> 899 | H22: =RawFS!M21 -> 1012 | I22: =RawFS!N21 -> 1197
B23: =RawFS!B22 -> Equipments | E23: =RawFS!J22 -> 96 | F23: =RawFS!K22 -> 130 | G23: =RawFS!L22 -> 110 | H23: =RawFS!M22 -> 127 | I23: =RawFS!N22 -> 176
B24: =RawFS!B23 -> Computers | E24: =RawFS!J23 -> 159 | F24: =RawFS!K23 -> 204 | G24: =RawFS!L23 -> 212 | H24: =RawFS!M23 -> 228 | I24: =RawFS!N23 -> 264
B25: =RawFS!B24 -> Furniture n fittings | E25: =RawFS!J24 -> 321 | F25: =RawFS!K24 -> 376 | G25: =RawFS!L24 -> 173 | H25: =RawFS!M24 -> 193 | I25: =RawFS!N24 -> 379
B26: =RawFS!B25 -> Vehicles | E26: =RawFS!J25 -> 38 | F26: =RawFS!K25 -> 40 | G26: =RawFS!L25 -> 50 | H26: =RawFS!M25 -> 57 | I26: =RawFS!N25 -> 68
B27: =RawFS!B26 -> Intangible Assets | E27: =RawFS!J26 -> 320 | F27: =RawFS!K26 -> 320 | G27: =RawFS!L26 -> 320 | H27: =RawFS!M26 -> 320 | I27: =RawFS!N26 -> 1782
B28: =RawFS!B27 -> Other fixed assets | E28: =RawFS!J27 -> 157 | F28: =RawFS!K27 -> 205 | G28: =RawFS!L27 -> 305 | H28: =RawFS!M27 -> 369 | I28: =RawFS!N27 -> 540
B29: =RawFS!B28 -> Gross Block | E29: =RawFS!J28 -> 3848 | F29: =RawFS!K28 -> 4660 | G29: =RawFS!L28 -> 5778 | H29: =RawFS!M28 -> 6646 | I29: =RawFS!N28 -> 10085
B30: =RawFS!B29 -> Accumulated Depreciation | E30: =RawFS!J29 -> 1304 | F30: =RawFS!K29 -> 1662 | G30: =RawFS!L29 -> 2069 | H30: =RawFS!M29 -> 2584 | I30: =RawFS!N29 -> 3207
B31: Total Non Current Assets | E31: =E29-E30 -> 2544 | F31: =F29-F30 -> 2998 | G31: =G29-G30 -> 3709 | H31: =H29-H30 -> 4062 | I31: =I29-I30 -> 6878
B33: Capital Invested | E33: =SUM(E31,E17) -> 14656 | F33: =SUM(F31,F17) -> 17269 | G33: =SUM(G31,G17) -> 20953 | H33: =SUM(H31,H17) -> 28724 | I33: =SUM(I31,I17) -> 40738
B34: EBIT | E34: =HistoricalFS!H30 -> 3122 | F34: =HistoricalFS!I30 -> 4747 | G34: =HistoricalFS!J30 -> 5242 | H34: =HistoricalFS!K30 -> 5488 | I34: =HistoricalFS!L30 -> 7981
B35: EBIT(1-T) | E35: =E34*(1-'Assumptions Sheet'!D16) -> 2363.0014 | F35: =F34*(1-'Assumptions Sheet'!E16) -> 3494.868 | G35: =G34*(1-'Assumptions Sheet'!F16) -> 3964.0995 | H35: =H34*(1-'Assumptions Sheet'!G16) -> 4038.2483 | I35: =I34*(1-'Assumptions Sheet'!H16) -> 5953.1853
B37: ROIC | E37: =E35/E33 -> 0.16123099 | F37: =F35/F33 -> 0.20237813 | G37: =G35/G33 -> 0.18919007 | H37: =H35/H33 -> 0.14058795 | I37: =I35/I33 -> 0.14613347
B39: Calculation of Reinvested Capital | E39: =E2 -> 44651 | F39: =F2 -> 45016 | G39: =G2 -> 45382 | H39: =H2 -> 45747 | I39: =I2 -> 46112
B41: Net Capex | E41: =-SUM(HistoricalFS!H92:H93) -> 216 | F41: =-SUM(HistoricalFS!I92:I93) -> 420 | G41: =-SUM(HistoricalFS!J92:J93) -> 671 | H41: =-SUM(HistoricalFS!K92:K93) -> 470 | I41: =-SUM(HistoricalFS!L92:L93) -> 877
B42: Change in working capital | F42: =F17-E17 -> 2159 | G42: =G17-F17 -> 2973 | H42: =H17-G17 -> 7418 | I42: =I17-H17 -> 9198
B44: =B34 -> EBIT | E44: =E34 -> 3122 | F44: =F34 -> 4747 | G44: =G34 -> 5242 | H44: =H34 -> 5488 | I44: =I34 -> 7981
B45: =B35 -> EBIT(1-T) | E45: =E35 -> 2363.0014 | F45: =F35 -> 3494.868 | G45: =G35 -> 3964.0995 | H45: =H35 -> 4038.2483 | I45: =I35 -> 5953.1853
B47: Reinvestment | F47: =SUM(F41:F42) -> 2579 | G47: =SUM(G41:G42) -> 3644 | H47: =SUM(H41:H42) -> 7888 | I47: =SUM(I41:I42) -> 10075
B48: Reinvestment Rate | F48: =F47/F45 -> 0.73793917 | G48: =G47/G45 -> 0.91925039 | H48: =H47/H45 -> 1.9533222 | I48: =I47/I45 -> 1.6923713
H50: Average | I50: =AVERAGE(F48:I48) -> 1.3257208
H51: Median | I51: =MEDIAN(F48:I48) -> 1.3058109
B53: Calculation of Intrinsic Growth | E53: =E39 -> 44651 | F53: =F39 -> 45016 | G53: =G39 -> 45382 | H53: =H39 -> 45747 | I53: =I39 -> 46112
B55: =B48 -> Reinvestment Rate | F55: =F48 -> 0.73793917 | G55: =G48 -> 0.91925039 | H55: =H48 -> 1.9533222 | I55: =I48 -> 1.6923713
B56: =B37 -> ROIC | E56: =E37 -> 0.16123099 | F56: =F37 -> 0.20237813 | G56: =G37 -> 0.18919007 | H56: =H37 -> 0.14058795 | I56: =I37 -> 0.14613347
B58: Intrinsic Growth | F58: =F56*F55 -> 0.14934275 | G58: =G56*G55 -> 0.17391304 | H58: =H56*H55 -> 0.27461356 | I58: =I56*I55 -> 0.24731209
H60: Average | I60: =AVERAGE(F58:I58) -> 0.21129536
H61: Median | I61: =MEDIAN(F58:I58) -> 0.21061257

Sheet DCF
B2: Calculation of PV of FCFF | G2: =ForcastedFS!F5 -> 45747 | H2: =ForcastedFS!G5 -> 46112 | I2: =ForcastedFS!H5 -> 46477 | J2: =ForcastedFS!I5 -> 46842 | K2: =ForcastedFS!J5 -> 47207 | L2: =ForcastedFS!K5 -> 47572 | M2: =ForcastedFS!L5 -> 47937
B4: EBIT | G4: =ForcastedFS!F24 -> 5488 | H4: =ForcastedFS!G24 -> 7981 | I4: =ForcastedFS!H24 -> 9983.3611 | J4: =ForcastedFS!I24 -> 12399.693 | K4: =ForcastedFS!J24 -> 15197.496 | L4: =ForcastedFS!K24 -> 18231.64 | M4: =ForcastedFS!L24 -> 21618.701
B6: Tax Rate | G6: ='Assumptions Sheet'!G16 -> 0.26416759 | H6: ='Assumptions Sheet'!H16 -> 0.25408028 | I6: ='Assumptions Sheet'!I16 -> 0.2535 | J6: ='Assumptions Sheet'!J16 -> 0.2535 | K6: ='Assumptions Sheet'!K16 -> 0.2535 | L6: ='Assumptions Sheet'!L16 -> 0.2535 | M6: ='Assumptions Sheet'!M16 -> 0.2535
B8: EBIT(1-T) | G8: =G4*(1-G6) -> 4038.2483 | H8: =H4*(1-H6) -> 5953.1853 | I8: =I4*(1-I6) -> 7452.5791 | J8: =J4*(1-J6) -> 9256.3706 | K8: =K4*(1-K6) -> 11344.931 | L8: =L4*(1-L6) -> 13609.919 | M8: =M4*(1-M6) -> 16138.361
B10: Less: Reinvestment Rate | G10: ='Intrinsic Growth'!H48 -> 1.9533222 | H10: ='Intrinsic Growth'!I48 -> 1.6923713 | I10: ='Assumptions Sheet'!I55 -> 1.4650611 | J10: ='Assumptions Sheet'!J55 -> 0.76580649 | K10: ='Assumptions Sheet'!K55 -> 0.64668816 | L10: ='Assumptions Sheet'!L55 -> 0.54633705 | M10: ='Assumptions Sheet'!M55 -> 0.46518057
B12: Free Cash Flow To Firm | G12: =G8*(1-G10) -> -3849.7517 | H12: =H8*(1-H10) -> -4121.8147 | I12: =I8*(1-I10) -> -3465.9047 | J12: =J8*(1-J10) -> 2167.7819 | K12: =K8*(1-K10) -> 4008.2983 | L12: =L8*(1-L10) -> 6174.3162 | M12: =M8*(1-M10) -> 8631.1088
B14: Mid Year Convention | H14: 0.5 | I14: =H14+1 -> 1.5 | J14: =I14+1 -> 2.5 | K14: =J14+1 -> 3.5 | L14: =K14+1 -> 4.5 | M14: =L14+1 -> 5.5
B15: Discounting Factor | H15: =1/(1+$D$21)^H14 -> 0.94971557 | I15: =1/(1+$D$21)^I14 -> 0.85660513 | J15: =1/(1+$D$21)^J14 -> 0.77262328 | K15: =1/(1+$D$21)^K14 -> 0.69687503 | L15: =1/(1+$D$21)^L14 -> 0.62855317 | M15: =1/(1+$D$21)^M14 -> 0.5669296
B17: PV of FCFF | H17: =H12*H15 -> -3914.5516 | I17: =I12*I15 -> -2968.9118 | J17: =J12*J15 -> 1674.8788 | K17: =K12*K15 -> 2793.283 | L17: =L12*L15 -> 3880.886 | M17: =M12*M15 -> 4893.2311
B19: Expected Growth | D19: 0.1
B20: Terminal Growth | D20: 0.05
B21: WACC | D21: =WACC!J40 -> 0.10869703
B23: Calculation of Terminal Value | F23: Scenerio Analysis
B25: FCFF(n+1) | D25: =M12*(1+D20) -> 9062.6643 | J25: WACC
B26: WACC | D26: =D21 -> 0.10869703 | G26: =D41 -> 734.2672 | H26: 0.09 | I26: 0.1 | J26: =D21 -> 0.10869703 | K26: 0.12 | L26: 0.13 | M26: 0.14
B27: Terminal Growth Rate | D27: =D20 -> 0.05 | G27: 0.03 | H27: 712.85589 | I27: 575.06282 | J27: 483.69542 | K27: 391.33874 | L27: 327.03531 | M27: 274.42341
F28: Growth Rate | G28: 0.04 | H28: 905.76618 | I28: 712.85589 | J28: 590.74385 | K28: 471.71802 | L28: 391.33874 | M28: 327.03531
B29: Terminal Value | D29: =D25/(D26-D27) -> 154397.32 | G29: =D20 -> 0.05 | H29: 1195.1316 | I29: 905.76618 | J29: 734.2672 | K29: 575.06282 | L29: 471.71802 | M29: 391.33874
G30: 0.06 | H30: 1677.4074 | I30: 1195.1316 | J30: 936.73596 | K30: 712.85589 | L30: 575.06282 | M30: 471.71802
B31: Calculation of Equity Value | G31: 0.07 | H31: 2641.9588 | I31: 1677.4074 | J31: 1243.8478 | K31: 905.76618 | L31: 712.85589 | M31: 575.06282
B33: PV of FCFF | D33: =SUM(H17:M17) -> 6358.8155
B34: PV of Terminal Value | D34: =M15*D29 -> 87532.411
B35: Value of Operating Assets | D35: =SUM(D33:D34) -> 93891.226
B37: Add: Cash | D37: ='Data Sheet'!K69 -> 1917
B38: Less: Debt | D38: ='Data Sheet'!K59 -> 30621
B39: Value of Equity | D39: =D35+D37-D38 -> 65187.226
B40: No of Shares | D40: ='Data Sheet'!B6 -> 88.778617
B41: Equity Value per Shares | D41: =D39/D40 -> 734.2672
B43: Share Price | D43: ='Data Sheet'!B8 -> 4584.4
B44: Discount/Premium | D44: =D43/D41-1 -> 5.2435037

Sheet Comps_Valuation
B2: Comparable Company Valuation
D4: Market Data | K4: Financial | O4: Valuation
E6: Share | F6: Share | G6: Equity | I6: Enterprise
B7: Company | D7: Ticker | E7: Price | F7: Outstanding | G7: Value | H7: Net Debt | I7: Value | K7: Revenue | L7: EBITDA | M7: Net Income | O7: EV/Revenue | P7: EV/EBITDA | Q7: P/E
B8: Titan Company | E8: 4584.4 | F8: 88.78 | G8: =F8*E8 -> 407003.03 | H8: =comps_data!F3-comps_data!G3 -> 28704 | I8: =G8+H8 -> 435707.03 | K8: =comps_data!I3 -> 87584 | L8: =comps_data!L3 -> 8354 | M8: =comps_data!K3 -> 5073 | O8: =I8/K8 -> 4.9747332 | P8: =I8/L8 -> 52.155498 | Q8: =G8/M8 -> 80.229259
B9: Kalyan Jewellers | E9: 573.55 | F9: 103.27 | G9: =F9*E9 -> 59230.508 | H9: =comps_data!F4-comps_data!G4 -> 5256.42 | I9: =G9+H9 -> 64486.928 | K9: =comps_data!I4 -> 35742.86 | L9: =comps_data!L4 -> 2699.22 | M9: =comps_data!K4 -> 1350.4 | O9: =I9/K9 -> 1.8041905 | P9: =I9/L9 -> 23.890949 | Q9: =G9/M9 -> 43.861455
B10: Thangamayil Jew. | E10: 6906.5 | F10: 3.11 | G10: =F10*E10 -> 21479.215 | H10: =comps_data!F5-comps_data!G5 -> 531.98 | I10: =G10+H10 -> 22011.195 | K10: =comps_data!I5 -> 8499.33 | L10: =comps_data!L5 -> 579.12 | M10: =comps_data!K5 -> 351.65 | O10: =I10/K10 -> 2.5897565 | P10: =I10/L10 -> 38.008004 | Q10: =G10/M10 -> 61.081231
B11: Bluestone Jewel | E11: 772.4 | F11: 15.24 | G11: =F11*E11 -> 11771.376 | H11: =comps_data!F6-comps_data!G6 -> 1187.42 | I11: =G11+H11 -> 12958.796 | K11: =comps_data!I6 -> 2680.6 | L11: =comps_data!L6 -> 433.52 | M11: =comps_data!K6 -> 53.89 | O11: =I11/K11 -> 4.8342893 | P11: =I11/L11 -> 29.892037 | Q11: =G11/M11 -> 218.4334
B12: Sky Gold & Diam. | E12: 653.7 | F12: 15.49 | G12: =F12*E12 -> 10125.813 | H12: =comps_data!F7-comps_data!G7 -> 633.67 | I12: =G12+H12 -> 10759.483 | K12: =comps_data!I7 -> 6294.89 | L12: =comps_data!L7 -> 470.75 | M12: =comps_data!K7 -> 281.83 | O12: =I12/K12 -> 1.7092408 | P12: =I12/L12 -> 22.856045 | Q12: =G12/M12 -> 35.928798
B13: PC Jeweller | E13: 9.28 | F13: 971.05 | G13: =F13*E13 -> 9011.344 | H13: =comps_data!F8-comps_data!G8 -> 1030.39 | I13: =G13+H13 -> 10041.734 | K13: =comps_data!I8 -> 3352.88 | L13: =comps_data!L8 -> 867.84 | M13: =comps_data!K8 -> 714.46 | O13: =I13/K13 -> 2.9949578 | P13: =I13/L13 -> 11.570951 | Q13: =G13/M13 -> 12.612804
B14: P N Gadgil Jewe. | E14: 647 | F14: 13.57 | G14: =F14*E14 -> 8779.79 | H14: =comps_data!F9-comps_data!G9 -> 1232.64 | I14: =G14+H14 -> 10012.43 | K14: =comps_data!I9 -> 10739.1 | L14: =comps_data!L9 -> 704.02 | M14: =comps_data!K9 -> 409.82 | O14: =I14/K14 -> 0.93233418 | P14: =I14/L14 -> 14.221798 | Q14: =G14/M14 -> 21.423527
B16: High | O16: =MAX(O8:O14) -> 4.9747332 | P16: =MAX(P8:P14) -> 52.155498 | Q16: =MAX(Q8:Q14) -> 218.4334
B17: 75th Percentile | O17: =QUARTILE(O8:O14,3) -> 3.9146236 | P17: =QUARTILE(P8:P14,3) -> 33.95002 | Q17: =QUARTILE(Q8:Q14,3) -> 70.655245
B18: Average | O18: =AVERAGE(O8:O14) -> 2.8342146 | P18: =AVERAGE(P8:P14) -> 27.513612 | Q18: =AVERAGE(Q8:Q14) -> 67.652925
B19: Median | O19: =MEDIAN(O8:O14) -> 2.5897565 | P19: =MEDIAN(P8:P14) -> 23.890949 | Q19: =MEDIAN(Q8:Q14) -> 43.861455
B20: 25th Percentile | O20: =QUARTILE(O8:O14,1) -> 1.7567157 | P20: =QUARTILE(P8:P14,1) -> 18.538921 | Q20: =QUARTILE(Q8:Q14,1) -> 28.676162
B21: Low | O21: =MIN(O8:O14) -> 0.93233418 | P21: =MIN(P8:P14) -> 11.570951 | Q21: =MIN(Q8:Q14) -> 12.612804
B23: Titan Company Ltd Valuation | O23: EV/Revenue | P23: EV/EBITDA | Q23: P/E
B25: Implied Enterprise Value | O25: =K8*O19 -> 226821.23 | P25: =L8*P19 -> 199584.99 | Q25: =Q27+Q26 -> 251213.16
B26: New Debt | O26: =$H$8 -> 28704 | P26: =$H$8 -> 28704 | Q26: =$H$8 -> 28704
B27: Implied Market Value | O27: =O25-O26 -> 198117.23 | P27: =P25-P26 -> 170880.99 | Q27: =M8*Q19 -> 222509.16
B28: Shares Outstanding | O28: =$F$8 -> 88.78 | P28: =$F$8 -> 88.78 | Q28: =$F$8 -> 88.78
B29: Implied Value Per Share | O29: =O27/O28 -> 2231.5525 | P29: =P27/P28 -> 1924.769 | Q29: =Q27/Q28 -> 2506.2983
O31: =IF(O29>$E$8,"Undervalued","Overvalued") -> Overvalued | P31: =IF(P29>$E$8,"Undervalued","Overvalued") -> Overvalued | Q31: =IF(Q29>$E$8,"Undervalued","Overvalued") -> Overvalued

Sheet Football_Field_Analysis
B2: ="Football Field Valuation Summary"&" - "&'Data Sheet'!B1 -> Football Field Valuation Summary - TITAN COMPANY LTD
B4: Football Field Analysis
D5: OpenLow | E5: Low | F5: OpenHigh | G5: High
B6: Comps | D6: =E6 -> 2231.5525 | E6: =Comps_Valuation!O29 -> 2231.5525 | F6: =G6 -> 2506.2983 | G6: =Comps_Valuation!Q29 -> 2506.2983
B7: DCF Bear | D7: =E7 -> 274.42341 | E7: =DCF!M27 -> 274.42341 | F7: =G7 -> 575.06282 | G7: =DCF!M31 -> 575.06282
B8: DCF Base | D8: =E8 -> 483.69542 | E8: =DCF!J27 -> 483.69542 | F8: =G8 -> 1243.8478 | G8: =DCF!J31 -> 1243.8478
B9: DCF Bull | D9: =E9 -> 712.85589 | E9: =DCF!H27 -> 712.85589 | F9: =G9 -> 2641.9588 | G9: =DCF!H31 -> 2641.9588
B10: 52W H/L | D10: =E10 -> 3303.1 | E10: 3303.1 | F10: =G10 -> 4679.8 | G10: 4679.8

Sheet VAR Historical Approach
B2: Date | C2: Close | D2: Return | E2: Sorted Return | G2: Calculation of VAR
B3: 46213.646 | C3: 4584.4 | D3: =(C3-C4)/C4 -> 0.0062777119 | E3: 0.10602286
B4: 46212.646 | C4: 4555.8 | D4: =(C4-C5)/C5 -> -0.0066718995 | E4: 0.067154803 | G4: Mean | K4: =AVERAGE(E3:E1360) -> 0.00091471442
B5: 46211.646 | C5: 4586.4 | D5: =(C5-C6)/C6 -> -0.0038660354 | E5: 0.066532131 | G5: St. Deviation | K5: =STDEV(E3:E1360) -> 0.015523116
B6: 46210.646 | C6: 4604.2 | D6: =(C6-C7)/C7 -> 0.026714834 | E6: 0.065264484 | G6: Min. | K6: =MIN(E3:E1360) -> -0.071804522
B7: 46209.646 | C7: 4484.4 | D7: =(C7-C8)/C8 -> 0.0052229271 | E7: 0.061906113 | G7: Max. | K7: =MAX(E3:E1360) -> 0.10602286
B8: 46206.646 | C8: 4461.1 | D8: =(C8-C9)/C9 -> -0.0044631898 | E8: 0.05933629 | G8: CMP | K8: ='Data Sheet'!$B$8 -> 4584.4
B9: 46205.646 | C9: 4481.1 | D9: =(C9-C10)/C10 -> 0.018755968 | E9: 0.057206224
B10: 46204.646 | C10: 4398.6 | D10: =(C10-C11)/C11 -> -0.001226158 | E10: 0.056591592 | G10: Percentile | H10: Confidence | I10: VAR% | J10: Stock Price | K10: VAR(INR)
B11: 46203.646 | C11: 4404 | D11: =(C11-C12)/C12 -> 0.029645563 | E11: 0.055113444
B12: 46202.646 | C12: 4277.2 | D12: =(C12-C13)/C13 -> -0.0032857176 | E12: 0.053088301 | G12: 0.05 | H12: =100%-G12 -> 0.95 | I12: =_xlfn.PERCENTILE.INC($E$3:$E$1360,H12) -> 0.025997171 | J12: =$K$8*(1-G12) -> 4355.18 | K12: =$K$8-J12 -> 229.22
B13: 46198.646 | C13: 4291.3 | D13: =(C13-C14)/C14 -> -0.0075165364 | E13: 0.04964638 | G13: 0.01 | H13: =100%-G13 -> 0.99 | I13: =_xlfn.PERCENTILE.INC($E$3:$E$1360,H13) -> 0.043840831 | J13: =$K$8*(1-G13) -> 4538.556 | K13: =$K$8-J13 -> 45.844
B14: 46197.646 | C14: 4323.8 | D14: =(C14-C15)/C15 -> 0.0042970292 | E14: 0.048321188 | G14: 0.005 | H14: =100%-G14 -> 0.995 | I14: =_xlfn.PERCENTILE.INC($E$3:$E$1360,H14) -> 0.056723738 | J14: =$K$8*(1-G14) -> 4561.478 | K14: =$K$8-J14 -> 22.922
B15: 46196.646 | C15: 4305.3 | D15: =(C15-C16)/C16 -> -0.015368782 | E15: 0.046778874
B16: 46195.646 | C16: 4372.5 | D16: =(C16-C17)/C17 -> -0.010724225 | E16: 0.044718432
B17: 46192.646 | C17: 4419.9 | D17: =(C17-C18)/C18 -> 0.0072927824 | E17: 0.043178781
B18: 46191.646 | C18: 4387.9 | D18: =(C18-C19)/C19 -> 0.0016893049 | E18: 0.043122111
B19: 46190.646 | C19: 4380.5 | D19: =(C19-C20)/C20 -> 0.0097971415 | E19: 0.041848455
B20: 46189.646 | C20: 4338 | D20: =(C20-C21)/C21 -> 0.01272324 | E20: 0.041520045
B21: 46188.646 | C21: 4283.5 | D21: =(C21-C22)/C22 -> 0.023781071 | E21: 0.040979094
B22: 46185.646 | C22: 4184 | D22: =(C22-C23)/C23 -> 0.039451456 | E22: 0.040825688
B23: 46184.646 | C23: 4025.2 | D23: =(C23-C24)/C24 -> -0.004180995 | E23: 0.039451456
B24: 46183.646 | C24: 4042.1 | D24: =(C24-C25)/C25 -> -0.015298789 | E24: 0.039252882
B25: 46182.646 | C25: 4104.9 | D25: =(C25-C26)/C26 -> -0.0208711 | E25: 0.039217193
B26: 46181.646 | C26: 4192.4 | D26: =(C26-C27)/C27 -> -0.015914746 | E26: 0.039040945
... B1360: 44200.646 | C1360: 1550.9 | D1360: =(C1360-C1361)/C1361 -> -0.0049403311 | E1360: -0.071804522
B1361: 44197.646 | C1361: 1558.6 | D1361: =(C1361-C1372)/C1372 -> #DIV/0!

Sheet Monte Carlo Simulation
B2: Date | C2: Close | D2: Return | E2: Sorted Return | F2: Replication | G2: Simulated Return | I2: ="Calculation of VAR (Monte Carlo Simulation)"&" - "&'Data Sheet'!B1 -> Calculation of VAR (Monte Carlo Simulation) - TITAN COMPANY LTD
B3: 46213.646 | C3: 4584.4 | D3: =(C3-C4)/C4 -> 0.0062777119 | E3: 0.10602286 | F3: 1 | G3: =_xlfn.NORM.INV(RAND(),'VAR Historical Approach'!K$4,'VAR Historical Approach'!K$5) -> 0.011126216
B4: 46212.646 | C4: 4555.8 | D4: =(C4-C5)/C5 -> -0.0066718995 | E4: 0.067154803 | F4: 2 | G4: =_xlfn.NORM.INV(RAND(),'VAR Historical Approach'!K$4,'VAR Historical Approach'!K$5) -> -0.0018058423 | I4: Mean | M4: =AVERAGE(G3:G1360) -> 0.0015819375
B5: 46211.646 | C5: 4586.4 | D5: =(C5-C6)/C6 -> -0.0038660354 | E5: 0.066532131 | F5: 3 | G5: =_xlfn.NORM.INV(RAND(),'VAR Historical Approach'!K$4,'VAR Historical Approach'!K$5) -> 0.016884459 | I5: Standard Deviation | M5: =STDEV(G3:G1360) -> 0.015686262
B6: 46210.646 | C6: 4604.2 | D6: =(C6-C7)/C7 -> 0.026714834 | E6: 0.065264484 | F6: 4 | G6: =_xlfn.NORM.INV(RAND(),'VAR Historical Approach'!K$4,'VAR Historical Approach'!K$5) -> 0.013353493 | I6: Max | M6: =MAX(G3:G1360) -> 0.04763799
B7: 46209.646 | C7: 4484.4 | D7: =(C7-C8)/C8 -> 0.0052229271 | E7: 0.061906113 | F7: 5 | G7: =_xlfn.NORM.INV(RAND(),'VAR Historical Approach'!K$4,'VAR Historical Approach'!K$5) -> -0.0059284949 | I7: Min | M7: =MIN(G3:G1360) -> -0.048577785
B8: 46206.646 | C8: 4461.1 | D8: =(C8-C9)/C9 -> -0.0044631898 | E8: 0.05933629 | F8: 6 | G8: =_xlfn.NORM.INV(RAND(),'VAR Historical Approach'!K$4,'VAR Historical Approach'!K$5) -> 0.0020842146 | I8: CMP | M8: ='Data Sheet'!$B$8 -> 4584.4
B9: 46205.646 | C9: 4481.1 | D9: =(C9-C10)/C10 -> 0.018755968 | E9: 0.057206224 | F9: 7 | G9: =_xlfn.NORM.INV(RAND(),'VAR Historical Approach'!K$4,'VAR Historical Approach'!K$5) -> -0.013758992
B10: 46204.646 | C10: 4398.6 | D10: =(C10-C11)/C11 -> -0.001226158 | E10: 0.056591592 | F10: 8 | G10: =_xlfn.NORM.INV(RAND(),'VAR Historical Approach'!K$4,'VAR Historical Approach'!K$5) -> -0.034508951 | I10: Percentile | J10: Confidence | K10: VAR% | L10: Stock Price | M10: VAR(INR)
B11: 46203.646 | C11: 4404 | D11: =(C11-C12)/C12 -> 0.029645563 | E11: 0.055113444 | F11: 9 | G11: =_xlfn.NORM.INV(RAND(),'VAR Historical Approach'!K$4,'VAR Historical Approach'!K$5) -> -0.019728349
B12: 46202.646 | C12: 4277.2 | D12: =(C12-C13)/C13 -> -0.0032857176 | E12: 0.053088301 | F12: 10 | G12: =_xlfn.NORM.INV(RAND(),'VAR Historical Approach'!K$4,'VAR Historical Approach'!K$5) -> 0.025413877 | I12: 0.05 | J12: =100%-I12 -> 0.95 | K12: =_xlfn.PERCENTILE.INC($G$3:$G$1360,I12) -> -0.025177502 | L12: =$M$8*(1-I12) -> 4355.18 | M12: =$M$8-L12 -> 229.22
B13: 46198.646 | C13: 4291.3 | D13: =(C13-C14)/C14 -> -0.0075165364 | E13: 0.04964638 | F13: 11 | G13: =_xlfn.NORM.INV(RAND(),'VAR Historical Approach'!K$4,'VAR Historical Approach'!K$5) -> 0.0046093904 | I13: 0.01 | J13: =100%-I13 -> 0.99 | K13: =_xlfn.PERCENTILE.INC($G$3:$G$1360,I13) -> -0.035521154 | L13: =$M$8*(1-I13) -> 4538.556 | M13: =$M$8-L13 -> 45.844
B14: 46197.646 | C14: 4323.8 | D14: =(C14-C15)/C15 -> 0.0042970292 | E14: 0.048321188 | F14: 12 | G14: =_xlfn.NORM.INV(RAND(),'VAR Historical Approach'!K$4,'VAR Historical Approach'!K$5) -> 0.0339451 | I14: 0.005 | J14: =100%-I14 -> 0.995 | K14: =_xlfn.PERCENTILE.INC($G$3:$G$1360,I14) -> -0.040242826 | L14: =$M$8*(1-I14) -> 4561.478 | M14: =$M$8-L14 -> 22.922
B15: 46196.646 | C15: 4305.3 | D15: =(C15-C16)/C16 -> -0.015368782 | E15: 0.046778874 | F15: 13 | G15: =_xlfn.NORM.INV(RAND(),'VAR Historical Approach'!K$4,'VAR Historical Approach'!K$5) -> -0.02478736
B16: 46195.646 | C16: 4372.5 | D16: =(C16-C17)/C17 -> -0.010724225 | E16: 0.044718432 | F16: 14 | G16: =_xlfn.NORM.INV(RAND(),'VAR Historical Approach'!K$4,'VAR Historical Approach'!K$5) -> -0.033584608
B17: 46192.646 | C17: 4419.9 | D17: =(C17-C18)/C18 -> 0.0072927824 | E17: 0.043178781 | F17: 15 | G17: =_xlfn.NORM.INV(RAND(),'VAR Historical Approach'!K$4,'VAR Historical Approach'!K$5) -> 0.0021260935
B18: 46191.646 | C18: 4387.9 | D18: =(C18-C19)/C19 -> 0.0016893049 | E18: 0.043122111 | F18: 16 | G18: =_xlfn.NORM.INV(RAND(),'VAR Historical Approach'!K$4,'VAR Historical Approach'!K$5) -> -0.00018160586
B19: 46190.646 | C19: 4380.5 | D19: =(C19-C20)/C20 -> 0.0097971415 | E19: 0.041848455 | F19: 17 | G19: =_xlfn.NORM.INV(RAND(),'VAR Historical Approach'!K$4,'VAR Historical Approach'!K$5) -> 0.020985707
B20: 46189.646 | C20: 4338 | D20: =(C20-C21)/C21 -> 0.01272324 | E20: 0.041520045 | F20: 18 | G20: =_xlfn.NORM.INV(RAND(),'VAR Historical Approach'!K$4,'VAR Historical Approach'!K$5) -> -0.0057962702
B21: 46188.646 | C21: 4283.5 | D21: =(C21-C22)/C22 -> 0.023781071 | E21: 0.040979094 | F21: 19 | G21: =_xlfn.NORM.INV(RAND(),'VAR Historical Approach'!K$4,'VAR Historical Approach'!K$5) -> 0.0051470157
B22: 46185.646 | C22: 4184 | D22: =(C22-C23)/C23 -> 0.039451456 | E22: 0.040825688 | F22: 20 | G22: =_xlfn.NORM.INV(RAND(),'VAR Historical Approach'!K$4,'VAR Historical Approach'!K$5) -> -0.0082767071
B23: 46184.646 | C23: 4025.2 | D23: =(C23-C24)/C24 -> -0.004180995 | E23: 0.039451456 | F23: 21 | G23: =_xlfn.NORM.INV(RAND(),'VAR Historical Approach'!K$4,'VAR Historical Approach'!K$5) -> 0.01303494
B24: 46183.646 | C24: 4042.1 | D24: =(C24-C25)/C25 -> -0.015298789 | E24: 0.039252882 | F24: 22 | G24: =_xlfn.NORM.INV(RAND(),'VAR Historical Approach'!K$4,'VAR Historical Approach'!K$5) -> -0.019324117
B25: 46182.646 | C25: 4104.9 | D25: =(C25-C26)/C26 -> -0.0208711 | E25: 0.039217193 | F25: 23 | G25: =_xlfn.NORM.INV(RAND(),'VAR Historical Approach'!K$4,'VAR Historical Approach'!K$5) -> -0.01111259
B26: 46181.646 | C26: 4192.4 | D26: =(C26-C27)/C27 -> -0.015914746 | E26: 0.039040945 | F26: 24 | G26: =_xlfn.NORM.INV(RAND(),'VAR Historical Approach'!K$4,'VAR Historical Approach'!K$5) -> -0.00061598059
... B1360: 44200.646 | C1360: 1550.9 | D1360: =(C1360-C1361)/C1361 -> -0.0049403311 | E1360: -0.071804522 | F1360: 1358 | G1360: =_xlfn.NORM.INV(RAND(),'VAR Historical Approach'!K$4,'VAR Historical Approach'!K$5) -> -0.0082769052
B1361: 44197.646 | C1361: 1558.6 | D1361: =(C1361-C1372)/C1372 -> #DIV/0!

Sheet DUPONT Analysis
B3: ='Data Sheet'!B1 -> TITAN COMPANY LTD
B4: (TITAN | BSE Code: 500114)
B5: =CONCATENATE("INR "&'Data Sheet'!B9) -> INR 406996.69
B6: 52 Week (High - INR 4,679.80 & Low - 3,303.10)
B8: About The Company
B9: Titan Company Limited is an Indian fashion accessories company that mainly manufactures items such as jewellery, watches and eyewear. Part of the Tata Group and started as a joint venture with TIDCO, the company has its corporate headquarters in Electronic City, Bangalore and registered office in Hosur, Tamil Nadu.
B13: Financial Summary
B51: DUPONT Analysis - Return on Equity & Return on Assets
B53: Return on Equity (ROE)
D54: =HistoricalFS!F5 -> 43921 | E54: =HistoricalFS!G5 -> 44286 | F54: =HistoricalFS!H5 -> 44651 | G54: =HistoricalFS!I5 -> 45016 | H54: =HistoricalFS!J5 -> 45382 | I54: =HistoricalFS!K5 -> 45747 | J54: =HistoricalFS!L5 -> 46112
B55: Net Profit | D55: =HistoricalFS!F42 -> 1493 | E55: =HistoricalFS!G42 -> 974 | F55: =HistoricalFS!H42 -> 2198 | G55: =HistoricalFS!I42 -> 3274 | H55: =HistoricalFS!J42 -> 3496 | I55: =HistoricalFS!K42 -> 3337 | J55: =HistoricalFS!L42 -> 5073
B56: Average Shareholders Equity | D56: =(('Data Sheet'!E57+'Data Sheet'!E58)+('Data Sheet'!D57+'Data Sheet'!D58))/2 -> 6369.575 | E56: =(('Data Sheet'!F57+'Data Sheet'!F58)+('Data Sheet'!E57+'Data Sheet'!E58))/2 -> 7083 | F56: =(('Data Sheet'!G57+'Data Sheet'!G58)+('Data Sheet'!F57+'Data Sheet'!F58))/2 -> 8400 | G56: =(('Data Sheet'!H57+'Data Sheet'!H58)+('Data Sheet'!G57+'Data Sheet'!G58))/2 -> 10577 | H56: =(('Data Sheet'!I57+'Data Sheet'!I58)+('Data Sheet'!H57+'Data Sheet'!H58))/2 -> 10622 | I56: =(('Data Sheet'!J57+'Data Sheet'!J58)+('Data Sheet'!I57+'Data Sheet'!I58))/2 -> 10508.5 | J56: =(('Data Sheet'!K57+'Data Sheet'!K58)+('Data Sheet'!J57+'Data Sheet'!J58))/2 -> 13663.5
B57: Return on Equity (ROE) | D57: =D55/D56 -> 0.23439554 | E57: =E55/E56 -> 0.13751235 | F57: =F55/F56 -> 0.26166667 | G57: =G55/G56 -> 0.30953957 | H57: =H55/H56 -> 0.32912822 | I57: =I55/I56 -> 0.31755246 | J57: =J55/J56 -> 0.37128115
B59: ROE - DUPONT Equation
D60: =D54 -> 43921 | E60: =E54 -> 44286 | F60: =F54 -> 44651 | G60: =G54 -> 45016 | H60: =H54 -> 45382 | I60: =I54 -> 45747 | J60: =J54 -> 46112
B61: Net Profit | D61: =D55 -> 1493 | E61: =E55 -> 974 | F61: =F55 -> 2198 | G61: =G55 -> 3274 | H61: =H55 -> 3496 | I61: =I55 -> 3337 | J61: =J55 -> 5073
B62: Revenue | D62: =HistoricalFS!F9 -> 21052 | E62: =HistoricalFS!G9 -> 21644 | F62: =HistoricalFS!H9 -> 28799 | G62: =HistoricalFS!I9 -> 40575 | H62: =HistoricalFS!J9 -> 51084 | I62: =HistoricalFS!K9 -> 60456 | J62: =HistoricalFS!L9 -> 87584
B63: Net Profit Margin (A) | D63: =D61/D62 -> 0.070919628 | E63: =E61/E62 -> 0.045000924 | F63: =F61/F62 -> 0.076322095 | G63: =G61/G62 -> 0.08069008 | H63: =H61/H62 -> 0.068436301 | I63: =I61/I62 -> 0.055197168 | J63: =J61/J62 -> 0.057921538
B65: Revenue | D65: =D62 -> 21052 | E65: =E62 -> 21644 | F65: =F62 -> 28799 | G65: =G62 -> 40575 | H65: =H62 -> 51084 | I65: =I62 -> 60456 | J65: =J62 -> 87584
B66: Average Total Assets | D66: =('Data Sheet'!D66+'Data Sheet'!E66)/2 -> 12626.92 | E66: =('Data Sheet'!E66+'Data Sheet'!F66)/2 -> 14994 | F66: =('Data Sheet'!F66+'Data Sheet'!G66)/2 -> 18816 | G66: =('Data Sheet'!G66+'Data Sheet'!H66)/2 -> 24104 | H66: =('Data Sheet'!H66+'Data Sheet'!I66)/2 -> 29283.5 | I66: =('Data Sheet'!I66+'Data Sheet'!J66)/2 -> 36096 | J66: =('Data Sheet'!J66+'Data Sheet'!K66)/2 -> 50603
B67: Asset Turnover Ratio (B) | D67: =D65/D66 -> 1.6672316 | E67: =E65/E66 -> 1.4435107 | F67: =F65/F66 -> 1.5305591 | G67: =G65/G66 -> 1.6833306 | H67: =H65/H66 -> 1.7444636 | I67: =I65/I66 -> 1.674867 | J67: =J65/J66 -> 1.7308065
B68: Average Total Assets | D68: =D66 -> 12626.92 | E68: =E66 -> 14994 | F68: =F66 -> 18816 | G68: =G66 -> 24104 | H68: =H66 -> 29283.5 | I68: =I66 -> 36096 | J68: =J66 -> 50603
B69: Average Shareholders Equity | D69: =D56 -> 6369.575 | E69: =E56 -> 7083 | F69: =F56 -> 8400 | G69: =G56 -> 10577 | H69: =H56 -> 10622 | I69: =I56 -> 10508.5 | J69: =J56 -> 13663.5
B70: Equity Multiplier (C) | D70: =D68/D69 -> 1.9823803 | E70: =E68/E69 -> 2.1168996 | F70: =F68/F69 -> 2.24 | G70: =G68/G69 -> 2.2789071 | H70: =H68/H69 -> 2.7568725 | I70: =I68/I69 -> 3.4349336 | J70: =J68/J69 -> 3.7035167
B72: Return on Equity (A*B*C) | D72: =D70*D67*D63 -> 0.23439554 | E72: =E70*E67*E63 -> 0.13751235 | F72: =F70*F67*F63 -> 0.26166667 | G72: =G70*G67*G63 -> 0.30953957 | H72: =H70*H67*H63 -> 0.32912822 | I72: =I70*I67*I63 -> 0.31755246 | J72: =J70*J67*J63 -> 0.37128115
B74: Return on Assets (ROA)
D75: =D60 -> 43921 | E75: =E60 -> 44286 | F75: =F60 -> 44651 | G75: =G60 -> 45016 | H75: =H60 -> 45382 | I75: =I60 -> 45747 | J75: =J60 -> 46112
B76: Net Profit | D76: =D61 -> 1493 | E76: =E61 -> 974 | F76: =F61 -> 2198 | G76: =G61 -> 3274 | H76: =H61 -> 3496 | I76: =I61 -> 3337 | J76: =J61 -> 5073
B77: Average Total Assets | D77: =D66 -> 12626.92 | E77: =E66 -> 14994 | F77: =F66 -> 18816 | G77: =G66 -> 24104 | H77: =H66 -> 29283.5 | I77: =I66 -> 36096 | J77: =J66 -> 50603
B78: Return on Assets (ROA) | D78: =D76/D77 -> 0.11823944 | E78: =E76/E77 -> 0.064959317 | F78: =F76/F77 -> 0.11681548 | G78: =G76/G77 -> 0.13582808 | H78: =H76/H77 -> 0.11938464 | I78: =I76/I77 -> 0.092447917 | J78: =J76/J77 -> 0.10025097
B80: ROA - DUPONT Equation
D81: =D75 -> 43921 | E81: =E75 -> 44286 | F81: =F75 -> 44651 | G81: =G75 -> 45016 | H81: =H75 -> 45382 | I81: =I75 -> 45747 | J81: =J75 -> 46112
B82: Net Profit | D82: =D76 -> 1493 | E82: =E76 -> 974 | F82: =F76 -> 2198 | G82: =G76 -> 3274 | H82: =H76 -> 3496 | I82: =I76 -> 3337 | J82: =J76 -> 5073
B83: Revenue | D83: =D65 -> 21052 | E83: =E65 -> 21644 | F83: =F65 -> 28799 | G83: =G65 -> 40575 | H83: =H65 -> 51084 | I83: =I65 -> 60456 | J83: =J65 -> 87584
B84: Net Profit Margin (A) | D84: =D82/D83 -> 0.070919628 | E84: =E82/E83 -> 0.045000924 | F84: =F82/F83 -> 0.076322095 | G84: =G82/G83 -> 0.08069008 | H84: =H82/H83 -> 0.068436301 | I84: =I82/I83 -> 0.055197168 | J84: =J82/J83 -> 0.057921538
B85: Revenue | D85: =D83 -> 21052 | E85: =E83 -> 21644 | F85: =F83 -> 28799 | G85: =G83 -> 40575 | H85: =H83 -> 51084 | I85: =I83 -> 60456 | J85: =J83 -> 87584
B86: Average Total Assets | D86: =D77 -> 12626.92 | E86: =E77 -> 14994 | F86: =F77 -> 18816 | G86: =G77 -> 24104 | H86: =H77 -> 29283.5 | I86: =I77 -> 36096 | J86: =J77 -> 50603
B87: Asset Turnover Ratio (B) | D87: =D85/D86 -> 1.6672316 | E87: =E85/E86 -> 1.4435107 | F87: =F85/F86 -> 1.5305591 | G87: =G85/G86 -> 1.6833306 | H87: =H85/H86 -> 1.7444636 | I87: =I85/I86 -> 1.674867 | J87: =J85/J86 -> 1.7308065
B89: Return on Assets (A*B) | D89: =D87*D84 -> 0.11823944 | E89: =E87*E84 -> 0.064959317 | F89: =F87*F84 -> 0.11681548 | G89: =G87*G84 -> 0.13582808 | H89: =H87*H84 -> 0.11938464 | I89: =I87*I84 -> 0.092447917 | J89: =J87*J84 -> 0.10025097

Sheet Altman's z Score
B3: ='Data Sheet'!B1 -> TITAN COMPANY LTD
B4: (TITAN | BSE Code: 500114)
B5: =CONCATENATE("INR "&'Data Sheet'!B9) -> INR 406996.69
B6: 52 Week (High - INR 4,679.80 & Low - 3,303.10)
B8: Altman's Z Score Analysis
B9: Titan Company Limited is an Indian fashion accessories company that mainly manufactures items such as jewellery, watches and eyewear. Part of the Tata Group and started as a joint venture with TIDCO, the company has its corporate headquarters in Electronic City, Bangalore and registered office in Hosur, Tamil Nadu. In 1994, Titan diversified into jewellery with Tanishq and subsequently into eyewear with Titan Eyeplus.
B13: Financial Summary
B51: Altman's Z Score Analysis Calculation
B53: Working Capital/Total Assets
C54: =HistoricalFS!F5 -> 43921 | D54: =HistoricalFS!G5 -> 44286 | E54: =HistoricalFS!H5 -> 44651 | F54: =HistoricalFS!I5 -> 45016 | G54: =HistoricalFS!J5 -> 45382 | H54: =HistoricalFS!K5 -> 45747 | I54: =HistoricalFS!L5 -> 46112
B55: Working Capital | C55: ='Data Sheet'!E65-'Data Sheet'!E60 -> 7422 | D55: ='Data Sheet'!F65-'Data Sheet'!F60 -> 7756 | E55: ='Data Sheet'!G65-'Data Sheet'!G60 -> 13655 | F55: ='Data Sheet'!H65-'Data Sheet'!H60 -> 15561 | G55: ='Data Sheet'!I65-'Data Sheet'!I60 -> 18770 | H55: ='Data Sheet'!J65-'Data Sheet'!J60 -> 26246 | I55: ='Data Sheet'!K65-'Data Sheet'!K60 -> 35777
B56: Total Assets | C56: ='Data Sheet'!E66 -> 13544 | D56: ='Data Sheet'!F66 -> 16444 | E56: ='Data Sheet'!G66 -> 21188 | F56: ='Data Sheet'!H66 -> 27020 | G56: ='Data Sheet'!I66 -> 31547 | H56: ='Data Sheet'!J66 -> 40645 | I56: ='Data Sheet'!K66 -> 60561
B57: Working Capital/Total Assets (A) | C57: =C55/C56 -> 0.54799173 | D57: =D55/D56 -> 0.4716614 | E57: =E55/E56 -> 0.64446857 | F57: =F55/F56 -> 0.57590674 | G57: =G55/G56 -> 0.59498526 | H57: =H55/H56 -> 0.64573748 | I57: =I55/I56 -> 0.59075973
B59: Retained Earnings/Total Assets
C60: =C54 -> 43921 | D60: =D54 -> 44286 | E60: =E54 -> 44651 | F60: =F54 -> 45016 | G60: =G54 -> 45382 | H60: =H54 -> 45747 | I60: =I54 -> 46112
B61: Retained Earnings | C61: =HistoricalFS!F9*HistoricalFS!F53 -> 16032.233 | D61: =HistoricalFS!G9*HistoricalFS!G53 -> 13733.051 | E61: =HistoricalFS!H9*HistoricalFS!H53 -> 20053.171 | F61: =HistoricalFS!I9*HistoricalFS!I53 -> 29545.144 | G61: =HistoricalFS!J9*HistoricalFS!J53 -> 36778.727 | H61: =HistoricalFS!K9*HistoricalFS!K53 -> 42719.583 | I61: =HistoricalFS!L9*HistoricalFS!L53 -> 64535.579
B62: Total Assets | C62: =C56 -> 13544 | D62: =D56 -> 16444 | E62: =E56 -> 21188 | F62: =F56 -> 27020 | G62: =G56 -> 31547 | H62: =H56 -> 40645 | I62: =I56 -> 60561
B63: Retained Earnings/Total Assets (B) | C63: =C61/C62 -> 1.1837148 | D63: =D61/D62 -> 0.83514056 | E63: =E61/E62 -> 0.94644001 | F63: =F61/F62 -> 1.0934546 | G63: =G61/G62 -> 1.1658391 | H63: =H61/H62 -> 1.0510415 | I63: =I61/I62 -> 1.0656293
B65: EBIT/Total Assets
C66: =C60 -> 43921 | D66: =D60 -> 44286 | E66: =E60 -> 44651 | F66: =F60 -> 45016 | G66: =G60 -> 45382 | H66: =H60 -> 45747 | I66: =I60 -> 46112
B67: EBIT | C67: =HistoricalFS!F30 -> 2268 | D67: =HistoricalFS!G30 -> 1530 | E67: =HistoricalFS!H30 -> 3122 | F67: =HistoricalFS!I30 -> 4747 | G67: =HistoricalFS!J30 -> 5242 | H67: =HistoricalFS!K30 -> 5488 | I67: =HistoricalFS!L30 -> 7981
B68: Total Assets | C68: =C62 -> 13544 | D68: =D62 -> 16444 | E68: =E62 -> 21188 | F68: =F62 -> 27020 | G68: =G62 -> 31547 | H68: =H62 -> 40645 | I68: =I62 -> 60561
B69: EBIT/Total Assets (C) | C69: =C67/C68 -> 0.16745422 | D69: =D67/D68 -> 0.093043055 | E69: =E67/E68 -> 0.14734756 | F69: =F67/F68 -> 0.17568468 | G69: =G67/G68 -> 0.16616477 | H69: =H67/H68 -> 0.13502276 | I69: =I67/I68 -> 0.13178448
B71: Market Cap./Long Term Liabilities
C72: =C66 -> 43921 | D72: =D66 -> 44286 | E72: =E66 -> 44651 | F72: =F66 -> 45016 | G72: =G66 -> 45382 | H72: =H66 -> 45747 | I72: =I66 -> 46112
B73: Market Capitalization (In Crs) | C73: ='Data Sheet'!E93*'Data Sheet'!E95 -> 82893.886 | D73: ='Data Sheet'!F93*'Data Sheet'!F95 -> 138323.68 | E73: ='Data Sheet'!G93*'Data Sheet'!G95 -> 225159.4 | F73: ='Data Sheet'!H93*'Data Sheet'!H95 -> 223272.82 | G73: ='Data Sheet'!I93*'Data Sheet'!I95 -> 337523.8 | H73: ='Data Sheet'!J93*'Data Sheet'!J95 -> 271964.21 | I73: ='Data Sheet'!K93*'Data Sheet'!K95 -> 407003.03
B74: Long Term Liability | C74: ='Data Sheet'!E59 -> 3562 | D74: ='Data Sheet'!F59 -> 5638 | E74: ='Data Sheet'!G59 -> 7275 | F74: ='Data Sheet'!H59 -> 9367 | G74: ='Data Sheet'!I59 -> 15528 | H74: ='Data Sheet'!J59 -> 20777 | I74: ='Data Sheet'!K59 -> 30621
B75: Market Cap./Long Term Liab. (D) | C75: =C73/C74 -> 23.271725 | D75: =D73/D74 -> 24.534175 | E75: =E73/E74 -> 30.949745 | F75: =F73/F74 -> 23.836108 | G75: =G73/G74 -> 21.736463 | H75: =H73/H74 -> 13.089677 | I75: =I73/I74 -> 13.291631
B77: Sales/Total Assets
C78: =C54 -> 43921 | D78: =D54 -> 44286 | E78: =E54 -> 44651 | F78: =F54 -> 45016 | G78: =G54 -> 45382 | H78: =H54 -> 45747 | I78: =I54 -> 46112
B79: Sales | C79: =HistoricalFS!F9 -> 21052 | D79: =HistoricalFS!G9 -> 21644 | E79: =HistoricalFS!H9 -> 28799 | F79: =HistoricalFS!I9 -> 40575 | G79: =HistoricalFS!J9 -> 51084 | H79: =HistoricalFS!K9 -> 60456 | I79: =HistoricalFS!L9 -> 87584
B80: Total Assets | C80: =C68 -> 13544 | D80: =D68 -> 16444 | E80: =E68 -> 21188 | F80: =F68 -> 27020 | G80: =G68 -> 31547 | H80: =H68 -> 40645 | I80: =I68 -> 60561
B81: Sales/Total Assets (E) | C81: =C79/C80 -> 1.5543414 | D81: =D79/D80 -> 1.3162248 | E81: =E79/E80 -> 1.3592128 | F81: =F79/F80 -> 1.5016654 | G81: =G79/G80 -> 1.6192982 | H81: =H79/H80 -> 1.4874154 | I81: =I79/I80 -> 1.4462113
B83: Altman's Z Score
C84: =C78 -> 43921 | D84: =D78 -> 44286 | E84: =E78 -> 44651 | F84: =F78 -> 45016 | G84: =G78 -> 45382 | H84: =H78 -> 45747 | I84: =I78 -> 46112
B85: Final Score | C85: =(C57*1.2)+(C63*1.4)+(C69*3.3)+(C75*0.6)+(C81*1) -> 18.384766 | D85: =(D57*1.2)+(D63*1.4)+(D69*3.3)+(D75*0.6)+(D81*1) -> 18.078962 | E85: =(E57*1.2)+(E63*1.4)+(E69*3.3)+(E75*0.6)+(E81*1) -> 22.513685 | F85: =(F57*1.2)+(F63*1.4)+(F69*3.3)+(F75*0.6)+(F81*1) -> 18.605014 | G85: =(G57*1.2)+(G63*1.4)+(G69*3.3)+(G75*0.6)+(G81*1) -> 17.555677 | H85: =(H57*1.2)+(H63*1.4)+(H69*3.3)+(H75*0.6)+(H81*1) -> 12.03314 | I85: =(I57*1.2)+(I63*1.4)+(I69*3.3)+(I75*0.6)+(I81*1) -> 12.056871
B86: Financial Stability | C86: =IF(C85<1.81,"Distressed",IF(C85>3,"Strong","Grey Zone")) -> Strong | D86: =IF(D85<1.81,"Distressed",IF(D85>3,"Strong","Grey Zone")) -> Strong | E86: =IF(E85<1.81,"Distressed",IF(E85>3,"Strong","Grey Zone")) -> Strong | F86: =IF(F85<1.81,"Distressed",IF(F85>3,"Strong","Grey Zone")) -> Strong | G86: =IF(G85<1.81,"Distressed",IF(G85>3,"Strong","Grey Zone")) -> Strong | H86: =IF(H85<1.81,"Distressed",IF(H85>3,"Strong","Grey Zone")) -> Strong | I86: =IF(I85<1.81,"Distressed",IF(I85>3,"Strong","Grey Zone")) -> Strong

Sheet RawFS
B2: Particulars | C2: 42064 | D2: 42430 | E2: 42795 | F2: 43160 | G2: 43525 | H2: 43891 | I2: 44256 | J2: 44621 | K2: 44986 | L2: 45352 | M2: 45717 | N2: 46082
B4: Equity Capital | C4: 89 | D4: 89 | E4: 89 | F4: 89 | G4: 89 | H4: 89 | I4: 89 | J4: 89 | K4: 89 | L4: 89 | M4: 89 | N4: 89
B5: Reserves | C5: 2995 | D5: 3418 | E5: 4144 | F5: 5001 | G5: 5981 | H5: 6580 | I5: 7408 | J5: 9214 | K5: 11762 | L5: 9304 | M5: 11535 | N5: 15614
B6: Borrowings -
B7: Long term Borrowings | C7: 0 | D7: 0 | E7: 0 | F7: 0 | G7: 32 | H7: 17 | I7: 9 | J7: 2 | K7: 0 | L7: 3302 | M7: 595 | N7: 93
B8: Short term Borrowings | C8: 100 | D8: 113 | E8: 1882 | F8: 1691 | G8: 2353 | H8: 2291 | I8: 4367 | J8: 5914 | K8: 7494 | L8: 9877 | M8: 17501 | N8: 27355
B9: Lease Liabilities | C9: 0 | D9: 0 | E9: 0 | F9: 0 | G9: 0 | H9: 1243 | I9: 1256 | J9: 1359 | K9: 1873 | L9: 2349 | M9: 2681 | N9: 3173
B10: Other Borrowings | C10: 0 | D10: 0 | E10: 0 | F10: 0 | G10: 8 | H10: 11 | I10: 6 | J10: 0 | K10: 0 | L10: 0 | M10: 0 | N10: 0
B11: Other Liabilities -
B12: Non controlling int | C12: 0 | D12: 0 | E12: 26 | F12: -2 | G12: 14 | H12: 4 | I12: 5 | J12: 30 | K12: 53 | L12: 0 | M12: 0 | N12: 0
B13: Trade Payables | C13: 1940 | D13: 1655 | E13: 783 | F13: 878 | G13: 906 | H13: 596 | I13: 789 | J13: 1294 | K13: 1214 | L13: 1410 | M13: 1963 | N13: 2864
B14: Advance from Customers | C14: 160 | D14: 710 | E14: 943 | F14: 233 | G14: 290 | H14: 386 | I14: 479 | J14: 532 | K14: 718 | L14: 1085 | M14: 2140 | N14: 4745
B15: Other liability items | C15: 585 | D15: 358 | E15: 541 | F15: 1631 | G15: 2037 | H15: 2327 | I15: 2036 | J15: 2754 | K15: 3817 | L15: 4131 | M15: 4141 | N15: 6628
B16: Total Liabilities | C16: 5868 | D16: 6342 | E16: 8408 | F16: 9521 | G16: 11710 | H16: 13544 | I16: 16444 | J16: 21188 | K16: 27020 | L16: 31547 | M16: 40645 | N16: 60561
B18: Fixed Assets -
B19: Land | C19: 104 | D19: 85 | E19: 85 | F19: 85 | G19: 85 | H19: 108 | I19: 108 | J19: 136 | K19: 144 | L19: 163 | M19: 163 | N19: 440
B20: Building | C20: 156 | D20: 137 | E20: 198 | F20: 341 | G20: 386 | H20: 1473 | I20: 1617 | J20: 1853 | K20: 2403 | L20: 3546 | M20: 4177 | N20: 5239
B21: Plant Machinery | C21: 719 | D21: 445 | E21: 473 | F21: 563 | G21: 630 | H21: 724 | I21: 739 | J21: 768 | K21: 838 | L21: 899 | M21: 1012 | N21: 1197
B22: Equipments | C22: 24 | D22: 18 | E22: 24 | F22: 34 | G22: 50 | H22: 70 | I22: 76 | J22: 96 | K22: 130 | L22: 110 | M22: 127 | N22: 176
B23: Computers | C23: 0 | D23: 0 | E23: 46 | F23: 72 | G23: 92 | H23: 119 | I23: 142 | J23: 159 | K23: 204 | L23: 212 | M23: 228 | N23: 264
B24: Furniture n fittings | C24: 189 | D24: 107 | E24: 138 | F24: 203 | G24: 251 | H24: 313 | I24: 309 | J24: 321 | K24: 376 | L24: 173 | M24: 193 | N24: 379
B25: Vehicles | C25: 17 | D25: 11 | E25: 10 | F25: 16 | G25: 22 | H25: 28 | I25: 30 | J25: 38 | K25: 40 | L25: 50 | M25: 57 | N25: 68
B26: Intangible Assets | C26: 0 | D26: 13 | E26: 318 | F26: 319 | G26: 319 | H26: 333 | I26: 320 | J26: 320 | K26: 320 | L26: 320 | M26: 320 | N26: 1782
B27: Other fixed assets | C27: 73 | D27: 20 | E27: 26 | F27: 69 | G27: 96 | H27: 135 | I27: 158 | J27: 157 | K27: 205 | L27: 305 | M27: 369 | N27: 540
B28: Gross Block | C28: 1282 | D28: 836 | E28: 1318 | F28: 1704 | G28: 1931 | H28: 3303 | I28: 3499 | J28: 3848 | K28: 4660 | L28: 5778 | M28: 6646 | N28: 10085
B29: Accumulated Depreciation | C29: 583 | D29: 66 | E29: 130 | F29: 230 | G29: 365 | H29: 670 | I29: 976 | J29: 1304 | K29: 1662 | L29: 2069 | M29: 2584 | N29: 3207
B30: Net Block | C30: =C28-C29 -> 699 | D30: =D28-D29 -> 770 | E30: =E28-E29 -> 1188 | F30: =F28-F29 -> 1474 | G30: =G28-G29 -> 1566 | H30: =H28-H29 -> 2633 | I30: =I28-I29 -> 2523 | J30: =J28-J29 -> 2544 | ... N30: =N28-N29 -> 6878
B32: CWIP | C32: 55 | D32: 107 | E32: 152 | F32: 43 | G32: 32 | H32: 18 | I32: 32 | J32: 85 | K32: 144 | L32: 97 | M32: 105 | N32: 163
B33: Investments | C33: 3 | D33: 30 | E33: 431 | F33: 36 | G33: 108 | H33: 158 | I33: 2824 | J33: 294 | K33: 2515 | L33: 2345 | M33: 1988 | N33: 3506
B35: Other Assets -
B36: Inventories | C36: 4049 | D36: 4447 | E36: 4926 | F36: 5925 | G36: 7039 | H36: 8103 | I36: 8408 | J36: 13609 | K36: 16584 | L36: 19051 | M36: 28184 | N36: 42743
B37: Trade receivables | C37: 190 | D37: 192 | E37: 208 | F37: 296 | G37: 420 | H37: 312 | I37: 366 | J37: 565 | K37: 674 | L37: 1018 | M37: 1068 | N37: 916
B38: Cash Equivalents | C38: 214 | D38: 116 | E38: 779 | F38: 618 | G38: 1066 | H38: 381 | I38: 560 | J38: 1573 | K38: 1343 | L38: 1526 | M38: 1584 | N38: 1917
B39: Loans n Advances | C39: 47 | D39: 87 | E39: 122 | F39: 141 | G39: 25 | H39: 142 | I39: 109 | J39: 29 | K39: 167 | L39: 151 | M39: 324 | N39: 399
B40: Other asset items | C40: 611 | D40: 591 | E40: 602 | F40: 988 | G40: 1452 | H40: 1797 | I40: 1622 | J40: 2489 | K40: 2595 | L40: 3650 | M40: 3330 | N40: 4039
B41: Total Assets | C41: =SUM(C36:C40,C32:C33,C30) -> 5868 | D41: =SUM(D36:D40,D32:D33,D30) -> 6340 | E41: =SUM(E36:E40,E32:E33,E30) -> 8408 | F41: =SUM(F36:F40,F32:F33,F30) -> 9521 | G41: =SUM(G36:G40,G32:G33,G30) -> 11708 | H41: =SUM(H36:H40,H32:H33,H30) -> 13544 | I41: =SUM(I36:I40,I32:I33,I30) -> 16444 | J41: =SUM(J36:J40,J32:J33,J30) -> 21188 | ... N41: =SUM(N36:N40,N32:N33,N30) -> 60561
B43: Particulars | C43: 42064 | D43: 42430 | E43: 42795 | F43: 43160 | G43: 43525 | H43: 43891 | I43: 44256 | J43: 44621 | K43: 44986 | L43: 45352 | M43: 45717 | N43: 46082
B45: Cash from Operating Activity -
B46: Profit from operations | C46: 1163 | D46: 942 | E46: 1073 | F46: 1642 | G46: 2183 | H46: 2481 | I46: 1789 | J46: 3298 | K46: 4937 | L46: 5404 | M46: 5774 | N46: 8447
B47: Receivables | C47: -39 | D47: 0 | E47: -12 | F47: -90 | G47: -139 | H47: 109 | I47: -59 | J47: -207 | K47: -112 | L47: -348 | M47: -95 | N47: 210
B48: Inventory | C48: -180 | D48: -398 | E48: -448 | F48: -996 | G48: -1120 | H48: -1057 | I48: -316 | J48: -5199 | K48: -2977 | L48: -2462 | M48: -9072 | N48: -11592
B49: Payables | C49: 1079 | D49: -245 | E49: 238 | F49: 95 | G49: 32 | H49: -310 | I49: 195 | J49: 504 | K49: -89 | L49: 196 | M49: 564 | N49: 472
B50: Loans Advances | C50: -71 | D50: -66 | E50: 0 | F50: 3 | G50: -24 | H50: -20 | I50: -8 | J50: -3 | K50: -18 | L50: -21 | M50: 4 | N50: -8
B51: Operating borrowings | C51: 0 | D51: 0 | E51: 763 | F51: -270 | G51: 741 | H51: -768 | I51: 2625 | J51: 1188 | K51: -99 | L51: 42 | M51: 2468 | N51: 7304
B52: Other WC items | C52: -1204 | D52: 545 | E52: 375 | F52: 22 | G52: 206 | H52: -226 | I52: 184 | J52: 497 | K52: 882 | L52: 57 | M52: 905 | N52: 2494
B53: Working capital changes | C53: -415 | D53: -163 | E53: 916 | F53: -1237 | G53: -304 | H53: -2272 | I53: 2621 | J53: -3220 | K53: -2413 | L53: -2536 | M53: -5226 | N53: -1120
B54: Direct taxes | C54: -245 | D54: -202 | E54: -277 | F54: -456 | G54: -636 | H54: -557 | I54: -271 | J54: -802 | K54: -1154 | L54: -1173 | M54: -1089 | N54: -1737
B55: CFO | C55: =SUM(C53:C54,C46) -> 503 | D55: =SUM(D53:D54,D46) -> 577 | E55: =SUM(E53:E54,E46) -> 1712 | F55: =SUM(F53:F54,F46) -> -51 | G55: =SUM(G53:G54,G46) -> 1243 | H55: =SUM(H53:H54,H46) -> -348 | I55: =SUM(I53:I54,I46) -> 4139 | J55: =SUM(J53:J54,J46) -> -724 | ... N55: =SUM(N53:N54,N46) -> 5590
B57: Cash from Investing Activity -
B58: Fixed assets purchased | C58: -209 | D58: -254 | E58: -256 | F58: -305 | G58: -265 | H58: -355 | I58: -146 | J58: -224 | K58: -432 | L58: -691 | M58: -494 | N58: -902
B59: Fixed assets sold | C59: 2 | D59: 2 | E59: 5 | F59: 6 | G59: 1 | H59: 10 | I59: 7 | J59: 8 | K59: 12 | L59: 20 | M59: 24 | N59: 25
B60: Investments purchased | C60: -135 | D60: -1078 | E60: -325 | F60: 0 | G60: -36 | H60: -13 | I60: -2656 | J60: -253 | K60: -2104 | L60: -21893 | M60: -15342 | N60: -22035
B61: Investments sold | C61: 135 | D61: 1083 | E61: 0 | F61: 412 | G61: 18 | H61: 0 | I61: 43 | J61: 2870 | K61: 0 | L61: 22213 | M61: 15747 | N61: 20797
B62: Interest received | C62: 77 | D62: 58 | E62: 41 | F62: 64 | G62: 85 | H62: 73 | I62: 49 | J62: 56 | K62: 143 | L62: 249 | M62: 288 | N62: 227
B63: Invest in subsidiaries | C63: 0 | D63: 0 | E63: 0 | F63: 0 | G63: 0 | H63: -39 | I63: 0 | J63: 0 | K63: 0 | L63: 0 | M63: 0 | N63: 0
B64: Investment in group cos | C64: 0 | D64: -18 | E64: 0 | F64: 0 | G64: 0 | H64: 0 | I64: 0 | J64: 0 | K64: 0 | L64: 0 | M64: 0 | N64: 0
B65: Acquisition of companies | C65: 0 | D65: 0 | E65: -385 | F65: 0 | G65: 0 | H65: 0 | I65: 0 | J65: 0 | K65: 0 | L65: 0 | M65: 0 | N65: 0
B66: Inter corporate deposits | C66: -48 | D66: 38 | E66: 5 | F66: -35 | G66: -115 | H66: 200 | I66: -50 | J66: -344 | K66: 294 | L66: -143 | M66: 243 | N66: 0
B67: Other investing items | C67: 60 | D67: 10 | E67: -38 | F67: -43 | G67: -485 | H67: 359 | I67: -46 | J67: -948 | K67: 273 | L67: 56 | M67: 80 | N67: -1077
B68: CFI | C68: =SUM(C58:C67) -> -118 | D68: =SUM(D58:D67) -> -159 | E68: =SUM(E58:E67) -> -953 | F68: =SUM(F58:F67) -> 99 | G68: =SUM(G58:G67) -> -797 | H68: =SUM(H58:H67) -> 235 | I68: =SUM(I58:I67) -> -2799 | J68: =SUM(J58:J67) -> 1165 | ... N68: =SUM(N58:N67) -> -2965
B70: Cash from Financing Activity -
B71: Proceeds from borrowings | C71: 0 | D71: 0 | E71: 0 | F71: 0 | G71: 0 | H71: 693 | I71: 0 | J71: 349 | K71: 1684 | L71: 5629 | M71: 2599 | N71: 3314
B72: Repayment of borrowings | C72: 0 | D72: 0 | E72: 0 | F72: 0 | G72: -39 | H72: 0 | I72: -562 | J72: -7 | K72: -7 | L72: 0 | M72: -378 | N72: -2632
B73: Interest paid fin | C73: -81 | D73: -42 | E73: -38 | F73: -54 | G73: -53 | H73: -399 | I73: -317 | J73: -218 | K73: -300 | L73: -619 | M73: -538 | N73: -1000
B74: Dividends paid | C74: -185 | D74: -394 | E74: -4 | F74: -277 | G74: -397 | H74: -536 | I74: -355 | J74: -355 | K74: -666 | L74: -888 | M74: -976 | N74: -976
B75: Financial liabilities | C75: 0 | D75: 0 | E75: 0 | F75: 0 | G75: 0 | H75: 0 | I75: 0 | J75: -172 | K75: -254 | L75: -318 | M75: -700 | N75: -865
B76: Other financing items | C76: -739 | D76: -68 | E76: -124 | F76: 79 | G76: 0 | H76: 0 | I76: 0 | J76: 0 | K76: 0 | L76: -5133 | M76: -14 | N76: 0
B77: CFF | C77: =SUM(C71:C76) -> -1005 | D77: =SUM(D71:D76) -> -504 | E77: =SUM(E71:E76) -> -166 | F77: =SUM(F71:F76) -> -252 | G77: =SUM(G71:G76) -> -489 | H77: =SUM(H71:H76) -> -242 | I77: =SUM(I71:I76) -> -1234 | J77: =SUM(J71:J76) -> -403 | ... N77: =SUM(N71:N76) -> -2159
B79: Net Cash Flow | C79: =SUM(C77,C68,C55) -> -620 | D79: =SUM(D77,D68,D55) -> -86 | E79: =SUM(E77,E68,E55) -> 593 | F79: =SUM(F77,F68,F55) -> -204 | G79: =SUM(G77,G68,G55) -> -43 | H79: =SUM(H77,H68,H55) -> -355 | I79: =SUM(I77,I68,I55) -> 106 | J79: =SUM(J77,J68,J55) -> 38 | ... N79: =SUM(N77,N68,N55) -> 466
B81: Free Cash Flow | C81: 296 | D81: 324 | E81: 1461 | F81: -350 | G81: 980 | H81: -693 | I81: 4000 | J81: -940 | K81: 950 | L81: 1024 | M81: -1011 | N81: 4713
B82: CFO/OP | C82: 0.65 | D82: 0.83 | E82: 1.71 | F82: 0.25 | G82: 0.94 | H82: 0.08 | I82: 2.56 | J82: 0.02 | K82: 0.52 | L82: 0.54 | M82: 0.1 | N82: 0.88

Sheet Data>

Sheet comps_data
B2: S.No. | C2: Name | D2: CMP Rs. | E2: No. Eq. Shares Cr. | F2: Debt Rs.Cr. | G2: Cash End Rs.Cr. | H2: EV Rs.Cr. | I2: Sales Rs.Cr. | J2: EV / EBITDA | K2: NP 12M Rs.Cr. | L2: EBIDT Ann Rs.Cr.
B3: 1 | C3: Titan Company | D3: 4584.4 | E3: 88.78 | F3: 30621 | G3: 1917 | H3: 435707.03 | I3: 87584 | J3: =H3/L3 -> 52.155498 | K3: 5073 | L3: 8354
B4: 2 | C4: Kalyan Jewellers | D4: 573.55 | E4: 103.27 | F4: 6117.33 | G4: 860.91 | H4: 64486.928 | I4: 35742.86 | J4: =H4/L4 -> 23.890949 | K4: 1350.4 | L4: 2699.22
B5: 3 | C5: Thangamayil Jew. | D5: 6906.5 | E5: 3.11 | F5: 913.21 | G5: 381.23 | H5: 22011.195 | I5: 8499.33 | J5: =H5/L5 -> 38.008004 | K5: 351.65 | L5: 579.12
B6: 4 | C6: Bluestone Jewel | D6: 772.4 | E6: 15.24 | F6: 1699.09 | G6: 511.67 | H6: 12958.796 | I6: 2680.6 | J6: =H6/L6 -> 29.892037 | K6: 53.89 | L6: 433.52
B7: 5 | C7: Sky Gold & Diam. | D7: 653.7 | E7: 15.49 | F7: 869.11 | G7: 235.44 | H7: 10759.483 | I7: 6294.89 | J7: =H7/L7 -> 22.856045 | K7: 281.83 | L7: 470.75
B8: 6 | C8: PC Jeweller | D8: 9.28 | E8: 971.05 | F8: 1166.56 | G8: 136.17 | H8: 10041.734 | I8: 3352.88 | J8: =H8/L8 -> 11.570951 | K8: 714.46 | L8: 867.84
B9: 7 | C9: P N Gadgil Jewe. | D9: 647 | E9: 13.57 | F9: 1737.09 | G9: 504.45 | H9: 10012.43 | I9: 10739.1 | J9: =H9/L9 -> 14.221798 | K9: 409.82 | L9: 704.02
B11: Shareholder's name | C11: No. of Shares (Cr) | D11: Shareholding (%) | E11: Quarter Ending
B12: Tamilnadu Industrial Development Corporation Ltd | C12: 24.747672 | D12: 0.2788 | E12: 46174
B13: Tata Sons Private Limited | C13: 18.50589 | D13: 0.2084 | E13: 46174
B14: Rekha Jhunjhunwala | C14: 3.7643895 | D14: 0.0424 | E14: 46174
B15: Life Insurance Corporation Of India | C15: 1.9224672 | D15: 0.0217 | E15: 46174
B16: Tata Investment Corporation Ltd | C16: 1.787564 | D16: 0.0201 | E16: 46174
B17: Sbi Nifty 50 Etf | C17: 1.5999057 | D17: 0.018 | E17: 46174
B18: Nps Trust A/C Uti Pension Fund Limited-Scheme State Govt | C18: 1.5386048 | D18: 0.0173 | E18: 46174
B19: Tata Chemicals Limited | C19: 1.382618 | D19: 0.0156 | E19: 46174
B20: Icici Prudential Balanced Advantage Fund | C20: 1.1184971 | D20: 0.0126 | E20: 46174
B21: Uti Nifty 50 Etf | C21: 0.9851148 | D21: 0.0111 | E21: 46174

Sheet Data Sheet
A1: COMPANY NAME | B1: TITAN COMPANY LTD | E1: =IF(B2<>B3, "A NEW VERSION OF THE WORKSHEET IS AVAILABLE", "")
A2: LATEST VERSION | B2: 2.1 | E2: PLEASE DO NOT MAKE ANY CHANGES TO THIS SHEET
A3: CURRENT VERSION | B3: 2.1
A5: META
A6: Number of shares | B6: =IF(B9>0, B9/B8, 0) -> 88.778617
A7: Face Value | B7: 1
A8: Current Price | B8: 4584.4
A9: Market Capitalization | B9: 406996.69
A15: PROFIT & LOSS
A16: Report Date | B16: 42825 | C16: 43190 | D16: 43555 | E16: 43921 | F16: 44286 | G16: 44651 | H16: 45016 | I16: 45382 | J16: 45747 | K16: 46112
A17: Sales | B17: 13260.83 | C17: 16119.77 | D17: 19778.52 | E17: 21052 | F17: 21644 | G17: 28799 | H17: 40575 | I17: 51084 | J17: 60456 | K17: 87584
A18: Raw Material Cost | B18: 9821.14 | C18: 12664.83 | D18: 15170.66 | E18: 16033 | F18: 16292 | G18: 26436 | H18: 32589 | I18: 42103 | J18: 55271 | K18: 80243
A19: Change in Inventory | B19: 313.71 | C19: 978.61 | D19: 776.41 | E19: 878 | F19: -122 | G19: 4795 | H19: 2234 | I19: 2671 | J19: 7815 | K19: 9936
A20: Power and Fuel | B20: 43.84 | C20: 45.32 | D20: 48.51 | E20: 52 | F20: 37 | G20: 45 | H20: 59 | I20: 71 | J20: 78 | K20: 87
A21: Other Mfr. Exp | B21: 160.42 | C21: 124.83 | D21: 193.28 | E21: 215 | F21: 141 | G21: 183 | H21: 225 | I21: 286 | J21: 326 | K21: 375
A22: Employee Cost | B22: 894.32 | C22: 906.26 | D22: 1024.44 | E22: 1204 | F22: 1069 | G22: 1356 | H22: 1656 | I22: 1875 | J22: 2164 | K22: 2692
A23: Selling and admin | B23: 1211.16 | C23: 1277.81 | D23: 1454.32 | E23: 1470 | F23: 1029 | G23: 1697 | H23: 2715 | I23: 3249 | J23: 3494 | K23: 4185
A24: Other Expenses | B24: 279.76 | C24: 435.13 | D24: 669.93 | E24: 493 | F24: 1229 | G24: 533 | H24: 683 | I24: 879 | J24: 1244 | K24: 1581
A25: Other Income | B25: -42.38 | C25: 69.93 | D25: 178.48 | E25: 153 | F25: 180 | G25: 177 | H25: 306 | I25: 534 | J25: 487 | K25: 450
A26: Depreciation | B26: 110.53 | C26: 131.43 | D26: 162.84 | E26: 348 | F26: 375 | G26: 399 | H26: 441 | I26: 584 | J26: 693 | K26: 826
A27: Interest | B27: 37.74 | C27: 52.92 | D27: 52.54 | E27: 166 | F27: 203 | G27: 218 | H27: 300 | I27: 619 | J27: 953 | K27: 1180
... A33: Trade Payables | B33: 783 | C33: 878 | D33: 906 | E33: 596 | F33: 789 | G33: 1294 | H33: 1214 | I33: 1410 | J33: 1963 | K33: 2864
A34: EBITDA | B34: =HistoricalFS!C21 -> 1163.9 | C34: =HistoricalFS!D21 -> 1644.2 | D34: =HistoricalFS!E21 -> 1993.79 | E34: =HistoricalFS!F21 -> 2463 | F34: =HistoricalFS!G21 -> 1725 | G34: =HistoricalFS!H21 -> 3344 | H34: =HistoricalFS!I21 -> 4882 | I34: =HistoricalFS!J21 -> 5292 | ... K34: =HistoricalFS!L21 -> 8357
A40: Quarters
A41: Report Date | B41: 45291 | C41: 45382 | D41: 45473 | E41: 45565 | F41: 45657 | G41: 45747 | H41: 45838 | I41: 45930 | J41: 46022 | K41: 46112
A42: Sales | B42: 14164 | C42: 12494 | D42: 13266 | E42: 14534 | F42: 17740 | G42: 14916 | H42: 16523 | I42: 18725 | J42: 25416 | K42: 26920
A43: Expenses | B43: 12599 | C43: 11303 | D43: 12019 | E43: 13298 | F43: 16066 | G43: 13379 | H43: 14693 | I43: 16850 | J43: 22703 | K43: 24982
A44: Other Income | B44: 136 | C44: 159 | D44: 120 | E44: 123 | F44: 128 | G44: 116 | H44: 105 | I44: 113 | J44: -1 | K44: 235
A45: Depreciation | B45: 154 | C45: 158 | D45: 164 | E45: 171 | F45: 175 | G45: 183 | H45: 184 | I45: 189 | J45: 207 | K45: 246
A46: Interest | B46: 169 | C46: 201 | D46: 230 | E46: 240 | F46: 231 | G46: 252 | H46: 271 | I46: 277 | J46: 282 | K46: 350
A47: Profit before tax | B47: 1378 | C47: 991 | D47: 973 | E47: 948 | F47: 1396 | G47: 1218 | H47: 1480 | I47: 1522 | J47: 2223 | K47: 1577
A48: Tax | B48: 325 | C48: 220 | D48: 258 | E48: 244 | F48: 349 | G48: 347 | H48: 389 | I48: 402 | J48: 539 | K48: 398
A49: Net profit | B49: 1053 | C49: 771 | D49: 715 | E49: 704 | F49: 1047 | G49: 871 | H49: 1091 | I49: 1120 | J49: 1684 | K49: 1179
A50: Operating Profit | B50: 1565 | C50: 1191 | D50: 1247 | E50: 1236 | F50: 1674 | G50: 1537 | H50: 1830 | I50: 1875 | J50: 2713 | K50: 1938
A55: BALANCE SHEET
A56: Report Date | B56: 42825 | C56: 43190 | D56: 43555 | E56: 43921 | F56: 44286 | G56: 44651 | H56: 45016 | I56: 45382 | J56: 45747 | K56: 46112
A57: Equity Share Capital | B57: 88.78 | C57: 88.78 | D57: 88.78 | E57: 89 | F57: 89 | G57: 89 | H57: 89 | I57: 89 | J57: 89 | K57: 89
A58: Reserves | B58: 4143.6 | C58: 5001.1 | D58: 5981.37 | E58: 6580 | F58: 7408 | G58: 9214 | H58: 11762 | I58: 9304 | J58: 11535 | K58: 15614
A59: Borrowings | B59: 1882.43 | C59: 1691.01 | D59: 2392.98 | E59: 3562 | F59: 5638 | G59: 7275 | H59: 9367 | I59: 15528 | J59: 20777 | K59: 30621
A60: Other Liabilities | B60: 2292.76 | C60: 2740.15 | D60: 3246.71 | E60: 3313 | F60: 3309 | G60: 4610 | H60: 5802 | I60: 6626 | J60: 8244 | K60: 14237
A61: Total | B61: 8407.57 | C61: 9521.04 | D61: 11709.84 | E61: 13544 | F61: 16444 | G61: 21188 | H61: 27020 | I61: 31547 | J61: 40645 | K61: 60561
A62: Net Block | B62: 1188.72 | C62: 1473.81 | D62: 1566.63 | E62: 2633 | F62: 2523 | G62: 2544 | H62: 2998 | I62: 3709 | J62: 4062 | K62: 6878
A63: Capital Work in Progress | B63: 152.07 | C63: 43.37 | D63: 31.77 | E63: 18 | F63: 32 | G63: 85 | H63: 144 | I63: 97 | J63: 105 | K63: 163
A64: Investments | B64: 430.73 | C64: 35.99 | D64: 108.42 | E64: 158 | F64: 2824 | G64: 294 | H64: 2515 | I64: 2345 | J64: 1988 | K64: 3506
A65: Other Assets | B65: 6636.05 | C65: 7967.87 | D65: 10003.02 | E65: 10735 | F65: 11065 | G65: 18265 | H65: 21363 | I65: 25396 | J65: 34490 | K65: 50014
A66: Total | B66: 8407.57 | C66: 9521.04 | D66: 11709.84 | E66: 13544 | F66: 16444 | G66: 21188 | H66: 27020 | I66: 31547 | J66: 40645 | K66: 60561
A67: Receivables | B67: 207.6 | C67: 295.69 | D67: 420.45 | E67: 312 | F67: 366 | G67: 565 | H67: 674 | I67: 1018 | J67: 1068 | K67: 916
... A70: No. of Equity Shares | B70: 887786160 | C70: 887786160 | D70: 887786160 | E70: 887786160 | F70: 887786160 | G70: 887786160 | H70: 890000000 | I70: 890000000 | J70: 890000000 | K70: 890000000
A71: New Bonus Shares
A72: Face value | B72: 1 | C72: 1 | D72: 1 | E72: 1 | F72: 1 | G72: 1 | H72: 1 | I72: 1 | J72: 1 | K72: 1
A74: Other Assets | B74: =B65-SUM(B67:B69) -> 723.78 | C74: =C65-SUM(C67:C69) -> 1129.43 | D74: =D65-SUM(D67:D69) -> 1477.27 | E74: =E65-SUM(E67:E69) -> 1939 | F74: =F65-SUM(F67:F69) -> 1731 | G74: =G65-SUM(G67:G69) -> 2518 | H74: =H65-SUM(H67:H69) -> 2762 | I74: =I65-SUM(I67:I69) -> 3801 | ... K74: =K65-SUM(K67:K69) -> 4438
A75: EBITDA | B75: =HistoricalFS!C21 -> 1163.9 | C75: =HistoricalFS!D21 -> 1644.2 | D75: =HistoricalFS!E21 -> 1993.79 | E75: =HistoricalFS!F21 -> 2463 | F75: =HistoricalFS!G21 -> 1725 | G75: =HistoricalFS!H21 -> 3344 | H75: =HistoricalFS!I21 -> 4882 | I75: =HistoricalFS!J21 -> 5292 | ... K75: =HistoricalFS!L21 -> 8357
A80: CASH FLOW:
A81: Report Date | B81: 42825 | C81: 43190 | D81: 43555 | E81: 43921 | F81: 44286 | G81: 44651 | H81: 45016 | I81: 45382 | J81: 45747 | K81: 46112
A82: Cash from Operating Activity | B82: 1712.3 | C82: -51.12 | D82: 1242.92 | E82: -348 | F82: 4139 | G82: -724 | H82: 1370 | I82: 1695 | J82: -541 | K82: 5590
A83: Cash from Investing Activity | B83: -953.15 | C83: 97.62 | D83: -796.61 | E83: 235 | F83: -2799 | G83: 1165 | H83: -1814 | I83: -189 | J83: 546 | K83: -2965
A84: Cash from Financing Activity | B84: -165.6 | C84: -252.45 | D84: -488.83 | E84: -242 | F84: -1234 | G84: -403 | H84: 457 | I84: -1329 | J84: -7 | K84: -2159
A85: Net Cash Flow | B85: 593.55 | C85: -205.95 | D85: -42.52 | E85: -355 | F85: 106 | G85: 38 | H85: 13 | I85: 177 | J85: -2 | K85: 466
A90: PRICE: | B90: 462.75 | C90: 942.3 | D90: 1141.85 | E90: 933.7 | F90: 1558.05 | G90: 2536.15 | H90: 2514.9 | I90: 3801.8 | J90: 3063.35 | K90: 3951.4
A92: DERIVED:
A93: Adjusted Equity Shares in Cr | B93: 88.78 | C93: 88.78 | D93: 88.78 | E93: 88.78 | F93: 88.78 | G93: 88.78 | H93: 88.78 | I93: 88.78 | J93: 88.78 | K93: 88.78
A95: PRICE: | B95: 462.75 | C95: 942.3 | D95: 1141.85 | E95: 933.7 | F95: 1558.05 | G95: 2536.15 | H95: 2514.9 | I95: 3801.8 | J95: 3063.35 | K95: =B8 -> 4584.4
A96: Dividend Growth | B96: =B31/HistoricalFS!C45 -> 2.6000225 | C96: =C31/HistoricalFS!D45 -> 3.7499437 | D96: =D31/HistoricalFS!E45 -> 5 | E96: =E31/HistoricalFS!F45 -> 4.0099121 | F96: =F31/HistoricalFS!G45 -> 4.0099121 | G96: =G31/HistoricalFS!H45 -> 7.5185853 | H96: =H31/HistoricalFS!I45 -> 10.02478 | I96: =I31/HistoricalFS!J45 -> 11.027258 | ... K96: =K31/HistoricalFS!L45 -> 15.037171
A97: Dividend Growth Rate | C97: =C96/B96-1 -> 0.44227353 | D97: =D96/C96-1 -> 0.33335336 | E97: =E96/D96-1 -> -0.19801757 | F97: =F96/E96-1 -> 0 | G97: =G96/F96-1 -> 0.875 | H97: =H96/G96-1 -> 0.33333333 | I97: =I96/H96-1 -> 0.1 | J97: =J96/I96-1 -> 0 | K97: =K96/J96-1 -> 0.36363636
A98: Market Price per Share | B98: =B95 -> 462.75 | C98: =C95 -> 942.3 | D98: =D95 -> 1141.85 | E98: =E95 -> 933.7 | F98: =F95 -> 1558.05 | G98: =G95 -> 2536.15 | H98: =H95 -> 2514.9 | I98: =I95 -> 3801.8 | ... K98: =K95 -> 4584.4
A99: Market Capitalization | B99: =B93*B98 -> 41082.945 | C99: =C93*C98 -> 83657.394 | D99: =D93*D98 -> 101373.44 | E99: =E93*E98 -> 82893.886 | F99: =F93*F98 -> 138323.68 | G99: =G93*G98 -> 225159.4 | H99: =H93*H98 -> 223272.82 | I99: =I93*I98 -> 337523.8 | ... K99: =K93*K98 -> 407003.03
A100: Enterprise Value(EV) | B100: =B99+B59-B69 -> 42186.445 | C100: =C99+C59-C69 -> 84730.494 | D100: =D99+D59-D69 -> 102699.94 | E100: =E99+E59-E69 -> 86074.886 | F100: =F99+F59-F69 -> 143401.68 | G100: =G99+G59-G69 -> 230861.4 | H100: =H99+H59-H69 -> 231296.82 | I100: =I99+I59-I69 -> 351525.8 | ... K100: =K99+K59-K69 -> 435707.03
A101: EV/EBITDA | B101: =B100/B34 -> 36.245764 | C101: =C100/C34 -> 51.532961 | D101: =D100/D34 -> 51.50991 | E101: =E100/E34 -> 34.947173 | F101: =F100/F34 -> 83.131408 | G101: =G100/G34 -> 69.037499 | H101: =H100/H34 -> 47.377473 | I101: =I100/I34 -> 66.425889 | ... K101: =K100/K34 -> 52.136775
A102: EV/Sales | B102: =B100/B17 -> 3.1812824 | C102: =C100/C17 -> 5.2563091 | D102: =D100/D17 -> 5.1924989 | E102: =E100/E17 -> 4.0886797 | F102: =F100/F17 -> 6.6254703 | G102: =G100/G17 -> 8.0162991 | H102: =H100/H17 -> 5.7004762 | I102: =I100/I17 -> 6.8813289 | ... K102: =K100/K17 -> 4.9747332
A103: Book Value | B103: =SUM(B57:B58) -> 4232.38 | C103: =SUM(C57:C58) -> 5089.88 | D103: =SUM(D57:D58) -> 6070.15 | E103: =SUM(E57:E58) -> 6669 | F103: =SUM(F57:F58) -> 7497 | G103: =SUM(G57:G58) -> 9303 | H103: =SUM(H57:H58) -> 11851 | I103: =SUM(I57:I58) -> 9393 | ... K103: =SUM(K57:K58) -> 15703
A104: Price to book (P/B) | B104: =B98/B103 -> 0.10933565 | C104: =C98/C103 -> 0.18513207 | D104: =D98/D103 -> 0.18810903 | E104: =E98/E103 -> 0.140006 | F104: =F98/F103 -> 0.20782313 | G104: =G98/G103 -> 0.27261636 | H104: =H98/H103 -> 0.21220994 | I104: =I98/I103 -> 0.40474822 | ... K104: =K98/K103 -> 0.29194421
A105: Price to Earning | B105: =$B$8/HistoricalFS!C47 -> 583.701 | C105: =$B$8/HistoricalFS!D47 -> 369.36141 | D105: =$B$8/HistoricalFS!E47 -> 293.09259 | E105: =$B$8/HistoricalFS!F47 -> 272.60752 | F105: =$B$8/HistoricalFS!G47 -> 417.86759 | G105: =$B$8/HistoricalFS!H47 -> 185.16971 | H105: =$B$8/HistoricalFS!I47 -> 124.31369 | I105: =$B$8/HistoricalFS!J47 -> 116.41963 | ... K105: =$B$8/HistoricalFS!L47 -> 80.229259

Sheet CashFlow
C2: 42064 | D2: 42430 | E2: 42795 | F2: 43160 | G2: 43525 | H2: 43891 | I2: 44256 | J2: 44621 | K2: 44986 | L2: 45352 | M2: 45717 | N2: 46082
B3: Cash from Operating Activity - | C3: 503 | D3: 576 | E3: 1712 | F3: -51 | G3: 1243 | H3: -348 | I3: 4139 | J3: -724 | K3: 1370 | L3: 1695 | M3: -541 | N3: 5590
B4: Profit from operations | C4: 1163 | D4: 942 | E4: 1073 | F4: 1642 | G4: 2183 | H4: 2481 | I4: 1789 | J4: 3298 | K4: 4937 | L4: 5404 | M4: 5774 | N4: 8447
B5: Receivables | C5: -39 | D5: 0 | E5: -12 | F5: -90 | G5: -139 | H5: 109 | I5: -59 | J5: -207 | K5: -112 | L5: -348 | M5: -95 | N5: 210
B6: Inventory | C6: -180 | D6: -398 | E6: -448 | F6: -996 | G6: -1120 | H6: -1057 | I6: -316 | J6: -5199 | K6: -2977 | L6: -2462 | M6: -9072 | N6: -11592
B7: Payables | C7: 1079 | D7: -245 | E7: 238 | F7: 95 | G7: 32 | H7: -310 | I7: 195 | J7: 504 | K7: -89 | L7: 196 | M7: 564 | N7: 472
B8: Loans Advances | C8: -71 | D8: -66 | E8: 0 | F8: 3 | G8: -24 | H8: -20 | I8: -8 | J8: -3 | K8: -18 | L8: -21 | M8: 4 | N8: -8
B9: Operating borrowings | C9: 0 | D9: 0 | E9: 763 | F9: -270 | G9: 741 | H9: -768 | I9: 2625 | J9: 1188 | K9: -99 | L9: 42 | M9: 2468 | N9: 7304
B10: Other WC items | C10: -1204 | D10: 545 | E10: 375 | F10: 22 | G10: 206 | H10: -226 | I10: 184 | J10: 497 | K10: 882 | L10: 57 | M10: 905 | N10: 2494
B11: Working capital changes | C11: -415 | D11: -163 | E11: 916 | F11: -1237 | G11: -304 | H11: -2272 | I11: 2621 | J11: -3220 | K11: -2413 | L11: -2536 | M11: -5226 | N11: -1120
B12: Direct taxes | C12: -245 | D12: -202 | E12: -277 | F12: -456 | G12: -636 | H12: -557 | I12: -271 | J12: -802 | K12: -1154 | L12: -1173 | M12: -1089 | N12: -1737
B13: Cash from Investing Activity - | C13: -118 | D13: -159 | E13: -953 | F13: 98 | G13: -797 | H13: 235 | I13: -2799 | J13: 1165 | K13: -1814 | L13: -189 | M13: 546 | N13: -2965
B14: Fixed assets purchased | C14: -209 | D14: -254 | E14: -256 | F14: -305 | G14: -265 | H14: -355 | I14: -146 | J14: -224 | K14: -432 | L14: -691 | M14: -494 | N14: -902
... B31: Net Cash Flow | C31: -620 | D31: -88 | E31: 594 | F31: -206 | G31: -43 | H31: -355 | I31: 106 | J31: 38 | K31: 13 | L31: 177 | M31: -2 | N31: 466

Sheet peer companies
B2: S.No. | C2: Name | D2: CMP Rs. | E2: No. Eq. Shares Cr. | F2: Debt Rs.Cr. | G2: Cash End Rs.Cr. | H2: EV Rs.Cr. | I2: Sales Rs.Cr. | J2: EV / EBITDA | K2: NP 12M Rs.Cr. | L2: EBIDT Ann Rs.Cr. | M2: Total Equity
B3: 1 | C3: Titan Company | D3: 4638.1 | E3: 88.78 | F3: 30621 | G3: 1917 | H3: 440468.1 | I3: 87584 | J3: 49.44 | K3: 5073 | L3: 8910 | M3: =D3*E3 -> 411770.52
B4: 2 | C4: Kalyan Jewellers | D4: 574.4 | E4: 103.27 | F4: 6117.33 | G4: 860.91 | H4: 64577.02 | I4: 35742.86 | J4: 23.92 | K4: 1350.4 | L4: 2699.22 | M4: =D4*E4 -> 59318.288
B5: 3 | C5: Thangamayil Jew. | D5: 6436 | E5: 3.11 | F5: 913.21 | G5: 381.23 | H5: 20536.37 | I5: 8499.33 | J5: 35.46 | K5: 351.65 | L5: 579.12 | M5: =D5*E5 -> 20015.96
B6: 4 | C6: Rajesh Exports | D6: 87.5 | E6: 29.53 | F6: 1015.9 | G6: 2615.22 | H6: 984.19 | I6: 778716.04 | J6: 2.59 | K6: 112.5 | L6: 380.05 | M6: =D6*E6 -> 2583.875

Sheet Raw Data
B2: Date | C2: Close | D2: Volume | M2: 3 Sep-24 | N2: 3 Dec-24 | O2: 3 Mar-25 | P2: 3 Jun-25 | Q2: 3 Sep-25 | R2: 3 Dec-25 | S2: 3 Mar-26 | T2: 3 Jun-26
B3: 46213.646 | C3: 4584.4 | D3: 7.450567 | K3: Promoters | M3: 0.529 | N3: 0.529 | O3: 0.529 | P3: 0.529 | Q3: 0.529 | R3: 0.529 | S3: 0.529 | T3: 0.529
B4: 46206.646 | C4: 4461.1 | D4: 4.344127 | K4: Total Public | M4: 0.47 | N4: 0.47 | O4: 0.47 | P4: 0.47 | Q4: 0.47 | R4: 0.47 | S4: 0.47 | T4: 0.47
B5: 46198.646 | C5: 4291.3 | D5: 2.383551 | K5: FII | M5: 0.1822 | N5: 0.181 | O5: 0.1781 | P5: 0.1753 | Q5: 0.161 | R5: 0.1554 | S5: 0.1565 | T5: 0.1539
B6: 46192.646 | C6: 4419.9 | D6: 3.984575 | K6: Institutions | M6: 0.1146 | N6: 0.1156 | O6: 0.1218 | P6: 0.1278 | Q6: 0.1416 | R6: 0.15 | S6: 0.1503 | T6: 0.1532
B7: 46185.646 | C7: 4184 | D7: 4.455266
B8: 46178.646 | C8: 4260.2 | D8: 5.0837
B9: 46171.646 | C9: 4074.9 | D9: 3.848266
B10: 46164.646 | C10: 4079.8 | D10: 4.107971
B11: 46157.646 | C11: 4169.1 | D11: 12.774192
B12: 46150.646 | C12: 4509 | D12: 9.175441
B13: 46142.646 | C13: 4385.2 | D13: 2.842029
B14: 46136.646 | C14: 4410 | D14: 4.537996
B15: 46129.646 | C15: 4525.9 | D15: 5.176716
B16: 46122.646 | C16: 4505 | D16: 9.73743
B17: 46114.646 | C17: 4097.2 | D17: 3.885065
B18: 46108.646 | C18: 3981.5 | D18: 5.181673
... B257: 44400.646 | C257: 1700.95 | D257: 3.851113
