Workbook

Sheet Financial>

Sheet HistoricalFS
B2: ="Historical Financial Statement"&" - "&'Data Sheet'!B1 -> Historical Financial Statement - MARUTI SUZUKI INDIA LTD
B3: Years | C3: ='Data Sheet'!B16 -> 42825 | D3: ='Data Sheet'!C16 -> 43190 | E3: ='Data Sheet'!D16 -> 43555 | F3: ='Data Sheet'!E16 -> 43921 | G3: ='Data Sheet'!F16 -> 44286 | H3: ='Data Sheet'!G16 -> 44651 | I3: ='Data Sheet'!H16 -> 45016 | J3: ='Data Sheet'!I16 -> 45382 | ... L3: ='Data Sheet'!K16 -> 46112 | M3: LTM
A5: # | B5: Income Statement
B6: Sales | C6: =IFERROR('Data Sheet'!B17,0) -> 68085 | D6: =IFERROR('Data Sheet'!C17,0) -> 79809.4 | E6: =IFERROR('Data Sheet'!D17,0) -> 86068.5 | F6: =IFERROR('Data Sheet'!E17,0) -> 75660 | G6: =IFERROR('Data Sheet'!F17,0) -> 70372 | H6: =IFERROR('Data Sheet'!G17,0) -> 88329.8 | I6: =IFERROR('Data Sheet'!H17,0) -> 117571.3 | J6: =IFERROR('Data Sheet'!I17,0) -> 141858.2 | ... L6: =IFERROR('Data Sheet'!K17,0) -> 183316 | M6: =IFERROR(SUM('Data Sheet'!H42:K42),0) -> 183316
B7: Sales Growth | D7: =IFERROR(D6/C6-1,0) -> 0.17220239 | E7: =IFERROR(E6/D6-1,0) -> 0.078425599 | F7: =IFERROR(F6/E6-1,0) -> -0.12093275 | G7: =IFERROR(G6/F6-1,0) -> -0.06989162 | H7: =IFERROR(H6/G6-1,0) -> 0.25518388 | I7: =IFERROR(I6/H6-1,0) -> 0.33104909 | J7: =IFERROR(J6/I6-1,0) -> 0.20657167 | K7: =IFERROR(K6/J6-1,0) -> 0.077928523 | ... M7: =IFERROR(M6/L6-1,0) -> 0
B9: COGS | C9: =IFERROR(SUM('Data Sheet'!B18,'Data Sheet'!B20:B22)-1*'Data Sheet'!B19,0) -> 50004 | D9: =IFERROR(SUM('Data Sheet'!C18,'Data Sheet'!C20:C22)-1*'Data Sheet'!C19,0) -> 58985 | E9: =IFERROR(SUM('Data Sheet'!D18,'Data Sheet'!D20:D22)-1*'Data Sheet'!D19,0) -> 64182.2 | F9: =IFERROR(SUM('Data Sheet'!E18,'Data Sheet'!E20:E22)-1*'Data Sheet'!E19,0) -> 57657.1 | G9: =IFERROR(SUM('Data Sheet'!F18,'Data Sheet'!F20:F22)-1*'Data Sheet'!F19,0) -> 55415.6 | H9: =IFERROR(SUM('Data Sheet'!G18,'Data Sheet'!G20:G22)-1*'Data Sheet'!G19,0) -> 71578.8 | I9: =IFERROR(SUM('Data Sheet'!H18,'Data Sheet'!H20:H22)-1*'Data Sheet'!H19,0) -> 92796.1 | J9: =IFERROR(SUM('Data Sheet'!I18,'Data Sheet'!I20:I22)-1*'Data Sheet'!I19,0) -> 108015.2 | ... L9: =IFERROR(SUM('Data Sheet'!K18,'Data Sheet'!K20:K22)-1*'Data Sheet'!K19,0) -> 141625.2 | M9: =IFERROR(SUM('Data Sheet'!H43:K43),0) -> 161876
B10: COGS % Sales | C10: =IFERROR(C9/C6,0) -> 0.7344349 | D10: =IFERROR(D9/D6,0) -> 0.73907334 | E10: =IFERROR(E9/E6,0) -> 0.74571068 | F10: =IFERROR(F9/F6,0) -> 0.76205525 | G10: =IFERROR(G9/G6,0) -> 0.78746661 | H10: =IFERROR(H9/H6,0) -> 0.81035845 | I10: =IFERROR(I9/I6,0) -> 0.7892751 | J10: =IFERROR(J9/J6,0) -> 0.76143078 | ... M10: =IFERROR(M9/M6,0) -> 0.88304349
B12: Gross Profit | C12: =IFERROR(C6-C9,0) -> 18081 | D12: =IFERROR(D6-D9,0) -> 20824.4 | E12: =IFERROR(E6-E9,0) -> 21886.3 | F12: =IFERROR(F6-F9,0) -> 18002.9 | G12: =IFERROR(G6-G9,0) -> 14956.4 | H12: =IFERROR(H6-H9,0) -> 16751 | I12: =IFERROR(I6-I9,0) -> 24775.2 | J12: =IFERROR(J6-J9,0) -> 33843 | ... M12: =IFERROR(M6-M9,0) -> 21440
B13: Gross Margin | C13: =IFERROR(C12/C6,0) -> 0.2655651 | D13: =IFERROR(D12/D6,0) -> 0.26092666 | E13: =IFERROR(E12/E6,0) -> 0.25428932 | F13: =IFERROR(F12/F6,0) -> 0.23794475 | G13: =IFERROR(G12/G6,0) -> 0.21253339 | H13: =IFERROR(H12/H6,0) -> 0.18964155 | I13: =IFERROR(I12/I6,0) -> 0.2107249 | J13: =IFERROR(J12/J6,0) -> 0.23856922 | ... M13: =IFERROR(M12/M6,0) -> 0.11695651
B15: Selling & General Expenses | C15: =IFERROR(SUM('Data Sheet'!B23:B24),0) -> 7659.7 | D15: =IFERROR(SUM('Data Sheet'!C23:C24),0) -> 8706.5 | E15: =IFERROR(SUM('Data Sheet'!D23:D24),0) -> 10830 | F15: =IFERROR(SUM('Data Sheet'!E23:E24),0) -> 10647.9 | G15: =IFERROR(SUM('Data Sheet'!F23:F24),0) -> 9545.8 | H15: =IFERROR(SUM('Data Sheet'!G23:G24),0) -> 10999 | I15: =IFERROR(SUM('Data Sheet'!H23:H24),0) -> 13746 | J15: =IFERROR(SUM('Data Sheet'!I23:I24),0) -> 15216.7 | ... M15: =IFERROR(SUM('Data Sheet'!L23:L24),0) -> 0
B16: S&G Exp % Sales | C16: =IFERROR(C15/C6,0) -> 0.11250202 | D16: =IFERROR(D15/D6,0) -> 0.10909116 | E16: =IFERROR(E15/E6,0) -> 0.12583001 | F16: =IFERROR(F15/F6,0) -> 0.14073354 | G16: =IFERROR(G15/G6,0) -> 0.1356477 | H16: =IFERROR(H15/H6,0) -> 0.12452196 | I16: =IFERROR(I15/I6,0) -> 0.11691629 | J16: =IFERROR(J15/J6,0) -> 0.10726698 | ... M16: =IFERROR(M15/M6,0) -> 0
B18: EBITDA | C18: =IFERROR(C12-C15,0) -> 10421.3 | D18: =IFERROR(D12-D15,0) -> 12117.9 | E18: =IFERROR(E12-E15,0) -> 11056.3 | F18: =IFERROR(F12-F15,0) -> 7355 | G18: =IFERROR(G12-G15,0) -> 5410.6 | H18: =IFERROR(H12-H15,0) -> 5752 | I18: =IFERROR(I12-I15,0) -> 11029.2 | J18: =IFERROR(J12-J15,0) -> 18626.3 | ... L18: =IFERROR(L12-L15,0) -> 21456.2 | M18: =IFERROR(SUM('Data Sheet'!H50:K50,'Data Sheet'!H45:K45),0) -> 28181.7
B19: EBITDA Margin | C19: =IFERROR(C18/C6,0) -> 0.15306308 | D19: =IFERROR(D18/D6,0) -> 0.1518355 | E19: =IFERROR(E18/E6,0) -> 0.12845931 | F19: =IFERROR(F18/F6,0) -> 0.097211208 | G19: =IFERROR(G18/G6,0) -> 0.076885693 | H19: =IFERROR(H18/H6,0) -> 0.065119586 | I19: =IFERROR(I18/I6,0) -> 0.093808608 | J19: =IFERROR(J18/J6,0) -> 0.13130224 | ... M19: =IFERROR(M18/M6,0) -> 0.1537329
B21: Other Income | C21: =IFERROR('Data Sheet'!B25,0) -> 2399.2 | D21: =IFERROR('Data Sheet'!C25,0) -> 2154.6 | E21: =IFERROR('Data Sheet'!D25,0) -> 2664.2 | F21: =IFERROR('Data Sheet'!E25,0) -> 3410.4 | G21: =IFERROR('Data Sheet'!F25,0) -> 3046.3 | H21: =IFERROR('Data Sheet'!G25,0) -> 1860.8 | I21: =IFERROR('Data Sheet'!H25,0) -> 2306.6 | J21: =IFERROR('Data Sheet'!I25,0) -> 4247.6 | ... L21: =IFERROR('Data Sheet'!K25,0) -> 4642.7 | M21: =IFERROR(SUM('Data Sheet'!H44:K44),0) -> 4658.9
B22: Other Income % sales | C22: =IFERROR(C21/C6,0) -> 0.035238305 | D22: =IFERROR(D21/D6,0) -> 0.02699682 | E22: =IFERROR(E21/E6,0) -> 0.030954414 | F22: =IFERROR(F21/F6,0) -> 0.045075337 | G22: =IFERROR(G21/G6,0) -> 0.043288524 | H22: =IFERROR(H21/H6,0) -> 0.021066503 | I22: =IFERROR(I21/I6,0) -> 0.019618733 | J22: =IFERROR(J21/J6,0) -> 0.029942576 | ... M22: =IFERROR(M21/M6,0) -> 0.025414585
B24: Interest | C24: =IFERROR('Data Sheet'!B27,0) -> 89.4 | D24: =IFERROR('Data Sheet'!C27,0) -> 345.8 | E24: =IFERROR('Data Sheet'!D27,0) -> 75.9 | F24: =IFERROR('Data Sheet'!E27,0) -> 134.2 | G24: =IFERROR('Data Sheet'!F27,0) -> 101.8 | H24: =IFERROR('Data Sheet'!G27,0) -> 126.6 | I24: =IFERROR('Data Sheet'!H27,0) -> 187 | J24: =IFERROR('Data Sheet'!I27,0) -> 193.6 | ... L24: =IFERROR('Data Sheet'!K27,0) -> 238.7 | M24: =IFERROR(SUM('Data Sheet'!H46:K46),0) -> 238.7
B25: Interest % Sales | C25: =IFERROR(C24/C6,0) -> 0.0013130646 | D25: =IFERROR(D24/D6,0) -> 0.004332823 | E25: =IFERROR(E24/E6,0) -> 0.00088185573 | F25: =IFERROR(F24/F6,0) -> 0.0017737246 | G25: =IFERROR(G24/G6,0) -> 0.0014465981 | H25: =IFERROR(H24/H6,0) -> 0.0014332649 | I25: =IFERROR(I24/I6,0) -> 0.0015905242 | J25: =IFERROR(J24/J6,0) -> 0.0013647431 | ... M25: =IFERROR(M24/M6,0) -> 0.0013021231
B27: Depreciation | C27: =IFERROR('Data Sheet'!B26,0) -> 2603.9 | D27: =IFERROR('Data Sheet'!C26,0) -> 2759.8 | E27: =IFERROR('Data Sheet'!D26,0) -> 3020.8 | F27: =IFERROR('Data Sheet'!E26,0) -> 3528.4 | G27: =IFERROR('Data Sheet'!F26,0) -> 3034.1 | H27: =IFERROR('Data Sheet'!G26,0) -> 2789 | I27: =IFERROR('Data Sheet'!H26,0) -> 2825.7 | J27: =IFERROR('Data Sheet'!I26,0) -> 5255.8 | ... L27: =IFERROR('Data Sheet'!K26,0) -> 6741.7 | M27: =IFERROR(SUM('Data Sheet'!H45:K45),0) -> 6741.7
B28: Depreciation % Sales | C28: =IFERROR(C27/C6,0) -> 0.038244841 | D28: =IFERROR(D27/D6,0) -> 0.034579887 | E28: =IFERROR(E27/E6,0) -> 0.035097626 | F28: =IFERROR(F27/F6,0) -> 0.046634946 | G28: =IFERROR(G27/G6,0) -> 0.043115159 | H28: =IFERROR(H27/H6,0) -> 0.031574848 | I28: =IFERROR(I27/I6,0) -> 0.024033927 | J28: =IFERROR(J27/J6,0) -> 0.037049674 | ... M28: =IFERROR(M27/M6,0) -> 0.036776386
B30: Earning Before Tax | C30: =IFERROR(SUM(C18,C21)-SUM(C24,C27),0) -> 10127.2 | D30: =IFERROR(SUM(D18,D21)-SUM(D24,D27),0) -> 11166.9 | E30: =IFERROR(SUM(E18,E21)-SUM(E24,E27),0) -> 10623.8 | F30: =IFERROR(SUM(F18,F21)-SUM(F24,F27),0) -> 7102.8 | G30: =IFERROR(SUM(G18,G21)-SUM(G24,G27),0) -> 5321 | H30: =IFERROR(SUM(H18,H21)-SUM(H24,H27),0) -> 4697.2 | I30: =IFERROR(SUM(I18,I21)-SUM(I24,I27),0) -> 10323.1 | J30: =IFERROR(SUM(J18,J21)-SUM(J24,J27),0) -> 17424.5 | ... M30: =IFERROR(SUM(M18,M21)-SUM(M24,M27),0) -> 25860.2
B31: EBT % Sales | C31: =IFERROR(C30/C6,0) -> 0.14874348 | D31: =IFERROR(D30/D6,0) -> 0.13991961 | E31: =IFERROR(E30/E6,0) -> 0.12343424 | F31: =IFERROR(F30/F6,0) -> 0.093877875 | G31: =IFERROR(G30/G6,0) -> 0.07561246 | H31: =IFERROR(H30/H6,0) -> 0.053177976 | I31: =IFERROR(I30/I6,0) -> 0.087802891 | J31: =IFERROR(J30/J6,0) -> 0.1228304 | ... M31: =IFERROR(M30/M6,0) -> 0.14106897
B33: Tax | C33: =IFERROR('Data Sheet'!B29,0) -> 2616.2 | D33: =IFERROR('Data Sheet'!C29,0) -> 3286.2 | E33: =IFERROR('Data Sheet'!D29,0) -> 2973.2 | F33: =IFERROR('Data Sheet'!E29,0) -> 1425.2 | G33: =IFERROR('Data Sheet'!F29,0) -> 931.9 | H33: =IFERROR('Data Sheet'!G29,0) -> 817.7 | I33: =IFERROR('Data Sheet'!H29,0) -> 2112.1 | J33: =IFERROR('Data Sheet'!I29,0) -> 3936.3 | ... L33: =IFERROR('Data Sheet'!K29,0) -> 4439 | M33: =IFERROR(SUM('Data Sheet'!H48:K48),0) -> 4439
B34: Effective Tax Rate | C34: =IFERROR(C33/C30,0) -> 0.25833399 | D34: =IFERROR(D33/D30,0) -> 0.29428042 | E34: =IFERROR(E33/E30,0) -> 0.2798622 | F34: =IFERROR(F33/F30,0) -> 0.20065326 | G34: =IFERROR(G33/G30,0) -> 0.17513625 | H34: =IFERROR(H33/H30,0) -> 0.17408243 | I34: =IFERROR(I33/I30,0) -> 0.20459939 | J34: =IFERROR(J33/J30,0) -> 0.22590605 | ... M34: =IFERROR(M33/M30,0) -> 0.17165374
B36: Net Profit | C36: =IFERROR(C30-C33,0) -> 7511 | D36: =IFERROR(D30-D33,0) -> 7880.7 | E36: =IFERROR(E30-E33,0) -> 7650.6 | F36: =IFERROR(F30-F33,0) -> 5677.6 | G36: =IFERROR(G30-G33,0) -> 4389.1 | H36: =IFERROR(H30-H33,0) -> 3879.5 | I36: =IFERROR(I30-I33,0) -> 8211 | J36: =IFERROR(J30-J33,0) -> 13488.2 | ... M36: =IFERROR(M30-M33,0) -> 21421.2
B37: Net Margin | C37: =IFERROR(C36/C6,0) -> 0.11031798 | D37: =IFERROR(D36/D6,0) -> 0.098744008 | E37: =IFERROR(E36/E6,0) -> 0.088889663 | F37: =IFERROR(F36/F6,0) -> 0.075040973 | G37: =IFERROR(G36/G6,0) -> 0.062369977 | H37: =IFERROR(H36/H6,0) -> 0.043920625 | I37: =IFERROR(I36/I6,0) -> 0.069838472 | J37: =IFERROR(J36/J6,0) -> 0.095082272 | ... M37: =IFERROR(M36/M6,0) -> 0.11685396
B39: No of Equity Shares | C39: =IFERROR('Data Sheet'!B93,0) -> 30.21 | D39: =IFERROR('Data Sheet'!C93,0) -> 30.21 | E39: =IFERROR('Data Sheet'!D93,0) -> 30.21 | F39: =IFERROR('Data Sheet'!E93,0) -> 30.21 | G39: =IFERROR('Data Sheet'!F93,0) -> 30.21 | H39: =IFERROR('Data Sheet'!G93,0) -> 30.21 | I39: =IFERROR('Data Sheet'!H93,0) -> 30.21 | J39: =IFERROR('Data Sheet'!I93,0) -> 31.44 | ... M39: =IFERROR('Data Sheet'!L93,0) -> 0
B41: Earning per Share | C41: =IFERROR(C36/C39,0) -> 248.62628 | D41: =IFERROR(D36/D39,0) -> 260.86395 | E41: =IFERROR(E36/E39,0) -> 253.24727 | F41: =IFERROR(F36/F39,0) -> 187.93777 | G41: =IFERROR(G36/G39,0) -> 145.28633 | H41: =IFERROR(H36/H39,0) -> 128.41774 | I41: =IFERROR(I36/I39,0) -> 271.79742 | J41: =IFERROR(J36/J39,0) -> 429.01399 | ... M41: =IFERROR(M36/M39,0) -> 0
B42: EPS Growth % | D42: =IFERROR(D41/C41-1,0) -> 0.049221142 | E42: =IFERROR(E41/D41-1,0) -> -0.029197914 | F42: =IFERROR(F41/E41-1,0) -> -0.25788827 | G42: =IFERROR(G41/F41-1,0) -> -0.22694448 | H42: =IFERROR(H41/G41-1,0) -> -0.11610581 | I42: =IFERROR(I41/H41-1,0) -> 1.1165099 | J42: =IFERROR(J41/I41-1,0) -> 0.57843293 | K42: =IFERROR(K41/J41-1,0) -> 0.075028543 | L42: =IFERROR(L41/K41-1,0) -> 0.012365347
B44: Dividend per Share | C44: =IFERROR('Data Sheet'!B31/HistoricalFS!C39,0) -> 74.975174 | D44: =IFERROR('Data Sheet'!C31/HistoricalFS!D39,0) -> 79.973519 | E44: =IFERROR('Data Sheet'!D31/HistoricalFS!E39,0) -> 79.973519 | F44: =IFERROR('Data Sheet'!E31/HistoricalFS!F39,0) -> 59.980139 | G44: =IFERROR('Data Sheet'!F31/HistoricalFS!G39,0) -> 44.985104 | H44: =IFERROR('Data Sheet'!G31/HistoricalFS!H39,0) -> 59.980139 | I44: =IFERROR('Data Sheet'!H31/HistoricalFS!I39,0) -> 89.970209 | J44: =IFERROR('Data Sheet'!I31/HistoricalFS!J39,0) -> 125 | ... M44: =IFERROR('Data Sheet'!L31/HistoricalFS!M39,0) -> 0
B45: Dividend payout ratio | C45: =IFERROR(C44/C41,0) -> 0.30155772 | D45: =IFERROR(D44/D41,0) -> 0.30657175 | E45: =IFERROR(E44/E41,0) -> 0.31579223 | F45: =IFERROR(F44/F41,0) -> 0.31914894 | G45: =IFERROR(G44/G41,0) -> 0.30963068 | H45: =IFERROR(H44/H41,0) -> 0.4670705 | I45: =IFERROR(I44/I41,0) -> 0.33101936 | J45: =IFERROR(J44/J41,0) -> 0.29136579 | ... M45: =IFERROR(M44/M41,0) -> 0
B47: Retained Earnings | C47: =IFERROR(IF(C41>C44,1-C45),0) -> 0.69844228 | D47: =IFERROR(IF(D41>D44,1-D45),0) -> 0.69342825 | E47: =IFERROR(IF(E41>E44,1-E45),0) -> 0.68420777 | F47: =IFERROR(IF(F41>F44,1-F45),0) -> 0.68085106 | G47: =IFERROR(IF(G41>G44,1-G45),0) -> 0.69036932 | H47: =IFERROR(IF(H41>H44,1-H45),0) -> 0.5329295 | I47: =IFERROR(IF(I41>I44,1-I45),0) -> 0.66898064 | J47: =IFERROR(IF(J41>J44,1-J45),0) -> 0.70863421 | ... L47: =IFERROR(IF(L41>L44,1-L45),0) -> 0.70015327
A49: # | B49: Balance Sheet
B50: Equity Share Capital | C50: =IFERROR('Data Sheet'!B57,0) -> 151 | D50: =IFERROR('Data Sheet'!C57,0) -> 151 | E50: =IFERROR('Data Sheet'!D57,0) -> 151 | F50: =IFERROR('Data Sheet'!E57,0) -> 151 | G50: =IFERROR('Data Sheet'!F57,0) -> 151 | H50: =IFERROR('Data Sheet'!G57,0) -> 151 | I50: =IFERROR('Data Sheet'!H57,0) -> 151 | J50: =IFERROR('Data Sheet'!I57,0) -> 157.2 | ... L50: =IFERROR('Data Sheet'!K57,0) -> 157.2
B51: Reserves | C51: =IFERROR('Data Sheet'!B58,0) -> 36924.1 | D51: =IFERROR('Data Sheet'!C58,0) -> 42408.4 | E51: =IFERROR('Data Sheet'!D58,0) -> 46941.1 | F51: =IFERROR('Data Sheet'!E58,0) -> 49262 | G51: =IFERROR('Data Sheet'!F58,0) -> 52349.6 | H51: =IFERROR('Data Sheet'!G58,0) -> 55182.5 | I51: =IFERROR('Data Sheet'!H58,0) -> 61640.3 | J51: =IFERROR('Data Sheet'!I58,0) -> 85478.8 | ... L51: =IFERROR('Data Sheet'!K58,0) -> 106999.1
B52: Borrowings | C52: =IFERROR('Data Sheet'!B59,0) -> 483.6 | D52: =IFERROR('Data Sheet'!C59,0) -> 120.8 | E52: =IFERROR('Data Sheet'!D59,0) -> 159.6 | F52: =IFERROR('Data Sheet'!E59,0) -> 184.1 | G52: =IFERROR('Data Sheet'!F59,0) -> 540.9 | H52: =IFERROR('Data Sheet'!G59,0) -> 425.5 | I52: =IFERROR('Data Sheet'!H59,0) -> 1247.3 | J52: =IFERROR('Data Sheet'!I59,0) -> 118.6 | ... L52: =IFERROR('Data Sheet'!K59,0) -> 102.5
B53: Other Liabilities | C53: =IFERROR('Data Sheet'!B60,0) -> 14401.8 | D53: =IFERROR('Data Sheet'!C60,0) -> 17568.2 | E53: =IFERROR('Data Sheet'!D60,0) -> 16717 | F53: =IFERROR('Data Sheet'!E60,0) -> 14030.6 | G53: =IFERROR('Data Sheet'!F60,0) -> 18334.6 | H53: =IFERROR('Data Sheet'!G60,0) -> 18896.5 | I53: =IFERROR('Data Sheet'!H60,0) -> 21558.3 | J53: =IFERROR('Data Sheet'!I60,0) -> 29549.5 | ... L53: =IFERROR('Data Sheet'!K60,0) -> 41622.2
B54: Total Liabilities | C54: =IFERROR('Data Sheet'!B61,0) -> 51960.5 | D54: =IFERROR('Data Sheet'!C61,0) -> 60248.4 | E54: =IFERROR('Data Sheet'!D61,0) -> 63968.7 | F54: =IFERROR('Data Sheet'!E61,0) -> 63627.7 | G54: =IFERROR('Data Sheet'!F61,0) -> 71376.1 | H54: =IFERROR('Data Sheet'!G61,0) -> 74655.5 | I54: =IFERROR('Data Sheet'!H61,0) -> 84596.9 | J54: =IFERROR('Data Sheet'!I61,0) -> 115304.1 | ... L54: =IFERROR('Data Sheet'!K61,0) -> 148881
B56: Fixed Assets Net Block | C56: =IFERROR('Data Sheet'!B62,0) -> 13310.7 | D56: =IFERROR('Data Sheet'!C62,0) -> 13388.8 | E56: =IFERROR('Data Sheet'!D62,0) -> 15437.3 | F56: =IFERROR('Data Sheet'!E62,0) -> 15744.4 | G56: =IFERROR('Data Sheet'!F62,0) -> 14988.7 | H56: =IFERROR('Data Sheet'!G62,0) -> 13747.2 | I56: =IFERROR('Data Sheet'!H62,0) -> 17830.4 | J56: =IFERROR('Data Sheet'!I62,0) -> 27864.8 | ... L56: =IFERROR('Data Sheet'!K62,0) -> 34955.4
B57: Capital Work in Progress | C57: =IFERROR('Data Sheet'!B63,0) -> 1252.3 | D57: =IFERROR('Data Sheet'!C63,0) -> 2132.1 | E57: =IFERROR('Data Sheet'!D63,0) -> 1606.9 | F57: =IFERROR('Data Sheet'!E63,0) -> 1415.2 | G57: =IFERROR('Data Sheet'!F63,0) -> 1496.8 | H57: =IFERROR('Data Sheet'!G63,0) -> 2936.5 | I57: =IFERROR('Data Sheet'!H63,0) -> 2904.1 | J57: =IFERROR('Data Sheet'!I63,0) -> 7734.8 | ... L57: =IFERROR('Data Sheet'!K63,0) -> 9406.2
B58: Investments | C58: =IFERROR('Data Sheet'!B64,0) -> 29150.6 | D58: =IFERROR('Data Sheet'!C64,0) -> 36123.1 | E58: =IFERROR('Data Sheet'!D64,0) -> 37503.6 | F58: =IFERROR('Data Sheet'!E64,0) -> 37488 | G58: =IFERROR('Data Sheet'!F64,0) -> 42944.8 | H58: =IFERROR('Data Sheet'!G64,0) -> 42034.7 | I58: =IFERROR('Data Sheet'!H64,0) -> 49184.3 | J58: =IFERROR('Data Sheet'!I64,0) -> 57296 | ... L58: =IFERROR('Data Sheet'!K64,0) -> 76838.5
B59: Other Assets | C59: =IFERROR('Data Sheet'!B65-SUM('Data Sheet'!B67:B69),0) -> 3757.1 | D59: =IFERROR('Data Sheet'!C65-SUM('Data Sheet'!C67:C69),0) -> 3904.8 | E59: =IFERROR('Data Sheet'!D65-SUM('Data Sheet'!D67:D69),0) -> 3597.7 | F59: =IFERROR('Data Sheet'!E65-SUM('Data Sheet'!E67:E69),0) -> 3759.5 | G59: =IFERROR('Data Sheet'!F65-SUM('Data Sheet'!F67:F69),0) -> 4569.8 | H59: =IFERROR('Data Sheet'!G65-SUM('Data Sheet'!G67:G69),0) -> 7328.1 | I59: =IFERROR('Data Sheet'!H65-SUM('Data Sheet'!H67:H69),0) -> 7051.6 | J59: =IFERROR('Data Sheet'!I65-SUM('Data Sheet'!I67:I69),0) -> 9666.2 | ... L59: =IFERROR('Data Sheet'!K65-SUM('Data Sheet'!K67:K69),0) -> 9438.3
B60: Total Non Current Assets | C60: =IFERROR(SUM(C56:C59),0) -> 47470.7 | D60: =IFERROR(SUM(D56:D59),0) -> 55548.8 | E60: =IFERROR(SUM(E56:E59),0) -> 58145.5 | F60: =IFERROR(SUM(F56:F59),0) -> 58407.1 | G60: =IFERROR(SUM(G56:G59),0) -> 64000.1 | H60: =IFERROR(SUM(H56:H59),0) -> 66046.5 | I60: =IFERROR(SUM(I56:I59),0) -> 76970.4 | J60: =IFERROR(SUM(J56:J59),0) -> 102561.8 | ... L60: =IFERROR(SUM(L56:L59),0) -> 130638.4
B62: Receivables | C62: =IFERROR('Data Sheet'!B67,0) -> 1202.6 | D62: =IFERROR('Data Sheet'!C67,0) -> 1465.4 | E62: =IFERROR('Data Sheet'!D67,0) -> 2312.8 | F62: =IFERROR('Data Sheet'!E67,0) -> 1977.7 | G62: =IFERROR('Data Sheet'!F67,0) -> 1279.9 | H62: =IFERROR('Data Sheet'!G67,0) -> 2034.5 | I62: =IFERROR('Data Sheet'!H67,0) -> 3301.4 | J62: =IFERROR('Data Sheet'!I67,0) -> 4596.8 | ... L62: =IFERROR('Data Sheet'!K67,0) -> 5342
B63: Inventory | C63: =IFERROR('Data Sheet'!B68,0) -> 3263.7 | D63: =IFERROR('Data Sheet'!C68,0) -> 3160.2 | E63: =IFERROR('Data Sheet'!D68,0) -> 3322.6 | F63: =IFERROR('Data Sheet'!E68,0) -> 3213.9 | G63: =IFERROR('Data Sheet'!F68,0) -> 3049 | H63: =IFERROR('Data Sheet'!G68,0) -> 3532.3 | I63: =IFERROR('Data Sheet'!H68,0) -> 4283.5 | J63: =IFERROR('Data Sheet'!I68,0) -> 5318.1 | ... L63: =IFERROR('Data Sheet'!K68,0) -> 11320.6
B64: Cash & Bank | C64: =IFERROR('Data Sheet'!B69,0) -> 23.5 | D64: =IFERROR('Data Sheet'!C69,0) -> 74 | E64: =IFERROR('Data Sheet'!D69,0) -> 187.8 | F64: =IFERROR('Data Sheet'!E69,0) -> 29 | G64: =IFERROR('Data Sheet'!F69,0) -> 3047.1 | H64: =IFERROR('Data Sheet'!G69,0) -> 3042.2 | I64: =IFERROR('Data Sheet'!H69,0) -> 41.6 | J64: =IFERROR('Data Sheet'!I69,0) -> 2827.4 | ... L64: =IFERROR('Data Sheet'!K69,0) -> 1580
B65: Total Current Assets | C65: =IFERROR(SUM(C62:C64),0) -> 4489.8 | D65: =IFERROR(SUM(D62:D64),0) -> 4699.6 | E65: =IFERROR(SUM(E62:E64),0) -> 5823.2 | F65: =IFERROR(SUM(F62:F64),0) -> 5220.6 | G65: =IFERROR(SUM(G62:G64),0) -> 7376 | H65: =IFERROR(SUM(H62:H64),0) -> 8609 | I65: =IFERROR(SUM(I62:I64),0) -> 7626.5 | J65: =IFERROR(SUM(J62:J64),0) -> 12742.3 | ... L65: =IFERROR(SUM(L62:L64),0) -> 18242.6
B67: Total Assets | C67: =IFERROR(SUM(C65,C60),0) -> 51960.5 | D67: =IFERROR(SUM(D65,D60),0) -> 60248.4 | E67: =IFERROR(SUM(E65,E60),0) -> 63968.7 | F67: =IFERROR(SUM(F65,F60),0) -> 63627.7 | G67: =IFERROR(SUM(G65,G60),0) -> 71376.1 | H67: =IFERROR(SUM(H65,H60),0) -> 74655.5 | I67: =IFERROR(SUM(I65,I60),0) -> 84596.9 | J67: =IFERROR(SUM(J65,J60),0) -> 115304.1 | ... L67: =IFERROR(SUM(L65,L60),0) -> 148881
B69: Check | C69: =IFERROR(C67=C54,0) -> TRUE | D69: =IFERROR(D67=D54,0) -> TRUE | E69: =IFERROR(E67=E54,0) -> TRUE | F69: =IFERROR(F67=F54,0) -> TRUE | G69: =IFERROR(G67=G54,0) -> TRUE | H69: =IFERROR(H67=H54,0) -> TRUE | I69: =IFERROR(I67=I54,0) -> TRUE | J69: =IFERROR(J67=J54,0) -> TRUE | ... L69: =IFERROR(L67=L54,0) -> TRUE
A71: # | B71: Cash Flow Statement
B72: Operating Activities
B73: Profit from operations | C73: =IFERROR('Cashflow Data'!E5,0) -> 10413 | D73: =IFERROR('Cashflow Data'!F5,0) -> 12036 | E73: =IFERROR('Cashflow Data'!G5,0) -> 11060 | F73: =IFERROR('Cashflow Data'!H5,0) -> 7503 | G73: =IFERROR('Cashflow Data'!I5,0) -> 5531 | H73: =IFERROR('Cashflow Data'!J5,0) -> 5832 | I73: =IFERROR('Cashflow Data'!K5,0) -> 11112 | J73: =IFERROR('Cashflow Data'!L5,0) -> 18676 | ... L73: =IFERROR('Cashflow Data'!N5,0) -> 21802
B74: Receivables | C74: =IFERROR('Cashflow Data'!E6,0) -> 122 | D74: =IFERROR('Cashflow Data'!F6,0) -> -262 | E74: =IFERROR('Cashflow Data'!G6,0) -> -851 | F74: =IFERROR('Cashflow Data'!H6,0) -> 340 | G74: =IFERROR('Cashflow Data'!I6,0) -> 696 | H74: =IFERROR('Cashflow Data'!J6,0) -> -764 | I74: =IFERROR('Cashflow Data'!K6,0) -> -1258 | J74: =IFERROR('Cashflow Data'!L6,0) -> -1316 | ... L74: =IFERROR('Cashflow Data'!N6,0) -> 1236
B75: Inventory | C75: =IFERROR('Cashflow Data'!E7,0) -> -131 | D75: =IFERROR('Cashflow Data'!F7,0) -> 104 | E75: =IFERROR('Cashflow Data'!G7,0) -> -162 | F75: =IFERROR('Cashflow Data'!H7,0) -> 109 | G75: =IFERROR('Cashflow Data'!I7,0) -> 165 | H75: =IFERROR('Cashflow Data'!J7,0) -> -483 | I75: =IFERROR('Cashflow Data'!K7,0) -> -751 | J75: =IFERROR('Cashflow Data'!L7,0) -> 125 | ... L75: =IFERROR('Cashflow Data'!N7,0) -> -4407
B76: Payables | C76: =IFERROR('Cashflow Data'!E8,0) -> 979 | D76: =IFERROR('Cashflow Data'!F8,0) -> 2128 | E76: =IFERROR('Cashflow Data'!G8,0) -> -858 | F76: =IFERROR('Cashflow Data'!H8,0) -> -2155 | G76: =IFERROR('Cashflow Data'!I8,0) -> 2680 | H76: =IFERROR('Cashflow Data'!J8,0) -> -396 | I76: =IFERROR('Cashflow Data'!K8,0) -> 2008 | J76: =IFERROR('Cashflow Data'!L8,0) -> 3321 | ... L76: =IFERROR('Cashflow Data'!N8,0) -> 5194
B77: Loans Advances | C77: =IFERROR('Cashflow Data'!E9,0) -> 1 | D77: =IFERROR('Cashflow Data'!F9,0) -> 0 | E77: =IFERROR('Cashflow Data'!G9,0) -> -13 | F77: =IFERROR('Cashflow Data'!H9,0) -> -1 | G77: =IFERROR('Cashflow Data'!I9,0) -> -6 | H77: =IFERROR('Cashflow Data'!J9,0) -> -8 | I77: =IFERROR('Cashflow Data'!K9,0) -> 1 | J77: =IFERROR('Cashflow Data'!L9,0) -> -3 | ... L77: =IFERROR('Cashflow Data'!N9,0) -> -1
B78: Other WC items | C78: =IFERROR('Cashflow Data'!E10,0) -> 1222 | D78: =IFERROR('Cashflow Data'!F10,0) -> 839 | E78: =IFERROR('Cashflow Data'!G10,0) -> 569 | F78: =IFERROR('Cashflow Data'!H10,0) -> -863 | G78: =IFERROR('Cashflow Data'!I10,0) -> 801 | H78: =IFERROR('Cashflow Data'!J10,0) -> -1162 | I78: =IFERROR('Cashflow Data'!K10,0) -> 374 | J78: =IFERROR('Cashflow Data'!L10,0) -> -406 | ... L78: =IFERROR('Cashflow Data'!N10,0) -> -387
B79: Working capital changes | C79: =IFERROR('Cashflow Data'!E11,0) -> 2192 | D79: =IFERROR('Cashflow Data'!F11,0) -> 2808 | E79: =IFERROR('Cashflow Data'!G11,0) -> -1315 | F79: =IFERROR('Cashflow Data'!H11,0) -> -2570 | G79: =IFERROR('Cashflow Data'!I11,0) -> 4336 | H79: =IFERROR('Cashflow Data'!J11,0) -> -2813 | I79: =IFERROR('Cashflow Data'!K11,0) -> 373 | J79: =IFERROR('Cashflow Data'!L11,0) -> 1722 | ... L79: =IFERROR('Cashflow Data'!N11,0) -> 1635
B80: Direct taxes | C80: =IFERROR('Cashflow Data'!E12,0) -> -2323 | D80: =IFERROR('Cashflow Data'!F12,0) -> -3056 | E80: =IFERROR('Cashflow Data'!G12,0) -> -3144 | F80: =IFERROR('Cashflow Data'!H12,0) -> -1438 | G80: =IFERROR('Cashflow Data'!I12,0) -> -1011 | H80: =IFERROR('Cashflow Data'!J12,0) -> -1178 | I80: =IFERROR('Cashflow Data'!K12,0) -> -2233 | J80: =IFERROR('Cashflow Data'!L12,0) -> -3597 | ... L80: =IFERROR('Cashflow Data'!N12,0) -> -4337
B81: Cash from Operating Activity | C81: =SUM(C73:C80) -> 12475 | D81: =SUM(D73:D80) -> 14597 | E81: =SUM(E73:E80) -> 5286 | F81: =SUM(F73:F80) -> 925 | G81: =SUM(G73:G80) -> 13192 | H81: =SUM(H73:H80) -> -972 | I81: =SUM(I73:I80) -> 9626 | J81: =SUM(J73:J80) -> 18522 | ... L81: =SUM(L73:L80) -> 20735
B83: Investing Activities
B84: Fixed assets purchased | C84: =IFERROR('Cashflow Data'!E14,0) -> -3391 | D84: =IFERROR('Cashflow Data'!F14,0) -> -3912 | E84: =IFERROR('Cashflow Data'!G14,0) -> -4872 | F84: =IFERROR('Cashflow Data'!H14,0) -> -3437 | G84: =IFERROR('Cashflow Data'!I14,0) -> -2370 | H84: =IFERROR('Cashflow Data'!J14,0) -> -3459 | I84: =IFERROR('Cashflow Data'!K14,0) -> -6347 | J84: =IFERROR('Cashflow Data'!L14,0) -> -9200 | ... L84: =IFERROR('Cashflow Data'!N14,0) -> -10398
B85: Fixed assets sold | C85: =IFERROR('Cashflow Data'!E15,0) -> 16 | D85: =IFERROR('Cashflow Data'!F15,0) -> 26 | E85: =IFERROR('Cashflow Data'!G15,0) -> 170 | F85: =IFERROR('Cashflow Data'!H15,0) -> 37 | G85: =IFERROR('Cashflow Data'!I15,0) -> 42 | H85: =IFERROR('Cashflow Data'!J15,0) -> 136 | I85: =IFERROR('Cashflow Data'!K15,0) -> 100 | J85: =IFERROR('Cashflow Data'!L15,0) -> 45 | ... L85: =IFERROR('Cashflow Data'!N15,0) -> 52
B86: Investments purchased | C86: =IFERROR('Cashflow Data'!E16,0) -> -17716 | D86: =IFERROR('Cashflow Data'!F16,0) -> -47069 | E86: =IFERROR('Cashflow Data'!G16,0) -> -52957 | F86: =IFERROR('Cashflow Data'!H16,0) -> -44205 | G86: =IFERROR('Cashflow Data'!I16,0) -> -44869 | H86: =IFERROR('Cashflow Data'!J16,0) -> -60525 | I86: =IFERROR('Cashflow Data'!K16,0) -> -66597 | J86: =IFERROR('Cashflow Data'!L16,0) -> -65736 | ... L86: =IFERROR('Cashflow Data'!N16,0) -> -108034
B87: Investments sold | C87: =IFERROR('Cashflow Data'!E17,0) -> 11839 | D87: =IFERROR('Cashflow Data'!F17,0) -> 42564 | E87: =IFERROR('Cashflow Data'!G17,0) -> 53986 | F87: =IFERROR('Cashflow Data'!H17,0) -> 46969 | G87: =IFERROR('Cashflow Data'!I17,0) -> 42920 | H87: =IFERROR('Cashflow Data'!J17,0) -> 63579 | I87: =IFERROR('Cashflow Data'!K17,0) -> 61605 | J87: =IFERROR('Cashflow Data'!L17,0) -> 61933 | ... L87: =IFERROR('Cashflow Data'!N17,0) -> 101969
B88: Interest received | C88: =IFERROR('Cashflow Data'!E18,0) -> 36 | D88: =IFERROR('Cashflow Data'!F18,0) -> 68 | E88: =IFERROR('Cashflow Data'!G18,0) -> 124 | F88: =IFERROR('Cashflow Data'!H18,0) -> 96 | G88: =IFERROR('Cashflow Data'!I18,0) -> 67 | H88: =IFERROR('Cashflow Data'!J18,0) -> 174 | I88: =IFERROR('Cashflow Data'!K18,0) -> 194 | J88: =IFERROR('Cashflow Data'!L18,0) -> 372 | ... L88: =IFERROR('Cashflow Data'!N18,0) -> 354
B89: Dividends received | C89: =IFERROR('Cashflow Data'!E19,0) -> 13 | D89: =IFERROR('Cashflow Data'!F19,0) -> 20 | E89: =IFERROR('Cashflow Data'!G19,0) -> 9 | F89: =IFERROR('Cashflow Data'!H19,0) -> 4 | G89: =IFERROR('Cashflow Data'!I19,0) -> 3 | H89: =IFERROR('Cashflow Data'!J19,0) -> 3 | I89: =IFERROR('Cashflow Data'!K19,0) -> 6 | J89: =IFERROR('Cashflow Data'!L19,0) -> 6 | ... L89: =IFERROR('Cashflow Data'!N19,0) -> 11
B90: Redemp n Canc of Shares | C90: =IFERROR('Cashflow Data'!E20,0) -> 22 | D90: =IFERROR('Cashflow Data'!F20,0) -> 0 | E90: =IFERROR('Cashflow Data'!G20,0) -> 0 | F90: =IFERROR('Cashflow Data'!H20,0) -> 0 | G90: =IFERROR('Cashflow Data'!I20,0) -> 0 | H90: =IFERROR('Cashflow Data'!J20,0) -> 0 | I90: =IFERROR('Cashflow Data'!K20,0) -> 0 | J90: =IFERROR('Cashflow Data'!L20,0) -> 0 | ... L90: =IFERROR('Cashflow Data'!N20,0) -> 0
B91: Acquisition of companies | C91: =IFERROR('Cashflow Data'!E21,0) -> 0 | D91: =IFERROR('Cashflow Data'!F21,0) -> 0 | E91: =IFERROR('Cashflow Data'!G21,0) -> 0 | F91: =IFERROR('Cashflow Data'!H21,0) -> -15 | G91: =IFERROR('Cashflow Data'!I21,0) -> -65 | H91: =IFERROR('Cashflow Data'!J21,0) -> -146 | I91: =IFERROR('Cashflow Data'!K21,0) -> 0 | J91: =IFERROR('Cashflow Data'!L21,0) -> -80 | ... L91: =IFERROR('Cashflow Data'!N21,0) -> 0
B92: Other investing items | C92: =IFERROR('Cashflow Data'!E22,0) -> 7 | D92: =IFERROR('Cashflow Data'!F22,0) -> 0 | E92: =IFERROR('Cashflow Data'!G22,0) -> 0 | F92: =IFERROR('Cashflow Data'!H22,0) -> -5 | G92: =IFERROR('Cashflow Data'!I22,0) -> -3019 | H92: =IFERROR('Cashflow Data'!J22,0) -> -1 | I92: =IFERROR('Cashflow Data'!K22,0) -> 3003 | J92: =IFERROR('Cashflow Data'!L22,0) -> 795 | ... L92: =IFERROR('Cashflow Data'!N22,0) -> 1311
B93: Cash from Investing Activities | C93: =SUM(C84:C92) -> -9174 | D93: =SUM(D84:D92) -> -8303 | E93: =SUM(E84:E92) -> -3540 | F93: =SUM(F84:F92) -> -556 | G93: =SUM(G84:G92) -> -7291 | H93: =SUM(H84:H92) -> -239 | I93: =SUM(I84:I92) -> -8036 | J93: =SUM(J84:J92) -> -11865 | ... L93: =SUM(L84:L92) -> -14735
B95: Financial Activities
B96: Proceeds from borrowings | C96: =IFERROR('Cashflow Data'!E24,0) -> 484 | D96: =IFERROR('Cashflow Data'!F24,0) -> 10 | E96: =IFERROR('Cashflow Data'!G24,0) -> 39 | F96: =IFERROR('Cashflow Data'!H24,0) -> 0 | G96: =IFERROR('Cashflow Data'!I24,0) -> 380 | H96: =IFERROR('Cashflow Data'!J24,0) -> 0 | I96: =IFERROR('Cashflow Data'!K24,0) -> 831 | J96: =IFERROR('Cashflow Data'!L24,0) -> 0 | ... L96: =IFERROR('Cashflow Data'!N24,0) -> 0
B97: Repayment of borrowings | C97: =IFERROR('Cashflow Data'!E25,0) -> -231 | D97: =IFERROR('Cashflow Data'!F25,0) -> -373 | E97: =IFERROR('Cashflow Data'!G25,0) -> 0 | F97: =IFERROR('Cashflow Data'!H25,0) -> -46 | G97: =IFERROR('Cashflow Data'!I25,0) -> 0 | H97: =IFERROR('Cashflow Data'!J25,0) -> -110 | I97: =IFERROR('Cashflow Data'!K25,0) -> 0 | J97: =IFERROR('Cashflow Data'!L25,0) -> -1183 | ... L97: =IFERROR('Cashflow Data'!N25,0) -> 0
B98: Interest paid fin | C98: =IFERROR('Cashflow Data'!E26,0) -> -110 | D98: =IFERROR('Cashflow Data'!F26,0) -> -346 | E98: =IFERROR('Cashflow Data'!G26,0) -> -73 | F98: =IFERROR('Cashflow Data'!H26,0) -> -136 | G98: =IFERROR('Cashflow Data'!I26,0) -> -102 | H98: =IFERROR('Cashflow Data'!J26,0) -> -130 | I98: =IFERROR('Cashflow Data'!K26,0) -> -186 | J98: =IFERROR('Cashflow Data'!L26,0) -> -147 | ... L98: =IFERROR('Cashflow Data'!N26,0) -> -204
B99: Dividends paid | C99: =IFERROR('Cashflow Data'!E27,0) -> -1057 | D99: =IFERROR('Cashflow Data'!F27,0) -> -2266 | E99: =IFERROR('Cashflow Data'!G27,0) -> -2417 | F99: =IFERROR('Cashflow Data'!H27,0) -> -2417 | G99: =IFERROR('Cashflow Data'!I27,0) -> -1812 | H99: =IFERROR('Cashflow Data'!J27,0) -> -1359 | I99: =IFERROR('Cashflow Data'!K27,0) -> -1812 | J99: =IFERROR('Cashflow Data'!L27,0) -> -2719 | ... L99: =IFERROR('Cashflow Data'!N27,0) -> -4244
B100: Financial liabilities | C100: =IFERROR('Cashflow Data'!E28,0) -> 0 | D100: =IFERROR('Cashflow Data'!F28,0) -> 0 | E100: =IFERROR('Cashflow Data'!G28,0) -> 0 | F100: =IFERROR('Cashflow Data'!H28,0) -> -10 | G100: =IFERROR('Cashflow Data'!I28,0) -> -11 | H100: =IFERROR('Cashflow Data'!J28,0) -> -8 | I100: =IFERROR('Cashflow Data'!K28,0) -> -46 | J100: =IFERROR('Cashflow Data'!L28,0) -> -13 | ... L100: =IFERROR('Cashflow Data'!N28,0) -> -36
B101: Other financing items | C101: =IFERROR('Cashflow Data'!E29,0) -> -215 | D101: =IFERROR('Cashflow Data'!F29,0) -> -461 | E101: =IFERROR('Cashflow Data'!G29,0) -> -497 | F101: =IFERROR('Cashflow Data'!H29,0) -> -497 | G101: =IFERROR('Cashflow Data'!I29,0) -> 0 | H101: =IFERROR('Cashflow Data'!J29,0) -> 0 | I101: =IFERROR('Cashflow Data'!K29,0) -> 0 | J101: =IFERROR('Cashflow Data'!L29,0) -> 0 | ... L101: =IFERROR('Cashflow Data'!N29,0) -> 0
B102: Cash from Financial Activities | C102: =SUM(C96:C101) -> -1129 | D102: =SUM(D96:D101) -> -3436 | E102: =SUM(E96:E101) -> -2948 | F102: =SUM(F96:F101) -> -3106 | G102: =SUM(G96:G101) -> -1545 | H102: =SUM(H96:H101) -> -1607 | I102: =SUM(I96:I101) -> -1213 | J102: =SUM(J96:J101) -> -4062 | ... L102: =SUM(L96:L101) -> -4484
B104: Net Cash Flow | C104: =SUM(C102,C93,C81) -> 2172 | D104: =SUM(D102,D93,D81) -> 2858 | E104: =SUM(E102,E93,E81) -> -1202 | F104: =SUM(F102,F93,F81) -> -2737 | G104: =SUM(G102,G93,G81) -> 4356 | H104: =SUM(H102,H93,H81) -> -2818 | I104: =SUM(I102,I93,I81) -> 377 | J104: =SUM(J102,J93,J81) -> 2595 | ... L104: =SUM(L102,L93,L81) -> 1516

Sheet Ratio Analysis
B2: ="Ratio Analysis"&" - "&'Data Sheet'!B1 -> Ratio Analysis - MARUTI SUZUKI INDIA LTD
B3: Years | C3: =HistoricalFS!C3 -> 42825 | D3: =HistoricalFS!D3 -> 43190 | E3: =HistoricalFS!E3 -> 43555 | F3: =HistoricalFS!F3 -> 43921 | G3: =HistoricalFS!G3 -> 44286 | H3: =HistoricalFS!H3 -> 44651 | I3: =HistoricalFS!I3 -> 45016 | J3: =HistoricalFS!J3 -> 45382 | ... L3: =HistoricalFS!L3 -> 46112 | M3: Trend Line | N3: Mean | O3: Median
B5: Sales Growth | D5: =IFERROR(HistoricalFS!D6/HistoricalFS!C6-1,0) -> 0.17220239 | E5: =IFERROR(HistoricalFS!E6/HistoricalFS!D6-1,0) -> 0.078425599 | F5: =IFERROR(HistoricalFS!F6/HistoricalFS!E6-1,0) -> -0.12093275 | G5: =IFERROR(HistoricalFS!G6/HistoricalFS!F6-1,0) -> -0.06989162 | H5: =IFERROR(HistoricalFS!H6/HistoricalFS!G6-1,0) -> 0.25518388 | I5: =IFERROR(HistoricalFS!I6/HistoricalFS!H6-1,0) -> 0.33104909 | J5: =IFERROR(HistoricalFS!J6/HistoricalFS!I6-1,0) -> 0.20657167 | K5: =IFERROR(HistoricalFS!K6/HistoricalFS!J6-1,0) -> 0.077928523 | L5: =IFERROR(HistoricalFS!L6/HistoricalFS!K6-1,0) -> 0.19882548 | N5: =IFERROR(AVERAGE(D5:L5),0) -> 0.1254847 | O5: =IFERROR(MEDIAN(D5:L5),0) -> 0.17220239
B6: EBITDA Growth | D6: =IFERROR(HistoricalFS!D18/HistoricalFS!C18-1,0) -> 0.16280119 | E6: =IFERROR(HistoricalFS!E18/HistoricalFS!D18-1,0) -> -0.087605938 | F6: =IFERROR(HistoricalFS!F18/HistoricalFS!E18-1,0) -> -0.33476841 | G6: =IFERROR(HistoricalFS!G18/HistoricalFS!F18-1,0) -> -0.26436438 | H6: =IFERROR(HistoricalFS!H18/HistoricalFS!G18-1,0) -> 0.063098362 | I6: =IFERROR(HistoricalFS!I18/HistoricalFS!H18-1,0) -> 0.9174548 | J6: =IFERROR(HistoricalFS!J18/HistoricalFS!I18-1,0) -> 0.68881696 | K6: =IFERROR(HistoricalFS!K18/HistoricalFS!J18-1,0) -> 0.085755088 | L6: =IFERROR(HistoricalFS!L18/HistoricalFS!K18-1,0) -> 0.060948595 | N6: =IFERROR(AVERAGE(D6:L6),0) -> 0.1435707 | O6: =IFERROR(MEDIAN(D6:L6),0) -> 0.063098362
B7: EBIT Growth | D7: =IFERROR(SUM(HistoricalFS!D24,HistoricalFS!D30)/SUM(HistoricalFS!C24,HistoricalFS!C30)-1,0) -> 0.12686217 | E7: =IFERROR(SUM(HistoricalFS!E24,HistoricalFS!E30)/SUM(HistoricalFS!D24,HistoricalFS!D30)-1,0) -> -0.070617666 | F7: =IFERROR(SUM(HistoricalFS!F24,HistoricalFS!F30)/SUM(HistoricalFS!E24,HistoricalFS!E30)-1,0) -> -0.3236259 | G7: =IFERROR(SUM(HistoricalFS!G24,HistoricalFS!G30)/SUM(HistoricalFS!F24,HistoricalFS!F30)-1,0) -> -0.25068399 | H7: =IFERROR(SUM(HistoricalFS!H24,HistoricalFS!H30)/SUM(HistoricalFS!G24,HistoricalFS!G30)-1,0) -> -0.11045954 | I7: =IFERROR(SUM(HistoricalFS!I24,HistoricalFS!I30)/SUM(HistoricalFS!H24,HistoricalFS!H30)-1,0) -> 1.1788009 | J7: =IFERROR(SUM(HistoricalFS!J24,HistoricalFS!J30)/SUM(HistoricalFS!I24,HistoricalFS!I30)-1,0) -> 0.67630184 | K7: =IFERROR(SUM(HistoricalFS!K24,HistoricalFS!K30)/SUM(HistoricalFS!J24,HistoricalFS!J30)-1,0) -> 0.12465022 | L7: =IFERROR(SUM(HistoricalFS!L24,HistoricalFS!L30)/SUM(HistoricalFS!K24,HistoricalFS!K30)-1,0) -> -0.023064267 | N7: =IFERROR(AVERAGE(D7:L7),0) -> 0.14757376 | O7: =IFERROR(MEDIAN(D7:L7),0) -> -0.023064267
B8: Net Profit Growth | D8: =IFERROR(HistoricalFS!D36/HistoricalFS!C36-1,0) -> 0.049221142 | E8: =IFERROR(HistoricalFS!E36/HistoricalFS!D36-1,0) -> -0.029197914 | F8: =IFERROR(HistoricalFS!F36/HistoricalFS!E36-1,0) -> -0.25788827 | G8: =IFERROR(HistoricalFS!G36/HistoricalFS!F36-1,0) -> -0.22694448 | H8: =IFERROR(HistoricalFS!H36/HistoricalFS!G36-1,0) -> -0.11610581 | I8: =IFERROR(HistoricalFS!I36/HistoricalFS!H36-1,0) -> 1.1165099 | J8: =IFERROR(HistoricalFS!J36/HistoricalFS!I36-1,0) -> 0.64269882 | K8: =IFERROR(HistoricalFS!K36/HistoricalFS!J36-1,0) -> 0.075028543 | L8: =IFERROR(HistoricalFS!L36/HistoricalFS!K36-1,0) -> 0.012365347 | N8: =IFERROR(AVERAGE(D8:L8),0) -> 0.14063192 | O8: =IFERROR(MEDIAN(D8:L8),0) -> 0.012365347
B9: Dividend Growth | D9: =IFERROR(HistoricalFS!D44/HistoricalFS!C44-1,0) -> 0.066666667 | E9: =IFERROR(HistoricalFS!E44/HistoricalFS!D44-1,0) -> 0 | F9: =IFERROR(HistoricalFS!F44/HistoricalFS!E44-1,0) -> -0.25 | G9: =IFERROR(HistoricalFS!G44/HistoricalFS!F44-1,0) -> -0.25 | H9: =IFERROR(HistoricalFS!H44/HistoricalFS!G44-1,0) -> 0.33333333 | I9: =IFERROR(HistoricalFS!I44/HistoricalFS!H44-1,0) -> 0.5 | J9: =IFERROR(HistoricalFS!J44/HistoricalFS!I44-1,0) -> 0.38934879 | K9: =IFERROR(HistoricalFS!K44/HistoricalFS!J44-1,0) -> 0.08 | L9: =IFERROR(HistoricalFS!L44/HistoricalFS!K44-1,0) -> 0.037037037 | N9: =IFERROR(AVERAGE(D9:L9),0) -> 0.10070954 | O9: =IFERROR(MEDIAN(D9:L9),0) -> 0.066666667
B11: Gross Margin | C11: =IFERROR(HistoricalFS!C13,0) -> 0.2655651 | D11: =IFERROR(HistoricalFS!D13,0) -> 0.26092666 | E11: =IFERROR(HistoricalFS!E13,0) -> 0.25428932 | F11: =IFERROR(HistoricalFS!F13,0) -> 0.23794475 | G11: =IFERROR(HistoricalFS!G13,0) -> 0.21253339 | H11: =IFERROR(HistoricalFS!H13,0) -> 0.18964155 | I11: =IFERROR(HistoricalFS!I13,0) -> 0.2107249 | J11: =IFERROR(HistoricalFS!J13,0) -> 0.23856922 | ... L11: =IFERROR(HistoricalFS!L13,0) -> 0.22742587 | N11: =IFERROR(AVERAGE(C11:L11),0) -> 0.23287927 | O11: =IFERROR(MEDIAN(C11:L11),0) -> 0.23455836
B12: EBITDA Margin | C12: =IFERROR(HistoricalFS!C19,0) -> 0.15306308 | D12: =IFERROR(HistoricalFS!D19,0) -> 0.1518355 | E12: =IFERROR(HistoricalFS!E19,0) -> 0.12845931 | F12: =IFERROR(HistoricalFS!F19,0) -> 0.097211208 | G12: =IFERROR(HistoricalFS!G19,0) -> 0.076885693 | H12: =IFERROR(HistoricalFS!H19,0) -> 0.065119586 | I12: =IFERROR(HistoricalFS!I19,0) -> 0.093808608 | J12: =IFERROR(HistoricalFS!J19,0) -> 0.13130224 | ... L12: =IFERROR(HistoricalFS!L19,0) -> 0.11704488 | N12: =IFERROR(AVERAGE(C12:L12),0) -> 0.11469857 | O12: =IFERROR(MEDIAN(C12:L12),0) -> 0.1227521
B13: EBIT Margin | C13: =IFERROR(SUM(HistoricalFS!C30,HistoricalFS!C24)/HistoricalFS!C6,0) -> 0.15005655 | D13: =IFERROR(SUM(HistoricalFS!D30,HistoricalFS!D24)/HistoricalFS!D6,0) -> 0.14425243 | E13: =IFERROR(SUM(HistoricalFS!E30,HistoricalFS!E24)/HistoricalFS!E6,0) -> 0.1243161 | F13: =IFERROR(SUM(HistoricalFS!F30,HistoricalFS!F24)/HistoricalFS!F6,0) -> 0.095651599 | G13: =IFERROR(SUM(HistoricalFS!G30,HistoricalFS!G24)/HistoricalFS!G6,0) -> 0.077059058 | H13: =IFERROR(SUM(HistoricalFS!H30,HistoricalFS!H24)/HistoricalFS!H6,0) -> 0.054611241 | I13: =IFERROR(SUM(HistoricalFS!I30,HistoricalFS!I24)/HistoricalFS!I6,0) -> 0.089393415 | J13: =IFERROR(SUM(HistoricalFS!J30,HistoricalFS!J24)/HistoricalFS!J6,0) -> 0.12419515 | ... L13: =IFERROR(SUM(HistoricalFS!L30,HistoricalFS!L24)/HistoricalFS!L6,0) -> 0.10559471 | N13: =IFERROR(AVERAGE(C13:L13),0) -> 0.10947085 | O13: =IFERROR(MEDIAN(C13:L13),0) -> 0.11489493
B14: EBT Margin | C14: =IFERROR(HistoricalFS!C31,0) -> 0.14874348 | D14: =IFERROR(HistoricalFS!D31,0) -> 0.13991961 | E14: =IFERROR(HistoricalFS!E31,0) -> 0.12343424 | F14: =IFERROR(HistoricalFS!F31,0) -> 0.093877875 | G14: =IFERROR(HistoricalFS!G31,0) -> 0.07561246 | H14: =IFERROR(HistoricalFS!H31,0) -> 0.053177976 | I14: =IFERROR(HistoricalFS!I31,0) -> 0.087802891 | J14: =IFERROR(HistoricalFS!J31,0) -> 0.1228304 | ... L14: =IFERROR(HistoricalFS!L31,0) -> 0.10429259 | N14: =IFERROR(AVERAGE(C14:L14),0) -> 0.10779998 | O14: =IFERROR(MEDIAN(C14:L14),0) -> 0.1135615
B15: Net Profit Margin | C15: =IFERROR(HistoricalFS!C37,0) -> 0.11031798 | D15: =IFERROR(HistoricalFS!D37,0) -> 0.098744008 | E15: =IFERROR(HistoricalFS!E37,0) -> 0.088889663 | F15: =IFERROR(HistoricalFS!F37,0) -> 0.075040973 | G15: =IFERROR(HistoricalFS!G37,0) -> 0.062369977 | H15: =IFERROR(HistoricalFS!H37,0) -> 0.043920625 | I15: =IFERROR(HistoricalFS!I37,0) -> 0.069838472 | J15: =IFERROR(HistoricalFS!J37,0) -> 0.095082272 | ... L15: =IFERROR(HistoricalFS!L37,0) -> 0.080077571 | N15: =IFERROR(AVERAGE(C15:L15),0) -> 0.081910802 | O15: =IFERROR(MEDIAN(C15:L15),0) -> 0.084483617
B17: Sales Exp % Sales | C17: =IFERROR(HistoricalFS!C16,0) -> 0.11250202 | D17: =IFERROR(HistoricalFS!D16,0) -> 0.10909116 | E17: =IFERROR(HistoricalFS!E16,0) -> 0.12583001 | F17: =IFERROR(HistoricalFS!F16,0) -> 0.14073354 | G17: =IFERROR(HistoricalFS!G16,0) -> 0.1356477 | H17: =IFERROR(HistoricalFS!H16,0) -> 0.12452196 | I17: =IFERROR(HistoricalFS!I16,0) -> 0.11691629 | J17: =IFERROR(HistoricalFS!J16,0) -> 0.10726698 | ... L17: =IFERROR(HistoricalFS!L16,0) -> 0.11038098 | N17: =IFERROR(AVERAGE(C17:L17),0) -> 0.1181807 | O17: =IFERROR(MEDIAN(C17:L17),0) -> 0.11470915
B18: Depreciation % Sales | C18: =IFERROR(HistoricalFS!C28,0) -> 0.038244841 | D18: =IFERROR(HistoricalFS!D28,0) -> 0.034579887 | E18: =IFERROR(HistoricalFS!E28,0) -> 0.035097626 | F18: =IFERROR(HistoricalFS!F28,0) -> 0.046634946 | G18: =IFERROR(HistoricalFS!G28,0) -> 0.043115159 | H18: =IFERROR(HistoricalFS!H28,0) -> 0.031574848 | I18: =IFERROR(HistoricalFS!I28,0) -> 0.024033927 | J18: =IFERROR(HistoricalFS!J28,0) -> 0.037049674 | ... L18: =IFERROR(HistoricalFS!L28,0) -> 0.036776386 | N18: =IFERROR(AVERAGE(C18:L18),0) -> 0.036378305 | O18: =IFERROR(MEDIAN(C18:L18),0) -> 0.036726071
B19: Operating Income % Sales | C19: =IFERROR('Ratio Analysis'!C13,0) -> 0.15005655 | D19: =IFERROR('Ratio Analysis'!D13,0) -> 0.14425243 | E19: =IFERROR('Ratio Analysis'!E13,0) -> 0.1243161 | F19: =IFERROR('Ratio Analysis'!F13,0) -> 0.095651599 | G19: =IFERROR('Ratio Analysis'!G13,0) -> 0.077059058 | H19: =IFERROR('Ratio Analysis'!H13,0) -> 0.054611241 | I19: =IFERROR('Ratio Analysis'!I13,0) -> 0.089393415 | J19: =IFERROR('Ratio Analysis'!J13,0) -> 0.12419515 | ... L19: =IFERROR('Ratio Analysis'!L13,0) -> 0.10559471 | N19: =IFERROR(AVERAGE(C19:L19),0) -> 0.10947085 | O19: =IFERROR(MEDIAN(C19:L19),0) -> 0.11489493
B21: Return on Capital Employed | C21: =IFERROR(SUM(HistoricalFS!C30,HistoricalFS!C24)/(SUM(HistoricalFS!C50:C52)),0) -> 0.27201687 | D21: =IFERROR(SUM(HistoricalFS!D30,HistoricalFS!D24)/(SUM(HistoricalFS!D50:D52)),0) -> 0.26974335 | E21: =IFERROR(SUM(HistoricalFS!E30,HistoricalFS!E24)/(SUM(HistoricalFS!E50:E52)),0) -> 0.22644053 | F21: =IFERROR(SUM(HistoricalFS!F30,HistoricalFS!F24)/(SUM(HistoricalFS!F50:F52)),0) -> 0.14591579 | G21: =IFERROR(SUM(HistoricalFS!G30,HistoricalFS!G24)/(SUM(HistoricalFS!G50:G52)),0) -> 0.10223693 | H21: =IFERROR(SUM(HistoricalFS!H30,HistoricalFS!H24)/(SUM(HistoricalFS!H50:H52)),0) -> 0.086511595 | I21: =IFERROR(SUM(HistoricalFS!I30,HistoricalFS!I24)/(SUM(HistoricalFS!I50:I52)),0) -> 0.16672483 | J21: =IFERROR(SUM(HistoricalFS!J30,HistoricalFS!J24)/(SUM(HistoricalFS!J50:J52)),0) -> 0.20544787 | ... L21: =IFERROR(SUM(HistoricalFS!L30,HistoricalFS!L24)/(SUM(HistoricalFS!L50:L52)),0) -> 0.18047191 | N21: =IFERROR(AVERAGE(C21:L21),0) -> 0.18612071 | O21: =IFERROR(MEDIAN(C21:L21),0) -> 0.19295989
B22: Retained Earning % | C22: =IFERROR(HistoricalFS!C47,0) -> 0.69844228 | D22: =IFERROR(HistoricalFS!D47,0) -> 0.69342825 | E22: =IFERROR(HistoricalFS!E47,0) -> 0.68420777 | F22: =IFERROR(HistoricalFS!F47,0) -> 0.68085106 | G22: =IFERROR(HistoricalFS!G47,0) -> 0.69036932 | H22: =IFERROR(HistoricalFS!H47,0) -> 0.5329295 | I22: =IFERROR(HistoricalFS!I47,0) -> 0.66898064 | J22: =IFERROR(HistoricalFS!J47,0) -> 0.70863421 | ... L22: =IFERROR(HistoricalFS!L47,0) -> 0.70015327 | N22: =IFERROR(AVERAGE(C22:L22),0) -> 0.67652831 | O22: =IFERROR(MEDIAN(C22:L22),0) -> 0.69189879
B23: Return on Equity % | C23: =IFERROR(HistoricalFS!C36/SUM(HistoricalFS!C50:C51),0) -> 0.2025888 | D23: =IFERROR(HistoricalFS!D36/SUM(HistoricalFS!D50:D51),0) -> 0.18516943 | E23: =IFERROR(HistoricalFS!E36/SUM(HistoricalFS!E50:E51),0) -> 0.16246037 | F23: =IFERROR(HistoricalFS!F36/SUM(HistoricalFS!F50:F51),0) -> 0.11490094 | G23: =IFERROR(HistoricalFS!G36/SUM(HistoricalFS!G50:G51),0) -> 0.083600949 | H23: =IFERROR(HistoricalFS!H36/SUM(HistoricalFS!H50:H51),0) -> 0.070111235 | I23: =IFERROR(HistoricalFS!I36/SUM(HistoricalFS!I50:I51),0) -> 0.13288278 | J23: =IFERROR(HistoricalFS!J36/SUM(HistoricalFS!J50:J51),0) -> 0.15750619 | ... L23: =IFERROR(HistoricalFS!L36/SUM(HistoricalFS!L50:L51),0) -> 0.13699148 | N23: =IFERROR(AVERAGE(C23:L23),0) -> 0.13968794 | O23: =IFERROR(MEDIAN(C23:L23),0) -> 0.14382936
B24: Self Sustained Growth Rate | C24: =IFERROR(C23*C22,0) -> 0.14149658 | D24: =IFERROR(D23*D22,0) -> 0.12840172 | E24: =IFERROR(E23*E22,0) -> 0.11115665 | F24: =IFERROR(F23*F22,0) -> 0.078230425 | G24: =IFERROR(G23*G22,0) -> 0.057715531 | H24: =IFERROR(H23*H22,0) -> 0.037364345 | I24: =IFERROR(I23*I22,0) -> 0.08889601 | J24: =IFERROR(J23*J22,0) -> 0.11161427 | ... L24: =IFERROR(L23*L22,0) -> 0.095915033 | N24: =IFERROR(AVERAGE(C24:L24),0) -> 0.095735552 | O24: =IFERROR(MEDIAN(C24:L24),0) -> 0.10123999
B25: Interest Coverage Ratio | C25: =IFERROR(SUM(HistoricalFS!C30,HistoricalFS!C24)/HistoricalFS!C24,0) -> 114.27964 | D25: =IFERROR(SUM(HistoricalFS!D30,HistoricalFS!D24)/HistoricalFS!D24,0) -> 33.292944 | E25: =IFERROR(SUM(HistoricalFS!E30,HistoricalFS!E24)/HistoricalFS!E24,0) -> 140.97101 | F25: =IFERROR(SUM(HistoricalFS!F30,HistoricalFS!F24)/HistoricalFS!F24,0) -> 53.926975 | G25: =IFERROR(SUM(HistoricalFS!G30,HistoricalFS!G24)/HistoricalFS!G24,0) -> 53.269155 | H25: =IFERROR(SUM(HistoricalFS!H30,HistoricalFS!H24)/HistoricalFS!H24,0) -> 38.102686 | I25: =IFERROR(SUM(HistoricalFS!I30,HistoricalFS!I24)/HistoricalFS!I24,0) -> 56.203743 | J25: =IFERROR(SUM(HistoricalFS!J30,HistoricalFS!J24)/HistoricalFS!J24,0) -> 91.002583 | ... L25: =IFERROR(SUM(HistoricalFS!L30,HistoricalFS!L24)/HistoricalFS!L24,0) -> 81.094261 | N25: =IFERROR(AVERAGE(C25:L25),0) -> 76.417287 | O25: =IFERROR(MEDIAN(C25:L25),0) -> 68.649002
B27: Debtor Turnover Ratio | C27: =IFERROR(HistoricalFS!C6/HistoricalFS!C62,0) -> 56.614835 | D27: =IFERROR(HistoricalFS!D6/HistoricalFS!D62,0) -> 54.462536 | E27: =IFERROR(HistoricalFS!E6/HistoricalFS!E62,0) -> 37.213983 | F27: =IFERROR(HistoricalFS!F6/HistoricalFS!F62,0) -> 38.256561 | G27: =IFERROR(HistoricalFS!G6/HistoricalFS!G62,0) -> 54.982421 | H27: =IFERROR(HistoricalFS!H6/HistoricalFS!H62,0) -> 43.415974 | I27: =IFERROR(HistoricalFS!I6/HistoricalFS!I62,0) -> 35.612558 | J27: =IFERROR(HistoricalFS!J6/HistoricalFS!J62,0) -> 30.860207 | ... L27: =IFERROR(HistoricalFS!L6/HistoricalFS!L62,0) -> 34.315987 | N27: =IFERROR(AVERAGE(C27:L27),0) -> 40.911733 | O27: =IFERROR(MEDIAN(C27:L27),0) -> 37.735272
B28: Creditor Turnover Ratio | C28: =IFERROR(HistoricalFS!C6/HistoricalFS!C53,0) -> 4.7275341 | D28: =IFERROR(HistoricalFS!D6/HistoricalFS!D53,0) -> 4.5428331 | E28: =IFERROR(HistoricalFS!E6/HistoricalFS!E53,0) -> 5.1485613 | F28: =IFERROR(HistoricalFS!F6/HistoricalFS!F53,0) -> 5.3924993 | G28: =IFERROR(HistoricalFS!G6/HistoricalFS!G53,0) -> 3.8382075 | H28: =IFERROR(HistoricalFS!H6/HistoricalFS!H53,0) -> 4.6744 | I28: =IFERROR(HistoricalFS!I6/HistoricalFS!I53,0) -> 5.4536443 | J28: =IFERROR(HistoricalFS!J6/HistoricalFS!J53,0) -> 4.8006971 | ... L28: =IFERROR(HistoricalFS!L6/HistoricalFS!L53,0) -> 4.4042843 | N28: =IFERROR(AVERAGE(C28:L28),0) -> 4.7272632 | O28: =IFERROR(MEDIAN(C28:L28),0) -> 4.700967
B29: Inventory Turnover Ratio | C29: =IFERROR(HistoricalFS!C6/HistoricalFS!C63,0) -> 20.861292 | D29: =IFERROR(HistoricalFS!D6/HistoricalFS!D63,0) -> 25.254541 | E29: =IFERROR(HistoricalFS!E6/HistoricalFS!E63,0) -> 25.903961 | F29: =IFERROR(HistoricalFS!F6/HistoricalFS!F63,0) -> 23.541492 | G29: =IFERROR(HistoricalFS!G6/HistoricalFS!G63,0) -> 23.080354 | H29: =IFERROR(HistoricalFS!H6/HistoricalFS!H63,0) -> 25.006313 | I29: =IFERROR(HistoricalFS!I6/HistoricalFS!I63,0) -> 27.447485 | J29: =IFERROR(HistoricalFS!J6/HistoricalFS!J63,0) -> 26.674602 | ... L29: =IFERROR(HistoricalFS!L6/HistoricalFS!L63,0) -> 16.193135 | N29: =IFERROR(AVERAGE(C29:L29),0) -> 23.608216 | O29: =IFERROR(MEDIAN(C29:L29),0) -> 24.273902
B30: Fixed Asset Turnover | C30: =IFERROR(HistoricalFS!C6/HistoricalFS!C56,0) -> 5.1150578 | D30: =IFERROR(HistoricalFS!D6/HistoricalFS!D56,0) -> 5.9609076 | E30: =IFERROR(HistoricalFS!E6/HistoricalFS!E56,0) -> 5.5753597 | F30: =IFERROR(HistoricalFS!F6/HistoricalFS!F56,0) -> 4.8055182 | G30: =IFERROR(HistoricalFS!G6/HistoricalFS!G56,0) -> 4.6950036 | H30: =IFERROR(HistoricalFS!H6/HistoricalFS!H56,0) -> 6.4252939 | I30: =IFERROR(HistoricalFS!I6/HistoricalFS!I56,0) -> 6.5938678 | J30: =IFERROR(HistoricalFS!J6/HistoricalFS!J56,0) -> 5.0909463 | ... L30: =IFERROR(HistoricalFS!L6/HistoricalFS!L56,0) -> 5.2442827 | N30: =IFERROR(AVERAGE(C30:L30),0) -> 5.4142395 | O30: =IFERROR(MEDIAN(C30:L30),0) -> 5.1796703
B31: Capital Turnover Ratio | C31: =IFERROR(HistoricalFS!C6/SUM(HistoricalFS!C50:C51),0) -> 1.8364077 | D31: =IFERROR(HistoricalFS!D6/SUM(HistoricalFS!D50:D51),0) -> 1.8752473 | E31: =IFERROR(HistoricalFS!E6/SUM(HistoricalFS!E50:E51),0) -> 1.8276632 | F31: =IFERROR(HistoricalFS!F6/SUM(HistoricalFS!F50:F51),0) -> 1.531176 | G31: =IFERROR(HistoricalFS!G6/SUM(HistoricalFS!G50:G51),0) -> 1.3404037 | H31: =IFERROR(HistoricalFS!H6/SUM(HistoricalFS!H50:H51),0) -> 1.5963169 | I31: =IFERROR(HistoricalFS!I6/SUM(HistoricalFS!I50:I51),0) -> 1.9027161 | J31: =IFERROR(HistoricalFS!J6/SUM(HistoricalFS!J50:J51),0) -> 1.6565253 | ... L31: =IFERROR(HistoricalFS!L6/SUM(HistoricalFS!L50:L51),0) -> 1.7107347 | N31: =IFERROR(AVERAGE(C31:L31),0) -> 1.6866064 | O31: =IFERROR(MEDIAN(C31:L31),0) -> 1.68363
B33: Debtor Days | C33: =IFERROR(365/C27,0) -> 6.4470735 | D33: =IFERROR(365/D27,0) -> 6.7018547 | E33: =IFERROR(365/E27,0) -> 9.8081412 | F33: =IFERROR(365/F27,0) -> 9.5408472 | G33: =IFERROR(365/G27,0) -> 6.6384855 | H33: =IFERROR(365/H27,0) -> 8.4070438 | I33: =IFERROR(365/I27,0) -> 10.249193 | J33: =IFERROR(365/J27,0) -> 11.827529 | ... L33: =IFERROR(365/L27,0) -> 10.636442 | N33: =IFERROR(AVERAGE(C33:L33),0) -> 9.5866732 | O33: =IFERROR(MEDIAN(C33:L33),0) -> 9.6744942
B34: Payable Days | C34: =IFERROR(365/C28,0) -> 77.20727 | D34: =IFERROR(365/D28,0) -> 80.346338 | E34: =IFERROR(365/E28,0) -> 70.893591 | F34: =IFERROR(365/F28,0) -> 67.686611 | G34: =IFERROR(365/G28,0) -> 95.096473 | H34: =IFERROR(365/H28,0) -> 78.084888 | I34: =IFERROR(365/I28,0) -> 66.927724 | J34: =IFERROR(365/J28,0) -> 76.030624 | ... L34: =IFERROR(365/L28,0) -> 82.873852 | N34: =IFERROR(AVERAGE(C34:L34),0) -> 78.022954 | O34: =IFERROR(MEDIAN(C34:L34),0) -> 77.646079
B35: Inventory Days | C35: =IFERROR(365/C29,0) -> 17.496519 | D35: =IFERROR(365/D29,0) -> 14.452846 | E35: =IFERROR(365/E29,0) -> 14.090509 | F35: =IFERROR(365/F29,0) -> 15.50454 | G35: =IFERROR(365/G29,0) -> 15.814315 | H35: =IFERROR(365/H29,0) -> 14.596314 | I35: =IFERROR(365/I29,0) -> 13.298122 | J35: =IFERROR(365/J29,0) -> 13.683428 | ... L35: =IFERROR(365/L29,0) -> 22.540417 | N35: =IFERROR(AVERAGE(C35:L35),0) -> 15.797867 | O35: =IFERROR(MEDIAN(C35:L35),0) -> 15.050427
B36: Cash Conversion Cycle | C36: =SUM(C33+C35-C34) -> -53.263678 | D36: =SUM(D33+D35-D34) -> -59.191637 | E36: =SUM(E33+E35-E34) -> -46.99494 | F36: =SUM(F33+F35-F34) -> -42.641224 | G36: =SUM(G33+G35-G34) -> -72.643672 | H36: =SUM(H33+H35-H34) -> -55.08153 | I36: =SUM(I33+I35-I34) -> -43.380408 | J36: =SUM(J33+J35-J34) -> -50.519667 | ... L36: =SUM(L33+L35-L34) -> -49.696993 | N36: =IFERROR(AVERAGE(C36:L36),0) -> -52.638414 | O36: =IFERROR(MEDIAN(C36:L36),0) -> -51.745028
B38: CFO/Sales | C38: =IFERROR(HistoricalFS!C81/HistoricalFS!C6,0) -> 0.18322685 | D38: =IFERROR(HistoricalFS!D81/HistoricalFS!D6,0) -> 0.18289826 | E38: =IFERROR(HistoricalFS!E81/HistoricalFS!E6,0) -> 0.061416198 | F38: =IFERROR(HistoricalFS!F81/HistoricalFS!F6,0) -> 0.012225747 | G38: =IFERROR(HistoricalFS!G81/HistoricalFS!G6,0) -> 0.18746092 | H38: =IFERROR(HistoricalFS!H81/HistoricalFS!H6,0) -> -0.011004214 | I38: =IFERROR(HistoricalFS!I81/HistoricalFS!I6,0) -> 0.081873723 | J38: =IFERROR(HistoricalFS!J81/HistoricalFS!J6,0) -> 0.130567 | ... L38: =IFERROR(HistoricalFS!L81/HistoricalFS!L6,0) -> 0.11311069 | N38: =IFERROR(AVERAGE(C38:L38),0) -> 0.10448338 | O38: =IFERROR(MEDIAN(C38:L38),0) -> 0.10808465
B39: CFO/Total Assets | C39: =IFERROR(HistoricalFS!C81/HistoricalFS!C67,0) -> 0.24008622 | D39: =IFERROR(HistoricalFS!D81/HistoricalFS!D67,0) -> 0.24228029 | E39: =IFERROR(HistoricalFS!E81/HistoricalFS!E67,0) -> 0.082634163 | F39: =IFERROR(HistoricalFS!F81/HistoricalFS!F67,0) -> 0.014537693 | G39: =IFERROR(HistoricalFS!G81/HistoricalFS!G67,0) -> 0.18482377 | H39: =IFERROR(HistoricalFS!H81/HistoricalFS!H67,0) -> -0.013019804 | I39: =IFERROR(HistoricalFS!I81/HistoricalFS!I67,0) -> 0.11378668 | J39: =IFERROR(HistoricalFS!J81/HistoricalFS!J67,0) -> 0.16063609 | ... L39: =IFERROR(HistoricalFS!L81/HistoricalFS!L67,0) -> 0.1392723 | N39: =IFERROR(AVERAGE(C39:L39),0) -> 0.12844498 | O39: =IFERROR(MEDIAN(C39:L39),0) -> 0.12934236
B40: CFO/Total Debt | D40: =IFERROR(HistoricalFS!D81/HistoricalFS!D52,0) -> 120.83609 | E40: =IFERROR(HistoricalFS!E81/HistoricalFS!E52,0) -> 33.120301 | F40: =IFERROR(HistoricalFS!F81/HistoricalFS!F52,0) -> 5.0244432 | G40: =IFERROR(HistoricalFS!G81/HistoricalFS!G52,0) -> 24.388981 | H40: =IFERROR(HistoricalFS!H81/HistoricalFS!H52,0) -> -2.2843713 | I40: =IFERROR(HistoricalFS!I81/HistoricalFS!I52,0) -> 7.7174697 | J40: =IFERROR(HistoricalFS!J81/HistoricalFS!J52,0) -> 156.17201 | K40: =IFERROR(HistoricalFS!K81/HistoricalFS!K52,0) -> 181.13793 | L40: =IFERROR(HistoricalFS!L81/HistoricalFS!L52,0) -> 202.29268 | N40: =IFERROR(AVERAGE(C40:L40),0) -> 80.933949 | O40: =IFERROR(MEDIAN(C40:L40),0) -> 33.120301

Sheet Common Size Statement
B2: ="Common Size Income Statement"&" - "&'Data Sheet'!B1 -> Common Size Income Statement - MARUTI SUZUKI INDIA LTD
B4: Particulars | C4: ='Data Sheet'!B16 -> 42825 | D4: ='Data Sheet'!C16 -> 43190 | E4: ='Data Sheet'!D16 -> 43555 | F4: ='Data Sheet'!E16 -> 43921 | G4: ='Data Sheet'!F16 -> 44286 | H4: ='Data Sheet'!G16 -> 44651 | I4: ='Data Sheet'!H16 -> 45016 | J4: ='Data Sheet'!I16 -> 45382 | ... L4: ='Data Sheet'!K16 -> 46112
B6: ='Data Sheet'!A17 -> Sales | C6: ='Data Sheet'!B17/'Data Sheet'!B$17 -> 1 | D6: ='Data Sheet'!C17/'Data Sheet'!C$17 -> 1 | E6: ='Data Sheet'!D17/'Data Sheet'!D$17 -> 1 | F6: ='Data Sheet'!E17/'Data Sheet'!E$17 -> 1 | G6: ='Data Sheet'!F17/'Data Sheet'!F$17 -> 1 | H6: ='Data Sheet'!G17/'Data Sheet'!G$17 -> 1 | I6: ='Data Sheet'!H17/'Data Sheet'!H$17 -> 1 | J6: ='Data Sheet'!I17/'Data Sheet'!I$17 -> 1 | ... L6: ='Data Sheet'!K17/'Data Sheet'!K$17 -> 1
B7: ='Data Sheet'!A18 -> Raw Material Cost | C7: ='Data Sheet'!B18/'Data Sheet'!B$17 -> 0.69209811 | D7: ='Data Sheet'!C18/'Data Sheet'!C$17 -> 0.6884565 | E7: ='Data Sheet'!D18/'Data Sheet'!D$17 -> 0.68952753 | F7: ='Data Sheet'!E18/'Data Sheet'!E$17 -> 0.70581549 | G7: ='Data Sheet'!F18/'Data Sheet'!F$17 -> 0.71833258 | H7: ='Data Sheet'!G18/'Data Sheet'!G$17 -> 0.74875184 | I7: ='Data Sheet'!H18/'Data Sheet'!H$17 -> 0.73703957 | J7: ='Data Sheet'!I18/'Data Sheet'!I$17 -> 0.70577168 | ... L7: ='Data Sheet'!K18/'Data Sheet'!K$17 -> 0.73560409
B8: ='Data Sheet'!A19 -> Change in Inventory | C8: ='Data Sheet'!B19/'Data Sheet'!B$17 -> 0.0055709775 | D8: ='Data Sheet'!C19/'Data Sheet'!C$17 -> -0.00051121798 | E8: ='Data Sheet'!D19/'Data Sheet'!D$17 -> -0.0024585069 | F8: ='Data Sheet'!E19/'Data Sheet'!E$17 -> 0.0031549035 | G8: ='Data Sheet'!F19/'Data Sheet'!F$17 -> -0.00388791 | H8: ='Data Sheet'!G19/'Data Sheet'!G$17 -> 0.0010540044 | I8: ='Data Sheet'!H19/'Data Sheet'!H$17 -> 0.0034353622 | J8: ='Data Sheet'!I19/'Data Sheet'!I$17 -> 0.0026688623 | ... L8: ='Data Sheet'!K19/'Data Sheet'!K$17 -> 0.012396627
B9: ='Data Sheet'!A20 -> Power and Fuel | C9: ='Data Sheet'!B20/'Data Sheet'!B$17 -> 0.0076169494 | D9: ='Data Sheet'!C20/'Data Sheet'!C$17 -> 0.0084376026 | E9: ='Data Sheet'!D20/'Data Sheet'!D$17 -> 0.010030383 | F9: ='Data Sheet'!E20/'Data Sheet'!E$17 -> 0.009245308 | G9: ='Data Sheet'!F20/'Data Sheet'!F$17 -> 0.00677258 | H9: ='Data Sheet'!G20/'Data Sheet'!G$17 -> 0.0071425499 | I9: ='Data Sheet'!H20/'Data Sheet'!H$17 -> 0.0067193269 | J9: ='Data Sheet'!I20/'Data Sheet'!I$17 -> 0.0072847393 | ... L9: ='Data Sheet'!K20/'Data Sheet'!K$17 -> 0
B10: ='Data Sheet'!A21 -> Other Mfr. Exp | C10: ='Data Sheet'!B21/'Data Sheet'!B$17 -> 0.0056238525 | D10: ='Data Sheet'!C21/'Data Sheet'!C$17 -> 0.0057900448 | E10: ='Data Sheet'!D21/'Data Sheet'!D$17 -> 0.005526993 | F10: ='Data Sheet'!E21/'Data Sheet'!E$17 -> 0.0049973566 | G10: ='Data Sheet'!F21/'Data Sheet'!F$17 -> 0.0097098278 | H10: ='Data Sheet'!G21/'Data Sheet'!G$17 -> 0.0096513294 | I10: ='Data Sheet'!H21/'Data Sheet'!H$17 -> 0.0095320882 | J10: ='Data Sheet'!I21/'Data Sheet'!I$17 -> 0.0066214008 | ... L10: ='Data Sheet'!K21/'Data Sheet'!K$17 -> 0
B11: ='Data Sheet'!A22 -> Employee Cost | C11: ='Data Sheet'!B22/'Data Sheet'!B$17 -> 0.03466696 | D11: ='Data Sheet'!C22/'Data Sheet'!C$17 -> 0.035877979 | E11: ='Data Sheet'!D22/'Data Sheet'!D$17 -> 0.038167274 | F11: ='Data Sheet'!E22/'Data Sheet'!E$17 -> 0.045151996 | G11: ='Data Sheet'!F22/'Data Sheet'!F$17 -> 0.048763713 | H11: ='Data Sheet'!G22/'Data Sheet'!G$17 -> 0.04586674 | I11: ='Data Sheet'!H22/'Data Sheet'!H$17 -> 0.039419484 | J11: ='Data Sheet'!I22/'Data Sheet'!I$17 -> 0.044421824 | ... L11: ='Data Sheet'!K22/'Data Sheet'!K$17 -> 0.049366667
B12: ='Data Sheet'!A23 -> Selling and admin | C12: ='Data Sheet'!B23/'Data Sheet'!B$17 -> 0.089759859 | D12: ='Data Sheet'!C23/'Data Sheet'!C$17 -> 0.084642912 | E12: ='Data Sheet'!D23/'Data Sheet'!D$17 -> 0.097483981 | F12: ='Data Sheet'!E23/'Data Sheet'!E$17 -> 0.11176712 | G12: ='Data Sheet'!F23/'Data Sheet'!F$17 -> 0.1126016 | H12: ='Data Sheet'!G23/'Data Sheet'!G$17 -> 0.10323922 | I12: ='Data Sheet'!H23/'Data Sheet'!H$17 -> 0.099471555 | J12: ='Data Sheet'!I23/'Data Sheet'!I$17 -> 0.085173786 | ... L12: ='Data Sheet'!K23/'Data Sheet'!K$17 -> 0
B13: ='Data Sheet'!A24 -> Other Expenses | C13: ='Data Sheet'!B24/'Data Sheet'!B$17 -> 0.022742161 | D13: ='Data Sheet'!C24/'Data Sheet'!C$17 -> 0.024448248 | E13: ='Data Sheet'!D24/'Data Sheet'!D$17 -> 0.028346027 | F13: ='Data Sheet'!E24/'Data Sheet'!E$17 -> 0.028966429 | G13: ='Data Sheet'!F24/'Data Sheet'!F$17 -> 0.023046098 | H13: ='Data Sheet'!G24/'Data Sheet'!G$17 -> 0.021282738 | I13: ='Data Sheet'!H24/'Data Sheet'!H$17 -> 0.017444734 | J13: ='Data Sheet'!I24/'Data Sheet'!I$17 -> 0.022093189 | ... L13: ='Data Sheet'!K24/'Data Sheet'!K$17 -> 0.11038098
B14: ='Data Sheet'!A25 -> Other Income | C14: ='Data Sheet'!B25/'Data Sheet'!B$17 -> 0.035238305 | D14: ='Data Sheet'!C25/'Data Sheet'!C$17 -> 0.02699682 | E14: ='Data Sheet'!D25/'Data Sheet'!D$17 -> 0.030954414 | F14: ='Data Sheet'!E25/'Data Sheet'!E$17 -> 0.045075337 | G14: ='Data Sheet'!F25/'Data Sheet'!F$17 -> 0.043288524 | H14: ='Data Sheet'!G25/'Data Sheet'!G$17 -> 0.021066503 | I14: ='Data Sheet'!H25/'Data Sheet'!H$17 -> 0.019618733 | J14: ='Data Sheet'!I25/'Data Sheet'!I$17 -> 0.029942576 | ... L14: ='Data Sheet'!K25/'Data Sheet'!K$17 -> 0.025326213
B15: ='Data Sheet'!A26 -> Depreciation | C15: ='Data Sheet'!B26/'Data Sheet'!B$17 -> 0.038244841 | D15: ='Data Sheet'!C26/'Data Sheet'!C$17 -> 0.034579887 | E15: ='Data Sheet'!D26/'Data Sheet'!D$17 -> 0.035097626 | F15: ='Data Sheet'!E26/'Data Sheet'!E$17 -> 0.046634946 | G15: ='Data Sheet'!F26/'Data Sheet'!F$17 -> 0.043115159 | H15: ='Data Sheet'!G26/'Data Sheet'!G$17 -> 0.031574848 | I15: ='Data Sheet'!H26/'Data Sheet'!H$17 -> 0.024033927 | J15: ='Data Sheet'!I26/'Data Sheet'!I$17 -> 0.037049674 | ... L15: ='Data Sheet'!K26/'Data Sheet'!K$17 -> 0.036776386
B16: ='Data Sheet'!A27 -> Interest | C16: ='Data Sheet'!B27/'Data Sheet'!B$17 -> 0.0013130646 | D16: ='Data Sheet'!C27/'Data Sheet'!C$17 -> 0.004332823 | E16: ='Data Sheet'!D27/'Data Sheet'!D$17 -> 0.00088185573 | F16: ='Data Sheet'!E27/'Data Sheet'!E$17 -> 0.0017737246 | G16: ='Data Sheet'!F27/'Data Sheet'!F$17 -> 0.0014465981 | H16: ='Data Sheet'!G27/'Data Sheet'!G$17 -> 0.0014332649 | I16: ='Data Sheet'!H27/'Data Sheet'!H$17 -> 0.0015905242 | J16: ='Data Sheet'!I27/'Data Sheet'!I$17 -> 0.0013647431 | ... L16: ='Data Sheet'!K27/'Data Sheet'!K$17 -> 0.0013021231
B17: ='Data Sheet'!A28 -> Profit before tax | C17: ='Data Sheet'!B28/'Data Sheet'!B$17 -> 0.14874348 | D17: ='Data Sheet'!C28/'Data Sheet'!C$17 -> 0.13991961 | E17: ='Data Sheet'!D28/'Data Sheet'!D$17 -> 0.12343424 | F17: ='Data Sheet'!E28/'Data Sheet'!E$17 -> 0.093877875 | G17: ='Data Sheet'!F28/'Data Sheet'!F$17 -> 0.07561246 | H17: ='Data Sheet'!G28/'Data Sheet'!G$17 -> 0.053177976 | I17: ='Data Sheet'!H28/'Data Sheet'!H$17 -> 0.087802891 | J17: ='Data Sheet'!I28/'Data Sheet'!I$17 -> 0.1228304 | ... L17: ='Data Sheet'!K28/'Data Sheet'!K$17 -> 0.10429259
... B21: ='Data Sheet'!A32 -> EBITDA | C21: ='Data Sheet'!B32/'Data Sheet'!B$17 -> 0.15304693 | D21: ='Data Sheet'!C32/'Data Sheet'!C$17 -> 0.15182673 | E21: ='Data Sheet'!D32/'Data Sheet'!D$17 -> 0.12844188 | F21: ='Data Sheet'!E32/'Data Sheet'!E$17 -> 0.097190061 | G21: ='Data Sheet'!F32/'Data Sheet'!F$17 -> 0.076885693 | H21: ='Data Sheet'!G32/'Data Sheet'!G$17 -> 0.065119586 | I21: ='Data Sheet'!H32/'Data Sheet'!H$17 -> 0.093808608 | J21: ='Data Sheet'!I32/'Data Sheet'!I$17 -> 0.13130224 | ... L21: ='Data Sheet'!K32/'Data Sheet'!K$17 -> 0.11704488
B23: ="Common Size Balance Sheet"&" - "&'Data Sheet'!B1 -> Common Size Balance Sheet - MARUTI SUZUKI INDIA LTD
B25: Particulars | C25: ='Data Sheet'!B16 -> 42825 | D25: ='Data Sheet'!C16 -> 43190 | E25: ='Data Sheet'!D16 -> 43555 | F25: ='Data Sheet'!E16 -> 43921 | G25: ='Data Sheet'!F16 -> 44286 | H25: ='Data Sheet'!G16 -> 44651 | I25: ='Data Sheet'!H16 -> 45016 | J25: ='Data Sheet'!I16 -> 45382 | ... L25: ='Data Sheet'!K16 -> 46112
B27: Total Liabilities | C27: ='Data Sheet'!B61/'Data Sheet'!B$61 -> 1 | D27: ='Data Sheet'!C61/'Data Sheet'!C$61 -> 1 | E27: ='Data Sheet'!D61/'Data Sheet'!D$61 -> 1 | F27: ='Data Sheet'!E61/'Data Sheet'!E$61 -> 1 | G27: ='Data Sheet'!F61/'Data Sheet'!F$61 -> 1 | H27: ='Data Sheet'!G61/'Data Sheet'!G$61 -> 1 | I27: ='Data Sheet'!H61/'Data Sheet'!H$61 -> 1 | J27: ='Data Sheet'!I61/'Data Sheet'!I$61 -> 1 | ... L27: ='Data Sheet'!K61/'Data Sheet'!K$61 -> 1
B28: ='Data Sheet'!A57 -> Equity Share Capital | C28: ='Data Sheet'!B57/'Data Sheet'!B$61 -> 0.0029060536 | D28: ='Data Sheet'!C57/'Data Sheet'!C$61 -> 0.0025062906 | E28: ='Data Sheet'!D57/'Data Sheet'!D$61 -> 0.0023605294 | F28: ='Data Sheet'!E57/'Data Sheet'!E$61 -> 0.0023731802 | G28: ='Data Sheet'!F57/'Data Sheet'!F$61 -> 0.0021155541 | H28: ='Data Sheet'!G57/'Data Sheet'!G$61 -> 0.0020226239 | I28: ='Data Sheet'!H57/'Data Sheet'!H$61 -> 0.0017849354 | J28: ='Data Sheet'!I57/'Data Sheet'!I$61 -> 0.0013633513 | ... L28: ='Data Sheet'!K57/'Data Sheet'!K$61 -> 0.0010558768
B29: ='Data Sheet'!A58 -> Reserves | C29: ='Data Sheet'!B58/'Data Sheet'!B$61 -> 0.71061864 | D29: ='Data Sheet'!C58/'Data Sheet'!C$61 -> 0.70389255 | E29: ='Data Sheet'!D58/'Data Sheet'!D$61 -> 0.73381357 | F29: ='Data Sheet'!E58/'Data Sheet'!E$61 -> 0.77422255 | G29: ='Data Sheet'!F58/'Data Sheet'!F$61 -> 0.73343318 | H29: ='Data Sheet'!G58/'Data Sheet'!G$61 -> 0.73916188 | I29: ='Data Sheet'!H58/'Data Sheet'!H$61 -> 0.72863545 | J29: ='Data Sheet'!I58/'Data Sheet'!I$61 -> 0.74133357 | ... L29: ='Data Sheet'!K58/'Data Sheet'!K$61 -> 0.71868875
B30: ='Data Sheet'!A59 -> Borrowings | C30: ='Data Sheet'!B59/'Data Sheet'!B$61 -> 0.0093070698 | D30: ='Data Sheet'!C59/'Data Sheet'!C$61 -> 0.0020050325 | E30: ='Data Sheet'!D59/'Data Sheet'!D$61 -> 0.0024949702 | F30: ='Data Sheet'!E59/'Data Sheet'!E$61 -> 0.0028933939 | G30: ='Data Sheet'!F59/'Data Sheet'!F$61 -> 0.0075781669 | H30: ='Data Sheet'!G59/'Data Sheet'!G$61 -> 0.0056995131 | I30: ='Data Sheet'!H59/'Data Sheet'!H$61 -> 0.014744039 | J30: ='Data Sheet'!I59/'Data Sheet'!I$61 -> 0.0010285844 | ... L30: ='Data Sheet'!K59/'Data Sheet'!K$61 -> 0.00068846931
B31: ='Data Sheet'!A60 -> Other Liabilities | C31: ='Data Sheet'!B60/'Data Sheet'!B$61 -> 0.27716823 | D31: ='Data Sheet'!C60/'Data Sheet'!C$61 -> 0.29159613 | E31: ='Data Sheet'!D60/'Data Sheet'!D$61 -> 0.26133093 | F31: ='Data Sheet'!E60/'Data Sheet'!E$61 -> 0.22051088 | G31: ='Data Sheet'!F60/'Data Sheet'!F$61 -> 0.2568731 | H31: ='Data Sheet'!G60/'Data Sheet'!G$61 -> 0.25311598 | I31: ='Data Sheet'!H60/'Data Sheet'!H$61 -> 0.25483558 | J31: ='Data Sheet'!I60/'Data Sheet'!I$61 -> 0.2562745 | ... L31: ='Data Sheet'!K60/'Data Sheet'!K$61 -> 0.2795669
B33: Total Assets | C33: ='Data Sheet'!B75/'Data Sheet'!B$75 -> 1 | D33: ='Data Sheet'!C75/'Data Sheet'!C$75 -> 1 | E33: ='Data Sheet'!D75/'Data Sheet'!D$75 -> 1 | F33: ='Data Sheet'!E75/'Data Sheet'!E$75 -> 1 | G33: ='Data Sheet'!F75/'Data Sheet'!F$75 -> 1 | H33: ='Data Sheet'!G75/'Data Sheet'!G$75 -> 1 | I33: ='Data Sheet'!H75/'Data Sheet'!H$75 -> 1 | J33: ='Data Sheet'!I75/'Data Sheet'!I$75 -> 1 | ... L33: ='Data Sheet'!K75/'Data Sheet'!K$75 -> 1
B34: ='Data Sheet'!A62 -> Net Block | C34: ='Data Sheet'!B62/'Data Sheet'!B$75 -> 0.25616959 | D34: ='Data Sheet'!C62/'Data Sheet'!C$75 -> 0.22222665 | E34: ='Data Sheet'!D62/'Data Sheet'!D$75 -> 0.24132584 | F34: ='Data Sheet'!E62/'Data Sheet'!E$75 -> 0.24744569 | G34: ='Data Sheet'!F62/'Data Sheet'!F$75 -> 0.20999606 | H34: ='Data Sheet'!G62/'Data Sheet'!G$75 -> 0.18414182 | I34: ='Data Sheet'!H62/'Data Sheet'!H$75 -> 0.21076895 | J34: ='Data Sheet'!I62/'Data Sheet'!I$75 -> 0.24166357 | ... L34: ='Data Sheet'!K62/'Data Sheet'!K$75 -> 0.23478751
B35: ='Data Sheet'!A63 -> Capital Work in Progress | C35: ='Data Sheet'!B63/'Data Sheet'!B$75 -> 0.024101 | D35: ='Data Sheet'!C63/'Data Sheet'!C$75 -> 0.035388492 | E35: ='Data Sheet'!D63/'Data Sheet'!D$75 -> 0.025120098 | F35: ='Data Sheet'!E63/'Data Sheet'!E$75 -> 0.022241885 | G35: ='Data Sheet'!F63/'Data Sheet'!F$75 -> 0.020970605 | H35: ='Data Sheet'!G63/'Data Sheet'!G$75 -> 0.039334008 | I35: ='Data Sheet'!H63/'Data Sheet'!H$75 -> 0.034328681 | J35: ='Data Sheet'!I63/'Data Sheet'!I$75 -> 0.067081743 | ... L35: ='Data Sheet'!K63/'Data Sheet'!K$75 -> 0.063179318
B36: ='Data Sheet'!A64 -> Investments | C36: ='Data Sheet'!B64/'Data Sheet'!B$75 -> 0.56101462 | D36: ='Data Sheet'!C64/'Data Sheet'!C$75 -> 0.59956945 | E36: ='Data Sheet'!D64/'Data Sheet'!D$75 -> 0.58628048 | F36: ='Data Sheet'!E64/'Data Sheet'!E$75 -> 0.58917736 | G36: ='Data Sheet'!F64/'Data Sheet'!F$75 -> 0.60166919 | H36: ='Data Sheet'!G64/'Data Sheet'!G$75 -> 0.56304894 | I36: ='Data Sheet'!H64/'Data Sheet'!H$75 -> 0.58139601 | J36: ='Data Sheet'!I64/'Data Sheet'!I$75 -> 0.49691208 | ... L36: ='Data Sheet'!K64/'Data Sheet'!K$75 -> 0.51610682
B37: ='Data Sheet'!A65 -> Other Assets | C37: ='Data Sheet'!B74/'Data Sheet'!B$75 -> 0.072306848 | D37: ='Data Sheet'!C74/'Data Sheet'!C$75 -> 0.06481168 | E37: ='Data Sheet'!D74/'Data Sheet'!D$75 -> 0.056241568 | F37: ='Data Sheet'!E74/'Data Sheet'!E$75 -> 0.059085901 | G37: ='Data Sheet'!F74/'Data Sheet'!F$75 -> 0.064024232 | H37: ='Data Sheet'!G74/'Data Sheet'!G$75 -> 0.098158876 | I37: ='Data Sheet'!H74/'Data Sheet'!H$75 -> 0.0833553 | J37: ='Data Sheet'!I74/'Data Sheet'!I$75 -> 0.083832231 | ... L37: ='Data Sheet'!K74/'Data Sheet'!K$75 -> 0.063394926
B38: ='Data Sheet'!A67 -> Receivables | C38: ='Data Sheet'!B67/'Data Sheet'!B$75 -> 0.023144504 | D38: ='Data Sheet'!C67/'Data Sheet'!C$75 -> 0.024322638 | E38: ='Data Sheet'!D67/'Data Sheet'!D$75 -> 0.036155182 | F38: ='Data Sheet'!E67/'Data Sheet'!E$75 -> 0.031082375 | G38: ='Data Sheet'!F67/'Data Sheet'!F$75 -> 0.017931773 | H38: ='Data Sheet'!G67/'Data Sheet'!G$75 -> 0.027251843 | I38: ='Data Sheet'!H67/'Data Sheet'!H$75 -> 0.039025071 | J38: ='Data Sheet'!I67/'Data Sheet'!I$75 -> 0.039866752 | ... L38: ='Data Sheet'!K67/'Data Sheet'!K$75 -> 0.035881006
B39: ='Data Sheet'!A68 -> Inventory | C39: ='Data Sheet'!B68/'Data Sheet'!B$75 -> 0.062811174 | D39: ='Data Sheet'!C68/'Data Sheet'!C$75 -> 0.052452845 | E39: ='Data Sheet'!D68/'Data Sheet'!D$75 -> 0.051941027 | F39: ='Data Sheet'!E68/'Data Sheet'!E$75 -> 0.05051102 | G39: ='Data Sheet'!F68/'Data Sheet'!F$75 -> 0.04271738 | H39: ='Data Sheet'!G68/'Data Sheet'!G$75 -> 0.047314665 | I39: ='Data Sheet'!H68/'Data Sheet'!H$75 -> 0.050634243 | J39: ='Data Sheet'!I68/'Data Sheet'!I$75 -> 0.046122384 | ... L39: ='Data Sheet'!K68/'Data Sheet'!K$75 -> 0.076037909
B40: ='Data Sheet'!A69 -> Cash & Bank | C40: ='Data Sheet'!B69/'Data Sheet'!B$75 -> 0.00045226663 | D40: ='Data Sheet'!C69/'Data Sheet'!C$75 -> 0.0012282484 | E40: ='Data Sheet'!D69/'Data Sheet'!D$75 -> 0.0029358108 | F40: ='Data Sheet'!E69/'Data Sheet'!E$75 -> 0.00045577634 | G40: ='Data Sheet'!F69/'Data Sheet'!F$75 -> 0.042690761 | H40: ='Data Sheet'!G69/'Data Sheet'!G$75 -> 0.040749844 | I40: ='Data Sheet'!H69/'Data Sheet'!H$75 -> 0.00049174379 | J40: ='Data Sheet'!I69/'Data Sheet'!I$75 -> 0.024521244 | ... L40: ='Data Sheet'!K69/'Data Sheet'!K$75 -> 0.010612503

Sheet IS-Forecasting
B2: ="Sales Forecasting"&" - "&'Data Sheet'!B1 -> Sales Forecasting - MARUTI SUZUKI INDIA LTD | G2: ="EBITDA Forecasting"&" - "&'Data Sheet'!B1 -> EBITDA Forecasting - MARUTI SUZUKI INDIA LTD | L2: ="COGS % Sales Forecasting"&" - "&'Data Sheet'!B1 -> COGS % Sales Forecasting - MARUTI SUZUKI INDIA LTD | R2: ="EBT Forecasting"&" - "&'Data Sheet'!B1 -> EBT Forecasting - MARUTI SUZUKI INDIA LTD | W2: ="Net Profit Forecasting"&" - "&'Data Sheet'!B1 -> Net Profit Forecasting - MARUTI SUZUKI INDIA LTD
B3: Year Weight | C3: Years | D3: Sales | E3: Sales Growth | G3: Year Weight | H3: Years | I3: EBITDA | J3: EBITDA Growth | L3: Year Weight | M3: Years | N3: Sales | O3: COGS | P3: COGS % Sales | R3: Year Weight | S3: Years | T3: EBT | U3: EBT Growth | W3: Year Weight | X3: Years | Y3: Sales | Z3: Net Profit | AA3: Net Margin
B4: 1 | C4: 2017 | D4: 68085 | G4: 1 | H4: 2017 | I4: 10421.3 | L4: 1 | M4: 2017 | N4: 68085 | O4: 50004 | P4: =O4/N4 -> 0.7344349 | R4: 1 | S4: 2017 | T4: 10127.2 | W4: 1 | X4: 2017 | Y4: 68085 | Z4: 7511 | AA4: =Z4/Y4 -> 0.11031798
B5: =B4+1 -> 2 | C5: =C4+1 -> 2018 | D5: 79809 | E5: =D5/D4-1 -> 0.17219652 | G5: =G4+1 -> 2 | H5: =H4+1 -> 2018 | I5: 12117.9 | J5: =I5/I4-1 -> 0.16280119 | L5: =L4+1 -> 2 | M5: =M4+1 -> 2018 | N5: 79809 | O5: 58985 | P5: =O5/N5 -> 0.73907705 | R5: =R4+1 -> 2 | S5: =S4+1 -> 2018 | T5: 11166.9 | U5: =T5/T4-1 -> 0.10266411 | W5: =W4+1 -> 2 | X5: =X4+1 -> 2018 | Y5: 79809 | Z5: 7880.7 | AA5: =Z5/Y5 -> 0.098744502
B6: =B5+1 -> 3 | C6: =C5+1 -> 2019 | D6: 86068 | E6: =D6/D5-1 -> 0.078424739 | G6: =G5+1 -> 3 | H6: =H5+1 -> 2019 | I6: 11056.3 | J6: =I6/I5-1 -> -0.087605938 | L6: =L5+1 -> 3 | M6: =M5+1 -> 2019 | N6: 86068 | O6: 64182.2 | P6: =O6/N6 -> 0.74571502 | R6: =R5+1 -> 3 | S6: =S5+1 -> 2019 | T6: 10623.8 | U6: =T6/T5-1 -> -0.048634805 | W6: =W5+1 -> 3 | X6: =X5+1 -> 2019 | Y6: 86068 | Z6: 7650.6 | AA6: =Z6/Y6 -> 0.08889018
B7: =B6+1 -> 4 | C7: =C6+1 -> 2020 | D7: 75660 | E7: =D7/D6-1 -> -0.12092764 | G7: =G6+1 -> 4 | H7: =H6+1 -> 2020 | I7: 7355 | J7: =I7/I6-1 -> -0.33476841 | L7: =L6+1 -> 4 | M7: =M6+1 -> 2020 | N7: 75660 | O7: 57657.1 | P7: =O7/N7 -> 0.76205525 | R7: =R6+1 -> 4 | S7: =S6+1 -> 2020 | T7: 7102.8 | U7: =T7/T6-1 -> -0.33142567 | W7: =W6+1 -> 4 | X7: =X6+1 -> 2020 | Y7: 75660 | Z7: 5677.6 | AA7: =Z7/Y7 -> 0.075040973
B8: =B7+1 -> 5 | C8: =C7+1 -> 2021 | D8: 70372 | E8: =D8/D7-1 -> -0.06989162 | G8: =G7+1 -> 5 | H8: =H7+1 -> 2021 | I8: 5410.6 | J8: =I8/I7-1 -> -0.26436438 | L8: =L7+1 -> 5 | M8: =M7+1 -> 2021 | N8: 70372 | O8: 55415.6 | P8: =O8/N8 -> 0.78746661 | R8: =R7+1 -> 5 | S8: =S7+1 -> 2021 | T8: 5321 | U8: =T8/T7-1 -> -0.25085882 | W8: =W7+1 -> 5 | X8: =X7+1 -> 2021 | Y8: 70372 | Z8: 4389.1 | AA8: =Z8/Y8 -> 0.062369977
B9: =B8+1 -> 6 | C9: =C8+1 -> 2022 | D9: 88330 | E9: =D9/D8-1 -> 0.25518672 | G9: =G8+1 -> 6 | H9: =H8+1 -> 2022 | I9: 5752 | J9: =I9/I8-1 -> 0.063098362 | L9: =L8+1 -> 6 | M9: =M8+1 -> 2022 | N9: 88330 | O9: 71578.8 | P9: =O9/N9 -> 0.81035662 | R9: =R8+1 -> 6 | S9: =S8+1 -> 2022 | T9: 4697.2 | U9: =T9/T8-1 -> -0.1172336 | W9: =W8+1 -> 6 | X9: =X8+1 -> 2022 | Y9: 88330 | Z9: 3879.5 | AA9: =Z9/Y9 -> 0.043920525
B10: =B9+1 -> 7 | C10: =C9+1 -> 2023 | D10: 117571 | E10: =D10/D9-1 -> 0.33104268 | G10: =G9+1 -> 7 | H10: =H9+1 -> 2023 | I10: 11029.2 | J10: =I10/I9-1 -> 0.9174548 | L10: =L9+1 -> 7 | M10: =M9+1 -> 2023 | N10: 117571 | O10: 92796.1 | P10: =O10/N10 -> 0.78927712 | R10: =R9+1 -> 7 | S10: =S9+1 -> 2023 | T10: 10323.1 | U10: =T10/T9-1 -> 1.1977135 | W10: =W9+1 -> 7 | X10: =X9+1 -> 2023 | Y10: 117571 | Z10: 8211 | AA10: =Z10/Y10 -> 0.069838651
B11: =B10+1 -> 8 | C11: =C10+1 -> 2024 | D11: 141858 | E11: =D11/D10-1 -> 0.20657305 | G11: =G10+1 -> 8 | H11: =H10+1 -> 2024 | I11: 18626.3 | J11: =I11/I10-1 -> 0.68881696 | L11: =L10+1 -> 8 | M11: =M10+1 -> 2024 | N11: 141858 | O11: 108015.2 | P11: =O11/N11 -> 0.76143185 | R11: =R10+1 -> 8 | S11: =S10+1 -> 2024 | T11: 17424.5 | U11: =T11/T10-1 -> 0.68791351 | W11: =W10+1 -> 8 | X11: =X10+1 -> 2024 | Y11: 141858 | Z11: 13488.2 | AA11: =Z11/Y11 -> 0.095082406
B12: =B11+1 -> 9 | C12: =C11+1 -> 2025 | D12: 152913 | E12: =D12/D11-1 -> 0.077930043 | G12: =G11+1 -> 9 | H12: =H11+1 -> 2025 | I12: 20223.6 | J12: =I12/I11-1 -> 0.085755088 | L12: =L11+1 -> 9 | M12: =M11+1 -> 2025 | N12: 152913 | O12: 117563.8 | P12: =O12/N12 -> 0.76882803 | R12: =R11+1 -> 9 | S12: =S11+1 -> 2025 | T12: 19620 | U12: =T12/T11-1 -> 0.12600075 | W12: =W11+1 -> 9 | X12: =X11+1 -> 2025 | Y12: 152913 | Z12: 14500.2 | AA12: =Z12/Y12 -> 0.09482647
B13: =B12+1 -> 10 | C13: =C12+1 -> 2026 | D13: 183316 | E13: =D13/D12-1 -> 0.19882548 | G13: =G12+1 -> 10 | H13: =H12+1 -> 2026 | I13: 21456.2 | J13: =I13/I12-1 -> 0.060948595 | L13: =L12+1 -> 10 | M13: =M12+1 -> 2026 | N13: 183316 | O13: 141625.2 | P13: =O13/N13 -> 0.77257413 | R13: =R12+1 -> 10 | S13: =S12+1 -> 2026 | T13: 19118.5 | U13: =T13/T12-1 -> -0.025560652 | W13: =W12+1 -> 10 | X13: =X12+1 -> 2026 | Y13: 183316 | Z13: 14679.5 | AA13: =Z13/Y13 -> 0.080077571
B14: =B13+1 -> 11 | C14: =C13+1 -> 2027 | D14: =$C$36+B14*$C$37 -> 172113.13 | E14: =D14/D13-1 -> -0.061112323 | G14: =G13+1 -> 11 | H14: =H13+1 -> 2027 | I14: =$C$55+G14*$C$56 -> 19187.107 | J14: =I14/I13-1 -> -0.10575467 | L14: =L13+1 -> 11 | M14: =M13+1 -> 2027 | N14: 172113.13 | O14: =$M$36+L14*$M$37 -> 134295.22 | P14: =O14/N14 -> 0.78027294 | R14: =R13+1 -> 11 | S14: =S13+1 -> 2027 | T14: =$M$55+R14*$M$56 -> 17656.967 | U14: =T14/T13-1 -> -0.076446025 | W14: =W13+1 -> 11 | X14: =X13+1 -> 2027 | Y14: 172113.13 | Z14: =$X$36+$X$37*W14 -> 13691.127 | AA14: =Z14/Y14 -> 0.079547251
B15: =B14+1 -> 12 | C15: =C14+1 -> 2028 | D15: =$C$36+B15*$C$37 -> 184061.3 | E15: =D15/D14-1 -> 0.069420441 | G15: =G14+1 -> 12 | H15: =H14+1 -> 2028 | I15: =$C$55+G15*$C$56 -> 20431.155 | J15: =I15/I14-1 -> 0.064837732 | L15: =L14+1 -> 12 | M15: =M14+1 -> 2028 | N15: 184061.3 | O15: =$M$36+L15*$M$37 -> 143843.02 | P15: =O15/N15 -> 0.78149519 | R15: =R14+1 -> 12 | S15: =S14+1 -> 2028 | T15: =$M$55+R15*$M$56 -> 18766.87 | U15: =T15/T14-1 -> 0.062859213 | W15: =W14+1 -> 12 | X15: =X14+1 -> 2028 | Y15: 184061.3 | Z15: =$X$36+$X$37*W15 -> 14582.833 | AA15: =Z15/Y15 -> 0.079228133
B16: =B15+1 -> 13 | C16: =C15+1 -> 2029 | D16: =$C$36+B16*$C$37 -> 196009.47 | E16: =D16/D15-1 -> 0.064914078 | G16: =G15+1 -> 13 | H16: =H15+1 -> 2029 | I16: =$C$55+G16*$C$56 -> 21675.204 | J16: =I16/I15-1 -> 0.060889777 | L16: =L15+1 -> 13 | M16: =M15+1 -> 2029 | N16: 196009.47 | O16: =$M$36+L16*$M$37 -> 153390.83 | P16: =O16/N16 -> 0.78256844 | R16: =R15+1 -> 13 | S16: =S15+1 -> 2029 | T16: =$M$55+R16*$M$56 -> 19876.773 | U16: =T16/T15-1 -> 0.059141618 | W16: =W15+1 -> 13 | X16: =X15+1 -> 2029 | Y16: 196009.47 | Z16: =$X$36+$X$37*W16 -> 15474.54 | AA16: =Z16/Y16 -> 0.078947919
B17: =B16+1 -> 14 | C17: =C16+1 -> 2030 | D17: =$C$36+B17*$C$37 -> 207957.64 | E17: =D17/D16-1 -> 0.060957103 | G17: =G16+1 -> 14 | H17: =H16+1 -> 2030 | I17: =$C$55+G17*$C$56 -> 22919.252 | J17: =I17/I16-1 -> 0.057395008 | L17: =L16+1 -> 14 | M17: =M16+1 -> 2030 | N17: 207957.64 | O17: =$M$36+L17*$M$37 -> 162938.63 | P17: =O17/N17 -> 0.78351836 | R17: =R16+1 -> 14 | S17: =S16+1 -> 2030 | T17: =$M$55+R17*$M$56 -> 20986.676 | U17: =T17/T16-1 -> 0.055839197 | W17: =W16+1 -> 14 | X17: =X16+1 -> 2030 | Y17: 207957.64 | Z17: =$X$36+$X$37*W17 -> 16366.247 | AA17: =Z17/Y17 -> 0.078699905
B18: =B17+1 -> 15 | C18: =C17+1 -> 2031 | D18: =$C$36+B18*$C$37 -> 219905.81 | E18: =D18/D17-1 -> 0.057454824 | G18: =G17+1 -> 15 | H18: =H17+1 -> 2031 | I18: =$C$55+G18*$C$56 -> 24163.301 | J18: =I18/I17-1 -> 0.054279628 | L18: =L17+1 -> 15 | M18: =M17+1 -> 2031 | N18: 219905.81 | O18: =$M$36+L18*$M$37 -> 172486.43 | P18: =O18/N18 -> 0.78436506 | R18: =R17+1 -> 15 | S18: =S17+1 -> 2031 | T18: =$M$55+R18*$M$56 -> 22096.579 | U18: =T18/T17-1 -> 0.052886081 | W18: =W17+1 -> 15 | X18: =X17+1 -> 2031 | Y18: 219905.81 | Z18: =$X$36+$X$37*W18 -> 17257.953 | AA18: =Z18/Y18 -> 0.078478841
B20: SUMMARY OUTPUT | D20: Y=mx+c | L20: SUMMARY OUTPUT | W20: SUMMARY OUTPUT
O21: COGS % Sales Forecasting | Z21: Net Profit Forecasting
B22: Regression Statistics | E22: Sales Forecasting | L22: Regression Statistics | W22: Regression Statistics
B23: Multiple R | C23: 0.89755432 | L23: Multiple R | M23: 0.919686 | W23: Multiple R | X23: 0.66886435
B24: R Square | C24: 0.80560376 | L24: R Square | M24: 0.84582234 | W24: R Square | X24: 0.44737952
B25: Adjusted R Square | C25: 0.78130423 | L25: Adjusted R Square | M25: 0.82655014 | W25: Adjusted R Square | X25: 0.37830196
B26: Standard Error | C26: 18848.056 | L26: Standard Error | M26: 13090.511 | W26: Standard Error | X26: 3182.5808
B27: Observations | C27: 10 | L27: Observations | M27: 10 | W27: Observations | X27: 10
B29: ANOVA | L29: ANOVA | W29: ANOVA
C30: df | D30: SS | E30: MS | F30: F | G30: Significance F | M30: df | N30: SS | O30: MS | P30: F | Q30: Significance F | X30: df | Y30: SS | Z30: MS | AA30: F | AB30: Significance F
B31: Regression | C31: 1 | D31: 1.1777598e+10 | E31: 1.1777598e+10 | F31: 33.153059 | G31: 0.00042514531 | L31: Regression | M31: 1 | N31: 7.5207457e+09 | O31: 7.5207457e+09 | P31: 43.888193 | Q31: 0.00016506689 | W31: Regression | X31: 1 | Y31: 65599114 | Z31: 65599114 | AA31: 6.4764812 | AB31: 0.03444739
B32: Residual | C32: 8 | D32: 2.8419936e+09 | E32: 3.552492e+08 | L32: Residual | M32: 8 | N32: 1.3708918e+09 | O32: 1.7136148e+08 | W32: Residual | X32: 8 | Y32: 81030563 | Z32: 10128820
B33: Total | C33: 9 | D33: 1.4619591e+10 | L33: Total | M33: 9 | N33: 8.8916376e+09 | W33: Total | X33: 9 | Y33: 1.4662968e+08
C35: Coefficients | D35: Standard Error | E35: t Stat | F35: P-value | G35: Lower 95% | H35: Upper 95% | I35: Lower 95.0% | J35: Upper 95.0% | M35: Coefficients | N35: Standard Error | O35: t Stat | P35: P-value | Q35: Lower 95% | R35: Upper 95% | S35: Lower 95.0% | T35: Upper 95.0% | X35: Coefficients | Y35: Standard Error | Z35: t Stat | AA35: P-value | AB35: Lower 95% | AC35: Upper 95% | AD35: Lower 95.0% | AE35: Upper 95.0%
B36: Intercept | C36: 40683.267 | D36: 12875.673 | E36: 3.1597002 | F36: 0.013401023 | G36: 10991.911 | H36: 70374.622 | I36: 10991.911 | J36: 70374.622 | L36: Intercept | M36: 29269.38 | N36: 8942.5215 | O36: 3.2730567 | P36: 0.011304456 | Q36: 8647.8884 | R36: 49890.872 | S36: 8647.8884 | T36: 49890.872 | W36: Intercept | X36: 3882.3533 | Y36: 2174.1166 | Z36: 1.7857154 | AA36: 0.11196959 | AB36: -1131.1684 | AC36: 8895.8751 | AD36: -1131.1684 | AE36: 8895.8751
B37: X Variable 1 | C37: 11948.17 | D37: 2075.1026 | E37: 5.7578693 | F37: 0.00042514531 | G37: 7162.9745 | H37: 16733.365 | I37: 7162.9745 | J37: 16733.365 | L37: X Variable 1 | M37: 9547.8036 | N37: 1441.2178 | O37: 6.6248165 | P37: 0.00016506689 | Q37: 6224.3493 | R37: 12871.258 | S37: 6224.3493 | T37: 12871.258 | W37: X Variable 1 | X37: 891.70667 | Y37: 350.39061 | Z37: 2.5448932 | AA37: 0.03444739 | AB37: 83.704471 | AC37: 1699.7089 | AD37: 83.704471 | AE37: 1699.7089
B39: SUMMARY OUTPUT | L39: SUMMARY OUTPUT
O40: EBT Forecasting
B41: Regression Statistics | E41: EBITDA Forecasting | L41: Regression Statistics
B42: Multiple R | C42: 0.64371107 | L42: Multiple R | M42: 0.61697074
B43: R Square | C43: 0.41436394 | L43: R Square | M43: 0.3806529
B44: Adjusted R Square | C44: 0.34115943 | L44: Adjusted R Square | M44: 0.30323451
B45: Standard Error | C45: 4749.4379 | L45: Standard Error | M45: 4546.4195
B46: Observations | C46: 10 | L46: Observations | M46: 10
B48: ANOVA | L48: ANOVA
C49: df | D49: SS | E49: MS | F49: F | G49: Significance F | M49: df | N49: SS | O49: MS | P49: F | Q49: Significance F
B50: Regression | C50: 1 | D50: 1.2768167e+08 | E50: 1.2768167e+08 | F50: 5.660361 | G50: 0.044604722 | L50: Regression | M50: 1 | N50: 1.0163049e+08 | O50: 1.0163049e+08 | P50: 4.916828 | Q50: 0.057415191
B51: Residual | C51: 8 | D51: 1.8045729e+08 | E51: 22557161 | L51: Residual | M51: 8 | N51: 1.6535944e+08 | O51: 20669930
B52: Total | C52: 9 | D52: 3.0813896e+08 | L52: Total | M52: 9 | N52: 2.6698993e+08
C54: Coefficients | D54: Standard Error | E54: t Stat | F54: P-value | G54: Lower 95% | H54: Upper 95% | I54: Lower 95.0% | J54: Upper 95.0% | M54: Coefficients | N54: Standard Error | O54: t Stat | P54: P-value | Q54: Lower 95% | R54: Upper 95% | S54: Lower 95.0% | T54: Upper 95.0%
B55: Intercept | C55: 5502.5733 | D55: 3244.4838 | E55: 1.6959781 | F55: 0.12833152 | G55: -1979.2197 | H55: 12984.366 | I55: -1979.2197 | J55: 12984.366 | L55: Intercept | M55: 5448.0333 | N55: 3105.7958 | O55: 1.7541505 | P55: 0.11748841 | Q55: -1713.9446 | R55: 12610.011 | S55: -1713.9446 | T55: 12610.011
B56: X Variable 1 | C56: 1244.0485 | D56: 522.89591 | E56: 2.3791513 | F56: 0.044604722 | G56: 38.248358 | H56: 2449.8486 | I56: 38.248358 | J56: 2449.8486 | L56: X Variable 1 | M56: 1109.903 | N56: 500.54431 | O56: 2.2173922 | P56: 0.057415191 | Q56: -44.354223 | R56: 2264.1603 | S56: -44.354223 | T56: 2264.1603

Sheet BS-Forcasting
B2: ="Balance Sheet Forcasting"&" - "&'Data Sheet'!B1 -> Balance Sheet Forcasting - MARUTI SUZUKI INDIA LTD
B3: Year Weight | C3: 1 | D3: =C3+1 -> 2 | E3: =D3+1 -> 3 | F3: =E3+1 -> 4 | G3: =F3+1 -> 5 | H3: =G3+1 -> 6 | I3: =H3+1 -> 7 | J3: =I3+1 -> 8 | K3: =J3+1 -> 9 | ... Q3: =P3+1 -> 15
B4: Years | C4: 2017 | D4: =C4+1 -> 2018 | E4: =D4+1 -> 2019 | F4: =E4+1 -> 2020 | G4: =F4+1 -> 2021 | H4: =G4+1 -> 2022 | I4: =H4+1 -> 2023 | J4: =I4+1 -> 2024 | K4: =J4+1 -> 2025 | ... Q4: =P4+1 -> 2031 | S4: Note:
B5: Balance Sheet | S5: Used Forecast Formula
B6: Equity Share Capital | C6: 151 | D6: 151 | E6: 151 | F6: 151 | G6: 151 | H6: 151 | I6: 151 | J6: 157.2 | K6: 157.2 | L6: 157.2 | M6: =FORECAST(M$3,$C$6:$L$6,$C$3:$L$3) -> 157.2 | N6: =FORECAST(N$3,$C$6:$L$6,$C$3:$L$3) -> 157.98909 | O6: =FORECAST(O$3,$C$6:$L$6,$C$3:$L$3) -> 158.77818 | P6: =FORECAST(P$3,$C$6:$L$6,$C$3:$L$3) -> 159.56727 | Q6: =FORECAST(Q$3,$C$6:$L$6,$C$3:$L$3) -> 160.35636 | S6: Run Regression for Total Assets to check accuracy of forecast formula
B7: Reserves | C7: 36924.1 | D7: 42408.4 | E7: 46941.1 | F7: 49262 | G7: 52349.6 | H7: 55182.5 | I7: 61640.3 | J7: 85478.8 | K7: 96082.7 | L7: 106999.1 | M7: =FORECAST(M$3,$C7:$L7,$C$3:$L$3) -> 104628.57 | N7: =FORECAST(N$3,$C7:$L7,$C$3:$L$3) -> 112137.98 | O7: =FORECAST(O$3,$C7:$L7,$C$3:$L$3) -> 119647.38 | P7: =FORECAST(P$3,$C7:$L7,$C$3:$L$3) -> 127156.78 | Q7: =FORECAST(Q$3,$C7:$L7,$C$3:$L$3) -> 134666.18
B8: Borrowings | C8: 483.6 | D8: 120.8 | E8: 159.6 | F8: 184.1 | G8: 540.9 | H8: 425.5 | I8: 1247.3 | J8: 118.6 | K8: 87 | L8: 102.5 | M8: =FORECAST(M$3,$C8:$L8,$C$3:$L$3) -> 320.41333 | N8: =FORECAST(N$3,$C8:$L8,$C$3:$L$3) -> 315.58121 | O8: =FORECAST(O$3,$C8:$L8,$C$3:$L$3) -> 310.74909 | P8: =FORECAST(P$3,$C8:$L8,$C$3:$L$3) -> 305.91697 | Q8: =FORECAST(Q$3,$C8:$L8,$C$3:$L$3) -> 301.08485 | W8: SUMMARY OUTPUT
B9: Other Liabilities | C9: 14401.8 | D9: 17568.2 | E9: 16717 | F9: 14030.6 | G9: 18334.6 | H9: 18896.5 | I9: 21558.3 | J9: 29549.5 | K9: 35644.3 | L9: 41622.2 | M9: =FORECAST(M$3,$C9:$L9,$C$3:$L$3) -> 38126.427 | N9: =FORECAST(N$3,$C9:$L9,$C$3:$L$3) -> 40907.177 | O9: =FORECAST(O$3,$C9:$L9,$C$3:$L$3) -> 43687.927 | P9: =FORECAST(P$3,$C9:$L9,$C$3:$L$3) -> 46468.678 | Q9: =FORECAST(Q$3,$C9:$L9,$C$3:$L$3) -> 49249.428 | S9: Total Assets
B10: Total Liabilities | C10: 51960.5 | D10: 60248.4 | E10: 63968.7 | F10: 63627.7 | G10: 71376.1 | H10: 74655.5 | I10: 84596.9 | J10: 115304.1 | K10: 131971.2 | L10: 148881 | M10: =SUM(M6:M9) -> 143232.61 | N10: =SUM(N6:N9) -> 153518.72 | O10: =SUM(O6:O9) -> 163804.83 | P10: =SUM(P6:P9) -> 174090.94 | Q10: =SUM(Q6:Q9) -> 184377.05 | S10: Year Weight | T10: Years | U10: Total Assers | W10: Regression Statistics
S11: 1 | T11: 2017 | U11: 51960.5 | W11: Multiple R | X11: 0.93084389
B12: Fixed Assets Net Block | C12: 13310.7 | D12: 13388.8 | E12: 15437.3 | F12: 15744.4 | G12: 14988.7 | H12: 13747.2 | I12: 17830.4 | J12: 27864.8 | K12: 32982.7 | L12: 34955.4 | M12: =FORECAST(M$3,$C12:$L12,$C$3:$L$3) -> 33328.827 | N12: =FORECAST(N$3,$C12:$L12,$C$3:$L$3) -> 35747.697 | O12: =FORECAST(O$3,$C12:$L12,$C$3:$L$3) -> 38166.567 | P12: =FORECAST(P$3,$C12:$L12,$C$3:$L$3) -> 40585.438 | Q12: =FORECAST(Q$3,$C12:$L12,$C$3:$L$3) -> 43004.308 | S12: =S11+1 -> 2 | T12: =T11+1 -> 2018 | U12: 60248.4 | W12: R Square | X12: 0.86647034
B13: Capital Work in Progress | C13: 1252.3 | D13: 2132.1 | E13: 1606.9 | F13: 1415.2 | G13: 1496.8 | H13: 2936.5 | I13: 2904.1 | J13: 7734.8 | K13: 7929 | L13: 9406.2 | M13: =FORECAST(M$3,$C13:$L13,$C$3:$L$3) -> 8898.3667 | N13: =FORECAST(N$3,$C13:$L13,$C$3:$L$3) -> 9810.5442 | O13: =FORECAST(O$3,$C13:$L13,$C$3:$L$3) -> 10722.722 | P13: =FORECAST(P$3,$C13:$L13,$C$3:$L$3) -> 11634.899 | Q13: =FORECAST(Q$3,$C13:$L13,$C$3:$L$3) -> 12547.077 | S13: =S12+1 -> 3 | T13: =T12+1 -> 2019 | U13: 63968.7 | W13: Adjusted R Square | X13: 0.84977913
B14: Investments | C14: 29150.6 | D14: 36123.1 | E14: 37503.6 | F14: 37488 | G14: 42944.8 | H14: 42034.7 | I14: 49184.3 | J14: 57296 | K14: 66265.4 | L14: 76838.5 | M14: =FORECAST(M$3,$C14:$L14,$C$3:$L$3) -> 73260.5 | N14: =FORECAST(N$3,$C14:$L14,$C$3:$L$3) -> 77947.336 | O14: =FORECAST(O$3,$C14:$L14,$C$3:$L$3) -> 82634.173 | P14: =FORECAST(P$3,$C14:$L14,$C$3:$L$3) -> 87321.009 | Q14: =FORECAST(Q$3,$C14:$L14,$C$3:$L$3) -> 92007.845 | S14: =S13+1 -> 4 | T14: =T13+1 -> 2020 | U14: 63627.7 | W14: Standard Error | X14: 12967.168
B15: Other Assets | C15: 3757.1 | D15: 3904.8 | E15: 3597.7 | F15: 3759.5 | G15: 4569.8 | H15: 7328.1 | I15: 7051.6 | J15: 9666.2 | K15: 10788.3 | L15: 9438.3 | M15: =FORECAST(M$3,$C15:$L15,$C$3:$L$3) -> 11129.22 | N15: =FORECAST(N$3,$C15:$L15,$C$3:$L$3) -> 11991.598 | O15: =FORECAST(O$3,$C15:$L15,$C$3:$L$3) -> 12853.976 | P15: =FORECAST(P$3,$C15:$L15,$C$3:$L$3) -> 13716.355 | Q15: =FORECAST(Q$3,$C15:$L15,$C$3:$L$3) -> 14578.733 | S15: =S14+1 -> 5 | T15: =T14+1 -> 2021 | U15: 71376.1 | W15: Observations | X15: 10
B16: Total Non Current Assets | C16: 47470.7 | D16: 55548.8 | E16: 58145.5 | F16: 58407.1 | G16: 64000.1 | H16: 66046.5 | I16: 76970.4 | J16: 102561.8 | K16: 117965.4 | L16: 130638.4 | M16: =SUM(M12:M15) -> 126616.91 | N16: =SUM(N12:N15) -> 135497.18 | O16: =SUM(O12:O15) -> 144377.44 | P16: =SUM(P12:P15) -> 153257.7 | Q16: =SUM(Q12:Q15) -> 162137.96 | S16: =S15+1 -> 6 | T16: =T15+1 -> 2022 | U16: 74655.5
S17: =S16+1 -> 7 | T17: =T16+1 -> 2023 | U17: 84596.9 | W17: ANOVA
B18: Receivables | C18: 1202.6 | D18: 1465.4 | E18: 2312.8 | F18: 1977.7 | G18: 1279.9 | H18: 2034.5 | I18: 3301.4 | J18: 4596.8 | K18: 6539.7 | L18: 5342 | M18: =FORECAST(M$3,$C18:$L18,$C$3:$L$3) -> 5969.2933 | N18: =FORECAST(N$3,$C18:$L18,$C$3:$L$3) -> 6508.2048 | O18: =FORECAST(O$3,$C18:$L18,$C$3:$L$3) -> 7047.1164 | P18: =FORECAST(P$3,$C18:$L18,$C$3:$L$3) -> 7586.0279 | Q18: =FORECAST(Q$3,$C18:$L18,$C$3:$L$3) -> 8124.9394 | S18: =S17+1 -> 8 | T18: =T17+1 -> 2024 | U18: 115304.1 | X18: df | Y18: SS | Z18: MS | AA18: F | AB18: Significance F
B19: Inventory | C19: 3263.7 | D19: 3160.2 | E19: 3322.6 | F19: 3213.9 | G19: 3049 | H19: 3532.3 | I19: 4283.5 | J19: 5318.1 | K19: 6913.2 | L19: 11320.6 | M19: =FORECAST(M$3,$C19:$L19,$C$3:$L$3) -> 8486.1333 | N19: =FORECAST(N$3,$C19:$L19,$C$3:$L$3) -> 9167.6648 | O19: =FORECAST(O$3,$C19:$L19,$C$3:$L$3) -> 9849.1964 | P19: =FORECAST(P$3,$C19:$L19,$C$3:$L$3) -> 10530.728 | Q19: =FORECAST(Q$3,$C19:$L19,$C$3:$L$3) -> 11212.259 | S19: =S18+1 -> 9 | T19: =T18+1 -> 2025 | U19: 131971.2 | W19: Regression | X19: 1 | Y19: 8.7288343e+09 | Z19: 8.7288343e+09 | AA19: 51.911784 | AB19: 9.200164e-05
B20: Cash & Bank | C20: 23.5 | D20: 74 | E20: 187.8 | F20: 29 | G20: 3047.1 | H20: 3042.2 | I20: 41.6 | J20: 2827.4 | K20: 552.9 | L20: 1580 | M20: =FORECAST(M$3,$C20:$L20,$C$3:$L$3) -> 2160.2733 | N20: =FORECAST(N$3,$C20:$L20,$C$3:$L$3) -> 2345.6776 | O20: =FORECAST(O$3,$C20:$L20,$C$3:$L$3) -> 2531.0818 | P20: =FORECAST(P$3,$C20:$L20,$C$3:$L$3) -> 2716.4861 | Q20: =FORECAST(Q$3,$C20:$L20,$C$3:$L$3) -> 2901.8903 | S20: =S19+1 -> 10 | T20: =T19+1 -> 2026 | U20: 148881 | W20: Residual | X20: 8 | Y20: 1.3451796e+09 | Z20: 1.6814746e+08
B21: Total Current Assets | C21: 4489.8 | D21: 4699.6 | E21: 5823.2 | F21: 5220.6 | G21: 7376 | H21: 8609 | I21: 7626.5 | J21: 12742.3 | K21: 14005.8 | L21: 18242.6 | M21: =SUM(M18:M20) -> 16615.7 | N21: =SUM(N18:N20) -> 18021.547 | O21: =SUM(O18:O20) -> 19427.395 | P21: =SUM(P18:P20) -> 20833.242 | Q21: =SUM(Q18:Q20) -> 22239.089 | S21: =S20+1 -> 11 | T21: =T20+1 -> 2027 | U21: =$X$24+$X$25*S21 -> 143232.61 | W21: Total | X21: 9 | Y21: 1.0074014e+10
S22: =S21+1 -> 12 | T22: =T21+1 -> 2028 | U22: =$X$24+$X$25*S22 -> 153518.72
B23: Total Assets | C23: 51960.5 | D23: 60248.4 | E23: 63968.7 | F23: 63627.7 | G23: 71376.1 | H23: 74655.5 | I23: 84596.9 | J23: 115304.1 | K23: 131971.2 | L23: 148881 | M23: =SUM(M21,M16,) -> 143232.61 | N23: =SUM(N21,N16,) -> 153518.72 | O23: =SUM(O21,O16,) -> 163804.83 | P23: =SUM(P21,P16,) -> 174090.94 | Q23: =SUM(Q21,Q16,) -> 184377.05 | S23: =S22+1 -> 13 | T23: =T22+1 -> 2029 | U23: =$X$24+$X$25*S23 -> 163804.83 | X23: Coefficients | Y23: Standard Error | Z23: t Stat | AA23: P-value | AB23: Lower 95% | AC23: Upper 95% | AD23: Lower 95.0% | AE23: Upper 95.0%
S24: =S23+1 -> 14 | T24: =T23+1 -> 2030 | U24: =$X$24+$X$25*S24 -> 174090.94 | W24: Intercept | X24: 30085.407 | Y24: 8858.2624 | Z24: 3.3963102 | AA24: 0.0094116849 | AB24: 9658.2169 | AC24: 50512.596 | AD24: 9658.2169 | AE24: 50512.596
B25: Check(Total Assets=Total Liabilities) | C25: TRUE | D25: TRUE | E25: TRUE | F25: TRUE | G25: TRUE | H25: TRUE | I25: TRUE | J25: TRUE | K25: TRUE | L25: TRUE | M25: TRUE | N25: TRUE | O25: TRUE | P25: TRUE | Q25: TRUE | S25: =S24+1 -> 15 | T25: =T24+1 -> 2031 | U25: =$X$24+$X$25*S25 -> 184377.05 | W25: X Variable 1 | X25: 10286.11 | Y25: 1427.6383 | Z25: 7.2049832 | AA25: 9.200164e-05 | AB25: 6993.97 | AC25: 13578.249 | AD25: 6993.97 | AE25: 13578.249

Sheet CashFlow-Forcasting
B2: ="Cash Flow Statement Forcasting"&" - "&'Data Sheet'!B1 -> Cash Flow Statement Forcasting - MARUTI SUZUKI INDIA LTD
B3: Year Weight | C3: 1 | D3: =C3+1 -> 2 | E3: =D3+1 -> 3 | F3: =E3+1 -> 4 | G3: =F3+1 -> 5 | H3: =G3+1 -> 6 | I3: =H3+1 -> 7 | J3: =I3+1 -> 8 | K3: =J3+1 -> 9 | ... Q3: =P3+1 -> 15
B4: Years | C4: 2017 | D4: =C4+1 -> 2018 | E4: =D4+1 -> 2019 | F4: =E4+1 -> 2020 | G4: =F4+1 -> 2021 | H4: =G4+1 -> 2022 | I4: =H4+1 -> 2023 | J4: =I4+1 -> 2024 | K4: =J4+1 -> 2025 | ... Q4: =P4+1 -> 2031
B5: Cash Flow Statement
B6: Operating Activities
B7: Profit from operations | C7: 10413 | D7: 12036 | E7: 11060 | F7: 7503 | G7: 5531 | H7: 5832 | I7: 11112 | J7: 18676 | K7: 20322 | L7: 21802 | M7: =FORECAST(M$3,$C7:$L7,$C$3:$L$3) -> 19419.067 | N7: =FORECAST(N$3,$C7:$L7,$C$3:$L$3) -> 20690.042 | O7: =FORECAST(O$3,$C7:$L7,$C$3:$L$3) -> 21961.018 | P7: =FORECAST(P$3,$C7:$L7,$C$3:$L$3) -> 23231.994 | Q7: =FORECAST(Q$3,$C7:$L7,$C$3:$L$3) -> 24502.97
B8: Receivables | C8: 122 | D8: -262 | E8: -851 | F8: 340 | G8: 696 | H8: -764 | I8: -1258 | J8: -1316 | K8: -1969 | L8: 1236 | M8: =FORECAST(M$3,$C8:$L8,$C$3:$L$3) -> -752.66667 | N8: =FORECAST(N$3,$C8:$L8,$C$3:$L$3) -> -816.31515 | O8: =FORECAST(O$3,$C8:$L8,$C$3:$L$3) -> -879.96364 | P8: =FORECAST(P$3,$C8:$L8,$C$3:$L$3) -> -943.61212 | Q8: =FORECAST(Q$3,$C8:$L8,$C$3:$L$3) -> -1007.2606
B9: Inventory | C9: -131 | D9: 104 | E9: -162 | F9: 109 | G9: 165 | H9: -483 | I9: -751 | J9: 125 | K9: -1595 | L9: -4407 | M9: =FORECAST(M$3,$C9:$L9,$C$3:$L$3) -> -2441.6 | N9: =FORECAST(N$3,$C9:$L9,$C$3:$L$3) -> -2757.7818 | O9: =FORECAST(O$3,$C9:$L9,$C$3:$L$3) -> -3073.9636 | P9: =FORECAST(P$3,$C9:$L9,$C$3:$L$3) -> -3390.1455 | Q9: =FORECAST(Q$3,$C9:$L9,$C$3:$L$3) -> -3706.3273
B10: Payables | C10: 979 | D10: 2128 | E10: -858 | F10: -2155 | G10: 2680 | H10: -396 | I10: 2008 | J10: 3321 | K10: 3509 | L10: 5194 | M10: =FORECAST(M$3,$C10:$L10,$C$3:$L$3) -> 4238 | N10: =FORECAST(N$3,$C10:$L10,$C$3:$L$3) -> 4710.1818 | O10: =FORECAST(O$3,$C10:$L10,$C$3:$L$3) -> 5182.3636 | P10: =FORECAST(P$3,$C10:$L10,$C$3:$L$3) -> 5654.5455 | Q10: =FORECAST(Q$3,$C10:$L10,$C$3:$L$3) -> 6126.7273
B11: Loans Advances | C11: 1 | D11: 0 | E11: -13 | F11: -1 | G11: -6 | H11: -8 | I11: 1 | J11: -3 | K11: -10 | L11: -1 | M11: =FORECAST(M$3,$C11:$L11,$C$3:$L$3) -> -5.1333333 | N11: =FORECAST(N$3,$C11:$L11,$C$3:$L$3) -> -5.3393939 | O11: =FORECAST(O$3,$C11:$L11,$C$3:$L$3) -> -5.5454545 | P11: =FORECAST(P$3,$C11:$L11,$C$3:$L$3) -> -5.7515152 | Q11: =FORECAST(Q$3,$C11:$L11,$C$3:$L$3) -> -5.9575758
B12: Other WC items | C12: 1222 | D12: 839 | E12: 569 | F12: -863 | G12: 801 | H12: -1162 | I12: 374 | J12: -406 | K12: -313 | L12: -387 | M12: =FORECAST(M$3,$C12:$L12,$C$3:$L$3) -> -788.33333 | N12: =FORECAST(N$3,$C12:$L12,$C$3:$L$3) -> -943.92121 | O12: =FORECAST(O$3,$C12:$L12,$C$3:$L$3) -> -1099.5091 | P12: =FORECAST(P$3,$C12:$L12,$C$3:$L$3) -> -1255.097 | Q12: =FORECAST(Q$3,$C12:$L12,$C$3:$L$3) -> -1410.6848
B13: Working capital changes | C13: 2192 | D13: 2808 | E13: -1315 | F13: -2570 | G13: 4336 | H13: -2813 | I13: 373 | J13: 1722 | K13: -378 | L13: 1635 | M13: =FORECAST(M$3,$C13:$L13,$C$3:$L$3) -> 250.66667 | N13: =FORECAST(N$3,$C13:$L13,$C$3:$L$3) -> 187.33333 | O13: =FORECAST(O$3,$C13:$L13,$C$3:$L$3) -> 124 | P13: =FORECAST(P$3,$C13:$L13,$C$3:$L$3) -> 60.666667 | Q13: =FORECAST(Q$3,$C13:$L13,$C$3:$L$3) -> -2.6666667
B14: Direct taxes | C14: -2323 | D14: -3056 | E14: -3144 | F14: -1438 | G14: -1011 | H14: -1178 | I14: -2233 | J14: -3597 | K14: -3807 | L14: -4337 | M14: =FORECAST(M$3,$C14:$L14,$C$3:$L$3) -> -3552.4 | N14: =FORECAST(N$3,$C14:$L14,$C$3:$L$3) -> -3723.3091 | O14: =FORECAST(O$3,$C14:$L14,$C$3:$L$3) -> -3894.2182 | P14: =FORECAST(P$3,$C14:$L14,$C$3:$L$3) -> -4065.1273 | Q14: =FORECAST(Q$3,$C14:$L14,$C$3:$L$3) -> -4236.0364
B15: Cash from Operating Activity | C15: 12475 | D15: 14597 | E15: 5286 | F15: 925 | G15: 13192 | H15: -972 | I15: 9626 | J15: 18522 | K15: 15759 | L15: 20735 | M15: =SUM(M7:M14) -> 16367.6 | N15: =SUM(N7:N14) -> 17340.891 | O15: =SUM(O7:O14) -> 18314.182 | P15: =SUM(P7:P14) -> 19287.473 | Q15: =SUM(Q7:Q14) -> 20260.764
B17: Investing Activities
B18: Fixed assets purchased | C18: -3391 | D18: -3912 | E18: -4872 | F18: -3437 | G18: -2370 | H18: -3459 | I18: -6347 | J18: -9200 | K18: -10641 | L18: -10398 | M18: =FORECAST(M$3,$C18:$L18,$C$3:$L$3) -> -10523.533 | N18: =FORECAST(N$3,$C18:$L18,$C$3:$L$3) -> -11381.867 | O18: =FORECAST(O$3,$C18:$L18,$C$3:$L$3) -> -12240.2 | P18: =FORECAST(P$3,$C18:$L18,$C$3:$L$3) -> -13098.533 | Q18: =FORECAST(Q$3,$C18:$L18,$C$3:$L$3) -> -13956.867
B19: Fixed assets sold | C19: 16 | D19: 26 | E19: 170 | F19: 37 | G19: 42 | H19: 136 | I19: 100 | J19: 45 | K19: 38 | L19: 52 | M19: =FORECAST(M$3,$C19:$L19,$C$3:$L$3) -> 68.4 | N19: =FORECAST(N$3,$C19:$L19,$C$3:$L$3) -> 68.8 | O19: =FORECAST(O$3,$C19:$L19,$C$3:$L$3) -> 69.2 | P19: =FORECAST(P$3,$C19:$L19,$C$3:$L$3) -> 69.6 | Q19: =FORECAST(Q$3,$C19:$L19,$C$3:$L$3) -> 70
B20: Investments purchased | C20: -17716 | D20: -47069 | E20: -52957 | F20: -44205 | G20: -44869 | H20: -60525 | I20: -66597 | J20: -65736 | K20: -73882 | L20: -108034 | M20: =FORECAST(M$3,$C20:$L20,$C$3:$L$3) -> -96401.667 | N20: =FORECAST(N$3,$C20:$L20,$C$3:$L$3) -> -103354.88 | O20: =FORECAST(O$3,$C20:$L20,$C$3:$L$3) -> -110308.09 | P20: =FORECAST(P$3,$C20:$L20,$C$3:$L$3) -> -117261.3 | Q20: =FORECAST(Q$3,$C20:$L20,$C$3:$L$3) -> -124214.52
B21: Investments sold | C21: 11839 | D21: 42564 | E21: 53986 | F21: 46969 | G21: 42920 | H21: 63579 | I21: 61605 | J21: 61933 | K21: 69795 | L21: 101969 | M21: =FORECAST(M$3,$C21:$L21,$C$3:$L$3) -> 92585.533 | N21: =FORECAST(N$3,$C21:$L21,$C$3:$L$3) -> 99289.103 | O21: =FORECAST(O$3,$C21:$L21,$C$3:$L$3) -> 105992.67 | P21: =FORECAST(P$3,$C21:$L21,$C$3:$L$3) -> 112696.24 | Q21: =FORECAST(Q$3,$C21:$L21,$C$3:$L$3) -> 119399.81
B22: Interest received | C22: 36 | D22: 68 | E22: 124 | F22: 96 | G22: 67 | H22: 174 | I22: 194 | J22: 372 | K22: 444 | L22: 354 | M22: =FORECAST(M$3,$C22:$L22,$C$3:$L$3) -> 430.73333 | N22: =FORECAST(N$3,$C22:$L22,$C$3:$L$3) -> 473.97576 | O22: =FORECAST(O$3,$C22:$L22,$C$3:$L$3) -> 517.21818 | P22: =FORECAST(P$3,$C22:$L22,$C$3:$L$3) -> 560.46061 | Q22: =FORECAST(Q$3,$C22:$L22,$C$3:$L$3) -> 603.70303
B23: Dividends received | C23: 13 | D23: 20 | E23: 9 | F23: 4 | G23: 3 | H23: 3 | I23: 6 | J23: 6 | K23: 9 | L23: 11 | M23: =FORECAST(M$3,$C23:$L23,$C$3:$L$3) -> 4.9333333 | N23: =FORECAST(N$3,$C23:$L23,$C$3:$L$3) -> 4.3030303 | O23: =FORECAST(O$3,$C23:$L23,$C$3:$L$3) -> 3.6727273 | P23: =FORECAST(P$3,$C23:$L23,$C$3:$L$3) -> 3.0424242 | Q23: =FORECAST(Q$3,$C23:$L23,$C$3:$L$3) -> 2.4121212
B24: Redemp n Canc of Shares | C24: 22 | D24: 0 | E24: 0 | F24: 0 | G24: 0 | H24: 0 | I24: 0 | J24: 0 | K24: 0 | L24: 0 | M24: =FORECAST(M$3,$C24:$L24,$C$3:$L$3) -> -4.4 | N24: =FORECAST(N$3,$C24:$L24,$C$3:$L$3) -> -5.6 | O24: =FORECAST(O$3,$C24:$L24,$C$3:$L$3) -> -6.8 | P24: =FORECAST(P$3,$C24:$L24,$C$3:$L$3) -> -8 | Q24: =FORECAST(Q$3,$C24:$L24,$C$3:$L$3) -> -9.2
B25: Acquisition of companies | C25: 0 | D25: 0 | E25: 0 | F25: -15 | G25: -65 | H25: -146 | I25: 0 | J25: -80 | K25: -18 | L25: 0 | M25: =FORECAST(M$3,$C25:$L25,$C$3:$L$3) -> -51.133333 | N25: =FORECAST(N$3,$C25:$L25,$C$3:$L$3) -> -54.539394 | O25: =FORECAST(O$3,$C25:$L25,$C$3:$L$3) -> -57.945455 | P25: =FORECAST(P$3,$C25:$L25,$C$3:$L$3) -> -61.351515 | Q25: =FORECAST(Q$3,$C25:$L25,$C$3:$L$3) -> -64.757576
B26: Other investing items | C26: 7 | D26: 0 | E26: 0 | F26: -5 | G26: -3019 | H26: -1 | I26: 3003 | J26: 795 | K26: -201 | L26: 1311 | M26: =FORECAST(M$3,$C26:$L26,$C$3:$L$3) -> 1067.2 | N26: =FORECAST(N$3,$C26:$L26,$C$3:$L$3) -> 1226.8727 | O26: =FORECAST(O$3,$C26:$L26,$C$3:$L$3) -> 1386.5455 | P26: =FORECAST(P$3,$C26:$L26,$C$3:$L$3) -> 1546.2182 | Q26: =FORECAST(Q$3,$C26:$L26,$C$3:$L$3) -> 1705.8909
B27: Cash from Investing Activities | C27: -9174 | D27: -8303 | E27: -3540 | F27: -556 | G27: -7291 | H27: -239 | I27: -8036 | J27: -11865 | K27: -14456 | L27: -14735 | M27: =SUM(M18:M26) -> -12823.933 | N27: =SUM(N18:N26) -> -13733.83 | O27: =SUM(O18:O26) -> -14643.727 | P27: =SUM(P18:P26) -> -15553.624 | Q27: =SUM(Q18:Q26) -> -16463.521
B29: Financial Activities
B30: Proceeds from borrowings | C30: 484 | D30: 10 | E30: 39 | F30: 0 | G30: 380 | H30: 0 | I30: 831 | J30: 0 | K30: 0 | L30: 0 | M30: =FORECAST(M$3,$C30:$L30,$C$3:$L$3) -> 90.8 | N30: =FORECAST(N$3,$C30:$L30,$C$3:$L$3) -> 75.6 | O30: =FORECAST(O$3,$C30:$L30,$C$3:$L$3) -> 60.4 | P30: =FORECAST(P$3,$C30:$L30,$C$3:$L$3) -> 45.2 | Q30: =FORECAST(Q$3,$C30:$L30,$C$3:$L$3) -> 30
B31: Repayment of borrowings | C31: -231 | D31: -373 | E31: 0 | F31: -46 | G31: 0 | H31: -110 | I31: 0 | J31: -1183 | K31: -33 | L31: 0 | M31: =FORECAST(M$3,$C31:$L31,$C$3:$L$3) -> -245.2 | N31: =FORECAST(N$3,$C31:$L31,$C$3:$L$3) -> -253.85455 | O31: =FORECAST(O$3,$C31:$L31,$C$3:$L$3) -> -262.50909 | P31: =FORECAST(P$3,$C31:$L31,$C$3:$L$3) -> -271.16364 | Q31: =FORECAST(Q$3,$C31:$L31,$C$3:$L$3) -> -279.81818
B32: Interest paid fin | C32: -110 | D32: -346 | E32: -73 | F32: -136 | G32: -102 | H32: -130 | I32: -186 | J32: -147 | K32: -167 | L32: -204 | M32: =FORECAST(M$3,$C32:$L32,$C$3:$L$3) -> -164.8 | N32: =FORECAST(N$3,$C32:$L32,$C$3:$L$3) -> -165.65455 | O32: =FORECAST(O$3,$C32:$L32,$C$3:$L$3) -> -166.50909 | P32: =FORECAST(P$3,$C32:$L32,$C$3:$L$3) -> -167.36364 | Q32: =FORECAST(Q$3,$C32:$L32,$C$3:$L$3) -> -168.21818
B33: Dividends paid | C33: -1057 | D33: -2266 | E33: -2417 | F33: -2417 | G33: -1812 | H33: -1359 | I33: -1812 | J33: -2719 | K33: -3930 | L33: -4244 | M33: =FORECAST(M$3,$C33:$L33,$C$3:$L$3) -> -3722.4 | N33: =FORECAST(N$3,$C33:$L33,$C$3:$L$3) -> -3962.2364 | O33: =FORECAST(O$3,$C33:$L33,$C$3:$L$3) -> -4202.0727 | P33: =FORECAST(P$3,$C33:$L33,$C$3:$L$3) -> -4441.9091 | Q33: =FORECAST(Q$3,$C33:$L33,$C$3:$L$3) -> -4681.7455
B34: Financial liabilities | C34: 0 | D34: 0 | E34: 0 | F34: -10 | G34: -11 | H34: -8 | I34: -46 | J34: -13 | K34: -25 | L34: -36 | M34: =FORECAST(M$3,$C34:$L34,$C$3:$L$3) -> -37.2 | N34: =FORECAST(N$3,$C34:$L34,$C$3:$L$3) -> -41.254545 | O34: =FORECAST(O$3,$C34:$L34,$C$3:$L$3) -> -45.309091 | P34: =FORECAST(P$3,$C34:$L34,$C$3:$L$3) -> -49.363636 | Q34: =FORECAST(Q$3,$C34:$L34,$C$3:$L$3) -> -53.418182
B35: Other financing items | C35: -215 | D35: -461 | E35: -497 | F35: -497 | G35: 0 | H35: 0 | I35: 0 | J35: 0 | K35: 0 | L35: 0 | M35: =FORECAST(M$3,$C35:$L35,$C$3:$L$3) -> 137.6 | N35: =FORECAST(N$3,$C35:$L35,$C$3:$L$3) -> 192.98182 | O35: =FORECAST(O$3,$C35:$L35,$C$3:$L$3) -> 248.36364 | P35: =FORECAST(P$3,$C35:$L35,$C$3:$L$3) -> 303.74545 | Q35: =FORECAST(Q$3,$C35:$L35,$C$3:$L$3) -> 359.12727
B36: Cash from Financial Activities | C36: -1129 | D36: -3436 | E36: -2948 | F36: -3106 | G36: -1545 | H36: -1607 | I36: -1213 | J36: -4062 | K36: -4155 | L36: -4484 | M36: =SUM(M30:M35) -> -3941.2 | N36: =SUM(N30:N35) -> -4154.4182 | O36: =SUM(O30:O35) -> -4367.6364 | P36: =SUM(P30:P35) -> -4580.8545 | Q36: =SUM(Q30:Q35) -> -4794.0727
B38: Net Cash Flow | C38: 2172 | D38: 2858 | E38: -1202 | F38: -2737 | G38: 4356 | H38: -2818 | I38: 377 | J38: 2595 | K38: -2852 | L38: 1516 | M38: =SUM(M36,M27,M15) -> -397.53333 | N38: =SUM(N36,N27,N15) -> -547.35758 | O38: =SUM(O36,O27,O15) -> -697.18182 | P38: =SUM(P36,P27,P15) -> -847.00606 | Q38: =SUM(Q36,Q27,Q15) -> -996.8303

Sheet DCF>

Sheet WACC
B2: Weighted Average Cost of Capital
B4: All figures are in INR unless stated otherwise.
B6: Peer Comps
J7: Debt/ | K7: Debt/ | L7: Levered | M7: Unlevered
B8: Name of the Company | F8: Country | G8: Total Debt | H8: Total Equity | I8: Taxrate1 | J8: Equity | K8: Capital | L8: Beta2 | M8: Beta3
B10: Maruti Suzuki | F10: India | G10: 102.5 | H10: 418196.27 | I10: 0.25 | J10: =G10/H10 -> 0.00024510023 | K10: =G10/(G10+H10) -> 0.00024504017 | L10: ='Beta - Regression'!O8 -> 1.3320929 | M10: =L10/(1+(1-I10)*J10) -> 1.3318481
B11: M & M | F11: India | G11: 133963.15 | H11: 382758.18 | I11: 0.25 | J11: =G11/H11 -> 0.34999422 | K11: =G11/(G11+H11) -> 0.25925609 | L11: 1.34 | M11: =L11/(1+(1-I11)*J11) -> 1.0613898
B12: Hyundai Motor I | F12: India | G12: 1097.56 | H12: 160395.62 | I12: 0.25 | J12: =G12/H12 -> 0.0068428302 | K12: =G12/(G12+H12) -> 0.0067963242 | L12: 1.09 | M12: =L12/(1+(1-I12)*J12) -> 1.0844345
B13: Tata Motors PVeh | F13: India | G13: 79109 | H13: 131063.15 | I13: 0.25 | J13: =G13/H13 -> 0.60359453 | K13: =G13/(G13+H13) -> 0.37640096 | L13: 0.519 | M13: =L13/(1+(1-I13)*J13) -> 0.35726679
F15: Average | G15: =AVERAGE(G10:G13) -> 53568.052 | H15: =AVERAGE(H10:H13) -> 273103.3 | I15: =AVERAGE(I10:I13) -> 0.25 | J15: =AVERAGE(J10:J13) -> 0.24016917 | K15: =AVERAGE(K10:K13) -> 0.1606746 | L15: =AVERAGE(L10:L13) -> 1.0702732 | M15: =AVERAGE(M10:M13) -> 0.9587348
F16: Median | G16: =MEDIAN(G10:G13) -> 40103.28 | H16: =MEDIAN(H10:H13) -> 271576.9 | I16: =MEDIAN(I10:I13) -> 0.25 | J16: =MEDIAN(J10:J13) -> 0.17841852 | K16: =MEDIAN(K10:K13) -> 0.13302621 | L16: =MEDIAN(L10:L13) -> 1.2110464 | M16: =MEDIAN(M10:M13) -> 1.0729122
B19: Cost of Debt | I19: Cost of Equity
B21: Pre-Tax Cost of Debt | F21: 0.08 | I21: Risk Free Rate | M21: 0.0683
B22: Tax Rate | F22: =I16 -> 0.25 | I22: Equity Risk Premium | M22: =Rm!G7-WACC!M21 -> 0.083192308
B23: Post Tax Cost of Debt | F23: =F21*(1-F22) -> 0.06 | I23: Levered Beta4 | M23: =M32 -> 1.2661725
I24: Cost of Equity | M24: =M21+(M22*M23) -> 0.17363581
B27: Capital Structure | I27: Levered Beta
E29: Current | F29: Target | I29: Comps Median Unlevered Beta | M29: =M16 -> 1.0729122
B30: Total Debt | D30: 102.5 | E30: =D30/D31 -> 0.00024510023 | F30: =K15 -> 0.1606746 | I30: Target Debt/Equity | M30: =J15 -> 0.24016917
B31: Market Capitalization | D31: 418196.27 | E31: =E32-E30 -> 0.9997549 | F31: =F32-F30 -> 0.8393254 | I31: Tax Rate | M31: =I15 -> 0.25
B32: Total Capital | D32: =SUM(D30:D31) -> 418298.77 | E32: 1 | F32: 1 | I32: Levered Beta | M32: =M29*(1+(1-M31)*M30) -> 1.2661725
B34: Debt/Equity | E34: =E30 -> 0.00024510023 | F34: =M30 -> 0.24016917 | I34: Weighted Average Cost of Capital
I36: Cost of Equity | M36: =M24 -> 0.17363581
I37: Equity Weight | M37: =F31 -> 0.8393254
B39: 1. Tax Rate considered as Marginal Tax Rate for the Country | I39: Cost of Debt | M39: =F23 -> 0.06
B40: 2. Levered Beta is based on 1 year Weekly Data | I40: Debt Weight | M40: =F30 -> 0.1606746
B41: 3. Unlevered Beta = Levered Beta/(1+(1-Tax Rate)*Debt/Equity
B42: 4. Levered Beta = Unlevered Beta*(1+(1-Tax Rate)*Debt/Equity | I42: WACC | M42: =(M36*M37)+(M39*M40) -> 0.15537742

Sheet Beta - Regression
B2: Regression Beta
B4: Maruti Suzuki India Limited | F4: NIFTY 50 | J4: Beta Drifting | N4: Beta 1 | O4: =SLOPE(D8:D60,H8:H60) -> 1.3320929 | P4: - | Q4: Using slope function
B6: Date | C6: Closing Price | D6: Weekly Return | F6: Date | G6: Closing Price | H6: Weekly Return | J6: Levered Raw Beta | K6: =O8 -> 1.3320929 | N6: Beta 2 | O6: =_xlfn.COVARIANCE.S(D7:D60,H7:H60)/_xlfn.VAR.S(H7:H60) -> 1.3320929 | P6: - | Q6: Using Covarience function
B7: Jun 23, 2025 | C7: 12506.64 | F7: Jun 23, 2025 | G7: 25637.8 | J7: Raw Beta Weight | K7: 0.75
B8: Jun 30, 2025 | C8: 12510.59 | D8: =C8/C7-1 -> 0.00031583223 | F8: Jun 30, 2025 | G8: 25461 | H8: =G8/G7-1 -> -0.0068960675 | N8: Beta3 | O8: =O27 -> 1.3320929 | P8: - | Q8: Using Regression
B9: Jul 7, 2025 | C9: 12439.36 | D9: =C9/C8-1 -> -0.0056935764 | F9: Jul 7, 2025 | G9: 25149.85 | H9: =G9/G8-1 -> -0.012220651 | J9: Market Beta | K9: 1
B10: Jul 14, 2025 | C10: 12286.02 | D10: =C10/C9-1 -> -0.012327001 | F10: Jul 14, 2025 | G10: 24968.4 | H10: =G10/G9-1 -> -0.0072147548 | J10: Market Beta weight | K10: 0.25 | N10: SUMMARY OUTPUT
B11: Jul 21, 2025 | C11: 12271.18 | D11: =C11/C10-1 -> -0.0012078769 | F11: Jul 21, 2025 | G11: 24837 | H11: =G11/G10-1 -> -0.005262652
B12: Jul 28, 2025 | C12: 12170.28 | D12: =C12/C11-1 -> -0.0082225181 | F12: Jul 28, 2025 | G12: 24565.35 | H12: =G12/G11-1 -> -0.010937311 | J12: Adjusted Beta | K12: =(K6*K7)+(K9*K10) -> 1.2490697 | N12: Regression Statistics
B13: Aug 4, 2025 | C13: 12590 | D13: =C13/C12-1 -> 0.034487292 | F13: Aug 4, 2025 | G13: 24363.3 | H13: =G13/G12-1 -> -0.0082249998 | N13: Multiple R | O13: 0.64509301
B14: Aug 11, 2025 | C14: 12936 | D14: =C14/C13-1 -> 0.027482129 | F14: Aug 11, 2025 | G14: 24631.3 | H14: =G14/G13-1 -> 0.011000152 | N14: R Square | O14: 0.416145
B15: Aug 18, 2025 | C15: 14349 | D15: =C15/C14-1 -> 0.10923006 | F15: Aug 18, 2025 | G15: 24870.1 | H15: =G15/G14-1 -> 0.0096949816 | N15: Adjusted R Square | O15: 0.40469686
B16: Aug 25, 2025 | C16: 14791 | D16: =C16/C15-1 -> 0.03080354 | F16: Aug 25, 2025 | G16: 24426.85 | H16: =G16/G15-1 -> -0.017822606 | N16: Standard Error | O16: 0.027156492
B17: Sep 1, 2025 | C17: 14895 | D17: =C17/C16-1 -> 0.0070313028 | F17: Sep 1, 2025 | G17: 24741 | H17: =G17/G16-1 -> 0.012860848 | N17: Observations | O17: 53
B18: Sep 8, 2025 | C18: 15325 | D18: =C18/C17-1 -> 0.028868748 | F18: Sep 8, 2025 | G18: 25114 | H18: =G18/G17-1 -> 0.015076189
B19: Sep 15, 2025 | C19: 15864 | D19: =C19/C18-1 -> 0.035171289 | F19: Sep 15, 2025 | G19: 25327.05 | H19: =G19/G18-1 -> 0.0084833161 | N19: ANOVA
B20: Sep 22, 2025 | C20: 16286 | D20: =C20/C19-1 -> 0.026601109 | F20: Sep 22, 2025 | G20: 24654.7 | H20: =G20/G19-1 -> -0.026546716 | O20: df | P20: SS | Q20: MS | R20: F | S20: Significance F
B21: Sep 29, 2025 | C21: 15806 | D21: =C21/C20-1 -> -0.029473167 | F21: Sep 29, 2025 | G21: 24894.25 | H21: =G21/G20-1 -> 0.0097162002 | N21: Regression | O21: 1 | P21: 0.026807553 | Q21: 0.026807553 | R21: 36.350455 | S21: 1.8464485e-07
B22: Oct 6, 2025 | C22: 16265 | D22: =C22/C21-1 -> 0.029039605 | F22: Oct 6, 2025 | G22: 25285.35 | H22: =G22/G21-1 -> 0.015710455 | N22: Residual | O22: 51 | P22: 0.037611227 | Q22: 0.00073747504
B23: Oct 13, 2025 | C23: 16401 | D23: =C23/C22-1 -> 0.0083615125 | F23: Oct 13, 2025 | G23: 25709.85 | H23: =G23/G22-1 -> 0.016788377 | N23: Total | O23: 52 | P23: 0.06441878
B24: Oct 20, 2025 | C24: 16274 | D24: =C24/C23-1 -> -0.0077434303 | F24: Oct 20, 2025 | G24: 25795.15 | H24: =G24/G23-1 -> 0.0033177945
B25: Oct 27, 2025 | C25: 16186 | D25: =C25/C24-1 -> -0.0054073983 | F25: Oct 27, 2025 | G25: 25722.1 | H25: =G25/G24-1 -> -0.0028319277 | O25: Coefficients | P25: Standard Error | Q25: t Stat | R25: P-value | S25: Lower 95% | T25: Upper 95% | U25: Lower 95.0% | V25: Upper 95.0%
B26: Nov 3, 2025 | C26: 15479 | D26: =C26/C25-1 -> -0.043679723 | F26: Nov 3, 2025 | G26: 25492.3 | H26: =G26/G25-1 -> -0.0089339517 | N26: Intercept | O26: 0.0031025924 | P26: 0.0037368312 | Q26: 0.83027363 | R26: 0.41025398 | S26: -0.0043994093 | T26: 0.010604594 | U26: -0.0043994093 | V26: 0.010604594
B27: Nov 10, 2025 | C27: 15684 | D27: =C27/C26-1 -> 0.01324375 | F27: Nov 10, 2025 | G27: 25910.05 | H27: =G27/G26-1 -> 0.016387301 | N27: X Variable 1 | O27: 1.3320929 | P27: 0.22094267 | Q27: 6.0291338 | R27: 1.8464485e-07 | S27: 0.88853199 | T27: 1.7756538 | U27: 0.88853199 | V27: 1.7756538
B28: Nov 17, 2025 | C28: 15977 | D28: =C28/C27-1 -> 0.018681459 | F28: Nov 17, 2025 | G28: 26068.15 | H28: =G28/G27-1 -> 0.0061018794
B29: Nov 24, 2025 | C29: 15900 | D29: =C29/C28-1 -> -0.0048194279 | F29: Nov 24, 2025 | G29: 26202.95 | H29: =G29/G28-1 -> 0.0051710612
B30: Dec 1, 2025 | C30: 16282 | D30: =C30/C29-1 -> 0.024025157 | F30: Dec 1, 2025 | G30: 26186.45 | H30: =G30/G29-1 -> -0.00062970009
B31: Dec 8, 2025 | C31: 16522 | D31: =C31/C30-1 -> 0.014740204 | F31: Dec 8, 2025 | G31: 26046.95 | H31: =G31/G30-1 -> -0.0053271826
B32: Dec 15, 2025 | C32: 16414 | D32: =C32/C31-1 -> -0.0065367389 | F32: Dec 15, 2025 | G32: 25966.4 | H32: =G32/G31-1 -> -0.0030924926
B33: Dec 22, 2025 | C33: 16596 | D33: =C33/C32-1 -> 0.011088096 | F33: Dec 22, 2025 | G33: 26042.3 | H33: =G33/G32-1 -> 0.0029230082
B34: Dec 29, 2025 | C34: 16960 | D34: =C34/C33-1 -> 0.021932996 | F34: Dec 29, 2025 | G34: 26328.55 | H34: =G34/G33-1 -> 0.010991733
B35: Jan 5, 2026 | C35: 16501 | D35: =C35/C34-1 -> -0.027063679 | F35: Jan 5, 2026 | G35: 25683.3 | H35: =G35/G34-1 -> -0.024507616
B36: Jan 12, 2026 | C36: 15859 | D36: =C36/C35-1 -> -0.038906733 | F36: Jan 12, 2026 | G36: 25694.35 | H36: =G36/G35-1 -> 0.00043024066
B37: Jan 19, 2026 | C37: 15469 | D37: =C37/C36-1 -> -0.024591714 | F37: Jan 19, 2026 | G37: 25048.65 | H37: =G37/G36-1 -> -0.025130038
B38: Jan 26, 2026 | C38: 14199 | D38: =C38/C37-1 -> -0.082099683 | F38: Jan 26, 2026 | G38: 24825.45 | H38: =G38/G37-1 -> -0.0089106599
B39: Feb 2, 2026 | C39: 14997 | D39: =C39/C38-1 -> 0.056201141 | F39: Feb 2, 2026 | G39: 25693.7 | H39: =G39/G38-1 -> 0.03497419
... B60: Jun 23, 2026 | C60: 13295 | D60: =C60/C59-1 -> -0.0093882721 | F60: Jun 23, 2026 | G60: 24124.65 | H60: =G60/G59-1 -> 0.00090238104

Sheet Rm
B2: Return on Market
B4: Year | C4: Annual
B5: 2000 | C5: -0.1465 | E5: Average Return | G5: =AVERAGE(C5:C30) -> 0.15149231
B6: 2001 | C6: -0.1618 | E6: Dividend Yield | G6: 1.30% 1
B7: 2002 | C7: 0.0325 | E7: Total Market Returns | G7: =SUM(G5:G6) -> 0.15149231
B8: 2003 | C8: 0.719
B9: 2004 | C9: 0.1068
B10: 2005 | C10: 0.3634
B11: 2006 | C11: 0.3983
B12: 2007 | C12: 0.5477
B13: 2008 | C13: -0.5179
B14: 2009 | C14: 0.7576
B15: 2010 | C15: 0.1795
B16: 2011 | C16: -0.2462
B17: 2012 | C17: 0.277
B18: 2013 | C18: 0.0676
B19: 2014 | C19: 0.3139
... B30: 2025 | C30: 0.1051

Sheet Intrinsic Growth
B2: Calculation of ROIC | G2: =RawFS!I2 -> 44256 | H2: =RawFS!J2 -> 44621 | I2: =RawFS!K2 -> 44986 | J2: =RawFS!L2 -> 45352 | K2: =RawFS!M2 -> 45717
A4: # | B4: Current Assest
B5: =RawFS!B36 -> Inventories | G5: =RawFS!I36 -> 3049 | H5: =RawFS!J36 -> 3532 | I5: =RawFS!K36 -> 4284 | J5: =RawFS!L36 -> 5318 | K5: =RawFS!M36 -> 6913
B6: =RawFS!B37 -> Trade receivables | G6: =RawFS!I37 -> 1280 | H6: =RawFS!J37 -> 2034 | I6: =RawFS!K37 -> 3301 | J6: =RawFS!L37 -> 4597 | K6: =RawFS!M37 -> 6540
B7: =RawFS!B39 -> Loans n Advances | G7: =RawFS!I39 -> 1412 | H7: =RawFS!J39 -> 2880 | I7: =RawFS!K39 -> 2828 | J7: =RawFS!L39 -> 266 | K7: =RawFS!M39 -> 851
B8: =RawFS!B40 -> Other asset items | G8: =RawFS!I40 -> 3158 | H8: =RawFS!J40 -> 4448 | I8: =RawFS!K40 -> 4223 | J8: =RawFS!L40 -> 9400 | K8: =RawFS!M40 -> 9937
B9: Total Current Assets | G9: =SUM(G5:G8) -> 8899 | H9: =SUM(H5:H8) -> 12894 | I9: =SUM(I5:I8) -> 14636 | J9: =SUM(J5:J8) -> 19581 | K9: =SUM(K5:K8) -> 24241
B11: Current Liabilities
B12: =RawFS!B13 -> Trade Payables | G12: =RawFS!I13 -> 10168 | H12: =RawFS!J13 -> 9765 | I12: =RawFS!K13 -> 11786 | J12: =RawFS!L13 -> 16988 | K12: =RawFS!M13 -> 20502
B13: =RawFS!B14 -> Advance from Customers | G13: =RawFS!I14 -> 1019 | H13: =RawFS!J14 -> 1124 | I13: =RawFS!K14 -> 1456 | J13: =RawFS!L14 -> 1464 | K13: =RawFS!M14 -> 1135
B14: =RawFS!B15 -> Other liability items | G14: =RawFS!I15 -> 7148 | H14: =RawFS!J15 -> 8007 | I14: =RawFS!K15 -> 8317 | J14: =RawFS!L15 -> 11098 | K14: =RawFS!M15 -> 14008
B15: Total Current Liabilities | G15: =SUM(G12:G14) -> 18335 | H15: =SUM(H12:H14) -> 18896 | I15: =SUM(I12:I14) -> 21559 | J15: =SUM(J12:J14) -> 29550 | K15: =SUM(K12:K14) -> 35645
A17: # | B17: Net Working Capital | G17: =G9-G15 -> -9436 | H17: =H9-H15 -> -6002 | I17: =I9-I15 -> -6923 | J17: =J9-J15 -> -9969 | K17: =K9-K15 -> -11404
B19: Total Non Current Assets
B20: =RawFS!B19 -> Land | G20: =RawFS!I19 -> 4566 | H20: =RawFS!J19 -> 4592 | I20: =RawFS!K19 -> 6757 | J20: =RawFS!L19 -> 6896 | K20: =RawFS!M19 -> 6921
B21: =RawFS!B20 -> Building | G21: =RawFS!I20 -> 2831 | H21: =RawFS!J20 -> 2955 | I21: =RawFS!K20 -> 3206 | J21: =RawFS!L20 -> 5604 | K21: =RawFS!M20 -> 8158
B22: =RawFS!B21 -> Plant Machinery | G22: =RawFS!I21 -> 22262 | H22: =RawFS!J21 -> 22712 | I22: =RawFS!K21 -> 26174 | J22: =RawFS!L21 -> 44745 | K22: =RawFS!M21 -> 51915
B23: =RawFS!B22 -> Computers | G23: =RawFS!I22 -> 292 | H23: =RawFS!J22 -> 324 | I23: =RawFS!K22 -> 368 | J23: =RawFS!L22 -> 601 | K23: =RawFS!M22 -> 698
B24: =RawFS!B23 -> Furniture n fittings | G24: =RawFS!I23 -> 403 | H24: =RawFS!J23 -> 445 | I24: =RawFS!K23 -> 485 | J24: =RawFS!L23 -> 636 | K24: =RawFS!M23 -> 698
B25: =RawFS!B24 -> Railway sidings | G25: =RawFS!I24 -> 0 | H25: =RawFS!J24 -> 0 | I25: =RawFS!K24 -> 73 | J25: =RawFS!L24 -> 74 | K25: =RawFS!M24 -> 94
B26: =RawFS!B25 -> Vehicles | G26: =RawFS!I25 -> 174 | H26: =RawFS!J25 -> 248 | I26: =RawFS!K25 -> 282 | J26: =RawFS!L25 -> 448 | K26: =RawFS!M25 -> 568
B27: =RawFS!B26 -> Intangible Assets | G27: =RawFS!I26 -> 0 | H27: =RawFS!J26 -> 0 | I27: =RawFS!K26 -> 0 | J27: =RawFS!L26 -> 0 | K27: =RawFS!M26 -> 0
B28: =RawFS!B27 -> Other fixed assets | G28: =RawFS!I27 -> 967 | H28: =RawFS!J27 -> 1254 | I28: =RawFS!K27 -> 1660 | J28: =RawFS!L27 -> 1783 | K28: =RawFS!M27 -> 2002
B30: =RawFS!B28 -> Gross Block | G30: =SUM(G20:G28) -> 31495 | H30: =SUM(H20:H28) -> 32530 | I30: =SUM(I20:I28) -> 39005 | J30: =SUM(J20:J28) -> 60787 | K30: =SUM(K20:K28) -> 71054
B31: =RawFS!B29 -> Accumulated Depreciation | G31: =RawFS!I29 -> 16508 | H31: =RawFS!J29 -> 18783 | I31: =RawFS!K29 -> 21174 | J31: =RawFS!L29 -> 32922 | K31: =RawFS!M29 -> 38070
A32: # | B32: Net Non Current Assets | G32: =G30-G31 -> 14987 | H32: =H30-H31 -> 13747 | I32: =I30-I31 -> 17831 | J32: =J30-J31 -> 27865 | K32: =K30-K31 -> 32984
A34: # | B34: Invested Capital | G34: =G32+G17 -> 5551 | H34: =H32+H17 -> 7745 | I34: =I32+I17 -> 10908 | J34: =J32+J17 -> 17896 | K34: =K32+K17 -> 21580
B35: EBIT | G35: =HistoricalFS!G30+HistoricalFS!G24 -> 5422.8 | H35: =HistoricalFS!H30+HistoricalFS!H24 -> 4823.8 | I35: =HistoricalFS!I30+HistoricalFS!I24 -> 10510.1 | J35: =HistoricalFS!J30+HistoricalFS!J24 -> 17618.1 | K35: =HistoricalFS!K30+HistoricalFS!K24 -> 19814.2
B36: =B47 -> EBIT(1-T) | G36: =G47 -> 4067.1 | H36: =H47 -> 3617.85 | I36: =I47 -> 7882.575 | J36: =J47 -> 13213.575 | K36: =K47 -> 14860.65
A38: # | B38: ROIC | G38: =G36/G34 -> 0.7326788 | H38: =H36/H34 -> 0.46712072 | I38: =I36/I34 -> 0.72264164 | J38: =J36/J34 -> 0.73835354 | K38: =K36/K34 -> 0.68863068
A40: # | B40: Calculation of Reinvestment Capital | G40: =G2 -> 44256 | H40: =H2 -> 44621 | I40: =I2 -> 44986 | J40: =J2 -> 45352 | K40: =K2 -> 45717
B42: Net Capex | G42: =-SUM(RawFS!I55:I56) -> 2328 | H42: =-SUM(RawFS!J55:J56) -> 3323 | I42: =-SUM(RawFS!K55:K56) -> 6247 | J42: =-SUM(RawFS!L55:L56) -> 9155 | K42: =-SUM(RawFS!M55:M56) -> 10603
B43: Change in Working Capital | H43: =H17-G17 -> 3434 | I43: =I17-H17 -> -921 | J43: =J17-I17 -> -3046 | K43: =K17-J17 -> -1435
B45: EBIT | G45: =G35 -> 5422.8 | H45: =H35 -> 4823.8 | I45: =I35 -> 10510.1 | J45: =J35 -> 17618.1 | K45: =K35 -> 19814.2
B46: Marginal Tax Rate | G46: 0.25 | H46: 0.25 | I46: 0.25 | J46: 0.25 | K46: 0.25
B47: EBIT(1-T) | G47: =G45*(1-G46) -> 4067.1 | H47: =H45*(1-H46) -> 3617.85 | I47: =I45*(1-I46) -> 7882.575 | J47: =J45*(1-J46) -> 13213.575 | K47: =K45*(1-K46) -> 14860.65
B49: Reinvestment | H49: =SUM(H42:H43) -> 6757 | I49: =SUM(I42:I43) -> 5326 | J49: =SUM(J42:J43) -> 6109 | K49: =SUM(K42:K43) -> 9168
B50: Reinvestment Rate | H50: =H49/H47 -> 1.8676838 | I50: =I49/I47 -> 0.67566753 | J50: =J49/J47 -> 0.46232757 | K50: =K49/K47 -> 0.61693129
I52: 4 Year Average | K52: =AVERAGE(H50:K50) -> 0.90565256
I53: 4 Year Median | K53: =MEDIAN(H50:K50) -> 0.64629941
A55: # | B55: Calculation of Growth Rate | G55: =G2 -> 44256 | H55: =H2 -> 44621 | I55: =I2 -> 44986 | J55: =J2 -> 45352 | K55: =K2 -> 45717
B57: =B50 -> Reinvestment Rate | H57: =H50 -> 1.8676838 | I57: =I50 -> 0.67566753 | J57: =J50 -> 0.46232757 | K57: =K50 -> 0.61693129
B58: =B38 -> ROIC | H58: =H38 -> 0.46712072 | I58: =I38 -> 0.72264164 | J58: =J38 -> 0.73835354 | K58: =K38 -> 0.68863068
B60: Intrinsic Growth | H60: =H57*H58 -> 0.87243383 | I60: =I57*I58 -> 0.48826549 | J60: =J57*J58 -> 0.3413612 | K60: =K57*K58 -> 0.42483781

Sheet DCF
B2: Calculation of PV of FCFF | G2: ='Data Sheet'!J16 -> 45747 | H2: =G2+365 -> 46112 | I2: =H2+365 -> 46477 | J2: =I2+365 -> 46842 | K2: =J2+365 -> 47207 | L2: =K2+365 -> 47572
B4: EBIT | G4: ='Data Sheet'!J32-'Data Sheet'!J26 -> 14615.4 | H4: =G4*(1+$D$19) -> 16076.94 | I4: =H4*(1+$D$19) -> 17684.634 | J4: =I4*(1+$D$19) -> 19453.097 | K4: =J4*(1+$D$19) -> 21398.407 | L4: =K4*(1+$D$19) -> 23538.248
B6: Tax Rate | G6: 0.25 | H6: =G6 -> 0.25 | I6: =H6 -> 0.25 | J6: =I6 -> 0.25 | K6: =J6 -> 0.25 | L6: =K6 -> 0.25
B8: EBIT(1-T) | G8: =G4*(1-G6) -> 10961.55 | H8: =H4*(1-H6) -> 12057.705 | I8: =I4*(1-I6) -> 13263.476 | J8: =J4*(1-J6) -> 14589.823 | K8: =K4*(1-K6) -> 16048.805 | L8: =L4*(1-L6) -> 17653.686
B10: Less: Reinvestment Rate | G10: ='Intrinsic Growth'!K50 -> 0.61693129 | H10: =G$10+(($L$10-$G$10)/4) -> 0.62519847 | I10: =H$10+(($L$10-$G$10)/4) -> 0.63346565 | J10: =I$10+(($L$10-$G$10)/4) -> 0.64173282 | K10: =J$10+(($L$10-$G$10)/4) -> 0.65 | L10: 0.65
B12: Free Cash Flow to Firm | G12: =G8*(1-G10) -> 4199.0268 | H12: =H8*(1-H10) -> 4519.2463 | I12: =I8*(1-I10) -> 4861.5194 | J12: =J8*(1-J10) -> 5227.0547 | K12: =K8*(1-K10) -> 5617.0819 | L12: =L8*(1-L10) -> 6178.7901
B14: Mid Year Covention | H14: 0.5 | I14: =H14+1 -> 1.5 | J14: =I14+1 -> 2.5 | K14: =J14+1 -> 3.5 | L14: =K14+1 -> 4.5
B15: Discounting Factor | H15: =1/(1+$D$21)^H14 -> 0.93033222 | I15: =1/(1+$D$21)^I14 -> 0.80521932 | J15: =1/(1+$D$21)^J14 -> 0.69693184 | K15: =1/(1+$D$21)^K14 -> 0.60320708 | L15: =1/(1+$D$21)^L14 -> 0.52208661
B17: PV of FCFF | H17: =H15*H12 -> 4204.4004 | I17: =I15*I12 -> 3914.5894 | J17: =J15*J12 -> 3642.9009 | K17: =K15*K12 -> 3388.2636 | L17: =L15*L12 -> 3225.8636
B19: Expected Growth | D19: 0.1
B20: Terminal Growth | D20: 0.05
B21: WACC | D21: =WACC!M42 -> 0.15537742
A23: # | B23: Calculation of Terminal Value
B25: FCFF(n+1) | D25: =L12*(1+D19) -> 6796.6691
B26: WACC | D26: =D21 -> 0.15537742
B27: Terminal Growth Rate | D27: =D20 -> 0.05
B29: Terminal Value | D29: =D25/(D26-D27) -> 64498.343
A31: # | B31: Calculation of Equity Value
B33: PV of FCFF | D33: =SUM(H17:L17) -> 18376.018
B34: PV of Terminal Value | D34: =D29*L15 -> 33673.721
B35: Value of Operating Assets | D35: =SUM(D33:D34) -> 52049.739
B37: Add: Cash | D37: ='Data Sheet'!J69 -> 552.9
B38: Less: Debt | D38: ='Data Sheet'!J59 -> 87
B39: Value of Equity | D39: =D37+D35-D38 -> 52515.639
B40: No of Shares | D40: ='Data Sheet'!B6 -> 31.440258
A41: # | B41: Equity Value per Shares | D41: =D39/D40 -> 1670.3311
B43: Share Price | D43: 13250
B44: Discount/Premium | D44: =D43/D41-1 -> 6.9325592

Sheet Data>

Sheet Data Sheet
A1: COMPANY NAME | B1: MARUTI SUZUKI INDIA LTD | E1: =IF(B2<>B3, "A NEW VERSION OF THE WORKSHEET IS AVAILABLE", "")
A2: LATEST VERSION | B2: 2.1 | E2: PLEASE DO NOT MAKE ANY CHANGES TO THIS SHEET
A3: CURRENT VERSION | B3: 2.1
A5: META
A6: Number of shares | B6: =IF(B9>0, B9/B8, 0) -> 31.440258
A7: Face Value | B7: 5
A8: Current Price | B8: 13395
A9: Market Capitalization | B9: 421142.25
A15: PROFIT & LOSS
A16: Report Date | B16: 42825 | C16: 43190 | D16: 43555 | E16: 43921 | F16: 44286 | G16: 44651 | H16: 45016 | I16: 45382 | J16: 45747 | K16: 46112
A17: Sales | B17: 68085 | C17: 79809.4 | D17: 86068.5 | E17: 75660 | F17: 70372 | G17: 88329.8 | H17: 117571.3 | I17: 141858.2 | J17: 152913 | K17: 183316
A18: Raw Material Cost | B18: 47121.5 | C18: 54945.3 | D18: 59346.6 | E18: 53402 | F18: 50550.5 | G18: 66137.1 | H18: 86654.7 | I18: 100119.5 | J18: 108718.3 | K18: 134848
A19: Change in Inventory | B19: 379.3 | C19: -40.8 | D19: -211.6 | E19: 238.7 | F19: -273.6 | G19: 93.1 | H19: 403.9 | I19: 378.6 | J19: 1227.5 | K19: 2272.5
A20: Power and Fuel | B20: 518.6 | C20: 673.4 | D20: 863.3 | E20: 699.5 | F20: 476.6 | G20: 630.9 | H20: 790 | I20: 1033.4 | J20: 1052.6
A21: Other Mfr. Exp | B21: 382.9 | C21: 462.1 | D21: 475.7 | E21: 378.1 | F21: 683.3 | G21: 852.5 | H21: 1120.7 | I21: 939.3 | J21: 1994.4
A22: Employee Cost | B22: 2360.3 | C22: 2863.4 | D22: 3285 | E22: 3416.2 | F22: 3431.6 | G22: 4051.4 | H22: 4634.6 | I22: 6301.6 | J22: 7026 | K22: 9049.7
A23: Selling and admin | B23: 6111.3 | C23: 6755.3 | D23: 8390.3 | E23: 8456.3 | F23: 7924 | G23: 9119.1 | H23: 11695 | I23: 12082.6 | J23: 11523.3
A24: Other Expenses | B24: 1548.4 | C24: 1951.2 | D24: 2439.7 | E24: 2191.6 | F24: 1621.8 | G24: 1879.9 | H24: 2051 | I24: 3134.1 | J24: 3602.3 | K24: 20234.6
A25: Other Income | B25: 2399.2 | C25: 2154.6 | D25: 2664.2 | E25: 3410.4 | F25: 3046.3 | G25: 1860.8 | H25: 2306.6 | I25: 4247.6 | J25: 5198.8 | K25: 4642.7
A26: Depreciation | B26: 2603.9 | C26: 2759.8 | D26: 3020.8 | E26: 3528.4 | F26: 3034.1 | G26: 2789 | H26: 2825.7 | I26: 5255.8 | J26: 5608.2 | K26: 6741.7
A27: Interest | B27: 89.4 | C27: 345.8 | D27: 75.9 | E27: 134.2 | F27: 101.8 | G27: 126.6 | H27: 187 | I27: 193.6 | J27: 194.2 | K27: 238.7
A28: Profit before tax | B28: 10127.2 | C28: 11166.9 | D28: 10623.8 | E28: 7102.8 | F28: 5321 | G28: 4697.2 | H28: 10323.1 | I28: 17424.5 | J28: 19620 | K28: 19118.5
A29: Tax | B29: 2616.2 | C29: 3286.2 | D29: 2973.2 | E29: 1425.2 | F29: 931.9 | G29: 817.7 | H29: 2112.1 | I29: 3936.3 | J29: 5119.8 | K29: 4439
A30: Net profit | B30: 7509.9 | C30: 7880 | D30: 7649.1 | E30: 5676 | F30: 4389.1 | G30: 3879.5 | H30: 8211 | I30: 13488.2 | J30: 14500.2 | K30: 14679.5
A31: Dividend Amount | B31: 2265 | C31: 2416 | D31: 2416 | E31: 1812 | F31: 1359 | G31: 1812 | H31: 2718 | I31: 3930 | J31: 4244.4 | K31: 4401.6
A32: EBITDA | B32: =B30+B29+B27+B26-B25 -> 10420.2 | C32: =C30+C29+C27+C26-C25 -> 12117.2 | D32: =D30+D29+D27+D26-D25 -> 11054.8 | E32: =E30+E29+E27+E26-E25 -> 7353.4 | F32: =F30+F29+F27+F26-F25 -> 5410.6 | G32: =G30+G29+G27+G26-G25 -> 5752 | H32: =H30+H29+H27+H26-H25 -> 11029.2 | I32: =I30+I29+I27+I26-I25 -> 18626.3 | ... K32: =K30+K29+K27+K26-K25 -> 21456.2
A40: Quarters
A41: Report Date | B41: 45291 | C41: 45382 | D41: 45473 | E41: 45565 | F41: 45657 | G41: 45747 | H41: 45838 | I41: 45930 | J41: 46022 | K41: 46112
A42: Sales | B42: 33512.8 | C42: 38471.2 | D42: 35779.4 | E42: 37449.2 | F42: 38764.3 | G42: 40920.1 | H42: 38605.2 | I42: 42344.2 | J42: 49904.1 | K42: 52462.5
A43: Expenses | B43: 29072.8 | C43: 33250.1 | D43: 30672.8 | E43: 32450.4 | F43: 33687.8 | G43: 36076.1 | H43: 33982.6 | I43: 37258.2 | J43: 44331 | K43: 46304.2
A44: Other Income | B44: 1052.9 | C44: 1261 | D44: 1118.1 | E44: 1570.5 | F44: 1124.8 | G44: 1583.1 | H44: 1923.7 | I44: 1013.5 | J44: 1140.5 | K44: 581.2
A45: Depreciation | B45: 1301.5 | C45: 1298.3 | D45: 1331.7 | E45: 1385.7 | F45: 1429 | G45: 1461.8 | H45: 1556 | I45: 1703 | J45: 1734.6 | K45: 1748.1
A46: Interest | B46: 35.8 | C46: 76.2 | D46: 57.3 | E46: 43 | F46: 46.3 | G46: 47.6 | H46: 46.8 | I46: 57.2 | J46: 61.7 | K46: 73
A47: Profit before tax | B47: 4155.6 | C47: 5107.6 | D47: 4835.7 | E47: 5140.6 | F47: 4726 | G47: 4917.7 | H47: 4943.5 | I47: 4339.3 | J47: 4917.3 | K47: 4918.4
A48: Tax | B48: 948.8 | C48: 1155.3 | D48: 1076 | E48: 2038.1 | F48: 999.1 | G48: 1006.6 | H48: 1151.1 | I48: 990.3 | J48: 1038.2 | K48: 1259.4
A49: Net profit | B49: 3206.8 | C49: 3952.3 | D49: 3759.7 | E49: 3102.5 | F49: 3726.9 | G49: 3911.1 | H49: 3792.4 | I49: 3349 | J49: 3879.1 | K49: 3659
A50: Operating Profit | B50: 4440 | C50: 5221.1 | D50: 5106.6 | E50: 4998.8 | F50: 5076.5 | G50: 4844 | H50: 4622.6 | I50: 5086 | J50: 5573.1 | K50: 6158.3
A55: BALANCE SHEET
A56: Report Date | B56: 42825 | C56: 43190 | D56: 43555 | E56: 43921 | F56: 44286 | G56: 44651 | H56: 45016 | I56: 45382 | J56: 45747 | K56: 46112
A57: Equity Share Capital | B57: 151 | C57: 151 | D57: 151 | E57: 151 | F57: 151 | G57: 151 | H57: 151 | I57: 157.2 | J57: 157.2 | K57: 157.2
A58: Reserves | B58: 36924.1 | C58: 42408.4 | D58: 46941.1 | E58: 49262 | F58: 52349.6 | G58: 55182.5 | H58: 61640.3 | I58: 85478.8 | J58: 96082.7 | K58: 106999.1
A59: Borrowings | B59: 483.6 | C59: 120.8 | D59: 159.6 | E59: 184.1 | F59: 540.9 | G59: 425.5 | H59: 1247.3 | I59: 118.6 | J59: 87 | K59: 102.5
A60: Other Liabilities | B60: 14401.8 | C60: 17568.2 | D60: 16717 | E60: 14030.6 | F60: 18334.6 | G60: 18896.5 | H60: 21558.3 | I60: 29549.5 | J60: 35644.3 | K60: 41622.2
A61: Total | B61: 51960.5 | C61: 60248.4 | D61: 63968.7 | E61: 63627.7 | F61: 71376.1 | G61: 74655.5 | H61: 84596.9 | I61: 115304.1 | J61: 131971.2 | K61: 148881
A62: Net Block | B62: 13310.7 | C62: 13388.8 | D62: 15437.3 | E62: 15744.4 | F62: 14988.7 | G62: 13747.2 | H62: 17830.4 | I62: 27864.8 | J62: 32982.7 | K62: 34955.4
A63: Capital Work in Progress | B63: 1252.3 | C63: 2132.1 | D63: 1606.9 | E63: 1415.2 | F63: 1496.8 | G63: 2936.5 | H63: 2904.1 | I63: 7734.8 | J63: 7929 | K63: 9406.2
A64: Investments | B64: 29150.6 | C64: 36123.1 | D64: 37503.6 | E64: 37488 | F64: 42944.8 | G64: 42034.7 | H64: 49184.3 | I64: 57296 | J64: 66265.4 | K64: 76838.5
A65: Other Assets | B65: 8246.9 | C65: 8604.4 | D65: 9420.9 | E65: 8980.1 | F65: 11945.8 | G65: 15937.1 | H65: 14678.1 | I65: 22408.5 | J65: 24794.1 | K65: 27680.9
A66: Total | B66: 51960.5 | C66: 60248.4 | D66: 63968.7 | E66: 63627.7 | F66: 71376.1 | G66: 74655.5 | H66: 84596.9 | I66: 115304.1 | J66: 131971.2 | K66: 148881
A67: Receivables | B67: 1202.6 | C67: 1465.4 | D67: 2312.8 | E67: 1977.7 | F67: 1279.9 | G67: 2034.5 | H67: 3301.4 | I67: 4596.8 | J67: 6539.7 | K67: 5342
... A69: Cash & Bank | B69: 23.5 | C69: 74 | D69: 187.8 | E69: 29 | F69: 3047.1 | G69: 3042.2 | H69: 41.6 | I69: 2827.4 | J69: 552.9 | K69: 1580
A70: No. of Equity Shares | B70: 302080060 | C70: 302080060 | D70: 302080060 | E70: 302080060 | F70: 302080060 | G70: 302080060 | H70: 302080060 | I70: 314402574 | J70: 314402574
A71: New Bonus Shares
A72: Face value | B72: 5 | C72: 5 | D72: 5 | E72: 5 | F72: 5 | G72: 5 | H72: 5 | I72: 5 | J72: 5 | K72: 5
A74: Other Assets | B74: =B65-SUM(B67:B69) -> 3757.1 | C74: =C65-SUM(C67:C69) -> 3904.8 | D74: =D65-SUM(D67:D69) -> 3597.7 | E74: =E65-SUM(E67:E69) -> 3759.5 | F74: =F65-SUM(F67:F69) -> 4569.8 | G74: =G65-SUM(G67:G69) -> 7328.1 | H74: =H65-SUM(H67:H69) -> 7051.6 | I74: =I65-SUM(I67:I69) -> 9666.2 | ... K74: =K65-SUM(K67:K69) -> 9438.3
A75: Total Assets | B75: =SUM(B74,B67:B69,B62:B64) -> 51960.5 | C75: =SUM(C74,C67:C69,C62:C64) -> 60248.4 | D75: =SUM(D74,D67:D69,D62:D64) -> 63968.7 | E75: =SUM(E74,E67:E69,E62:E64) -> 63627.7 | F75: =SUM(F74,F67:F69,F62:F64) -> 71376.1 | G75: =SUM(G74,G67:G69,G62:G64) -> 74655.5 | H75: =SUM(H74,H67:H69,H62:H64) -> 84596.9 | I75: =SUM(I74,I67:I69,I62:I64) -> 115304.1 | ... K75: =SUM(K74,K67:K69,K62:K64) -> 148881
A80: CASH FLOW:
A81: Report Date | B81: 42825 | C81: 43190 | D81: 43555 | E81: 43921 | F81: 44286 | G81: 44651 | H81: 45016 | I81: 45382 | J81: 45747 | K81: 46112
A82: Cash from Operating Activity | B82: 10282 | C82: 11787.9 | D82: 6600.9 | E82: 3495.8 | F82: 8856.2 | G82: 1840.5 | H82: 9251.4 | I82: 16801.1 | J82: 16136.2 | K82: 19099.9
A83: Cash from Investing Activity | B83: -9173.2 | C83: -8301.7 | D83: -3539.9 | E83: -556.6 | F83: -7291.3 | G83: -239.2 | H83: -8036.1 | I83: -11864.8 | J83: -14456.1 | K83: -14733.5
A84: Cash from Financing Activity | B84: -1129.3 | C84: -3436.1 | D84: -2947.9 | E84: -3104.3 | F84: -1544.9 | G84: -1607 | H84: -1213.1 | I84: -4062 | J84: -4155.1 | K84: -4484
A85: Net Cash Flow | B85: -20.5 | C85: 50.1 | D85: 113.1 | E85: -165.1 | F85: 20 | G85: -5.7 | H85: 2.2 | I85: 874.3 | J85: -2475 | K85: -117.6
A90: PRICE: | B90: 6015.7 | C90: 8861.1 | D90: 6672.55 | E90: 4288.3 | F90: 6859.2 | G90: 7561.3 | H90: 8292.15 | I90: 12600.35 | J90: 11522.15 | K90: 12306
A92: DERIVED:
A93: Adjusted Equity Shares in Cr | B93: 30.21 | C93: 30.21 | D93: 30.21 | E93: 30.21 | F93: 30.21 | G93: 30.21 | H93: 30.21 | I93: 31.44 | J93: 31.44 | K93: 31.44

Sheet Cashflow Data
C3: 42064 | D3: 42430 | E3: 42795 | F3: 43160 | G3: 43525 | H3: 43891 | I3: 44256 | J3: 44621 | K3: 44986 | L3: 45352 | M3: 45717 | N3: 46082
B4: Cash from Operating Activity - | C4: 6449 | D4: 8482 | E4: 10282 | F4: 11788 | G4: 6601 | H4: 3496 | I4: 8856 | J4: 1840 | K4: 9251 | L4: 16801 | M4: 16136 | N4: 19100
B5: Profit from operations | C5: 6779 | D5: 8935 | E5: 10413 | F5: 12036 | G5: 11060 | H5: 7503 | I5: 5531 | J5: 5832 | K5: 11112 | L5: 18676 | M5: 20322 | N5: 21802
B6: Receivables | C6: 345 | D6: -204 | E6: 122 | F6: -262 | G6: -851 | H6: 340 | I6: 696 | J6: -764 | K6: -1258 | L6: -1316 | M6: -1969 | N6: 1236
B7: Inventory | C7: -982 | D7: -450 | E7: -131 | F7: 104 | G7: -162 | H7: 109 | I7: 165 | J7: -483 | K7: -751 | L7: 125 | M7: -1595 | N7: -4407
B8: Payables | C8: 712 | D8: 1789 | E8: 979 | F8: 2128 | G8: -858 | H8: -2155 | I8: 2680 | J8: -396 | K8: 2008 | L8: 3321 | M8: 3509 | N8: 5194
B9: Loans Advances | C9: 23 | D9: -1 | E9: 1 | F9: 0 | G9: -13 | H9: -1 | I9: -6 | J9: -8 | K9: 1 | L9: -3 | M9: -10 | N9: -1
B10: Other WC items | C10: 648 | D10: 325 | E10: 1222 | F10: 839 | G10: 569 | H10: -863 | I10: 801 | J10: -1162 | K10: 374 | L10: -406 | M10: -313 | N10: -387
B11: Working capital changes | C11: 745 | D11: 1460 | E11: 2192 | F11: 2808 | G11: -1315 | H11: -2570 | I11: 4336 | J11: -2813 | K11: 373 | L11: 1722 | M11: -378 | N11: 1635
B12: Direct taxes | C12: -1075 | D12: -1912 | E12: -2323 | F12: -3056 | G12: -3144 | H12: -1438 | I12: -1011 | J12: -1178 | K12: -2233 | L12: -3597 | M12: -3807 | N12: -4337
B13: Cash from Investing Activity - | C13: -4491 | D13: -7230 | E13: -9173 | F13: -8302 | G13: -3540 | H13: -557 | I13: -7291 | J13: -239 | K13: -8036 | L13: -11865 | M13: -14456 | N13: -14734
B14: Fixed assets purchased | C14: -3058 | D14: -2469 | E14: -3391 | F14: -3912 | G14: -4872 | H14: -3437 | I14: -2370 | J14: -3459 | K14: -6347 | L14: -9200 | M14: -10641 | N14: -10398
B15: Fixed assets sold | C15: 16 | D15: 12 | E15: 16 | F15: 26 | G15: 170 | H15: 37 | I15: 42 | J15: 136 | K15: 100 | L15: 45 | M15: 38 | N15: 52
... B30: Net Cash Flow | C30: -45 | D30: 16 | E30: -20 | F30: 50 | G30: 113 | H30: -165 | I30: 20 | J30: -6 | K30: 2 | L30: 874 | M30: -2475 | N30: -118

Sheet Raw Data
I1: Nifty 50 returns
I3: Year | J3: Jan | K3: Feb | L3: Mar | M3: Apr | N3: May | O3: Jun | P3: Jul | Q3: Aug | R3: Sep | S3: Oct | T3: Nov | U3: Dec | V3: Annual
I4: 2000 | J4: 4.44 | K4: 7.02 | L4: -7.64 | M4: -7.98 | N4: -1.86 | O4: 6.59 | P4: -9.42 | Q4: 4.6 | R4: -8.78 | S4: -7.78 | T4: 8.13 | U4: -0.36 | V4: -14.65
B5: S.N | C5: Name | D5: CMP Rs. | E5: Mar Cap Rs.Cr. | F5: Debt Rs.Cr. | G5: Debt / Eq | I5: 2001 | J5: 8.56 | K5: -1.48 | L5: -15.04 | M5: -2 | N5: 3.79 | O5: -5.14 | P5: -3.16 | Q5: -1.78 | R5: -13.28 | S5: 6.35 | T5: 9.8 | U5: -0.76 | V5: -16.18
B6: 1 | C6: Maruti Suzuki | D6: 13301.3 | E6: 418196.27 | F6: 102.5 | G6: 0 | I6: 2002 | J6: 1.54 | K6: 6.2 | L6: -1.09 | M6: -3.99 | N6: -5.14 | O6: 2.82 | P6: -9.35 | Q6: 5.39 | R6: -4.7 | S6: -1.22 | T6: 10.38 | U6: 4.13 | V6: 3.25
B7: 2 | C7: M & M | D7: 3078 | E7: 382758.18 | F7: 133963.15 | G7: 1.44 | I7: 2003 | J7: -4.72 | K7: 2.07 | L7: -8.01 | M7: -4.51 | N7: 7.79 | O7: 12.65 | P7: 4.56 | Q7: 14.39 | R7: 4.46 | S7: 9.79 | T7: 3.81 | U7: 16.38 | V7: 71.9
B8: 3 | C8: Hyundai Motor I | D8: 1974 | E8: 160395.62 | F8: 1097.56 | G8: 0.05 | I8: 2004 | J8: -3.72 | K8: -0.52 | L8: -1.58 | M8: 1.37 | N8: -17.4 | O8: 1.48 | P8: 8.42 | Q8: -0.03 | R8: 6.97 | S8: 2.37 | T8: 9.62 | U8: 6.21 | V8: 10.68
B9: 4 | C9: Tata Motors PVeh | D9: 355.9 | E9: 131063.15 | F9: 79109 | G9: 0.71 | I9: 2005 | J9: -1.1 | K9: 2.22 | L9: -3.21 | M9: -6.54 | N9: 9.73 | O9: 6.37 | P9: 4.13 | Q9: 3.13 | R9: 9.09 | S9: -8.86 | T9: 11.86 | U9: 6.95 | V9: 36.34
I10: 2006 | J10: 5.8 | K10: 2.45 | L10: 10.66 | M10: 4.56 | N10: -13.68 | O10: 1.86 | P10: 0.48 | Q10: 8.61 | R10: 5.11 | S10: 4.34 | T10: 5.62 | U10: 0.3 | V10: 39.83
I11: 2007 | J11: 2.93 | K11: -8.26 | L11: 2.04 | M11: 6.97 | N11: 5.09 | O11: 0.52 | P11: 4.88 | Q11: -1.43 | R11: 12.49 | S11: 17.51 | T11: -2.34 | U11: 6.52 | V11: 54.77
I12: 2008 | J12: -16.31 | K12: 1.67 | L12: -9.36 | M12: 9.11 | N12: -5.73 | O12: -17.03 | P12: 7.24 | Q12: 0.62 | R12: -10.06 | S12: -26.41 | T12: -4.52 | U12: 7.41 | V12: -51.79
I13: 2009 | J13: -2.85 | K13: -3.87 | L13: 9.31 | M13: 15 | N13: 28.07 | O13: -3.55 | P13: 8.05 | Q13: 0.55 | R13: 9.05 | S13: -7.32 | T13: 6.81 | U13: 3.35 | V13: 75.76
I14: 2010 | J14: -6.13 | K14: 0.82 | L14: 6.64 | M14: 0.55 | N14: -3.63 | O14: 4.45 | P14: 1.04 | Q14: 0.65 | R14: 11.62 | S14: -0.2 | T14: -2.58 | U14: 4.64 | V14: 17.95
I15: 2011 | J15: -10.25 | K15: -3.14 | L15: 9.38 | M15: -1.44 | N15: -3.29 | O15: 1.57 | P15: -2.93 | Q15: -8.77 | R15: -1.15 | S15: 7.76 | T15: -9.28 | U15: -4.3 | V15: -24.62
I16: 2012 | J16: 12.43 | K16: 3.58 | L16: -1.66 | M16: -0.9 | N16: -6.17 | O16: 7.2 | P16: -0.95 | Q16: 0.56 | R16: 8.46 | S16: -1.47 | T16: 4.63 | U16: 0.43 | V16: 27.7
I17: 2013 | J17: 2.2 | K17: -5.66 | L17: -0.18 | M17: 4.36 | N17: 0.94 | O17: -2.4 | P17: -1.72 | Q17: -4.71 | R17: 4.82 | S17: 9.83 | T17: -1.95 | U17: 2.07 | V17: 6.76
I18: 2014 | J18: -3.4 | K18: 3.08 | L18: 6.81 | M18: -0.12 | N18: 7.97 | O18: 5.28 | P18: 1.44 | Q18: 3.02 | R18: 0.13 | S18: 4.49 | T18: 3.2 | U18: -3.56 | V18: 31.39
I19: 2015 | J19: 6.35 | K19: 1.06 | L19: -4.62 | M19: -3.65 | N19: 3.08 | O19: -0.77 | P19: 1.96 | Q19: -6.58 | R19: -0.28 | S19: 1.47 | T19: -1.62 | U19: 0.14 | V19: -4.06
I20: 2016 | J20: -4.82 | K20: -7.62 | L20: 10.75 | M20: 1.44 | N20: 3.95 | O20: 1.56 | P20: 4.23 | Q20: 1.71 | R20: -1.99 | S20: 0.17 | T20: -4.65 | U20: -0.47 | V20: 3.01
I21: 2017 | J21: 4.59 | K21: 3.72 | L21: 3.31 | M21: 1.42 | N21: 3.41 | O21: -1.04 | P21: 5.84 | Q21: -1.58 | R21: -1.3 | S21: 5.59 | T21: -1.05 | U21: 2.97 | V21: 28.65
... I29: 2025 | J29: -0.58 | K29: -5.89 | L29: 6.3 | M29: 3.46 | N29: 1.71 | O29: 3.1 | P29: -2.93 | Q29: -1.72 | R29: 0.76 | S29: 4.51 | T29: 1.87 | U29: -0.03 | V29: 10.51
I30: 2026 | J30: -3.16 | K30: -0.56 | L30: -11.31 | M30: 7.46 | N30: -1.87

Sheet RawFS
B2: Particulars | C2: 42064 | D2: 42430 | E2: 42795 | F2: 43160 | G2: 43525 | H2: 43891 | I2: 44256 | J2: 44621 | K2: 44986 | L2: 45352 | M2: 45717 | N2: 46082
B4: Equity Capital | C4: 151 | D4: 151 | E4: 151 | F4: 151 | G4: 151 | H4: 151 | I4: 151 | J4: 151 | K4: 151 | L4: 157 | M4: 157 | N4: 157
B5: Reserves | C5: 24167 | D5: 30465 | E5: 36924 | F5: 42408 | G5: 46941 | H5: 49262 | I5: 52350 | J5: 55182 | K5: 61640 | L5: 85479 | M5: 96083 | N5: 106999
B6: Borrowings -
B7: Long term Borrowings | C7: 278 | D7: 0 | E7: 0 | F7: 10 | G7: 8 | H7: 5 | I7: 3 | J7: 0 | K7: 0 | L7: 0 | M7: 0 | N7: 0
B8: Short term Borrowings | C8: 52 | D8: 77 | E8: 484 | F8: 111 | G8: 150 | H8: 106 | I8: 489 | J8: 382 | K8: 1216 | L8: 33 | M8: 0 | N8: 0
B9: Lease Liabilities | C9: 0 | D9: 0 | E9: 0 | F9: 0 | G9: 0 | H9: 70 | I9: 47 | J9: 41 | K9: 32 | L9: 86 | M9: 87 | N9: 102
B10: Other Borrowings | C10: 335 | D10: 154 | E10: 0 | F10: 0 | G10: 2 | H10: 2 | I10: 3 | J10: 3 | K10: 0 | L10: 0 | M10: 0
B11: Other Liabilities -
B12: Non controlling int | C12: 13 | D12: 14 | E12: 15 | F12: 16 | G12: 18 | H12: 19 | I12: 0 | J12: 0 | K12: 0 | L12: 0 | M12: 0 | N12: 0
B13: Trade Payables | C13: 5514 | D13: 7409 | E13: 8369 | F13: 10499 | G13: 9638 | H13: 7499 | I13: 10168 | J13: 9765 | K13: 11786 | L13: 16988 | M13: 20502 | N13: 22134
B14: Advance from Customers | C14: 428 | D14: 506 | E14: 941 | F14: 1152 | G14: 418 | H14: 468 | I14: 1019 | J14: 1124 | K14: 1456 | L14: 1464 | M14: 1135
B15: Other liability items | C15: 3538 | D15: 3950 | E15: 5076 | F15: 5900 | G15: 6644 | H15: 6045 | I15: 7148 | J15: 8007 | K15: 8317 | L15: 11098 | M15: 14008 | N15: 19488
B16: Total Liabilities | C16: 34477 | D16: 42726 | E16: 51960 | F16: 60248 | G16: 63969 | H16: 63628 | I16: 71376 | J16: 74656 | K16: 84597 | L16: 115304 | M16: 131971 | N16: 148881
B18: Fixed Assets -
B19: Land | C19: 2100 | D19: 1902 | E19: 1963 | F19: 3212 | G19: 3914 | H19: 4569 | I19: 4566 | J19: 4592 | K19: 6757 | L19: 6896 | M19: 6921
B20: Building | C20: 1882 | D20: 1513 | E20: 1835 | F20: 1983 | G20: 2333 | H20: 2697 | I20: 2831 | J20: 2955 | K20: 3206 | L20: 5604 | M20: 8158
B21: Plant Machinery | C21: 21802 | D21: 11163 | E21: 13888 | F21: 15082 | G21: 18550 | H21: 20775 | I21: 22262 | J21: 22712 | K21: 26174 | L21: 44745 | M21: 51915
B22: Computers | C22: 193 | D22: 83 | E22: 135 | F22: 172 | G22: 208 | H22: 238 | I22: 292 | J22: 324 | K22: 368 | L22: 601 | M22: 698
B23: Furniture n fittings | C23: 144 | D23: 109 | E23: 140 | F23: 206 | G23: 270 | H23: 347 | I23: 403 | J23: 445 | K23: 485 | L23: 636 | M23: 698
B24: Railway sidings | C24: 0 | D24: 0 | E24: 0 | F24: 0 | G24: 0 | H24: 0 | I24: 0 | J24: 0 | K24: 73 | L24: 74 | M24: 94
B25: Vehicles | C25: 108 | D25: 104 | E25: 130 | F25: 162 | G25: 184 | H25: 206 | I25: 174 | J25: 248 | K25: 282 | L25: 448 | M25: 568
B26: Intangible Assets | C26: 0 | D26: 0 | E26: 0 | F26: 0 | G26: 0 | H26: 0 | I26: 0 | J26: 0 | K26: 0 | L26: 0 | M26: 0 | N26: 936
B27: Other fixed assets | C27: 674 | D27: 468 | E27: 589 | F27: 640 | G27: 907 | H27: 937 | I27: 967 | J27: 1254 | K27: 1660 | L27: 1783 | M27: 2002
B28: Gross Block | C28: 26902 | D28: 15343 | E28: 18680 | F28: 21458 | G28: 26365 | H28: 29768 | I28: 31496 | J28: 32530 | K28: 39004 | L28: 60787 | M28: 71052
B29: Accumulated Depreciation | C29: 14412 | D29: 2813 | E29: 5370 | F29: 8069 | G29: 10928 | H29: 14024 | I29: 16508 | J29: 18783 | K29: 21174 | L29: 32922 | M29: 38070
B30: Net Block | C30: =C28-C29 -> 12490 | D30: =D28-D29 -> 12530 | E30: =E28-E29 -> 13310 | F30: =F28-F29 -> 13389 | G30: =G28-G29 -> 15437 | H30: =H28-H29 -> 15744 | I30: =I28-I29 -> 14988 | J30: =J28-J29 -> 13747 | ... N30: =N28-N29 -> 0
B32: CWIP | C32: 1890 | D32: 1007 | E32: 1252 | F32: 2132 | G32: 1607 | H32: 1415 | I32: 1497 | J32: 2936 | K32: 2904 | L32: 7735 | M32: 7929 | N32: 9406
B33: Investments | C33: 13298 | D33: 20676 | E33: 29151 | F33: 36123 | G33: 37504 | H33: 37488 | I33: 42945 | J33: 42035 | K33: 49184 | L33: 57296 | M33: 66265 | N33: 76838
B35: Other Assets -
B36: Inventories | C36: 2745 | D36: 3133 | E36: 3264 | F36: 3160 | G36: 3323 | H36: 3214 | I36: 3049 | J36: 3532 | K36: 4284 | L36: 5318 | M36: 6913 | N36: 11321
B37: Trade receivables | C37: 1144 | D37: 1323 | E37: 1203 | F37: 1465 | G37: 2313 | H37: 1978 | I37: 1280 | J37: 2034 | K37: 3301 | L37: 4597 | M37: 6540 | N37: 5342
B38: Cash Equivalents | C38: 43 | D38: 51 | E38: 24 | F38: 74 | G38: 188 | H38: 29 | I38: 3047 | J38: 3042 | K38: 42 | L38: 2827 | M38: 553 | N38: 1580
B39: Loans n Advances | C39: 126 | D39: 623 | E39: 688 | F39: 1290 | G39: 1160 | H39: 1362 | I39: 1412 | J39: 2880 | K39: 2828 | L39: 266 | M39: 851 | N39: 784
B40: Other asset items | C40: 2741 | D40: 3384 | E40: 3069 | F40: 2615 | G40: 2438 | H40: 2398 | I40: 3158 | J40: 4448 | K40: 4223 | L40: 9400 | M40: 9937 | N40: 8655
B41: Total Assets | C41: 34477 | D41: 42726 | E41: 51960 | F41: 60248 | G41: 63969 | H41: 63628 | I41: 71376 | J41: 74656 | K41: 84597 | L41: 115304 | M41: 131971 | N41: 148881
A43: # | B43: Particulars | C43: 42064 | D43: 42430 | E43: 42795 | F43: 43160 | G43: 43525 | H43: 43891 | I43: 44256 | J43: 44621 | K43: 44986 | L43: 45352 | M43: 45717 | N43: 46082
B45: Cash from Operating Activity - | C45: 6449 | D45: 8482 | E45: 10282 | F45: 11788 | G45: 6601 | H45: 3496 | I45: 8856 | J45: 1840 | K45: 9251 | L45: 16801 | M45: 16136 | N45: 19100
B46: Profit from operations | C46: 6779 | D46: 8935 | E46: 10413 | F46: 12036 | G46: 11060 | H46: 7503 | I46: 5531 | J46: 5832 | K46: 11112 | L46: 18676 | M46: 20322 | N46: 21802
B47: Receivables | C47: 345 | D47: -204 | E47: 122 | F47: -262 | G47: -851 | H47: 340 | I47: 696 | J47: -764 | K47: -1258 | L47: -1316 | M47: -1969 | N47: 1236
B48: Inventory | C48: -982 | D48: -450 | E48: -131 | F48: 104 | G48: -162 | H48: 109 | I48: 165 | J48: -483 | K48: -751 | L48: 125 | M48: -1595 | N48: -4407
B49: Payables | C49: 712 | D49: 1789 | E49: 979 | F49: 2128 | G49: -858 | H49: -2155 | I49: 2680 | J49: -396 | K49: 2008 | L49: 3321 | M49: 3509 | N49: 5194
B50: Loans Advances | C50: 23 | D50: -1 | E50: 1 | F50: 0 | G50: -13 | H50: -1 | I50: -6 | J50: -8 | K50: 1 | L50: -3 | M50: -10 | N50: -1
B51: Other WC items | C51: 648 | D51: 325 | E51: 1222 | F51: 839 | G51: 569 | H51: -863 | I51: 801 | J51: -1162 | K51: 374 | L51: -406 | M51: -313 | N51: -387
B52: Working capital changes | C52: 745 | D52: 1460 | E52: 2192 | F52: 2808 | G52: -1315 | H52: -2570 | I52: 4336 | J52: -2813 | K52: 373 | L52: 1722 | M52: -378 | N52: 1635
B53: Direct taxes | C53: -1075 | D53: -1912 | E53: -2323 | F53: -3056 | G53: -3144 | H53: -1438 | I53: -1011 | J53: -1178 | K53: -2233 | L53: -3597 | M53: -3807 | N53: -4337
B54: Cash from Investing Activity - | C54: -4491 | D54: -7230 | E54: -9173 | F54: -8302 | G54: -3540 | H54: -557 | I54: -7291 | J54: -239 | K54: -8036 | L54: -11865 | M54: -14456 | N54: -14734
B55: Fixed assets purchased | C55: -3058 | D55: -2469 | E55: -3391 | F55: -3912 | G55: -4872 | H55: -3437 | I55: -2370 | J55: -3459 | K55: -6347 | L55: -9200 | M55: -10641 | N55: -10398
B56: Fixed assets sold | C56: 16 | D56: 12 | E56: 16 | F56: 26 | G56: 170 | H56: 37 | I56: 42 | J56: 136 | K56: 100 | L56: 45 | M56: 38 | N56: 52
... B73: CFO/OP | C73: 1.09 | D73: 1.15 | E73: 1.21 | F73: 1.22 | G73: 0.88 | H73: 0.67 | I73: 1.82 | J73: 0.52 | K73: 1.04 | L73: 1.1 | M73: 0.99 | N73: 1.09
